Workbook
Name \0: '[1]PNT-QUOT-#3'!#REF!
Name \0: '[1]PNT-QUOT-#3'!#REF!
Name \a: #REF!
Name \a: #REF!
Name \a: #REF!
Name \P: #REF!
Name \P: #REF!
Name \P: #REF!
Name \z: #N/A
Name _: #REF!
Name _: #REF!
Name _?: #REF!
Name _?: #REF!
Name _?쨲?f: #REF!
Name _?쨲?f: #REF!
Name _________________MN1: #REF!
Name _________________MN1: #REF!
Name _________________MN2: #REF!
Name _________________MN2: #REF!
Name _________________MT1: #REF!
Name _________________MT1: #REF!
Name _________________MT2: #REF!
Name _________________tg427: #REF!
Name _________________UT2: #REF!
Name ________________atn1: #REF!
Name ________________atn10: #REF!
Name ________________atn2: #REF!
Name ________________atn3: #REF!
Name ________________atn4: #REF!
Name ________________atn5: #REF!
Name ________________atn6: #REF!
Name ________________atn7: #REF!
Name ________________atn8: #REF!
Name ________________atn9: #REF!
Name ________________CON1: #REF!
Name ________________CON2: #REF!
Name ________________cpd1: #REF!
Name ________________cpd2: #REF!
Name ________________deo1: #REF!
Name ________________deo10: #REF!
Name ________________deo2: #REF!
Name ________________deo3: #REF!
Name ________________deo4: #REF!
Name ________________deo5: #REF!
Name ________________deo6: #REF!
Name ________________deo7: #REF!
Name ________________deo8: #REF!
Name ________________deo9: #REF!
Name ________________khu7: #REF!
Name ________________nc151: #REF!
Name ________________NET2: #REF!
Name ________________tct5: #REF!
Name ________________TH20: #REF!
Name ________________xx3: #REF!
Name ________________xx4: #REF!
Name ________________xx5: #REF!
Name ________________xx6: #REF!
Name ________________xx7: #REF!
Name ______________Cau2: #REF!
Name ______________deo6: #REF!

Sheet TH1
C3: STT | D3: Tên | E3: Lĩnh vực HĐ | G3: Tên viết tắt
C4: 1 | D4: DV Quang Phát | E4: Bê Tông, TMDV Xi sắt | G4: =C4&"."&D4 -> 1.DV Quang Phát
C5: 2 | D5: BT Quang Phát | E5: Bê Tông, TMDV Xi sắt | G5: =C5&"."&D5 -> 2.BT Quang Phát
C6: 3 | D6: Kim Quang Phát | E6: Chăn nuôi gà giống và gà thịt | G6: =C6&"."&D6 -> 3.Kim Quang Phát
C7: 4 | D7: Kim Mỹ Linh | E7: Thương mại | G7: =C7&"."&D7 -> 4.Kim Mỹ Linh
C8: 5 | D8: Vạn Xuân | E8: Thương mại | G8: =C8&"."&D8 -> 5.Vạn Xuân
C9: 6 | G9: =C9&"."&D9 -> 6.
C14: NỘI DUNG
C16: 1 | D16: THÔNG TIN CHUNG
C17: 1.1 | D17: Lịch sử hình thành
C18: 1.2 | D18: Cấu trúc Sở hữu
C19: 1.3 | D19: Hoạt động (SP) | E19: đang cập nhật
C20: 1.4 | D20: Pháp nhân - NM
C21: 1.5 | D21: Công suất | E21: đang cập nhật
C23: 2 | D23: BÁO CÁO TÀI CHÍNH
C24: 2.1 | D24: BC_Phap nhan | E24: (Thuế)
C25: 2.2 | D25: BC_Năm | E25: (Thuế)
C26: 2.3 | D26: BC_San pham | E26: Chưa có dữ liệu
C27: 2.4 | D27: BC_Hoat dong | E27: Chưa có dữ liệu

Sheet 1.PL (VND) 
B2: KẾT QUẢ HOẠT ĐỘNG KINH DOANH | F2: Trước điều chỉnh | J2: Trước điều chỉnh | O2: Trước điều chỉnh | T2: Trước điều chỉnh | Y2: Trước điều chỉnh | AD2: Trước điều chỉnh | AJ2: Điều chỉnh | AO2: Điều chỉnh | AT2: Điều chỉnh | AY2: Điều chỉnh | BD2: Điều chỉnh | BI2: Điều chỉnh | BN2: Sau điều chỉnh | BS2: Sau điều chỉnh | BX2: Sau điều chỉnh | CM2: Sau điều chỉnh | CR2: Sau điều chỉnh | CW2: Điều chỉnh Nội bộ | DB2: Sau điều chỉnh nộ bộ
AH4: =$AH$5&$AJ$2&AH6 -> 1.DV Quang PhátĐiều chỉnh 2020 | AI4: =$AH$5&AI6 -> 1.DV Quang Phát2021 | AJ4: =$AH$5&$AJ$2&AJ6 -> 1.DV Quang PhátĐiều chỉnh 2022 | AK4: =$AH$5&$AJ$2&AK6 -> 1.DV Quang PhátĐiều chỉnh 2023 | AM4: =$AM5&$AJ$2&AM6 -> 2.BT Quang PhátĐiều chỉnh 2020 | AN4: =$AM5&$AJ$2&AN6 -> 2.BT Quang PhátĐiều chỉnh 2021 | AO4: =$AM5&$AJ$2&AO6 -> 2.BT Quang PhátĐiều chỉnh 2022 | AP4: =$AM5&$AJ$2&AP6 -> 2.BT Quang PhátĐiều chỉnh 2023 | AR4: =$AR$5&$AT$2&AR6 -> 3.Kim Quang PhátĐiều chỉnh 2020 | AS4: =$AR$5&$AT$2&AS6 -> 3.Kim Quang PhátĐiều chỉnh 2021 | AT4: =$AR$5&AT6 -> 3.Kim Quang Phát2022 | AU4: =$AR$5&$AT$2&AU6 -> 3.Kim Quang PhátĐiều chỉnh 2023 | AW4: =$AW$5&$AT$2&AW6 -> 4.Kim Mỹ LinhĐiều chỉnh 2020 | AX4: =$AW$5&$AT$2&AX6 -> 4.Kim Mỹ LinhĐiều chỉnh 2021 | AY4: =$AW$5&$AT$2&AY6 -> 4.Kim Mỹ LinhĐiều chỉnh 2022 | AZ4: =$AW$5&$AT$2&AZ6 -> 4.Kim Mỹ LinhĐiều chỉnh 2023 | BB4: =$BB$5&$AT$2&BB6 -> 5.Vạn XuânĐiều chỉnh 2020 | BC4: =$BB$5&$AT$2&BC6 -> 5.Vạn XuânĐiều chỉnh 2021 | BD4: =$BB$5&$AT$2&BD6 -> 5.Vạn XuânĐiều chỉnh 2022 | BE4: =$BB$5&$AT$2&BE6 -> 5.Vạn XuânĐiều chỉnh 2023 | BG4: =$BG5&$BI$2&BG6 -> 6.Điều chỉnh 2020 | BH4: =$BG5&$BI$2&BH6 -> 6.Điều chỉnh 2021 | BI4: =$BG5&$BI$2&BI6 -> 6.Điều chỉnh 2022 | BJ4: =$BG5&$BI$2&BJ6 -> 6.Điều chỉnh 2023 | CU4: ="ButruNB"&CU6 -> ButruNB2020 | CV4: ="ButruNB"&CV6 -> ButruNB2021 | CW4: ="ButruNB"&CW6 -> ButruNB2022 | CX4: ="ButruNB"&CX6 -> ButruNB2023
B5: Chỉ tiêu | C5: Mã số | D5: ='TH1'!G4 -> 1.DV Quang Phát | I5: ='TH1'!G5 -> 2.BT Quang Phát | N5: ='TH1'!G6 -> 3.Kim Quang Phát | S5: ='TH1'!G7 -> 4.Kim Mỹ Linh | X5: ='TH1'!G8 -> 5.Vạn Xuân | AC5: ='TH1'!G9 -> 6. | AH5: ='TH1'!G4 -> 1.DV Quang Phát | AM5: ='TH1'!G5 -> 2.BT Quang Phát | AR5: ='TH1'!G6 -> 3.Kim Quang Phát | AW5: ='TH1'!G7 -> 4.Kim Mỹ Linh | BB5: ='TH1'!G8 -> 5.Vạn Xuân | BG5: ='TH1'!G9 -> 6. | BL5: =AH5 -> 1.DV Quang Phát | BQ5: ='TH1'!G5 -> 2.BT Quang Phát | BV5: ='TH1'!G6 -> 3.Kim Quang Phát | CA5: ='TH1'!G7 -> 4.Kim Mỹ Linh | CF5: ='TH1'!G8 -> 5.Vạn Xuân | CK5: ='TH1'!G9 -> 6. | CP5: Tổng | CU5: Tổng | CZ5: Tổng
B6: 1000000000 | D6: 2020 | E6: 2021 | F6: 2022 | G6: 2023 | I6: 2020 | J6: 2021 | K6: 2022 | L6: 2023 | N6: 2020 | O6: 2021 | P6: 2022 | Q6: 2023 | S6: 2020 | T6: 2021 | U6: 2022 | V6: 2023 | X6: 2020 | Y6: 2021 | Z6: 2022 | AA6: 2023 | AC6: 2020 | AD6: 2021 | AE6: 2022 | AF6: 2023 | AH6: 2020 | AI6: 2021 | AJ6: 2022 | AK6: 2023 | AM6: 2020 | AN6: 2021 | AO6: 2022 | AP6: 2023 | AR6: 2020 | AS6: 2021 | AT6: 2022 | AU6: 2023 | AW6: 2020 | AX6: 2021 | AY6: 2022 | AZ6: 2023 | BB6: 2020 | BC6: 2021 | BD6: 2022 | BE6: 2023 | BG6: 2020 | BH6: 2021 | BI6: 2022 | BJ6: 2023 | BL6: 2020 | BM6: 2021 | BN6: 2022 | BO6: 2023 | BQ6: 2020 | BR6: 2021 | BS6: 2022 | BT6: 2023 | BV6: 2020 | BW6: 2021 | BX6: 2022 | BY6: 2023 | CA6: 2020 | CB6: 2021 | CC6: 2022 | CD6: 2023 | CF6: 2020 | CG6: 2021 | CH6: 2022 | CI6: 2023 | CK6: 2020 | CL6: 2021 | CM6: 2022 | CN6: 2023 | CP6: 2020 | CQ6: 2021 | CR6: 2022 | CS6: 2023 | CU6: 2020 | CV6: 2021 | CW6: 2022 | CX6: 2023 | CZ6: 2020 | DA6: 2021 | DB6: 2022 | DC6: 2023
B8: 1. Doanh thu bán hàng | C8: 01 | D8: 272815509098 | E8: 361225907557 | F8: 423679605375 | G8: 441344076314 | I8: 0 | J8: 41462536713 | K8: 69811635749 | L8: 74678752638 | N8: 59548559255 | O8: 54917326996 | P8: 64008838727 | Q8: 58809727981 | S8: 20700982927 | T8: 43997295527 | U8: 45487103106 | V8: 43100304580 | AH8: =-SUMIFS('1.DC_Ra soat'!$L:$L,'1.DC_Ra soat'!$F:$F,'1.PL (VND) '!AH$4,'1.DC_Ra soat'!$H:$H,'1.PL (VND) '!$C8)+SUMIFS('1.DC_Ra soat'!$L:$L,'1.DC_Ra soat'!$F:$F,'1.PL (VND) '!AH$4,'1.DC_Ra soat'!$I:$I,'1.PL (VND) '!$C8) -> 0 | AI8: =-SUMIFS('1.DC_Ra soat'!$L:$L,'1.DC_Ra soat'!$F:$F,'1.PL (VND) '!AI$4,'1.DC_Ra soat'!$H:$H,'1.PL (VND) '!$C8)+SUMIFS('1.DC_Ra soat'!$L:$L,'1.DC_Ra soat'!$F:$F,'1.PL (VND) '!AI$4,'1.DC_Ra soat'!$I:$I,'1.PL (VND) '!$C8) -> 0 | AJ8: =-SUMIFS('1.DC_Ra soat'!$L:$L,'1.DC_Ra soat'!$F:$F,'1.PL (VND) '!AJ$4,'1.DC_Ra soat'!$H:$H,'1.PL (VND) '!$C8)+SUMIFS('1.DC_Ra soat'!$L:$L,'1.DC_Ra soat'!$F:$F,'1.PL (VND) '!AJ$4,'1.DC_Ra soat'!$I:$I,'1.PL (VND) '!$C8) -> 0 | AK8: =-SUMIFS('1.DC_Ra soat'!$L:$L,'1.DC_Ra soat'!$F:$F,'1.PL (VND) '!AK$4,'1.DC_Ra soat'!$H:$H,'1.PL (VND) '!$C8)+SUMIFS('1.DC_Ra soat'!$L:$L,'1.DC_Ra soat'!$F:$F,'1.PL (VND) '!AK$4,'1.DC_Ra soat'!$I:$I,'1.PL (VND) '!$C8) -> 0 | AM8: =-SUMIFS('1.DC_Ra soat'!$L:$L,'1.DC_Ra soat'!$F:$F,'1.PL (VND) '!AM$4,'1.DC_Ra soat'!$H:$H,'1.PL (VND) '!$C8)+SUMIFS('1.DC_Ra soat'!$L:$L,'1.DC_Ra soat'!$F:$F,'1.PL (VND) '!AM$4,'1.DC_Ra soat'!$I:$I,'1.PL (VND) '!$C8) -> 0 | AN8: =-SUMIFS('1.DC_Ra soat'!$L:$L,'1.DC_Ra soat'!$F:$F,'1.PL (VND) '!AN$4,'1.DC_Ra soat'!$H:$H,'1.PL (VND) '!$C8)+SUMIFS('1.DC_Ra soat'!$L:$L,'1.DC_Ra soat'!$F:$F,'1.PL (VND) '!AN$4,'1.DC_Ra soat'!$I:$I,'1.PL (VND) '!$C8) -> 0 | AO8: =-SUMIFS('1.DC_Ra soat'!$L:$L,'1.DC_Ra soat'!$F:$F,'1.PL (VND) '!AO$4,'1.DC_Ra soat'!$H:$H,'1.PL (VND) '!$C8)+SUMIFS('1.DC_Ra soat'!$L:$L,'1.DC_Ra soat'!$F:$F,'1.PL (VND) '!AO$4,'1.DC_Ra soat'!$I:$I,'1.PL (VND) '!$C8) -> 0 | AP8: =-SUMIFS('1.DC_Ra soat'!$L:$L,'1.DC_Ra soat'!$F:$F,'1.PL (VND) '!AP$4,'1.DC_Ra soat'!$H:$H,'1.PL (VND) '!$C8)+SUMIFS('1.DC_Ra soat'!$L:$L,'1.DC_Ra soat'!$F:$F,'1.PL (VND) '!AP$4,'1.DC_Ra soat'!$I:$I,'1.PL (VND) '!$C8) -> 0 | AR8: =-SUMIFS('1.DC_Ra soat'!$L:$L,'1.DC_Ra soat'!$F:$F,'1.PL (VND) '!AR$4,'1.DC_Ra soat'!$H:$H,'1.PL (VND) '!$C8)+SUMIFS('1.DC_Ra soat'!$L:$L,'1.DC_Ra soat'!$F:$F,'1.PL (VND) '!AR$4,'1.DC_Ra soat'!$I:$I,'1.PL (VND) '!$C8) -> 0 | AS8: =-SUMIFS('1.DC_Ra soat'!$L:$L,'1.DC_Ra soat'!$F:$F,'1.PL (VND) '!AS$4,'1.DC_Ra soat'!$H:$H,'1.PL (VND) '!$C8)+SUMIFS('1.DC_Ra soat'!$L:$L,'1.DC_Ra soat'!$F:$F,'1.PL (VND) '!AS$4,'1.DC_Ra soat'!$I:$I,'1.PL (VND) '!$C8) -> 0 | AT8: =-SUMIFS('1.DC_Ra soat'!$L:$L,'1.DC_Ra soat'!$F:$F,'1.PL (VND) '!AT$4,'1.DC_Ra soat'!$H:$H,'1.PL (VND) '!$C8)+SUMIFS('1.DC_Ra soat'!$L:$L,'1.DC_Ra soat'!$F:$F,'1.PL (VND) '!AT$4,'1.DC_Ra soat'!$I:$I,'1.PL (VND) '!$C8) -> 0 | AU8: =-SUMIFS('1.DC_Ra soat'!$L:$L,'1.DC_Ra soat'!$F:$F,'1.PL (VND) '!AU$4,'1.DC_Ra soat'!$H:$H,'1.PL (VND) '!$C8)+SUMIFS('1.DC_Ra soat'!$L:$L,'1.DC_Ra soat'!$F:$F,'1.PL (VND) '!AU$4,'1.DC_Ra soat'!$I:$I,'1.PL (VND) '!$C8) -> 0 | AW8: =-SUMIFS('1.DC_Ra soat'!$L:$L,'1.DC_Ra soat'!$F:$F,'1.PL (VND) '!AW$4,'1.DC_Ra soat'!$H:$H,'1.PL (VND) '!$C8)+SUMIFS('1.DC_Ra soat'!$L:$L,'1.DC_Ra soat'!$F:$F,'1.PL (VND) '!AW$4,'1.DC_Ra soat'!$I:$I,'1.PL (VND) '!$C8) -> 0 | AX8: =-SUMIFS('1.DC_Ra soat'!$L:$L,'1.DC_Ra soat'!$F:$F,'1.PL (VND) '!AX$4,'1.DC_Ra soat'!$H:$H,'1.PL (VND) '!$C8)+SUMIFS('1.DC_Ra soat'!$L:$L,'1.DC_Ra soat'!$F:$F,'1.PL (VND) '!AX$4,'1.DC_Ra soat'!$I:$I,'1.PL (VND) '!$C8) -> 0 | AY8: =-SUMIFS('1.DC_Ra soat'!$L:$L,'1.DC_Ra soat'!$F:$F,'1.PL (VND) '!AY$4,'1.DC_Ra soat'!$H:$H,'1.PL (VND) '!$C8)+SUMIFS('1.DC_Ra soat'!$L:$L,'1.DC_Ra soat'!$F:$F,'1.PL (VND) '!AY$4,'1.DC_Ra soat'!$I:$I,'1.PL (VND) '!$C8) -> 0 | AZ8: =-SUMIFS('1.DC_Ra soat'!$L:$L,'1.DC_Ra soat'!$F:$F,'1.PL (VND) '!AZ$4,'1.DC_Ra soat'!$H:$H,'1.PL (VND) '!$C8)+SUMIFS('1.DC_Ra soat'!$L:$L,'1.DC_Ra soat'!$F:$F,'1.PL (VND) '!AZ$4,'1.DC_Ra soat'!$I:$I,'1.PL (VND) '!$C8) -> 0 | BB8: =-SUMIFS('1.DC_Ra soat'!$L:$L,'1.DC_Ra soat'!$F:$F,'1.PL (VND) '!BB$4,'1.DC_Ra soat'!$H:$H,'1.PL (VND) '!$C8)+SUMIFS('1.DC_Ra soat'!$L:$L,'1.DC_Ra soat'!$F:$F,'1.PL (VND) '!BB$4,'1.DC_Ra soat'!$I:$I,'1.PL (VND) '!$C8) -> 0 | BC8: =-SUMIFS('1.DC_Ra soat'!$L:$L,'1.DC_Ra soat'!$F:$F,'1.PL (VND) '!BC$4,'1.DC_Ra soat'!$H:$H,'1.PL (VND) '!$C8)+SUMIFS('1.DC_Ra soat'!$L:$L,'1.DC_Ra soat'!$F:$F,'1.PL (VND) '!BC$4,'1.DC_Ra soat'!$I:$I,'1.PL (VND) '!$C8) -> 0 | BD8: =-SUMIFS('1.DC_Ra soat'!$L:$L,'1.DC_Ra soat'!$F:$F,'1.PL (VND) '!BD$4,'1.DC_Ra soat'!$H:$H,'1.PL (VND) '!$C8)+SUMIFS('1.DC_Ra soat'!$L:$L,'1.DC_Ra soat'!$F:$F,'1.PL (VND) '!BD$4,'1.DC_Ra soat'!$I:$I,'1.PL (VND) '!$C8) -> 0 | BE8: =-SUMIFS('1.DC_Ra soat'!$L:$L,'1.DC_Ra soat'!$F:$F,'1.PL (VND) '!BE$4,'1.DC_Ra soat'!$H:$H,'1.PL (VND) '!$C8)+SUMIFS('1.DC_Ra soat'!$L:$L,'1.DC_Ra soat'!$F:$F,'1.PL (VND) '!BE$4,'1.DC_Ra soat'!$I:$I,'1.PL (VND) '!$C8) -> 0 | BG8: =-SUMIFS('1.DC_Ra soat'!$L:$L,'1.DC_Ra soat'!$F:$F,'1.PL (VND) '!BG$4,'1.DC_Ra soat'!$H:$H,'1.PL (VND) '!$C8)+SUMIFS('1.DC_Ra soat'!$L:$L,'1.DC_Ra soat'!$F:$F,'1.PL (VND) '!BG$4,'1.DC_Ra soat'!$I:$I,'1.PL (VND) '!$C8) -> 0 | BH8: =-SUMIFS('1.DC_Ra soat'!$L:$L,'1.DC_Ra soat'!$F:$F,'1.PL (VND) '!BH$4,'1.DC_Ra soat'!$H:$H,'1.PL (VND) '!$C8)+SUMIFS('1.DC_Ra soat'!$L:$L,'1.DC_Ra soat'!$F:$F,'1.PL (VND) '!BH$4,'1.DC_Ra soat'!$I:$I,'1.PL (VND) '!$C8) -> 0 | BI8: =-SUMIFS('1.DC_Ra soat'!$L:$L,'1.DC_Ra soat'!$F:$F,'1.PL (VND) '!BI$4,'1.DC_Ra soat'!$H:$H,'1.PL (VND) '!$C8)+SUMIFS('1.DC_Ra soat'!$L:$L,'1.DC_Ra soat'!$F:$F,'1.PL (VND) '!BI$4,'1.DC_Ra soat'!$I:$I,'1.PL (VND) '!$C8) -> 0 | BJ8: =-SUMIFS('1.DC_Ra soat'!$L:$L,'1.DC_Ra soat'!$F:$F,'1.PL (VND) '!BJ$4,'1.DC_Ra soat'!$H:$H,'1.PL (VND) '!$C8)+SUMIFS('1.DC_Ra soat'!$L:$L,'1.DC_Ra soat'!$F:$F,'1.PL (VND) '!BJ$4,'1.DC_Ra soat'!$I:$I,'1.PL (VND) '!$C8) -> 0 | BL8: =D8+AH8 -> 272815509098 | BM8: =E8+AI8 -> 361225907557 | BN8: =F8+AJ8 -> 423679605375 | BO8: =G8+AK8 -> 441344076314 | BQ8: =I8+AM8 -> 0 | BR8: =J8+AN8 -> 41462536713 | BS8: =K8+AO8 -> 69811635749 | BT8: =L8+AP8 -> 74678752638 | BV8: =N8+AR8 -> 59548559255 | BW8: =O8+AS8 -> 54917326996 | BX8: =P8+AT8 -> 64008838727 | BY8: =Q8+AU8 -> 58809727981 | CA8: =S8+AW8 -> 20700982927 | CB8: =T8+AX8 -> 43997295527 | CC8: =U8+AY8 -> 45487103106 | CD8: =V8+AZ8 -> 43100304580 | CF8: =X8+BB8 -> 0 | CG8: =Y8+BC8 -> 0 | CH8: =Z8+BD8 -> 0 | CI8: =AA8+BE8 -> 0 | CK8: =AC8+BG8 -> 0 | CL8: =AD8+BH8 -> 0 | CM8: =AE8+BI8 -> 0 | CN8: =AF8+BJ8 -> 0 | CP8: =SUMIF($BL$6:$CD$6,CP$6,$BL8:$CD8) -> 353065051280 | CQ8: =SUMIF($BL$6:$CD$6,CQ$6,$BL8:$CD8) -> 501603066793 | CR8: =SUMIF($BL$6:$CD$6,CR$6,$BL8:$CD8) -> 602987182957 | CS8: =SUMIF($BL$6:$CD$6,CS$6,$BL8:$CD8) -> 617932861513 | CU8: =-SUMIFS('1.DC_Ra soat'!$L:$L,'1.DC_Ra soat'!$F:$F,'1.PL (VND) '!CU$4,'1.DC_Ra soat'!$H:$H,'1.PL (VND) '!$C8)+SUMIFS('1.DC_Ra soat'!$L:$L,'1.DC_Ra soat'!$F:$F,'1.PL (VND) '!CU$4,'1.DC_Ra soat'!$I:$I,'1.PL (VND) '!$C8) -> 0 | CV8: =-SUMIFS('1.DC_Ra soat'!$L:$L,'1.DC_Ra soat'!$F:$F,'1.PL (VND) '!CV$4,'1.DC_Ra soat'!$H:$H,'1.PL (VND) '!$C8)+SUMIFS('1.DC_Ra soat'!$L:$L,'1.DC_Ra soat'!$F:$F,'1.PL (VND) '!CV$4,'1.DC_Ra soat'!$I:$I,'1.PL (VND) '!$C8) -> 0 | CW8: =-SUMIFS('1.DC_Ra soat'!$L:$L,'1.DC_Ra soat'!$F:$F,'1.PL (VND) '!CW$4,'1.DC_Ra soat'!$H:$H,'1.PL (VND) '!$C8)+SUMIFS('1.DC_Ra soat'!$L:$L,'1.DC_Ra soat'!$F:$F,'1.PL (VND) '!CW$4,'1.DC_Ra soat'!$I:$I,'1.PL (VND) '!$C8) -> -97491273670 | CX8: =-SUMIFS('1.DC_Ra soat'!$L:$L,'1.DC_Ra soat'!$F:$F,'1.PL (VND) '!CX$4,'1.DC_Ra soat'!$H:$H,'1.PL (VND) '!$C8)+SUMIFS('1.DC_Ra soat'!$L:$L,'1.DC_Ra soat'!$F:$F,'1.PL (VND) '!CX$4,'1.DC_Ra soat'!$I:$I,'1.PL (VND) '!$C8) -> -85934511540 | CZ8: =CP8+CU8 -> 353065051280 | DA8: =CQ8+CV8 -> 501603066793 | DB8: =CR8+CW8 -> 505495909287 | DC8: =CS8+CX8 -> 531998349973
B9: 2. Các khoản giảm trừ | C9: 02 | F9: 311800426 | G9: 0 | I9: 0 | J9: 0 | K9: 0 | L9: 0 | AH9: =SUMIFS('1.DC_Ra soat'!$L:$L,'1.DC_Ra soat'!$F:$F,'1.PL (VND) '!AH$4,'1.DC_Ra soat'!$H:$H,'1.PL (VND) '!$C9)-SUMIFS('1.DC_Ra soat'!$L:$L,'1.DC_Ra soat'!$F:$F,'1.PL (VND) '!AH$4,'1.DC_Ra soat'!$I:$I,'1.PL (VND) '!$C9) -> 0 | AI9: =SUMIFS('1.DC_Ra soat'!$L:$L,'1.DC_Ra soat'!$F:$F,'1.PL (VND) '!AI$4,'1.DC_Ra soat'!$H:$H,'1.PL (VND) '!$C9)-SUMIFS('1.DC_Ra soat'!$L:$L,'1.DC_Ra soat'!$F:$F,'1.PL (VND) '!AI$4,'1.DC_Ra soat'!$I:$I,'1.PL (VND) '!$C9) -> 0 | AJ9: =SUMIFS('1.DC_Ra soat'!$L:$L,'1.DC_Ra soat'!$F:$F,'1.PL (VND) '!AJ$4,'1.DC_Ra soat'!$H:$H,'1.PL (VND) '!$C9)-SUMIFS('1.DC_Ra soat'!$L:$L,'1.DC_Ra soat'!$F:$F,'1.PL (VND) '!AJ$4,'1.DC_Ra soat'!$I:$I,'1.PL (VND) '!$C9) -> 0 | AK9: =SUMIFS('1.DC_Ra soat'!$L:$L,'1.DC_Ra soat'!$F:$F,'1.PL (VND) '!AK$4,'1.DC_Ra soat'!$H:$H,'1.PL (VND) '!$C9)-SUMIFS('1.DC_Ra soat'!$L:$L,'1.DC_Ra soat'!$F:$F,'1.PL (VND) '!AK$4,'1.DC_Ra soat'!$I:$I,'1.PL (VND) '!$C9) -> 0 | AM9: =SUMIFS('1.DC_Ra soat'!$L:$L,'1.DC_Ra soat'!$F:$F,'1.PL (VND) '!AM$4,'1.DC_Ra soat'!$H:$H,'1.PL (VND) '!$C9)-SUMIFS('1.DC_Ra soat'!$L:$L,'1.DC_Ra soat'!$F:$F,'1.PL (VND) '!AM$4,'1.DC_Ra soat'!$I:$I,'1.PL (VND) '!$C9) -> 0 | AN9: =SUMIFS('1.DC_Ra soat'!$L:$L,'1.DC_Ra soat'!$F:$F,'1.PL (VND) '!AN$4,'1.DC_Ra soat'!$H:$H,'1.PL (VND) '!$C9)-SUMIFS('1.DC_Ra soat'!$L:$L,'1.DC_Ra soat'!$F:$F,'1.PL (VND) '!AN$4,'1.DC_Ra soat'!$I:$I,'1.PL (VND) '!$C9) -> 0 | AO9: =SUMIFS('1.DC_Ra soat'!$L:$L,'1.DC_Ra soat'!$F:$F,'1.PL (VND) '!AO$4,'1.DC_Ra soat'!$H:$H,'1.PL (VND) '!$C9)-SUMIFS('1.DC_Ra soat'!$L:$L,'1.DC_Ra soat'!$F:$F,'1.PL (VND) '!AO$4,'1.DC_Ra soat'!$I:$I,'1.PL (VND) '!$C9) -> 0 | AP9: =SUMIFS('1.DC_Ra soat'!$L:$L,'1.DC_Ra soat'!$F:$F,'1.PL (VND) '!AP$4,'1.DC_Ra soat'!$H:$H,'1.PL (VND) '!$C9)-SUMIFS('1.DC_Ra soat'!$L:$L,'1.DC_Ra soat'!$F:$F,'1.PL (VND) '!AP$4,'1.DC_Ra soat'!$I:$I,'1.PL (VND) '!$C9) -> 0 | AR9: =SUMIFS('1.DC_Ra soat'!$L:$L,'1.DC_Ra soat'!$F:$F,'1.PL (VND) '!AR$4,'1.DC_Ra soat'!$H:$H,'1.PL (VND) '!$C9)-SUMIFS('1.DC_Ra soat'!$L:$L,'1.DC_Ra soat'!$F:$F,'1.PL (VND) '!AR$4,'1.DC_Ra soat'!$I:$I,'1.PL (VND) '!$C9) -> 0 | AS9: =SUMIFS('1.DC_Ra soat'!$L:$L,'1.DC_Ra soat'!$F:$F,'1.PL (VND) '!AS$4,'1.DC_Ra soat'!$H:$H,'1.PL (VND) '!$C9)-SUMIFS('1.DC_Ra soat'!$L:$L,'1.DC_Ra soat'!$F:$F,'1.PL (VND) '!AS$4,'1.DC_Ra soat'!$I:$I,'1.PL (VND) '!$C9) -> 0 | AT9: =SUMIFS('1.DC_Ra soat'!$L:$L,'1.DC_Ra soat'!$F:$F,'1.PL (VND) '!AT$4,'1.DC_Ra soat'!$H:$H,'1.PL (VND) '!$C9)-SUMIFS('1.DC_Ra soat'!$L:$L,'1.DC_Ra soat'!$F:$F,'1.PL (VND) '!AT$4,'1.DC_Ra soat'!$I:$I,'1.PL (VND) '!$C9) -> 0 | AU9: =SUMIFS('1.DC_Ra soat'!$L:$L,'1.DC_Ra soat'!$F:$F,'1.PL (VND) '!AU$4,'1.DC_Ra soat'!$H:$H,'1.PL (VND) '!$C9)-SUMIFS('1.DC_Ra soat'!$L:$L,'1.DC_Ra soat'!$F:$F,'1.PL (VND) '!AU$4,'1.DC_Ra soat'!$I:$I,'1.PL (VND) '!$C9) -> 0 | AW9: =SUMIFS('1.DC_Ra soat'!$L:$L,'1.DC_Ra soat'!$F:$F,'1.PL (VND) '!AW$4,'1.DC_Ra soat'!$H:$H,'1.PL (VND) '!$C9)-SUMIFS('1.DC_Ra soat'!$L:$L,'1.DC_Ra soat'!$F:$F,'1.PL (VND) '!AW$4,'1.DC_Ra soat'!$I:$I,'1.PL (VND) '!$C9) -> 0 | AX9: =SUMIFS('1.DC_Ra soat'!$L:$L,'1.DC_Ra soat'!$F:$F,'1.PL (VND) '!AX$4,'1.DC_Ra soat'!$H:$H,'1.PL (VND) '!$C9)-SUMIFS('1.DC_Ra soat'!$L:$L,'1.DC_Ra soat'!$F:$F,'1.PL (VND) '!AX$4,'1.DC_Ra soat'!$I:$I,'1.PL (VND) '!$C9) -> 0 | AY9: =SUMIFS('1.DC_Ra soat'!$L:$L,'1.DC_Ra soat'!$F:$F,'1.PL (VND) '!AY$4,'1.DC_Ra soat'!$H:$H,'1.PL (VND) '!$C9)-SUMIFS('1.DC_Ra soat'!$L:$L,'1.DC_Ra soat'!$F:$F,'1.PL (VND) '!AY$4,'1.DC_Ra soat'!$I:$I,'1.PL (VND) '!$C9) -> 0 | AZ9: =SUMIFS('1.DC_Ra soat'!$L:$L,'1.DC_Ra soat'!$F:$F,'1.PL (VND) '!AZ$4,'1.DC_Ra soat'!$H:$H,'1.PL (VND) '!$C9)-SUMIFS('1.DC_Ra soat'!$L:$L,'1.DC_Ra soat'!$F:$F,'1.PL (VND) '!AZ$4,'1.DC_Ra soat'!$I:$I,'1.PL (VND) '!$C9) -> 0 | BB9: =SUMIFS('1.DC_Ra soat'!$L:$L,'1.DC_Ra soat'!$F:$F,'1.PL (VND) '!BB$4,'1.DC_Ra soat'!$H:$H,'1.PL (VND) '!$C9)-SUMIFS('1.DC_Ra soat'!$L:$L,'1.DC_Ra soat'!$F:$F,'1.PL (VND) '!BB$4,'1.DC_Ra soat'!$I:$I,'1.PL (VND) '!$C9) -> 0 | BC9: =SUMIFS('1.DC_Ra soat'!$L:$L,'1.DC_Ra soat'!$F:$F,'1.PL (VND) '!BC$4,'1.DC_Ra soat'!$H:$H,'1.PL (VND) '!$C9)-SUMIFS('1.DC_Ra soat'!$L:$L,'1.DC_Ra soat'!$F:$F,'1.PL (VND) '!BC$4,'1.DC_Ra soat'!$I:$I,'1.PL (VND) '!$C9) -> 0 | BD9: =SUMIFS('1.DC_Ra soat'!$L:$L,'1.DC_Ra soat'!$F:$F,'1.PL (VND) '!BD$4,'1.DC_Ra soat'!$H:$H,'1.PL (VND) '!$C9)-SUMIFS('1.DC_Ra soat'!$L:$L,'1.DC_Ra soat'!$F:$F,'1.PL (VND) '!BD$4,'1.DC_Ra soat'!$I:$I,'1.PL (VND) '!$C9) -> 0 | BE9: =SUMIFS('1.DC_Ra soat'!$L:$L,'1.DC_Ra soat'!$F:$F,'1.PL (VND) '!BE$4,'1.DC_Ra soat'!$H:$H,'1.PL (VND) '!$C9)-SUMIFS('1.DC_Ra soat'!$L:$L,'1.DC_Ra soat'!$F:$F,'1.PL (VND) '!BE$4,'1.DC_Ra soat'!$I:$I,'1.PL (VND) '!$C9) -> 0 | BG9: =SUMIFS('1.DC_Ra soat'!$L:$L,'1.DC_Ra soat'!$F:$F,'1.PL (VND) '!BG$4,'1.DC_Ra soat'!$H:$H,'1.PL (VND) '!$C9)-SUMIFS('1.DC_Ra soat'!$L:$L,'1.DC_Ra soat'!$F:$F,'1.PL (VND) '!BG$4,'1.DC_Ra soat'!$I:$I,'1.PL (VND) '!$C9) -> 0 | BH9: =SUMIFS('1.DC_Ra soat'!$L:$L,'1.DC_Ra soat'!$F:$F,'1.PL (VND) '!BH$4,'1.DC_Ra soat'!$H:$H,'1.PL (VND) '!$C9)-SUMIFS('1.DC_Ra soat'!$L:$L,'1.DC_Ra soat'!$F:$F,'1.PL (VND) '!BH$4,'1.DC_Ra soat'!$I:$I,'1.PL (VND) '!$C9) -> 0 | BI9: =SUMIFS('1.DC_Ra soat'!$L:$L,'1.DC_Ra soat'!$F:$F,'1.PL (VND) '!BI$4,'1.DC_Ra soat'!$H:$H,'1.PL (VND) '!$C9)-SUMIFS('1.DC_Ra soat'!$L:$L,'1.DC_Ra soat'!$F:$F,'1.PL (VND) '!BI$4,'1.DC_Ra soat'!$I:$I,'1.PL (VND) '!$C9) -> 0 | BJ9: =SUMIFS('1.DC_Ra soat'!$L:$L,'1.DC_Ra soat'!$F:$F,'1.PL (VND) '!BJ$4,'1.DC_Ra soat'!$H:$H,'1.PL (VND) '!$C9)-SUMIFS('1.DC_Ra soat'!$L:$L,'1.DC_Ra soat'!$F:$F,'1.PL (VND) '!BJ$4,'1.DC_Ra soat'!$I:$I,'1.PL (VND) '!$C9) -> 0 | BL9: =D9+AH9 -> 0 | BM9: =E9+AI9 -> 0 | BN9: =F9+AJ9 -> 311800426 | BO9: =G9+AK9 -> 0 | BQ9: =I9+AM9 -> 0 | BR9: =J9+AN9 -> 0 | BS9: =K9+AO9 -> 0 | BT9: =L9+AP9 -> 0 | BV9: =N9+AR9 -> 0 | BW9: =O9+AS9 -> 0 | BX9: =P9+AT9 -> 0 | BY9: =Q9+AU9 -> 0 | CA9: =S9+AW9 -> 0 | CB9: =T9+AX9 -> 0 | CC9: =U9+AY9 -> 0 | CD9: =V9+AZ9 -> 0 | CF9: =X9+BB9 -> 0 | CG9: =Y9+BC9 -> 0 | CH9: =Z9+BD9 -> 0 | CI9: =AA9+BE9 -> 0 | CK9: =AC9+BG9 -> 0 | CL9: =AD9+BH9 -> 0 | CM9: =AE9+BI9 -> 0 | CN9: =AF9+BJ9 -> 0 | CP9: =SUMIF($BL$6:$CD$6,CP$6,$BL9:$CD9) -> 0 | CQ9: =SUMIF($BL$6:$CD$6,CQ$6,$BL9:$CD9) -> 0 | CR9: =SUMIF($BL$6:$CD$6,CR$6,$BL9:$CD9) -> 311800426 | CS9: =SUMIF($BL$6:$CD$6,CS$6,$BL9:$CD9) -> 0 | CU9: =-SUMIFS('1.DC_Ra soat'!$L:$L,'1.DC_Ra soat'!$F:$F,'1.PL (VND) '!CU$4,'1.DC_Ra soat'!$H:$H,'1.PL (VND) '!$C9)+SUMIFS('1.DC_Ra soat'!$L:$L,'1.DC_Ra soat'!$F:$F,'1.PL (VND) '!CU$4,'1.DC_Ra soat'!$I:$I,'1.PL (VND) '!$C9) -> 0 | CV9: =-SUMIFS('1.DC_Ra soat'!$L:$L,'1.DC_Ra soat'!$F:$F,'1.PL (VND) '!CV$4,'1.DC_Ra soat'!$H:$H,'1.PL (VND) '!$C9)+SUMIFS('1.DC_Ra soat'!$L:$L,'1.DC_Ra soat'!$F:$F,'1.PL (VND) '!CV$4,'1.DC_Ra soat'!$I:$I,'1.PL (VND) '!$C9) -> 0 | CW9: =-SUMIFS('1.DC_Ra soat'!$L:$L,'1.DC_Ra soat'!$F:$F,'1.PL (VND) '!CW$4,'1.DC_Ra soat'!$H:$H,'1.PL (VND) '!$C9)+SUMIFS('1.DC_Ra soat'!$L:$L,'1.DC_Ra soat'!$F:$F,'1.PL (VND) '!CW$4,'1.DC_Ra soat'!$I:$I,'1.PL (VND) '!$C9) -> 0 | CX9: =-SUMIFS('1.DC_Ra soat'!$L:$L,'1.DC_Ra soat'!$F:$F,'1.PL (VND) '!CX$4,'1.DC_Ra soat'!$H:$H,'1.PL (VND) '!$C9)+SUMIFS('1.DC_Ra soat'!$L:$L,'1.DC_Ra soat'!$F:$F,'1.PL (VND) '!CX$4,'1.DC_Ra soat'!$I:$I,'1.PL (VND) '!$C9) -> 0 | CZ9: =CP9+CU9 -> 0 | DA9: =CQ9+CV9 -> 0 | DB9: =CR9+CW9 -> 311800426 | DC9: =CS9+CX9 -> 0
B10: 3. Doanh thu thuần bán hàng | C10: 10 | D10: =D8-D9 -> 272815509098 | E10: =SUM(E8:E9) -> 361225907557 | F10: =SUM(F8:F9) -> 423991405801 | G10: =G8-G9 -> 441344076314 | I10: =I8-I9 -> 0 | J10: =J8-J9 -> 41462536713 | K10: =K8-K9 -> 69811635749 | L10: =L8-L9 -> 74678752638 | N10: =N8-N9 -> 59548559255 | O10: =O8-O9 -> 54917326996 | P10: =P8-P9 -> 64008838727 | Q10: =Q8-Q9 -> 58809727981 | S10: =S8-S9 -> 20700982927 | T10: =T8-T9 -> 43997295527 | U10: =U8-U9 -> 45487103106 | V10: =V8-V9 -> 43100304580 | X10: =X8-X9 -> 0 | Y10: =Y8-Y9 -> 0 | Z10: =Z8-Z9 -> 0 | AA10: =AA8-AA9 -> 0 | AC10: =AC8-AC9 -> 0 | AD10: =AD8-AD9 -> 0 | AE10: =AE8-AE9 -> 0 | AF10: =AF8-AF9 -> 0 | AH10: =AH8-AH9 -> 0 | AI10: =SUM(AI8:AI9) -> 0 | AJ10: =SUM(AJ8:AJ9) -> 0 | AK10: =SUM(AK8:AK9) -> 0 | AM10: =AM8-AM9 -> 0 | AN10: =AN8-AN9 -> 0 | AO10: =AO8-AO9 -> 0 | AP10: =AP8-AP9 -> 0 | AR10: =AR8-AR9 -> 0 | AS10: =AS8-AS9 -> 0 | AT10: =AT8-AT9 -> 0 | AU10: =AU8-AU9 -> 0 | AW10: =AW8-AW9 -> 0 | AX10: =AX8-AX9 -> 0 | AY10: =AY8-AY9 -> 0 | AZ10: =AZ8-AZ9 -> 0 | BB10: =BB8-BB9 -> 0 | BC10: =BC8-BC9 -> 0 | BD10: =BD8-BD9 -> 0 | BG10: =BG8-BG9 -> 0 | BH10: =BH8-BH9 -> 0 | BI10: =BI8-BI9 -> 0 | BL10: =D10+AH10 -> 272815509098 | BM10: =E10+AI10 -> 361225907557 | BN10: =F10+AJ10 -> 423991405801 | BO10: =G10+AK10 -> 441344076314 | BQ10: =I10+AM10 -> 0 | BR10: =J10+AN10 -> 41462536713 | BS10: =K10+AO10 -> 69811635749 | BT10: =L10+AP10 -> 74678752638 | BV10: =N10+AR10 -> 59548559255 | BW10: =O10+AS10 -> 54917326996 | BX10: =P10+AT10 -> 64008838727 | BY10: =Q10+AU10 -> 58809727981 | CA10: =S10+AW10 -> 20700982927 | CB10: =T10+AX10 -> 43997295527 | CC10: =U10+AY10 -> 45487103106 | CD10: =V10+AZ10 -> 43100304580 | CF10: =X10+BB10 -> 0 | CG10: =Y10+BC10 -> 0 | CH10: =Z10+BD10 -> 0 | CI10: =AA10+BE10 -> 0 | CK10: =AC10+BG10 -> 0 | CL10: =AD10+BH10 -> 0 | CM10: =AE10+BI10 -> 0 | CN10: =AF10+BJ10 -> 0 | CP10: =SUMIF($BL$6:$CD$6,CP$6,$BL10:$CD10) -> 353065051280 | CQ10: =SUMIF($BL$6:$CD$6,CQ$6,$BL10:$CD10) -> 501603066793 | CR10: =SUMIF($BL$6:$CD$6,CR$6,$BL10:$CD10) -> 603298983383 | CS10: =SUMIF($BL$6:$CD$6,CS$6,$BL10:$CD10) -> 617932861513 | CU10: =CU8-CU9 -> 0 | CV10: =CV8-CV9 -> 0 | CW10: =CW8-CW9 -> -97491273670 | CX10: =CX8-CX9 -> -85934511540 | CZ10: =CP10+CU10 -> 353065051280 | DA10: =CQ10+CV10 -> 501603066793 | DB10: =CR10+CW10 -> 505807709713 | DC10: =CS10+CX10 -> 531998349973
B11: 4. Giá vốn hàng bán | C11: 11 | D11: 258558885567 | E11: 344462402703 | F11: 407464072565 | G11: 407961793699 | J11: 39077128120 | K11: 70442604236 | L11: 41666803163 | N11: 53813171869 | O11: 47543364530 | P11: 60151917597 | Q11: 58359783404 | S11: 20334102810 | T11: 41893581101 | U11: 44696628066 | V11: 42396032419 | AH11: =SUMIFS('1.DC_Ra soat'!$L:$L,'1.DC_Ra soat'!$F:$F,'1.PL (VND) '!AH$4,'1.DC_Ra soat'!$H:$H,'1.PL (VND) '!$C11)-SUMIFS('1.DC_Ra soat'!$L:$L,'1.DC_Ra soat'!$F:$F,'1.PL (VND) '!AH$4,'1.DC_Ra soat'!$I:$I,'1.PL (VND) '!$C11) -> 0 | AI11: =SUMIFS('1.DC_Ra soat'!$L:$L,'1.DC_Ra soat'!$F:$F,'1.PL (VND) '!AI$4,'1.DC_Ra soat'!$H:$H,'1.PL (VND) '!$C11)-SUMIFS('1.DC_Ra soat'!$L:$L,'1.DC_Ra soat'!$F:$F,'1.PL (VND) '!AI$4,'1.DC_Ra soat'!$I:$I,'1.PL (VND) '!$C11) -> 0 | AJ11: =SUMIFS('1.DC_Ra soat'!$L:$L,'1.DC_Ra soat'!$F:$F,'1.PL (VND) '!AJ$4,'1.DC_Ra soat'!$H:$H,'1.PL (VND) '!$C11)-SUMIFS('1.DC_Ra soat'!$L:$L,'1.DC_Ra soat'!$F:$F,'1.PL (VND) '!AJ$4,'1.DC_Ra soat'!$I:$I,'1.PL (VND) '!$C11) -> 5249296703 | AK11: =SUMIFS('1.DC_Ra soat'!$L:$L,'1.DC_Ra soat'!$F:$F,'1.PL (VND) '!AK$4,'1.DC_Ra soat'!$H:$H,'1.PL (VND) '!$C11)-SUMIFS('1.DC_Ra soat'!$L:$L,'1.DC_Ra soat'!$F:$F,'1.PL (VND) '!AK$4,'1.DC_Ra soat'!$I:$I,'1.PL (VND) '!$C11) -> 1073603888 | AM11: =SUMIFS('1.DC_Ra soat'!$L:$L,'1.DC_Ra soat'!$F:$F,'1.PL (VND) '!AM$4,'1.DC_Ra soat'!$H:$H,'1.PL (VND) '!$C11)-SUMIFS('1.DC_Ra soat'!$L:$L,'1.DC_Ra soat'!$F:$F,'1.PL (VND) '!AM$4,'1.DC_Ra soat'!$I:$I,'1.PL (VND) '!$C11) -> 0 | AN11: =SUMIFS('1.DC_Ra soat'!$L:$L,'1.DC_Ra soat'!$F:$F,'1.PL (VND) '!AN$4,'1.DC_Ra soat'!$H:$H,'1.PL (VND) '!$C11)-SUMIFS('1.DC_Ra soat'!$L:$L,'1.DC_Ra soat'!$F:$F,'1.PL (VND) '!AN$4,'1.DC_Ra soat'!$I:$I,'1.PL (VND) '!$C11) -> 0 | AO11: =SUMIFS('1.DC_Ra soat'!$L:$L,'1.DC_Ra soat'!$F:$F,'1.PL (VND) '!AO$4,'1.DC_Ra soat'!$H:$H,'1.PL (VND) '!$C11)-SUMIFS('1.DC_Ra soat'!$L:$L,'1.DC_Ra soat'!$F:$F,'1.PL (VND) '!AO$4,'1.DC_Ra soat'!$I:$I,'1.PL (VND) '!$C11) -> 0 | AP11: =SUMIFS('1.DC_Ra soat'!$L:$L,'1.DC_Ra soat'!$F:$F,'1.PL (VND) '!AP$4,'1.DC_Ra soat'!$H:$H,'1.PL (VND) '!$C11)-SUMIFS('1.DC_Ra soat'!$L:$L,'1.DC_Ra soat'!$F:$F,'1.PL (VND) '!AP$4,'1.DC_Ra soat'!$I:$I,'1.PL (VND) '!$C11) -> 0 | AR11: =SUMIFS('1.DC_Ra soat'!$L:$L,'1.DC_Ra soat'!$F:$F,'1.PL (VND) '!AR$4,'1.DC_Ra soat'!$H:$H,'1.PL (VND) '!$C11)-SUMIFS('1.DC_Ra soat'!$L:$L,'1.DC_Ra soat'!$F:$F,'1.PL (VND) '!AR$4,'1.DC_Ra soat'!$I:$I,'1.PL (VND) '!$C11) -> 0 | AS11: =SUMIFS('1.DC_Ra soat'!$L:$L,'1.DC_Ra soat'!$F:$F,'1.PL (VND) '!AS$4,'1.DC_Ra soat'!$H:$H,'1.PL (VND) '!$C11)-SUMIFS('1.DC_Ra soat'!$L:$L,'1.DC_Ra soat'!$F:$F,'1.PL (VND) '!AS$4,'1.DC_Ra soat'!$I:$I,'1.PL (VND) '!$C11) -> 0 | AT11: =SUMIFS('1.DC_Ra soat'!$L:$L,'1.DC_Ra soat'!$F:$F,'1.PL (VND) '!AT$4,'1.DC_Ra soat'!$H:$H,'1.PL (VND) '!$C11)-SUMIFS('1.DC_Ra soat'!$L:$L,'1.DC_Ra soat'!$F:$F,'1.PL (VND) '!AT$4,'1.DC_Ra soat'!$I:$I,'1.PL (VND) '!$C11) -> 0 | AU11: =SUMIFS('1.DC_Ra soat'!$L:$L,'1.DC_Ra soat'!$F:$F,'1.PL (VND) '!AU$4,'1.DC_Ra soat'!$H:$H,'1.PL (VND) '!$C11)-SUMIFS('1.DC_Ra soat'!$L:$L,'1.DC_Ra soat'!$F:$F,'1.PL (VND) '!AU$4,'1.DC_Ra soat'!$I:$I,'1.PL (VND) '!$C11) -> 0 | AW11: =SUMIFS('1.DC_Ra soat'!$L:$L,'1.DC_Ra soat'!$F:$F,'1.PL (VND) '!AW$4,'1.DC_Ra soat'!$H:$H,'1.PL (VND) '!$C11)-SUMIFS('1.DC_Ra soat'!$L:$L,'1.DC_Ra soat'!$F:$F,'1.PL (VND) '!AW$4,'1.DC_Ra soat'!$I:$I,'1.PL (VND) '!$C11) -> 0 | AX11: =SUMIFS('1.DC_Ra soat'!$L:$L,'1.DC_Ra soat'!$F:$F,'1.PL (VND) '!AX$4,'1.DC_Ra soat'!$H:$H,'1.PL (VND) '!$C11)-SUMIFS('1.DC_Ra soat'!$L:$L,'1.DC_Ra soat'!$F:$F,'1.PL (VND) '!AX$4,'1.DC_Ra soat'!$I:$I,'1.PL (VND) '!$C11) -> 0 | AY11: =SUMIFS('1.DC_Ra soat'!$L:$L,'1.DC_Ra soat'!$F:$F,'1.PL (VND) '!AY$4,'1.DC_Ra soat'!$H:$H,'1.PL (VND) '!$C11)-SUMIFS('1.DC_Ra soat'!$L:$L,'1.DC_Ra soat'!$F:$F,'1.PL (VND) '!AY$4,'1.DC_Ra soat'!$I:$I,'1.PL (VND) '!$C11) -> 0 | AZ11: =SUMIFS('1.DC_Ra soat'!$L:$L,'1.DC_Ra soat'!$F:$F,'1.PL (VND) '!AZ$4,'1.DC_Ra soat'!$H:$H,'1.PL (VND) '!$C11)-SUMIFS('1.DC_Ra soat'!$L:$L,'1.DC_Ra soat'!$F:$F,'1.PL (VND) '!AZ$4,'1.DC_Ra soat'!$I:$I,'1.PL (VND) '!$C11) -> 0 | BB11: =SUMIFS('1.DC_Ra soat'!$L:$L,'1.DC_Ra soat'!$F:$F,'1.PL (VND) '!BB$4,'1.DC_Ra soat'!$H:$H,'1.PL (VND) '!$C11)-SUMIFS('1.DC_Ra soat'!$L:$L,'1.DC_Ra soat'!$F:$F,'1.PL (VND) '!BB$4,'1.DC_Ra soat'!$I:$I,'1.PL (VND) '!$C11) -> 0 | BC11: =SUMIFS('1.DC_Ra soat'!$L:$L,'1.DC_Ra soat'!$F:$F,'1.PL (VND) '!BC$4,'1.DC_Ra soat'!$H:$H,'1.PL (VND) '!$C11)-SUMIFS('1.DC_Ra soat'!$L:$L,'1.DC_Ra soat'!$F:$F,'1.PL (VND) '!BC$4,'1.DC_Ra soat'!$I:$I,'1.PL (VND) '!$C11) -> 0 | BD11: =SUMIFS('1.DC_Ra soat'!$L:$L,'1.DC_Ra soat'!$F:$F,'1.PL (VND) '!BD$4,'1.DC_Ra soat'!$H:$H,'1.PL (VND) '!$C11)-SUMIFS('1.DC_Ra soat'!$L:$L,'1.DC_Ra soat'!$F:$F,'1.PL (VND) '!BD$4,'1.DC_Ra soat'!$I:$I,'1.PL (VND) '!$C11) -> 0 | BE11: =SUMIFS('1.DC_Ra soat'!$L:$L,'1.DC_Ra soat'!$F:$F,'1.PL (VND) '!BE$4,'1.DC_Ra soat'!$H:$H,'1.PL (VND) '!$C11)-SUMIFS('1.DC_Ra soat'!$L:$L,'1.DC_Ra soat'!$F:$F,'1.PL (VND) '!BE$4,'1.DC_Ra soat'!$I:$I,'1.PL (VND) '!$C11) -> 0 | BG11: =SUMIFS('1.DC_Ra soat'!$L:$L,'1.DC_Ra soat'!$F:$F,'1.PL (VND) '!BG$4,'1.DC_Ra soat'!$H:$H,'1.PL (VND) '!$C11)-SUMIFS('1.DC_Ra soat'!$L:$L,'1.DC_Ra soat'!$F:$F,'1.PL (VND) '!BG$4,'1.DC_Ra soat'!$I:$I,'1.PL (VND) '!$C11) -> 0 | BH11: =SUMIFS('1.DC_Ra soat'!$L:$L,'1.DC_Ra soat'!$F:$F,'1.PL (VND) '!BH$4,'1.DC_Ra soat'!$H:$H,'1.PL (VND) '!$C11)-SUMIFS('1.DC_Ra soat'!$L:$L,'1.DC_Ra soat'!$F:$F,'1.PL (VND) '!BH$4,'1.DC_Ra soat'!$I:$I,'1.PL (VND) '!$C11) -> 0 | BI11: =SUMIFS('1.DC_Ra soat'!$L:$L,'1.DC_Ra soat'!$F:$F,'1.PL (VND) '!BI$4,'1.DC_Ra soat'!$H:$H,'1.PL (VND) '!$C11)-SUMIFS('1.DC_Ra soat'!$L:$L,'1.DC_Ra soat'!$F:$F,'1.PL (VND) '!BI$4,'1.DC_Ra soat'!$I:$I,'1.PL (VND) '!$C11) -> 0 | BJ11: =SUMIFS('1.DC_Ra soat'!$L:$L,'1.DC_Ra soat'!$F:$F,'1.PL (VND) '!BJ$4,'1.DC_Ra soat'!$H:$H,'1.PL (VND) '!$C11)-SUMIFS('1.DC_Ra soat'!$L:$L,'1.DC_Ra soat'!$F:$F,'1.PL (VND) '!BJ$4,'1.DC_Ra soat'!$I:$I,'1.PL (VND) '!$C11) -> 0 | BL11: =D11+AH11 -> 258558885567 | BM11: =E11+AI11 -> 344462402703 | BN11: =F11+AJ11 -> 412713369268 | BO11: =G11+AK11 -> 409035397587 | BQ11: =I11+AM11 -> 0 | BR11: =J11+AN11 -> 39077128120 | BS11: =K11+AO11 -> 70442604236 | BT11: =L11+AP11 -> 41666803163 | BV11: =N11+AR11 -> 53813171869 | BW11: =O11+AS11 -> 47543364530 | BX11: =P11+AT11 -> 60151917597 | BY11: =Q11+AU11 -> 58359783404 | CA11: =S11+AW11 -> 20334102810 | CB11: =T11+AX11 -> 41893581101 | CC11: =U11+AY11 -> 44696628066 | CD11: =V11+AZ11 -> 42396032419 | CF11: =X11+BB11 -> 0 | CG11: =Y11+BC11 -> 0 | CH11: =Z11+BD11 -> 0 | CI11: =AA11+BE11 -> 0 | CK11: =AC11+BG11 -> 0 | CL11: =AD11+BH11 -> 0 | CM11: =AE11+BI11 -> 0 | CN11: =AF11+BJ11 -> 0 | CP11: =SUMIF($BL$6:$CD$6,CP$6,$BL11:$CD11) -> 332706160246 | CQ11: =SUMIF($BL$6:$CD$6,CQ$6,$BL11:$CD11) -> 472976476454 | CR11: =SUMIF($BL$6:$CD$6,CR$6,$BL11:$CD11) -> 588004519167 | CS11: =SUMIF($BL$6:$CD$6,CS$6,$BL11:$CD11) -> 551458016573 | CU11: =SUMIFS('1.DC_Ra soat'!$L:$L,'1.DC_Ra soat'!$F:$F,'1.PL (VND) '!CU$4,'1.DC_Ra soat'!$H:$H,'1.PL (VND) '!$C11)-SUMIFS('1.DC_Ra soat'!$L:$L,'1.DC_Ra soat'!$F:$F,'1.PL (VND) '!CU$4,'1.DC_Ra soat'!$I:$I,'1.PL (VND) '!$C11) -> 0 | CV11: =SUMIFS('1.DC_Ra soat'!$L:$L,'1.DC_Ra soat'!$F:$F,'1.PL (VND) '!CV$4,'1.DC_Ra soat'!$H:$H,'1.PL (VND) '!$C11)-SUMIFS('1.DC_Ra soat'!$L:$L,'1.DC_Ra soat'!$F:$F,'1.PL (VND) '!CV$4,'1.DC_Ra soat'!$I:$I,'1.PL (VND) '!$C11) -> 0 | CW11: =SUMIFS('1.DC_Ra soat'!$L:$L,'1.DC_Ra soat'!$F:$F,'1.PL (VND) '!CW$4,'1.DC_Ra soat'!$H:$H,'1.PL (VND) '!$C11)-SUMIFS('1.DC_Ra soat'!$L:$L,'1.DC_Ra soat'!$F:$F,'1.PL (VND) '!CW$4,'1.DC_Ra soat'!$I:$I,'1.PL (VND) '!$C11) -> -97491273670 | CX11: =SUMIFS('1.DC_Ra soat'!$L:$L,'1.DC_Ra soat'!$F:$F,'1.PL (VND) '!CX$4,'1.DC_Ra soat'!$H:$H,'1.PL (VND) '!$C11)-SUMIFS('1.DC_Ra soat'!$L:$L,'1.DC_Ra soat'!$F:$F,'1.PL (VND) '!CX$4,'1.DC_Ra soat'!$I:$I,'1.PL (VND) '!$C11) -> -85934511540 | CZ11: =CP11+CU11 -> 332706160246 | DA11: =CQ11+CV11 -> 472976476454 | DB11: =CR11+CW11 -> 490513245497 | DC11: =CS11+CX11 -> 465523505033
B12: 5. Lợi nhuận gộp về bán hàng | C12: 20 | D12: =D10-D11 -> 14256623531 | E12: =E10-E11 -> 16763504854 | F12: =F10-F11 -> 16527333236 | G12: =G10-G11 -> 33382282615 | I12: =I10-I11 -> 0 | J12: =J10-J11 -> 2385408593 | K12: =K10-K11 -> -630968487 | L12: =L10-L11 -> 33011949475 | N12: =N10-N11 -> 5735387386 | O12: =O10-O11 -> 7373962466 | P12: =P10-P11 -> 3856921130 | Q12: =Q10-Q11 -> 449944577 | S12: =S10-S11 -> 366880117 | T12: =T10-T11 -> 2103714426 | U12: =U10-U11 -> 790475040 | V12: =V10-V11 -> 704272161 | X12: =X10-X11 -> 0 | Y12: =Y10-Y11 -> 0 | Z12: =Z10-Z11 -> 0 | AA12: =AA10-AA11 -> 0 | AC12: =AC10-AC11 -> 0 | AD12: =AD10-AD11 -> 0 | AE12: =AE10-AE11 -> 0 | AF12: =AF10-AF11 -> 0 | AH12: =AH10-AH11 -> 0 | AI12: =AI10-AI11 -> 0 | AJ12: =AJ10-AJ11 -> -5249296703 | AK12: =AK10-AK11 -> -1073603888 | AM12: =AM10-AM11 -> 0 | AN12: =AN10-AN11 -> 0 | AO12: =AO10-AO11 -> 0 | AP12: =AP10-AP11 -> 0 | AR12: =AR10-AR11 -> 0 | AS12: =AS10-AS11 -> 0 | AT12: =AT10-AT11 -> 0 | AU12: =AU10-AU11 -> 0 | AW12: =AW10-AW11 -> 0 | AX12: =AX10-AX11 -> 0 | AY12: =AY10-AY11 -> 0 | AZ12: =AZ10-AZ11 -> 0 | BB12: =BB10-BB11 -> 0 | BC12: =BC10-BC11 -> 0 | BD12: =BD10-BD11 -> 0 | BG12: =BG10-BG11 -> 0 | BH12: =BH10-BH11 -> 0 | BI12: =BI10-BI11 -> 0 | BL12: =D12+AH12 -> 14256623531 | BM12: =E12+AI12 -> 16763504854 | BN12: =F12+AJ12 -> 11278036533 | BO12: =G12+AK12 -> 32308678727 | BQ12: =I12+AM12 -> 0 | BR12: =J12+AN12 -> 2385408593 | BS12: =K12+AO12 -> -630968487 | BT12: =L12+AP12 -> 33011949475 | BV12: =N12+AR12 -> 5735387386 | BW12: =O12+AS12 -> 7373962466 | BX12: =P12+AT12 -> 3856921130 | BY12: =Q12+AU12 -> 449944577 | CA12: =S12+AW12 -> 366880117 | CB12: =T12+AX12 -> 2103714426 | CC12: =U12+AY12 -> 790475040 | CD12: =V12+AZ12 -> 704272161 | CF12: =X12+BB12 -> 0 | CG12: =Y12+BC12 -> 0 | CH12: =Z12+BD12 -> 0 | CI12: =AA12+BE12 -> 0 | CK12: =AC12+BG12 -> 0 | CL12: =AD12+BH12 -> 0 | CM12: =AE12+BI12 -> 0 | CN12: =AF12+BJ12 -> 0 | CP12: =SUMIF($BL$6:$CD$6,CP$6,$BL12:$CD12) -> 20358891034 | CQ12: =SUMIF($BL$6:$CD$6,CQ$6,$BL12:$CD12) -> 28626590339 | CR12: =SUMIF($BL$6:$CD$6,CR$6,$BL12:$CD12) -> 15294464216 | CS12: =SUMIF($BL$6:$CD$6,CS$6,$BL12:$CD12) -> 66474844940 | CU12: =CU10-CU11 -> 0 | CV12: =CV10-CV11 -> 0 | CW12: =CW10-CW11 -> 0 | CX12: =CX10-CX11 -> 0 | CZ12: =CP12+CU12 -> 20358891034 | DA12: =CQ12+CV12 -> 28626590339 | DB12: =CR12+CW12 -> 15294464216 | DC12: =CS12+CX12 -> 66474844940
B13: 6. Doanh thu hoạt động tài chính | C13: 21 | D13: 833883 | E13: 524620 | F13: 2988510 | G13: 38735873 | I13: 1151 | J13: 28281 | K13: 135642 | L13: 99182 | N13: 87952 | O13: 42349 | P13: 154503 | Q13: 102331 | S13: 50076 | T13: 98187 | U13: 64876 | V13: 71367 | AH13: =-SUMIFS('1.DC_Ra soat'!$L:$L,'1.DC_Ra soat'!$F:$F,'1.PL (VND) '!AH$4,'1.DC_Ra soat'!$H:$H,'1.PL (VND) '!$C13)+SUMIFS('1.DC_Ra soat'!$L:$L,'1.DC_Ra soat'!$F:$F,'1.PL (VND) '!AH$4,'1.DC_Ra soat'!$I:$I,'1.PL (VND) '!$C13) -> 0 | AI13: =-SUMIFS('1.DC_Ra soat'!$L:$L,'1.DC_Ra soat'!$F:$F,'1.PL (VND) '!AI$4,'1.DC_Ra soat'!$H:$H,'1.PL (VND) '!$C13)+SUMIFS('1.DC_Ra soat'!$L:$L,'1.DC_Ra soat'!$F:$F,'1.PL (VND) '!AI$4,'1.DC_Ra soat'!$I:$I,'1.PL (VND) '!$C13) -> 0 | AJ13: =-SUMIFS('1.DC_Ra soat'!$L:$L,'1.DC_Ra soat'!$F:$F,'1.PL (VND) '!AJ$4,'1.DC_Ra soat'!$H:$H,'1.PL (VND) '!$C13)+SUMIFS('1.DC_Ra soat'!$L:$L,'1.DC_Ra soat'!$F:$F,'1.PL (VND) '!AJ$4,'1.DC_Ra soat'!$I:$I,'1.PL (VND) '!$C13) -> 0 | AK13: =-SUMIFS('1.DC_Ra soat'!$L:$L,'1.DC_Ra soat'!$F:$F,'1.PL (VND) '!AK$4,'1.DC_Ra soat'!$H:$H,'1.PL (VND) '!$C13)+SUMIFS('1.DC_Ra soat'!$L:$L,'1.DC_Ra soat'!$F:$F,'1.PL (VND) '!AK$4,'1.DC_Ra soat'!$I:$I,'1.PL (VND) '!$C13) -> 0 | AM13: =-SUMIFS('1.DC_Ra soat'!$L:$L,'1.DC_Ra soat'!$F:$F,'1.PL (VND) '!AM$4,'1.DC_Ra soat'!$H:$H,'1.PL (VND) '!$C13)+SUMIFS('1.DC_Ra soat'!$L:$L,'1.DC_Ra soat'!$F:$F,'1.PL (VND) '!AM$4,'1.DC_Ra soat'!$I:$I,'1.PL (VND) '!$C13) -> 0 | AN13: =-SUMIFS('1.DC_Ra soat'!$L:$L,'1.DC_Ra soat'!$F:$F,'1.PL (VND) '!AN$4,'1.DC_Ra soat'!$H:$H,'1.PL (VND) '!$C13)+SUMIFS('1.DC_Ra soat'!$L:$L,'1.DC_Ra soat'!$F:$F,'1.PL (VND) '!AN$4,'1.DC_Ra soat'!$I:$I,'1.PL (VND) '!$C13) -> 0 | AO13: =-SUMIFS('1.DC_Ra soat'!$L:$L,'1.DC_Ra soat'!$F:$F,'1.PL (VND) '!AO$4,'1.DC_Ra soat'!$H:$H,'1.PL (VND) '!$C13)+SUMIFS('1.DC_Ra soat'!$L:$L,'1.DC_Ra soat'!$F:$F,'1.PL (VND) '!AO$4,'1.DC_Ra soat'!$I:$I,'1.PL (VND) '!$C13) -> 0 | AP13: =-SUMIFS('1.DC_Ra soat'!$L:$L,'1.DC_Ra soat'!$F:$F,'1.PL (VND) '!AP$4,'1.DC_Ra soat'!$H:$H,'1.PL (VND) '!$C13)+SUMIFS('1.DC_Ra soat'!$L:$L,'1.DC_Ra soat'!$F:$F,'1.PL (VND) '!AP$4,'1.DC_Ra soat'!$I:$I,'1.PL (VND) '!$C13) -> 0 | AR13: =-SUMIFS('1.DC_Ra soat'!$L:$L,'1.DC_Ra soat'!$F:$F,'1.PL (VND) '!AR$4,'1.DC_Ra soat'!$H:$H,'1.PL (VND) '!$C13)+SUMIFS('1.DC_Ra soat'!$L:$L,'1.DC_Ra soat'!$F:$F,'1.PL (VND) '!AR$4,'1.DC_Ra soat'!$I:$I,'1.PL (VND) '!$C13) -> 0 | AS13: =-SUMIFS('1.DC_Ra soat'!$L:$L,'1.DC_Ra soat'!$F:$F,'1.PL (VND) '!AS$4,'1.DC_Ra soat'!$H:$H,'1.PL (VND) '!$C13)+SUMIFS('1.DC_Ra soat'!$L:$L,'1.DC_Ra soat'!$F:$F,'1.PL (VND) '!AS$4,'1.DC_Ra soat'!$I:$I,'1.PL (VND) '!$C13) -> 0 | AT13: =-SUMIFS('1.DC_Ra soat'!$L:$L,'1.DC_Ra soat'!$F:$F,'1.PL (VND) '!AT$4,'1.DC_Ra soat'!$H:$H,'1.PL (VND) '!$C13)+SUMIFS('1.DC_Ra soat'!$L:$L,'1.DC_Ra soat'!$F:$F,'1.PL (VND) '!AT$4,'1.DC_Ra soat'!$I:$I,'1.PL (VND) '!$C13) -> 0 | AU13: =-SUMIFS('1.DC_Ra soat'!$L:$L,'1.DC_Ra soat'!$F:$F,'1.PL (VND) '!AU$4,'1.DC_Ra soat'!$H:$H,'1.PL (VND) '!$C13)+SUMIFS('1.DC_Ra soat'!$L:$L,'1.DC_Ra soat'!$F:$F,'1.PL (VND) '!AU$4,'1.DC_Ra soat'!$I:$I,'1.PL (VND) '!$C13) -> 0 | AW13: =-SUMIFS('1.DC_Ra soat'!$L:$L,'1.DC_Ra soat'!$F:$F,'1.PL (VND) '!AW$4,'1.DC_Ra soat'!$H:$H,'1.PL (VND) '!$C13)+SUMIFS('1.DC_Ra soat'!$L:$L,'1.DC_Ra soat'!$F:$F,'1.PL (VND) '!AW$4,'1.DC_Ra soat'!$I:$I,'1.PL (VND) '!$C13) -> 0 | AX13: =-SUMIFS('1.DC_Ra soat'!$L:$L,'1.DC_Ra soat'!$F:$F,'1.PL (VND) '!AX$4,'1.DC_Ra soat'!$H:$H,'1.PL (VND) '!$C13)+SUMIFS('1.DC_Ra soat'!$L:$L,'1.DC_Ra soat'!$F:$F,'1.PL (VND) '!AX$4,'1.DC_Ra soat'!$I:$I,'1.PL (VND) '!$C13) -> 0 | AY13: =-SUMIFS('1.DC_Ra soat'!$L:$L,'1.DC_Ra soat'!$F:$F,'1.PL (VND) '!AY$4,'1.DC_Ra soat'!$H:$H,'1.PL (VND) '!$C13)+SUMIFS('1.DC_Ra soat'!$L:$L,'1.DC_Ra soat'!$F:$F,'1.PL (VND) '!AY$4,'1.DC_Ra soat'!$I:$I,'1.PL (VND) '!$C13) -> 0 | AZ13: =-SUMIFS('1.DC_Ra soat'!$L:$L,'1.DC_Ra soat'!$F:$F,'1.PL (VND) '!AZ$4,'1.DC_Ra soat'!$H:$H,'1.PL (VND) '!$C13)+SUMIFS('1.DC_Ra soat'!$L:$L,'1.DC_Ra soat'!$F:$F,'1.PL (VND) '!AZ$4,'1.DC_Ra soat'!$I:$I,'1.PL (VND) '!$C13) -> 0 | BB13: =-SUMIFS('1.DC_Ra soat'!$L:$L,'1.DC_Ra soat'!$F:$F,'1.PL (VND) '!BB$4,'1.DC_Ra soat'!$H:$H,'1.PL (VND) '!$C13)+SUMIFS('1.DC_Ra soat'!$L:$L,'1.DC_Ra soat'!$F:$F,'1.PL (VND) '!BB$4,'1.DC_Ra soat'!$I:$I,'1.PL (VND) '!$C13) -> 0 | BC13: =-SUMIFS('1.DC_Ra soat'!$L:$L,'1.DC_Ra soat'!$F:$F,'1.PL (VND) '!BC$4,'1.DC_Ra soat'!$H:$H,'1.PL (VND) '!$C13)+SUMIFS('1.DC_Ra soat'!$L:$L,'1.DC_Ra soat'!$F:$F,'1.PL (VND) '!BC$4,'1.DC_Ra soat'!$I:$I,'1.PL (VND) '!$C13) -> 0 | BD13: =-SUMIFS('1.DC_Ra soat'!$L:$L,'1.DC_Ra soat'!$F:$F,'1.PL (VND) '!BD$4,'1.DC_Ra soat'!$H:$H,'1.PL (VND) '!$C13)+SUMIFS('1.DC_Ra soat'!$L:$L,'1.DC_Ra soat'!$F:$F,'1.PL (VND) '!BD$4,'1.DC_Ra soat'!$I:$I,'1.PL (VND) '!$C13) -> 0 | BE13: =-SUMIFS('1.DC_Ra soat'!$L:$L,'1.DC_Ra soat'!$F:$F,'1.PL (VND) '!BE$4,'1.DC_Ra soat'!$H:$H,'1.PL (VND) '!$C13)+SUMIFS('1.DC_Ra soat'!$L:$L,'1.DC_Ra soat'!$F:$F,'1.PL (VND) '!BE$4,'1.DC_Ra soat'!$I:$I,'1.PL (VND) '!$C13) -> 0 | BG13: =-SUMIFS('1.DC_Ra soat'!$L:$L,'1.DC_Ra soat'!$F:$F,'1.PL (VND) '!BG$4,'1.DC_Ra soat'!$H:$H,'1.PL (VND) '!$C13)+SUMIFS('1.DC_Ra soat'!$L:$L,'1.DC_Ra soat'!$F:$F,'1.PL (VND) '!BG$4,'1.DC_Ra soat'!$I:$I,'1.PL (VND) '!$C13) -> 0 | BH13: =-SUMIFS('1.DC_Ra soat'!$L:$L,'1.DC_Ra soat'!$F:$F,'1.PL (VND) '!BH$4,'1.DC_Ra soat'!$H:$H,'1.PL (VND) '!$C13)+SUMIFS('1.DC_Ra soat'!$L:$L,'1.DC_Ra soat'!$F:$F,'1.PL (VND) '!BH$4,'1.DC_Ra soat'!$I:$I,'1.PL (VND) '!$C13) -> 0 | BI13: =-SUMIFS('1.DC_Ra soat'!$L:$L,'1.DC_Ra soat'!$F:$F,'1.PL (VND) '!BI$4,'1.DC_Ra soat'!$H:$H,'1.PL (VND) '!$C13)+SUMIFS('1.DC_Ra soat'!$L:$L,'1.DC_Ra soat'!$F:$F,'1.PL (VND) '!BI$4,'1.DC_Ra soat'!$I:$I,'1.PL (VND) '!$C13) -> 0 | BJ13: =-SUMIFS('1.DC_Ra soat'!$L:$L,'1.DC_Ra soat'!$F:$F,'1.PL (VND) '!BJ$4,'1.DC_Ra soat'!$H:$H,'1.PL (VND) '!$C13)+SUMIFS('1.DC_Ra soat'!$L:$L,'1.DC_Ra soat'!$F:$F,'1.PL (VND) '!BJ$4,'1.DC_Ra soat'!$I:$I,'1.PL (VND) '!$C13) -> 0 | BL13: =D13+AH13 -> 833883 | BM13: =E13+AI13 -> 524620 | BN13: =F13+AJ13 -> 2988510 | BO13: =G13+AK13 -> 38735873 | BQ13: =I13+AM13 -> 1151 | BR13: =J13+AN13 -> 28281 | BS13: =K13+AO13 -> 135642 | BT13: =L13+AP13 -> 99182 | BV13: =N13+AR13 -> 87952 | BW13: =O13+AS13 -> 42349 | BX13: =P13+AT13 -> 154503 | BY13: =Q13+AU13 -> 102331 | CA13: =S13+AW13 -> 50076 | CB13: =T13+AX13 -> 98187 | CC13: =U13+AY13 -> 64876 | CD13: =V13+AZ13 -> 71367 | CF13: =X13+BB13 -> 0 | CG13: =Y13+BC13 -> 0 | CH13: =Z13+BD13 -> 0 | CI13: =AA13+BE13 -> 0 | CK13: =AC13+BG13 -> 0 | CL13: =AD13+BH13 -> 0 | CM13: =AE13+BI13 -> 0 | CN13: =AF13+BJ13 -> 0 | CP13: =SUMIF($BL$6:$CD$6,CP$6,$BL13:$CD13) -> 973062 | CQ13: =SUMIF($BL$6:$CD$6,CQ$6,$BL13:$CD13) -> 693437 | CR13: =SUMIF($BL$6:$CD$6,CR$6,$BL13:$CD13) -> 3343531 | CS13: =SUMIF($BL$6:$CD$6,CS$6,$BL13:$CD13) -> 39008753 | CU13: =-SUMIFS('1.DC_Ra soat'!$L:$L,'1.DC_Ra soat'!$F:$F,'1.PL (VND) '!CU$4,'1.DC_Ra soat'!$H:$H,'1.PL (VND) '!$C13)+SUMIFS('1.DC_Ra soat'!$L:$L,'1.DC_Ra soat'!$F:$F,'1.PL (VND) '!CU$4,'1.DC_Ra soat'!$I:$I,'1.PL (VND) '!$C13) -> 0 | CV13: =-SUMIFS('1.DC_Ra soat'!$L:$L,'1.DC_Ra soat'!$F:$F,'1.PL (VND) '!CV$4,'1.DC_Ra soat'!$H:$H,'1.PL (VND) '!$C13)+SUMIFS('1.DC_Ra soat'!$L:$L,'1.DC_Ra soat'!$F:$F,'1.PL (VND) '!CV$4,'1.DC_Ra soat'!$I:$I,'1.PL (VND) '!$C13) -> 0 | CW13: =-SUMIFS('1.DC_Ra soat'!$L:$L,'1.DC_Ra soat'!$F:$F,'1.PL (VND) '!CW$4,'1.DC_Ra soat'!$H:$H,'1.PL (VND) '!$C13)+SUMIFS('1.DC_Ra soat'!$L:$L,'1.DC_Ra soat'!$F:$F,'1.PL (VND) '!CW$4,'1.DC_Ra soat'!$I:$I,'1.PL (VND) '!$C13) -> 0 | CX13: =-SUMIFS('1.DC_Ra soat'!$L:$L,'1.DC_Ra soat'!$F:$F,'1.PL (VND) '!CX$4,'1.DC_Ra soat'!$H:$H,'1.PL (VND) '!$C13)+SUMIFS('1.DC_Ra soat'!$L:$L,'1.DC_Ra soat'!$F:$F,'1.PL (VND) '!CX$4,'1.DC_Ra soat'!$I:$I,'1.PL (VND) '!$C13) -> 0 | CZ13: =CP13+CU13 -> 973062 | DA13: =CQ13+CV13 -> 693437 | DB13: =CR13+CW13 -> 3343531 | DC13: =CS13+CX13 -> 39008753
B14: 7. Chi phí tài chính | C14: 22 | D14: 8171598143 | E14: 4496061333 | F14: 8332900199 | G14: 12548808701 | J14: 725227638 | K14: 2586469172 | L14: 1890560444 | N14: 1336298435 | O14: 1675370773 | P14: 2178070579 | Q14: 2214890036 | S14: 296662990 | T14: 832438007 | U14: 1092759146 | V14: 1540066497 | AH14: =SUMIFS('1.DC_Ra soat'!$L:$L,'1.DC_Ra soat'!$F:$F,'1.PL (VND) '!AH$4,'1.DC_Ra soat'!$H:$H,'1.PL (VND) '!$C14)-SUMIFS('1.DC_Ra soat'!$L:$L,'1.DC_Ra soat'!$F:$F,'1.PL (VND) '!AH$4,'1.DC_Ra soat'!$I:$I,'1.PL (VND) '!$C14) -> 0 | AI14: =SUMIFS('1.DC_Ra soat'!$L:$L,'1.DC_Ra soat'!$F:$F,'1.PL (VND) '!AI$4,'1.DC_Ra soat'!$H:$H,'1.PL (VND) '!$C14)-SUMIFS('1.DC_Ra soat'!$L:$L,'1.DC_Ra soat'!$F:$F,'1.PL (VND) '!AI$4,'1.DC_Ra soat'!$I:$I,'1.PL (VND) '!$C14) -> 0 | AJ14: =SUMIFS('1.DC_Ra soat'!$L:$L,'1.DC_Ra soat'!$F:$F,'1.PL (VND) '!AJ$4,'1.DC_Ra soat'!$H:$H,'1.PL (VND) '!$C14)-SUMIFS('1.DC_Ra soat'!$L:$L,'1.DC_Ra soat'!$F:$F,'1.PL (VND) '!AJ$4,'1.DC_Ra soat'!$I:$I,'1.PL (VND) '!$C14) -> 5500420923 | AK14: =SUMIFS('1.DC_Ra soat'!$L:$L,'1.DC_Ra soat'!$F:$F,'1.PL (VND) '!AK$4,'1.DC_Ra soat'!$H:$H,'1.PL (VND) '!$C14)-SUMIFS('1.DC_Ra soat'!$L:$L,'1.DC_Ra soat'!$F:$F,'1.PL (VND) '!AK$4,'1.DC_Ra soat'!$I:$I,'1.PL (VND) '!$C14) -> 0 | AM14: =SUMIFS('1.DC_Ra soat'!$L:$L,'1.DC_Ra soat'!$F:$F,'1.PL (VND) '!AM$4,'1.DC_Ra soat'!$H:$H,'1.PL (VND) '!$C14)-SUMIFS('1.DC_Ra soat'!$L:$L,'1.DC_Ra soat'!$F:$F,'1.PL (VND) '!AM$4,'1.DC_Ra soat'!$I:$I,'1.PL (VND) '!$C14) -> 0 | AN14: =SUMIFS('1.DC_Ra soat'!$L:$L,'1.DC_Ra soat'!$F:$F,'1.PL (VND) '!AN$4,'1.DC_Ra soat'!$H:$H,'1.PL (VND) '!$C14)-SUMIFS('1.DC_Ra soat'!$L:$L,'1.DC_Ra soat'!$F:$F,'1.PL (VND) '!AN$4,'1.DC_Ra soat'!$I:$I,'1.PL (VND) '!$C14) -> 0 | AO14: =SUMIFS('1.DC_Ra soat'!$L:$L,'1.DC_Ra soat'!$F:$F,'1.PL (VND) '!AO$4,'1.DC_Ra soat'!$H:$H,'1.PL (VND) '!$C14)-SUMIFS('1.DC_Ra soat'!$L:$L,'1.DC_Ra soat'!$F:$F,'1.PL (VND) '!AO$4,'1.DC_Ra soat'!$I:$I,'1.PL (VND) '!$C14) -> 741540549 | AP14: =SUMIFS('1.DC_Ra soat'!$L:$L,'1.DC_Ra soat'!$F:$F,'1.PL (VND) '!AP$4,'1.DC_Ra soat'!$H:$H,'1.PL (VND) '!$C14)-SUMIFS('1.DC_Ra soat'!$L:$L,'1.DC_Ra soat'!$F:$F,'1.PL (VND) '!AP$4,'1.DC_Ra soat'!$I:$I,'1.PL (VND) '!$C14) -> 0 | AR14: =SUMIFS('1.DC_Ra soat'!$L:$L,'1.DC_Ra soat'!$F:$F,'1.PL (VND) '!AR$4,'1.DC_Ra soat'!$H:$H,'1.PL (VND) '!$C14)-SUMIFS('1.DC_Ra soat'!$L:$L,'1.DC_Ra soat'!$F:$F,'1.PL (VND) '!AR$4,'1.DC_Ra soat'!$I:$I,'1.PL (VND) '!$C14) -> 0 | AS14: =SUMIFS('1.DC_Ra soat'!$L:$L,'1.DC_Ra soat'!$F:$F,'1.PL (VND) '!AS$4,'1.DC_Ra soat'!$H:$H,'1.PL (VND) '!$C14)-SUMIFS('1.DC_Ra soat'!$L:$L,'1.DC_Ra soat'!$F:$F,'1.PL (VND) '!AS$4,'1.DC_Ra soat'!$I:$I,'1.PL (VND) '!$C14) -> 0 | AT14: =SUMIFS('1.DC_Ra soat'!$L:$L,'1.DC_Ra soat'!$F:$F,'1.PL (VND) '!AT$4,'1.DC_Ra soat'!$H:$H,'1.PL (VND) '!$C14)-SUMIFS('1.DC_Ra soat'!$L:$L,'1.DC_Ra soat'!$F:$F,'1.PL (VND) '!AT$4,'1.DC_Ra soat'!$I:$I,'1.PL (VND) '!$C14) -> 0 | AU14: =SUMIFS('1.DC_Ra soat'!$L:$L,'1.DC_Ra soat'!$F:$F,'1.PL (VND) '!AU$4,'1.DC_Ra soat'!$H:$H,'1.PL (VND) '!$C14)-SUMIFS('1.DC_Ra soat'!$L:$L,'1.DC_Ra soat'!$F:$F,'1.PL (VND) '!AU$4,'1.DC_Ra soat'!$I:$I,'1.PL (VND) '!$C14) -> 0 | AW14: =SUMIFS('1.DC_Ra soat'!$L:$L,'1.DC_Ra soat'!$F:$F,'1.PL (VND) '!AW$4,'1.DC_Ra soat'!$H:$H,'1.PL (VND) '!$C14)-SUMIFS('1.DC_Ra soat'!$L:$L,'1.DC_Ra soat'!$F:$F,'1.PL (VND) '!AW$4,'1.DC_Ra soat'!$I:$I,'1.PL (VND) '!$C14) -> 0 | AX14: =SUMIFS('1.DC_Ra soat'!$L:$L,'1.DC_Ra soat'!$F:$F,'1.PL (VND) '!AX$4,'1.DC_Ra soat'!$H:$H,'1.PL (VND) '!$C14)-SUMIFS('1.DC_Ra soat'!$L:$L,'1.DC_Ra soat'!$F:$F,'1.PL (VND) '!AX$4,'1.DC_Ra soat'!$I:$I,'1.PL (VND) '!$C14) -> 0 | AY14: =SUMIFS('1.DC_Ra soat'!$L:$L,'1.DC_Ra soat'!$F:$F,'1.PL (VND) '!AY$4,'1.DC_Ra soat'!$H:$H,'1.PL (VND) '!$C14)-SUMIFS('1.DC_Ra soat'!$L:$L,'1.DC_Ra soat'!$F:$F,'1.PL (VND) '!AY$4,'1.DC_Ra soat'!$I:$I,'1.PL (VND) '!$C14) -> 1262355349 | AZ14: =SUMIFS('1.DC_Ra soat'!$L:$L,'1.DC_Ra soat'!$F:$F,'1.PL (VND) '!AZ$4,'1.DC_Ra soat'!$H:$H,'1.PL (VND) '!$C14)-SUMIFS('1.DC_Ra soat'!$L:$L,'1.DC_Ra soat'!$F:$F,'1.PL (VND) '!AZ$4,'1.DC_Ra soat'!$I:$I,'1.PL (VND) '!$C14) -> 0 | BB14: =SUMIFS('1.DC_Ra soat'!$L:$L,'1.DC_Ra soat'!$F:$F,'1.PL (VND) '!BB$4,'1.DC_Ra soat'!$H:$H,'1.PL (VND) '!$C14)-SUMIFS('1.DC_Ra soat'!$L:$L,'1.DC_Ra soat'!$F:$F,'1.PL (VND) '!BB$4,'1.DC_Ra soat'!$I:$I,'1.PL (VND) '!$C14) -> 0 | BC14: =SUMIFS('1.DC_Ra soat'!$L:$L,'1.DC_Ra soat'!$F:$F,'1.PL (VND) '!BC$4,'1.DC_Ra soat'!$H:$H,'1.PL (VND) '!$C14)-SUMIFS('1.DC_Ra soat'!$L:$L,'1.DC_Ra soat'!$F:$F,'1.PL (VND) '!BC$4,'1.DC_Ra soat'!$I:$I,'1.PL (VND) '!$C14) -> 0 | BD14: =SUMIFS('1.DC_Ra soat'!$L:$L,'1.DC_Ra soat'!$F:$F,'1.PL (VND) '!BD$4,'1.DC_Ra soat'!$H:$H,'1.PL (VND) '!$C14)-SUMIFS('1.DC_Ra soat'!$L:$L,'1.DC_Ra soat'!$F:$F,'1.PL (VND) '!BD$4,'1.DC_Ra soat'!$I:$I,'1.PL (VND) '!$C14) -> 0 | BE14: =SUMIFS('1.DC_Ra soat'!$L:$L,'1.DC_Ra soat'!$F:$F,'1.PL (VND) '!BE$4,'1.DC_Ra soat'!$H:$H,'1.PL (VND) '!$C14)-SUMIFS('1.DC_Ra soat'!$L:$L,'1.DC_Ra soat'!$F:$F,'1.PL (VND) '!BE$4,'1.DC_Ra soat'!$I:$I,'1.PL (VND) '!$C14) -> 0 | BG14: =SUMIFS('1.DC_Ra soat'!$L:$L,'1.DC_Ra soat'!$F:$F,'1.PL (VND) '!BG$4,'1.DC_Ra soat'!$H:$H,'1.PL (VND) '!$C14)-SUMIFS('1.DC_Ra soat'!$L:$L,'1.DC_Ra soat'!$F:$F,'1.PL (VND) '!BG$4,'1.DC_Ra soat'!$I:$I,'1.PL (VND) '!$C14) -> 0 | BH14: =SUMIFS('1.DC_Ra soat'!$L:$L,'1.DC_Ra soat'!$F:$F,'1.PL (VND) '!BH$4,'1.DC_Ra soat'!$H:$H,'1.PL (VND) '!$C14)-SUMIFS('1.DC_Ra soat'!$L:$L,'1.DC_Ra soat'!$F:$F,'1.PL (VND) '!BH$4,'1.DC_Ra soat'!$I:$I,'1.PL (VND) '!$C14) -> 0 | BI14: =SUMIFS('1.DC_Ra soat'!$L:$L,'1.DC_Ra soat'!$F:$F,'1.PL (VND) '!BI$4,'1.DC_Ra soat'!$H:$H,'1.PL (VND) '!$C14)-SUMIFS('1.DC_Ra soat'!$L:$L,'1.DC_Ra soat'!$F:$F,'1.PL (VND) '!BI$4,'1.DC_Ra soat'!$I:$I,'1.PL (VND) '!$C14) -> 0 | BJ14: =SUMIFS('1.DC_Ra soat'!$L:$L,'1.DC_Ra soat'!$F:$F,'1.PL (VND) '!BJ$4,'1.DC_Ra soat'!$H:$H,'1.PL (VND) '!$C14)-SUMIFS('1.DC_Ra soat'!$L:$L,'1.DC_Ra soat'!$F:$F,'1.PL (VND) '!BJ$4,'1.DC_Ra soat'!$I:$I,'1.PL (VND) '!$C14) -> 0 | BL14: =D14+AH14 -> 8171598143 | BM14: =E14+AI14 -> 4496061333 | BN14: =F14+AJ14 -> 13833321122 | BO14: =G14+AK14 -> 12548808701 | BQ14: =I14+AM14 -> 0 | BR14: =J14+AN14 -> 725227638 | BS14: =K14+AO14 -> 3328009721 | BT14: =L14+AP14 -> 1890560444 | BV14: =N14+AR14 -> 1336298435 | BW14: =O14+AS14 -> 1675370773 | BX14: =P14+AT14 -> 2178070579 | BY14: =Q14+AU14 -> 2214890036 | CA14: =S14+AW14 -> 296662990 | CB14: =T14+AX14 -> 832438007 | CC14: =U14+AY14 -> 2355114495 | CD14: =V14+AZ14 -> 1540066497 | CF14: =X14+BB14 -> 0 | CG14: =Y14+BC14 -> 0 | CH14: =Z14+BD14 -> 0 | CI14: =AA14+BE14 -> 0 | CK14: =AC14+BG14 -> 0 | CL14: =AD14+BH14 -> 0 | CM14: =AE14+BI14 -> 0 | CN14: =AF14+BJ14 -> 0 | CP14: =SUMIF($BL$6:$CD$6,CP$6,$BL14:$CD14) -> 9804559568 | CQ14: =SUMIF($BL$6:$CD$6,CQ$6,$BL14:$CD14) -> 7729097751 | CR14: =SUMIF($BL$6:$CD$6,CR$6,$BL14:$CD14) -> 21694515917 | CS14: =SUMIF($BL$6:$CD$6,CS$6,$BL14:$CD14) -> 18194325678 | CU14: =-SUMIFS('1.DC_Ra soat'!$L:$L,'1.DC_Ra soat'!$F:$F,'1.PL (VND) '!CU$4,'1.DC_Ra soat'!$H:$H,'1.PL (VND) '!$C14)+SUMIFS('1.DC_Ra soat'!$L:$L,'1.DC_Ra soat'!$F:$F,'1.PL (VND) '!CU$4,'1.DC_Ra soat'!$I:$I,'1.PL (VND) '!$C14) -> 0 | CV14: =-SUMIFS('1.DC_Ra soat'!$L:$L,'1.DC_Ra soat'!$F:$F,'1.PL (VND) '!CV$4,'1.DC_Ra soat'!$H:$H,'1.PL (VND) '!$C14)+SUMIFS('1.DC_Ra soat'!$L:$L,'1.DC_Ra soat'!$F:$F,'1.PL (VND) '!CV$4,'1.DC_Ra soat'!$I:$I,'1.PL (VND) '!$C14) -> 0 | CW14: =-SUMIFS('1.DC_Ra soat'!$L:$L,'1.DC_Ra soat'!$F:$F,'1.PL (VND) '!CW$4,'1.DC_Ra soat'!$H:$H,'1.PL (VND) '!$C14)+SUMIFS('1.DC_Ra soat'!$L:$L,'1.DC_Ra soat'!$F:$F,'1.PL (VND) '!CW$4,'1.DC_Ra soat'!$I:$I,'1.PL (VND) '!$C14) -> 0 | CX14: =-SUMIFS('1.DC_Ra soat'!$L:$L,'1.DC_Ra soat'!$F:$F,'1.PL (VND) '!CX$4,'1.DC_Ra soat'!$H:$H,'1.PL (VND) '!$C14)+SUMIFS('1.DC_Ra soat'!$L:$L,'1.DC_Ra soat'!$F:$F,'1.PL (VND) '!CX$4,'1.DC_Ra soat'!$I:$I,'1.PL (VND) '!$C14) -> 0 | CZ14: =CP14+CU14 -> 9804559568 | DA14: =CQ14+CV14 -> 7729097751 | DB14: =CR14+CW14 -> 21694515917 | DC14: =CS14+CX14 -> 18194325678
B15: Trong đó: chi phí lãi vay | C15: 23 | D15: =D14 -> 8171598143 | E15: =E14 -> 4496061333 | F15: =F14 -> 8332900199 | G15: =G14 -> 12548808701 | I15: =I14 -> 0 | J15: =J14 -> 725227638 | K15: =K14 -> 2586469172 | L15: =L14 -> 1890560444 | N15: =N14 -> 1336298435 | O15: =O14 -> 1675370773 | P15: =P14 -> 2178070579 | Q15: =Q14 -> 2214890036 | S15: =S14 -> 296662990 | T15: =T14 -> 832438007 | U15: =U14 -> 1092759146 | V15: =V14 -> 1540066497 | AC15: =AC14 -> 0 | AD15: =AD14 -> 0 | AE15: =AE14 -> 0 | AF15: 0 | AH15: =SUMIFS('1.DC_Ra soat'!$L:$L,'1.DC_Ra soat'!$F:$F,'1.PL (VND) '!AH$4,'1.DC_Ra soat'!$H:$H,'1.PL (VND) '!$C15)-SUMIFS('1.DC_Ra soat'!$L:$L,'1.DC_Ra soat'!$F:$F,'1.PL (VND) '!AH$4,'1.DC_Ra soat'!$I:$I,'1.PL (VND) '!$C15) -> 0 | AI15: =SUMIFS('1.DC_Ra soat'!$L:$L,'1.DC_Ra soat'!$F:$F,'1.PL (VND) '!AI$4,'1.DC_Ra soat'!$H:$H,'1.PL (VND) '!$C15)-SUMIFS('1.DC_Ra soat'!$L:$L,'1.DC_Ra soat'!$F:$F,'1.PL (VND) '!AI$4,'1.DC_Ra soat'!$I:$I,'1.PL (VND) '!$C15) -> 0 | AJ15: =SUMIFS('1.DC_Ra soat'!$L:$L,'1.DC_Ra soat'!$F:$F,'1.PL (VND) '!AJ$4,'1.DC_Ra soat'!$H:$H,'1.PL (VND) '!$C15)-SUMIFS('1.DC_Ra soat'!$L:$L,'1.DC_Ra soat'!$F:$F,'1.PL (VND) '!AJ$4,'1.DC_Ra soat'!$I:$I,'1.PL (VND) '!$C15) -> 0 | AK15: =SUMIFS('1.DC_Ra soat'!$L:$L,'1.DC_Ra soat'!$F:$F,'1.PL (VND) '!AK$4,'1.DC_Ra soat'!$H:$H,'1.PL (VND) '!$C15)-SUMIFS('1.DC_Ra soat'!$L:$L,'1.DC_Ra soat'!$F:$F,'1.PL (VND) '!AK$4,'1.DC_Ra soat'!$I:$I,'1.PL (VND) '!$C15) -> 0 | AM15: =SUMIFS('1.DC_Ra soat'!$L:$L,'1.DC_Ra soat'!$F:$F,'1.PL (VND) '!AM$4,'1.DC_Ra soat'!$H:$H,'1.PL (VND) '!$C15)-SUMIFS('1.DC_Ra soat'!$L:$L,'1.DC_Ra soat'!$F:$F,'1.PL (VND) '!AM$4,'1.DC_Ra soat'!$I:$I,'1.PL (VND) '!$C15) -> 0 | AN15: =SUMIFS('1.DC_Ra soat'!$L:$L,'1.DC_Ra soat'!$F:$F,'1.PL (VND) '!AN$4,'1.DC_Ra soat'!$H:$H,'1.PL (VND) '!$C15)-SUMIFS('1.DC_Ra soat'!$L:$L,'1.DC_Ra soat'!$F:$F,'1.PL (VND) '!AN$4,'1.DC_Ra soat'!$I:$I,'1.PL (VND) '!$C15) -> 0 | AO15: =SUMIFS('1.DC_Ra soat'!$L:$L,'1.DC_Ra soat'!$F:$F,'1.PL (VND) '!AO$4,'1.DC_Ra soat'!$H:$H,'1.PL (VND) '!$C15)-SUMIFS('1.DC_Ra soat'!$L:$L,'1.DC_Ra soat'!$F:$F,'1.PL (VND) '!AO$4,'1.DC_Ra soat'!$I:$I,'1.PL (VND) '!$C15) -> 0 | AP15: =SUMIFS('1.DC_Ra soat'!$L:$L,'1.DC_Ra soat'!$F:$F,'1.PL (VND) '!AP$4,'1.DC_Ra soat'!$H:$H,'1.PL (VND) '!$C15)-SUMIFS('1.DC_Ra soat'!$L:$L,'1.DC_Ra soat'!$F:$F,'1.PL (VND) '!AP$4,'1.DC_Ra soat'!$I:$I,'1.PL (VND) '!$C15) -> 0 | AR15: =SUMIFS('1.DC_Ra soat'!$L:$L,'1.DC_Ra soat'!$F:$F,'1.PL (VND) '!AR$4,'1.DC_Ra soat'!$H:$H,'1.PL (VND) '!$C15)-SUMIFS('1.DC_Ra soat'!$L:$L,'1.DC_Ra soat'!$F:$F,'1.PL (VND) '!AR$4,'1.DC_Ra soat'!$I:$I,'1.PL (VND) '!$C15) -> 0 | AS15: =SUMIFS('1.DC_Ra soat'!$L:$L,'1.DC_Ra soat'!$F:$F,'1.PL (VND) '!AS$4,'1.DC_Ra soat'!$H:$H,'1.PL (VND) '!$C15)-SUMIFS('1.DC_Ra soat'!$L:$L,'1.DC_Ra soat'!$F:$F,'1.PL (VND) '!AS$4,'1.DC_Ra soat'!$I:$I,'1.PL (VND) '!$C15) -> 0 | AT15: =AT14 -> 0 | AU15: =SUMIFS('1.DC_Ra soat'!$L:$L,'1.DC_Ra soat'!$F:$F,'1.PL (VND) '!AU$4,'1.DC_Ra soat'!$H:$H,'1.PL (VND) '!$C15)-SUMIFS('1.DC_Ra soat'!$L:$L,'1.DC_Ra soat'!$F:$F,'1.PL (VND) '!AU$4,'1.DC_Ra soat'!$I:$I,'1.PL (VND) '!$C15) -> 0 | AW15: =SUMIFS('1.DC_Ra soat'!$L:$L,'1.DC_Ra soat'!$F:$F,'1.PL (VND) '!AW$4,'1.DC_Ra soat'!$H:$H,'1.PL (VND) '!$C15)-SUMIFS('1.DC_Ra soat'!$L:$L,'1.DC_Ra soat'!$F:$F,'1.PL (VND) '!AW$4,'1.DC_Ra soat'!$I:$I,'1.PL (VND) '!$C15) -> 0 | AX15: =SUMIFS('1.DC_Ra soat'!$L:$L,'1.DC_Ra soat'!$F:$F,'1.PL (VND) '!AX$4,'1.DC_Ra soat'!$H:$H,'1.PL (VND) '!$C15)-SUMIFS('1.DC_Ra soat'!$L:$L,'1.DC_Ra soat'!$F:$F,'1.PL (VND) '!AX$4,'1.DC_Ra soat'!$I:$I,'1.PL (VND) '!$C15) -> 0 | AY15: =SUMIFS('1.DC_Ra soat'!$L:$L,'1.DC_Ra soat'!$F:$F,'1.PL (VND) '!AY$4,'1.DC_Ra soat'!$H:$H,'1.PL (VND) '!$C15)-SUMIFS('1.DC_Ra soat'!$L:$L,'1.DC_Ra soat'!$F:$F,'1.PL (VND) '!AY$4,'1.DC_Ra soat'!$I:$I,'1.PL (VND) '!$C15) -> 0 | AZ15: =SUMIFS('1.DC_Ra soat'!$L:$L,'1.DC_Ra soat'!$F:$F,'1.PL (VND) '!AZ$4,'1.DC_Ra soat'!$H:$H,'1.PL (VND) '!$C15)-SUMIFS('1.DC_Ra soat'!$L:$L,'1.DC_Ra soat'!$F:$F,'1.PL (VND) '!AZ$4,'1.DC_Ra soat'!$I:$I,'1.PL (VND) '!$C15) -> 0 | BB15: =SUMIFS('1.DC_Ra soat'!$L:$L,'1.DC_Ra soat'!$F:$F,'1.PL (VND) '!BB$4,'1.DC_Ra soat'!$H:$H,'1.PL (VND) '!$C15)-SUMIFS('1.DC_Ra soat'!$L:$L,'1.DC_Ra soat'!$F:$F,'1.PL (VND) '!BB$4,'1.DC_Ra soat'!$I:$I,'1.PL (VND) '!$C15) -> 0 | BC15: =SUMIFS('1.DC_Ra soat'!$L:$L,'1.DC_Ra soat'!$F:$F,'1.PL (VND) '!BC$4,'1.DC_Ra soat'!$H:$H,'1.PL (VND) '!$C15)-SUMIFS('1.DC_Ra soat'!$L:$L,'1.DC_Ra soat'!$F:$F,'1.PL (VND) '!BC$4,'1.DC_Ra soat'!$I:$I,'1.PL (VND) '!$C15) -> 0 | BD15: =SUMIFS('1.DC_Ra soat'!$L:$L,'1.DC_Ra soat'!$F:$F,'1.PL (VND) '!BD$4,'1.DC_Ra soat'!$H:$H,'1.PL (VND) '!$C15)-SUMIFS('1.DC_Ra soat'!$L:$L,'1.DC_Ra soat'!$F:$F,'1.PL (VND) '!BD$4,'1.DC_Ra soat'!$I:$I,'1.PL (VND) '!$C15) -> 0 | BE15: =SUMIFS('1.DC_Ra soat'!$L:$L,'1.DC_Ra soat'!$F:$F,'1.PL (VND) '!BE$4,'1.DC_Ra soat'!$H:$H,'1.PL (VND) '!$C15)-SUMIFS('1.DC_Ra soat'!$L:$L,'1.DC_Ra soat'!$F:$F,'1.PL (VND) '!BE$4,'1.DC_Ra soat'!$I:$I,'1.PL (VND) '!$C15) -> 0 | BG15: =SUMIFS('1.DC_Ra soat'!$L:$L,'1.DC_Ra soat'!$F:$F,'1.PL (VND) '!BG$4,'1.DC_Ra soat'!$H:$H,'1.PL (VND) '!$C15)-SUMIFS('1.DC_Ra soat'!$L:$L,'1.DC_Ra soat'!$F:$F,'1.PL (VND) '!BG$4,'1.DC_Ra soat'!$I:$I,'1.PL (VND) '!$C15) -> 0 | BH15: =SUMIFS('1.DC_Ra soat'!$L:$L,'1.DC_Ra soat'!$F:$F,'1.PL (VND) '!BH$4,'1.DC_Ra soat'!$H:$H,'1.PL (VND) '!$C15)-SUMIFS('1.DC_Ra soat'!$L:$L,'1.DC_Ra soat'!$F:$F,'1.PL (VND) '!BH$4,'1.DC_Ra soat'!$I:$I,'1.PL (VND) '!$C15) -> 0 | BI15: =SUMIFS('1.DC_Ra soat'!$L:$L,'1.DC_Ra soat'!$F:$F,'1.PL (VND) '!BI$4,'1.DC_Ra soat'!$H:$H,'1.PL (VND) '!$C15)-SUMIFS('1.DC_Ra soat'!$L:$L,'1.DC_Ra soat'!$F:$F,'1.PL (VND) '!BI$4,'1.DC_Ra soat'!$I:$I,'1.PL (VND) '!$C15) -> 0 | BJ15: =SUMIFS('1.DC_Ra soat'!$L:$L,'1.DC_Ra soat'!$F:$F,'1.PL (VND) '!BJ$4,'1.DC_Ra soat'!$H:$H,'1.PL (VND) '!$C15)-SUMIFS('1.DC_Ra soat'!$L:$L,'1.DC_Ra soat'!$F:$F,'1.PL (VND) '!BJ$4,'1.DC_Ra soat'!$I:$I,'1.PL (VND) '!$C15) -> 0 | BL15: =D15+AH15 -> 8171598143 | BM15: =E15+AI15 -> 4496061333 | BN15: =F15+AJ15 -> 8332900199 | BO15: =G15+AK15 -> 12548808701 | BQ15: =I15+AM15 -> 0 | BR15: =J15+AN15 -> 725227638 | BS15: =K15+AO15 -> 2586469172 | BT15: =L15+AP15 -> 1890560444 | BV15: =N15+AR15 -> 1336298435 | BW15: =O15+AS15 -> 1675370773 | BX15: =P15+AT15 -> 2178070579 | BY15: =Q15+AU15 -> 2214890036 | CA15: =S15+AW15 -> 296662990 | CB15: =T15+AX15 -> 832438007 | CC15: =U15+AY15 -> 1092759146 | CD15: =V15+AZ15 -> 1540066497 | CF15: =X15+BB15 -> 0 | CG15: =Y15+BC15 -> 0 | CH15: =Z15+BD15 -> 0 | CI15: =AA15+BE15 -> 0 | CK15: =AC15+BG15 -> 0 | CL15: =AD15+BH15 -> 0 | CM15: =AE15+BI15 -> 0 | CN15: =AF15+BJ15 -> 0 | CP15: =SUMIF($BL$6:$CD$6,CP$6,$BL15:$CD15) -> 9804559568 | CQ15: =SUMIF($BL$6:$CD$6,CQ$6,$BL15:$CD15) -> 7729097751 | CR15: =SUMIF($BL$6:$CD$6,CR$6,$BL15:$CD15) -> 14190199096 | CS15: =SUMIF($BL$6:$CD$6,CS$6,$BL15:$CD15) -> 18194325678 | CU15: =CU14 -> 0 | CV15: =CV14 -> 0 | CW15: =CW14 -> 0 | CX15: =CX14 -> 0 | CZ15: =CP15+CU15 -> 9804559568 | DA15: =CQ15+CV15 -> 7729097751 | DB15: =CR15+CW15 -> 14190199096 | DC15: =CS15+CX15 -> 18194325678
B16: Phần lãi lỗ trong Công ty liên doanh liên kết | C16: 24 | AH16: =-SUMIFS('1.DC_Ra soat'!$L:$L,'1.DC_Ra soat'!$F:$F,'1.PL (VND) '!AH$4,'1.DC_Ra soat'!$H:$H,'1.PL (VND) '!$C16)+SUMIFS('1.DC_Ra soat'!$L:$L,'1.DC_Ra soat'!$F:$F,'1.PL (VND) '!AH$4,'1.DC_Ra soat'!$I:$I,'1.PL (VND) '!$C16) -> 0 | AI16: =-SUMIFS('1.DC_Ra soat'!$L:$L,'1.DC_Ra soat'!$F:$F,'1.PL (VND) '!AI$4,'1.DC_Ra soat'!$H:$H,'1.PL (VND) '!$C16)+SUMIFS('1.DC_Ra soat'!$L:$L,'1.DC_Ra soat'!$F:$F,'1.PL (VND) '!AI$4,'1.DC_Ra soat'!$I:$I,'1.PL (VND) '!$C16) -> 0 | AJ16: =-SUMIFS('1.DC_Ra soat'!$L:$L,'1.DC_Ra soat'!$F:$F,'1.PL (VND) '!AJ$4,'1.DC_Ra soat'!$H:$H,'1.PL (VND) '!$C16)+SUMIFS('1.DC_Ra soat'!$L:$L,'1.DC_Ra soat'!$F:$F,'1.PL (VND) '!AJ$4,'1.DC_Ra soat'!$I:$I,'1.PL (VND) '!$C16) -> 0 | AK16: =-SUMIFS('1.DC_Ra soat'!$L:$L,'1.DC_Ra soat'!$F:$F,'1.PL (VND) '!AK$4,'1.DC_Ra soat'!$H:$H,'1.PL (VND) '!$C16)+SUMIFS('1.DC_Ra soat'!$L:$L,'1.DC_Ra soat'!$F:$F,'1.PL (VND) '!AK$4,'1.DC_Ra soat'!$I:$I,'1.PL (VND) '!$C16) -> 0 | AM16: =-SUMIFS('1.DC_Ra soat'!$L:$L,'1.DC_Ra soat'!$F:$F,'1.PL (VND) '!AM$4,'1.DC_Ra soat'!$H:$H,'1.PL (VND) '!$C16)+SUMIFS('1.DC_Ra soat'!$L:$L,'1.DC_Ra soat'!$F:$F,'1.PL (VND) '!AM$4,'1.DC_Ra soat'!$I:$I,'1.PL (VND) '!$C16) -> 0 | AN16: =-SUMIFS('1.DC_Ra soat'!$L:$L,'1.DC_Ra soat'!$F:$F,'1.PL (VND) '!AN$4,'1.DC_Ra soat'!$H:$H,'1.PL (VND) '!$C16)+SUMIFS('1.DC_Ra soat'!$L:$L,'1.DC_Ra soat'!$F:$F,'1.PL (VND) '!AN$4,'1.DC_Ra soat'!$I:$I,'1.PL (VND) '!$C16) -> 0 | AO16: =-SUMIFS('1.DC_Ra soat'!$L:$L,'1.DC_Ra soat'!$F:$F,'1.PL (VND) '!AO$4,'1.DC_Ra soat'!$H:$H,'1.PL (VND) '!$C16)+SUMIFS('1.DC_Ra soat'!$L:$L,'1.DC_Ra soat'!$F:$F,'1.PL (VND) '!AO$4,'1.DC_Ra soat'!$I:$I,'1.PL (VND) '!$C16) -> 0 | AP16: =-SUMIFS('1.DC_Ra soat'!$L:$L,'1.DC_Ra soat'!$F:$F,'1.PL (VND) '!AP$4,'1.DC_Ra soat'!$H:$H,'1.PL (VND) '!$C16)+SUMIFS('1.DC_Ra soat'!$L:$L,'1.DC_Ra soat'!$F:$F,'1.PL (VND) '!AP$4,'1.DC_Ra soat'!$I:$I,'1.PL (VND) '!$C16) -> 0 | AR16: =-SUMIFS('1.DC_Ra soat'!$L:$L,'1.DC_Ra soat'!$F:$F,'1.PL (VND) '!AR$4,'1.DC_Ra soat'!$H:$H,'1.PL (VND) '!$C16)+SUMIFS('1.DC_Ra soat'!$L:$L,'1.DC_Ra soat'!$F:$F,'1.PL (VND) '!AR$4,'1.DC_Ra soat'!$I:$I,'1.PL (VND) '!$C16) -> 0 | AS16: =-SUMIFS('1.DC_Ra soat'!$L:$L,'1.DC_Ra soat'!$F:$F,'1.PL (VND) '!AS$4,'1.DC_Ra soat'!$H:$H,'1.PL (VND) '!$C16)+SUMIFS('1.DC_Ra soat'!$L:$L,'1.DC_Ra soat'!$F:$F,'1.PL (VND) '!AS$4,'1.DC_Ra soat'!$I:$I,'1.PL (VND) '!$C16) -> 0 | AT16: =-SUMIFS('1.DC_Ra soat'!$L:$L,'1.DC_Ra soat'!$F:$F,'1.PL (VND) '!AT$4,'1.DC_Ra soat'!$H:$H,'1.PL (VND) '!$C16)+SUMIFS('1.DC_Ra soat'!$L:$L,'1.DC_Ra soat'!$F:$F,'1.PL (VND) '!AT$4,'1.DC_Ra soat'!$I:$I,'1.PL (VND) '!$C16) -> 0 | AU16: =-SUMIFS('1.DC_Ra soat'!$L:$L,'1.DC_Ra soat'!$F:$F,'1.PL (VND) '!AU$4,'1.DC_Ra soat'!$H:$H,'1.PL (VND) '!$C16)+SUMIFS('1.DC_Ra soat'!$L:$L,'1.DC_Ra soat'!$F:$F,'1.PL (VND) '!AU$4,'1.DC_Ra soat'!$I:$I,'1.PL (VND) '!$C16) -> 0 | AW16: =-SUMIFS('1.DC_Ra soat'!$L:$L,'1.DC_Ra soat'!$F:$F,'1.PL (VND) '!AW$4,'1.DC_Ra soat'!$H:$H,'1.PL (VND) '!$C16)+SUMIFS('1.DC_Ra soat'!$L:$L,'1.DC_Ra soat'!$F:$F,'1.PL (VND) '!AW$4,'1.DC_Ra soat'!$I:$I,'1.PL (VND) '!$C16) -> 0 | AX16: =-SUMIFS('1.DC_Ra soat'!$L:$L,'1.DC_Ra soat'!$F:$F,'1.PL (VND) '!AX$4,'1.DC_Ra soat'!$H:$H,'1.PL (VND) '!$C16)+SUMIFS('1.DC_Ra soat'!$L:$L,'1.DC_Ra soat'!$F:$F,'1.PL (VND) '!AX$4,'1.DC_Ra soat'!$I:$I,'1.PL (VND) '!$C16) -> 0 | AY16: =-SUMIFS('1.DC_Ra soat'!$L:$L,'1.DC_Ra soat'!$F:$F,'1.PL (VND) '!AY$4,'1.DC_Ra soat'!$H:$H,'1.PL (VND) '!$C16)+SUMIFS('1.DC_Ra soat'!$L:$L,'1.DC_Ra soat'!$F:$F,'1.PL (VND) '!AY$4,'1.DC_Ra soat'!$I:$I,'1.PL (VND) '!$C16) -> 0 | AZ16: =-SUMIFS('1.DC_Ra soat'!$L:$L,'1.DC_Ra soat'!$F:$F,'1.PL (VND) '!AZ$4,'1.DC_Ra soat'!$H:$H,'1.PL (VND) '!$C16)+SUMIFS('1.DC_Ra soat'!$L:$L,'1.DC_Ra soat'!$F:$F,'1.PL (VND) '!AZ$4,'1.DC_Ra soat'!$I:$I,'1.PL (VND) '!$C16) -> 0 | BB16: =-SUMIFS('1.DC_Ra soat'!$L:$L,'1.DC_Ra soat'!$F:$F,'1.PL (VND) '!BB$4,'1.DC_Ra soat'!$H:$H,'1.PL (VND) '!$C16)+SUMIFS('1.DC_Ra soat'!$L:$L,'1.DC_Ra soat'!$F:$F,'1.PL (VND) '!BB$4,'1.DC_Ra soat'!$I:$I,'1.PL (VND) '!$C16) -> 0 | BC16: =-SUMIFS('1.DC_Ra soat'!$L:$L,'1.DC_Ra soat'!$F:$F,'1.PL (VND) '!BC$4,'1.DC_Ra soat'!$H:$H,'1.PL (VND) '!$C16)+SUMIFS('1.DC_Ra soat'!$L:$L,'1.DC_Ra soat'!$F:$F,'1.PL (VND) '!BC$4,'1.DC_Ra soat'!$I:$I,'1.PL (VND) '!$C16) -> 0 | BD16: =-SUMIFS('1.DC_Ra soat'!$L:$L,'1.DC_Ra soat'!$F:$F,'1.PL (VND) '!BD$4,'1.DC_Ra soat'!$H:$H,'1.PL (VND) '!$C16)+SUMIFS('1.DC_Ra soat'!$L:$L,'1.DC_Ra soat'!$F:$F,'1.PL (VND) '!BD$4,'1.DC_Ra soat'!$I:$I,'1.PL (VND) '!$C16) -> 0 | BE16: =-SUMIFS('1.DC_Ra soat'!$L:$L,'1.DC_Ra soat'!$F:$F,'1.PL (VND) '!BE$4,'1.DC_Ra soat'!$H:$H,'1.PL (VND) '!$C16)+SUMIFS('1.DC_Ra soat'!$L:$L,'1.DC_Ra soat'!$F:$F,'1.PL (VND) '!BE$4,'1.DC_Ra soat'!$I:$I,'1.PL (VND) '!$C16) -> 0 | BG16: =-SUMIFS('1.DC_Ra soat'!$L:$L,'1.DC_Ra soat'!$F:$F,'1.PL (VND) '!BG$4,'1.DC_Ra soat'!$H:$H,'1.PL (VND) '!$C16)+SUMIFS('1.DC_Ra soat'!$L:$L,'1.DC_Ra soat'!$F:$F,'1.PL (VND) '!BG$4,'1.DC_Ra soat'!$I:$I,'1.PL (VND) '!$C16) -> 0 | BH16: =-SUMIFS('1.DC_Ra soat'!$L:$L,'1.DC_Ra soat'!$F:$F,'1.PL (VND) '!BH$4,'1.DC_Ra soat'!$H:$H,'1.PL (VND) '!$C16)+SUMIFS('1.DC_Ra soat'!$L:$L,'1.DC_Ra soat'!$F:$F,'1.PL (VND) '!BH$4,'1.DC_Ra soat'!$I:$I,'1.PL (VND) '!$C16) -> 0 | BI16: =-SUMIFS('1.DC_Ra soat'!$L:$L,'1.DC_Ra soat'!$F:$F,'1.PL (VND) '!BI$4,'1.DC_Ra soat'!$H:$H,'1.PL (VND) '!$C16)+SUMIFS('1.DC_Ra soat'!$L:$L,'1.DC_Ra soat'!$F:$F,'1.PL (VND) '!BI$4,'1.DC_Ra soat'!$I:$I,'1.PL (VND) '!$C16) -> 0 | BJ16: =-SUMIFS('1.DC_Ra soat'!$L:$L,'1.DC_Ra soat'!$F:$F,'1.PL (VND) '!BJ$4,'1.DC_Ra soat'!$H:$H,'1.PL (VND) '!$C16)+SUMIFS('1.DC_Ra soat'!$L:$L,'1.DC_Ra soat'!$F:$F,'1.PL (VND) '!BJ$4,'1.DC_Ra soat'!$I:$I,'1.PL (VND) '!$C16) -> 0 | BL16: =D16+AH16 -> 0 | BM16: =E16+AI16 -> 0 | BN16: =F16+AJ16 -> 0 | BO16: =G16+AK16 -> 0 | BQ16: =I16+AM16 -> 0 | BR16: =J16+AN16 -> 0 | BS16: =K16+AO16 -> 0 | BT16: =L16+AP16 -> 0 | BV16: =N16+AR16 -> 0 | BW16: =O16+AS16 -> 0 | BX16: =P16+AT16 -> 0 | BY16: =Q16+AU16 -> 0 | CA16: =S16+AW16 -> 0 | CB16: =T16+AX16 -> 0 | CC16: =U16+AY16 -> 0 | CD16: =V16+AZ16 -> 0 | CF16: =X16+BB16 -> 0 | CG16: =Y16+BC16 -> 0 | CH16: =Z16+BD16 -> 0 | CI16: =AA16+BE16 -> 0 | CK16: =AC16+BG16 -> 0 | CL16: =AD16+BH16 -> 0 | CM16: =AE16+BI16 -> 0 | CN16: =AF16+BJ16 -> 0 | CP16: =SUMIF($BL$6:$CD$6,CP$6,$BL16:$CD16) -> 0 | CQ16: =SUMIF($BL$6:$CD$6,CQ$6,$BL16:$CD16) -> 0 | CR16: =SUMIF($BL$6:$CD$6,CR$6,$BL16:$CD16) -> 0 | CS16: =SUMIF($BL$6:$CD$6,CS$6,$BL16:$CD16) -> 0 | CU16: =-SUMIFS('1.DC_Ra soat'!$L:$L,'1.DC_Ra soat'!$F:$F,'1.PL (VND) '!CU$4,'1.DC_Ra soat'!$H:$H,'1.PL (VND) '!$C16)+SUMIFS('1.DC_Ra soat'!$L:$L,'1.DC_Ra soat'!$F:$F,'1.PL (VND) '!CU$4,'1.DC_Ra soat'!$I:$I,'1.PL (VND) '!$C16) -> 0 | CV16: =-SUMIFS('1.DC_Ra soat'!$L:$L,'1.DC_Ra soat'!$F:$F,'1.PL (VND) '!CV$4,'1.DC_Ra soat'!$H:$H,'1.PL (VND) '!$C16)+SUMIFS('1.DC_Ra soat'!$L:$L,'1.DC_Ra soat'!$F:$F,'1.PL (VND) '!CV$4,'1.DC_Ra soat'!$I:$I,'1.PL (VND) '!$C16) -> 0 | CW16: =-SUMIFS('1.DC_Ra soat'!$L:$L,'1.DC_Ra soat'!$F:$F,'1.PL (VND) '!CW$4,'1.DC_Ra soat'!$H:$H,'1.PL (VND) '!$C16)+SUMIFS('1.DC_Ra soat'!$L:$L,'1.DC_Ra soat'!$F:$F,'1.PL (VND) '!CW$4,'1.DC_Ra soat'!$I:$I,'1.PL (VND) '!$C16) -> 0 | CX16: =-SUMIFS('1.DC_Ra soat'!$L:$L,'1.DC_Ra soat'!$F:$F,'1.PL (VND) '!CX$4,'1.DC_Ra soat'!$H:$H,'1.PL (VND) '!$C16)+SUMIFS('1.DC_Ra soat'!$L:$L,'1.DC_Ra soat'!$F:$F,'1.PL (VND) '!CX$4,'1.DC_Ra soat'!$I:$I,'1.PL (VND) '!$C16) -> 0 | CZ16: =CP16+CU16 -> 0 | DA16: =CQ16+CV16 -> 0 | DB16: =CR16+CW16 -> 0 | DC16: =CS16+CX16 -> 0
B17: 8. Chi phí bán hàng | C17: 25 | D17: 0 | E17: 0 | F17: 0 | G17: 0 | J17: 0 | K17: 0 | L17: 240600000 | O17: 0 | P17: 0 | Q17: 0 | AH17: =SUMIFS('1.DC_Ra soat'!$L:$L,'1.DC_Ra soat'!$F:$F,'1.PL (VND) '!AH$4,'1.DC_Ra soat'!$H:$H,'1.PL (VND) '!$C17)-SUMIFS('1.DC_Ra soat'!$L:$L,'1.DC_Ra soat'!$F:$F,'1.PL (VND) '!AH$4,'1.DC_Ra soat'!$I:$I,'1.PL (VND) '!$C17) -> 0 | AI17: =SUMIFS('1.DC_Ra soat'!$L:$L,'1.DC_Ra soat'!$F:$F,'1.PL (VND) '!AI$4,'1.DC_Ra soat'!$H:$H,'1.PL (VND) '!$C17)-SUMIFS('1.DC_Ra soat'!$L:$L,'1.DC_Ra soat'!$F:$F,'1.PL (VND) '!AI$4,'1.DC_Ra soat'!$I:$I,'1.PL (VND) '!$C17) -> 0 | AJ17: =SUMIFS('1.DC_Ra soat'!$L:$L,'1.DC_Ra soat'!$F:$F,'1.PL (VND) '!AJ$4,'1.DC_Ra soat'!$H:$H,'1.PL (VND) '!$C17)-SUMIFS('1.DC_Ra soat'!$L:$L,'1.DC_Ra soat'!$F:$F,'1.PL (VND) '!AJ$4,'1.DC_Ra soat'!$I:$I,'1.PL (VND) '!$C17) -> 0 | AK17: =SUMIFS('1.DC_Ra soat'!$L:$L,'1.DC_Ra soat'!$F:$F,'1.PL (VND) '!AK$4,'1.DC_Ra soat'!$H:$H,'1.PL (VND) '!$C17)-SUMIFS('1.DC_Ra soat'!$L:$L,'1.DC_Ra soat'!$F:$F,'1.PL (VND) '!AK$4,'1.DC_Ra soat'!$I:$I,'1.PL (VND) '!$C17) -> 0 | AM17: =SUMIFS('1.DC_Ra soat'!$L:$L,'1.DC_Ra soat'!$F:$F,'1.PL (VND) '!AM$4,'1.DC_Ra soat'!$H:$H,'1.PL (VND) '!$C17)-SUMIFS('1.DC_Ra soat'!$L:$L,'1.DC_Ra soat'!$F:$F,'1.PL (VND) '!AM$4,'1.DC_Ra soat'!$I:$I,'1.PL (VND) '!$C17) -> 0 | AN17: =SUMIFS('1.DC_Ra soat'!$L:$L,'1.DC_Ra soat'!$F:$F,'1.PL (VND) '!AN$4,'1.DC_Ra soat'!$H:$H,'1.PL (VND) '!$C17)-SUMIFS('1.DC_Ra soat'!$L:$L,'1.DC_Ra soat'!$F:$F,'1.PL (VND) '!AN$4,'1.DC_Ra soat'!$I:$I,'1.PL (VND) '!$C17) -> 0 | AO17: =SUMIFS('1.DC_Ra soat'!$L:$L,'1.DC_Ra soat'!$F:$F,'1.PL (VND) '!AO$4,'1.DC_Ra soat'!$H:$H,'1.PL (VND) '!$C17)-SUMIFS('1.DC_Ra soat'!$L:$L,'1.DC_Ra soat'!$F:$F,'1.PL (VND) '!AO$4,'1.DC_Ra soat'!$I:$I,'1.PL (VND) '!$C17) -> 0 | AP17: =SUMIFS('1.DC_Ra soat'!$L:$L,'1.DC_Ra soat'!$F:$F,'1.PL (VND) '!AP$4,'1.DC_Ra soat'!$H:$H,'1.PL (VND) '!$C17)-SUMIFS('1.DC_Ra soat'!$L:$L,'1.DC_Ra soat'!$F:$F,'1.PL (VND) '!AP$4,'1.DC_Ra soat'!$I:$I,'1.PL (VND) '!$C17) -> 0 | AR17: =SUMIFS('1.DC_Ra soat'!$L:$L,'1.DC_Ra soat'!$F:$F,'1.PL (VND) '!AR$4,'1.DC_Ra soat'!$H:$H,'1.PL (VND) '!$C17)-SUMIFS('1.DC_Ra soat'!$L:$L,'1.DC_Ra soat'!$F:$F,'1.PL (VND) '!AR$4,'1.DC_Ra soat'!$I:$I,'1.PL (VND) '!$C17) -> 0 | AS17: =SUMIFS('1.DC_Ra soat'!$L:$L,'1.DC_Ra soat'!$F:$F,'1.PL (VND) '!AS$4,'1.DC_Ra soat'!$H:$H,'1.PL (VND) '!$C17)-SUMIFS('1.DC_Ra soat'!$L:$L,'1.DC_Ra soat'!$F:$F,'1.PL (VND) '!AS$4,'1.DC_Ra soat'!$I:$I,'1.PL (VND) '!$C17) -> 0 | AT17: =SUMIFS('1.DC_Ra soat'!$L:$L,'1.DC_Ra soat'!$F:$F,'1.PL (VND) '!AT$4,'1.DC_Ra soat'!$H:$H,'1.PL (VND) '!$C17)-SUMIFS('1.DC_Ra soat'!$L:$L,'1.DC_Ra soat'!$F:$F,'1.PL (VND) '!AT$4,'1.DC_Ra soat'!$I:$I,'1.PL (VND) '!$C17) -> 0 | AU17: =SUMIFS('1.DC_Ra soat'!$L:$L,'1.DC_Ra soat'!$F:$F,'1.PL (VND) '!AU$4,'1.DC_Ra soat'!$H:$H,'1.PL (VND) '!$C17)-SUMIFS('1.DC_Ra soat'!$L:$L,'1.DC_Ra soat'!$F:$F,'1.PL (VND) '!AU$4,'1.DC_Ra soat'!$I:$I,'1.PL (VND) '!$C17) -> 0 | AW17: =SUMIFS('1.DC_Ra soat'!$L:$L,'1.DC_Ra soat'!$F:$F,'1.PL (VND) '!AW$4,'1.DC_Ra soat'!$H:$H,'1.PL (VND) '!$C17)-SUMIFS('1.DC_Ra soat'!$L:$L,'1.DC_Ra soat'!$F:$F,'1.PL (VND) '!AW$4,'1.DC_Ra soat'!$I:$I,'1.PL (VND) '!$C17) -> 0 | AX17: =SUMIFS('1.DC_Ra soat'!$L:$L,'1.DC_Ra soat'!$F:$F,'1.PL (VND) '!AX$4,'1.DC_Ra soat'!$H:$H,'1.PL (VND) '!$C17)-SUMIFS('1.DC_Ra soat'!$L:$L,'1.DC_Ra soat'!$F:$F,'1.PL (VND) '!AX$4,'1.DC_Ra soat'!$I:$I,'1.PL (VND) '!$C17) -> 0 | AY17: =SUMIFS('1.DC_Ra soat'!$L:$L,'1.DC_Ra soat'!$F:$F,'1.PL (VND) '!AY$4,'1.DC_Ra soat'!$H:$H,'1.PL (VND) '!$C17)-SUMIFS('1.DC_Ra soat'!$L:$L,'1.DC_Ra soat'!$F:$F,'1.PL (VND) '!AY$4,'1.DC_Ra soat'!$I:$I,'1.PL (VND) '!$C17) -> 0 | AZ17: =SUMIFS('1.DC_Ra soat'!$L:$L,'1.DC_Ra soat'!$F:$F,'1.PL (VND) '!AZ$4,'1.DC_Ra soat'!$H:$H,'1.PL (VND) '!$C17)-SUMIFS('1.DC_Ra soat'!$L:$L,'1.DC_Ra soat'!$F:$F,'1.PL (VND) '!AZ$4,'1.DC_Ra soat'!$I:$I,'1.PL (VND) '!$C17) -> 0 | BB17: =SUMIFS('1.DC_Ra soat'!$L:$L,'1.DC_Ra soat'!$F:$F,'1.PL (VND) '!BB$4,'1.DC_Ra soat'!$H:$H,'1.PL (VND) '!$C17)-SUMIFS('1.DC_Ra soat'!$L:$L,'1.DC_Ra soat'!$F:$F,'1.PL (VND) '!BB$4,'1.DC_Ra soat'!$I:$I,'1.PL (VND) '!$C17) -> 0 | BC17: =SUMIFS('1.DC_Ra soat'!$L:$L,'1.DC_Ra soat'!$F:$F,'1.PL (VND) '!BC$4,'1.DC_Ra soat'!$H:$H,'1.PL (VND) '!$C17)-SUMIFS('1.DC_Ra soat'!$L:$L,'1.DC_Ra soat'!$F:$F,'1.PL (VND) '!BC$4,'1.DC_Ra soat'!$I:$I,'1.PL (VND) '!$C17) -> 0 | BD17: =SUMIFS('1.DC_Ra soat'!$L:$L,'1.DC_Ra soat'!$F:$F,'1.PL (VND) '!BD$4,'1.DC_Ra soat'!$H:$H,'1.PL (VND) '!$C17)-SUMIFS('1.DC_Ra soat'!$L:$L,'1.DC_Ra soat'!$F:$F,'1.PL (VND) '!BD$4,'1.DC_Ra soat'!$I:$I,'1.PL (VND) '!$C17) -> 0 | BE17: =SUMIFS('1.DC_Ra soat'!$L:$L,'1.DC_Ra soat'!$F:$F,'1.PL (VND) '!BE$4,'1.DC_Ra soat'!$H:$H,'1.PL (VND) '!$C17)-SUMIFS('1.DC_Ra soat'!$L:$L,'1.DC_Ra soat'!$F:$F,'1.PL (VND) '!BE$4,'1.DC_Ra soat'!$I:$I,'1.PL (VND) '!$C17) -> 0 | BG17: =SUMIFS('1.DC_Ra soat'!$L:$L,'1.DC_Ra soat'!$F:$F,'1.PL (VND) '!BG$4,'1.DC_Ra soat'!$H:$H,'1.PL (VND) '!$C17)-SUMIFS('1.DC_Ra soat'!$L:$L,'1.DC_Ra soat'!$F:$F,'1.PL (VND) '!BG$4,'1.DC_Ra soat'!$I:$I,'1.PL (VND) '!$C17) -> 0 | BH17: =SUMIFS('1.DC_Ra soat'!$L:$L,'1.DC_Ra soat'!$F:$F,'1.PL (VND) '!BH$4,'1.DC_Ra soat'!$H:$H,'1.PL (VND) '!$C17)-SUMIFS('1.DC_Ra soat'!$L:$L,'1.DC_Ra soat'!$F:$F,'1.PL (VND) '!BH$4,'1.DC_Ra soat'!$I:$I,'1.PL (VND) '!$C17) -> 0 | BI17: =SUMIFS('1.DC_Ra soat'!$L:$L,'1.DC_Ra soat'!$F:$F,'1.PL (VND) '!BI$4,'1.DC_Ra soat'!$H:$H,'1.PL (VND) '!$C17)-SUMIFS('1.DC_Ra soat'!$L:$L,'1.DC_Ra soat'!$F:$F,'1.PL (VND) '!BI$4,'1.DC_Ra soat'!$I:$I,'1.PL (VND) '!$C17) -> 0 | BJ17: =SUMIFS('1.DC_Ra soat'!$L:$L,'1.DC_Ra soat'!$F:$F,'1.PL (VND) '!BJ$4,'1.DC_Ra soat'!$H:$H,'1.PL (VND) '!$C17)-SUMIFS('1.DC_Ra soat'!$L:$L,'1.DC_Ra soat'!$F:$F,'1.PL (VND) '!BJ$4,'1.DC_Ra soat'!$I:$I,'1.PL (VND) '!$C17) -> 0 | BL17: =D17+AH17 -> 0 | BM17: =E17+AI17 -> 0 | BN17: =F17+AJ17 -> 0 | BO17: =G17+AK17 -> 0 | BQ17: =I17+AM17 -> 0 | BR17: =J17+AN17 -> 0 | BS17: =K17+AO17 -> 0 | BT17: =L17+AP17 -> 240600000 | BV17: =N17+AR17 -> 0 | BW17: =O17+AS17 -> 0 | BX17: =P17+AT17 -> 0 | BY17: =Q17+AU17 -> 0 | CA17: =S17+AW17 -> 0 | CB17: =T17+AX17 -> 0 | CC17: =U17+AY17 -> 0 | CD17: =V17+AZ17 -> 0 | CF17: =X17+BB17 -> 0 | CG17: =Y17+BC17 -> 0 | CH17: =Z17+BD17 -> 0 | CI17: =AA17+BE17 -> 0 | CK17: =AC17+BG17 -> 0 | CL17: =AD17+BH17 -> 0 | CM17: =AE17+BI17 -> 0 | CN17: =AF17+BJ17 -> 0 | CP17: =SUMIF($BL$6:$CD$6,CP$6,$BL17:$CD17) -> 0 | CQ17: =SUMIF($BL$6:$CD$6,CQ$6,$BL17:$CD17) -> 0 | CR17: =SUMIF($BL$6:$CD$6,CR$6,$BL17:$CD17) -> 0 | CS17: =SUMIF($BL$6:$CD$6,CS$6,$BL17:$CD17) -> 240600000 | CU17: =-SUMIFS('1.DC_Ra soat'!$L:$L,'1.DC_Ra soat'!$F:$F,'1.PL (VND) '!CU$4,'1.DC_Ra soat'!$H:$H,'1.PL (VND) '!$C17)+SUMIFS('1.DC_Ra soat'!$L:$L,'1.DC_Ra soat'!$F:$F,'1.PL (VND) '!CU$4,'1.DC_Ra soat'!$I:$I,'1.PL (VND) '!$C17) -> 0 | CV17: =-SUMIFS('1.DC_Ra soat'!$L:$L,'1.DC_Ra soat'!$F:$F,'1.PL (VND) '!CV$4,'1.DC_Ra soat'!$H:$H,'1.PL (VND) '!$C17)+SUMIFS('1.DC_Ra soat'!$L:$L,'1.DC_Ra soat'!$F:$F,'1.PL (VND) '!CV$4,'1.DC_Ra soat'!$I:$I,'1.PL (VND) '!$C17) -> 0 | CW17: =-SUMIFS('1.DC_Ra soat'!$L:$L,'1.DC_Ra soat'!$F:$F,'1.PL (VND) '!CW$4,'1.DC_Ra soat'!$H:$H,'1.PL (VND) '!$C17)+SUMIFS('1.DC_Ra soat'!$L:$L,'1.DC_Ra soat'!$F:$F,'1.PL (VND) '!CW$4,'1.DC_Ra soat'!$I:$I,'1.PL (VND) '!$C17) -> 0 | CX17: =-SUMIFS('1.DC_Ra soat'!$L:$L,'1.DC_Ra soat'!$F:$F,'1.PL (VND) '!CX$4,'1.DC_Ra soat'!$H:$H,'1.PL (VND) '!$C17)+SUMIFS('1.DC_Ra soat'!$L:$L,'1.DC_Ra soat'!$F:$F,'1.PL (VND) '!CX$4,'1.DC_Ra soat'!$I:$I,'1.PL (VND) '!$C17) -> 0 | CZ17: =CP17+CU17 -> 0 | DA17: =CQ17+CV17 -> 0 | DB17: =CR17+CW17 -> 0 | DC17: =CS17+CX17 -> 240600000
B18: 9. Chi phí quản lý doanh nghiệp | C18: 26 | D18: 6112406836 | E18: 11423662819 | F18: 7465300147 | G18: 11492599238 | I18: 1010849 | J18: 1454227638 | K18: 2063563404 | L18: 380420389 | N18: 4380500388 | O18: 5725104791 | P18: 1648893959 | Q18: 1709584146 | S18: 376250812 | T18: 1247001186 | U18: 1246767325 | V18: 1138916982 | AH18: =SUMIFS('1.DC_Ra soat'!$L:$L,'1.DC_Ra soat'!$F:$F,'1.PL (VND) '!AH$4,'1.DC_Ra soat'!$H:$H,'1.PL (VND) '!$C18)-SUMIFS('1.DC_Ra soat'!$L:$L,'1.DC_Ra soat'!$F:$F,'1.PL (VND) '!AH$4,'1.DC_Ra soat'!$I:$I,'1.PL (VND) '!$C18) -> 0 | AI18: =SUMIFS('1.DC_Ra soat'!$L:$L,'1.DC_Ra soat'!$F:$F,'1.PL (VND) '!AI$4,'1.DC_Ra soat'!$H:$H,'1.PL (VND) '!$C18)-SUMIFS('1.DC_Ra soat'!$L:$L,'1.DC_Ra soat'!$F:$F,'1.PL (VND) '!AI$4,'1.DC_Ra soat'!$I:$I,'1.PL (VND) '!$C18) -> 0 | AJ18: =SUMIFS('1.DC_Ra soat'!$L:$L,'1.DC_Ra soat'!$F:$F,'1.PL (VND) '!AJ$4,'1.DC_Ra soat'!$H:$H,'1.PL (VND) '!$C18)-SUMIFS('1.DC_Ra soat'!$L:$L,'1.DC_Ra soat'!$F:$F,'1.PL (VND) '!AJ$4,'1.DC_Ra soat'!$I:$I,'1.PL (VND) '!$C18) -> 0 | AK18: =SUMIFS('1.DC_Ra soat'!$L:$L,'1.DC_Ra soat'!$F:$F,'1.PL (VND) '!AK$4,'1.DC_Ra soat'!$H:$H,'1.PL (VND) '!$C18)-SUMIFS('1.DC_Ra soat'!$L:$L,'1.DC_Ra soat'!$F:$F,'1.PL (VND) '!AK$4,'1.DC_Ra soat'!$I:$I,'1.PL (VND) '!$C18) -> 3550000000 | AM18: =SUMIFS('1.DC_Ra soat'!$L:$L,'1.DC_Ra soat'!$F:$F,'1.PL (VND) '!AM$4,'1.DC_Ra soat'!$H:$H,'1.PL (VND) '!$C18)-SUMIFS('1.DC_Ra soat'!$L:$L,'1.DC_Ra soat'!$F:$F,'1.PL (VND) '!AM$4,'1.DC_Ra soat'!$I:$I,'1.PL (VND) '!$C18) -> 0 | AN18: =SUMIFS('1.DC_Ra soat'!$L:$L,'1.DC_Ra soat'!$F:$F,'1.PL (VND) '!AN$4,'1.DC_Ra soat'!$H:$H,'1.PL (VND) '!$C18)-SUMIFS('1.DC_Ra soat'!$L:$L,'1.DC_Ra soat'!$F:$F,'1.PL (VND) '!AN$4,'1.DC_Ra soat'!$I:$I,'1.PL (VND) '!$C18) -> 0 | AO18: =SUMIFS('1.DC_Ra soat'!$L:$L,'1.DC_Ra soat'!$F:$F,'1.PL (VND) '!AO$4,'1.DC_Ra soat'!$H:$H,'1.PL (VND) '!$C18)-SUMIFS('1.DC_Ra soat'!$L:$L,'1.DC_Ra soat'!$F:$F,'1.PL (VND) '!AO$4,'1.DC_Ra soat'!$I:$I,'1.PL (VND) '!$C18) -> 0 | AP18: =SUMIFS('1.DC_Ra soat'!$L:$L,'1.DC_Ra soat'!$F:$F,'1.PL (VND) '!AP$4,'1.DC_Ra soat'!$H:$H,'1.PL (VND) '!$C18)-SUMIFS('1.DC_Ra soat'!$L:$L,'1.DC_Ra soat'!$F:$F,'1.PL (VND) '!AP$4,'1.DC_Ra soat'!$I:$I,'1.PL (VND) '!$C18) -> 0 | AR18: =SUMIFS('1.DC_Ra soat'!$L:$L,'1.DC_Ra soat'!$F:$F,'1.PL (VND) '!AR$4,'1.DC_Ra soat'!$H:$H,'1.PL (VND) '!$C18)-SUMIFS('1.DC_Ra soat'!$L:$L,'1.DC_Ra soat'!$F:$F,'1.PL (VND) '!AR$4,'1.DC_Ra soat'!$I:$I,'1.PL (VND) '!$C18) -> 0 | AS18: =SUMIFS('1.DC_Ra soat'!$L:$L,'1.DC_Ra soat'!$F:$F,'1.PL (VND) '!AS$4,'1.DC_Ra soat'!$H:$H,'1.PL (VND) '!$C18)-SUMIFS('1.DC_Ra soat'!$L:$L,'1.DC_Ra soat'!$F:$F,'1.PL (VND) '!AS$4,'1.DC_Ra soat'!$I:$I,'1.PL (VND) '!$C18) -> 0 | AT18: =SUMIFS('1.DC_Ra soat'!$L:$L,'1.DC_Ra soat'!$F:$F,'1.PL (VND) '!AT$4,'1.DC_Ra soat'!$H:$H,'1.PL (VND) '!$C18)-SUMIFS('1.DC_Ra soat'!$L:$L,'1.DC_Ra soat'!$F:$F,'1.PL (VND) '!AT$4,'1.DC_Ra soat'!$I:$I,'1.PL (VND) '!$C18) -> 0 | AU18: =SUMIFS('1.DC_Ra soat'!$L:$L,'1.DC_Ra soat'!$F:$F,'1.PL (VND) '!AU$4,'1.DC_Ra soat'!$H:$H,'1.PL (VND) '!$C18)-SUMIFS('1.DC_Ra soat'!$L:$L,'1.DC_Ra soat'!$F:$F,'1.PL (VND) '!AU$4,'1.DC_Ra soat'!$I:$I,'1.PL (VND) '!$C18) -> 4950000000 | AW18: =SUMIFS('1.DC_Ra soat'!$L:$L,'1.DC_Ra soat'!$F:$F,'1.PL (VND) '!AW$4,'1.DC_Ra soat'!$H:$H,'1.PL (VND) '!$C18)-SUMIFS('1.DC_Ra soat'!$L:$L,'1.DC_Ra soat'!$F:$F,'1.PL (VND) '!AW$4,'1.DC_Ra soat'!$I:$I,'1.PL (VND) '!$C18) -> 0 | AX18: =SUMIFS('1.DC_Ra soat'!$L:$L,'1.DC_Ra soat'!$F:$F,'1.PL (VND) '!AX$4,'1.DC_Ra soat'!$H:$H,'1.PL (VND) '!$C18)-SUMIFS('1.DC_Ra soat'!$L:$L,'1.DC_Ra soat'!$F:$F,'1.PL (VND) '!AX$4,'1.DC_Ra soat'!$I:$I,'1.PL (VND) '!$C18) -> 0 | AY18: =SUMIFS('1.DC_Ra soat'!$L:$L,'1.DC_Ra soat'!$F:$F,'1.PL (VND) '!AY$4,'1.DC_Ra soat'!$H:$H,'1.PL (VND) '!$C18)-SUMIFS('1.DC_Ra soat'!$L:$L,'1.DC_Ra soat'!$F:$F,'1.PL (VND) '!AY$4,'1.DC_Ra soat'!$I:$I,'1.PL (VND) '!$C18) -> 0 | AZ18: =SUMIFS('1.DC_Ra soat'!$L:$L,'1.DC_Ra soat'!$F:$F,'1.PL (VND) '!AZ$4,'1.DC_Ra soat'!$H:$H,'1.PL (VND) '!$C18)-SUMIFS('1.DC_Ra soat'!$L:$L,'1.DC_Ra soat'!$F:$F,'1.PL (VND) '!AZ$4,'1.DC_Ra soat'!$I:$I,'1.PL (VND) '!$C18) -> 5000000000 | BB18: =SUMIFS('1.DC_Ra soat'!$L:$L,'1.DC_Ra soat'!$F:$F,'1.PL (VND) '!BB$4,'1.DC_Ra soat'!$H:$H,'1.PL (VND) '!$C18)-SUMIFS('1.DC_Ra soat'!$L:$L,'1.DC_Ra soat'!$F:$F,'1.PL (VND) '!BB$4,'1.DC_Ra soat'!$I:$I,'1.PL (VND) '!$C18) -> 0 | BC18: =SUMIFS('1.DC_Ra soat'!$L:$L,'1.DC_Ra soat'!$F:$F,'1.PL (VND) '!BC$4,'1.DC_Ra soat'!$H:$H,'1.PL (VND) '!$C18)-SUMIFS('1.DC_Ra soat'!$L:$L,'1.DC_Ra soat'!$F:$F,'1.PL (VND) '!BC$4,'1.DC_Ra soat'!$I:$I,'1.PL (VND) '!$C18) -> 0 | BD18: =SUMIFS('1.DC_Ra soat'!$L:$L,'1.DC_Ra soat'!$F:$F,'1.PL (VND) '!BD$4,'1.DC_Ra soat'!$H:$H,'1.PL (VND) '!$C18)-SUMIFS('1.DC_Ra soat'!$L:$L,'1.DC_Ra soat'!$F:$F,'1.PL (VND) '!BD$4,'1.DC_Ra soat'!$I:$I,'1.PL (VND) '!$C18) -> 0 | BE18: =SUMIFS('1.DC_Ra soat'!$L:$L,'1.DC_Ra soat'!$F:$F,'1.PL (VND) '!BE$4,'1.DC_Ra soat'!$H:$H,'1.PL (VND) '!$C18)-SUMIFS('1.DC_Ra soat'!$L:$L,'1.DC_Ra soat'!$F:$F,'1.PL (VND) '!BE$4,'1.DC_Ra soat'!$I:$I,'1.PL (VND) '!$C18) -> 0 | BG18: =SUMIFS('1.DC_Ra soat'!$L:$L,'1.DC_Ra soat'!$F:$F,'1.PL (VND) '!BG$4,'1.DC_Ra soat'!$H:$H,'1.PL (VND) '!$C18)-SUMIFS('1.DC_Ra soat'!$L:$L,'1.DC_Ra soat'!$F:$F,'1.PL (VND) '!BG$4,'1.DC_Ra soat'!$I:$I,'1.PL (VND) '!$C18) -> 0 | BH18: =SUMIFS('1.DC_Ra soat'!$L:$L,'1.DC_Ra soat'!$F:$F,'1.PL (VND) '!BH$4,'1.DC_Ra soat'!$H:$H,'1.PL (VND) '!$C18)-SUMIFS('1.DC_Ra soat'!$L:$L,'1.DC_Ra soat'!$F:$F,'1.PL (VND) '!BH$4,'1.DC_Ra soat'!$I:$I,'1.PL (VND) '!$C18) -> 0 | BI18: =SUMIFS('1.DC_Ra soat'!$L:$L,'1.DC_Ra soat'!$F:$F,'1.PL (VND) '!BI$4,'1.DC_Ra soat'!$H:$H,'1.PL (VND) '!$C18)-SUMIFS('1.DC_Ra soat'!$L:$L,'1.DC_Ra soat'!$F:$F,'1.PL (VND) '!BI$4,'1.DC_Ra soat'!$I:$I,'1.PL (VND) '!$C18) -> 0 | BJ18: =SUMIFS('1.DC_Ra soat'!$L:$L,'1.DC_Ra soat'!$F:$F,'1.PL (VND) '!BJ$4,'1.DC_Ra soat'!$H:$H,'1.PL (VND) '!$C18)-SUMIFS('1.DC_Ra soat'!$L:$L,'1.DC_Ra soat'!$F:$F,'1.PL (VND) '!BJ$4,'1.DC_Ra soat'!$I:$I,'1.PL (VND) '!$C18) -> 0 | BL18: =D18+AH18 -> 6112406836 | BM18: =E18+AI18 -> 11423662819 | BN18: =F18+AJ18 -> 7465300147 | BO18: =G18+AK18 -> 15042599238 | BQ18: =I18+AM18 -> 1010849 | BR18: =J18+AN18 -> 1454227638 | BS18: =K18+AO18 -> 2063563404 | BT18: =L18+AP18 -> 380420389 | BV18: =N18+AR18 -> 4380500388 | BW18: =O18+AS18 -> 5725104791 | BX18: =P18+AT18 -> 1648893959 | BY18: =Q18+AU18 -> 6659584146 | CA18: =S18+AW18 -> 376250812 | CB18: =T18+AX18 -> 1247001186 | CC18: =U18+AY18 -> 1246767325 | CD18: =V18+AZ18 -> 6138916982 | CF18: =X18+BB18 -> 0 | CG18: =Y18+BC18 -> 0 | CH18: =Z18+BD18 -> 0 | CI18: =AA18+BE18 -> 0 | CK18: =AC18+BG18 -> 0 | CL18: =AD18+BH18 -> 0 | CM18: =AE18+BI18 -> 0 | CN18: =AF18+BJ18 -> 0 | CP18: =SUMIF($BL$6:$CD$6,CP$6,$BL18:$CD18) -> 10870168885 | CQ18: =SUMIF($BL$6:$CD$6,CQ$6,$BL18:$CD18) -> 19849996434 | CR18: =SUMIF($BL$6:$CD$6,CR$6,$BL18:$CD18) -> 12424524835 | CS18: =SUMIF($BL$6:$CD$6,CS$6,$BL18:$CD18) -> 28221520755 | CU18: =-SUMIFS('1.DC_Ra soat'!$L:$L,'1.DC_Ra soat'!$F:$F,'1.PL (VND) '!CU$4,'1.DC_Ra soat'!$H:$H,'1.PL (VND) '!$C18)+SUMIFS('1.DC_Ra soat'!$L:$L,'1.DC_Ra soat'!$F:$F,'1.PL (VND) '!CU$4,'1.DC_Ra soat'!$I:$I,'1.PL (VND) '!$C18) -> 0 | CV18: =-SUMIFS('1.DC_Ra soat'!$L:$L,'1.DC_Ra soat'!$F:$F,'1.PL (VND) '!CV$4,'1.DC_Ra soat'!$H:$H,'1.PL (VND) '!$C18)+SUMIFS('1.DC_Ra soat'!$L:$L,'1.DC_Ra soat'!$F:$F,'1.PL (VND) '!CV$4,'1.DC_Ra soat'!$I:$I,'1.PL (VND) '!$C18) -> 0 | CW18: =-SUMIFS('1.DC_Ra soat'!$L:$L,'1.DC_Ra soat'!$F:$F,'1.PL (VND) '!CW$4,'1.DC_Ra soat'!$H:$H,'1.PL (VND) '!$C18)+SUMIFS('1.DC_Ra soat'!$L:$L,'1.DC_Ra soat'!$F:$F,'1.PL (VND) '!CW$4,'1.DC_Ra soat'!$I:$I,'1.PL (VND) '!$C18) -> 0 | CX18: =-SUMIFS('1.DC_Ra soat'!$L:$L,'1.DC_Ra soat'!$F:$F,'1.PL (VND) '!CX$4,'1.DC_Ra soat'!$H:$H,'1.PL (VND) '!$C18)+SUMIFS('1.DC_Ra soat'!$L:$L,'1.DC_Ra soat'!$F:$F,'1.PL (VND) '!CX$4,'1.DC_Ra soat'!$I:$I,'1.PL (VND) '!$C18) -> 0 | CZ18: =CP18+CU18 -> 10870168885 | DA18: =CQ18+CV18 -> 19849996434 | DB18: =CR18+CW18 -> 12424524835 | DC18: =CS18+CX18 -> 28221520755
B19: 10. Lợi nhuận thuần từ hoạt động kinh doanh | C19: 30 | D19: =D12+D13-D14-D17-D18 -> -26547565 | E19: =E12+E13-E14-E17-E18 -> 844305322 | F19: =F12+F13-F14-F17-F18 -> 732121400 | G19: =G12+G13-G14-G17-G18 -> 9379610549 | I19: =I12+I13-I14-I17-I18 -> -1009698 | J19: =J12+J13-J14-J17-J18 -> 205981598 | K19: =K12+K13-K14-K17-K18 -> -5280865421 | L19: =L12+L13-L14-L17-L18 -> 30500467824 | N19: =N12+N13-N14-N17-N18 -> 18676515 | O19: =O12+O13-O14-O17-O18 -> -26470749 | P19: =P12+P13-P14-P17-P18 -> 30111095 | Q19: =Q12+Q13-Q14-Q17-Q18 -> -3474427274 | S19: =S12+S13-S14-S17-S18 -> -305983609 | T19: =T12+T13-T14-T17-T18 -> 24373420 | U19: =U12+U13-U14-U17-U18 -> -1548986555 | V19: =V12+V13-V14-V17-V18 -> -1974639951 | X19: =X12+X13-X14-X17-X18 -> 0 | Y19: =Y12+Y13-Y14-Y17-Y18 -> 0 | Z19: =Z12+Z13-Z14-Z17-Z18 -> 0 | AA19: =AA12+AA13-AA14-AA17-AA18 -> 0 | AC19: =AC12+AC13-AC14-AC17-AC18 -> 0 | AD19: =AD12+AD13-AD14-AD17-AD18 -> 0 | AE19: =AE12+AE13-AE14-AE17-AE18 -> 0 | AF19: =AF12+AF13-AF14-AF17-AF18 -> 0 | AH19: =AH12+AH13-AH14-AH17-AH18 -> 0 | AI19: =AI12+AI13-AI14-AI17-AI18 -> 0 | AJ19: =AJ12+AJ13-AJ14-AJ17-AJ18 -> -10749717626 | AK19: =AK12+AK13-AK14-AK17-AK18 -> -4623603888 | AM19: =AM12+AM13-AM14-AM17-AM18 -> 0 | AN19: =AN12+AN13-AN14-AN17-AN18 -> 0 | AO19: =AO12+AO13-AO14-AO17-AO18 -> -741540549 | AP19: =AP12+AP13-AP14-AP17-AP18 -> 0 | AR19: =AR12+AR13-AR14-AR17-AR18 -> 0 | AS19: =AS12+AS13-AS14-AS17-AS18 -> 0 | AT19: =AT12+AT13-AT14-AT17-AT18 -> 0 | AU19: =AU12+AU13-AU14-AU17-AU18 -> -4950000000 | AW19: =AW12+AW13-AW14-AW17-AW18 -> 0 | AX19: =AX12+AX13-AX14-AX17-AX18 -> 0 | AY19: =AY12+AY13-AY14-AY17-AY18 -> -1262355349 | AZ19: =AZ12+AZ13-AZ14-AZ17-AZ18 -> -5000000000 | BB19: =BB12+BB13-BB14-BB17-BB18 -> 0 | BC19: =BC12+BC13-BC14-BC17-BC18 -> 0 | BD19: =BD12+BD13-BD14-BD17-BD18 -> 0 | BG19: =BG12+BG13-BG14-BG17-BG18 -> 0 | BH19: =BH12+BH13-BH14-BH17-BH18 -> 0 | BI19: =BI12+BI13-BI14-BI17-BI18 -> 0 | BL19: =D19+AH19 -> -26547565 | BM19: =E19+AI19 -> 844305322 | BN19: =F19+AJ19 -> -10017596226 | BO19: =G19+AK19 -> 4756006661 | BQ19: =I19+AM19 -> -1009698 | BR19: =J19+AN19 -> 205981598 | BS19: =K19+AO19 -> -6022405970 | BT19: =L19+AP19 -> 30500467824 | BV19: =N19+AR19 -> 18676515 | BW19: =O19+AS19 -> -26470749 | BX19: =P19+AT19 -> 30111095 | BY19: =Q19+AU19 -> -8424427274 | CA19: =S19+AW19 -> -305983609 | CB19: =T19+AX19 -> 24373420 | CC19: =U19+AY19 -> -2811341904 | CD19: =V19+AZ19 -> -6974639951 | CF19: =X19+BB19 -> 0 | CG19: =Y19+BC19 -> 0 | CH19: =Z19+BD19 -> 0 | CI19: =AA19+BE19 -> 0 | CK19: =AC19+BG19 -> 0 | CL19: =AD19+BH19 -> 0 | CM19: =AE19+BI19 -> 0 | CN19: =AF19+BJ19 -> 0 | CP19: =SUMIF($BL$6:$CD$6,CP$6,$BL19:$CD19) -> -314864357 | CQ19: =SUMIF($BL$6:$CD$6,CQ$6,$BL19:$CD19) -> 1048189591 | CR19: =SUMIF($BL$6:$CD$6,CR$6,$BL19:$CD19) -> -18821233005 | CS19: =SUMIF($BL$6:$CD$6,CS$6,$BL19:$CD19) -> 19857407260 | CU19: =CU12+CU13-CU14-CU17-CU18 -> 0 | CV19: =CV12+CV13-CV14-CV17-CV18 -> 0 | CW19: =CW12+CW13-CW14-CW17-CW18 -> 0 | CX19: =CX12+CX13-CX14-CX17-CX18 -> 0 | CZ19: =CP19+CU19 -> -314864357 | DA19: =CQ19+CV19 -> 1048189591 | DB19: =CR19+CW19 -> -18821233005 | DC19: =CS19+CX19 -> 19857407260
B20: 11. Thu nhập khác | C20: 31 | D20: 106425000 | E20: 1776946759 | F20: 106250000 | G20: 23752535 | J20: 3300000 | L20: 2105000 | O20: 181835662 | P20: 2817796296 | Q20: 4800001 | S20: 0 | T20: 0 | U20: 185185185 | AH20: =-SUMIFS('1.DC_Ra soat'!$L:$L,'1.DC_Ra soat'!$F:$F,'1.PL (VND) '!AH$4,'1.DC_Ra soat'!$H:$H,'1.PL (VND) '!$C20)+SUMIFS('1.DC_Ra soat'!$L:$L,'1.DC_Ra soat'!$F:$F,'1.PL (VND) '!AH$4,'1.DC_Ra soat'!$I:$I,'1.PL (VND) '!$C20) -> 0 | AI20: =-SUMIFS('1.DC_Ra soat'!$L:$L,'1.DC_Ra soat'!$F:$F,'1.PL (VND) '!AI$4,'1.DC_Ra soat'!$H:$H,'1.PL (VND) '!$C20)+SUMIFS('1.DC_Ra soat'!$L:$L,'1.DC_Ra soat'!$F:$F,'1.PL (VND) '!AI$4,'1.DC_Ra soat'!$I:$I,'1.PL (VND) '!$C20) -> 0 | AJ20: =-SUMIFS('1.DC_Ra soat'!$L:$L,'1.DC_Ra soat'!$F:$F,'1.PL (VND) '!AJ$4,'1.DC_Ra soat'!$H:$H,'1.PL (VND) '!$C20)+SUMIFS('1.DC_Ra soat'!$L:$L,'1.DC_Ra soat'!$F:$F,'1.PL (VND) '!AJ$4,'1.DC_Ra soat'!$I:$I,'1.PL (VND) '!$C20) -> 0 | AK20: =-SUMIFS('1.DC_Ra soat'!$L:$L,'1.DC_Ra soat'!$F:$F,'1.PL (VND) '!AK$4,'1.DC_Ra soat'!$H:$H,'1.PL (VND) '!$C20)+SUMIFS('1.DC_Ra soat'!$L:$L,'1.DC_Ra soat'!$F:$F,'1.PL (VND) '!AK$4,'1.DC_Ra soat'!$I:$I,'1.PL (VND) '!$C20) -> 0 | AM20: =-SUMIFS('1.DC_Ra soat'!$L:$L,'1.DC_Ra soat'!$F:$F,'1.PL (VND) '!AM$4,'1.DC_Ra soat'!$H:$H,'1.PL (VND) '!$C20)+SUMIFS('1.DC_Ra soat'!$L:$L,'1.DC_Ra soat'!$F:$F,'1.PL (VND) '!AM$4,'1.DC_Ra soat'!$I:$I,'1.PL (VND) '!$C20) -> 0 | AN20: =-SUMIFS('1.DC_Ra soat'!$L:$L,'1.DC_Ra soat'!$F:$F,'1.PL (VND) '!AN$4,'1.DC_Ra soat'!$H:$H,'1.PL (VND) '!$C20)+SUMIFS('1.DC_Ra soat'!$L:$L,'1.DC_Ra soat'!$F:$F,'1.PL (VND) '!AN$4,'1.DC_Ra soat'!$I:$I,'1.PL (VND) '!$C20) -> 0 | AO20: =-SUMIFS('1.DC_Ra soat'!$L:$L,'1.DC_Ra soat'!$F:$F,'1.PL (VND) '!AO$4,'1.DC_Ra soat'!$H:$H,'1.PL (VND) '!$C20)+SUMIFS('1.DC_Ra soat'!$L:$L,'1.DC_Ra soat'!$F:$F,'1.PL (VND) '!AO$4,'1.DC_Ra soat'!$I:$I,'1.PL (VND) '!$C20) -> 0 | AP20: =-SUMIFS('1.DC_Ra soat'!$L:$L,'1.DC_Ra soat'!$F:$F,'1.PL (VND) '!AP$4,'1.DC_Ra soat'!$H:$H,'1.PL (VND) '!$C20)+SUMIFS('1.DC_Ra soat'!$L:$L,'1.DC_Ra soat'!$F:$F,'1.PL (VND) '!AP$4,'1.DC_Ra soat'!$I:$I,'1.PL (VND) '!$C20) -> 0 | AR20: =-SUMIFS('1.DC_Ra soat'!$L:$L,'1.DC_Ra soat'!$F:$F,'1.PL (VND) '!AR$4,'1.DC_Ra soat'!$H:$H,'1.PL (VND) '!$C20)+SUMIFS('1.DC_Ra soat'!$L:$L,'1.DC_Ra soat'!$F:$F,'1.PL (VND) '!AR$4,'1.DC_Ra soat'!$I:$I,'1.PL (VND) '!$C20) -> 0 | AS20: =-SUMIFS('1.DC_Ra soat'!$L:$L,'1.DC_Ra soat'!$F:$F,'1.PL (VND) '!AS$4,'1.DC_Ra soat'!$H:$H,'1.PL (VND) '!$C20)+SUMIFS('1.DC_Ra soat'!$L:$L,'1.DC_Ra soat'!$F:$F,'1.PL (VND) '!AS$4,'1.DC_Ra soat'!$I:$I,'1.PL (VND) '!$C20) -> 0 | AT20: =-SUMIFS('1.DC_Ra soat'!$L:$L,'1.DC_Ra soat'!$F:$F,'1.PL (VND) '!AT$4,'1.DC_Ra soat'!$H:$H,'1.PL (VND) '!$C20)+SUMIFS('1.DC_Ra soat'!$L:$L,'1.DC_Ra soat'!$F:$F,'1.PL (VND) '!AT$4,'1.DC_Ra soat'!$I:$I,'1.PL (VND) '!$C20) -> 0 | AU20: =-SUMIFS('1.DC_Ra soat'!$L:$L,'1.DC_Ra soat'!$F:$F,'1.PL (VND) '!AU$4,'1.DC_Ra soat'!$H:$H,'1.PL (VND) '!$C20)+SUMIFS('1.DC_Ra soat'!$L:$L,'1.DC_Ra soat'!$F:$F,'1.PL (VND) '!AU$4,'1.DC_Ra soat'!$I:$I,'1.PL (VND) '!$C20) -> 0 | AW20: =-SUMIFS('1.DC_Ra soat'!$L:$L,'1.DC_Ra soat'!$F:$F,'1.PL (VND) '!AW$4,'1.DC_Ra soat'!$H:$H,'1.PL (VND) '!$C20)+SUMIFS('1.DC_Ra soat'!$L:$L,'1.DC_Ra soat'!$F:$F,'1.PL (VND) '!AW$4,'1.DC_Ra soat'!$I:$I,'1.PL (VND) '!$C20) -> 0 | AX20: =-SUMIFS('1.DC_Ra soat'!$L:$L,'1.DC_Ra soat'!$F:$F,'1.PL (VND) '!AX$4,'1.DC_Ra soat'!$H:$H,'1.PL (VND) '!$C20)+SUMIFS('1.DC_Ra soat'!$L:$L,'1.DC_Ra soat'!$F:$F,'1.PL (VND) '!AX$4,'1.DC_Ra soat'!$I:$I,'1.PL (VND) '!$C20) -> 0 | AY20: =-SUMIFS('1.DC_Ra soat'!$L:$L,'1.DC_Ra soat'!$F:$F,'1.PL (VND) '!AY$4,'1.DC_Ra soat'!$H:$H,'1.PL (VND) '!$C20)+SUMIFS('1.DC_Ra soat'!$L:$L,'1.DC_Ra soat'!$F:$F,'1.PL (VND) '!AY$4,'1.DC_Ra soat'!$I:$I,'1.PL (VND) '!$C20) -> 0 | AZ20: =-SUMIFS('1.DC_Ra soat'!$L:$L,'1.DC_Ra soat'!$F:$F,'1.PL (VND) '!AZ$4,'1.DC_Ra soat'!$H:$H,'1.PL (VND) '!$C20)+SUMIFS('1.DC_Ra soat'!$L:$L,'1.DC_Ra soat'!$F:$F,'1.PL (VND) '!AZ$4,'1.DC_Ra soat'!$I:$I,'1.PL (VND) '!$C20) -> 0 | BB20: =-SUMIFS('1.DC_Ra soat'!$L:$L,'1.DC_Ra soat'!$F:$F,'1.PL (VND) '!BB$4,'1.DC_Ra soat'!$H:$H,'1.PL (VND) '!$C20)+SUMIFS('1.DC_Ra soat'!$L:$L,'1.DC_Ra soat'!$F:$F,'1.PL (VND) '!BB$4,'1.DC_Ra soat'!$I:$I,'1.PL (VND) '!$C20) -> 0 | BC20: =-SUMIFS('1.DC_Ra soat'!$L:$L,'1.DC_Ra soat'!$F:$F,'1.PL (VND) '!BC$4,'1.DC_Ra soat'!$H:$H,'1.PL (VND) '!$C20)+SUMIFS('1.DC_Ra soat'!$L:$L,'1.DC_Ra soat'!$F:$F,'1.PL (VND) '!BC$4,'1.DC_Ra soat'!$I:$I,'1.PL (VND) '!$C20) -> 0 | BD20: =-SUMIFS('1.DC_Ra soat'!$L:$L,'1.DC_Ra soat'!$F:$F,'1.PL (VND) '!BD$4,'1.DC_Ra soat'!$H:$H,'1.PL (VND) '!$C20)+SUMIFS('1.DC_Ra soat'!$L:$L,'1.DC_Ra soat'!$F:$F,'1.PL (VND) '!BD$4,'1.DC_Ra soat'!$I:$I,'1.PL (VND) '!$C20) -> 0 | BE20: =-SUMIFS('1.DC_Ra soat'!$L:$L,'1.DC_Ra soat'!$F:$F,'1.PL (VND) '!BE$4,'1.DC_Ra soat'!$H:$H,'1.PL (VND) '!$C20)+SUMIFS('1.DC_Ra soat'!$L:$L,'1.DC_Ra soat'!$F:$F,'1.PL (VND) '!BE$4,'1.DC_Ra soat'!$I:$I,'1.PL (VND) '!$C20) -> 0 | BG20: =-SUMIFS('1.DC_Ra soat'!$L:$L,'1.DC_Ra soat'!$F:$F,'1.PL (VND) '!BG$4,'1.DC_Ra soat'!$H:$H,'1.PL (VND) '!$C20)+SUMIFS('1.DC_Ra soat'!$L:$L,'1.DC_Ra soat'!$F:$F,'1.PL (VND) '!BG$4,'1.DC_Ra soat'!$I:$I,'1.PL (VND) '!$C20) -> 0 | BH20: =-SUMIFS('1.DC_Ra soat'!$L:$L,'1.DC_Ra soat'!$F:$F,'1.PL (VND) '!BH$4,'1.DC_Ra soat'!$H:$H,'1.PL (VND) '!$C20)+SUMIFS('1.DC_Ra soat'!$L:$L,'1.DC_Ra soat'!$F:$F,'1.PL (VND) '!BH$4,'1.DC_Ra soat'!$I:$I,'1.PL (VND) '!$C20) -> 0 | BI20: =-SUMIFS('1.DC_Ra soat'!$L:$L,'1.DC_Ra soat'!$F:$F,'1.PL (VND) '!BI$4,'1.DC_Ra soat'!$H:$H,'1.PL (VND) '!$C20)+SUMIFS('1.DC_Ra soat'!$L:$L,'1.DC_Ra soat'!$F:$F,'1.PL (VND) '!BI$4,'1.DC_Ra soat'!$I:$I,'1.PL (VND) '!$C20) -> 0 | BJ20: =-SUMIFS('1.DC_Ra soat'!$L:$L,'1.DC_Ra soat'!$F:$F,'1.PL (VND) '!BJ$4,'1.DC_Ra soat'!$H:$H,'1.PL (VND) '!$C20)+SUMIFS('1.DC_Ra soat'!$L:$L,'1.DC_Ra soat'!$F:$F,'1.PL (VND) '!BJ$4,'1.DC_Ra soat'!$I:$I,'1.PL (VND) '!$C20) -> 0 | BL20: =D20+AH20 -> 106425000 | BM20: =E20+AI20 -> 1776946759 | BN20: =F20+AJ20 -> 106250000 | BO20: =G20+AK20 -> 23752535 | BQ20: =I20+AM20 -> 0 | BR20: =J20+AN20 -> 3300000 | BS20: =K20+AO20 -> 0 | BT20: =L20+AP20 -> 2105000 | BV20: =N20+AR20 -> 0 | BW20: =O20+AS20 -> 181835662 | BX20: =P20+AT20 -> 2817796296 | BY20: =Q20+AU20 -> 4800001 | CA20: =S20+AW20 -> 0 | CB20: =T20+AX20 -> 0 | CC20: =U20+AY20 -> 185185185 | CD20: =V20+AZ20 -> 0 | CF20: =X20+BB20 -> 0 | CG20: =Y20+BC20 -> 0 | CH20: =Z20+BD20 -> 0 | CI20: =AA20+BE20 -> 0 | CK20: =AC20+BG20 -> 0 | CL20: =AD20+BH20 -> 0 | CM20: =AE20+BI20 -> 0 | CN20: =AF20+BJ20 -> 0 | CP20: =SUMIF($BL$6:$CD$6,CP$6,$BL20:$CD20) -> 106425000 | CQ20: =SUMIF($BL$6:$CD$6,CQ$6,$BL20:$CD20) -> 1962082421 | CR20: =SUMIF($BL$6:$CD$6,CR$6,$BL20:$CD20) -> 3109231481 | CS20: =SUMIF($BL$6:$CD$6,CS$6,$BL20:$CD20) -> 30657536 | CU20: =-SUMIFS('1.DC_Ra soat'!$L:$L,'1.DC_Ra soat'!$F:$F,'1.PL (VND) '!CU$4,'1.DC_Ra soat'!$H:$H,'1.PL (VND) '!$C20)+SUMIFS('1.DC_Ra soat'!$L:$L,'1.DC_Ra soat'!$F:$F,'1.PL (VND) '!CU$4,'1.DC_Ra soat'!$I:$I,'1.PL (VND) '!$C20) -> 0 | CV20: =-SUMIFS('1.DC_Ra soat'!$L:$L,'1.DC_Ra soat'!$F:$F,'1.PL (VND) '!CV$4,'1.DC_Ra soat'!$H:$H,'1.PL (VND) '!$C20)+SUMIFS('1.DC_Ra soat'!$L:$L,'1.DC_Ra soat'!$F:$F,'1.PL (VND) '!CV$4,'1.DC_Ra soat'!$I:$I,'1.PL (VND) '!$C20) -> 0 | CW20: =-SUMIFS('1.DC_Ra soat'!$L:$L,'1.DC_Ra soat'!$F:$F,'1.PL (VND) '!CW$4,'1.DC_Ra soat'!$H:$H,'1.PL (VND) '!$C20)+SUMIFS('1.DC_Ra soat'!$L:$L,'1.DC_Ra soat'!$F:$F,'1.PL (VND) '!CW$4,'1.DC_Ra soat'!$I:$I,'1.PL (VND) '!$C20) -> 0 | CX20: =-SUMIFS('1.DC_Ra soat'!$L:$L,'1.DC_Ra soat'!$F:$F,'1.PL (VND) '!CX$4,'1.DC_Ra soat'!$H:$H,'1.PL (VND) '!$C20)+SUMIFS('1.DC_Ra soat'!$L:$L,'1.DC_Ra soat'!$F:$F,'1.PL (VND) '!CX$4,'1.DC_Ra soat'!$I:$I,'1.PL (VND) '!$C20) -> 0 | CZ20: =CP20+CU20 -> 106425000 | DA20: =CQ20+CV20 -> 1962082421 | DB20: =CR20+CW20 -> 3109231481 | DC20: =CS20+CX20 -> 30657536
B21: 12. Chi phí khác | C21: 32 | E21: 2450371322 | G21: 152726972 | L21: 380001 | O21: 78282827 | P21: 2811473154 | U21: 573037500 | V21: 2271321 | AH21: =SUMIFS('1.DC_Ra soat'!$L:$L,'1.DC_Ra soat'!$F:$F,'1.PL (VND) '!AH$4,'1.DC_Ra soat'!$H:$H,'1.PL (VND) '!$C21)-SUMIFS('1.DC_Ra soat'!$L:$L,'1.DC_Ra soat'!$F:$F,'1.PL (VND) '!AH$4,'1.DC_Ra soat'!$I:$I,'1.PL (VND) '!$C21) -> 0 | AI21: =SUMIFS('1.DC_Ra soat'!$L:$L,'1.DC_Ra soat'!$F:$F,'1.PL (VND) '!AI$4,'1.DC_Ra soat'!$H:$H,'1.PL (VND) '!$C21)-SUMIFS('1.DC_Ra soat'!$L:$L,'1.DC_Ra soat'!$F:$F,'1.PL (VND) '!AI$4,'1.DC_Ra soat'!$I:$I,'1.PL (VND) '!$C21) -> 0 | AJ21: =SUMIFS('1.DC_Ra soat'!$L:$L,'1.DC_Ra soat'!$F:$F,'1.PL (VND) '!AJ$4,'1.DC_Ra soat'!$H:$H,'1.PL (VND) '!$C21)-SUMIFS('1.DC_Ra soat'!$L:$L,'1.DC_Ra soat'!$F:$F,'1.PL (VND) '!AJ$4,'1.DC_Ra soat'!$I:$I,'1.PL (VND) '!$C21) -> 0 | AK21: =SUMIFS('1.DC_Ra soat'!$L:$L,'1.DC_Ra soat'!$F:$F,'1.PL (VND) '!AK$4,'1.DC_Ra soat'!$H:$H,'1.PL (VND) '!$C21)-SUMIFS('1.DC_Ra soat'!$L:$L,'1.DC_Ra soat'!$F:$F,'1.PL (VND) '!AK$4,'1.DC_Ra soat'!$I:$I,'1.PL (VND) '!$C21) -> 0 | AM21: =SUMIFS('1.DC_Ra soat'!$L:$L,'1.DC_Ra soat'!$F:$F,'1.PL (VND) '!AM$4,'1.DC_Ra soat'!$H:$H,'1.PL (VND) '!$C21)-SUMIFS('1.DC_Ra soat'!$L:$L,'1.DC_Ra soat'!$F:$F,'1.PL (VND) '!AM$4,'1.DC_Ra soat'!$I:$I,'1.PL (VND) '!$C21) -> 0 | AN21: =SUMIFS('1.DC_Ra soat'!$L:$L,'1.DC_Ra soat'!$F:$F,'1.PL (VND) '!AN$4,'1.DC_Ra soat'!$H:$H,'1.PL (VND) '!$C21)-SUMIFS('1.DC_Ra soat'!$L:$L,'1.DC_Ra soat'!$F:$F,'1.PL (VND) '!AN$4,'1.DC_Ra soat'!$I:$I,'1.PL (VND) '!$C21) -> 0 | AO21: =SUMIFS('1.DC_Ra soat'!$L:$L,'1.DC_Ra soat'!$F:$F,'1.PL (VND) '!AO$4,'1.DC_Ra soat'!$H:$H,'1.PL (VND) '!$C21)-SUMIFS('1.DC_Ra soat'!$L:$L,'1.DC_Ra soat'!$F:$F,'1.PL (VND) '!AO$4,'1.DC_Ra soat'!$I:$I,'1.PL (VND) '!$C21) -> 0 | AP21: =SUMIFS('1.DC_Ra soat'!$L:$L,'1.DC_Ra soat'!$F:$F,'1.PL (VND) '!AP$4,'1.DC_Ra soat'!$H:$H,'1.PL (VND) '!$C21)-SUMIFS('1.DC_Ra soat'!$L:$L,'1.DC_Ra soat'!$F:$F,'1.PL (VND) '!AP$4,'1.DC_Ra soat'!$I:$I,'1.PL (VND) '!$C21) -> 0 | AR21: =SUMIFS('1.DC_Ra soat'!$L:$L,'1.DC_Ra soat'!$F:$F,'1.PL (VND) '!AR$4,'1.DC_Ra soat'!$H:$H,'1.PL (VND) '!$C21)-SUMIFS('1.DC_Ra soat'!$L:$L,'1.DC_Ra soat'!$F:$F,'1.PL (VND) '!AR$4,'1.DC_Ra soat'!$I:$I,'1.PL (VND) '!$C21) -> 0 | AS21: =SUMIFS('1.DC_Ra soat'!$L:$L,'1.DC_Ra soat'!$F:$F,'1.PL (VND) '!AS$4,'1.DC_Ra soat'!$H:$H,'1.PL (VND) '!$C21)-SUMIFS('1.DC_Ra soat'!$L:$L,'1.DC_Ra soat'!$F:$F,'1.PL (VND) '!AS$4,'1.DC_Ra soat'!$I:$I,'1.PL (VND) '!$C21) -> 0 | AT21: =SUMIFS('1.DC_Ra soat'!$L:$L,'1.DC_Ra soat'!$F:$F,'1.PL (VND) '!AT$4,'1.DC_Ra soat'!$H:$H,'1.PL (VND) '!$C21)-SUMIFS('1.DC_Ra soat'!$L:$L,'1.DC_Ra soat'!$F:$F,'1.PL (VND) '!AT$4,'1.DC_Ra soat'!$I:$I,'1.PL (VND) '!$C21) -> 0 | AU21: =SUMIFS('1.DC_Ra soat'!$L:$L,'1.DC_Ra soat'!$F:$F,'1.PL (VND) '!AU$4,'1.DC_Ra soat'!$H:$H,'1.PL (VND) '!$C21)-SUMIFS('1.DC_Ra soat'!$L:$L,'1.DC_Ra soat'!$F:$F,'1.PL (VND) '!AU$4,'1.DC_Ra soat'!$I:$I,'1.PL (VND) '!$C21) -> 0 | AW21: =SUMIFS('1.DC_Ra soat'!$L:$L,'1.DC_Ra soat'!$F:$F,'1.PL (VND) '!AW$4,'1.DC_Ra soat'!$H:$H,'1.PL (VND) '!$C21)-SUMIFS('1.DC_Ra soat'!$L:$L,'1.DC_Ra soat'!$F:$F,'1.PL (VND) '!AW$4,'1.DC_Ra soat'!$I:$I,'1.PL (VND) '!$C21) -> 0 | AX21: =SUMIFS('1.DC_Ra soat'!$L:$L,'1.DC_Ra soat'!$F:$F,'1.PL (VND) '!AX$4,'1.DC_Ra soat'!$H:$H,'1.PL (VND) '!$C21)-SUMIFS('1.DC_Ra soat'!$L:$L,'1.DC_Ra soat'!$F:$F,'1.PL (VND) '!AX$4,'1.DC_Ra soat'!$I:$I,'1.PL (VND) '!$C21) -> 0 | AY21: =SUMIFS('1.DC_Ra soat'!$L:$L,'1.DC_Ra soat'!$F:$F,'1.PL (VND) '!AY$4,'1.DC_Ra soat'!$H:$H,'1.PL (VND) '!$C21)-SUMIFS('1.DC_Ra soat'!$L:$L,'1.DC_Ra soat'!$F:$F,'1.PL (VND) '!AY$4,'1.DC_Ra soat'!$I:$I,'1.PL (VND) '!$C21) -> 0 | AZ21: =SUMIFS('1.DC_Ra soat'!$L:$L,'1.DC_Ra soat'!$F:$F,'1.PL (VND) '!AZ$4,'1.DC_Ra soat'!$H:$H,'1.PL (VND) '!$C21)-SUMIFS('1.DC_Ra soat'!$L:$L,'1.DC_Ra soat'!$F:$F,'1.PL (VND) '!AZ$4,'1.DC_Ra soat'!$I:$I,'1.PL (VND) '!$C21) -> 0 | BB21: =SUMIFS('1.DC_Ra soat'!$L:$L,'1.DC_Ra soat'!$F:$F,'1.PL (VND) '!BB$4,'1.DC_Ra soat'!$H:$H,'1.PL (VND) '!$C21)-SUMIFS('1.DC_Ra soat'!$L:$L,'1.DC_Ra soat'!$F:$F,'1.PL (VND) '!BB$4,'1.DC_Ra soat'!$I:$I,'1.PL (VND) '!$C21) -> 0 | BC21: =SUMIFS('1.DC_Ra soat'!$L:$L,'1.DC_Ra soat'!$F:$F,'1.PL (VND) '!BC$4,'1.DC_Ra soat'!$H:$H,'1.PL (VND) '!$C21)-SUMIFS('1.DC_Ra soat'!$L:$L,'1.DC_Ra soat'!$F:$F,'1.PL (VND) '!BC$4,'1.DC_Ra soat'!$I:$I,'1.PL (VND) '!$C21) -> 0 | BD21: =SUMIFS('1.DC_Ra soat'!$L:$L,'1.DC_Ra soat'!$F:$F,'1.PL (VND) '!BD$4,'1.DC_Ra soat'!$H:$H,'1.PL (VND) '!$C21)-SUMIFS('1.DC_Ra soat'!$L:$L,'1.DC_Ra soat'!$F:$F,'1.PL (VND) '!BD$4,'1.DC_Ra soat'!$I:$I,'1.PL (VND) '!$C21) -> 0 | BE21: =SUMIFS('1.DC_Ra soat'!$L:$L,'1.DC_Ra soat'!$F:$F,'1.PL (VND) '!BE$4,'1.DC_Ra soat'!$H:$H,'1.PL (VND) '!$C21)-SUMIFS('1.DC_Ra soat'!$L:$L,'1.DC_Ra soat'!$F:$F,'1.PL (VND) '!BE$4,'1.DC_Ra soat'!$I:$I,'1.PL (VND) '!$C21) -> 0 | BG21: =SUMIFS('1.DC_Ra soat'!$L:$L,'1.DC_Ra soat'!$F:$F,'1.PL (VND) '!BG$4,'1.DC_Ra soat'!$H:$H,'1.PL (VND) '!$C21)-SUMIFS('1.DC_Ra soat'!$L:$L,'1.DC_Ra soat'!$F:$F,'1.PL (VND) '!BG$4,'1.DC_Ra soat'!$I:$I,'1.PL (VND) '!$C21) -> 0 | BH21: =SUMIFS('1.DC_Ra soat'!$L:$L,'1.DC_Ra soat'!$F:$F,'1.PL (VND) '!BH$4,'1.DC_Ra soat'!$H:$H,'1.PL (VND) '!$C21)-SUMIFS('1.DC_Ra soat'!$L:$L,'1.DC_Ra soat'!$F:$F,'1.PL (VND) '!BH$4,'1.DC_Ra soat'!$I:$I,'1.PL (VND) '!$C21) -> 0 | BI21: =SUMIFS('1.DC_Ra soat'!$L:$L,'1.DC_Ra soat'!$F:$F,'1.PL (VND) '!BI$4,'1.DC_Ra soat'!$H:$H,'1.PL (VND) '!$C21)-SUMIFS('1.DC_Ra soat'!$L:$L,'1.DC_Ra soat'!$F:$F,'1.PL (VND) '!BI$4,'1.DC_Ra soat'!$I:$I,'1.PL (VND) '!$C21) -> 0 | BJ21: =SUMIFS('1.DC_Ra soat'!$L:$L,'1.DC_Ra soat'!$F:$F,'1.PL (VND) '!BJ$4,'1.DC_Ra soat'!$H:$H,'1.PL (VND) '!$C21)-SUMIFS('1.DC_Ra soat'!$L:$L,'1.DC_Ra soat'!$F:$F,'1.PL (VND) '!BJ$4,'1.DC_Ra soat'!$I:$I,'1.PL (VND) '!$C21) -> 0 | BL21: =D21+AH21 -> 0 | BM21: =E21+AI21 -> 2450371322 | BN21: =F21+AJ21 -> 0 | BO21: =G21+AK21 -> 152726972 | BQ21: =I21+AM21 -> 0 | BR21: =J21+AN21 -> 0 | BS21: =K21+AO21 -> 0 | BT21: =L21+AP21 -> 380001 | BV21: =N21+AR21 -> 0 | BW21: =O21+AS21 -> 78282827 | BX21: =P21+AT21 -> 2811473154 | BY21: =Q21+AU21 -> 0 | CA21: =S21+AW21 -> 0 | CB21: =T21+AX21 -> 0 | CC21: =U21+AY21 -> 573037500 | CD21: =V21+AZ21 -> 2271321 | CF21: =X21+BB21 -> 0 | CG21: =Y21+BC21 -> 0 | CH21: =Z21+BD21 -> 0 | CI21: =AA21+BE21 -> 0 | CK21: =AC21+BG21 -> 0 | CL21: =AD21+BH21 -> 0 | CM21: =AE21+BI21 -> 0 | CN21: =AF21+BJ21 -> 0 | CP21: =SUMIF($BL$6:$CD$6,CP$6,$BL21:$CD21) -> 0 | CQ21: =SUMIF($BL$6:$CD$6,CQ$6,$BL21:$CD21) -> 2528654149 | CR21: =SUMIF($BL$6:$CD$6,CR$6,$BL21:$CD21) -> 3384510654 | CS21: =SUMIF($BL$6:$CD$6,CS$6,$BL21:$CD21) -> 155378294 | CU21: =-SUMIFS('1.DC_Ra soat'!$L:$L,'1.DC_Ra soat'!$F:$F,'1.PL (VND) '!CU$4,'1.DC_Ra soat'!$H:$H,'1.PL (VND) '!$C21)+SUMIFS('1.DC_Ra soat'!$L:$L,'1.DC_Ra soat'!$F:$F,'1.PL (VND) '!CU$4,'1.DC_Ra soat'!$I:$I,'1.PL (VND) '!$C21) -> 0 | CV21: =-SUMIFS('1.DC_Ra soat'!$L:$L,'1.DC_Ra soat'!$F:$F,'1.PL (VND) '!CV$4,'1.DC_Ra soat'!$H:$H,'1.PL (VND) '!$C21)+SUMIFS('1.DC_Ra soat'!$L:$L,'1.DC_Ra soat'!$F:$F,'1.PL (VND) '!CV$4,'1.DC_Ra soat'!$I:$I,'1.PL (VND) '!$C21) -> 0 | CW21: =-SUMIFS('1.DC_Ra soat'!$L:$L,'1.DC_Ra soat'!$F:$F,'1.PL (VND) '!CW$4,'1.DC_Ra soat'!$H:$H,'1.PL (VND) '!$C21)+SUMIFS('1.DC_Ra soat'!$L:$L,'1.DC_Ra soat'!$F:$F,'1.PL (VND) '!CW$4,'1.DC_Ra soat'!$I:$I,'1.PL (VND) '!$C21) -> 0 | CX21: =-SUMIFS('1.DC_Ra soat'!$L:$L,'1.DC_Ra soat'!$F:$F,'1.PL (VND) '!CX$4,'1.DC_Ra soat'!$H:$H,'1.PL (VND) '!$C21)+SUMIFS('1.DC_Ra soat'!$L:$L,'1.DC_Ra soat'!$F:$F,'1.PL (VND) '!CX$4,'1.DC_Ra soat'!$I:$I,'1.PL (VND) '!$C21) -> 0 | CZ21: =CP21+CU21 -> 0 | DA21: =CQ21+CV21 -> 2528654149 | DB21: =CR21+CW21 -> 3384510654 | DC21: =CS21+CX21 -> 155378294
B22: 13. Lợi nhuận khác | C22: 40 | D22: =D20-D21 -> 106425000 | E22: =E20-E21 -> -673424563 | F22: =F20-F21 -> 106250000 | G22: =G20-G21 -> -128974437 | I22: =I20-I21 -> 0 | J22: =J20-J21 -> 3300000 | K22: =K20-K21 -> 0 | L22: =L20-L21 -> 1724999 | N22: =N20-N21 -> 0 | O22: =O20-O21 -> 103552835 | P22: =P20-P21 -> 6323142 | Q22: =Q20-Q21 -> 4800001 | S22: =S20-S21 -> 0 | T22: =T20-T21 -> 0 | U22: =U20-U21 -> -387852315 | V22: =V20-V21 -> -2271321 | X22: =X20-X21 -> 0 | Y22: =Y20-Y21 -> 0 | Z22: =Z20-Z21 -> 0 | AA22: =AA20-AA21 -> 0 | AC22: =AC20-AC21 -> 0 | AD22: =AD20-AD21 -> 0 | AE22: =AE20-AE21 -> 0 | AF22: =AF20-AF21 -> 0 | AH22: =AH20-AH21 -> 0 | AI22: =AI20-AI21 -> 0 | AJ22: =AJ20-AJ21 -> 0 | AK22: =AK20-AK21 -> 0 | AM22: =AM20-AM21 -> 0 | AN22: =AN20-AN21 -> 0 | AO22: =AO20-AO21 -> 0 | AP22: =AP20-AP21 -> 0 | AR22: =AR20-AR21 -> 0 | AS22: =AS20-AS21 -> 0 | AT22: =AT20-AT21 -> 0 | AU22: =AU20-AU21 -> 0 | AW22: =AW20-AW21 -> 0 | AX22: =AX20-AX21 -> 0 | AY22: =AY20-AY21 -> 0 | AZ22: =AZ20-AZ21 -> 0 | BB22: =BB20-BB21 -> 0 | BC22: =BC20-BC21 -> 0 | BD22: =BD20-BD21 -> 0 | BG22: =BG20-BG21 -> 0 | BH22: =BH20-BH21 -> 0 | BI22: =BI20-BI21 -> 0 | BL22: =D22+AH22 -> 106425000 | BM22: =E22+AI22 -> -673424563 | BN22: =F22+AJ22 -> 106250000 | BO22: =G22+AK22 -> -128974437 | BQ22: =I22+AM22 -> 0 | BR22: =J22+AN22 -> 3300000 | BS22: =K22+AO22 -> 0 | BT22: =L22+AP22 -> 1724999 | BV22: =N22+AR22 -> 0 | BW22: =O22+AS22 -> 103552835 | BX22: =P22+AT22 -> 6323142 | BY22: =Q22+AU22 -> 4800001 | CA22: =S22+AW22 -> 0 | CB22: =T22+AX22 -> 0 | CC22: =U22+AY22 -> -387852315 | CD22: =V22+AZ22 -> -2271321 | CF22: =X22+BB22 -> 0 | CG22: =Y22+BC22 -> 0 | CH22: =Z22+BD22 -> 0 | CI22: =AA22+BE22 -> 0 | CK22: =AC22+BG22 -> 0 | CL22: =AD22+BH22 -> 0 | CM22: =AE22+BI22 -> 0 | CN22: =AF22+BJ22 -> 0 | CP22: =SUMIF($BL$6:$CD$6,CP$6,$BL22:$CD22) -> 106425000 | CQ22: =SUMIF($BL$6:$CD$6,CQ$6,$BL22:$CD22) -> -566571728 | CR22: =SUMIF($BL$6:$CD$6,CR$6,$BL22:$CD22) -> -275279173 | CS22: =SUMIF($BL$6:$CD$6,CS$6,$BL22:$CD22) -> -124720758 | CU22: =CU20-CU21 -> 0 | CV22: =CV20-CV21 -> 0 | CW22: =CW20-CW21 -> 0 | CX22: =CX20-CX21 -> 0 | CZ22: =CP22+CU22 -> 106425000 | DA22: =CQ22+CV22 -> -566571728 | DB22: =CR22+CW22 -> -275279173 | DC22: =CS22+CX22 -> -124720758
B23: 14. Tổng lợi nhuận kế toán trước thuế | C23: 50 | D23: =D19+D22 -> 79877435 | E23: =E19+E22 -> 170880759 | F23: =F19+F22 -> 838371400 | G23: =G19+G22 -> 9250636112 | I23: =I19+I22 -> -1009698 | J23: =J19+J22 -> 209281598 | K23: =K19+K22 -> -5280865421 | L23: =L19+L22 -> 30502192823 | N23: =N19+N22 -> 18676515 | O23: =O19+O22 -> 77082086 | P23: =P19+P22 -> 36434237 | Q23: =Q19+Q22 -> -3469627273 | S23: =S19+S22 -> -305983609 | T23: =T19+T22 -> 24373420 | U23: =U19+U22 -> -1936838870 | V23: =V19+V22 -> -1976911272 | X23: =X19+X22 -> 0 | Y23: =Y19+Y22 -> 0 | Z23: =Z19+Z22 -> 0 | AA23: =AA19+AA22 -> 0 | AC23: =AC19+AC22 -> 0 | AD23: =AD19+AD22 -> 0 | AE23: =AE19+AE22 -> 0 | AF23: =AF19+AF22 -> 0 | AH23: =AH19+AH22 -> 0 | AI23: =AI19+AI22 -> 0 | AJ23: =AJ19+AJ22 -> -10749717626 | AK23: =AK19+AK22 -> -4623603888 | AM23: =AM19+AM22 -> 0 | AN23: =AN19+AN22 -> 0 | AO23: =AO19+AO22 -> -741540549 | AP23: =AP19+AP22 -> 0 | AR23: =AR19+AR22 -> 0 | AS23: =AS19+AS22 -> 0 | AT23: =AT19+AT22 -> 0 | AU23: =AU19+AU22 -> -4950000000 | AW23: =AW19+AW22 -> 0 | AX23: =AX19+AX22 -> 0 | AY23: =AY19+AY22 -> -1262355349 | AZ23: =AZ19+AZ22 -> -5000000000 | BB23: =BB19+BB22 -> 0 | BC23: =BC19+BC22 -> 0 | BD23: =BD19+BD22 -> 0 | BG23: =BG19+BG22 -> 0 | BH23: =BH19+BH22 -> 0 | BI23: =BI19+BI22 -> 0 | BL23: =D23+AH23 -> 79877435 | BM23: =E23+AI23 -> 170880759 | BN23: =F23+AJ23 -> -9911346226 | BO23: =G23+AK23 -> 4627032224 | BQ23: =I23+AM23 -> -1009698 | BR23: =J23+AN23 -> 209281598 | BS23: =K23+AO23 -> -6022405970 | BT23: =L23+AP23 -> 30502192823 | BV23: =N23+AR23 -> 18676515 | BW23: =O23+AS23 -> 77082086 | BX23: =P23+AT23 -> 36434237 | BY23: =Q23+AU23 -> -8419627273 | CA23: =S23+AW23 -> -305983609 | CB23: =T23+AX23 -> 24373420 | CC23: =U23+AY23 -> -3199194219 | CD23: =V23+AZ23 -> -6976911272 | CF23: =X23+BB23 -> 0 | CG23: =Y23+BC23 -> 0 | CH23: =Z23+BD23 -> 0 | CI23: =AA23+BE23 -> 0 | CK23: =AC23+BG23 -> 0 | CL23: =AD23+BH23 -> 0 | CM23: =AE23+BI23 -> 0 | CN23: =AF23+BJ23 -> 0 | CP23: =SUMIF($BL$6:$CD$6,CP$6,$BL23:$CD23) -> -208439357 | CQ23: =SUMIF($BL$6:$CD$6,CQ$6,$BL23:$CD23) -> 481617863 | CR23: =SUMIF($BL$6:$CD$6,CR$6,$BL23:$CD23) -> -19096512178 | CS23: =SUMIF($BL$6:$CD$6,CS$6,$BL23:$CD23) -> 19732686502 | CU23: =CU19+CU22 -> 0 | CV23: =CV19+CV22 -> 0 | CW23: =CW19+CW22 -> 0 | CX23: =CX19+CX22 -> 0 | CZ23: =CP23+CU23 -> -208439357 | DA23: =CQ23+CV23 -> 481617863 | DB23: =CR23+CW23 -> -19096512178 | DC23: =CS23+CX23 -> 19732686502
B24: 15. Chi phí thuế thu nhập doanh nghiệp hiện hành | C24: 51 | D24: 15975487 | E24: 34176152 | F24: 28102224 | G24: 1.8501272e+09 | L24: 6.1485586e+09 | N24: 2614712 | O24: 10791492 | P24: 7286847 | Q24: 0 | T24: 3412279 | V24: 2271321 | AD24: 0 | AE24: 0 | AH24: =SUMIFS('1.DC_Ra soat'!$L:$L,'1.DC_Ra soat'!$F:$F,'1.PL (VND) '!AH$4,'1.DC_Ra soat'!$H:$H,'1.PL (VND) '!$C24)-SUMIFS('1.DC_Ra soat'!$L:$L,'1.DC_Ra soat'!$F:$F,'1.PL (VND) '!AH$4,'1.DC_Ra soat'!$I:$I,'1.PL (VND) '!$C24) -> 0 | AI24: =SUMIFS('1.DC_Ra soat'!$L:$L,'1.DC_Ra soat'!$F:$F,'1.PL (VND) '!AI$4,'1.DC_Ra soat'!$H:$H,'1.PL (VND) '!$C24)-SUMIFS('1.DC_Ra soat'!$L:$L,'1.DC_Ra soat'!$F:$F,'1.PL (VND) '!AI$4,'1.DC_Ra soat'!$I:$I,'1.PL (VND) '!$C24) -> 0 | AJ24: =SUMIFS('1.DC_Ra soat'!$L:$L,'1.DC_Ra soat'!$F:$F,'1.PL (VND) '!AJ$4,'1.DC_Ra soat'!$H:$H,'1.PL (VND) '!$C24)-SUMIFS('1.DC_Ra soat'!$L:$L,'1.DC_Ra soat'!$F:$F,'1.PL (VND) '!AJ$4,'1.DC_Ra soat'!$I:$I,'1.PL (VND) '!$C24) -> 0 | AK24: =SUMIFS('1.DC_Ra soat'!$L:$L,'1.DC_Ra soat'!$F:$F,'1.PL (VND) '!AK$4,'1.DC_Ra soat'!$H:$H,'1.PL (VND) '!$C24)-SUMIFS('1.DC_Ra soat'!$L:$L,'1.DC_Ra soat'!$F:$F,'1.PL (VND) '!AK$4,'1.DC_Ra soat'!$I:$I,'1.PL (VND) '!$C24) -> 0 | AM24: =SUMIFS('1.DC_Ra soat'!$L:$L,'1.DC_Ra soat'!$F:$F,'1.PL (VND) '!AM$4,'1.DC_Ra soat'!$H:$H,'1.PL (VND) '!$C24)-SUMIFS('1.DC_Ra soat'!$L:$L,'1.DC_Ra soat'!$F:$F,'1.PL (VND) '!AM$4,'1.DC_Ra soat'!$I:$I,'1.PL (VND) '!$C24) -> 0 | AN24: =SUMIFS('1.DC_Ra soat'!$L:$L,'1.DC_Ra soat'!$F:$F,'1.PL (VND) '!AN$4,'1.DC_Ra soat'!$H:$H,'1.PL (VND) '!$C24)-SUMIFS('1.DC_Ra soat'!$L:$L,'1.DC_Ra soat'!$F:$F,'1.PL (VND) '!AN$4,'1.DC_Ra soat'!$I:$I,'1.PL (VND) '!$C24) -> 0 | AO24: =SUMIFS('1.DC_Ra soat'!$L:$L,'1.DC_Ra soat'!$F:$F,'1.PL (VND) '!AO$4,'1.DC_Ra soat'!$H:$H,'1.PL (VND) '!$C24)-SUMIFS('1.DC_Ra soat'!$L:$L,'1.DC_Ra soat'!$F:$F,'1.PL (VND) '!AO$4,'1.DC_Ra soat'!$I:$I,'1.PL (VND) '!$C24) -> 0 | AP24: =SUMIFS('1.DC_Ra soat'!$L:$L,'1.DC_Ra soat'!$F:$F,'1.PL (VND) '!AP$4,'1.DC_Ra soat'!$H:$H,'1.PL (VND) '!$C24)-SUMIFS('1.DC_Ra soat'!$L:$L,'1.DC_Ra soat'!$F:$F,'1.PL (VND) '!AP$4,'1.DC_Ra soat'!$I:$I,'1.PL (VND) '!$C24) -> 0 | AR24: =SUMIFS('1.DC_Ra soat'!$L:$L,'1.DC_Ra soat'!$F:$F,'1.PL (VND) '!AR$4,'1.DC_Ra soat'!$H:$H,'1.PL (VND) '!$C24)-SUMIFS('1.DC_Ra soat'!$L:$L,'1.DC_Ra soat'!$F:$F,'1.PL (VND) '!AR$4,'1.DC_Ra soat'!$I:$I,'1.PL (VND) '!$C24) -> 0 | AS24: =SUMIFS('1.DC_Ra soat'!$L:$L,'1.DC_Ra soat'!$F:$F,'1.PL (VND) '!AS$4,'1.DC_Ra soat'!$H:$H,'1.PL (VND) '!$C24)-SUMIFS('1.DC_Ra soat'!$L:$L,'1.DC_Ra soat'!$F:$F,'1.PL (VND) '!AS$4,'1.DC_Ra soat'!$I:$I,'1.PL (VND) '!$C24) -> 0 | AT24: =SUMIFS('1.DC_Ra soat'!$L:$L,'1.DC_Ra soat'!$F:$F,'1.PL (VND) '!AT$4,'1.DC_Ra soat'!$H:$H,'1.PL (VND) '!$C24)-SUMIFS('1.DC_Ra soat'!$L:$L,'1.DC_Ra soat'!$F:$F,'1.PL (VND) '!AT$4,'1.DC_Ra soat'!$I:$I,'1.PL (VND) '!$C24) -> 0 | AU24: =SUMIFS('1.DC_Ra soat'!$L:$L,'1.DC_Ra soat'!$F:$F,'1.PL (VND) '!AU$4,'1.DC_Ra soat'!$H:$H,'1.PL (VND) '!$C24)-SUMIFS('1.DC_Ra soat'!$L:$L,'1.DC_Ra soat'!$F:$F,'1.PL (VND) '!AU$4,'1.DC_Ra soat'!$I:$I,'1.PL (VND) '!$C24) -> 0 | AW24: =SUMIFS('1.DC_Ra soat'!$L:$L,'1.DC_Ra soat'!$F:$F,'1.PL (VND) '!AW$4,'1.DC_Ra soat'!$H:$H,'1.PL (VND) '!$C24)-SUMIFS('1.DC_Ra soat'!$L:$L,'1.DC_Ra soat'!$F:$F,'1.PL (VND) '!AW$4,'1.DC_Ra soat'!$I:$I,'1.PL (VND) '!$C24) -> 0 | AX24: =SUMIFS('1.DC_Ra soat'!$L:$L,'1.DC_Ra soat'!$F:$F,'1.PL (VND) '!AX$4,'1.DC_Ra soat'!$H:$H,'1.PL (VND) '!$C24)-SUMIFS('1.DC_Ra soat'!$L:$L,'1.DC_Ra soat'!$F:$F,'1.PL (VND) '!AX$4,'1.DC_Ra soat'!$I:$I,'1.PL (VND) '!$C24) -> 0 | AY24: =SUMIFS('1.DC_Ra soat'!$L:$L,'1.DC_Ra soat'!$F:$F,'1.PL (VND) '!AY$4,'1.DC_Ra soat'!$H:$H,'1.PL (VND) '!$C24)-SUMIFS('1.DC_Ra soat'!$L:$L,'1.DC_Ra soat'!$F:$F,'1.PL (VND) '!AY$4,'1.DC_Ra soat'!$I:$I,'1.PL (VND) '!$C24) -> 0 | AZ24: =SUMIFS('1.DC_Ra soat'!$L:$L,'1.DC_Ra soat'!$F:$F,'1.PL (VND) '!AZ$4,'1.DC_Ra soat'!$H:$H,'1.PL (VND) '!$C24)-SUMIFS('1.DC_Ra soat'!$L:$L,'1.DC_Ra soat'!$F:$F,'1.PL (VND) '!AZ$4,'1.DC_Ra soat'!$I:$I,'1.PL (VND) '!$C24) -> 0 | BB24: =SUMIFS('1.DC_Ra soat'!$L:$L,'1.DC_Ra soat'!$F:$F,'1.PL (VND) '!BB$4,'1.DC_Ra soat'!$H:$H,'1.PL (VND) '!$C24)-SUMIFS('1.DC_Ra soat'!$L:$L,'1.DC_Ra soat'!$F:$F,'1.PL (VND) '!BB$4,'1.DC_Ra soat'!$I:$I,'1.PL (VND) '!$C24) -> 0 | BC24: =SUMIFS('1.DC_Ra soat'!$L:$L,'1.DC_Ra soat'!$F:$F,'1.PL (VND) '!BC$4,'1.DC_Ra soat'!$H:$H,'1.PL (VND) '!$C24)-SUMIFS('1.DC_Ra soat'!$L:$L,'1.DC_Ra soat'!$F:$F,'1.PL (VND) '!BC$4,'1.DC_Ra soat'!$I:$I,'1.PL (VND) '!$C24) -> 0 | BD24: =SUMIFS('1.DC_Ra soat'!$L:$L,'1.DC_Ra soat'!$F:$F,'1.PL (VND) '!BD$4,'1.DC_Ra soat'!$H:$H,'1.PL (VND) '!$C24)-SUMIFS('1.DC_Ra soat'!$L:$L,'1.DC_Ra soat'!$F:$F,'1.PL (VND) '!BD$4,'1.DC_Ra soat'!$I:$I,'1.PL (VND) '!$C24) -> 0 | BE24: =SUMIFS('1.DC_Ra soat'!$L:$L,'1.DC_Ra soat'!$F:$F,'1.PL (VND) '!BE$4,'1.DC_Ra soat'!$H:$H,'1.PL (VND) '!$C24)-SUMIFS('1.DC_Ra soat'!$L:$L,'1.DC_Ra soat'!$F:$F,'1.PL (VND) '!BE$4,'1.DC_Ra soat'!$I:$I,'1.PL (VND) '!$C24) -> 0 | BG24: =SUMIFS('1.DC_Ra soat'!$L:$L,'1.DC_Ra soat'!$F:$F,'1.PL (VND) '!BG$4,'1.DC_Ra soat'!$H:$H,'1.PL (VND) '!$C24)-SUMIFS('1.DC_Ra soat'!$L:$L,'1.DC_Ra soat'!$F:$F,'1.PL (VND) '!BG$4,'1.DC_Ra soat'!$I:$I,'1.PL (VND) '!$C24) -> 0 | BH24: =SUMIFS('1.DC_Ra soat'!$L:$L,'1.DC_Ra soat'!$F:$F,'1.PL (VND) '!BH$4,'1.DC_Ra soat'!$H:$H,'1.PL (VND) '!$C24)-SUMIFS('1.DC_Ra soat'!$L:$L,'1.DC_Ra soat'!$F:$F,'1.PL (VND) '!BH$4,'1.DC_Ra soat'!$I:$I,'1.PL (VND) '!$C24) -> 0 | BI24: =SUMIFS('1.DC_Ra soat'!$L:$L,'1.DC_Ra soat'!$F:$F,'1.PL (VND) '!BI$4,'1.DC_Ra soat'!$H:$H,'1.PL (VND) '!$C24)-SUMIFS('1.DC_Ra soat'!$L:$L,'1.DC_Ra soat'!$F:$F,'1.PL (VND) '!BI$4,'1.DC_Ra soat'!$I:$I,'1.PL (VND) '!$C24) -> 0 | BJ24: =SUMIFS('1.DC_Ra soat'!$L:$L,'1.DC_Ra soat'!$F:$F,'1.PL (VND) '!BJ$4,'1.DC_Ra soat'!$H:$H,'1.PL (VND) '!$C24)-SUMIFS('1.DC_Ra soat'!$L:$L,'1.DC_Ra soat'!$F:$F,'1.PL (VND) '!BJ$4,'1.DC_Ra soat'!$I:$I,'1.PL (VND) '!$C24) -> 0 | BL24: =D24+AH24 -> 15975487 | BM24: =E24+AI24 -> 34176152 | BN24: =F24+AJ24 -> 28102224 | BO24: =G24+AK24 -> 1.8501272e+09 | BQ24: =I24+AM24 -> 0 | BR24: =J24+AN24 -> 0 | BS24: =K24+AO24 -> 0 | BT24: =L24+AP24 -> 6.1485586e+09 | BV24: =N24+AR24 -> 2614712 | BW24: =O24+AS24 -> 10791492 | BX24: =P24+AT24 -> 7286847 | BY24: =Q24+AU24 -> 0 | CA24: =S24+AW24 -> 0 | CB24: =T24+AX24 -> 3412279 | CC24: =U24+AY24 -> 0 | CD24: =V24+AZ24 -> 2271321 | CF24: =X24+BB24 -> 0 | CG24: =Y24+BC24 -> 0 | CH24: =Z24+BD24 -> 0 | CI24: =AA24+BE24 -> 0 | CK24: =AC24+BG24 -> 0 | CL24: =AD24+BH24 -> 0 | CM24: =AE24+BI24 -> 0 | CN24: =AF24+BJ24 -> 0 | CP24: =SUMIF($BL$6:$CD$6,CP$6,$BL24:$CD24) -> 18590199 | CQ24: =SUMIF($BL$6:$CD$6,CQ$6,$BL24:$CD24) -> 48379923 | CR24: =SUMIF($BL$6:$CD$6,CR$6,$BL24:$CD24) -> 35389071 | CS24: =SUMIF($BL$6:$CD$6,CS$6,$BL24:$CD24) -> 8000957108 | CU24: =-SUMIFS('1.DC_Ra soat'!$L:$L,'1.DC_Ra soat'!$F:$F,'1.PL (VND) '!CU$4,'1.DC_Ra soat'!$H:$H,'1.PL (VND) '!$C24)+SUMIFS('1.DC_Ra soat'!$L:$L,'1.DC_Ra soat'!$F:$F,'1.PL (VND) '!CU$4,'1.DC_Ra soat'!$I:$I,'1.PL (VND) '!$C24) -> 0 | CV24: =-SUMIFS('1.DC_Ra soat'!$L:$L,'1.DC_Ra soat'!$F:$F,'1.PL (VND) '!CV$4,'1.DC_Ra soat'!$H:$H,'1.PL (VND) '!$C24)+SUMIFS('1.DC_Ra soat'!$L:$L,'1.DC_Ra soat'!$F:$F,'1.PL (VND) '!CV$4,'1.DC_Ra soat'!$I:$I,'1.PL (VND) '!$C24) -> 0 | CW24: =-SUMIFS('1.DC_Ra soat'!$L:$L,'1.DC_Ra soat'!$F:$F,'1.PL (VND) '!CW$4,'1.DC_Ra soat'!$H:$H,'1.PL (VND) '!$C24)+SUMIFS('1.DC_Ra soat'!$L:$L,'1.DC_Ra soat'!$F:$F,'1.PL (VND) '!CW$4,'1.DC_Ra soat'!$I:$I,'1.PL (VND) '!$C24) -> 0 | CX24: =-SUMIFS('1.DC_Ra soat'!$L:$L,'1.DC_Ra soat'!$F:$F,'1.PL (VND) '!CX$4,'1.DC_Ra soat'!$H:$H,'1.PL (VND) '!$C24)+SUMIFS('1.DC_Ra soat'!$L:$L,'1.DC_Ra soat'!$F:$F,'1.PL (VND) '!CX$4,'1.DC_Ra soat'!$I:$I,'1.PL (VND) '!$C24) -> 0 | CZ24: =CP24+CU24 -> 18590199 | DA24: =CQ24+CV24 -> 48379923 | DB24: =CR24+CW24 -> 35389071 | DC24: =CS24+CX24 -> 8000957108
B25: 16. Chi phí thuế thu nhập doanh nghiệp hoãn lại | C25: 52 | E25: 0 | F25: 0 | AD25: 0 | AE25: 0 | AH25: =SUMIFS('1.DC_Ra soat'!$L:$L,'1.DC_Ra soat'!$F:$F,'1.PL (VND) '!AH$4,'1.DC_Ra soat'!$H:$H,'1.PL (VND) '!$C25)-SUMIFS('1.DC_Ra soat'!$L:$L,'1.DC_Ra soat'!$F:$F,'1.PL (VND) '!AH$4,'1.DC_Ra soat'!$I:$I,'1.PL (VND) '!$C25) -> 0 | AI25: =SUMIFS('1.DC_Ra soat'!$L:$L,'1.DC_Ra soat'!$F:$F,'1.PL (VND) '!AI$4,'1.DC_Ra soat'!$H:$H,'1.PL (VND) '!$C25)-SUMIFS('1.DC_Ra soat'!$L:$L,'1.DC_Ra soat'!$F:$F,'1.PL (VND) '!AI$4,'1.DC_Ra soat'!$I:$I,'1.PL (VND) '!$C25) -> 0 | AJ25: =SUMIFS('1.DC_Ra soat'!$L:$L,'1.DC_Ra soat'!$F:$F,'1.PL (VND) '!AJ$4,'1.DC_Ra soat'!$H:$H,'1.PL (VND) '!$C25)-SUMIFS('1.DC_Ra soat'!$L:$L,'1.DC_Ra soat'!$F:$F,'1.PL (VND) '!AJ$4,'1.DC_Ra soat'!$I:$I,'1.PL (VND) '!$C25) -> 0 | AK25: =SUMIFS('1.DC_Ra soat'!$L:$L,'1.DC_Ra soat'!$F:$F,'1.PL (VND) '!AK$4,'1.DC_Ra soat'!$H:$H,'1.PL (VND) '!$C25)-SUMIFS('1.DC_Ra soat'!$L:$L,'1.DC_Ra soat'!$F:$F,'1.PL (VND) '!AK$4,'1.DC_Ra soat'!$I:$I,'1.PL (VND) '!$C25) -> 0 | AM25: =SUMIFS('1.DC_Ra soat'!$L:$L,'1.DC_Ra soat'!$F:$F,'1.PL (VND) '!AM$4,'1.DC_Ra soat'!$H:$H,'1.PL (VND) '!$C25)-SUMIFS('1.DC_Ra soat'!$L:$L,'1.DC_Ra soat'!$F:$F,'1.PL (VND) '!AM$4,'1.DC_Ra soat'!$I:$I,'1.PL (VND) '!$C25) -> 0 | AN25: =SUMIFS('1.DC_Ra soat'!$L:$L,'1.DC_Ra soat'!$F:$F,'1.PL (VND) '!AN$4,'1.DC_Ra soat'!$H:$H,'1.PL (VND) '!$C25)-SUMIFS('1.DC_Ra soat'!$L:$L,'1.DC_Ra soat'!$F:$F,'1.PL (VND) '!AN$4,'1.DC_Ra soat'!$I:$I,'1.PL (VND) '!$C25) -> 0 | AO25: =SUMIFS('1.DC_Ra soat'!$L:$L,'1.DC_Ra soat'!$F:$F,'1.PL (VND) '!AO$4,'1.DC_Ra soat'!$H:$H,'1.PL (VND) '!$C25)-SUMIFS('1.DC_Ra soat'!$L:$L,'1.DC_Ra soat'!$F:$F,'1.PL (VND) '!AO$4,'1.DC_Ra soat'!$I:$I,'1.PL (VND) '!$C25) -> 0 | AP25: =SUMIFS('1.DC_Ra soat'!$L:$L,'1.DC_Ra soat'!$F:$F,'1.PL (VND) '!AP$4,'1.DC_Ra soat'!$H:$H,'1.PL (VND) '!$C25)-SUMIFS('1.DC_Ra soat'!$L:$L,'1.DC_Ra soat'!$F:$F,'1.PL (VND) '!AP$4,'1.DC_Ra soat'!$I:$I,'1.PL (VND) '!$C25) -> 0 | AR25: =SUMIFS('1.DC_Ra soat'!$L:$L,'1.DC_Ra soat'!$F:$F,'1.PL (VND) '!AR$4,'1.DC_Ra soat'!$H:$H,'1.PL (VND) '!$C25)-SUMIFS('1.DC_Ra soat'!$L:$L,'1.DC_Ra soat'!$F:$F,'1.PL (VND) '!AR$4,'1.DC_Ra soat'!$I:$I,'1.PL (VND) '!$C25) -> 0 | AS25: =SUMIFS('1.DC_Ra soat'!$L:$L,'1.DC_Ra soat'!$F:$F,'1.PL (VND) '!AS$4,'1.DC_Ra soat'!$H:$H,'1.PL (VND) '!$C25)-SUMIFS('1.DC_Ra soat'!$L:$L,'1.DC_Ra soat'!$F:$F,'1.PL (VND) '!AS$4,'1.DC_Ra soat'!$I:$I,'1.PL (VND) '!$C25) -> 0 | AT25: =SUMIFS('1.DC_Ra soat'!$L:$L,'1.DC_Ra soat'!$F:$F,'1.PL (VND) '!AT$4,'1.DC_Ra soat'!$H:$H,'1.PL (VND) '!$C25)-SUMIFS('1.DC_Ra soat'!$L:$L,'1.DC_Ra soat'!$F:$F,'1.PL (VND) '!AT$4,'1.DC_Ra soat'!$I:$I,'1.PL (VND) '!$C25) -> 0 | AU25: =SUMIFS('1.DC_Ra soat'!$L:$L,'1.DC_Ra soat'!$F:$F,'1.PL (VND) '!AU$4,'1.DC_Ra soat'!$H:$H,'1.PL (VND) '!$C25)-SUMIFS('1.DC_Ra soat'!$L:$L,'1.DC_Ra soat'!$F:$F,'1.PL (VND) '!AU$4,'1.DC_Ra soat'!$I:$I,'1.PL (VND) '!$C25) -> 0 | AW25: =SUMIFS('1.DC_Ra soat'!$L:$L,'1.DC_Ra soat'!$F:$F,'1.PL (VND) '!AW$4,'1.DC_Ra soat'!$H:$H,'1.PL (VND) '!$C25)-SUMIFS('1.DC_Ra soat'!$L:$L,'1.DC_Ra soat'!$F:$F,'1.PL (VND) '!AW$4,'1.DC_Ra soat'!$I:$I,'1.PL (VND) '!$C25) -> 0 | AX25: =SUMIFS('1.DC_Ra soat'!$L:$L,'1.DC_Ra soat'!$F:$F,'1.PL (VND) '!AX$4,'1.DC_Ra soat'!$H:$H,'1.PL (VND) '!$C25)-SUMIFS('1.DC_Ra soat'!$L:$L,'1.DC_Ra soat'!$F:$F,'1.PL (VND) '!AX$4,'1.DC_Ra soat'!$I:$I,'1.PL (VND) '!$C25) -> 0 | AY25: =SUMIFS('1.DC_Ra soat'!$L:$L,'1.DC_Ra soat'!$F:$F,'1.PL (VND) '!AY$4,'1.DC_Ra soat'!$H:$H,'1.PL (VND) '!$C25)-SUMIFS('1.DC_Ra soat'!$L:$L,'1.DC_Ra soat'!$F:$F,'1.PL (VND) '!AY$4,'1.DC_Ra soat'!$I:$I,'1.PL (VND) '!$C25) -> 0 | AZ25: =SUMIFS('1.DC_Ra soat'!$L:$L,'1.DC_Ra soat'!$F:$F,'1.PL (VND) '!AZ$4,'1.DC_Ra soat'!$H:$H,'1.PL (VND) '!$C25)-SUMIFS('1.DC_Ra soat'!$L:$L,'1.DC_Ra soat'!$F:$F,'1.PL (VND) '!AZ$4,'1.DC_Ra soat'!$I:$I,'1.PL (VND) '!$C25) -> 0 | BB25: =SUMIFS('1.DC_Ra soat'!$L:$L,'1.DC_Ra soat'!$F:$F,'1.PL (VND) '!BB$4,'1.DC_Ra soat'!$H:$H,'1.PL (VND) '!$C25)-SUMIFS('1.DC_Ra soat'!$L:$L,'1.DC_Ra soat'!$F:$F,'1.PL (VND) '!BB$4,'1.DC_Ra soat'!$I:$I,'1.PL (VND) '!$C25) -> 0 | BC25: =SUMIFS('1.DC_Ra soat'!$L:$L,'1.DC_Ra soat'!$F:$F,'1.PL (VND) '!BC$4,'1.DC_Ra soat'!$H:$H,'1.PL (VND) '!$C25)-SUMIFS('1.DC_Ra soat'!$L:$L,'1.DC_Ra soat'!$F:$F,'1.PL (VND) '!BC$4,'1.DC_Ra soat'!$I:$I,'1.PL (VND) '!$C25) -> 0 | BD25: =SUMIFS('1.DC_Ra soat'!$L:$L,'1.DC_Ra soat'!$F:$F,'1.PL (VND) '!BD$4,'1.DC_Ra soat'!$H:$H,'1.PL (VND) '!$C25)-SUMIFS('1.DC_Ra soat'!$L:$L,'1.DC_Ra soat'!$F:$F,'1.PL (VND) '!BD$4,'1.DC_Ra soat'!$I:$I,'1.PL (VND) '!$C25) -> 0 | BE25: =SUMIFS('1.DC_Ra soat'!$L:$L,'1.DC_Ra soat'!$F:$F,'1.PL (VND) '!BE$4,'1.DC_Ra soat'!$H:$H,'1.PL (VND) '!$C25)-SUMIFS('1.DC_Ra soat'!$L:$L,'1.DC_Ra soat'!$F:$F,'1.PL (VND) '!BE$4,'1.DC_Ra soat'!$I:$I,'1.PL (VND) '!$C25) -> 0 | BG25: =SUMIFS('1.DC_Ra soat'!$L:$L,'1.DC_Ra soat'!$F:$F,'1.PL (VND) '!BG$4,'1.DC_Ra soat'!$H:$H,'1.PL (VND) '!$C25)-SUMIFS('1.DC_Ra soat'!$L:$L,'1.DC_Ra soat'!$F:$F,'1.PL (VND) '!BG$4,'1.DC_Ra soat'!$I:$I,'1.PL (VND) '!$C25) -> 0 | BH25: =SUMIFS('1.DC_Ra soat'!$L:$L,'1.DC_Ra soat'!$F:$F,'1.PL (VND) '!BH$4,'1.DC_Ra soat'!$H:$H,'1.PL (VND) '!$C25)-SUMIFS('1.DC_Ra soat'!$L:$L,'1.DC_Ra soat'!$F:$F,'1.PL (VND) '!BH$4,'1.DC_Ra soat'!$I:$I,'1.PL (VND) '!$C25) -> 0 | BI25: =SUMIFS('1.DC_Ra soat'!$L:$L,'1.DC_Ra soat'!$F:$F,'1.PL (VND) '!BI$4,'1.DC_Ra soat'!$H:$H,'1.PL (VND) '!$C25)-SUMIFS('1.DC_Ra soat'!$L:$L,'1.DC_Ra soat'!$F:$F,'1.PL (VND) '!BI$4,'1.DC_Ra soat'!$I:$I,'1.PL (VND) '!$C25) -> 0 | BJ25: =SUMIFS('1.DC_Ra soat'!$L:$L,'1.DC_Ra soat'!$F:$F,'1.PL (VND) '!BJ$4,'1.DC_Ra soat'!$H:$H,'1.PL (VND) '!$C25)-SUMIFS('1.DC_Ra soat'!$L:$L,'1.DC_Ra soat'!$F:$F,'1.PL (VND) '!BJ$4,'1.DC_Ra soat'!$I:$I,'1.PL (VND) '!$C25) -> 0 | BL25: =D25+AH25 -> 0 | BM25: =E25+AI25 -> 0 | BN25: =F25+AJ25 -> 0 | BO25: =G25+AK25 -> 0 | BQ25: =I25+AM25 -> 0 | BR25: =J25+AN25 -> 0 | BS25: =K25+AO25 -> 0 | BT25: =L25+AP25 -> 0 | BV25: =N25+AR25 -> 0 | BW25: =O25+AS25 -> 0 | BX25: =P25+AT25 -> 0 | BY25: =Q25+AU25 -> 0 | CA25: =S25+AW25 -> 0 | CB25: =T25+AX25 -> 0 | CC25: =U25+AY25 -> 0 | CD25: =V25+AZ25 -> 0 | CF25: =X25+BB25 -> 0 | CG25: =Y25+BC25 -> 0 | CH25: =Z25+BD25 -> 0 | CI25: =AA25+BE25 -> 0 | CK25: =AC25+BG25 -> 0 | CL25: =AD25+BH25 -> 0 | CM25: =AE25+BI25 -> 0 | CN25: =AF25+BJ25 -> 0 | CP25: =SUMIF($BL$6:$CD$6,CP$6,$BL25:$CD25) -> 0 | CQ25: =SUMIF($BL$6:$CD$6,CQ$6,$BL25:$CD25) -> 0 | CR25: =SUMIF($BL$6:$CD$6,CR$6,$BL25:$CD25) -> 0 | CS25: =SUMIF($BL$6:$CD$6,CS$6,$BL25:$CD25) -> 0 | CU25: =-SUMIFS('1.DC_Ra soat'!$L:$L,'1.DC_Ra soat'!$F:$F,'1.PL (VND) '!CU$4,'1.DC_Ra soat'!$H:$H,'1.PL (VND) '!$C25)+SUMIFS('1.DC_Ra soat'!$L:$L,'1.DC_Ra soat'!$F:$F,'1.PL (VND) '!CU$4,'1.DC_Ra soat'!$I:$I,'1.PL (VND) '!$C25) -> 0 | CV25: =-SUMIFS('1.DC_Ra soat'!$L:$L,'1.DC_Ra soat'!$F:$F,'1.PL (VND) '!CV$4,'1.DC_Ra soat'!$H:$H,'1.PL (VND) '!$C25)+SUMIFS('1.DC_Ra soat'!$L:$L,'1.DC_Ra soat'!$F:$F,'1.PL (VND) '!CV$4,'1.DC_Ra soat'!$I:$I,'1.PL (VND) '!$C25) -> 0 | CW25: =-SUMIFS('1.DC_Ra soat'!$L:$L,'1.DC_Ra soat'!$F:$F,'1.PL (VND) '!CW$4,'1.DC_Ra soat'!$H:$H,'1.PL (VND) '!$C25)+SUMIFS('1.DC_Ra soat'!$L:$L,'1.DC_Ra soat'!$F:$F,'1.PL (VND) '!CW$4,'1.DC_Ra soat'!$I:$I,'1.PL (VND) '!$C25) -> 0 | CX25: =-SUMIFS('1.DC_Ra soat'!$L:$L,'1.DC_Ra soat'!$F:$F,'1.PL (VND) '!CX$4,'1.DC_Ra soat'!$H:$H,'1.PL (VND) '!$C25)+SUMIFS('1.DC_Ra soat'!$L:$L,'1.DC_Ra soat'!$F:$F,'1.PL (VND) '!CX$4,'1.DC_Ra soat'!$I:$I,'1.PL (VND) '!$C25) -> 0 | CZ25: =CP25+CU25 -> 0 | DA25: =CQ25+CV25 -> 0 | DB25: =CR25+CW25 -> 0 | DC25: =CS25+CX25 -> 0
B26: 17. Lợi nhuận sau thuế thu nhập doanh nghiệp | C26: 60 | D26: =D23-D24-D25 -> 63901948 | E26: =E23-E24-E25 -> 136704607 | F26: =F23-F24-F25 -> 810269176 | G26: =G23-G24-G25 -> 7.4005089e+09 | I26: =I23-I24-I25 -> -1009698 | J26: =J23-J24-J25 -> 209281598 | K26: =K23-K24-K25 -> -5280865421 | L26: =L23-L24-L25 -> 2.4353634e+10 | N26: =N23-N24-N25 -> 16061803 | O26: =O23-O24-O25 -> 66290594 | P26: =P23-P24-P25 -> 29147390 | Q26: =Q23-Q24-Q25 -> -3469627273 | S26: =S23-S24-S25 -> -305983609 | T26: =T23-T24-T25 -> 20961141 | U26: =U23-U24-U25 -> -1936838870 | V26: =V23-V24-V25 -> -1979182593 | X26: =X23-X24-X25 -> 0 | Y26: =Y23-Y24-Y25 -> 0 | Z26: =Z23-Z24-Z25 -> 0 | AA26: =AA23-AA24-AA25 -> 0 | AC26: =AC23-AC24-AC25 -> 0 | AD26: =AD23-AD24-AD25 -> 0 | AE26: =AE23-AE24-AE25 -> 0 | AF26: =AF23-AF24-AF25 -> 0 | AH26: =AH23-AH24-AH25 -> 0 | AI26: =AI23-AI24-AI25 -> 0 | AJ26: =AJ23-AJ24-AJ25 -> -10749717626 | AK26: =AK23-AK24-AK25 -> -4623603888 | AM26: =AM23-AM24-AM25 -> 0 | AN26: =AN23-AN24-AN25 -> 0 | AO26: =AO23-AO24-AO25 -> -741540549 | AP26: =AP23-AP24-AP25 -> 0 | AR26: =AR23-AR24-AR25 -> 0 | AS26: =AS23-AS24-AS25 -> 0 | AT26: =AT23-AT24-AT25 -> 0 | AU26: =AU23-AU24-AU25 -> -4950000000 | AW26: =AW23-AW24-AW25 -> 0 | AX26: =AX23-AX24-AX25 -> 0 | AY26: =AY23-AY24-AY25 -> -1262355349 | AZ26: =AZ23-AZ24-AZ25 -> -5000000000 | BB26: =BB23-BB24-BB25 -> 0 | BC26: =BC23-BC24-BC25 -> 0 | BD26: =BD23-BD24-BD25 -> 0 | BE26: =BE23-BE24-BE25 -> 0 | BG26: =BG23-BG24-BG25 -> 0 | BH26: =BH23-BH24-BH25 -> 0 | BI26: =BI23-BI24-BI25 -> 0 | BL26: =D26+AH26 -> 63901948 | BM26: =E26+AI26 -> 136704607 | BN26: =F26+AJ26 -> -9939448450 | BO26: =G26+AK26 -> 2.776905e+09 | BQ26: =I26+AM26 -> -1009698 | BR26: =J26+AN26 -> 209281598 | BS26: =K26+AO26 -> -6022405970 | BT26: =L26+AP26 -> 2.4353634e+10 | BV26: =N26+AR26 -> 16061803 | BW26: =O26+AS26 -> 66290594 | BX26: =P26+AT26 -> 29147390 | BY26: =Q26+AU26 -> -8419627273 | CA26: =S26+AW26 -> -305983609 | CB26: =T26+AX26 -> 20961141 | CC26: =U26+AY26 -> -3199194219 | CD26: =V26+AZ26 -> -6979182593 | CF26: =X26+BB26 -> 0 | CG26: =Y26+BC26 -> 0 | CH26: =Z26+BD26 -> 0 | CI26: =AA26+BE26 -> 0 | CK26: =AC26+BG26 -> 0 | CL26: =AD26+BH26 -> 0 | CM26: =AE26+BI26 -> 0 | CN26: =AF26+BJ26 -> 0 | CP26: =SUMIF($BL$6:$CD$6,CP$6,$BL26:$CD26) -> -227029556 | CQ26: =SUMIF($BL$6:$CD$6,CQ$6,$BL26:$CD26) -> 433237940 | CR26: =SUMIF($BL$6:$CD$6,CR$6,$BL26:$CD26) -> -19131901249 | CS26: =SUMIF($BL$6:$CD$6,CS$6,$BL26:$CD26) -> 11731729394 | CU26: =CU23-CU24-CU25 -> 0 | CV26: =CV23-CV24-CV25 -> 0 | CW26: =CW23-CW24-CW25 -> 0 | CX26: =CX23-CX24-CX25 -> 0 | CZ26: =CP26+CU26 -> -227029556 | DA26: =CQ26+CV26 -> 433237940 | DB26: =CR26+CW26 -> -19131901249 | DC26: =CS26+CX26 -> 11731729394
B27: 18. Lợi nhuận sau thuế của Công ty mẹ | I27: 0 | L27: 0 | BL27: =D27+AH27 -> 0 | BM27: =E27+AI27 -> 0 | BN27: =F27+AJ27 -> 0 | BO27: =G27+AK27 -> 0 | BQ27: =I27+AM27 -> 0 | BR27: =J27+AN27 -> 0 | BS27: =K27+AO27 -> 0 | BT27: =L27+AP27 -> 0 | BV27: =N27+AR27 -> 0 | BW27: =O27+AS27 -> 0 | BX27: =P27+AT27 -> 0 | BY27: =Q27+AU27 -> 0 | CA27: =S27+AW27 -> 0 | CB27: =T27+AX27 -> 0 | CC27: =U27+AY27 -> 0 | CD27: =V27+AZ27 -> 0 | CF27: =X27+BB27 -> 0 | CG27: =Y27+BC27 -> 0 | CH27: =Z27+BD27 -> 0 | CI27: =AA27+BE27 -> 0 | CK27: =AC27+BG27 -> 0 | CL27: =AD27+BH27 -> 0 | CM27: =AE27+BI27 -> 0 | CN27: =AF27+BJ27 -> 0 | CP27: =AH27+BL27 -> 0 | CQ27: =AI27+BM27 -> 0 | CR27: =AJ27+BN27 -> 0 | CS27: =AK27+BO27 -> 0 | CU27: =AM27+BQ27 -> 0 | CV27: =AN27+BR27 -> 0 | CW27: =AO27+BS27 -> 0 | CX27: =AP27+BT27 -> 0 | CZ27: =AR27+BV27 -> 0 | DA27: =AS27+BW27 -> 0 | DB27: =AT27+BX27 -> 0 | DC27: =AU27+BY27 -> 0
B28: 19. Lợi nhuận sau thuế của Cổ đông không kiểm soát | I28: 0 | BL28: =D28+AH28 -> 0 | BM28: =E28+AI28 -> 0 | BN28: =F28+AJ28 -> 0 | BO28: =G28+AK28 -> 0 | BQ28: =I28+AM28 -> 0 | BR28: =J28+AN28 -> 0 | BS28: =K28+AO28 -> 0 | BT28: =L28+AP28 -> 0 | BV28: =N28+AR28 -> 0 | BW28: =O28+AS28 -> 0 | BX28: =P28+AT28 -> 0 | BY28: =Q28+AU28 -> 0 | CA28: =S28+AW28 -> 0 | CB28: =T28+AX28 -> 0 | CC28: =U28+AY28 -> 0 | CD28: =V28+AZ28 -> 0 | CF28: =X28+BB28 -> 0 | CG28: =Y28+BC28 -> 0 | CH28: =Z28+BD28 -> 0 | CI28: =AA28+BE28 -> 0 | CK28: =AC28+BG28 -> 0 | CL28: =AD28+BH28 -> 0 | CM28: =AE28+BI28 -> 0 | CN28: =AF28+BJ28 -> 0 | CP28: =AH28+BL28 -> 0 | CQ28: =AI28+BM28 -> 0 | CR28: =AJ28+BN28 -> 0 | CS28: =AK28+BO28 -> 0 | CU28: =AM28+BQ28 -> 0 | CV28: =AN28+BR28 -> 0 | CW28: =AO28+BS28 -> 0 | CX28: =AP28+BT28 -> 0 | CZ28: =AR28+BV28 -> 0 | DA28: =AS28+BW28 -> 0 | DB28: =AT28+BX28 -> 0 | DC28: =AU28+BY28 -> 0
B29: Biên LNG | D29: =D12/D10 -> 0.052257379 | E29: =E12/E10 -> 0.046407261 | F29: =F12/F10 -> 0.03898035 | G29: =G12/G10 -> 0.075637772 | I29: =I12/I10 -> #DIV/0! | J29: =J12/J10 -> 0.057531661 | K29: =K12/K10 -> -0.0090381565 | L29: =L12/L10 -> 0.44205277 | N29: =N12/N10 -> 0.096314461 | O29: =O12/O10 -> 0.13427388 | P29: =P12/P10 -> 0.060256071 | Q29: =Q12/Q10 -> 0.0076508529 | S29: =S12/S10 -> 0.017722836 | T29: =T12/T10 -> 0.04781463 | U29: =U12/U10 -> 0.017378004 | V29: =V12/V10 -> 0.016340306 | X29: =X12/X10 -> #DIV/0! | Y29: =Y12/Y10 -> #DIV/0! | Z29: =Z12/Z10 -> #DIV/0! | AA29: =AA12/AA10 -> #DIV/0! | AC29: =AC12/AC10 -> #DIV/0! | AD29: =AD12/AD10 -> #DIV/0! | AE29: =AE12/AE10 -> #DIV/0! | AF29: =AF12/AF10 -> #DIV/0! | BL29: =BL12/BL10 -> 0.052257379 | BM29: =BM12/BM10 -> 0.046407261 | BN29: =BN12/BN10 -> 0.026599682 | BO29: =BO12/BO10 -> 0.073205194 | BQ29: =BQ12/BQ10 -> #DIV/0! | BR29: =BR12/BR10 -> 0.057531661 | BS29: =BS12/BS10 -> -0.0090381565 | BT29: =BT12/BT10 -> 0.44205277 | BV29: =BV12/BV10 -> 0.096314461 | BW29: =BW12/BW10 -> 0.13427388 | BX29: =BX12/BX10 -> 0.060256071 | BY29: =BY12/BY10 -> 0.0076508529 | CA29: =CA12/CA10 -> 0.017722836 | CB29: =CB12/CB10 -> 0.04781463 | CC29: =CC12/CC10 -> 0.017378004 | CD29: =CD12/CD10 -> 0.016340306 | CP29: =CP12/CP10 -> 0.057663286 | CQ29: =CQ12/CQ10 -> 0.057070206 | CR29: =CR12/CR10 -> 0.025351384 | CS29: =CS12/CS10 -> 0.10757616 | CU29: =CU12/CU10 -> #DIV/0! | CV29: =CV12/CV10 -> #DIV/0! | CW29: =CW12/CW10 -> 0 | CX29: =CX12/CX10 -> 0 | CZ29: =CZ12/CZ10 -> 0.057663286 | DA29: =DA12/DA10 -> 0.057070206 | DB29: =DB12/DB10 -> 0.030237705
B30: ROS | D30: =D26/D10 -> 0.00023423136 | E30: =E26/E10 -> 0.0003784463 | F30: =F26/F10 -> 0.0019110509 | G30: =G26/G10 -> 0.016768117 | I30: =I26/I10 -> #DIV/0! | J30: =J26/J10 -> 0.0050474866 | K30: =K26/K10 -> -0.075644488 | L30: =L26/L10 -> 0.32611196 | N30: =N26/N10 -> 0.00026972614 | O30: =O26/O10 -> 0.001207098 | P30: =P26/P10 -> 0.00045536508 | Q30: =Q26/Q10 -> -0.058997506 | S30: =S26/S10 -> -0.014781115 | T30: =T26/T10 -> 0.00047641885 | U30: =U26/U10 -> -0.042579956 | V30: =V26/V10 -> -0.045920385 | X30: =X26/X10 -> #DIV/0! | Y30: =Y26/Y10 -> #DIV/0! | Z30: =Z26/Z10 -> #DIV/0! | AA30: =AA26/AA10 -> #DIV/0! | AC30: =AC26/AC10 -> #DIV/0! | AD30: =AD26/AD10 -> #DIV/0! | AE30: =AE26/AE10 -> #DIV/0! | AF30: =AF26/AF10 -> #DIV/0! | BL30: =BL26/BL10 -> 0.00023423136 | BM30: =BM26/BM10 -> 0.0003784463 | BN30: =BN26/BN10 -> -0.023442571 | BO30: =BO26/BO10 -> 0.0062919277 | BQ30: =BQ26/BQ10 -> #DIV/0! | BR30: =BR26/BR10 -> 0.0050474866 | BS30: =BS26/BS10 -> -0.086266507 | BT30: =BT26/BT10 -> 0.32611196 | BV30: =BV26/BV10 -> 0.00026972614 | BW30: =BW26/BW10 -> 0.001207098 | BX30: =BX26/BX10 -> 0.00045536508 | BY30: =BY26/BY10 -> -0.14316725 | CA30: =CA26/CA10 -> -0.014781115 | CB30: =CB26/CB10 -> 0.00047641885 | CC30: =CC26/CC10 -> -0.070331896 | CD30: =CD26/CD10 -> -0.16192885 | CP30: =CP26/CP10 -> -0.00064302472 | CQ30: =CQ26/CQ10 -> 0.00086370672 | CR30: =CR26/CR10 -> -0.031712139 | CS30: =CS26/CS10 -> 0.018985443 | CU30: =CU26/CU10 -> #DIV/0! | CV30: =CV26/CV10 -> #DIV/0! | CW30: =CW26/CW10 -> 0 | CX30: =CX13/CX11 -> 0 | CZ30: =CZ26/CZ10 -> -0.00064302472 | DA30: =DA26/DA10 -> 0.00086370672 | DB30: =DB26/DB10 -> -0.037824456

Sheet 1.BS (VND)
C3: BẢNG CÂN ĐỐI KẾ TOÁN | G3: Trước điều chỉnh | K3: Trước điều chỉnh | P3: Trước điều chỉnh | U3: Trước điều chỉnh | Z3: Trước điều chỉnh | AE3: Trước điều chỉnh | AK3: Điều chỉnh | AP3: Điều chỉnh | AU3: Điều chỉnh | AY3: Điều chỉnh | BD3: Điều chỉnh | BJ3: Điều chỉnh | BO3: Sau điều chỉnh | BT3: Sau điều chỉnh | BY3: Sau điều chỉnh | CN3: Sau điều chỉnh | CS3: Sau điều chỉnh | CX3: Điều chỉnh Nội bộ | DC3: Sau điều chỉnh nộ bộ
AI4: =$AI$5&$AK$3&AI6 -> 1.DV Quang PhátĐiều chỉnh 2020 | AJ4: =$AI$5&AJ6 -> 1.DV Quang Phát2021 | AK4: =$AI$5&$AK$3&AK6 -> 1.DV Quang PhátĐiều chỉnh 2022 | AL4: =$AI$5&$AK$3&AL6 -> 1.DV Quang PhátĐiều chỉnh 2023 | AN4: =$AN5&$AP$3&AN6 -> 2.BT Quang PhátĐiều chỉnh 2020 | AO4: =$AN5&$AP$3&AO6 -> 2.BT Quang PhátĐiều chỉnh 2021 | AP4: =$AN5&$AP$3&AP6 -> 2.BT Quang PhátĐiều chỉnh 2022 | AQ4: =$AN5&$AP$3&AQ6 -> 2.BT Quang PhátĐiều chỉnh 2023 | AS4: =$AS$5&$AU$3&AS6 -> 3.Kim Quang PhátĐiều chỉnh 2020 | AT4: =$AS$5&$AU$3&AT6 -> 3.Kim Quang PhátĐiều chỉnh 2021 | AU4: =$AS$5&$AU$3&AU6 -> 3.Kim Quang PhátĐiều chỉnh 2022 | AV4: =$AS$5&$AU$3&AV6 -> 3.Kim Quang PhátĐiều chỉnh 2023 | AX4: =$AX$5&$AY$3&AX6 -> 4.Kim Mỹ LinhĐiều chỉnh 2020 | AY4: =$AX$5&$AY$3&AY6 -> 4.Kim Mỹ LinhĐiều chỉnh 2021 | AZ4: =$AX$5&$AY$3&AZ6 -> 4.Kim Mỹ LinhĐiều chỉnh 2022 | BA4: =$AX$5&$AY$3&BA6 -> 4.Kim Mỹ LinhĐiều chỉnh 2023 | BC4: =$BC$5&$BD$3&BC6 -> 5.Vạn XuânĐiều chỉnh 2020 | BD4: =$BC$5&$BD$3&BD6 -> 5.Vạn XuânĐiều chỉnh 2021 | BE4: =$BC$5&$BD$3&BE6 -> 5.Vạn XuânĐiều chỉnh 2022 | BF4: =$BC$5&$BD$3&BF6 -> 5.Vạn XuânĐiều chỉnh 2023 | BH4: =$BH5&$BJ$3&BH6 -> 6.Điều chỉnh 2020 | BI4: =$BH5&$BJ$3&BI6 -> 6.Điều chỉnh 2021 | BJ4: =$BH5&$BJ$3&BJ6 -> 6.Điều chỉnh 2022 | BK4: =$BH5&$BJ$3&BK6 -> 6.Điều chỉnh 2023
C5: Chỉ tiêu | D5: Mã số | E5: ='TH1'!G4 -> 1.DV Quang Phát | J5: ='TH1'!G5 -> 2.BT Quang Phát | O5: ='TH1'!G6 -> 3.Kim Quang Phát | T5: ='TH1'!G7 -> 4.Kim Mỹ Linh | Y5: ='TH1'!G8 -> 5.Vạn Xuân | AD5: ='TH1'!G9 -> 6. | AI5: ='TH1'!G4 -> 1.DV Quang Phát | AN5: ='TH1'!G5 -> 2.BT Quang Phát | AS5: ='TH1'!G6 -> 3.Kim Quang Phát | AX5: ='TH1'!G7 -> 4.Kim Mỹ Linh | BC5: ='TH1'!G8 -> 5.Vạn Xuân | BH5: ='TH1'!G9 -> 6. | BM5: =AI5 -> 1.DV Quang Phát | BR5: ='TH1'!G5 -> 2.BT Quang Phát | BW5: ='TH1'!G6 -> 3.Kim Quang Phát | CB5: ='TH1'!G7 -> 4.Kim Mỹ Linh | CG5: ='TH1'!G8 -> 5.Vạn Xuân | CL5: ='TH1'!G9 -> 6. | CQ5: Tổng | CV5: Tổng | DA5: Tổng
C6: 1000000000 | E6: 2020 | F6: 2021 | G6: 2022 | H6: 2023 | J6: 2020 | K6: 2021 | L6: 2022 | M6: 2023 | O6: 2020 | P6: 2021 | Q6: 2022 | R6: 2023 | T6: 2020 | U6: 2021 | V6: 2022 | W6: 2023 | Y6: 2020 | Z6: 2021 | AA6: 2022 | AB6: 2023 | AD6: 2020 | AE6: 2021 | AF6: 2022 | AG6: 2023 | AI6: 2020 | AJ6: 2021 | AK6: 2022 | AL6: 2023 | AN6: 2020 | AO6: 2021 | AP6: 2022 | AQ6: 2023 | AS6: 2020 | AT6: 2021 | AU6: 2022 | AV6: 2023 | AX6: 2020 | AY6: 2021 | AZ6: 2022 | BA6: 2023 | BC6: 2020 | BD6: 2021 | BE6: 2022 | BF6: 2023 | BH6: 2020 | BI6: 2021 | BJ6: 2022 | BK6: 2023 | BM6: 2020 | BN6: 2021 | BO6: 2022 | BP6: 2023 | BR6: 2020 | BS6: 2021 | BT6: 2022 | BU6: 2023 | BW6: 2020 | BX6: 2021 | BY6: 2022 | BZ6: 2023 | CB6: 2020 | CC6: 2021 | CD6: 2022 | CE6: 2023 | CG6: 2020 | CH6: 2021 | CI6: 2022 | CJ6: 2023 | CL6: 2020 | CM6: 2021 | CN6: 2022 | CO6: 2023 | CQ6: 2020 | CR6: 2021 | CS6: 2022 | CT6: 2023 | CV6: 2020 | CW6: 2021 | CX6: 2022 | CY6: 2023 | DA6: 2020 | DB6: 2021 | DC6: 2022 | DD6: 2023
A8: =IF(SUM(J8:AJ8)<>0,1,"hide") -> 1 | C8: A. TÀI SẢN NGẮN HẠN | D8: 100 | E8: =E9+E12+E16+E25+E28 -> 175345220135 | F8: =F9+F12+F16+F25+F28 -> 135753562121 | G8: =G9+G12+G16+G25+G28 -> 141180974615 | H8: =H9+H12+H16+H25+H28 -> 282122408949 | J8: =J9+J12+J16+J25+J28 -> 4059489151 | K8: =K9+K12+K16+K25+K28 -> 13701001543 | L8: =L9+L12+L16+L25+L28 -> 34984450561 | M8: =M9+M12+M16+M25+M28 -> 91016523059 | O8: =O9+O12+O16+O25+O28 -> 43575171571 | P8: =P9+P12+P16+P25+P28 -> 21116038273 | Q8: =Q9+Q12+Q16+Q25+Q28 -> 57369669881 | R8: =R9+R12+R16+R25+R28 -> 49668844116 | T8: =T9+T12+T16+T25+T28 -> 21489338773 | U8: =U9+U12+U16+U25+U28 -> 17609121050 | V8: =V9+V12+V16+V25+V28 -> 21098515573 | W8: =W9+W12+W16+W25+W28 -> 56370294152 | Y8: =Y9+Y12+Y16+Y25+Y28 -> 0 | Z8: =Z9+Z12+Z16+Z25+Z28 -> 0 | AA8: =AA9+AA12+AA16+AA25+AA28 -> 0 | AB8: =AB9+AB12+AB16+AB25+AB28 -> 0 | AD8: =AD9+AD12+AD16+AD25+AD28 -> 0 | AE8: =AE9+AE12+AE16+AE25+AE28 -> 0 | AF8: =AF9+AF12+AF16+AF25+AF28 -> 0 | AG8: =AG9+AG12+AG16+AG25+AG28 -> 0 | AI8: =AI9+AI12+AI16+AI25+AI28 -> 0 | AJ8: =AJ9+AJ12+AJ16+AJ25+AJ28 -> 0 | AK8: =AK9+AK12+AK16+AK25+AK28 -> 0 | AL8: =AL9+AL12+AL16+AL25+AL28 -> -3550000000 | AN8: =AN9+AN12+AN16+AN25+AN28 -> 0 | AO8: =AO9+AO12+AO16+AO25+AO28 -> 0 | AP8: =AP9+AP12+AP16+AP25+AP28 -> -741540549 | AQ8: =AQ9+AQ12+AQ16+AQ25+AQ28 -> 0 | AS8: =AS9+AS12+AS16+AS25+AS28 -> 0 | AT8: =AT9+AT12+AT16+AT25+AT28 -> 0 | AU8: =AU9+AU12+AU16+AU25+AU28 -> 0 | AV8: =AV9+AV12+AV16+AV25+AV28 -> -4950000000 | AX8: =AX9+AX12+AX16+AX25+AX28 -> 0 | AY8: =AY9+AY12+AY16+AY25+AY28 -> 0 | AZ8: =AZ9+AZ12+AZ16+AZ25+AZ28 -> 0 | BA8: =BA9+BA12+BA16+BA25+BA28 -> -5000000000 | BC8: =BC9+BC12+BC16+BC25+BC28 -> 0 | BD8: =BD9+BD12+BD16+BD25+BD28 -> 0 | BE8: =BE9+BE12+BE16+BE25+BE28 -> 0 | BF8: =BF9+BF12+BF16+BF25+BF28 -> 0 | BH8: =BH9+BH12+BH16+BH25+BH28 -> 0 | BI8: =BI9+BI12+BI16+BI25+BI28 -> 0 | BJ8: =BJ9+BJ12+BJ16+BJ25+BJ28 -> 0 | BK8: =BK9+BK12+BK16+BK25+BK28 -> 0 | BM8: =E8+AI8 -> 175345220135 | BN8: =F8+AJ8 -> 135753562121 | BO8: =G8+AK8 -> 141180974615 | BP8: =H8+AL8 -> 278572408949 | BR8: =J8+AN8 -> 4059489151 | BS8: =K8+AO8 -> 13701001543 | BT8: =L8+AP8 -> 34242910012 | BU8: =M8+AQ8 -> 91016523059 | BW8: =O8+AS8 -> 43575171571 | BX8: =P8+AT8 -> 21116038273 | BY8: =Q8+AU8 -> 57369669881 | BZ8: =R8+AV8 -> 44718844116 | CB8: =T8+AX8 -> 21489338773 | CC8: =U8+AY8 -> 17609121050 | CD8: =V8+AZ8 -> 21098515573 | CE8: =W8+BA8 -> 51370294152 | CG8: =Y8+BC8 -> 0 | CH8: =Z8+BD8 -> 0 | CI8: =AA8+BE8 -> 0 | CJ8: =AB8+BF8 -> 0 | CL8: =AD8+BH8 -> 0 | CM8: =AE8+BI8 -> 0 | CN8: =AF8+BJ8 -> 0 | CO8: =AG8+BK8 -> 0 | CQ8: =SUMIF('1.PL (VND) '!$BL$6:$CD$6,'1.PL (VND) '!CP$6,$BM8:$CE8) -> 244469219630 | CR8: =SUMIF('1.PL (VND) '!$BL$6:$CD$6,'1.PL (VND) '!CQ$6,$BM8:$CE8) -> 188179722987 | CS8: =SUMIF('1.PL (VND) '!$BL$6:$CD$6,'1.PL (VND) '!CR$6,$BM8:$CE8) -> 253892070081 | CT8: =SUMIF('1.PL (VND) '!$BL$6:$CD$6,'1.PL (VND) '!CS$6,$BM8:$CE8) -> 465678070276 | CV8: =CV9+CV12+CV16+CV25+CV28 -> 0 | CW8: =CW9+CW12+CW16+CW25+CW28 -> 0 | CX8: =CX9+CX12+CX16+CX25+CX28 -> 0 | CY8: =CY9+CY12+CY16+CY25+CY28 -> 0 | DA8: =CQ8+CV8 -> 244469219630 | DB8: =CR8+CW8 -> 188179722987 | DC8: =CS8+CX8 -> 253892070081 | DD8: =CT8+CY8 -> 465678070276
A9: =IF(SUM(J9:AJ9)<>0,1,"hide") -> 1 | C9: I. Tiền và các khoản tương đương tiền | D9: 110 | E9: =E10+E11 -> 1863564686 | F9: =F10+F11 -> 1839270717 | G9: =G10+G11 -> 10212877174 | H9: =H10+H11 -> 25094023905 | J9: =J10+J11 -> 4056409151 | K9: =K10+K11 -> 959826685 | L9: =L10+L11 -> 10758610238 | M9: =M10+M11 -> 16482060872 | O9: =O10+O11 -> 256675949 | P9: =P10+P11 -> 490654595 | Q9: =Q10+Q11 -> 11130311158 | R9: =R10+R11 -> 1963401127 | T9: =T10+T11 -> 1748942200 | U9: =U10+U11 -> 760026044 | V9: =V10+V11 -> 454988514 | W9: =W10+W11 -> 247864074 | Y9: =Y10+Y11 -> 0 | Z9: =Z10+Z11 -> 0 | AA9: =AA10+AA11 -> 0 | AB9: =AB10+AB11 -> 0 | AD9: =AD10+AD11 -> 0 | AE9: =AE10+AE11 -> 0 | AF9: =AF10+AF11 -> 0 | AG9: =AG10+AG11 -> 0 | AI9: =AI10+AI11 -> 0 | AJ9: =AJ10+AJ11 -> 0 | AK9: =AK10+AK11 -> 0 | AL9: =AL10+AL11 -> 0 | AN9: =AN10+AN11 -> 0 | AO9: =AO10+AO11 -> 0 | AP9: =AP10+AP11 -> 0 | AQ9: =AQ10+AQ11 -> 0 | AS9: =AS10+AS11 -> 0 | AT9: =AT10+AT11 -> 0 | AU9: =AU10+AU11 -> 0 | AV9: =AV10+AV11 -> 0 | AX9: =AX10+AX11 -> 0 | AY9: =AY10+AY11 -> 0 | AZ9: =AZ10+AZ11 -> 0 | BA9: =BA10+BA11 -> 0 | BC9: =BC10+BC11 -> 0 | BD9: =BD10+BD11 -> 0 | BE9: =BE10+BE11 -> 0 | BF9: =BF10+BF11 -> 0 | BH9: =BH10+BH11 -> 0 | BI9: =BI10+BI11 -> 0 | BJ9: =BJ10+BJ11 -> 0 | BK9: =BK10+BK11 -> 0 | BM9: =E9+AI9 -> 1863564686 | BN9: =F9+AJ9 -> 1839270717 | BO9: =G9+AK9 -> 10212877174 | BP9: =H9+AL9 -> 25094023905 | BR9: =J9+AN9 -> 4056409151 | BS9: =K9+AO9 -> 959826685 | BT9: =L9+AP9 -> 10758610238 | BU9: =M9+AQ9 -> 16482060872 | BW9: =O9+AS9 -> 256675949 | BX9: =P9+AT9 -> 490654595 | BY9: =Q9+AU9 -> 11130311158 | BZ9: =R9+AV9 -> 1963401127 | CB9: =T9+AX9 -> 1748942200 | CC9: =U9+AY9 -> 760026044 | CD9: =V9+AZ9 -> 454988514 | CE9: =W9+BA9 -> 247864074 | CG9: =Y9+BC9 -> 0 | CH9: =Z9+BD9 -> 0 | CI9: =AA9+BE9 -> 0 | CJ9: =AB9+BF9 -> 0 | CL9: =AD9+BH9 -> 0 | CM9: =AE9+BI9 -> 0 | CN9: =AF9+BJ9 -> 0 | CO9: =AG9+BK9 -> 0 | CQ9: =SUMIF('1.PL (VND) '!$BL$6:$CD$6,'1.PL (VND) '!CP$6,$BM9:$CE9) -> 7925591986 | CR9: =SUMIF('1.PL (VND) '!$BL$6:$CD$6,'1.PL (VND) '!CQ$6,$BM9:$CE9) -> 4049778041 | CS9: =SUMIF('1.PL (VND) '!$BL$6:$CD$6,'1.PL (VND) '!CR$6,$BM9:$CE9) -> 32556787084 | CT9: =SUMIF('1.PL (VND) '!$BL$6:$CD$6,'1.PL (VND) '!CS$6,$BM9:$CE9) -> 43787349978 | CV9: =CV10+CV11 -> 0 | CW9: =CW10+CW11 -> 0 | CX9: =CX10+CX11 -> 0 | CY9: =CY10+CY11 -> 0 | DA9: =CQ9+CV9 -> 7925591986 | DB9: =CR9+CW9 -> 4049778041 | DC9: =CS9+CX9 -> 32556787084 | DD9: =CT9+CY9 -> 43787349978
A10: =IF(SUM(E10:DD10)<>0,1,"hide") -> 1 | C10: 1. Tiền | D10: 111 | E10: 1863564686 | F10: 1839270717 | G10: 10212877174 | H10: 25094023905 | J10: 4056409151 | K10: 959826685 | L10: 10758610238 | M10: 16482060872 | O10: 256675949 | P10: 490654595 | Q10: 11130311158 | R10: 1963401127 | T10: 1748942200 | U10: 760026044 | V10: 454988514 | W10: 247864074 | AI10: =SUMIFS('1.DC_Ra soat'!$L:$L,'1.DC_Ra soat'!$F:$F,AI$4,'1.DC_Ra soat'!$H:$H,'1.BS (VND)'!$D10)-SUMIFS('1.DC_Ra soat'!$L:$L,'1.DC_Ra soat'!$F:$F,AI$4,'1.DC_Ra soat'!$I:$I,'1.BS (VND)'!$D10) -> 0 | AJ10: =SUMIFS('1.DC_Ra soat'!$L:$L,'1.DC_Ra soat'!$F:$F,AJ$4,'1.DC_Ra soat'!$H:$H,'1.BS (VND)'!$D10)-SUMIFS('1.DC_Ra soat'!$L:$L,'1.DC_Ra soat'!$F:$F,AJ$4,'1.DC_Ra soat'!$I:$I,'1.BS (VND)'!$D10) -> 0 | AK10: =SUMIFS('1.DC_Ra soat'!$L:$L,'1.DC_Ra soat'!$F:$F,AK$4,'1.DC_Ra soat'!$H:$H,'1.BS (VND)'!$D10)-SUMIFS('1.DC_Ra soat'!$L:$L,'1.DC_Ra soat'!$F:$F,AK$4,'1.DC_Ra soat'!$I:$I,'1.BS (VND)'!$D10) -> 0 | AL10: =SUMIFS('1.DC_Ra soat'!$L:$L,'1.DC_Ra soat'!$F:$F,AL$4,'1.DC_Ra soat'!$H:$H,'1.BS (VND)'!$D10)-SUMIFS('1.DC_Ra soat'!$L:$L,'1.DC_Ra soat'!$F:$F,AL$4,'1.DC_Ra soat'!$I:$I,'1.BS (VND)'!$D10) -> 0 | AN10: =SUMIFS('1.DC_Ra soat'!$L:$L,'1.DC_Ra soat'!$F:$F,AN$4,'1.DC_Ra soat'!$H:$H,'1.BS (VND)'!$D10)-SUMIFS('1.DC_Ra soat'!$L:$L,'1.DC_Ra soat'!$F:$F,AN$4,'1.DC_Ra soat'!$I:$I,'1.BS (VND)'!$D10) -> 0 | AO10: =SUMIFS('1.DC_Ra soat'!$L:$L,'1.DC_Ra soat'!$F:$F,AO$4,'1.DC_Ra soat'!$H:$H,'1.BS (VND)'!$D10)-SUMIFS('1.DC_Ra soat'!$L:$L,'1.DC_Ra soat'!$F:$F,AO$4,'1.DC_Ra soat'!$I:$I,'1.BS (VND)'!$D10) -> 0 | AP10: =SUMIFS('1.DC_Ra soat'!$L:$L,'1.DC_Ra soat'!$F:$F,AP$4,'1.DC_Ra soat'!$H:$H,'1.BS (VND)'!$D10)-SUMIFS('1.DC_Ra soat'!$L:$L,'1.DC_Ra soat'!$F:$F,AP$4,'1.DC_Ra soat'!$I:$I,'1.BS (VND)'!$D10) -> 0 | AQ10: =SUMIFS('1.DC_Ra soat'!$L:$L,'1.DC_Ra soat'!$F:$F,AQ$4,'1.DC_Ra soat'!$H:$H,'1.BS (VND)'!$D10)-SUMIFS('1.DC_Ra soat'!$L:$L,'1.DC_Ra soat'!$F:$F,AQ$4,'1.DC_Ra soat'!$I:$I,'1.BS (VND)'!$D10) -> 0 | AS10: =SUMIFS('1.DC_Ra soat'!$L:$L,'1.DC_Ra soat'!$F:$F,AS$4,'1.DC_Ra soat'!$H:$H,'1.BS (VND)'!$D10)-SUMIFS('1.DC_Ra soat'!$L:$L,'1.DC_Ra soat'!$F:$F,AS$4,'1.DC_Ra soat'!$I:$I,'1.BS (VND)'!$D10) -> 0 | AT10: =SUMIFS('1.DC_Ra soat'!$L:$L,'1.DC_Ra soat'!$F:$F,AT$4,'1.DC_Ra soat'!$H:$H,'1.BS (VND)'!$D10)-SUMIFS('1.DC_Ra soat'!$L:$L,'1.DC_Ra soat'!$F:$F,AT$4,'1.DC_Ra soat'!$I:$I,'1.BS (VND)'!$D10) -> 0 | AU10: =SUMIFS('1.DC_Ra soat'!$L:$L,'1.DC_Ra soat'!$F:$F,AU$4,'1.DC_Ra soat'!$H:$H,'1.BS (VND)'!$D10)-SUMIFS('1.DC_Ra soat'!$L:$L,'1.DC_Ra soat'!$F:$F,AU$4,'1.DC_Ra soat'!$I:$I,'1.BS (VND)'!$D10) -> 0 | AV10: =SUMIFS('1.DC_Ra soat'!$L:$L,'1.DC_Ra soat'!$F:$F,AV$4,'1.DC_Ra soat'!$H:$H,'1.BS (VND)'!$D10)-SUMIFS('1.DC_Ra soat'!$L:$L,'1.DC_Ra soat'!$F:$F,AV$4,'1.DC_Ra soat'!$I:$I,'1.BS (VND)'!$D10) -> 0 | AX10: =SUMIFS('1.DC_Ra soat'!$L:$L,'1.DC_Ra soat'!$F:$F,AX$4,'1.DC_Ra soat'!$H:$H,'1.BS (VND)'!$D10)-SUMIFS('1.DC_Ra soat'!$L:$L,'1.DC_Ra soat'!$F:$F,AX$4,'1.DC_Ra soat'!$I:$I,'1.BS (VND)'!$D10) -> 0 | AY10: =SUMIFS('1.DC_Ra soat'!$L:$L,'1.DC_Ra soat'!$F:$F,AY$4,'1.DC_Ra soat'!$H:$H,'1.BS (VND)'!$D10)-SUMIFS('1.DC_Ra soat'!$L:$L,'1.DC_Ra soat'!$F:$F,AY$4,'1.DC_Ra soat'!$I:$I,'1.BS (VND)'!$D10) -> 0 | AZ10: =SUMIFS('1.DC_Ra soat'!$L:$L,'1.DC_Ra soat'!$F:$F,AZ$4,'1.DC_Ra soat'!$H:$H,'1.BS (VND)'!$D10)-SUMIFS('1.DC_Ra soat'!$L:$L,'1.DC_Ra soat'!$F:$F,AZ$4,'1.DC_Ra soat'!$I:$I,'1.BS (VND)'!$D10) -> 0 | BA10: =SUMIFS('1.DC_Ra soat'!$L:$L,'1.DC_Ra soat'!$F:$F,BA$4,'1.DC_Ra soat'!$H:$H,'1.BS (VND)'!$D10)-SUMIFS('1.DC_Ra soat'!$L:$L,'1.DC_Ra soat'!$F:$F,BA$4,'1.DC_Ra soat'!$I:$I,'1.BS (VND)'!$D10) -> 0 | BC10: =SUMIFS('1.DC_Ra soat'!$L:$L,'1.DC_Ra soat'!$F:$F,'1.PL (VND) '!BI$4,'1.DC_Ra soat'!$H:$H,'1.BS (VND)'!$D10)-SUMIFS('1.DC_Ra soat'!$L:$L,'1.DC_Ra soat'!$F:$F,'1.PL (VND) '!BI$4,'1.DC_Ra soat'!$I:$I,'1.BS (VND)'!$D10) -> 0 | BD10: =SUMIFS('1.DC_Ra soat'!$L:$L,'1.DC_Ra soat'!$F:$F,'1.PL (VND) '!BJ$4,'1.DC_Ra soat'!$H:$H,'1.BS (VND)'!$D10)-SUMIFS('1.DC_Ra soat'!$L:$L,'1.DC_Ra soat'!$F:$F,'1.PL (VND) '!BJ$4,'1.DC_Ra soat'!$I:$I,'1.BS (VND)'!$D10) -> 0 | BE10: =SUMIFS('1.DC_Ra soat'!$L:$L,'1.DC_Ra soat'!$F:$F,'1.PL (VND) '!BK$4,'1.DC_Ra soat'!$H:$H,'1.BS (VND)'!$D10)-SUMIFS('1.DC_Ra soat'!$L:$L,'1.DC_Ra soat'!$F:$F,'1.PL (VND) '!BK$4,'1.DC_Ra soat'!$I:$I,'1.BS (VND)'!$D10) -> 0 | BF10: =SUMIFS('1.DC_Ra soat'!$L:$L,'1.DC_Ra soat'!$F:$F,'1.PL (VND) '!BL$4,'1.DC_Ra soat'!$H:$H,'1.BS (VND)'!$D10)-SUMIFS('1.DC_Ra soat'!$L:$L,'1.DC_Ra soat'!$F:$F,'1.PL (VND) '!BL$4,'1.DC_Ra soat'!$I:$I,'1.BS (VND)'!$D10) -> 0 | BH10: =SUMIFS('1.DC_Ra soat'!$L:$L,'1.DC_Ra soat'!$F:$F,'1.PL (VND) '!BO$4,'1.DC_Ra soat'!$H:$H,'1.BS (VND)'!$D10)-SUMIFS('1.DC_Ra soat'!$L:$L,'1.DC_Ra soat'!$F:$F,'1.PL (VND) '!BO$4,'1.DC_Ra soat'!$I:$I,'1.BS (VND)'!$D10) -> 0 | BI10: =SUMIFS('1.DC_Ra soat'!$L:$L,'1.DC_Ra soat'!$F:$F,'1.PL (VND) '!BP$4,'1.DC_Ra soat'!$H:$H,'1.BS (VND)'!$D10)-SUMIFS('1.DC_Ra soat'!$L:$L,'1.DC_Ra soat'!$F:$F,'1.PL (VND) '!BP$4,'1.DC_Ra soat'!$I:$I,'1.BS (VND)'!$D10) -> 0 | BJ10: =SUMIFS('1.DC_Ra soat'!$L:$L,'1.DC_Ra soat'!$F:$F,'1.PL (VND) '!BQ$4,'1.DC_Ra soat'!$H:$H,'1.BS (VND)'!$D10)-SUMIFS('1.DC_Ra soat'!$L:$L,'1.DC_Ra soat'!$F:$F,'1.PL (VND) '!BQ$4,'1.DC_Ra soat'!$I:$I,'1.BS (VND)'!$D10) -> 0 | BK10: =SUMIFS('1.DC_Ra soat'!$L:$L,'1.DC_Ra soat'!$F:$F,'1.PL (VND) '!BR$4,'1.DC_Ra soat'!$H:$H,'1.BS (VND)'!$D10)-SUMIFS('1.DC_Ra soat'!$L:$L,'1.DC_Ra soat'!$F:$F,'1.PL (VND) '!BR$4,'1.DC_Ra soat'!$I:$I,'1.BS (VND)'!$D10) -> 0 | BM10: =E10+AI10 -> 1863564686 | BN10: =F10+AJ10 -> 1839270717 | BO10: =G10+AK10 -> 10212877174 | BP10: =H10+AL10 -> 25094023905 | BR10: =J10+AN10 -> 4056409151 | BS10: =K10+AO10 -> 959826685 | BT10: =L10+AP10 -> 10758610238 | BU10: =M10+AQ10 -> 16482060872 | BW10: =O10+AS10 -> 256675949 | BX10: =P10+AT10 -> 490654595 | BY10: =Q10+AU10 -> 11130311158 | BZ10: =R10+AV10 -> 1963401127 | CB10: =T10+AX10 -> 1748942200 | CC10: =U10+AY10 -> 760026044 | CD10: =V10+AZ10 -> 454988514 | CE10: =W10+BA10 -> 247864074 | CG10: =Y10+BC10 -> 0 | CH10: =Z10+BD10 -> 0 | CI10: =AA10+BE10 -> 0 | CJ10: =AB10+BF10 -> 0 | CL10: =AD10+BH10 -> 0 | CM10: =AE10+BI10 -> 0 | CN10: =AF10+BJ10 -> 0 | CO10: =AG10+BK10 -> 0 | CQ10: =SUMIF('1.PL (VND) '!$BL$6:$CD$6,'1.PL (VND) '!CP$6,$BM10:$CE10) -> 7925591986 | CR10: =SUMIF('1.PL (VND) '!$BL$6:$CD$6,'1.PL (VND) '!CQ$6,$BM10:$CE10) -> 4049778041 | CS10: =SUMIF('1.PL (VND) '!$BL$6:$CD$6,'1.PL (VND) '!CR$6,$BM10:$CE10) -> 32556787084 | CT10: =SUMIF('1.PL (VND) '!$BL$6:$CD$6,'1.PL (VND) '!CS$6,$BM10:$CE10) -> 43787349978 | CV10: =-SUMIFS('1.DC_Ra soat'!$L:$L,'1.DC_Ra soat'!$F:$F,'1.PL (VND) '!DK$4,'1.DC_Ra soat'!$H:$H,'1.BS (VND)'!$D10)+SUMIFS('1.DC_Ra soat'!$L:$L,'1.DC_Ra soat'!$F:$F,'1.PL (VND) '!DK$4,'1.DC_Ra soat'!$I:$I,'1.BS (VND)'!$D10) -> 0 | CW10: =-SUMIFS('1.DC_Ra soat'!$L:$L,'1.DC_Ra soat'!$F:$F,'1.PL (VND) '!DL$4,'1.DC_Ra soat'!$H:$H,'1.BS (VND)'!$D10)+SUMIFS('1.DC_Ra soat'!$L:$L,'1.DC_Ra soat'!$F:$F,'1.PL (VND) '!DL$4,'1.DC_Ra soat'!$I:$I,'1.BS (VND)'!$D10) -> 0 | CX10: =-SUMIFS('1.DC_Ra soat'!$L:$L,'1.DC_Ra soat'!$F:$F,'1.PL (VND) '!DM$4,'1.DC_Ra soat'!$H:$H,'1.BS (VND)'!$D10)+SUMIFS('1.DC_Ra soat'!$L:$L,'1.DC_Ra soat'!$F:$F,'1.PL (VND) '!DM$4,'1.DC_Ra soat'!$I:$I,'1.BS (VND)'!$D10) -> 0 | CY10: =-SUMIFS('1.DC_Ra soat'!$L:$L,'1.DC_Ra soat'!$F:$F,'1.PL (VND) '!DN$4,'1.DC_Ra soat'!$H:$H,'1.BS (VND)'!$D10)+SUMIFS('1.DC_Ra soat'!$L:$L,'1.DC_Ra soat'!$F:$F,'1.PL (VND) '!DN$4,'1.DC_Ra soat'!$I:$I,'1.BS (VND)'!$D10) -> 0 | DA10: =CQ10+CV10 -> 7925591986 | DB10: =CR10+CW10 -> 4049778041 | DC10: =CS10+CX10 -> 32556787084 | DD10: =CT10+CY10 -> 43787349978
A11: =IF(SUM(E11:DD11)<>0,1,"hide") -> hide | C11: 2. Các khoản tương đương tiền | D11: 112 | M11: 0 | AI11: =SUMIFS('1.DC_Ra soat'!$L:$L,'1.DC_Ra soat'!$F:$F,AI$4,'1.DC_Ra soat'!$H:$H,'1.BS (VND)'!$D11)-SUMIFS('1.DC_Ra soat'!$L:$L,'1.DC_Ra soat'!$F:$F,AI$4,'1.DC_Ra soat'!$I:$I,'1.BS (VND)'!$D11) -> 0 | AJ11: =SUMIFS('1.DC_Ra soat'!$L:$L,'1.DC_Ra soat'!$F:$F,AJ$4,'1.DC_Ra soat'!$H:$H,'1.BS (VND)'!$D11)-SUMIFS('1.DC_Ra soat'!$L:$L,'1.DC_Ra soat'!$F:$F,AJ$4,'1.DC_Ra soat'!$I:$I,'1.BS (VND)'!$D11) -> 0 | AK11: =SUMIFS('1.DC_Ra soat'!$L:$L,'1.DC_Ra soat'!$F:$F,AK$4,'1.DC_Ra soat'!$H:$H,'1.BS (VND)'!$D11)-SUMIFS('1.DC_Ra soat'!$L:$L,'1.DC_Ra soat'!$F:$F,AK$4,'1.DC_Ra soat'!$I:$I,'1.BS (VND)'!$D11) -> 0 | AL11: =SUMIFS('1.DC_Ra soat'!$L:$L,'1.DC_Ra soat'!$F:$F,AL$4,'1.DC_Ra soat'!$H:$H,'1.BS (VND)'!$D11)-SUMIFS('1.DC_Ra soat'!$L:$L,'1.DC_Ra soat'!$F:$F,AL$4,'1.DC_Ra soat'!$I:$I,'1.BS (VND)'!$D11) -> 0 | AN11: =SUMIFS('1.DC_Ra soat'!$L:$L,'1.DC_Ra soat'!$F:$F,AN$4,'1.DC_Ra soat'!$H:$H,'1.BS (VND)'!$D11)-SUMIFS('1.DC_Ra soat'!$L:$L,'1.DC_Ra soat'!$F:$F,AN$4,'1.DC_Ra soat'!$I:$I,'1.BS (VND)'!$D11) -> 0 | AO11: =SUMIFS('1.DC_Ra soat'!$L:$L,'1.DC_Ra soat'!$F:$F,AO$4,'1.DC_Ra soat'!$H:$H,'1.BS (VND)'!$D11)-SUMIFS('1.DC_Ra soat'!$L:$L,'1.DC_Ra soat'!$F:$F,AO$4,'1.DC_Ra soat'!$I:$I,'1.BS (VND)'!$D11) -> 0 | AP11: =SUMIFS('1.DC_Ra soat'!$L:$L,'1.DC_Ra soat'!$F:$F,AP$4,'1.DC_Ra soat'!$H:$H,'1.BS (VND)'!$D11)-SUMIFS('1.DC_Ra soat'!$L:$L,'1.DC_Ra soat'!$F:$F,AP$4,'1.DC_Ra soat'!$I:$I,'1.BS (VND)'!$D11) -> 0 | AQ11: =SUMIFS('1.DC_Ra soat'!$L:$L,'1.DC_Ra soat'!$F:$F,AQ$4,'1.DC_Ra soat'!$H:$H,'1.BS (VND)'!$D11)-SUMIFS('1.DC_Ra soat'!$L:$L,'1.DC_Ra soat'!$F:$F,AQ$4,'1.DC_Ra soat'!$I:$I,'1.BS (VND)'!$D11) -> 0 | AS11: =SUMIFS('1.DC_Ra soat'!$L:$L,'1.DC_Ra soat'!$F:$F,AS$4,'1.DC_Ra soat'!$H:$H,'1.BS (VND)'!$D11)-SUMIFS('1.DC_Ra soat'!$L:$L,'1.DC_Ra soat'!$F:$F,AS$4,'1.DC_Ra soat'!$I:$I,'1.BS (VND)'!$D11) -> 0 | AT11: =SUMIFS('1.DC_Ra soat'!$L:$L,'1.DC_Ra soat'!$F:$F,AT$4,'1.DC_Ra soat'!$H:$H,'1.BS (VND)'!$D11)-SUMIFS('1.DC_Ra soat'!$L:$L,'1.DC_Ra soat'!$F:$F,AT$4,'1.DC_Ra soat'!$I:$I,'1.BS (VND)'!$D11) -> 0 | AU11: =SUMIFS('1.DC_Ra soat'!$L:$L,'1.DC_Ra soat'!$F:$F,AU$4,'1.DC_Ra soat'!$H:$H,'1.BS (VND)'!$D11)-SUMIFS('1.DC_Ra soat'!$L:$L,'1.DC_Ra soat'!$F:$F,AU$4,'1.DC_Ra soat'!$I:$I,'1.BS (VND)'!$D11) -> 0 | AV11: =SUMIFS('1.DC_Ra soat'!$L:$L,'1.DC_Ra soat'!$F:$F,AV$4,'1.DC_Ra soat'!$H:$H,'1.BS (VND)'!$D11)-SUMIFS('1.DC_Ra soat'!$L:$L,'1.DC_Ra soat'!$F:$F,AV$4,'1.DC_Ra soat'!$I:$I,'1.BS (VND)'!$D11) -> 0 | AX11: =SUMIFS('1.DC_Ra soat'!$L:$L,'1.DC_Ra soat'!$F:$F,AX$4,'1.DC_Ra soat'!$H:$H,'1.BS (VND)'!$D11)-SUMIFS('1.DC_Ra soat'!$L:$L,'1.DC_Ra soat'!$F:$F,AX$4,'1.DC_Ra soat'!$I:$I,'1.BS (VND)'!$D11) -> 0 | AY11: =SUMIFS('1.DC_Ra soat'!$L:$L,'1.DC_Ra soat'!$F:$F,AY$4,'1.DC_Ra soat'!$H:$H,'1.BS (VND)'!$D11)-SUMIFS('1.DC_Ra soat'!$L:$L,'1.DC_Ra soat'!$F:$F,AY$4,'1.DC_Ra soat'!$I:$I,'1.BS (VND)'!$D11) -> 0 | AZ11: =SUMIFS('1.DC_Ra soat'!$L:$L,'1.DC_Ra soat'!$F:$F,AZ$4,'1.DC_Ra soat'!$H:$H,'1.BS (VND)'!$D11)-SUMIFS('1.DC_Ra soat'!$L:$L,'1.DC_Ra soat'!$F:$F,AZ$4,'1.DC_Ra soat'!$I:$I,'1.BS (VND)'!$D11) -> 0 | BA11: =SUMIFS('1.DC_Ra soat'!$L:$L,'1.DC_Ra soat'!$F:$F,BA$4,'1.DC_Ra soat'!$H:$H,'1.BS (VND)'!$D11)-SUMIFS('1.DC_Ra soat'!$L:$L,'1.DC_Ra soat'!$F:$F,BA$4,'1.DC_Ra soat'!$I:$I,'1.BS (VND)'!$D11) -> 0 | BC11: =SUMIFS('1.DC_Ra soat'!$L:$L,'1.DC_Ra soat'!$F:$F,'1.PL (VND) '!BI$4,'1.DC_Ra soat'!$H:$H,'1.BS (VND)'!$D11)-SUMIFS('1.DC_Ra soat'!$L:$L,'1.DC_Ra soat'!$F:$F,'1.PL (VND) '!BI$4,'1.DC_Ra soat'!$I:$I,'1.BS (VND)'!$D11) -> 0 | BD11: =SUMIFS('1.DC_Ra soat'!$L:$L,'1.DC_Ra soat'!$F:$F,'1.PL (VND) '!BJ$4,'1.DC_Ra soat'!$H:$H,'1.BS (VND)'!$D11)-SUMIFS('1.DC_Ra soat'!$L:$L,'1.DC_Ra soat'!$F:$F,'1.PL (VND) '!BJ$4,'1.DC_Ra soat'!$I:$I,'1.BS (VND)'!$D11) -> 0 | BE11: =SUMIFS('1.DC_Ra soat'!$L:$L,'1.DC_Ra soat'!$F:$F,'1.PL (VND) '!BK$4,'1.DC_Ra soat'!$H:$H,'1.BS (VND)'!$D11)-SUMIFS('1.DC_Ra soat'!$L:$L,'1.DC_Ra soat'!$F:$F,'1.PL (VND) '!BK$4,'1.DC_Ra soat'!$I:$I,'1.BS (VND)'!$D11) -> 0 | BF11: =SUMIFS('1.DC_Ra soat'!$L:$L,'1.DC_Ra soat'!$F:$F,'1.PL (VND) '!BL$4,'1.DC_Ra soat'!$H:$H,'1.BS (VND)'!$D11)-SUMIFS('1.DC_Ra soat'!$L:$L,'1.DC_Ra soat'!$F:$F,'1.PL (VND) '!BL$4,'1.DC_Ra soat'!$I:$I,'1.BS (VND)'!$D11) -> 0 | BH11: =SUMIFS('1.DC_Ra soat'!$L:$L,'1.DC_Ra soat'!$F:$F,'1.PL (VND) '!BO$4,'1.DC_Ra soat'!$H:$H,'1.BS (VND)'!$D11)-SUMIFS('1.DC_Ra soat'!$L:$L,'1.DC_Ra soat'!$F:$F,'1.PL (VND) '!BO$4,'1.DC_Ra soat'!$I:$I,'1.BS (VND)'!$D11) -> 0 | BI11: =SUMIFS('1.DC_Ra soat'!$L:$L,'1.DC_Ra soat'!$F:$F,'1.PL (VND) '!BP$4,'1.DC_Ra soat'!$H:$H,'1.BS (VND)'!$D11)-SUMIFS('1.DC_Ra soat'!$L:$L,'1.DC_Ra soat'!$F:$F,'1.PL (VND) '!BP$4,'1.DC_Ra soat'!$I:$I,'1.BS (VND)'!$D11) -> 0 | BJ11: =SUMIFS('1.DC_Ra soat'!$L:$L,'1.DC_Ra soat'!$F:$F,'1.PL (VND) '!BQ$4,'1.DC_Ra soat'!$H:$H,'1.BS (VND)'!$D11)-SUMIFS('1.DC_Ra soat'!$L:$L,'1.DC_Ra soat'!$F:$F,'1.PL (VND) '!BQ$4,'1.DC_Ra soat'!$I:$I,'1.BS (VND)'!$D11) -> 0 | BK11: =SUMIFS('1.DC_Ra soat'!$L:$L,'1.DC_Ra soat'!$F:$F,'1.PL (VND) '!BR$4,'1.DC_Ra soat'!$H:$H,'1.BS (VND)'!$D11)-SUMIFS('1.DC_Ra soat'!$L:$L,'1.DC_Ra soat'!$F:$F,'1.PL (VND) '!BR$4,'1.DC_Ra soat'!$I:$I,'1.BS (VND)'!$D11) -> 0 | BM11: =E11+AI11 -> 0 | BN11: =F11+AJ11 -> 0 | BO11: =G11+AK11 -> 0 | BP11: =H11+AL11 -> 0 | BR11: =J11+AN11 -> 0 | BS11: =K11+AO11 -> 0 | BT11: =L11+AP11 -> 0 | BU11: =M11+AQ11 -> 0 | BW11: =O11+AS11 -> 0 | BX11: =P11+AT11 -> 0 | BY11: =Q11+AU11 -> 0 | BZ11: =R11+AV11 -> 0 | CB11: =T11+AX11 -> 0 | CC11: =U11+AY11 -> 0 | CD11: =V11+AZ11 -> 0 | CE11: =W11+BA11 -> 0 | CG11: =Y11+BC11 -> 0 | CH11: =Z11+BD11 -> 0 | CI11: =AA11+BE11 -> 0 | CJ11: =AB11+BF11 -> 0 | CL11: =AD11+BH11 -> 0 | CM11: =AE11+BI11 -> 0 | CN11: =AF11+BJ11 -> 0 | CO11: =AG11+BK11 -> 0 | CQ11: =SUMIF('1.PL (VND) '!$BL$6:$CD$6,'1.PL (VND) '!CP$6,$BM11:$CE11) -> 0 | CR11: =SUMIF('1.PL (VND) '!$BL$6:$CD$6,'1.PL (VND) '!CQ$6,$BM11:$CE11) -> 0 | CS11: =SUMIF('1.PL (VND) '!$BL$6:$CD$6,'1.PL (VND) '!CR$6,$BM11:$CE11) -> 0 | CT11: =SUMIF('1.PL (VND) '!$BL$6:$CD$6,'1.PL (VND) '!CS$6,$BM11:$CE11) -> 0 | CV11: =-SUMIFS('1.DC_Ra soat'!$L:$L,'1.DC_Ra soat'!$F:$F,'1.PL (VND) '!DK$4,'1.DC_Ra soat'!$H:$H,'1.BS (VND)'!$D11)+SUMIFS('1.DC_Ra soat'!$L:$L,'1.DC_Ra soat'!$F:$F,'1.PL (VND) '!DK$4,'1.DC_Ra soat'!$I:$I,'1.BS (VND)'!$D11) -> 0 | CW11: =-SUMIFS('1.DC_Ra soat'!$L:$L,'1.DC_Ra soat'!$F:$F,'1.PL (VND) '!DL$4,'1.DC_Ra soat'!$H:$H,'1.BS (VND)'!$D11)+SUMIFS('1.DC_Ra soat'!$L:$L,'1.DC_Ra soat'!$F:$F,'1.PL (VND) '!DL$4,'1.DC_Ra soat'!$I:$I,'1.BS (VND)'!$D11) -> 0 | CX11: =-SUMIFS('1.DC_Ra soat'!$L:$L,'1.DC_Ra soat'!$F:$F,'1.PL (VND) '!DM$4,'1.DC_Ra soat'!$H:$H,'1.BS (VND)'!$D11)+SUMIFS('1.DC_Ra soat'!$L:$L,'1.DC_Ra soat'!$F:$F,'1.PL (VND) '!DM$4,'1.DC_Ra soat'!$I:$I,'1.BS (VND)'!$D11) -> 0 | CY11: =-SUMIFS('1.DC_Ra soat'!$L:$L,'1.DC_Ra soat'!$F:$F,'1.PL (VND) '!DN$4,'1.DC_Ra soat'!$H:$H,'1.BS (VND)'!$D11)+SUMIFS('1.DC_Ra soat'!$L:$L,'1.DC_Ra soat'!$F:$F,'1.PL (VND) '!DN$4,'1.DC_Ra soat'!$I:$I,'1.BS (VND)'!$D11) -> 0 | DA11: =CQ11+CV11 -> 0 | DB11: =CR11+CW11 -> 0 | DC11: =CS11+CX11 -> 0 | DD11: =CT11+CY11 -> 0
A12: =IF(SUM(E12:DD12)<>0,1,"hide") -> hide | C12: II. Đầu tư tài chính ngắn hạn | D12: 120 | E12: =SUM(E13:E15) -> 0 | F12: =SUM(F13:F15) -> 0 | G12: =SUM(G13:G15) -> 0 | H12: =SUM(H13:H15) -> 0 | M12: 0 | T12: =SUM(T13:T15) -> 0 | U12: =SUM(U13:U15) -> 0 | V12: =SUM(V13:V15) -> 0 | W12: =SUM(W13:W15) -> 0 | AI12: =SUM(AI13:AI15) -> 0 | AJ12: =SUM(AJ13:AJ15) -> 0 | AK12: =SUM(AK13:AK15) -> 0 | AL12: =SUM(AL13:AL15) -> 0 | AN12: =SUM(AN13:AN15) -> 0 | AO12: =SUM(AO13:AO15) -> 0 | AP12: =SUM(AP13:AP15) -> 0 | AQ12: =SUM(AQ13:AQ15) -> 0 | AS12: =SUMIFS('1.DC_Ra soat'!$L:$L,'1.DC_Ra soat'!$F:$F,AS$4,'1.DC_Ra soat'!$H:$H,'1.BS (VND)'!$D12)-SUMIFS('1.DC_Ra soat'!$L:$L,'1.DC_Ra soat'!$F:$F,AS$4,'1.DC_Ra soat'!$I:$I,'1.BS (VND)'!$D12) -> 0 | AT12: =SUMIFS('1.DC_Ra soat'!$L:$L,'1.DC_Ra soat'!$F:$F,AT$4,'1.DC_Ra soat'!$H:$H,'1.BS (VND)'!$D12)-SUMIFS('1.DC_Ra soat'!$L:$L,'1.DC_Ra soat'!$F:$F,AT$4,'1.DC_Ra soat'!$I:$I,'1.BS (VND)'!$D12) -> 0 | AU12: =SUMIFS('1.DC_Ra soat'!$L:$L,'1.DC_Ra soat'!$F:$F,AU$4,'1.DC_Ra soat'!$H:$H,'1.BS (VND)'!$D12)-SUMIFS('1.DC_Ra soat'!$L:$L,'1.DC_Ra soat'!$F:$F,AU$4,'1.DC_Ra soat'!$I:$I,'1.BS (VND)'!$D12) -> 0 | AV12: =SUMIFS('1.DC_Ra soat'!$L:$L,'1.DC_Ra soat'!$F:$F,AV$4,'1.DC_Ra soat'!$H:$H,'1.BS (VND)'!$D12)-SUMIFS('1.DC_Ra soat'!$L:$L,'1.DC_Ra soat'!$F:$F,AV$4,'1.DC_Ra soat'!$I:$I,'1.BS (VND)'!$D12) -> 0 | BM12: =E12+AI12 -> 0 | BN12: =F12+AJ12 -> 0 | BO12: =G12+AK12 -> 0 | BP12: =H12+AL12 -> 0 | BR12: =J12+AN12 -> 0 | BS12: =K12+AO12 -> 0 | BT12: =L12+AP12 -> 0 | BU12: =M12+AQ12 -> 0 | BW12: =O12+AS12 -> 0 | BX12: =P12+AT12 -> 0 | BY12: =Q12+AU12 -> 0 | BZ12: =R12+AV12 -> 0 | CB12: =T12+AX12 -> 0 | CC12: =U12+AY12 -> 0 | CD12: =V12+AZ12 -> 0 | CE12: =W12+BA12 -> 0 | CG12: =Y12+BC12 -> 0 | CH12: =Z12+BD12 -> 0 | CI12: =AA12+BE12 -> 0 | CJ12: =AB12+BF12 -> 0 | CL12: =AD12+BH12 -> 0 | CM12: =AE12+BI12 -> 0 | CN12: =AF12+BJ12 -> 0 | CO12: =AG12+BK12 -> 0 | CQ12: =SUMIF('1.PL (VND) '!$BL$6:$CD$6,'1.PL (VND) '!CP$6,$BM12:$CE12) -> 0 | CR12: =SUMIF('1.PL (VND) '!$BL$6:$CD$6,'1.PL (VND) '!CQ$6,$BM12:$CE12) -> 0 | CS12: =SUMIF('1.PL (VND) '!$BL$6:$CD$6,'1.PL (VND) '!CR$6,$BM12:$CE12) -> 0 | CT12: =SUMIF('1.PL (VND) '!$BL$6:$CD$6,'1.PL (VND) '!CS$6,$BM12:$CE12) -> 0 | CV12: =-SUMIFS('1.DC_Ra soat'!$L:$L,'1.DC_Ra soat'!$F:$F,'1.PL (VND) '!DK$4,'1.DC_Ra soat'!$H:$H,'1.BS (VND)'!$D12)+SUMIFS('1.DC_Ra soat'!$L:$L,'1.DC_Ra soat'!$F:$F,'1.PL (VND) '!DK$4,'1.DC_Ra soat'!$I:$I,'1.BS (VND)'!$D12) -> 0 | CW12: =-SUMIFS('1.DC_Ra soat'!$L:$L,'1.DC_Ra soat'!$F:$F,'1.PL (VND) '!DL$4,'1.DC_Ra soat'!$H:$H,'1.BS (VND)'!$D12)+SUMIFS('1.DC_Ra soat'!$L:$L,'1.DC_Ra soat'!$F:$F,'1.PL (VND) '!DL$4,'1.DC_Ra soat'!$I:$I,'1.BS (VND)'!$D12) -> 0 | CX12: =-SUMIFS('1.DC_Ra soat'!$L:$L,'1.DC_Ra soat'!$F:$F,'1.PL (VND) '!DM$4,'1.DC_Ra soat'!$H:$H,'1.BS (VND)'!$D12)+SUMIFS('1.DC_Ra soat'!$L:$L,'1.DC_Ra soat'!$F:$F,'1.PL (VND) '!DM$4,'1.DC_Ra soat'!$I:$I,'1.BS (VND)'!$D12) -> 0 | CY12: =-SUMIFS('1.DC_Ra soat'!$L:$L,'1.DC_Ra soat'!$F:$F,'1.PL (VND) '!DN$4,'1.DC_Ra soat'!$H:$H,'1.BS (VND)'!$D12)+SUMIFS('1.DC_Ra soat'!$L:$L,'1.DC_Ra soat'!$F:$F,'1.PL (VND) '!DN$4,'1.DC_Ra soat'!$I:$I,'1.BS (VND)'!$D12) -> 0 | DA12: =CQ12+CV12 -> 0 | DB12: =CR12+CW12 -> 0 | DC12: =CS12+CX12 -> 0 | DD12: =CT12+CY12 -> 0
A13: =IF(SUM(E13:DD13)<>0,1,"hide") -> hide | C13: 1. Chứng khoán kinh doanh | D13: 121 | M13: 0 | AI13: =SUMIFS('1.DC_Ra soat'!$L:$L,'1.DC_Ra soat'!$F:$F,AI$4,'1.DC_Ra soat'!$H:$H,'1.BS (VND)'!$D13)-SUMIFS('1.DC_Ra soat'!$L:$L,'1.DC_Ra soat'!$F:$F,AI$4,'1.DC_Ra soat'!$I:$I,'1.BS (VND)'!$D13) -> 0 | AJ13: =SUMIFS('1.DC_Ra soat'!$L:$L,'1.DC_Ra soat'!$F:$F,AJ$4,'1.DC_Ra soat'!$H:$H,'1.BS (VND)'!$D13)-SUMIFS('1.DC_Ra soat'!$L:$L,'1.DC_Ra soat'!$F:$F,AJ$4,'1.DC_Ra soat'!$I:$I,'1.BS (VND)'!$D13) -> 0 | AK13: =SUMIFS('1.DC_Ra soat'!$L:$L,'1.DC_Ra soat'!$F:$F,AK$4,'1.DC_Ra soat'!$H:$H,'1.BS (VND)'!$D13)-SUMIFS('1.DC_Ra soat'!$L:$L,'1.DC_Ra soat'!$F:$F,AK$4,'1.DC_Ra soat'!$I:$I,'1.BS (VND)'!$D13) -> 0 | AL13: =SUMIFS('1.DC_Ra soat'!$L:$L,'1.DC_Ra soat'!$F:$F,AL$4,'1.DC_Ra soat'!$H:$H,'1.BS (VND)'!$D13)-SUMIFS('1.DC_Ra soat'!$L:$L,'1.DC_Ra soat'!$F:$F,AL$4,'1.DC_Ra soat'!$I:$I,'1.BS (VND)'!$D13) -> 0 | AN13: =SUMIFS('1.DC_Ra soat'!$L:$L,'1.DC_Ra soat'!$F:$F,AN$4,'1.DC_Ra soat'!$H:$H,'1.BS (VND)'!$D13)-SUMIFS('1.DC_Ra soat'!$L:$L,'1.DC_Ra soat'!$F:$F,AN$4,'1.DC_Ra soat'!$I:$I,'1.BS (VND)'!$D13) -> 0 | AO13: =SUMIFS('1.DC_Ra soat'!$L:$L,'1.DC_Ra soat'!$F:$F,AO$4,'1.DC_Ra soat'!$H:$H,'1.BS (VND)'!$D13)-SUMIFS('1.DC_Ra soat'!$L:$L,'1.DC_Ra soat'!$F:$F,AO$4,'1.DC_Ra soat'!$I:$I,'1.BS (VND)'!$D13) -> 0 | AP13: =SUMIFS('1.DC_Ra soat'!$L:$L,'1.DC_Ra soat'!$F:$F,AP$4,'1.DC_Ra soat'!$H:$H,'1.BS (VND)'!$D13)-SUMIFS('1.DC_Ra soat'!$L:$L,'1.DC_Ra soat'!$F:$F,AP$4,'1.DC_Ra soat'!$I:$I,'1.BS (VND)'!$D13) -> 0 | AQ13: =SUMIFS('1.DC_Ra soat'!$L:$L,'1.DC_Ra soat'!$F:$F,AQ$4,'1.DC_Ra soat'!$H:$H,'1.BS (VND)'!$D13)-SUMIFS('1.DC_Ra soat'!$L:$L,'1.DC_Ra soat'!$F:$F,AQ$4,'1.DC_Ra soat'!$I:$I,'1.BS (VND)'!$D13) -> 0 | AS13: =SUMIFS('1.DC_Ra soat'!$L:$L,'1.DC_Ra soat'!$F:$F,AS$4,'1.DC_Ra soat'!$H:$H,'1.BS (VND)'!$D13)-SUMIFS('1.DC_Ra soat'!$L:$L,'1.DC_Ra soat'!$F:$F,AS$4,'1.DC_Ra soat'!$I:$I,'1.BS (VND)'!$D13) -> 0 | AT13: =SUMIFS('1.DC_Ra soat'!$L:$L,'1.DC_Ra soat'!$F:$F,AT$4,'1.DC_Ra soat'!$H:$H,'1.BS (VND)'!$D13)-SUMIFS('1.DC_Ra soat'!$L:$L,'1.DC_Ra soat'!$F:$F,AT$4,'1.DC_Ra soat'!$I:$I,'1.BS (VND)'!$D13) -> 0 | AU13: =SUMIFS('1.DC_Ra soat'!$L:$L,'1.DC_Ra soat'!$F:$F,AU$4,'1.DC_Ra soat'!$H:$H,'1.BS (VND)'!$D13)-SUMIFS('1.DC_Ra soat'!$L:$L,'1.DC_Ra soat'!$F:$F,AU$4,'1.DC_Ra soat'!$I:$I,'1.BS (VND)'!$D13) -> 0 | AV13: =SUMIFS('1.DC_Ra soat'!$L:$L,'1.DC_Ra soat'!$F:$F,AV$4,'1.DC_Ra soat'!$H:$H,'1.BS (VND)'!$D13)-SUMIFS('1.DC_Ra soat'!$L:$L,'1.DC_Ra soat'!$F:$F,AV$4,'1.DC_Ra soat'!$I:$I,'1.BS (VND)'!$D13) -> 0 | AX13: =SUMIFS('1.DC_Ra soat'!$L:$L,'1.DC_Ra soat'!$F:$F,AX$4,'1.DC_Ra soat'!$H:$H,'1.BS (VND)'!$D13)-SUMIFS('1.DC_Ra soat'!$L:$L,'1.DC_Ra soat'!$F:$F,AX$4,'1.DC_Ra soat'!$I:$I,'1.BS (VND)'!$D13) -> 0 | AY13: =SUMIFS('1.DC_Ra soat'!$L:$L,'1.DC_Ra soat'!$F:$F,'1.PL (VND) '!BD$4,'1.DC_Ra soat'!$H:$H,'1.BS (VND)'!$D13)-SUMIFS('1.DC_Ra soat'!$L:$L,'1.DC_Ra soat'!$F:$F,'1.PL (VND) '!BD$4,'1.DC_Ra soat'!$I:$I,'1.BS (VND)'!$D13) -> 0 | AZ13: =SUMIFS('1.DC_Ra soat'!$L:$L,'1.DC_Ra soat'!$F:$F,'1.PL (VND) '!BE$4,'1.DC_Ra soat'!$H:$H,'1.BS (VND)'!$D13)-SUMIFS('1.DC_Ra soat'!$L:$L,'1.DC_Ra soat'!$F:$F,'1.PL (VND) '!BE$4,'1.DC_Ra soat'!$I:$I,'1.BS (VND)'!$D13) -> 0 | BA13: =SUMIFS('1.DC_Ra soat'!$L:$L,'1.DC_Ra soat'!$F:$F,'1.PL (VND) '!BF$4,'1.DC_Ra soat'!$H:$H,'1.BS (VND)'!$D13)-SUMIFS('1.DC_Ra soat'!$L:$L,'1.DC_Ra soat'!$F:$F,'1.PL (VND) '!BF$4,'1.DC_Ra soat'!$I:$I,'1.BS (VND)'!$D13) -> 0 | BC13: =SUMIFS('1.DC_Ra soat'!$L:$L,'1.DC_Ra soat'!$F:$F,'1.PL (VND) '!BI$4,'1.DC_Ra soat'!$H:$H,'1.BS (VND)'!$D13)-SUMIFS('1.DC_Ra soat'!$L:$L,'1.DC_Ra soat'!$F:$F,'1.PL (VND) '!BI$4,'1.DC_Ra soat'!$I:$I,'1.BS (VND)'!$D13) -> 0 | BD13: =SUMIFS('1.DC_Ra soat'!$L:$L,'1.DC_Ra soat'!$F:$F,'1.PL (VND) '!BJ$4,'1.DC_Ra soat'!$H:$H,'1.BS (VND)'!$D13)-SUMIFS('1.DC_Ra soat'!$L:$L,'1.DC_Ra soat'!$F:$F,'1.PL (VND) '!BJ$4,'1.DC_Ra soat'!$I:$I,'1.BS (VND)'!$D13) -> 0 | BE13: =SUMIFS('1.DC_Ra soat'!$L:$L,'1.DC_Ra soat'!$F:$F,'1.PL (VND) '!BK$4,'1.DC_Ra soat'!$H:$H,'1.BS (VND)'!$D13)-SUMIFS('1.DC_Ra soat'!$L:$L,'1.DC_Ra soat'!$F:$F,'1.PL (VND) '!BK$4,'1.DC_Ra soat'!$I:$I,'1.BS (VND)'!$D13) -> 0 | BF13: =SUMIFS('1.DC_Ra soat'!$L:$L,'1.DC_Ra soat'!$F:$F,'1.PL (VND) '!BL$4,'1.DC_Ra soat'!$H:$H,'1.BS (VND)'!$D13)-SUMIFS('1.DC_Ra soat'!$L:$L,'1.DC_Ra soat'!$F:$F,'1.PL (VND) '!BL$4,'1.DC_Ra soat'!$I:$I,'1.BS (VND)'!$D13) -> 0 | BH13: =SUMIFS('1.DC_Ra soat'!$L:$L,'1.DC_Ra soat'!$F:$F,'1.PL (VND) '!BO$4,'1.DC_Ra soat'!$H:$H,'1.BS (VND)'!$D13)-SUMIFS('1.DC_Ra soat'!$L:$L,'1.DC_Ra soat'!$F:$F,'1.PL (VND) '!BO$4,'1.DC_Ra soat'!$I:$I,'1.BS (VND)'!$D13) -> 0 | BI13: =SUMIFS('1.DC_Ra soat'!$L:$L,'1.DC_Ra soat'!$F:$F,'1.PL (VND) '!BP$4,'1.DC_Ra soat'!$H:$H,'1.BS (VND)'!$D13)-SUMIFS('1.DC_Ra soat'!$L:$L,'1.DC_Ra soat'!$F:$F,'1.PL (VND) '!BP$4,'1.DC_Ra soat'!$I:$I,'1.BS (VND)'!$D13) -> 0 | BJ13: =SUMIFS('1.DC_Ra soat'!$L:$L,'1.DC_Ra soat'!$F:$F,'1.PL (VND) '!BQ$4,'1.DC_Ra soat'!$H:$H,'1.BS (VND)'!$D13)-SUMIFS('1.DC_Ra soat'!$L:$L,'1.DC_Ra soat'!$F:$F,'1.PL (VND) '!BQ$4,'1.DC_Ra soat'!$I:$I,'1.BS (VND)'!$D13) -> 0 | BK13: =SUMIFS('1.DC_Ra soat'!$L:$L,'1.DC_Ra soat'!$F:$F,'1.PL (VND) '!BR$4,'1.DC_Ra soat'!$H:$H,'1.BS (VND)'!$D13)-SUMIFS('1.DC_Ra soat'!$L:$L,'1.DC_Ra soat'!$F:$F,'1.PL (VND) '!BR$4,'1.DC_Ra soat'!$I:$I,'1.BS (VND)'!$D13) -> 0 | BM13: =E13+AI13 -> 0 | BN13: =F13+AJ13 -> 0 | BO13: =G13+AK13 -> 0 | BP13: =H13+AL13 -> 0 | BR13: =J13+AN13 -> 0 | BS13: =K13+AO13 -> 0 | BT13: =L13+AP13 -> 0 | BU13: =M13+AQ13 -> 0 | BW13: =O13+AS13 -> 0 | BX13: =P13+AT13 -> 0 | BY13: =Q13+AU13 -> 0 | BZ13: =R13+AV13 -> 0 | CB13: =T13+AX13 -> 0 | CC13: =U13+AY13 -> 0 | CD13: =V13+AZ13 -> 0 | CE13: =W13+BA13 -> 0 | CG13: =Y13+BC13 -> 0 | CH13: =Z13+BD13 -> 0 | CI13: =AA13+BE13 -> 0 | CJ13: =AB13+BF13 -> 0 | CL13: =AD13+BH13 -> 0 | CM13: =AE13+BI13 -> 0 | CN13: =AF13+BJ13 -> 0 | CO13: =AG13+BK13 -> 0 | CQ13: =SUMIF('1.PL (VND) '!$BL$6:$CD$6,'1.PL (VND) '!CP$6,$BM13:$CE13) -> 0 | CR13: =SUMIF('1.PL (VND) '!$BL$6:$CD$6,'1.PL (VND) '!CQ$6,$BM13:$CE13) -> 0 | CS13: =SUMIF('1.PL (VND) '!$BL$6:$CD$6,'1.PL (VND) '!CR$6,$BM13:$CE13) -> 0 | CT13: =SUMIF('1.PL (VND) '!$BL$6:$CD$6,'1.PL (VND) '!CS$6,$BM13:$CE13) -> 0 | CV13: =-SUMIFS('1.DC_Ra soat'!$L:$L,'1.DC_Ra soat'!$F:$F,'1.PL (VND) '!DK$4,'1.DC_Ra soat'!$H:$H,'1.BS (VND)'!$D13)+SUMIFS('1.DC_Ra soat'!$L:$L,'1.DC_Ra soat'!$F:$F,'1.PL (VND) '!DK$4,'1.DC_Ra soat'!$I:$I,'1.BS (VND)'!$D13) -> 0 | CW13: =-SUMIFS('1.DC_Ra soat'!$L:$L,'1.DC_Ra soat'!$F:$F,'1.PL (VND) '!DL$4,'1.DC_Ra soat'!$H:$H,'1.BS (VND)'!$D13)+SUMIFS('1.DC_Ra soat'!$L:$L,'1.DC_Ra soat'!$F:$F,'1.PL (VND) '!DL$4,'1.DC_Ra soat'!$I:$I,'1.BS (VND)'!$D13) -> 0 | CX13: =-SUMIFS('1.DC_Ra soat'!$L:$L,'1.DC_Ra soat'!$F:$F,'1.PL (VND) '!DM$4,'1.DC_Ra soat'!$H:$H,'1.BS (VND)'!$D13)+SUMIFS('1.DC_Ra soat'!$L:$L,'1.DC_Ra soat'!$F:$F,'1.PL (VND) '!DM$4,'1.DC_Ra soat'!$I:$I,'1.BS (VND)'!$D13) -> 0 | CY13: =-SUMIFS('1.DC_Ra soat'!$L:$L,'1.DC_Ra soat'!$F:$F,'1.PL (VND) '!DN$4,'1.DC_Ra soat'!$H:$H,'1.BS (VND)'!$D13)+SUMIFS('1.DC_Ra soat'!$L:$L,'1.DC_Ra soat'!$F:$F,'1.PL (VND) '!DN$4,'1.DC_Ra soat'!$I:$I,'1.BS (VND)'!$D13) -> 0 | DA13: =CQ13+CV13 -> 0 | DB13: =CR13+CW13 -> 0 | DC13: =CS13+CX13 -> 0 | DD13: =CT13+CY13 -> 0
A14: =IF(SUM(E14:DD14)<>0,1,"hide") -> hide | C14: 2. Dự phòng giảm giá chứng khoán kinh doanh (*) | D14: 122 | M14: 0 | AI14: =SUMIFS('1.DC_Ra soat'!$L:$L,'1.DC_Ra soat'!$F:$F,AI$4,'1.DC_Ra soat'!$H:$H,'1.BS (VND)'!$D14)-SUMIFS('1.DC_Ra soat'!$L:$L,'1.DC_Ra soat'!$F:$F,AI$4,'1.DC_Ra soat'!$I:$I,'1.BS (VND)'!$D14) -> 0 | AJ14: =SUMIFS('1.DC_Ra soat'!$L:$L,'1.DC_Ra soat'!$F:$F,AJ$4,'1.DC_Ra soat'!$H:$H,'1.BS (VND)'!$D14)-SUMIFS('1.DC_Ra soat'!$L:$L,'1.DC_Ra soat'!$F:$F,AJ$4,'1.DC_Ra soat'!$I:$I,'1.BS (VND)'!$D14) -> 0 | AK14: =SUMIFS('1.DC_Ra soat'!$L:$L,'1.DC_Ra soat'!$F:$F,AK$4,'1.DC_Ra soat'!$H:$H,'1.BS (VND)'!$D14)-SUMIFS('1.DC_Ra soat'!$L:$L,'1.DC_Ra soat'!$F:$F,AK$4,'1.DC_Ra soat'!$I:$I,'1.BS (VND)'!$D14) -> 0 | AL14: =SUMIFS('1.DC_Ra soat'!$L:$L,'1.DC_Ra soat'!$F:$F,AL$4,'1.DC_Ra soat'!$H:$H,'1.BS (VND)'!$D14)-SUMIFS('1.DC_Ra soat'!$L:$L,'1.DC_Ra soat'!$F:$F,AL$4,'1.DC_Ra soat'!$I:$I,'1.BS (VND)'!$D14) -> 0 | AN14: =SUMIFS('1.DC_Ra soat'!$L:$L,'1.DC_Ra soat'!$F:$F,AN$4,'1.DC_Ra soat'!$H:$H,'1.BS (VND)'!$D14)-SUMIFS('1.DC_Ra soat'!$L:$L,'1.DC_Ra soat'!$F:$F,AN$4,'1.DC_Ra soat'!$I:$I,'1.BS (VND)'!$D14) -> 0 | AO14: =SUMIFS('1.DC_Ra soat'!$L:$L,'1.DC_Ra soat'!$F:$F,AO$4,'1.DC_Ra soat'!$H:$H,'1.BS (VND)'!$D14)-SUMIFS('1.DC_Ra soat'!$L:$L,'1.DC_Ra soat'!$F:$F,AO$4,'1.DC_Ra soat'!$I:$I,'1.BS (VND)'!$D14) -> 0 | AP14: =SUMIFS('1.DC_Ra soat'!$L:$L,'1.DC_Ra soat'!$F:$F,AP$4,'1.DC_Ra soat'!$H:$H,'1.BS (VND)'!$D14)-SUMIFS('1.DC_Ra soat'!$L:$L,'1.DC_Ra soat'!$F:$F,AP$4,'1.DC_Ra soat'!$I:$I,'1.BS (VND)'!$D14) -> 0 | AQ14: =SUMIFS('1.DC_Ra soat'!$L:$L,'1.DC_Ra soat'!$F:$F,AQ$4,'1.DC_Ra soat'!$H:$H,'1.BS (VND)'!$D14)-SUMIFS('1.DC_Ra soat'!$L:$L,'1.DC_Ra soat'!$F:$F,AQ$4,'1.DC_Ra soat'!$I:$I,'1.BS (VND)'!$D14) -> 0 | AS14: =SUMIFS('1.DC_Ra soat'!$L:$L,'1.DC_Ra soat'!$F:$F,AS$4,'1.DC_Ra soat'!$H:$H,'1.BS (VND)'!$D14)-SUMIFS('1.DC_Ra soat'!$L:$L,'1.DC_Ra soat'!$F:$F,AS$4,'1.DC_Ra soat'!$I:$I,'1.BS (VND)'!$D14) -> 0 | AT14: =SUMIFS('1.DC_Ra soat'!$L:$L,'1.DC_Ra soat'!$F:$F,AT$4,'1.DC_Ra soat'!$H:$H,'1.BS (VND)'!$D14)-SUMIFS('1.DC_Ra soat'!$L:$L,'1.DC_Ra soat'!$F:$F,AT$4,'1.DC_Ra soat'!$I:$I,'1.BS (VND)'!$D14) -> 0 | AU14: =SUMIFS('1.DC_Ra soat'!$L:$L,'1.DC_Ra soat'!$F:$F,AU$4,'1.DC_Ra soat'!$H:$H,'1.BS (VND)'!$D14)-SUMIFS('1.DC_Ra soat'!$L:$L,'1.DC_Ra soat'!$F:$F,AU$4,'1.DC_Ra soat'!$I:$I,'1.BS (VND)'!$D14) -> 0 | AV14: =SUMIFS('1.DC_Ra soat'!$L:$L,'1.DC_Ra soat'!$F:$F,AV$4,'1.DC_Ra soat'!$H:$H,'1.BS (VND)'!$D14)-SUMIFS('1.DC_Ra soat'!$L:$L,'1.DC_Ra soat'!$F:$F,AV$4,'1.DC_Ra soat'!$I:$I,'1.BS (VND)'!$D14) -> 0 | AX14: =SUMIFS('1.DC_Ra soat'!$L:$L,'1.DC_Ra soat'!$F:$F,AX$4,'1.DC_Ra soat'!$H:$H,'1.BS (VND)'!$D14)-SUMIFS('1.DC_Ra soat'!$L:$L,'1.DC_Ra soat'!$F:$F,AX$4,'1.DC_Ra soat'!$I:$I,'1.BS (VND)'!$D14) -> 0 | AY14: =SUMIFS('1.DC_Ra soat'!$L:$L,'1.DC_Ra soat'!$F:$F,'1.PL (VND) '!BD$4,'1.DC_Ra soat'!$H:$H,'1.BS (VND)'!$D14)-SUMIFS('1.DC_Ra soat'!$L:$L,'1.DC_Ra soat'!$F:$F,'1.PL (VND) '!BD$4,'1.DC_Ra soat'!$I:$I,'1.BS (VND)'!$D14) -> 0 | AZ14: =SUMIFS('1.DC_Ra soat'!$L:$L,'1.DC_Ra soat'!$F:$F,'1.PL (VND) '!BE$4,'1.DC_Ra soat'!$H:$H,'1.BS (VND)'!$D14)-SUMIFS('1.DC_Ra soat'!$L:$L,'1.DC_Ra soat'!$F:$F,'1.PL (VND) '!BE$4,'1.DC_Ra soat'!$I:$I,'1.BS (VND)'!$D14) -> 0 | BA14: =SUMIFS('1.DC_Ra soat'!$L:$L,'1.DC_Ra soat'!$F:$F,'1.PL (VND) '!BF$4,'1.DC_Ra soat'!$H:$H,'1.BS (VND)'!$D14)-SUMIFS('1.DC_Ra soat'!$L:$L,'1.DC_Ra soat'!$F:$F,'1.PL (VND) '!BF$4,'1.DC_Ra soat'!$I:$I,'1.BS (VND)'!$D14) -> 0 | BC14: =SUMIFS('1.DC_Ra soat'!$L:$L,'1.DC_Ra soat'!$F:$F,'1.PL (VND) '!BI$4,'1.DC_Ra soat'!$H:$H,'1.BS (VND)'!$D14)-SUMIFS('1.DC_Ra soat'!$L:$L,'1.DC_Ra soat'!$F:$F,'1.PL (VND) '!BI$4,'1.DC_Ra soat'!$I:$I,'1.BS (VND)'!$D14) -> 0 | BD14: =SUMIFS('1.DC_Ra soat'!$L:$L,'1.DC_Ra soat'!$F:$F,'1.PL (VND) '!BJ$4,'1.DC_Ra soat'!$H:$H,'1.BS (VND)'!$D14)-SUMIFS('1.DC_Ra soat'!$L:$L,'1.DC_Ra soat'!$F:$F,'1.PL (VND) '!BJ$4,'1.DC_Ra soat'!$I:$I,'1.BS (VND)'!$D14) -> 0 | BE14: =SUMIFS('1.DC_Ra soat'!$L:$L,'1.DC_Ra soat'!$F:$F,'1.PL (VND) '!BK$4,'1.DC_Ra soat'!$H:$H,'1.BS (VND)'!$D14)-SUMIFS('1.DC_Ra soat'!$L:$L,'1.DC_Ra soat'!$F:$F,'1.PL (VND) '!BK$4,'1.DC_Ra soat'!$I:$I,'1.BS (VND)'!$D14) -> 0 | BF14: =SUMIFS('1.DC_Ra soat'!$L:$L,'1.DC_Ra soat'!$F:$F,'1.PL (VND) '!BL$4,'1.DC_Ra soat'!$H:$H,'1.BS (VND)'!$D14)-SUMIFS('1.DC_Ra soat'!$L:$L,'1.DC_Ra soat'!$F:$F,'1.PL (VND) '!BL$4,'1.DC_Ra soat'!$I:$I,'1.BS (VND)'!$D14) -> 0 | BH14: =SUMIFS('1.DC_Ra soat'!$L:$L,'1.DC_Ra soat'!$F:$F,'1.PL (VND) '!BO$4,'1.DC_Ra soat'!$H:$H,'1.BS (VND)'!$D14)-SUMIFS('1.DC_Ra soat'!$L:$L,'1.DC_Ra soat'!$F:$F,'1.PL (VND) '!BO$4,'1.DC_Ra soat'!$I:$I,'1.BS (VND)'!$D14) -> 0 | BI14: =SUMIFS('1.DC_Ra soat'!$L:$L,'1.DC_Ra soat'!$F:$F,'1.PL (VND) '!BP$4,'1.DC_Ra soat'!$H:$H,'1.BS (VND)'!$D14)-SUMIFS('1.DC_Ra soat'!$L:$L,'1.DC_Ra soat'!$F:$F,'1.PL (VND) '!BP$4,'1.DC_Ra soat'!$I:$I,'1.BS (VND)'!$D14) -> 0 | BJ14: =SUMIFS('1.DC_Ra soat'!$L:$L,'1.DC_Ra soat'!$F:$F,'1.PL (VND) '!BQ$4,'1.DC_Ra soat'!$H:$H,'1.BS (VND)'!$D14)-SUMIFS('1.DC_Ra soat'!$L:$L,'1.DC_Ra soat'!$F:$F,'1.PL (VND) '!BQ$4,'1.DC_Ra soat'!$I:$I,'1.BS (VND)'!$D14) -> 0 | BK14: =SUMIFS('1.DC_Ra soat'!$L:$L,'1.DC_Ra soat'!$F:$F,'1.PL (VND) '!BR$4,'1.DC_Ra soat'!$H:$H,'1.BS (VND)'!$D14)-SUMIFS('1.DC_Ra soat'!$L:$L,'1.DC_Ra soat'!$F:$F,'1.PL (VND) '!BR$4,'1.DC_Ra soat'!$I:$I,'1.BS (VND)'!$D14) -> 0 | BM14: =E14+AI14 -> 0 | BN14: =F14+AJ14 -> 0 | BO14: =G14+AK14 -> 0 | BP14: =H14+AL14 -> 0 | BR14: =J14+AN14 -> 0 | BS14: =K14+AO14 -> 0 | BT14: =L14+AP14 -> 0 | BU14: =M14+AQ14 -> 0 | BW14: =O14+AS14 -> 0 | BX14: =P14+AT14 -> 0 | BY14: =Q14+AU14 -> 0 | BZ14: =R14+AV14 -> 0 | CB14: =T14+AX14 -> 0 | CC14: =U14+AY14 -> 0 | CD14: =V14+AZ14 -> 0 | CE14: =W14+BA14 -> 0 | CG14: =Y14+BC14 -> 0 | CH14: =Z14+BD14 -> 0 | CI14: =AA14+BE14 -> 0 | CJ14: =AB14+BF14 -> 0 | CL14: =AD14+BH14 -> 0 | CM14: =AE14+BI14 -> 0 | CN14: =AF14+BJ14 -> 0 | CO14: =AG14+BK14 -> 0 | CQ14: =SUMIF('1.PL (VND) '!$BL$6:$CD$6,'1.PL (VND) '!CP$6,$BM14:$CE14) -> 0 | CR14: =SUMIF('1.PL (VND) '!$BL$6:$CD$6,'1.PL (VND) '!CQ$6,$BM14:$CE14) -> 0 | CS14: =SUMIF('1.PL (VND) '!$BL$6:$CD$6,'1.PL (VND) '!CR$6,$BM14:$CE14) -> 0 | CT14: =SUMIF('1.PL (VND) '!$BL$6:$CD$6,'1.PL (VND) '!CS$6,$BM14:$CE14) -> 0 | CV14: =-SUMIFS('1.DC_Ra soat'!$L:$L,'1.DC_Ra soat'!$F:$F,'1.PL (VND) '!DK$4,'1.DC_Ra soat'!$H:$H,'1.BS (VND)'!$D14)+SUMIFS('1.DC_Ra soat'!$L:$L,'1.DC_Ra soat'!$F:$F,'1.PL (VND) '!DK$4,'1.DC_Ra soat'!$I:$I,'1.BS (VND)'!$D14) -> 0 | CW14: =-SUMIFS('1.DC_Ra soat'!$L:$L,'1.DC_Ra soat'!$F:$F,'1.PL (VND) '!DL$4,'1.DC_Ra soat'!$H:$H,'1.BS (VND)'!$D14)+SUMIFS('1.DC_Ra soat'!$L:$L,'1.DC_Ra soat'!$F:$F,'1.PL (VND) '!DL$4,'1.DC_Ra soat'!$I:$I,'1.BS (VND)'!$D14) -> 0 | CX14: =-SUMIFS('1.DC_Ra soat'!$L:$L,'1.DC_Ra soat'!$F:$F,'1.PL (VND) '!DM$4,'1.DC_Ra soat'!$H:$H,'1.BS (VND)'!$D14)+SUMIFS('1.DC_Ra soat'!$L:$L,'1.DC_Ra soat'!$F:$F,'1.PL (VND) '!DM$4,'1.DC_Ra soat'!$I:$I,'1.BS (VND)'!$D14) -> 0 | CY14: =-SUMIFS('1.DC_Ra soat'!$L:$L,'1.DC_Ra soat'!$F:$F,'1.PL (VND) '!DN$4,'1.DC_Ra soat'!$H:$H,'1.BS (VND)'!$D14)+SUMIFS('1.DC_Ra soat'!$L:$L,'1.DC_Ra soat'!$F:$F,'1.PL (VND) '!DN$4,'1.DC_Ra soat'!$I:$I,'1.BS (VND)'!$D14) -> 0 | DA14: =CQ14+CV14 -> 0 | DB14: =CR14+CW14 -> 0 | DC14: =CS14+CX14 -> 0 | DD14: =CT14+CY14 -> 0
A15: =IF(SUM(E15:DD15)<>0,1,"hide") -> hide | C15: 3. Đầu tư nắm giữ đến ngày đáo hạn | D15: 123 | M15: 0 | AI15: =SUMIFS('1.DC_Ra soat'!$L:$L,'1.DC_Ra soat'!$F:$F,AI$4,'1.DC_Ra soat'!$H:$H,'1.BS (VND)'!$D15)-SUMIFS('1.DC_Ra soat'!$L:$L,'1.DC_Ra soat'!$F:$F,AI$4,'1.DC_Ra soat'!$I:$I,'1.BS (VND)'!$D15) -> 0 | AJ15: =SUMIFS('1.DC_Ra soat'!$L:$L,'1.DC_Ra soat'!$F:$F,AJ$4,'1.DC_Ra soat'!$H:$H,'1.BS (VND)'!$D15)-SUMIFS('1.DC_Ra soat'!$L:$L,'1.DC_Ra soat'!$F:$F,AJ$4,'1.DC_Ra soat'!$I:$I,'1.BS (VND)'!$D15) -> 0 | AK15: =SUMIFS('1.DC_Ra soat'!$L:$L,'1.DC_Ra soat'!$F:$F,AK$4,'1.DC_Ra soat'!$H:$H,'1.BS (VND)'!$D15)-SUMIFS('1.DC_Ra soat'!$L:$L,'1.DC_Ra soat'!$F:$F,AK$4,'1.DC_Ra soat'!$I:$I,'1.BS (VND)'!$D15) -> 0 | AL15: =SUMIFS('1.DC_Ra soat'!$L:$L,'1.DC_Ra soat'!$F:$F,AL$4,'1.DC_Ra soat'!$H:$H,'1.BS (VND)'!$D15)-SUMIFS('1.DC_Ra soat'!$L:$L,'1.DC_Ra soat'!$F:$F,AL$4,'1.DC_Ra soat'!$I:$I,'1.BS (VND)'!$D15) -> 0 | AN15: =SUMIFS('1.DC_Ra soat'!$L:$L,'1.DC_Ra soat'!$F:$F,AN$4,'1.DC_Ra soat'!$H:$H,'1.BS (VND)'!$D15)-SUMIFS('1.DC_Ra soat'!$L:$L,'1.DC_Ra soat'!$F:$F,AN$4,'1.DC_Ra soat'!$I:$I,'1.BS (VND)'!$D15) -> 0 | AO15: =SUMIFS('1.DC_Ra soat'!$L:$L,'1.DC_Ra soat'!$F:$F,AO$4,'1.DC_Ra soat'!$H:$H,'1.BS (VND)'!$D15)-SUMIFS('1.DC_Ra soat'!$L:$L,'1.DC_Ra soat'!$F:$F,AO$4,'1.DC_Ra soat'!$I:$I,'1.BS (VND)'!$D15) -> 0 | AP15: =SUMIFS('1.DC_Ra soat'!$L:$L,'1.DC_Ra soat'!$F:$F,AP$4,'1.DC_Ra soat'!$H:$H,'1.BS (VND)'!$D15)-SUMIFS('1.DC_Ra soat'!$L:$L,'1.DC_Ra soat'!$F:$F,AP$4,'1.DC_Ra soat'!$I:$I,'1.BS (VND)'!$D15) -> 0 | AQ15: =SUMIFS('1.DC_Ra soat'!$L:$L,'1.DC_Ra soat'!$F:$F,AQ$4,'1.DC_Ra soat'!$H:$H,'1.BS (VND)'!$D15)-SUMIFS('1.DC_Ra soat'!$L:$L,'1.DC_Ra soat'!$F:$F,AQ$4,'1.DC_Ra soat'!$I:$I,'1.BS (VND)'!$D15) -> 0 | AS15: =SUMIFS('1.DC_Ra soat'!$L:$L,'1.DC_Ra soat'!$F:$F,AS$4,'1.DC_Ra soat'!$H:$H,'1.BS (VND)'!$D15)-SUMIFS('1.DC_Ra soat'!$L:$L,'1.DC_Ra soat'!$F:$F,AS$4,'1.DC_Ra soat'!$I:$I,'1.BS (VND)'!$D15) -> 0 | AT15: =SUMIFS('1.DC_Ra soat'!$L:$L,'1.DC_Ra soat'!$F:$F,AT$4,'1.DC_Ra soat'!$H:$H,'1.BS (VND)'!$D15)-SUMIFS('1.DC_Ra soat'!$L:$L,'1.DC_Ra soat'!$F:$F,AT$4,'1.DC_Ra soat'!$I:$I,'1.BS (VND)'!$D15) -> 0 | AU15: =SUMIFS('1.DC_Ra soat'!$L:$L,'1.DC_Ra soat'!$F:$F,AU$4,'1.DC_Ra soat'!$H:$H,'1.BS (VND)'!$D15)-SUMIFS('1.DC_Ra soat'!$L:$L,'1.DC_Ra soat'!$F:$F,AU$4,'1.DC_Ra soat'!$I:$I,'1.BS (VND)'!$D15) -> 0 | AV15: =SUMIFS('1.DC_Ra soat'!$L:$L,'1.DC_Ra soat'!$F:$F,AV$4,'1.DC_Ra soat'!$H:$H,'1.BS (VND)'!$D15)-SUMIFS('1.DC_Ra soat'!$L:$L,'1.DC_Ra soat'!$F:$F,AV$4,'1.DC_Ra soat'!$I:$I,'1.BS (VND)'!$D15) -> 0 | AX15: =SUMIFS('1.DC_Ra soat'!$L:$L,'1.DC_Ra soat'!$F:$F,AX$4,'1.DC_Ra soat'!$H:$H,'1.BS (VND)'!$D15)-SUMIFS('1.DC_Ra soat'!$L:$L,'1.DC_Ra soat'!$F:$F,AX$4,'1.DC_Ra soat'!$I:$I,'1.BS (VND)'!$D15) -> 0 | AY15: =SUMIFS('1.DC_Ra soat'!$L:$L,'1.DC_Ra soat'!$F:$F,'1.PL (VND) '!BD$4,'1.DC_Ra soat'!$H:$H,'1.BS (VND)'!$D15)-SUMIFS('1.DC_Ra soat'!$L:$L,'1.DC_Ra soat'!$F:$F,'1.PL (VND) '!BD$4,'1.DC_Ra soat'!$I:$I,'1.BS (VND)'!$D15) -> 0 | AZ15: =SUMIFS('1.DC_Ra soat'!$L:$L,'1.DC_Ra soat'!$F:$F,'1.PL (VND) '!BE$4,'1.DC_Ra soat'!$H:$H,'1.BS (VND)'!$D15)-SUMIFS('1.DC_Ra soat'!$L:$L,'1.DC_Ra soat'!$F:$F,'1.PL (VND) '!BE$4,'1.DC_Ra soat'!$I:$I,'1.BS (VND)'!$D15) -> 0 | BA15: =SUMIFS('1.DC_Ra soat'!$L:$L,'1.DC_Ra soat'!$F:$F,'1.PL (VND) '!BF$4,'1.DC_Ra soat'!$H:$H,'1.BS (VND)'!$D15)-SUMIFS('1.DC_Ra soat'!$L:$L,'1.DC_Ra soat'!$F:$F,'1.PL (VND) '!BF$4,'1.DC_Ra soat'!$I:$I,'1.BS (VND)'!$D15) -> 0 | BC15: =SUMIFS('1.DC_Ra soat'!$L:$L,'1.DC_Ra soat'!$F:$F,'1.PL (VND) '!BI$4,'1.DC_Ra soat'!$H:$H,'1.BS (VND)'!$D15)-SUMIFS('1.DC_Ra soat'!$L:$L,'1.DC_Ra soat'!$F:$F,'1.PL (VND) '!BI$4,'1.DC_Ra soat'!$I:$I,'1.BS (VND)'!$D15) -> 0 | BD15: =SUMIFS('1.DC_Ra soat'!$L:$L,'1.DC_Ra soat'!$F:$F,'1.PL (VND) '!BJ$4,'1.DC_Ra soat'!$H:$H,'1.BS (VND)'!$D15)-SUMIFS('1.DC_Ra soat'!$L:$L,'1.DC_Ra soat'!$F:$F,'1.PL (VND) '!BJ$4,'1.DC_Ra soat'!$I:$I,'1.BS (VND)'!$D15) -> 0 | BE15: =SUMIFS('1.DC_Ra soat'!$L:$L,'1.DC_Ra soat'!$F:$F,'1.PL (VND) '!BK$4,'1.DC_Ra soat'!$H:$H,'1.BS (VND)'!$D15)-SUMIFS('1.DC_Ra soat'!$L:$L,'1.DC_Ra soat'!$F:$F,'1.PL (VND) '!BK$4,'1.DC_Ra soat'!$I:$I,'1.BS (VND)'!$D15) -> 0 | BF15: =SUMIFS('1.DC_Ra soat'!$L:$L,'1.DC_Ra soat'!$F:$F,'1.PL (VND) '!BL$4,'1.DC_Ra soat'!$H:$H,'1.BS (VND)'!$D15)-SUMIFS('1.DC_Ra soat'!$L:$L,'1.DC_Ra soat'!$F:$F,'1.PL (VND) '!BL$4,'1.DC_Ra soat'!$I:$I,'1.BS (VND)'!$D15) -> 0 | BH15: =SUMIFS('1.DC_Ra soat'!$L:$L,'1.DC_Ra soat'!$F:$F,'1.PL (VND) '!BO$4,'1.DC_Ra soat'!$H:$H,'1.BS (VND)'!$D15)-SUMIFS('1.DC_Ra soat'!$L:$L,'1.DC_Ra soat'!$F:$F,'1.PL (VND) '!BO$4,'1.DC_Ra soat'!$I:$I,'1.BS (VND)'!$D15) -> 0 | BI15: =SUMIFS('1.DC_Ra soat'!$L:$L,'1.DC_Ra soat'!$F:$F,'1.PL (VND) '!BP$4,'1.DC_Ra soat'!$H:$H,'1.BS (VND)'!$D15)-SUMIFS('1.DC_Ra soat'!$L:$L,'1.DC_Ra soat'!$F:$F,'1.PL (VND) '!BP$4,'1.DC_Ra soat'!$I:$I,'1.BS (VND)'!$D15) -> 0 | BJ15: =SUMIFS('1.DC_Ra soat'!$L:$L,'1.DC_Ra soat'!$F:$F,'1.PL (VND) '!BQ$4,'1.DC_Ra soat'!$H:$H,'1.BS (VND)'!$D15)-SUMIFS('1.DC_Ra soat'!$L:$L,'1.DC_Ra soat'!$F:$F,'1.PL (VND) '!BQ$4,'1.DC_Ra soat'!$I:$I,'1.BS (VND)'!$D15) -> 0 | BK15: =SUMIFS('1.DC_Ra soat'!$L:$L,'1.DC_Ra soat'!$F:$F,'1.PL (VND) '!BR$4,'1.DC_Ra soat'!$H:$H,'1.BS (VND)'!$D15)-SUMIFS('1.DC_Ra soat'!$L:$L,'1.DC_Ra soat'!$F:$F,'1.PL (VND) '!BR$4,'1.DC_Ra soat'!$I:$I,'1.BS (VND)'!$D15) -> 0 | BM15: =E15+AI15 -> 0 | BN15: =F15+AJ15 -> 0 | BO15: =G15+AK15 -> 0 | BP15: =H15+AL15 -> 0 | BR15: =J15+AN15 -> 0 | BS15: =K15+AO15 -> 0 | BT15: =L15+AP15 -> 0 | BU15: =M15+AQ15 -> 0 | BW15: =O15+AS15 -> 0 | BX15: =P15+AT15 -> 0 | BY15: =Q15+AU15 -> 0 | BZ15: =R15+AV15 -> 0 | CB15: =T15+AX15 -> 0 | CC15: =U15+AY15 -> 0 | CD15: =V15+AZ15 -> 0 | CE15: =W15+BA15 -> 0 | CG15: =Y15+BC15 -> 0 | CH15: =Z15+BD15 -> 0 | CI15: =AA15+BE15 -> 0 | CJ15: =AB15+BF15 -> 0 | CL15: =AD15+BH15 -> 0 | CM15: =AE15+BI15 -> 0 | CN15: =AF15+BJ15 -> 0 | CO15: =AG15+BK15 -> 0 | CQ15: =SUMIF('1.PL (VND) '!$BL$6:$CD$6,'1.PL (VND) '!CP$6,$BM15:$CE15) -> 0 | CR15: =SUMIF('1.PL (VND) '!$BL$6:$CD$6,'1.PL (VND) '!CQ$6,$BM15:$CE15) -> 0 | CS15: =SUMIF('1.PL (VND) '!$BL$6:$CD$6,'1.PL (VND) '!CR$6,$BM15:$CE15) -> 0 | CT15: =SUMIF('1.PL (VND) '!$BL$6:$CD$6,'1.PL (VND) '!CS$6,$BM15:$CE15) -> 0 | CV15: =-SUMIFS('1.DC_Ra soat'!$L:$L,'1.DC_Ra soat'!$F:$F,'1.PL (VND) '!DK$4,'1.DC_Ra soat'!$H:$H,'1.BS (VND)'!$D15)+SUMIFS('1.DC_Ra soat'!$L:$L,'1.DC_Ra soat'!$F:$F,'1.PL (VND) '!DK$4,'1.DC_Ra soat'!$I:$I,'1.BS (VND)'!$D15) -> 0 | CW15: =-SUMIFS('1.DC_Ra soat'!$L:$L,'1.DC_Ra soat'!$F:$F,'1.PL (VND) '!DL$4,'1.DC_Ra soat'!$H:$H,'1.BS (VND)'!$D15)+SUMIFS('1.DC_Ra soat'!$L:$L,'1.DC_Ra soat'!$F:$F,'1.PL (VND) '!DL$4,'1.DC_Ra soat'!$I:$I,'1.BS (VND)'!$D15) -> 0 | CX15: =-SUMIFS('1.DC_Ra soat'!$L:$L,'1.DC_Ra soat'!$F:$F,'1.PL (VND) '!DM$4,'1.DC_Ra soat'!$H:$H,'1.BS (VND)'!$D15)+SUMIFS('1.DC_Ra soat'!$L:$L,'1.DC_Ra soat'!$F:$F,'1.PL (VND) '!DM$4,'1.DC_Ra soat'!$I:$I,'1.BS (VND)'!$D15) -> 0 | CY15: =-SUMIFS('1.DC_Ra soat'!$L:$L,'1.DC_Ra soat'!$F:$F,'1.PL (VND) '!DN$4,'1.DC_Ra soat'!$H:$H,'1.BS (VND)'!$D15)+SUMIFS('1.DC_Ra soat'!$L:$L,'1.DC_Ra soat'!$F:$F,'1.PL (VND) '!DN$4,'1.DC_Ra soat'!$I:$I,'1.BS (VND)'!$D15) -> 0 | DA15: =CQ15+CV15 -> 0 | DB15: =CR15+CW15 -> 0 | DC15: =CS15+CX15 -> 0 | DD15: =CT15+CY15 -> 0
A16: =IF(SUM(E16:DD16)<>0,1,"hide") -> 1 | C16: III. Các khoản phải thu ngắn hạn | D16: 130 | E16: =SUM(E17:E24) -> 97498763941 | F16: =SUM(F17:F24) -> 33835444196 | G16: =SUM(G17:G24) -> 36647695915 | H16: =H17+H18+H19+H20+H21+H22+H23+H24 -> 157234925762 | J16: =SUM(J17:J24) -> 280000 | K16: =SUM(K17:K24) -> 7841603472 | L16: =SUM(L17:L24) -> 13003454124 | M16: =SUM(M17:M24) -> 50668668330 | O16: =SUM(O17:O24) -> 42594784969 | P16: =SUM(P17:P24) -> 14981552601 | Q16: =SUM(Q17:Q24) -> 29281648146 | R16: =SUM(R17:R24) -> 33772683963 | T16: =SUM(T17:T24) -> 19088145881 | U16: =SUM(U17:U24) -> 13200431075 | V16: =SUM(V17:V24) -> 14547999516 | W16: =SUM(W17:W24) -> 50012927700 | Y16: =SUM(Y17:Y24) -> 0 | Z16: =SUM(Z17:Z24) -> 0 | AA16: =SUM(AA17:AA24) -> 0 | AD16: =SUM(AD17:AD24) -> 0 | AE16: =SUM(AE17:AE24) -> 0 | AF16: =SUM(AF17:AF24) -> 0 | AG16: =SUM(AG17:AG24) -> 0 | AI16: =SUM(AI17:AI24) -> 0 | AJ16: =SUM(AJ17:AJ24) -> 0 | AK16: =SUM(AK17:AK24) -> 0 | AL16: =SUM(AL17:AL24) -> -3550000000 | AN16: =SUM(AN17:AN24) -> 0 | AO16: =SUM(AO17:AO24) -> 0 | AP16: =SUM(AP17:AP24) -> 0 | AQ16: =SUM(AQ17:AQ24) -> 0 | AS16: =SUM(AS17:AS24) -> 0 | AT16: =SUM(AT17:AT24) -> 0 | AU16: =SUM(AU17:AU24) -> 0 | AV16: =SUM(AV17:AV24) -> -4950000000 | AX16: =SUM(AX17:AX24) -> 0 | AY16: =SUM(AY17:AY24) -> 0 | AZ16: =SUM(AZ17:AZ24) -> 0 | BA16: =SUM(BA17:BA24) -> -5000000000 | BC16: =SUM(BC17:BC24) -> 0 | BD16: =SUM(BD17:BD24) -> 0 | BE16: =SUM(BE17:BE24) -> 0 | BF16: =SUM(BF17:BF24) -> 0 | BH16: =SUM(BH17:BH24) -> 0 | BI16: =SUM(BI17:BI24) -> 0 | BJ16: =SUM(BJ17:BJ24) -> 0 | BK16: =SUM(BK17:BK24) -> 0 | BM16: =E16+AI16 -> 97498763941 | BN16: =F16+AJ16 -> 33835444196 | BO16: =G16+AK16 -> 36647695915 | BP16: =H16+AL16 -> 153684925762 | BR16: =J16+AN16 -> 280000 | BS16: =K16+AO16 -> 7841603472 | BT16: =L16+AP16 -> 13003454124 | BU16: =M16+AQ16 -> 50668668330 | BW16: =O16+AS16 -> 42594784969 | BX16: =P16+AT16 -> 14981552601 | BY16: =Q16+AU16 -> 29281648146 | BZ16: =R16+AV16 -> 28822683963 | CB16: =T16+AX16 -> 19088145881 | CC16: =U16+AY16 -> 13200431075 | CD16: =V16+AZ16 -> 14547999516 | CE16: =W16+BA16 -> 45012927700 | CG16: =Y16+BC16 -> 0 | CH16: =Z16+BD16 -> 0 | CI16: =AA16+BE16 -> 0 | CJ16: =AB16+BF16 -> 0 | CL16: =AD16+BH16 -> 0 | CM16: =AE16+BI16 -> 0 | CN16: =AF16+BJ16 -> 0 | CO16: =AG16+BK16 -> 0 | CQ16: =SUMIF('1.PL (VND) '!$BL$6:$CD$6,'1.PL (VND) '!CP$6,$BM16:$CE16) -> 159181974791 | CR16: =SUMIF('1.PL (VND) '!$BL$6:$CD$6,'1.PL (VND) '!CQ$6,$BM16:$CE16) -> 69859031344 | CS16: =SUMIF('1.PL (VND) '!$BL$6:$CD$6,'1.PL (VND) '!CR$6,$BM16:$CE16) -> 93480797701 | CT16: =SUMIF('1.PL (VND) '!$BL$6:$CD$6,'1.PL (VND) '!CS$6,$BM16:$CE16) -> 278189205755 | CV16: =SUM(CV17:CV24) -> 0 | CW16: =SUM(CW17:CW24) -> 0 | CX16: =SUM(CX17:CX24) -> 0 | CY16: =SUM(CY17:CY24) -> 0 | DA16: =CQ16+CV16 -> 159181974791 | DB16: =CR16+CW16 -> 69859031344 | DC16: =CS16+CX16 -> 93480797701 | DD16: =CT16+CY16 -> 278189205755
A17: =IF(SUM(E17:DD17)<>0,1,"hide") -> 1 | C17: 1. Phải thu ngắn hạn của khách hàng | D17: 131 | E17: 84240636025 | F17: 29286683582 | G17: 29625341610 | H17: 101833460095 | K17: 5268045366 | L17: 11812757297 | M17: 48957714647 | O17: 36968498262 | P17: 14799733171 | Q17: 29280642158 | R17: 33772674580 | T17: 17621052183 | U17: 13082433252 | V17: 14491580087 | W17: 33234622688 | AI17: =SUMIFS('1.DC_Ra soat'!$L:$L,'1.DC_Ra soat'!$F:$F,AI$4,'1.DC_Ra soat'!$H:$H,'1.BS (VND)'!$D17)-SUMIFS('1.DC_Ra soat'!$L:$L,'1.DC_Ra soat'!$F:$F,AI$4,'1.DC_Ra soat'!$I:$I,'1.BS (VND)'!$D17) -> 0 | AJ17: =SUMIFS('1.DC_Ra soat'!$L:$L,'1.DC_Ra soat'!$F:$F,AJ$4,'1.DC_Ra soat'!$H:$H,'1.BS (VND)'!$D17)-SUMIFS('1.DC_Ra soat'!$L:$L,'1.DC_Ra soat'!$F:$F,AJ$4,'1.DC_Ra soat'!$I:$I,'1.BS (VND)'!$D17) -> 0 | AK17: =SUMIFS('1.DC_Ra soat'!$L:$L,'1.DC_Ra soat'!$F:$F,AK$4,'1.DC_Ra soat'!$H:$H,'1.BS (VND)'!$D17)-SUMIFS('1.DC_Ra soat'!$L:$L,'1.DC_Ra soat'!$F:$F,AK$4,'1.DC_Ra soat'!$I:$I,'1.BS (VND)'!$D17) -> 0 | AL17: =SUMIFS('1.DC_Ra soat'!$L:$L,'1.DC_Ra soat'!$F:$F,AL$4,'1.DC_Ra soat'!$H:$H,'1.BS (VND)'!$D17)-SUMIFS('1.DC_Ra soat'!$L:$L,'1.DC_Ra soat'!$F:$F,AL$4,'1.DC_Ra soat'!$I:$I,'1.BS (VND)'!$D17) -> 0 | AN17: =SUMIFS('1.DC_Ra soat'!$L:$L,'1.DC_Ra soat'!$F:$F,AN$4,'1.DC_Ra soat'!$H:$H,'1.BS (VND)'!$D17)-SUMIFS('1.DC_Ra soat'!$L:$L,'1.DC_Ra soat'!$F:$F,AN$4,'1.DC_Ra soat'!$I:$I,'1.BS (VND)'!$D17) -> 0 | AO17: =SUMIFS('1.DC_Ra soat'!$L:$L,'1.DC_Ra soat'!$F:$F,AO$4,'1.DC_Ra soat'!$H:$H,'1.BS (VND)'!$D17)-SUMIFS('1.DC_Ra soat'!$L:$L,'1.DC_Ra soat'!$F:$F,AO$4,'1.DC_Ra soat'!$I:$I,'1.BS (VND)'!$D17) -> 0 | AP17: =SUMIFS('1.DC_Ra soat'!$L:$L,'1.DC_Ra soat'!$F:$F,AP$4,'1.DC_Ra soat'!$H:$H,'1.BS (VND)'!$D17)-SUMIFS('1.DC_Ra soat'!$L:$L,'1.DC_Ra soat'!$F:$F,AP$4,'1.DC_Ra soat'!$I:$I,'1.BS (VND)'!$D17) -> 0 | AQ17: =SUMIFS('1.DC_Ra soat'!$L:$L,'1.DC_Ra soat'!$F:$F,AQ$4,'1.DC_Ra soat'!$H:$H,'1.BS (VND)'!$D17)-SUMIFS('1.DC_Ra soat'!$L:$L,'1.DC_Ra soat'!$F:$F,AQ$4,'1.DC_Ra soat'!$I:$I,'1.BS (VND)'!$D17) -> 0 | AS17: =SUMIFS('1.DC_Ra soat'!$L:$L,'1.DC_Ra soat'!$F:$F,AS$4,'1.DC_Ra soat'!$H:$H,'1.BS (VND)'!$D17)-SUMIFS('1.DC_Ra soat'!$L:$L,'1.DC_Ra soat'!$F:$F,AS$4,'1.DC_Ra soat'!$I:$I,'1.BS (VND)'!$D17) -> 0 | AT17: =SUMIFS('1.DC_Ra soat'!$L:$L,'1.DC_Ra soat'!$F:$F,AT$4,'1.DC_Ra soat'!$H:$H,'1.BS (VND)'!$D17)-SUMIFS('1.DC_Ra soat'!$L:$L,'1.DC_Ra soat'!$F:$F,AT$4,'1.DC_Ra soat'!$I:$I,'1.BS (VND)'!$D17) -> 0 | AU17: =SUMIFS('1.DC_Ra soat'!$L:$L,'1.DC_Ra soat'!$F:$F,AU$4,'1.DC_Ra soat'!$H:$H,'1.BS (VND)'!$D17)-SUMIFS('1.DC_Ra soat'!$L:$L,'1.DC_Ra soat'!$F:$F,AU$4,'1.DC_Ra soat'!$I:$I,'1.BS (VND)'!$D17) -> 0 | AV17: =SUMIFS('1.DC_Ra soat'!$L:$L,'1.DC_Ra soat'!$F:$F,AV$4,'1.DC_Ra soat'!$H:$H,'1.BS (VND)'!$D17)-SUMIFS('1.DC_Ra soat'!$L:$L,'1.DC_Ra soat'!$F:$F,AV$4,'1.DC_Ra soat'!$I:$I,'1.BS (VND)'!$D17) -> 0 | AX17: =SUMIFS('1.DC_Ra soat'!$L:$L,'1.DC_Ra soat'!$F:$F,AX$4,'1.DC_Ra soat'!$H:$H,'1.BS (VND)'!$D17)-SUMIFS('1.DC_Ra soat'!$L:$L,'1.DC_Ra soat'!$F:$F,AX$4,'1.DC_Ra soat'!$I:$I,'1.BS (VND)'!$D17) -> 0 | AY17: =SUMIFS('1.DC_Ra soat'!$L:$L,'1.DC_Ra soat'!$F:$F,AY$4,'1.DC_Ra soat'!$H:$H,'1.BS (VND)'!$D17)-SUMIFS('1.DC_Ra soat'!$L:$L,'1.DC_Ra soat'!$F:$F,AY$4,'1.DC_Ra soat'!$I:$I,'1.BS (VND)'!$D17) -> 0 | AZ17: =SUMIFS('1.DC_Ra soat'!$L:$L,'1.DC_Ra soat'!$F:$F,AZ$4,'1.DC_Ra soat'!$H:$H,'1.BS (VND)'!$D17)-SUMIFS('1.DC_Ra soat'!$L:$L,'1.DC_Ra soat'!$F:$F,AZ$4,'1.DC_Ra soat'!$I:$I,'1.BS (VND)'!$D17) -> 0 | BA17: =SUMIFS('1.DC_Ra soat'!$L:$L,'1.DC_Ra soat'!$F:$F,BA$4,'1.DC_Ra soat'!$H:$H,'1.BS (VND)'!$D17)-SUMIFS('1.DC_Ra soat'!$L:$L,'1.DC_Ra soat'!$F:$F,BA$4,'1.DC_Ra soat'!$I:$I,'1.BS (VND)'!$D17) -> 0 | BC17: =SUMIFS('1.DC_Ra soat'!$L:$L,'1.DC_Ra soat'!$F:$F,'1.PL (VND) '!BI$4,'1.DC_Ra soat'!$H:$H,'1.BS (VND)'!$D17)-SUMIFS('1.DC_Ra soat'!$L:$L,'1.DC_Ra soat'!$F:$F,'1.PL (VND) '!BI$4,'1.DC_Ra soat'!$I:$I,'1.BS (VND)'!$D17) -> 0 | BD17: =SUMIFS('1.DC_Ra soat'!$L:$L,'1.DC_Ra soat'!$F:$F,'1.PL (VND) '!BJ$4,'1.DC_Ra soat'!$H:$H,'1.BS (VND)'!$D17)-SUMIFS('1.DC_Ra soat'!$L:$L,'1.DC_Ra soat'!$F:$F,'1.PL (VND) '!BJ$4,'1.DC_Ra soat'!$I:$I,'1.BS (VND)'!$D17) -> 0 | BE17: =SUMIFS('1.DC_Ra soat'!$L:$L,'1.DC_Ra soat'!$F:$F,'1.PL (VND) '!BK$4,'1.DC_Ra soat'!$H:$H,'1.BS (VND)'!$D17)-SUMIFS('1.DC_Ra soat'!$L:$L,'1.DC_Ra soat'!$F:$F,'1.PL (VND) '!BK$4,'1.DC_Ra soat'!$I:$I,'1.BS (VND)'!$D17) -> 0 | BF17: =SUMIFS('1.DC_Ra soat'!$L:$L,'1.DC_Ra soat'!$F:$F,'1.PL (VND) '!BL$4,'1.DC_Ra soat'!$H:$H,'1.BS (VND)'!$D17)-SUMIFS('1.DC_Ra soat'!$L:$L,'1.DC_Ra soat'!$F:$F,'1.PL (VND) '!BL$4,'1.DC_Ra soat'!$I:$I,'1.BS (VND)'!$D17) -> 0 | BH17: =SUMIFS('1.DC_Ra soat'!$L:$L,'1.DC_Ra soat'!$F:$F,'1.PL (VND) '!BO$4,'1.DC_Ra soat'!$H:$H,'1.BS (VND)'!$D17)-SUMIFS('1.DC_Ra soat'!$L:$L,'1.DC_Ra soat'!$F:$F,'1.PL (VND) '!BO$4,'1.DC_Ra soat'!$I:$I,'1.BS (VND)'!$D17) -> 0 | BI17: =SUMIFS('1.DC_Ra soat'!$L:$L,'1.DC_Ra soat'!$F:$F,'1.PL (VND) '!BP$4,'1.DC_Ra soat'!$H:$H,'1.BS (VND)'!$D17)-SUMIFS('1.DC_Ra soat'!$L:$L,'1.DC_Ra soat'!$F:$F,'1.PL (VND) '!BP$4,'1.DC_Ra soat'!$I:$I,'1.BS (VND)'!$D17) -> 0 | BJ17: =SUMIFS('1.DC_Ra soat'!$L:$L,'1.DC_Ra soat'!$F:$F,'1.PL (VND) '!BQ$4,'1.DC_Ra soat'!$H:$H,'1.BS (VND)'!$D17)-SUMIFS('1.DC_Ra soat'!$L:$L,'1.DC_Ra soat'!$F:$F,'1.PL (VND) '!BQ$4,'1.DC_Ra soat'!$I:$I,'1.BS (VND)'!$D17) -> 0 | BK17: =SUMIFS('1.DC_Ra soat'!$L:$L,'1.DC_Ra soat'!$F:$F,'1.PL (VND) '!BR$4,'1.DC_Ra soat'!$H:$H,'1.BS (VND)'!$D17)-SUMIFS('1.DC_Ra soat'!$L:$L,'1.DC_Ra soat'!$F:$F,'1.PL (VND) '!BR$4,'1.DC_Ra soat'!$I:$I,'1.BS (VND)'!$D17) -> 0 | BM17: =E17+AI17 -> 84240636025 | BN17: =F17+AJ17 -> 29286683582 | BO17: =G17+AK17 -> 29625341610 | BP17: =H17+AL17 -> 101833460095 | BR17: =J17+AN17 -> 0 | BS17: =K17+AO17 -> 5268045366 | BT17: =L17+AP17 -> 11812757297 | BU17: =M17+AQ17 -> 48957714647 | BW17: =O17+AS17 -> 36968498262 | BX17: =P17+AT17 -> 14799733171 | BY17: =Q17+AU17 -> 29280642158 | BZ17: =R17+AV17 -> 33772674580 | CB17: =T17+AX17 -> 17621052183 | CC17: =U17+AY17 -> 13082433252 | CD17: =V17+AZ17 -> 14491580087 | CE17: =W17+BA17 -> 33234622688 | CG17: =Y17+BC17 -> 0 | CH17: =Z17+BD17 -> 0 | CI17: =AA17+BE17 -> 0 | CJ17: =AB17+BF17 -> 0 | CL17: =AD17+BH17 -> 0 | CM17: =AE17+BI17 -> 0 | CN17: =AF17+BJ17 -> 0 | CO17: =AG17+BK17 -> 0 | CQ17: =SUMIF('1.PL (VND) '!$BL$6:$CD$6,'1.PL (VND) '!CP$6,$BM17:$CE17) -> 138830186470 | CR17: =SUMIF('1.PL (VND) '!$BL$6:$CD$6,'1.PL (VND) '!CQ$6,$BM17:$CE17) -> 62436895371 | CS17: =SUMIF('1.PL (VND) '!$BL$6:$CD$6,'1.PL (VND) '!CR$6,$BM17:$CE17) -> 85210321152 | CT17: =SUMIF('1.PL (VND) '!$BL$6:$CD$6,'1.PL (VND) '!CS$6,$BM17:$CE17) -> 217798472010 | CV17: =SUMIFS('1.DC_Ra soat'!$L:$L,'1.DC_Ra soat'!$F:$F,'1.PL (VND) '!DK$4,'1.DC_Ra soat'!$H:$H,'1.BS (VND)'!$D17)-SUMIFS('1.DC_Ra soat'!$L:$L,'1.DC_Ra soat'!$F:$F,'1.PL (VND) '!DK$4,'1.DC_Ra soat'!$I:$I,'1.BS (VND)'!$D17) -> 0 | CW17: =SUMIFS('1.DC_Ra soat'!$L:$L,'1.DC_Ra soat'!$F:$F,'1.PL (VND) '!DL$4,'1.DC_Ra soat'!$H:$H,'1.BS (VND)'!$D17)-SUMIFS('1.DC_Ra soat'!$L:$L,'1.DC_Ra soat'!$F:$F,'1.PL (VND) '!DL$4,'1.DC_Ra soat'!$I:$I,'1.BS (VND)'!$D17) -> 0 | CX17: =SUMIFS('1.DC_Ra soat'!$L:$L,'1.DC_Ra soat'!$F:$F,'1.PL (VND) '!DM$4,'1.DC_Ra soat'!$H:$H,'1.BS (VND)'!$D17)-SUMIFS('1.DC_Ra soat'!$L:$L,'1.DC_Ra soat'!$F:$F,'1.PL (VND) '!DM$4,'1.DC_Ra soat'!$I:$I,'1.BS (VND)'!$D17) -> 0 | CY17: =SUMIFS('1.DC_Ra soat'!$L:$L,'1.DC_Ra soat'!$F:$F,'1.PL (VND) '!DN$4,'1.DC_Ra soat'!$H:$H,'1.BS (VND)'!$D17)-SUMIFS('1.DC_Ra soat'!$L:$L,'1.DC_Ra soat'!$F:$F,'1.PL (VND) '!DN$4,'1.DC_Ra soat'!$I:$I,'1.BS (VND)'!$D17) -> 0 | DA17: =CQ17+CV17 -> 138830186470 | DB17: =CR17+CW17 -> 62436895371 | DC17: =CS17+CX17 -> 85210321152 | DD17: =CT17+CY17 -> 217798472010
A18: =IF(SUM(E18:DD18)<>0,1,"hide") -> 1 | C18: 2. Trả trước cho người bán ngắn hạn | D18: 132 | E18: 12787684560 | F18: 2453662967 | G18: 4297120409 | H18: 51552067613 | K18: 1970134106 | M18: 550613283 | O18: 5626286707 | T18: 1467093698 | U18: 117223130 | V18: 55644736 | W18: 16777440319 | AI18: =SUMIFS('1.DC_Ra soat'!$L:$L,'1.DC_Ra soat'!$F:$F,AI$4,'1.DC_Ra soat'!$H:$H,'1.BS (VND)'!$D18)-SUMIFS('1.DC_Ra soat'!$L:$L,'1.DC_Ra soat'!$F:$F,AI$4,'1.DC_Ra soat'!$I:$I,'1.BS (VND)'!$D18) -> 0 | AJ18: =SUMIFS('1.DC_Ra soat'!$L:$L,'1.DC_Ra soat'!$F:$F,AJ$4,'1.DC_Ra soat'!$H:$H,'1.BS (VND)'!$D18)-SUMIFS('1.DC_Ra soat'!$L:$L,'1.DC_Ra soat'!$F:$F,AJ$4,'1.DC_Ra soat'!$I:$I,'1.BS (VND)'!$D18) -> 0 | AK18: =SUMIFS('1.DC_Ra soat'!$L:$L,'1.DC_Ra soat'!$F:$F,AK$4,'1.DC_Ra soat'!$H:$H,'1.BS (VND)'!$D18)-SUMIFS('1.DC_Ra soat'!$L:$L,'1.DC_Ra soat'!$F:$F,AK$4,'1.DC_Ra soat'!$I:$I,'1.BS (VND)'!$D18) -> 0 | AL18: =SUMIFS('1.DC_Ra soat'!$L:$L,'1.DC_Ra soat'!$F:$F,AL$4,'1.DC_Ra soat'!$H:$H,'1.BS (VND)'!$D18)-SUMIFS('1.DC_Ra soat'!$L:$L,'1.DC_Ra soat'!$F:$F,AL$4,'1.DC_Ra soat'!$I:$I,'1.BS (VND)'!$D18) -> 0 | AN18: =SUMIFS('1.DC_Ra soat'!$L:$L,'1.DC_Ra soat'!$F:$F,AN$4,'1.DC_Ra soat'!$H:$H,'1.BS (VND)'!$D18)-SUMIFS('1.DC_Ra soat'!$L:$L,'1.DC_Ra soat'!$F:$F,AN$4,'1.DC_Ra soat'!$I:$I,'1.BS (VND)'!$D18) -> 0 | AO18: =SUMIFS('1.DC_Ra soat'!$L:$L,'1.DC_Ra soat'!$F:$F,AO$4,'1.DC_Ra soat'!$H:$H,'1.BS (VND)'!$D18)-SUMIFS('1.DC_Ra soat'!$L:$L,'1.DC_Ra soat'!$F:$F,AO$4,'1.DC_Ra soat'!$I:$I,'1.BS (VND)'!$D18) -> 0 | AP18: =SUMIFS('1.DC_Ra soat'!$L:$L,'1.DC_Ra soat'!$F:$F,AP$4,'1.DC_Ra soat'!$H:$H,'1.BS (VND)'!$D18)-SUMIFS('1.DC_Ra soat'!$L:$L,'1.DC_Ra soat'!$F:$F,AP$4,'1.DC_Ra soat'!$I:$I,'1.BS (VND)'!$D18) -> 0 | AQ18: =SUMIFS('1.DC_Ra soat'!$L:$L,'1.DC_Ra soat'!$F:$F,AQ$4,'1.DC_Ra soat'!$H:$H,'1.BS (VND)'!$D18)-SUMIFS('1.DC_Ra soat'!$L:$L,'1.DC_Ra soat'!$F:$F,AQ$4,'1.DC_Ra soat'!$I:$I,'1.BS (VND)'!$D18) -> 0 | AS18: =SUMIFS('1.DC_Ra soat'!$L:$L,'1.DC_Ra soat'!$F:$F,AS$4,'1.DC_Ra soat'!$H:$H,'1.BS (VND)'!$D18)-SUMIFS('1.DC_Ra soat'!$L:$L,'1.DC_Ra soat'!$F:$F,AS$4,'1.DC_Ra soat'!$I:$I,'1.BS (VND)'!$D18) -> 0 | AT18: =SUMIFS('1.DC_Ra soat'!$L:$L,'1.DC_Ra soat'!$F:$F,AT$4,'1.DC_Ra soat'!$H:$H,'1.BS (VND)'!$D18)-SUMIFS('1.DC_Ra soat'!$L:$L,'1.DC_Ra soat'!$F:$F,AT$4,'1.DC_Ra soat'!$I:$I,'1.BS (VND)'!$D18) -> 0 | AU18: =SUMIFS('1.DC_Ra soat'!$L:$L,'1.DC_Ra soat'!$F:$F,AU$4,'1.DC_Ra soat'!$H:$H,'1.BS (VND)'!$D18)-SUMIFS('1.DC_Ra soat'!$L:$L,'1.DC_Ra soat'!$F:$F,AU$4,'1.DC_Ra soat'!$I:$I,'1.BS (VND)'!$D18) -> 0 | AV18: =SUMIFS('1.DC_Ra soat'!$L:$L,'1.DC_Ra soat'!$F:$F,AV$4,'1.DC_Ra soat'!$H:$H,'1.BS (VND)'!$D18)-SUMIFS('1.DC_Ra soat'!$L:$L,'1.DC_Ra soat'!$F:$F,AV$4,'1.DC_Ra soat'!$I:$I,'1.BS (VND)'!$D18) -> 0 | AX18: =SUMIFS('1.DC_Ra soat'!$L:$L,'1.DC_Ra soat'!$F:$F,AX$4,'1.DC_Ra soat'!$H:$H,'1.BS (VND)'!$D18)-SUMIFS('1.DC_Ra soat'!$L:$L,'1.DC_Ra soat'!$F:$F,AX$4,'1.DC_Ra soat'!$I:$I,'1.BS (VND)'!$D18) -> 0 | AY18: =SUMIFS('1.DC_Ra soat'!$L:$L,'1.DC_Ra soat'!$F:$F,AY$4,'1.DC_Ra soat'!$H:$H,'1.BS (VND)'!$D18)-SUMIFS('1.DC_Ra soat'!$L:$L,'1.DC_Ra soat'!$F:$F,AY$4,'1.DC_Ra soat'!$I:$I,'1.BS (VND)'!$D18) -> 0 | AZ18: =SUMIFS('1.DC_Ra soat'!$L:$L,'1.DC_Ra soat'!$F:$F,AZ$4,'1.DC_Ra soat'!$H:$H,'1.BS (VND)'!$D18)-SUMIFS('1.DC_Ra soat'!$L:$L,'1.DC_Ra soat'!$F:$F,AZ$4,'1.DC_Ra soat'!$I:$I,'1.BS (VND)'!$D18) -> 0 | BA18: =SUMIFS('1.DC_Ra soat'!$L:$L,'1.DC_Ra soat'!$F:$F,BA$4,'1.DC_Ra soat'!$H:$H,'1.BS (VND)'!$D18)-SUMIFS('1.DC_Ra soat'!$L:$L,'1.DC_Ra soat'!$F:$F,BA$4,'1.DC_Ra soat'!$I:$I,'1.BS (VND)'!$D18) -> 0 | BC18: =SUMIFS('1.DC_Ra soat'!$L:$L,'1.DC_Ra soat'!$F:$F,'1.PL (VND) '!BI$4,'1.DC_Ra soat'!$H:$H,'1.BS (VND)'!$D18)-SUMIFS('1.DC_Ra soat'!$L:$L,'1.DC_Ra soat'!$F:$F,'1.PL (VND) '!BI$4,'1.DC_Ra soat'!$I:$I,'1.BS (VND)'!$D18) -> 0 | BD18: =SUMIFS('1.DC_Ra soat'!$L:$L,'1.DC_Ra soat'!$F:$F,'1.PL (VND) '!BJ$4,'1.DC_Ra soat'!$H:$H,'1.BS (VND)'!$D18)-SUMIFS('1.DC_Ra soat'!$L:$L,'1.DC_Ra soat'!$F:$F,'1.PL (VND) '!BJ$4,'1.DC_Ra soat'!$I:$I,'1.BS (VND)'!$D18) -> 0 | BE18: =SUMIFS('1.DC_Ra soat'!$L:$L,'1.DC_Ra soat'!$F:$F,'1.PL (VND) '!BK$4,'1.DC_Ra soat'!$H:$H,'1.BS (VND)'!$D18)-SUMIFS('1.DC_Ra soat'!$L:$L,'1.DC_Ra soat'!$F:$F,'1.PL (VND) '!BK$4,'1.DC_Ra soat'!$I:$I,'1.BS (VND)'!$D18) -> 0 | BF18: =SUMIFS('1.DC_Ra soat'!$L:$L,'1.DC_Ra soat'!$F:$F,'1.PL (VND) '!BL$4,'1.DC_Ra soat'!$H:$H,'1.BS (VND)'!$D18)-SUMIFS('1.DC_Ra soat'!$L:$L,'1.DC_Ra soat'!$F:$F,'1.PL (VND) '!BL$4,'1.DC_Ra soat'!$I:$I,'1.BS (VND)'!$D18) -> 0 | BH18: =SUMIFS('1.DC_Ra soat'!$L:$L,'1.DC_Ra soat'!$F:$F,'1.PL (VND) '!BO$4,'1.DC_Ra soat'!$H:$H,'1.BS (VND)'!$D18)-SUMIFS('1.DC_Ra soat'!$L:$L,'1.DC_Ra soat'!$F:$F,'1.PL (VND) '!BO$4,'1.DC_Ra soat'!$I:$I,'1.BS (VND)'!$D18) -> 0 | BI18: =SUMIFS('1.DC_Ra soat'!$L:$L,'1.DC_Ra soat'!$F:$F,'1.PL (VND) '!BP$4,'1.DC_Ra soat'!$H:$H,'1.BS (VND)'!$D18)-SUMIFS('1.DC_Ra soat'!$L:$L,'1.DC_Ra soat'!$F:$F,'1.PL (VND) '!BP$4,'1.DC_Ra soat'!$I:$I,'1.BS (VND)'!$D18) -> 0 | BJ18: =SUMIFS('1.DC_Ra soat'!$L:$L,'1.DC_Ra soat'!$F:$F,'1.PL (VND) '!BQ$4,'1.DC_Ra soat'!$H:$H,'1.BS (VND)'!$D18)-SUMIFS('1.DC_Ra soat'!$L:$L,'1.DC_Ra soat'!$F:$F,'1.PL (VND) '!BQ$4,'1.DC_Ra soat'!$I:$I,'1.BS (VND)'!$D18) -> 0 | BK18: =SUMIFS('1.DC_Ra soat'!$L:$L,'1.DC_Ra soat'!$F:$F,'1.PL (VND) '!BR$4,'1.DC_Ra soat'!$H:$H,'1.BS (VND)'!$D18)-SUMIFS('1.DC_Ra soat'!$L:$L,'1.DC_Ra soat'!$F:$F,'1.PL (VND) '!BR$4,'1.DC_Ra soat'!$I:$I,'1.BS (VND)'!$D18) -> 0 | BM18: =E18+AI18 -> 12787684560 | BN18: =F18+AJ18 -> 2453662967 | BO18: =G18+AK18 -> 4297120409 | BP18: =H18+AL18 -> 51552067613 | BR18: =J18+AN18 -> 0 | BS18: =K18+AO18 -> 1970134106 | BT18: =L18+AP18 -> 0 | BU18: =M18+AQ18 -> 550613283 | BW18: =O18+AS18 -> 5626286707 | BX18: =P18+AT18 -> 0 | BY18: =Q18+AU18 -> 0 | BZ18: =R18+AV18 -> 0 | CB18: =T18+AX18 -> 1467093698 | CC18: =U18+AY18 -> 117223130 | CD18: =V18+AZ18 -> 55644736 | CE18: =W18+BA18 -> 16777440319 | CG18: =Y18+BC18 -> 0 | CH18: =Z18+BD18 -> 0 | CI18: =AA18+BE18 -> 0 | CJ18: =AB18+BF18 -> 0 | CL18: =AD18+BH18 -> 0 | CM18: =AE18+BI18 -> 0 | CN18: =AF18+BJ18 -> 0 | CO18: =AG18+BK18 -> 0 | CQ18: =SUMIF('1.PL (VND) '!$BL$6:$CD$6,'1.PL (VND) '!CP$6,$BM18:$CE18) -> 19881064965 | CR18: =SUMIF('1.PL (VND) '!$BL$6:$CD$6,'1.PL (VND) '!CQ$6,$BM18:$CE18) -> 4541020203 | CS18: =SUMIF('1.PL (VND) '!$BL$6:$CD$6,'1.PL (VND) '!CR$6,$BM18:$CE18) -> 4352765145 | CT18: =SUMIF('1.PL (VND) '!$BL$6:$CD$6,'1.PL (VND) '!CS$6,$BM18:$CE18) -> 68880121215 | CV18: =SUMIFS('1.DC_Ra soat'!$L:$L,'1.DC_Ra soat'!$F:$F,'1.PL (VND) '!DK$4,'1.DC_Ra soat'!$H:$H,'1.BS (VND)'!$D18)-SUMIFS('1.DC_Ra soat'!$L:$L,'1.DC_Ra soat'!$F:$F,'1.PL (VND) '!DK$4,'1.DC_Ra soat'!$I:$I,'1.BS (VND)'!$D18) -> 0 | CW18: =SUMIFS('1.DC_Ra soat'!$L:$L,'1.DC_Ra soat'!$F:$F,'1.PL (VND) '!DL$4,'1.DC_Ra soat'!$H:$H,'1.BS (VND)'!$D18)-SUMIFS('1.DC_Ra soat'!$L:$L,'1.DC_Ra soat'!$F:$F,'1.PL (VND) '!DL$4,'1.DC_Ra soat'!$I:$I,'1.BS (VND)'!$D18) -> 0 | CX18: =SUMIFS('1.DC_Ra soat'!$L:$L,'1.DC_Ra soat'!$F:$F,'1.PL (VND) '!DM$4,'1.DC_Ra soat'!$H:$H,'1.BS (VND)'!$D18)-SUMIFS('1.DC_Ra soat'!$L:$L,'1.DC_Ra soat'!$F:$F,'1.PL (VND) '!DM$4,'1.DC_Ra soat'!$I:$I,'1.BS (VND)'!$D18) -> 0 | CY18: =SUMIFS('1.DC_Ra soat'!$L:$L,'1.DC_Ra soat'!$F:$F,'1.PL (VND) '!DN$4,'1.DC_Ra soat'!$H:$H,'1.BS (VND)'!$D18)-SUMIFS('1.DC_Ra soat'!$L:$L,'1.DC_Ra soat'!$F:$F,'1.PL (VND) '!DN$4,'1.DC_Ra soat'!$I:$I,'1.BS (VND)'!$D18) -> 0 | DA18: =CQ18+CV18 -> 19881064965 | DB18: =CR18+CW18 -> 4541020203 | DC18: =CS18+CX18 -> 4352765145 | DD18: =CT18+CY18 -> 68880121215
A19: =IF(SUM(E19:DD19)<>0,1,"hide") -> 1 | C19: 3. Phải thu nội bộ ngắn hạn | D19: 133 | G19: 2725233896 | H19: 3849398054 | M19: 1160340400 | AI19: =SUMIFS('1.DC_Ra soat'!$L:$L,'1.DC_Ra soat'!$F:$F,AI$4,'1.DC_Ra soat'!$H:$H,'1.BS (VND)'!$D19)-SUMIFS('1.DC_Ra soat'!$L:$L,'1.DC_Ra soat'!$F:$F,AI$4,'1.DC_Ra soat'!$I:$I,'1.BS (VND)'!$D19) -> 0 | AJ19: =SUMIFS('1.DC_Ra soat'!$L:$L,'1.DC_Ra soat'!$F:$F,AJ$4,'1.DC_Ra soat'!$H:$H,'1.BS (VND)'!$D19)-SUMIFS('1.DC_Ra soat'!$L:$L,'1.DC_Ra soat'!$F:$F,AJ$4,'1.DC_Ra soat'!$I:$I,'1.BS (VND)'!$D19) -> 0 | AK19: =SUMIFS('1.DC_Ra soat'!$L:$L,'1.DC_Ra soat'!$F:$F,AK$4,'1.DC_Ra soat'!$H:$H,'1.BS (VND)'!$D19)-SUMIFS('1.DC_Ra soat'!$L:$L,'1.DC_Ra soat'!$F:$F,AK$4,'1.DC_Ra soat'!$I:$I,'1.BS (VND)'!$D19) -> 0 | AL19: =SUMIFS('1.DC_Ra soat'!$L:$L,'1.DC_Ra soat'!$F:$F,AL$4,'1.DC_Ra soat'!$H:$H,'1.BS (VND)'!$D19)-SUMIFS('1.DC_Ra soat'!$L:$L,'1.DC_Ra soat'!$F:$F,AL$4,'1.DC_Ra soat'!$I:$I,'1.BS (VND)'!$D19) -> 0 | AN19: =SUMIFS('1.DC_Ra soat'!$L:$L,'1.DC_Ra soat'!$F:$F,AN$4,'1.DC_Ra soat'!$H:$H,'1.BS (VND)'!$D19)-SUMIFS('1.DC_Ra soat'!$L:$L,'1.DC_Ra soat'!$F:$F,AN$4,'1.DC_Ra soat'!$I:$I,'1.BS (VND)'!$D19) -> 0 | AO19: =SUMIFS('1.DC_Ra soat'!$L:$L,'1.DC_Ra soat'!$F:$F,AO$4,'1.DC_Ra soat'!$H:$H,'1.BS (VND)'!$D19)-SUMIFS('1.DC_Ra soat'!$L:$L,'1.DC_Ra soat'!$F:$F,AO$4,'1.DC_Ra soat'!$I:$I,'1.BS (VND)'!$D19) -> 0 | AP19: =SUMIFS('1.DC_Ra soat'!$L:$L,'1.DC_Ra soat'!$F:$F,AP$4,'1.DC_Ra soat'!$H:$H,'1.BS (VND)'!$D19)-SUMIFS('1.DC_Ra soat'!$L:$L,'1.DC_Ra soat'!$F:$F,AP$4,'1.DC_Ra soat'!$I:$I,'1.BS (VND)'!$D19) -> 0 | AQ19: =SUMIFS('1.DC_Ra soat'!$L:$L,'1.DC_Ra soat'!$F:$F,AQ$4,'1.DC_Ra soat'!$H:$H,'1.BS (VND)'!$D19)-SUMIFS('1.DC_Ra soat'!$L:$L,'1.DC_Ra soat'!$F:$F,AQ$4,'1.DC_Ra soat'!$I:$I,'1.BS (VND)'!$D19) -> 0 | AS19: =SUMIFS('1.DC_Ra soat'!$L:$L,'1.DC_Ra soat'!$F:$F,AS$4,'1.DC_Ra soat'!$H:$H,'1.BS (VND)'!$D19)-SUMIFS('1.DC_Ra soat'!$L:$L,'1.DC_Ra soat'!$F:$F,AS$4,'1.DC_Ra soat'!$I:$I,'1.BS (VND)'!$D19) -> 0 | AT19: =SUMIFS('1.DC_Ra soat'!$L:$L,'1.DC_Ra soat'!$F:$F,AT$4,'1.DC_Ra soat'!$H:$H,'1.BS (VND)'!$D19)-SUMIFS('1.DC_Ra soat'!$L:$L,'1.DC_Ra soat'!$F:$F,AT$4,'1.DC_Ra soat'!$I:$I,'1.BS (VND)'!$D19) -> 0 | AU19: =SUMIFS('1.DC_Ra soat'!$L:$L,'1.DC_Ra soat'!$F:$F,AU$4,'1.DC_Ra soat'!$H:$H,'1.BS (VND)'!$D19)-SUMIFS('1.DC_Ra soat'!$L:$L,'1.DC_Ra soat'!$F:$F,AU$4,'1.DC_Ra soat'!$I:$I,'1.BS (VND)'!$D19) -> 0 | AV19: =SUMIFS('1.DC_Ra soat'!$L:$L,'1.DC_Ra soat'!$F:$F,AV$4,'1.DC_Ra soat'!$H:$H,'1.BS (VND)'!$D19)-SUMIFS('1.DC_Ra soat'!$L:$L,'1.DC_Ra soat'!$F:$F,AV$4,'1.DC_Ra soat'!$I:$I,'1.BS (VND)'!$D19) -> 0 | AX19: =SUMIFS('1.DC_Ra soat'!$L:$L,'1.DC_Ra soat'!$F:$F,AX$4,'1.DC_Ra soat'!$H:$H,'1.BS (VND)'!$D19)-SUMIFS('1.DC_Ra soat'!$L:$L,'1.DC_Ra soat'!$F:$F,AX$4,'1.DC_Ra soat'!$I:$I,'1.BS (VND)'!$D19) -> 0 | AY19: =SUMIFS('1.DC_Ra soat'!$L:$L,'1.DC_Ra soat'!$F:$F,AY$4,'1.DC_Ra soat'!$H:$H,'1.BS (VND)'!$D19)-SUMIFS('1.DC_Ra soat'!$L:$L,'1.DC_Ra soat'!$F:$F,AY$4,'1.DC_Ra soat'!$I:$I,'1.BS (VND)'!$D19) -> 0 | AZ19: =SUMIFS('1.DC_Ra soat'!$L:$L,'1.DC_Ra soat'!$F:$F,AZ$4,'1.DC_Ra soat'!$H:$H,'1.BS (VND)'!$D19)-SUMIFS('1.DC_Ra soat'!$L:$L,'1.DC_Ra soat'!$F:$F,AZ$4,'1.DC_Ra soat'!$I:$I,'1.BS (VND)'!$D19) -> 0 | BA19: =SUMIFS('1.DC_Ra soat'!$L:$L,'1.DC_Ra soat'!$F:$F,BA$4,'1.DC_Ra soat'!$H:$H,'1.BS (VND)'!$D19)-SUMIFS('1.DC_Ra soat'!$L:$L,'1.DC_Ra soat'!$F:$F,BA$4,'1.DC_Ra soat'!$I:$I,'1.BS (VND)'!$D19) -> 0 | BC19: =SUMIFS('1.DC_Ra soat'!$L:$L,'1.DC_Ra soat'!$F:$F,'1.PL (VND) '!BI$4,'1.DC_Ra soat'!$H:$H,'1.BS (VND)'!$D19)-SUMIFS('1.DC_Ra soat'!$L:$L,'1.DC_Ra soat'!$F:$F,'1.PL (VND) '!BI$4,'1.DC_Ra soat'!$I:$I,'1.BS (VND)'!$D19) -> 0 | BD19: =SUMIFS('1.DC_Ra soat'!$L:$L,'1.DC_Ra soat'!$F:$F,'1.PL (VND) '!BJ$4,'1.DC_Ra soat'!$H:$H,'1.BS (VND)'!$D19)-SUMIFS('1.DC_Ra soat'!$L:$L,'1.DC_Ra soat'!$F:$F,'1.PL (VND) '!BJ$4,'1.DC_Ra soat'!$I:$I,'1.BS (VND)'!$D19) -> 0 | BE19: =SUMIFS('1.DC_Ra soat'!$L:$L,'1.DC_Ra soat'!$F:$F,'1.PL (VND) '!BK$4,'1.DC_Ra soat'!$H:$H,'1.BS (VND)'!$D19)-SUMIFS('1.DC_Ra soat'!$L:$L,'1.DC_Ra soat'!$F:$F,'1.PL (VND) '!BK$4,'1.DC_Ra soat'!$I:$I,'1.BS (VND)'!$D19) -> 0 | BF19: =SUMIFS('1.DC_Ra soat'!$L:$L,'1.DC_Ra soat'!$F:$F,'1.PL (VND) '!BL$4,'1.DC_Ra soat'!$H:$H,'1.BS (VND)'!$D19)-SUMIFS('1.DC_Ra soat'!$L:$L,'1.DC_Ra soat'!$F:$F,'1.PL (VND) '!BL$4,'1.DC_Ra soat'!$I:$I,'1.BS (VND)'!$D19) -> 0 | BH19: =SUMIFS('1.DC_Ra soat'!$L:$L,'1.DC_Ra soat'!$F:$F,'1.PL (VND) '!BO$4,'1.DC_Ra soat'!$H:$H,'1.BS (VND)'!$D19)-SUMIFS('1.DC_Ra soat'!$L:$L,'1.DC_Ra soat'!$F:$F,'1.PL (VND) '!BO$4,'1.DC_Ra soat'!$I:$I,'1.BS (VND)'!$D19) -> 0 | BI19: =SUMIFS('1.DC_Ra soat'!$L:$L,'1.DC_Ra soat'!$F:$F,'1.PL (VND) '!BP$4,'1.DC_Ra soat'!$H:$H,'1.BS (VND)'!$D19)-SUMIFS('1.DC_Ra soat'!$L:$L,'1.DC_Ra soat'!$F:$F,'1.PL (VND) '!BP$4,'1.DC_Ra soat'!$I:$I,'1.BS (VND)'!$D19) -> 0 | BJ19: =SUMIFS('1.DC_Ra soat'!$L:$L,'1.DC_Ra soat'!$F:$F,'1.PL (VND) '!BQ$4,'1.DC_Ra soat'!$H:$H,'1.BS (VND)'!$D19)-SUMIFS('1.DC_Ra soat'!$L:$L,'1.DC_Ra soat'!$F:$F,'1.PL (VND) '!BQ$4,'1.DC_Ra soat'!$I:$I,'1.BS (VND)'!$D19) -> 0 | BK19: =SUMIFS('1.DC_Ra soat'!$L:$L,'1.DC_Ra soat'!$F:$F,'1.PL (VND) '!BR$4,'1.DC_Ra soat'!$H:$H,'1.BS (VND)'!$D19)-SUMIFS('1.DC_Ra soat'!$L:$L,'1.DC_Ra soat'!$F:$F,'1.PL (VND) '!BR$4,'1.DC_Ra soat'!$I:$I,'1.BS (VND)'!$D19) -> 0 | BM19: =E19+AI19 -> 0 | BN19: =F19+AJ19 -> 0 | BO19: =G19+AK19 -> 2725233896 | BP19: =H19+AL19 -> 3849398054 | BR19: =J19+AN19 -> 0 | BS19: =K19+AO19 -> 0 | BT19: =L19+AP19 -> 0 | BU19: =M19+AQ19 -> 1160340400 | BW19: =O19+AS19 -> 0 | BX19: =P19+AT19 -> 0 | BY19: =Q19+AU19 -> 0 | BZ19: =R19+AV19 -> 0 | CB19: =T19+AX19 -> 0 | CC19: =U19+AY19 -> 0 | CD19: =V19+AZ19 -> 0 | CE19: =W19+BA19 -> 0 | CG19: =Y19+BC19 -> 0 | CH19: =Z19+BD19 -> 0 | CI19: =AA19+BE19 -> 0 | CJ19: =AB19+BF19 -> 0 | CL19: =AD19+BH19 -> 0 | CM19: =AE19+BI19 -> 0 | CN19: =AF19+BJ19 -> 0 | CO19: =AG19+BK19 -> 0 | CQ19: =SUMIF('1.PL (VND) '!$BL$6:$CD$6,'1.PL (VND) '!CP$6,$BM19:$CE19) -> 0 | CR19: =SUMIF('1.PL (VND) '!$BL$6:$CD$6,'1.PL (VND) '!CQ$6,$BM19:$CE19) -> 0 | CS19: =SUMIF('1.PL (VND) '!$BL$6:$CD$6,'1.PL (VND) '!CR$6,$BM19:$CE19) -> 2725233896 | CT19: =SUMIF('1.PL (VND) '!$BL$6:$CD$6,'1.PL (VND) '!CS$6,$BM19:$CE19) -> 5009738454 | CV19: =SUMIFS('1.DC_Ra soat'!$L:$L,'1.DC_Ra soat'!$F:$F,'1.PL (VND) '!DK$4,'1.DC_Ra soat'!$H:$H,'1.BS (VND)'!$D19)-SUMIFS('1.DC_Ra soat'!$L:$L,'1.DC_Ra soat'!$F:$F,'1.PL (VND) '!DK$4,'1.DC_Ra soat'!$I:$I,'1.BS (VND)'!$D19) -> 0 | CW19: =SUMIFS('1.DC_Ra soat'!$L:$L,'1.DC_Ra soat'!$F:$F,'1.PL (VND) '!DL$4,'1.DC_Ra soat'!$H:$H,'1.BS (VND)'!$D19)-SUMIFS('1.DC_Ra soat'!$L:$L,'1.DC_Ra soat'!$F:$F,'1.PL (VND) '!DL$4,'1.DC_Ra soat'!$I:$I,'1.BS (VND)'!$D19) -> 0 | CX19: =SUMIFS('1.DC_Ra soat'!$L:$L,'1.DC_Ra soat'!$F:$F,'1.PL (VND) '!DM$4,'1.DC_Ra soat'!$H:$H,'1.BS (VND)'!$D19)-SUMIFS('1.DC_Ra soat'!$L:$L,'1.DC_Ra soat'!$F:$F,'1.PL (VND) '!DM$4,'1.DC_Ra soat'!$I:$I,'1.BS (VND)'!$D19) -> 0 | CY19: =SUMIFS('1.DC_Ra soat'!$L:$L,'1.DC_Ra soat'!$F:$F,'1.PL (VND) '!DN$4,'1.DC_Ra soat'!$H:$H,'1.BS (VND)'!$D19)-SUMIFS('1.DC_Ra soat'!$L:$L,'1.DC_Ra soat'!$F:$F,'1.PL (VND) '!DN$4,'1.DC_Ra soat'!$I:$I,'1.BS (VND)'!$D19) -> 0 | DA19: =CQ19+CV19 -> 0 | DB19: =CR19+CW19 -> 0 | DC19: =CS19+CX19 -> 2725233896 | DD19: =CT19+CY19 -> 5009738454
