Workbook

Sheet Cover
B9: JOB
B11: SOFTWARE BUSINESS ANALYST
F15: Code | I15: 13e-CV/HR/HDCV/CM
F16: Version | I16: 1.0
F17: Effect Date | I17: MAR.31.2023

Sheet Table of Content
A1: TABLE OF CONTENT
A3: 1 | B3: Guidelines | G3: Click here
A4: 2 | B4: Models | G4: Click here
A5: 3 | B5: Career Paths | G5: Click here
A6: 4 | B6: Job Descriptions | G6: Click here
A7: 5 | B7: Job Rankings | G7: Click here
A8: 6 | B8: Assessment Summary | G8: Click here
A9: 7 | B9: Roles & Responsibilities | G9: Click here
A10: 8 | B10: Definitions | G10: Click here
A11: 9 | B11: Records of Change | G11: Click here

Sheet 01. Guidelines
A1: Guidelines
B2: Business Analyst Capabilities Assessment & Development
B3: 1. Purpose
B4: - This document use to assess current Software Business Analyst (BA) capabilities base on Job Description of FSOFT and specific requirement of BU.
B5: - This template will help BA find out the SKILL GAP to fulfill the required/desired ranking then define action to improve to achieve specific ranking.
B6: 2. Users:
B7: BA can use this template whenever they need to determine their competency or new onboarding BA in FSOFT.
B8: BUL/Project manager can use this template to verify BA ranking at CHE or Ad-hoc event.
B9: 3. Assessment criteria
C10: Career Path Development => Refer to sheet 03. Career Paths
C11: Competency Framework => Refer to sheet 04. Job Descriptions
C12: Job Assessment => Refer to sheet 05. Job Rankings
C13: Definitions and Parameters => Refer to sheet 08. Definitions
B14: 4. Steps to do the Assessment
C15: STEP 1: | D15: Go to sheet [05. Job Rankings],
D16: Enter your account + name in cell B3
D17: Input any description in cell C3
D18: Choose your current or ranking that you need to achieve in cell H3
C19: STEP 2: | D19: Continue with sheet [05. Job Rankings],
D20: Choose the correct value of each criteria at the Listbox in cells E7:E35
D21: Provide evidence or description in cells F7:F35 for corresponding criteria if any
C22: STEP 3: | D22: Filter "Yes" value in column J-[Need to improve?] and fill in the improvement to column K -[Action to improve] and appropriate deadline in column L.
D23: * Refer the required skill for each item in column H-[Ranking Requirement] to define what action need to be taken.
C24: STEP 4: | D24: Go to sheet [06. Assessment Summary] to view the Overall capabilities & actions needed to achieve your expected Ranking.
C25: STEP 5: | D25: Add the Action to improve to your Personal Development Plan and follow up for closure before the next Ranking Review.

Sheet 02. Models
A1: Models
B2: Software Business Analyst Role | D2: BUILD-UP | E2: BUY-IN
B3: Assessment Items | C3: Code | D3: Weight % | E3: Weight %
D4: =D5+D8+D25+D15+D30 -> 1 | E4: =E5+E8+E25+E15+E30 -> 1
B5: Roles & Responsibilities | D5: =SUM(D6:D7) -> 0.15 | E5: =SUM(E6:E7) -> 0
B6: Roles and Responsibilities | C6: SBA01 | D6: 0.12 | E6: 0
B7: Team Size To Lead for BA Leader | C7: SBA02 | D7: 0.03 | E7: 0
B8: Experiences & Contributions | D8: =SUM(D9:D14) -> 0.25 | E8: =SUM(E9:E14) -> 0.3
B9: Business Analysis Experiences (*) | C9: SBA03 | D9: 0.05 | E9: 0.15
B10: Subordinate Development | C10: SBA04 | D10: 0.03 | E10: 0
B11: Number of Projects/Phases | C11: SBA05 | D11: 0.03 | E11: 0.05
B12: Community Contributions | C12: SBA06 | D12: 0.02 | E12: 0
B13: Industry Experiences (IT and Non-IT fields) | C13: SBA07 | D13: 0.1 | E13: 0.1
B14: Consulting for Sales/Biding Teams | C14: SBA08 | D14: 0.02 | E14: 0
B15: Professional Business Analysis Skills | D15: =SUM(D16:D24) -> 0.4 | E15: =SUM(E16:E24) -> 0.5
B16: Business Analysis Planning & Monitoring (*) | C16: SBA09 | D16: 0.08 | E16: 0.08
B17: Requirement Elicitation & Collaboration (*) | C17: SBA10 | D17: 0.07 | E17: 0.07
B18: Business Requirement Analysis (*) | C18: SBA11 | D18: 0.1 | E18: 0.2
B19: Business Solution Evaluation | C19: SBA12 | D19: 0.05 | E19: 0.05
B20: Business Requirement Life-Cycle | C20: SBA13 | D20: 0.02 | E20: 0.02
B21: Business Strategy Design | C21: SBA14 | D21: 0.02 | E21: 0.02
B22: Business Acumen and Mindsets | C22: SBA15 | D22: 0.03 | E22: 0.03
B23: Software Design and Technology Stack | C23: SBA16 | D23: 0.01 | E23: 0.01
B24: Business Analysis Tools | C24: SBA17 | D24: 0.02 | E24: 0.02
B25: Foreign Language & Certificates | D25: =SUM(D26:D29) -> 0.1 | E25: =SUM(E26:E29) -> 0.1
B26: Foreign Language | C26: SBA18 | D26: 0.05 | E26: 0.05
B27: Education Background | C27: SBA19 | D27: 0.02 | E27: 0.02
B28: Business Analysis Certifications | C28: SBA20 | D28: 0.02 | E28: 0.02
B29: Individual Learning in Year | C29: SBA21 | D29: 0.01 | E29: 0.01
B30: Non-Engineering and Softskills | D30: =SUM(D31:D35) -> 0.1 | E30: =SUM(E31:E35) -> 0.1
B31: Communication and Problem Solving | C31: SBA22 | D31: 0.03 | E31: 0.03
B32: Organization and Industry Knowledge | C32: SBA23 | D32: 0.02 | E32: 0.02
B33: Analytical and Critical Thinking | C33: SBA24 | D33: 0.02 | E33: 0.02
B34: Project Risk Management | C34: SBA25 | D34: 0.02 | E34: 0.02
B35: Project Human Resource Management | C35: SBA26 | D35: 0.01 | E35: 0.01

Sheet 03. Career Paths
A1: Career Paths | V1: CURRENT VERSION:
V15: NEW VERSION:
V16: The Competency-Based JD Components and Weight | X16: =SUM(X17:X21) -> 1
V17: I | W17: ='02. Models'!B5 -> Roles & Responsibilities | X17: ='02. Models'!D5 -> 0.15
V18: II | W18: ='02. Models'!B8 -> Experiences & Contributions | X18: ='02. Models'!D8 -> 0.25
V19: III | W19: ='02. Models'!B15 -> Professional Business Analysis Skills | X19: ='02. Models'!D15 -> 0.4
V20: IV | W20: ='02. Models'!B25 -> Foreign Language & Certificates | X20: ='02. Models'!D25 -> 0.1
V21: V | W21: ='02. Models'!B30 -> Non-Engineering and Softskills | X21: ='02. Models'!D30 -> 0.1
V24: JOB INTERVIEW:
V25: The Competency-Based JD Components and Weight | X25: =SUM(X26:X29) -> 1
V26: I | W26: ='02. Models'!B13 -> Industry Experiences (IT and Non-IT fields) | X26: ='02. Models'!E8 -> 0.3
V27: II | W27: ='02. Models'!B17 -> Requirement Elicitation & Collaboration (*) | X27: ='02. Models'!E15 -> 0.5
V28: III | W28: ='02. Models'!B24 -> Business Analysis Tools | X28: ='02. Models'!E25 -> 0.1
V29: IV | W29: ='02. Models'!B34 -> Project Risk Management | X29: ='02. Models'!E30 -> 0.1

Sheet 04. Job Descriptions
A1: Job Descriptions | D1: Software Business Analyst Role - Job Description | M1: RANKING INDEX
B2: (*) Mandatory assessment items. If there is any unqualified item, you will not qualified this rank. | M2: =E3 -> Associate Business Analyst | N2: =F3 -> Business Analyst | O2: =G3 -> Senior Business Analyst | P2: =H3 -> Business Analysis Leader | Q2: =I3 -> Senior Business Analysis Consultant / Leader | R2: =J3 -> Principal Business Analysis Consultant / Leader
B3: Assessment Items | C3: Weight % | D3: Explanation of Assessment Items | E3: ='08. Definitions'!$D14 -> Associate Business Analyst | F3: ='08. Definitions'!$D15 -> Business Analyst | G3: ='08. Definitions'!$D16 -> Senior Business Analyst | H3: ='08. Definitions'!$D17 -> Business Analysis Leader | I3: ='08. Definitions'!$D19 -> Senior Business Analysis Consultant / Leader | J3: ='08. Definitions'!$D20 -> Principal Business Analysis Consultant / Leader | M3: =E4 -> BANE01 | N3: =F4 -> BANE02 | O3: =G4 -> BANE03 | P3: =H4 -> BANE04 | Q3: =I4 -> BANE05 | R3: =J4 -> BANE06
C4: =C5+C8+C25+C15+C30 -> 1 | E4: ='08. Definitions'!C14 -> BANE01 | F4: ='08. Definitions'!C15 -> BANE02 | G4: ='08. Definitions'!C16 -> BANE03 | H4: ='08. Definitions'!C17 -> BANE04 | I4: ='08. Definitions'!C19 -> BANE05 | J4: ='08. Definitions'!C20 -> BANE06 | M4: =M5+M8+M15+M25+M30 -> 25.733333 | N4: =N5+N8+N15+N25+N30 -> 34.233333 | O4: =O5+O8+O15+O25+O30 -> 49.916667 | P4: =P5+P8+P15+P25+P30 -> 67.816667 | Q4: =Q5+Q8+Q15+Q25+Q30 -> 81 | R4: =R5+R8+R15+R25+R30 -> 100
B5: ='02. Models'!B5 -> Roles & Responsibilities | C5: =SUM(C6:C7) -> 0.15 | D5: FSOFTER is required to have the role and responsibility to perform one or more of the following tasks | E5: Level 1 | F5: Level 2 | G5: Level 3 | H5: Level 4 | I5: Level 5 | J5: Level 6 | M5: =SUM(M6:M7) -> 2.4 | N5: =SUM(N6:N7) -> 4.8 | O5: =SUM(O6:O7) -> 7.2 | P5: =SUM(P6:P7) -> 10.35 | Q5: =SUM(Q6:Q7) -> 11.85 | R5: =SUM(R6:R7) -> 15
B6: ='02. Models'!B6 -> Roles and Responsibilities | C6: ='02. Models'!D6 -> 0.12 | D6: Implementing all the processes and activities related to business analysis which can be analyzing and designing functional and non-functional requirements to the development, client or production environment, including but not limited to following responsibilities: BANE01: - Has responsibility for documenting requirement, supporting communicate requirement to stakeholders (under guidance) as role BA member. - Project Diversity and Complexity - Low: >=5 items in Elementary Complexity Criteria BANE02: - Has responsibility for gathering requirement, elaborating and validating gathered requirement as role BA member. - Project Diversity and Complexity - Normal: All items of Elementary Complexity Criteria & >= 1 item in General Advanced Complexity Criteria BANE03: - Has responsibility for designing, analyzing and evaluating business solution to ensure that it aligns with the project's goal as role BA member. - Project Diversity and Complexity - Medium: >= 4 items of General Advanced Complexity Criteria & >= 2 items of Management Complexity Criteria OR >= 4 items of General Advanced Complexity Criteria & >=1 item in Consultant Complexity Criteria BANE04: - Has responsibility for defining requirement approach & process, planning and monitoring business analysis activities as role BA consultant. - Project Diversity and Complexity - Complex: >= 4 items in General Advanced Complexity Criteria & All items in Management Complexity Criteria OR >= 5 items in General Advanced Complexity Criteria & >= 2 item of Consultant Complexity Criteria BANE05: - Has responsibility for performing system evaluation & enterprise solution consultation as role BA consultant. - Project Diversity and Complexity - Complex: >= 4 items in General Advanced Complexity Criteria & All items in Management Complexity Criteria OR >= 5 items in General Advanced Complexity Criteria & >= 2 item of Consultant Complexity Criteria BANE06: - Has responsibility for performing system evaluation & enterprise solution consultation as role BA consultant. - Project Diversity and Complexity - Very Complex: >= 4 items of Advanced Complexity Criteria & All items of Management Complexity Criteria OR All items in General Advanced & All Consultant Complexity Criteria | E6: 1: Follow (BANE01) | F6: 2: Assist (BANE02) | G6: 3: Apply (BANE03) | H6: 4: Create (BANE04) | I6: 4: Create (BANE04) | J6: 5: Design (BANE05/BANE06) | K6: =MAX(LEFT(E6,1),LEFT(F6,1), LEFT(G6,1), LEFT(H6,1), LEFT(I6,1), LEFT(J6,1)) -> 5 | M6: =(LEFT(E6,1)*$C6/$K$6)*100 -> 2.4 | N6: =(LEFT(F6,1)*$C6/$K$6)*100 -> 4.8 | O6: =(LEFT(G6,1)*$C6/$K$6)*100 -> 7.2 | P6: =(LEFT(H6,1)*$C6/$K$6)*100 -> 9.6 | Q6: =(LEFT(I6,1)*$C6/$K$6)*100 -> 9.6 | R6: =(LEFT(J6,1)*$C6/$K$6)*100 -> 12
B7: ='02. Models'!B7 -> Team Size To Lead for BA Leader | C7: ='02. Models'!D7 -> 0.03 | D7: 4: Global Level - Have at least 70% BA2, 10% BA3, 3% BA4, 0.75%BA5 3: FSOFT Level - Have at least 50% BA2, 10% BA3, 3% BA4, 0.75%BA5 2: FSU Level - Have at least 50% BA2, 12% BA3, 3% BA4 1: BU Level - Have at least 50% BA2, 12% BA3 0: Not Required | E7: 0: Not Requried | F7: 0: Not Requried | G7: 0: Not Requried | H7: 1: BU Level | I7: 3: FSOFT Level | J7: 4: Global Level | K7: =MAX(LEFT(E7,1),LEFT(F7,1), LEFT(G7,1), LEFT(H7,1), LEFT(I7,1), LEFT(J7,1)) -> 4 | M7: =(LEFT(E7,1)*$C7/$K$7)*100 -> 0 | N7: =(LEFT(F7,1)*$C7/$K$7)*100 -> 0 | O7: =(LEFT(G7,1)*$C7/$K$7)*100 -> 0 | P7: =(LEFT(H7,1)*$C7/$K$7)*100 -> 0.75 | Q7: =(LEFT(I7,1)*$C7/$K$7)*100 -> 2.25 | R7: =(LEFT(J7,1)*$C7/$K$7)*100 -> 3
B8: ='02. Models'!B8 -> Experiences & Contributions | C8: =SUM(C9:C14) -> 0.25 | D8: FSOFTER is required to have one or more of the following professional experiences and project contributions | M8: =SUM(M9:M14) -> 0 | N8: =SUM(N9:N14) -> 1.6 | O8: =SUM(O9:O14) -> 7.45 | P8: =SUM(P9:P14) -> 13.3 | Q8: =SUM(Q9:Q14) -> 19.15 | R8: =SUM(R9:R14) -> 25
B9: ='02. Models'!B9 -> Business Analysis Experiences (*) | C9: ='02. Models'!D9 -> 0.05 | D9: Number of years working as Business Analyst, Software Business Analyst, Software Development Life Cycle, Team Work, Agile Mindset | E9: 0: Fundamental awareness | F9: 1: ~1 year experience | G9: 2: 2-3 years experience | H9: 3: 3-5 years experience | I9: 4: 5-7 years experience | J9: 5: 8-10 years experience | K9: =MAX(LEFT(E9,1),LEFT(F9,1), LEFT(G9,1), LEFT(H9,1), LEFT(I9,1), LEFT(J9,1)) -> 5 | M9: =(LEFT(E9,1)*$C9/$K$9)*100 -> 0 | N9: =(LEFT(F9,1)*$C9/$K$9)*100 -> 1 | O9: =(LEFT(G9,1)*$C9/$K$9)*100 -> 2 | P9: =(LEFT(H9,1)*$C9/$K$9)*100 -> 3 | Q9: =(LEFT(I9,1)*$C9/$K$9)*100 -> 4 | R9: =(LEFT(J9,1)*$C9/$K$9)*100 -> 5
B10: ='02. Models'!B10 -> Subordinate Development | C10: ='02. Models'!D10 -> 0.03 | D10: Number of team members or number of people trained/coached | E10: 0: Not Required | F10: 0: Not Required | G10: 1: 1-5 Members or Coaching 1-2 Junior BA | H10: 2: 5-10 Members or Coaching 3-4 Junior BA | I10: 3: 10-20 Members or Coaching 1-2 Senior BA | J10: 4: >20 Members or Coaching 3-4 Senior BA | K10: =MAX(LEFT(E10,1),LEFT(F10,1), LEFT(G10,1), LEFT(H10,1), LEFT(I10,1), LEFT(J10,1)) -> 4 | M10: =(LEFT(E10,1)*$C10/$K$10)*100 -> 0 | N10: =(LEFT(F10,1)*$C10/$K$10)*100 -> 0 | O10: =(LEFT(G10,1)*$C10/$K$10)*100 -> 0.75 | P10: =(LEFT(H10,1)*$C10/$K$10)*100 -> 1.5 | Q10: =(LEFT(I10,1)*$C10/$K$10)*100 -> 2.25 | R10: =(LEFT(J10,1)*$C10/$K$10)*100 -> 3
B11: ='02. Models'!B11 -> Number of Projects/Phases | C11: ='02. Models'!D11 -> 0.03 | D11: The successful projects in business requirements that you have done at least one of the following tasks: analyze, design, develop, support, migrate, deploy, manage software projects or phases (FSOFTER can provide joined project is project rank of Project Rank A, Project Rank B, Project Rank C in Evidence section) | E11: 0: Not Required | F11: 1: ~01-03 Projects / Phases | G11: 2: ~04-05 Projects / Phases | H11: 3: ~06-10 Projects / Phases | I11: 4: ~11-15 Projects / Phases | J11: 5: ~16-20 Projects / Phases | K11: =MAX(LEFT(E11,1),LEFT(F11,1), LEFT(G11,1), LEFT(H11,1), LEFT(I11,1), LEFT(J11,1)) -> 5 | M11: =(LEFT(E11,1)*$C11/$K$11)*100 -> 0 | N11: =(LEFT(F11,1)*$C11/$K$11)*100 -> 0.6 | O11: =(LEFT(G11,1)*$C11/$K$11)*100 -> 1.2 | P11: =(LEFT(H11,1)*$C11/$K$11)*100 -> 1.8 | Q11: =(LEFT(I11,1)*$C11/$K$11)*100 -> 2.4 | R11: =(LEFT(J11,1)*$C11/$K$11)*100 -> 3
B12: ='02. Models'!B12 -> Community Contributions | C12: ='02. Models'!D12 -> 0.02 | D12: Business Analyst Activities to support/training other projects/team, presenter of workshop, contribute IP/solution… | E12: 0: Not Required | F12: 0: Not Required | G12: 1: Training, support other projects | H12: 2: Contribute >= 1 IP/Solution at project level | I12: 3: Contribute >= 1 IP/Solution at BU/FSU level | J12: 4: Contribute >= 1 IP/Solution at FSOFT level | K12: =MAX(LEFT(E12,1),LEFT(F12,1), LEFT(G12,1), LEFT(H12,1), LEFT(I12,1), LEFT(J12,1)) -> 4 | M12: =(LEFT(E12,1)*$C12/$K$12)*100 -> 0 | N12: =(LEFT(F12,1)*$C12/$K$12)*100 -> 0 | O12: =(LEFT(G12,1)*$C12/$K$12)*100 -> 0.5 | P12: =(LEFT(H12,1)*$C12/$K$12)*100 -> 1 | Q12: =(LEFT(I12,1)*$C12/$K$12)*100 -> 1.5 | R12: =(LEFT(J12,1)*$C12/$K$12)*100 -> 2
B13: ='02. Models'!B13 -> Industry Experiences (IT and Non-IT fields) | C13: ='02. Models'!D13 -> 0.1 | D13: Banking, Finance, Insurance, Aviation, Automotive, Oil and Gas, Health Care, ERP, Data Warehouse, Logistic, Real estate, Telecom, … | E13: 0: Fundamental awareness | F13: 0: Fundamental awareness | G13: 1: ~1 year experience | H13: 2: 2-3 years experience | I13: 3: 3-5 years experience | J13: 4: 5-7 years experience | K13: =MAX(LEFT(E13,1),LEFT(F13,1), LEFT(G13,1), LEFT(H13,1), LEFT(I13,1), LEFT(J13,1)) -> 4 | M13: =(LEFT(E13,1)*$C13/$K$13)*100 -> 0 | N13: =(LEFT(F13,1)*$C13/$K$13)*100 -> 0 | O13: =(LEFT(G13,1)*$C13/$K$13)*100 -> 2.5 | P13: =(LEFT(H13,1)*$C13/$K$13)*100 -> 5 | Q13: =(LEFT(I13,1)*$C13/$K$13)*100 -> 7.5 | R13: =(LEFT(J13,1)*$C13/$K$13)*100 -> 10
B14: ='02. Models'!B14 -> Consulting for Sales/Biding Teams | C14: ='02. Models'!D14 -> 0.02 | D14: Business Requirements, Technology Stack, Customer Experience, Vision Development, Processes and Activities, Pricing and Positioning Strategies, Drive Product Launch, … | E14: 0: Not Required | F14: 0: Not Required | G14: 1: ~1 year experience | H14: 2: 2-3 years experience | I14: 3: 3-5 years experience | J14: 4: 5-7 years experience | K14: =MAX(LEFT(E14,1),LEFT(F14,1), LEFT(G14,1), LEFT(H14,1), LEFT(I14,1), LEFT(J14,1)) -> 4 | M14: =(LEFT(E14,1)*$C14/$K$14)*100 -> 0 | N14: =(LEFT(F14,1)*$C14/$K$14)*100 -> 0 | O14: =(LEFT(G14,1)*$C14/$K$14)*100 -> 0.5 | P14: =(LEFT(H14,1)*$C14/$K$14)*100 -> 1 | Q14: =(LEFT(I14,1)*$C14/$K$14)*100 -> 1.5 | R14: =(LEFT(J14,1)*$C14/$K$14)*100 -> 2
B15: ='02. Models'!B15 -> Professional Business Analysis Skills | C15: =SUM(C16:C24) -> 0.4 | D15: FSOFTER is required to have one or more of the following specialized skills to perform assigned tasks | M15: =SUM(M16:M24) -> 16 | N15: =SUM(N16:N24) -> 19 | O15: =SUM(O16:O24) -> 22.6 | P15: =SUM(P16:P24) -> 29 | Q15: =SUM(Q16:Q24) -> 32 | R15: =SUM(R16:R24) -> 40
B16: ='02. Models'!B16 -> Business Analysis Planning & Monitoring (*) | C16: ='02. Models'!D16 -> 0.08 | D16: - Plan Business Analysis Approach - Plan Stakeholders Engagement - Plan Business Analysis Governance - Plan Business Analysis Information Management - Identify Business Analysis Performance Improvement | E16: 2: Limited Experience | F16: 2: Limited Experience | G16: 3: Intermediate | H16: 3: Intermediate | I16: 4: Advanced | J16: 5: Expert | K16: =MAX(LEFT(E16,1),LEFT(F16,1), LEFT(G16,1), LEFT(H16,1), LEFT(I16,1), LEFT(J16,1)) -> 5 | M16: =(LEFT(E16,1)*$C16/$K$16)*100 -> 3.2 | N16: =(LEFT(F16,1)*$C16/$K$16)*100 -> 3.2 | O16: =(LEFT(G16,1)*$C16/$K$16)*100 -> 4.8 | P16: =(LEFT(H16,1)*$C16/$K$16)*100 -> 4.8 | Q16: =(LEFT(I16,1)*$C16/$K$16)*100 -> 6.4 | R16: =(LEFT(J16,1)*$C16/$K$16)*100 -> 8
B17: ='02. Models'!B17 -> Requirement Elicitation & Collaboration (*) | C17: ='02. Models'!D17 -> 0.07 | D17: - Elicitation Preparation - Requirement Workshop / Conduct Elicitation - Requirement Transfer & Confirmation - Requirement Management & Communication - Stakeholders Management | E17: 2: Limited Experience | F17: 2: Limited Experience | G17: 2: Limited Experience | H17: 3: Intermediate | I17: 4: Advanced | J17: 5: Expert | K17: =MAX(LEFT(E17,1),LEFT(F17,1), LEFT(G17,1), LEFT(H17,1), LEFT(I17,1), LEFT(J17,1)) -> 5 | M17: =(LEFT(E17,1)*$C17/$K$17)*100 -> 2.8 | N17: =(LEFT(F17,1)*$C17/$K$17)*100 -> 2.8 | O17: =(LEFT(G17,1)*$C17/$K$17)*100 -> 2.8 | P17: =(LEFT(H17,1)*$C17/$K$17)*100 -> 4.2 | Q17: =(LEFT(I17,1)*$C17/$K$17)*100 -> 5.6 | R17: =(LEFT(J17,1)*$C17/$K$17)*100 -> 7
B18: ='02. Models'!B18 -> Business Requirement Analysis (*) | C18: ='02. Models'!D18 -> 0.1 | D18: - Requirement Specification - Requirement Verification - Requirement Validation - Requirement UI/UX Behavior Design & Principles - Requirement CX (Customer Experience / Customer Journey) - Solution Definition & Assessment | E18: 2: Limited Experience | F18: 3: Intermediate | G18: 3: Intermediate | H18: 4: Advanced | I18: 4: Advanced | J18: 5: Expert | K18: =MAX(LEFT(E18,1),LEFT(F18,1), LEFT(G18,1), LEFT(H18,1), LEFT(I18,1), LEFT(J18,1)) -> 5 | M18: =(LEFT(E18,1)*$C18/$K$18)*100 -> 4 | N18: =(LEFT(F18,1)*$C18/$K$18)*100 -> 6 | O18: =(LEFT(G18,1)*$C18/$K$18)*100 -> 6 | P18: =(LEFT(H18,1)*$C18/$K$18)*100 -> 8 | Q18: =(LEFT(I18,1)*$C18/$K$18)*100 -> 8 | R18: =(LEFT(J18,1)*$C18/$K$18)*100 -> 10
B19: ='02. Models'!B19 -> Business Solution Evaluation | C19: ='02. Models'!D19 -> 0.05 | D19: - Measure Solution Performance - Analyze Performance Measured - Assess Solution Limitations - Assess Enterprise Limitations - Recommend Actions to Increase Solution's Value | E19: 2: Limited Experience | F19: 2: Limited Experience | G19: 3: Intermediate | H19: 4: Advanced | I19: 4: Advanced | J19: 5: Expert | K19: =MAX(LEFT(E19,1),LEFT(F19,1), LEFT(G19,1), LEFT(H19,1), LEFT(I19,1), LEFT(J19,1)) -> 5 | M19: =(LEFT(E19,1)*$C19/$K$19)*100 -> 2 | N19: =(LEFT(F19,1)*$C19/$K$19)*100 -> 2 | O19: =(LEFT(G19,1)*$C19/$K$19)*100 -> 3 | P19: =(LEFT(H19,1)*$C19/$K$19)*100 -> 4 | Q19: =(LEFT(I19,1)*$C19/$K$19)*100 -> 4 | R19: =(LEFT(J19,1)*$C19/$K$19)*100 -> 5
B20: ='02. Models'!B20 -> Business Requirement Life-Cycle | C20: ='02. Models'!D20 -> 0.02 | D20: - Requirement Tracing - Requirement Maintenance - Requirement Prioritization - Requirement Change Management - Requirement Approval | E20: 2: Limited Experience | F20: 2: Limited Experience | G20: 3: Intermediate | H20: 4: Advanced | I20: 4: Advanced | J20: 5: Expert | K20: =MAX(LEFT(E20,1),LEFT(F20,1), LEFT(G20,1), LEFT(H20,1), LEFT(I20,1), LEFT(J20,1)) -> 5 | M20: =(LEFT(E20,1)*$C20/$K$20)*100 -> 0.8 | N20: =(LEFT(F20,1)*$C20/$K$20)*100 -> 0.8 | O20: =(LEFT(G20,1)*$C20/$K$20)*100 -> 1.2 | P20: =(LEFT(H20,1)*$C20/$K$20)*100 -> 1.6 | Q20: =(LEFT(I20,1)*$C20/$K$20)*100 -> 1.6 | R20: =(LEFT(J20,1)*$C20/$K$20)*100 -> 2
B21: ='02. Models'!B21 -> Business Strategy Design | C21: ='02. Models'!D21 -> 0.02 | D21: - Current State Analysis - Future State Analysis - Risk Analysis - Define Change Strategy | E21: 2: Limited Experience | F21: 2: Limited Experience | G21: 3: Intermediate | H21: 4: Advanced | I21: 4: Advanced | J21: 5: Expert | K21: =MAX(LEFT(E21,1),LEFT(F21,1), LEFT(G21,1), LEFT(H21,1), LEFT(I21,1), LEFT(J21,1)) -> 5 | M21: =(LEFT(E21,1)*$C21/$K$21)*100 -> 0.8 | N21: =(LEFT(F21,1)*$C21/$K$21)*100 -> 0.8 | O21: =(LEFT(G21,1)*$C21/$K$21)*100 -> 1.2 | P21: =(LEFT(H21,1)*$C21/$K$21)*100 -> 1.6 | Q21: =(LEFT(I21,1)*$C21/$K$21)*100 -> 1.6 | R21: =(LEFT(J21,1)*$C21/$K$21)*100 -> 2
B22: ='02. Models'!B22 -> Business Acumen and Mindsets | C22: ='02. Models'!D22 -> 0.03 | D22: - Understanding of fundamental business principles and best practices. - Analysis mindsets | E22: 2: Limited Experience | F22: 3: Intermediate | G22: 3: Intermediate | H22: 4: Advanced | I22: 4: Advanced | J22: 5: Expert | K22: =MAX(LEFT(E22,1),LEFT(F22,1), LEFT(G22,1), LEFT(H22,1), LEFT(I22,1), LEFT(J22,1)) -> 5 | M22: =(LEFT(E22,1)*$C22/$K$22)*100 -> 1.2 | N22: =(LEFT(F22,1)*$C22/$K$22)*100 -> 1.8 | O22: =(LEFT(G22,1)*$C22/$K$22)*100 -> 1.8 | P22: =(LEFT(H22,1)*$C22/$K$22)*100 -> 2.4 | Q22: =(LEFT(I22,1)*$C22/$K$22)*100 -> 2.4 | R22: =(LEFT(J22,1)*$C22/$K$22)*100 -> 3
B23: ='02. Models'!B23 -> Software Design and Technology Stack | C23: ='02. Models'!D23 -> 0.01 | D23: - Software Architecture Design - Object Oriented Design - Relational and Non-Relational Database Platforms | E23: 2: Limited Experience | F23: 2: Limited Experience | G23: 3: Intermediate | H23: 4: Advanced | I23: 4: Advanced | J23: 5: Expert | K23: =MAX(LEFT(E23,1),LEFT(F23,1), LEFT(G23,1), LEFT(H23,1), LEFT(I23,1), LEFT(J23,1)) -> 5 | M23: =(LEFT(E23,1)*$C23/$K$23)*100 -> 0.4 | N23: =(LEFT(F23,1)*$C23/$K$23)*100 -> 0.4 | O23: =(LEFT(G23,1)*$C23/$K$23)*100 -> 0.6 | P23: =(LEFT(H23,1)*$C23/$K$23)*100 -> 0.8 | Q23: =(LEFT(I23,1)*$C23/$K$23)*100 -> 0.8 | R23: =(LEFT(J23,1)*$C23/$K$23)*100 -> 1
B24: ='02. Models'!B24 -> Business Analysis Tools | C24: ='02. Models'!D24 -> 0.02 | D24: - Business Analysis Tools - UI/UX Design Tools - Architecture Design Tools - Communication Tools | E24: 2: Limited Experience | F24: 3: Intermediate | G24: 3: Intermediate | H24: 4: Advanced | I24: 4: Advanced | J24: 5: Expert | K24: =MAX(LEFT(E24,1),LEFT(F24,1), LEFT(G24,1), LEFT(H24,1), LEFT(I24,1), LEFT(J24,1)) -> 5 | M24: =(LEFT(E24,1)*$C24/$K$24)*100 -> 0.8 | N24: =(LEFT(F24,1)*$C24/$K$24)*100 -> 1.2 | O24: =(LEFT(G24,1)*$C24/$K$24)*100 -> 1.2 | P24: =(LEFT(H24,1)*$C24/$K$24)*100 -> 1.6 | Q24: =(LEFT(I24,1)*$C24/$K$24)*100 -> 1.6 | R24: =(LEFT(J24,1)*$C24/$K$24)*100 -> 2
B25: ='02. Models'!B25 -> Foreign Language & Certificates | C25: =SUM(C26:C29) -> 0.1 | D25: FSOFTER may have one or more of the following Foreign Language/Technical qualifications to perform assigned tasks | M25: =SUM(M26:M29) -> 4.8333333 | N25: =SUM(N26:N29) -> 5.8333333 | O25: =SUM(O26:O29) -> 7.6666667 | P25: =SUM(P26:P29) -> 8.6666667 | Q25: =SUM(Q26:Q29) -> 9.5 | R25: =SUM(R26:R29) -> 10
B26: ='02. Models'!B26 -> Foreign Language | C26: ='02. Models'!D26 -> 0.05 | D26: - Language Proficiency: English, Japanese, Korean, Chinese, Germany, French, Thailand | E26: 2: TOEIC 451-500, TOELF iBT 42-50, IELTS 4.0-4.5, CEFR B1, JP N4 or equivalent | F26: 3: TOEIC 501-600, TOELF iBT 51-60, IELTS 4.6-5.5, CEFR B1+, JP N4+ or equivalent | G26: 4: TOEIC 601-700, TOELF iBT 61-70, IELTS 5.6-6.5, CEFR B2, JP N3 or equivalent | H26: 5: TOEIC 701-800, TOELF iBT 71-80, IELTS 6.6-7.5, CEFR B2+, JP N3+ or equivalent | I26: 5: TOEIC 701-800, TOELF iBT 71-80, IELTS 6.6-7.5, CEFR B2+, JP N3+ or equivalent | J26: 5: TOEIC 701-800, TOELF iBT 71-80, IELTS 6.6-7.5, CEFR B2+, JP N3+ or equivalent | K26: =MAX(LEFT(E26,1),LEFT(F26,1), LEFT(G26,1), LEFT(H26,1), LEFT(I26,1), LEFT(J26,1)) -> 5 | M26: =(LEFT(E26,1)*$C26/$K$26)*100 -> 2 | N26: =(LEFT(F26,1)*$C26/$K$26)*100 -> 3 | O26: =(LEFT(G26,1)*$C26/$K$26)*100 -> 4 | P26: =(LEFT(H26,1)*$C26/$K$26)*100 -> 5 | Q26: =(LEFT(I26,1)*$C26/$K$26)*100 -> 5 | R26: =(LEFT(J26,1)*$C26/$K$26)*100 -> 5
B27: ='02. Models'!B27 -> Education Background | C27: ='02. Models'!D27 -> 0.02 | D27: Required one of degree in Engineering and Non-Engineering: - Engineering: Computer Science | Information Technology | Computer Engineering | Software Engineering, ... - Non-Engineering: Economics, Finances, Administrations, Social Science, Supply Chain, Logistics, ... | E27: 3-Bachelor Degree / Post-Baccalaureate Certificate | F27: 3-Bachelor Degree / Post-Baccalaureate Certificate | G27: 3-Bachelor Degree / Post-Baccalaureate Certificate | H27: 3-Bachelor Degree / Post-Baccalaureate Certificate | I27: 3-Bachelor Degree / Post-Baccalaureate Certificate | J27: 3-Bachelor Degree / Post-Baccalaureate Certificate | K27: =MAX(LEFT(E27,1),LEFT(F27,1), LEFT(G27,1), LEFT(H27,1), LEFT(I27,1), LEFT(J27,1)) -> 3 | M27: =(LEFT(E27,1)*$C27/$K$27)*100 -> 2 | N27: =(LEFT(F27,1)*$C27/$K$27)*100 -> 2 | O27: =(LEFT(G27,1)*$C27/$K$27)*100 -> 2 | P27: =(LEFT(H27,1)*$C27/$K$27)*100 -> 2 | Q27: =(LEFT(I27,1)*$C27/$K$27)*100 -> 2 | R27: =(LEFT(J27,1)*$C27/$K$27)*100 -> 2
B28: ='02. Models'!B28 -> Business Analysis Certifications | C28: ='02. Models'!D28 -> 0.02 | D28: - Required certificates in Business Analysis: Business Analyst, Software Business Analyst | E28: 1: At least 1 Certified Business Analyst Foundation or Equivalent | F28: 1: At least 1 Certified Business Analyst Foundation or Equivalent | G28: 2: Certified Business Analyst Advance or Equivalent | H28: 2: Certified Business Analyst Advance or Equivalent | I28: 3: >=2 Certificates of Business Analyst Advance or Equivalent | J28: 4: >=3 Certificates of Business Analyst Advance or Equivalent | K28: =MAX(LEFT(E28,1),LEFT(F28,1), LEFT(G28,1), LEFT(H28,1), LEFT(I28,1), LEFT(J28,1)) -> 4 | M28: =(LEFT(E28,1)*$C28/$K$28)*100 -> 0.5 | N28: =(LEFT(F28,1)*$C28/$K$28)*100 -> 0.5 | O28: =(LEFT(G28,1)*$C28/$K$28)*100 -> 1 | P28: =(LEFT(H28,1)*$C28/$K$28)*100 -> 1 | Q28: =(LEFT(I28,1)*$C28/$K$28)*100 -> 1.5 | R28: =(LEFT(J28,1)*$C28/$K$28)*100 -> 2
B29: ='02. Models'!B29 -> Individual Learning in Year | C29: ='02. Models'!D29 -> 0.01 | D29: - Joined the training courses of any FSOFT program (upskilling, reskilling, fasttrack, internal training) related to Business Analysis in year (ranking year) | E29: 1: Join <=2 training or workshop | F29: 1: Join <=2 training or workshop | G29: 2: Join >=3 training or workshop | H29: 2: Join >=3 training or workshop | I29: 3: Join >=5 training or workshop | J29: 3: Join >=5 training or workshop | K29: =MAX(LEFT(E29,1),LEFT(F29,1), LEFT(G29,1), LEFT(H29,1), LEFT(I29,1), LEFT(J29,1)) -> 3 | M29: =(LEFT(E29,1)*$C29/$K$29)*100 -> 0.33333333 | N29: =(LEFT(F29,1)*$C29/$K$29)*100 -> 0.33333333 | O29: =(LEFT(G29,1)*$C29/$K$29)*100 -> 0.66666667 | P29: =(LEFT(H29,1)*$C29/$K$29)*100 -> 0.66666667 | Q29: =(LEFT(I29,1)*$C29/$K$29)*100 -> 1 | R29: =(LEFT(J29,1)*$C29/$K$29)*100 -> 1
B30: ='02. Models'!B30 -> Non-Engineering and Softskills | C30: =SUM(C31:C35) -> 0.1 | D30: FSOFTER is required to have one or more of the following soft skills and other skills to perform assigned tasks | M30: =SUM(M31:M35) -> 2.5 | N30: =SUM(N31:N35) -> 3 | O30: =SUM(O31:O35) -> 5 | P30: =SUM(P31:P35) -> 6.5 | Q30: =SUM(Q31:Q35) -> 8.5 | R30: =SUM(R31:R35) -> 10
B31: ='02. Models'!B31 -> Communication and Problem Solving | C31: ='02. Models'!D31 -> 0.03 | D31: - Team Work - Leadership & Motivation - Communication - Problem Solving - Change Management - Networking/ Relationship building | E31: 1: Fundamental Awareness | F31: 1: Fundamental Awareness | G31: 2: Limited Experience | H31: 2: Limited Experience | I31: 3: Intermediate | J31: 4: Advanced | K31: =MAX(LEFT(E31,1),LEFT(F31,1), LEFT(G31,1), LEFT(H31,1), LEFT(I31,1), LEFT(J31,1)) -> 4 | M31: =(LEFT(E31,1)*$C31/$K$31)*100 -> 0.75 | N31: =(LEFT(F31,1)*$C31/$K$31)*100 -> 0.75 | O31: =(LEFT(G31,1)*$C31/$K$31)*100 -> 1.5 | P31: =(LEFT(H31,1)*$C31/$K$31)*100 -> 1.5 | Q31: =(LEFT(I31,1)*$C31/$K$31)*100 -> 2.25 | R31: =(LEFT(J31,1)*$C31/$K$31)*100 -> 3
B32: ='02. Models'!B33 -> Analytical and Critical Thinking | C32: ='02. Models'!D33 -> 0.02 | D32: - Research - Forecasting - Data mining - Data and metrics interpreting - Reporting - Organization | E32: 1: Fundamental Awareness | F32: 2: Limited Experience | G32: 2: Limited Experience | H32: 3: Intermediate | I32: 4: Advanced | J32: 4: Advanced | K32: =MAX(LEFT(E32,1),LEFT(F32,1), LEFT(G32,1), LEFT(H32,1), LEFT(I32,1), LEFT(J32,1)) -> 4 | M32: =(LEFT(E32,1)*$C32/$K$32)*100 -> 0.5 | N32: =(LEFT(F32,1)*$C32/$K$32)*100 -> 1 | O32: =(LEFT(G32,1)*$C32/$K$32)*100 -> 1 | P32: =(LEFT(H32,1)*$C32/$K$32)*100 -> 1.5 | Q32: =(LEFT(I32,1)*$C32/$K$32)*100 -> 2 | R32: =(LEFT(J32,1)*$C32/$K$32)*100 -> 2
B33: ='02. Models'!B32 -> Organization and Industry Knowledge | C33: ='02. Models'!D32 -> 0.02 | D33: - Agile Mindset - Process Understanding - Product Understanding - Market trends & Challenges - Market drivers - Customer Segmentation Understanding - Organization Knowledge | E33: 1: Fundamental Awareness | F33: 1: Fundamental Awareness | G33: 2: Limited Experience | H33: 3: Intermediate | I33: 3: Intermediate | J33: 4: Advanced | K33: =MAX(LEFT(E33,1),LEFT(F33,1), LEFT(G33,1), LEFT(H33,1), LEFT(I33,1), LEFT(J33,1)) -> 4 | M33: =(LEFT(E33,1)*$C33/$K$33)*100 -> 0.5 | N33: =(LEFT(F33,1)*$C33/$K$33)*100 -> 0.5 | O33: =(LEFT(G33,1)*$C33/$K$33)*100 -> 1 | P33: =(LEFT(H33,1)*$C33/$K$33)*100 -> 1.5 | Q33: =(LEFT(I33,1)*$C33/$K$33)*100 -> 1.5 | R33: =(LEFT(J33,1)*$C33/$K$33)*100 -> 2
B34: ='02. Models'!B34 -> Project Risk Management | C34: ='02. Models'!D34 -> 0.02 | D34: - Understand and utilize process of implementing risk response plans - Tracking identified risks, monitoring residual risks, identifying new risks - Evaluating risk process effectiveness throughout the project. - Forecast risk that may occur in range of project that the team is responsible for. - Analyze and perform preventitive actions to reduce risks raised by members. - In the case that risks cannot be closed, raise the risk to leader/mamager and discuss with leader/manger to find out preventitive actions then follow up. (the risk in Methodology is the risk of Business solution. the risk mentioned in this sheet derives from project activities, especially in oursourcing project.) | E34: 1: Fundamental Awareness | F34: 1: Fundamental Awareness | G34: 2: Limited Experience | H34: 3: Intermediate | I34: 4: Advanced | J34: 4: Advanced | K34: =MAX(LEFT(E34,1),LEFT(F34,1), LEFT(G34,1), LEFT(H34,1), LEFT(I34,1), LEFT(J34,1)) -> 4 | M34: =(LEFT(E34,1)*$C34/$K$34)*100 -> 0.5 | N34: =(LEFT(F34,1)*$C34/$K$34)*100 -> 0.5 | O34: =(LEFT(G34,1)*$C34/$K$34)*100 -> 1 | P34: =(LEFT(H34,1)*$C34/$K$34)*100 -> 1.5 | Q34: =(LEFT(I34,1)*$C34/$K$34)*100 -> 2 | R34: =(LEFT(J34,1)*$C34/$K$34)*100 -> 2
B35: ='02. Models'!B35 -> Project Human Resource Management | C35: ='02. Models'!D35 -> 0.01 | D35: - Understand the ability of each BA to assign appropriate projects/tasks. - Understand project request for BA service to determine proper resource plan. - Regularly control BA allocation to optimize resource. - Monitor and control progress and status of BA involvement in each and every project; detect, resolve and followup to close any issue arising. - Evaluate performance, identify strengths as well as improvement points and propose career path for each BA | E35: 1: Fundamental Awareness | F35: 1: Fundamental Awareness | G35: 2: Limited Experience | H35: 2: Limited Experience | I35: 3: Intermediate | J35: 4: Advanced | K35: =MAX(LEFT(E35,1),LEFT(F35,1), LEFT(G35,1), LEFT(H35,1), LEFT(I35,1), LEFT(J35,1)) -> 4 | M35: =(LEFT(E35,1)*$C35/$K$35)*100 -> 0.25 | N35: =(LEFT(F35,1)*$C35/$K$35)*100 -> 0.25 | O35: =(LEFT(G35,1)*$C35/$K$35)*100 -> 0.5 | P35: =(LEFT(H35,1)*$C35/$K$35)*100 -> 0.5 | Q35: =(LEFT(I35,1)*$C35/$K$35)*100 -> 0.75 | R35: =(LEFT(J35,1)*$C35/$K$35)*100 -> 1

Sheet 05. Job Rankings
A1: Job Rankings | E1: CANDIDATE'S SELF-RANKED RESULTS SCORED BY MANAGER / LEADER / HOD | H1: YOUR ASSESSMENT RANK TO COMPARE CORRESPONDING RANK | J1: ="Number of the required criteria not passed for RANK: " & H3 -> Number of the required criteria not passed for RANK: BANE04 | K1: CHOOSE EXPECTED RANK TO COMPARE | M1: ACTIONS TO IMPROVE YOUR RANKINGS
B2: Software Business Analyst Role - Job Assessment
B3: [Name] - [Account] | E3: =IF(J5=0,"YOUR ASSESSMENT RANK: "&IF(G3>='04. Job Descriptions'!R4,'04. Job Descriptions'!R2&"-"&'04. Job Descriptions'!R3,IF(G3>='04. Job Descriptions'!Q4,'04. Job Descriptions'!Q2&"-"&'04. Job Descriptions'!Q3,IF(G3>='04. Job Descriptions'!P4,'04. Job Descriptions'!P2&"-"&'04. Job Descriptions'!P3,IF(G3>='04. Job Descriptions'!O4,'04. Job Descriptions'!O2&"-"&'04. Job Descriptions'!O3,IF(G3>='04. Job Descriptions'!N4,'04. Job Descriptions'!N2&"-"&'04. Job Descriptions'!N3,IF(G3>='04. Job Descriptions'!M4,'04. Job Descriptions'!M2&"-"&'04. Job Descriptions'!M3,'06. Assessment Summary'!E5)))))),"YOU ACHIEVED RANK: "&VLOOKUP(LEFT(H3,5)&RIGHT(H3,1)-1,'08. Definitions'!$C$14:$D$20,2,FALSE)&"-"&LEFT(H3,5)&RIGHT(H3,1)-1) -> YOU ACHIEVED RANK: Senior Business Analyst-BANE03 | G3: =G5+G8+G15+G25+G30 -> 70.316667 | H3: =IF(G3>='04. Job Descriptions'!R4,'04. Job Descriptions'!R3,IF(G3>='04. Job Descriptions'!Q4,'04. Job Descriptions'!Q3,IF(G3>='04. Job Descriptions'!P4,'04. Job Descriptions'!P3,IF(G3>='04. Job Descriptions'!O4,'04. Job Descriptions'!O3,IF(G3>='04. Job Descriptions'!N4,'04. Job Descriptions'!N3,IF(G3>='04. Job Descriptions'!M4,'04. Job Descriptions'!M3,'06. Assessment Summary'!E5)))))) -> BANE04 | K3: BANE04 | L3: =L5+L8+L15+L25+L30 -> 67.816667
B4: Assessment Items | C4: Explanation of Assessment Items | D4: Weighted % | E4: Choose competency level for each evaluation criteria | F4: Add remarks or evidences for each evaluation if any | G4: Actual Score | H4: ="Competency Level for RANK: " & H3 -> Competency Level for RANK: BANE04 | I4: =H3 & " Score(s)" -> BANE04 Score(s) | K4: Required Competency Level for Your Expected RANK | L4: Required Score | M4: Need to improve? | N4: Action to improve | O4: Deadline
B5: ='04. Job Descriptions'!B5 -> Roles & Responsibilities | C5: ='04. Job Descriptions'!D5 -> FSOFTER is required to have the role and responsibility to perform one or more of the following tasks | D5: ='04. Job Descriptions'!C5 -> 0.15 | G5: =SUM(G6:G7) -> 10.35 | I5: =SUM(I6:I7) -> 10.35 | J5: =COUNTIF(J6:J35,"Yes") -> 1 | L5: =SUM(L6:L7) -> 10.35
B6: ='04. Job Descriptions'!B6 -> Roles and Responsibilities | C6: ='04. Job Descriptions'!D6 -> Implementing all the processes and activities related to business analysis which can be analyzing and designing functional and non-functional requirements to the development, client or production environment, including but not limited to following responsibilities: BANE01: - Has responsibility for documenting requirement, supporting communicate requirement to stakeholders (under guidance) as role BA member. - Project Diversity and Complexity - Low: >=5 items in Elementary Complexity Criteria BANE02: - Has responsibility for gathering requirement, elaborating and validating gathered requirement as role BA member. - Project Diversity and Complexity - Normal: All items of Elementary Complexity Criteria & >= 1 item in General Advanced Complexity Criteria BANE03: - Has responsibility for designing, analyzing and evaluating business solution to ensure that it aligns with the project's goal as role BA member. - Project Diversity and Complexity - Medium: >= 4 items of General Advanced Complexity Criteria & >= 2 items of Management Complexity Criteria OR >= 4 items of General Advanced Complexity Criteria & >=1 item in Consultant Complexity Criteria BANE04: - Has responsibility for defining requirement approach & process, planning and monitoring business analysis activities as role BA consultant. - Project Diversity and Complexity - Complex: >= 4 items in General Advanced Complexity Criteria & All items in Management Complexity Criteria OR >= 5 items in General Advanced Complexity Criteria & >= 2 item of Consultant Complexity Criteria BANE05: - Has responsibility for performing system evaluation & enterprise solution consultation as role BA consultant. - Project Diversity and Complexity - Complex: >= 4 items in General Advanced Complexity Criteria & All items in Management Complexity Criteria OR >= 5 items in General Advanced Complexity Criteria & >= 2 item of Consultant Complexity Criteria BANE06: - Has responsibility for performing system evaluation & enterprise solution consultation as role BA consultant. - Project Diversity and Complexity - Very Complex: >= 4 items of Advanced Complexity Criteria & All items of Management Complexity Criteria OR All items in General Advanced & All Consultant Complexity Criteria | D6: ='04. Job Descriptions'!C6 -> 0.12 | E6: 4: Create (BANE04) | G6: =IFERROR((LEFT(E6,1)*$D6/'04. Job Descriptions'!K6)*100,0) -> 9.6 | H6: =IFERROR(HLOOKUP(H3,'04. Job Descriptions'!$B$4:$J$35,3,0),"NA") -> 4: Create (BANE04) | I6: =IFERROR(HLOOKUP($H$3,'04. Job Descriptions'!$M$3:$R$35,4,0),"NA") -> 9.6 | J6: =IF(G6<I6,"Yes","No") -> No | K6: =IFERROR(HLOOKUP($K$3,'04. Job Descriptions'!$B$4:$J$35,3,0),"NA") -> 4: Create (BANE04) | L6: =IFERROR(HLOOKUP($K$3,'04. Job Descriptions'!$M$3:$R$35,4,0),"NA") -> 9.6 | M6: =IF(G6<L6,"Yes","No") -> No
B7: ='04. Job Descriptions'!B7 -> Team Size To Lead for BA Leader | C7: ='04. Job Descriptions'!D7 -> 4: Global Level - Have at least 70% BA2, 10% BA3, 3% BA4, 0.75%BA5 3: FSOFT Level - Have at least 50% BA2, 10% BA3, 3% BA4, 0.75%BA5 2: FSU Level - Have at least 50% BA2, 12% BA3, 3% BA4 1: BU Level - Have at least 50% BA2, 12% BA3 0: Not Required | D7: ='04. Job Descriptions'!C7 -> 0.03 | E7: 1: BU Level | G7: =IFERROR((LEFT(E7,1)*$D7/'04. Job Descriptions'!K7)*100,0) -> 0.75 | H7: =IFERROR(HLOOKUP(H3,'04. Job Descriptions'!$B$4:$J$35,4,0),"NA") -> 1: BU Level | I7: =IFERROR(HLOOKUP($H$3,'04. Job Descriptions'!$M$3:$R$35,5,0),"NA") -> 0.75 | J7: =IF(G7<I7,"Yes","No") -> No | K7: =IFERROR(HLOOKUP($K$3,'04. Job Descriptions'!$B$4:$J$35,4,0),"NA") -> 1: BU Level | L7: =IFERROR(HLOOKUP($K$3,'04. Job Descriptions'!$M$3:$R$35,5,0),"NA") -> 0.75 | M7: =IF(G7<L7,"Yes","No") -> No
B8: ='04. Job Descriptions'!B8 -> Experiences & Contributions | C8: ='04. Job Descriptions'!D8 -> FSOFTER is required to have one or more of the following professional experiences and project contributions | D8: ='04. Job Descriptions'!C8 -> 0.25 | G8: =SUM(G9:G14) -> 17.4 | I8: =SUM(I9:I14) -> 13.3 | L8: =SUM(L9:L14) -> 13.3
B9: ='04. Job Descriptions'!B9 -> Business Analysis Experiences (*) | C9: ='04. Job Descriptions'!D9 -> Number of years working as Business Analyst, Software Business Analyst, Software Development Life Cycle, Team Work, Agile Mindset | D9: ='04. Job Descriptions'!C9 -> 0.05 | E9: 3: 3-5 years experience | G9: =IFERROR((LEFT(E9,1)*D9/'04. Job Descriptions'!K9)*100,0) -> 3 | H9: =IFERROR(HLOOKUP($H$3,'04. Job Descriptions'!$B$4:$J$35,6,0),"NA") -> 3: 3-5 years experience | I9: =IFERROR(HLOOKUP($H$3,'04. Job Descriptions'!$M$3:$R$35,7,0),"NA") -> 3 | J9: =IF(G9<I9,"Yes","No") -> No | K9: =IFERROR(HLOOKUP($K$3,'04. Job Descriptions'!$B$4:$J$35,6,0),"NA") -> 3: 3-5 years experience | L9: =IFERROR(HLOOKUP($K$3,'04. Job Descriptions'!$M$3:$R$35,7,0),"NA") -> 3 | M9: =IF(G9<L9,"Yes","No") -> No
B10: ='04. Job Descriptions'!B10 -> Subordinate Development | C10: ='04. Job Descriptions'!D10 -> Number of team members or number of people trained/coached | D10: ='04. Job Descriptions'!C10 -> 0.03 | E10: 2: 5-10 Members or Coaching 3-4 Junior BA | G10: =IFERROR((LEFT(E10,1)*D10/'04. Job Descriptions'!K10)*100,0) -> 1.5 | H10: =IFERROR(HLOOKUP($H$3,'04. Job Descriptions'!$B$4:$J$35,7,0),"NA") -> 2: 5-10 Members or Coaching 3-4 Junior BA | I10: =IFERROR(HLOOKUP($H$3,'04. Job Descriptions'!$M$3:$R$35,8,0),"NA") -> 1.5 | K10: =IFERROR(HLOOKUP($K$3,'04. Job Descriptions'!$B$4:$J$35,7,0),"NA") -> 2: 5-10 Members or Coaching 3-4 Junior BA | L10: =IFERROR(HLOOKUP($K$3,'04. Job Descriptions'!$M$3:$R$35,8,0),"NA") -> 1.5 | M10: =IF(G10<L10,"Yes","No") -> No
B11: ='04. Job Descriptions'!B11 -> Number of Projects/Phases | C11: ='04. Job Descriptions'!D11 -> The successful projects in business requirements that you have done at least one of the following tasks: analyze, design, develop, support, migrate, deploy, manage software projects or phases (FSOFTER can provide joined project is project rank of Project Rank A, Project Rank B, Project Rank C in Evidence section) | D11: ='04. Job Descriptions'!C11 -> 0.03 | E11: 4: ~11-15 Projects / Phases | G11: =IFERROR((LEFT(E11,1)*D11/'04. Job Descriptions'!K11)*100,0) -> 2.4 | H11: =IFERROR(HLOOKUP($H$3,'04. Job Descriptions'!$B$4:$J$35,8,0),"NA") -> 3: ~06-10 Projects / Phases | I11: =IFERROR(HLOOKUP($H$3,'04. Job Descriptions'!$M$3:$R$35,9,0),"NA") -> 1.8 | K11: =IFERROR(HLOOKUP($K$3,'04. Job Descriptions'!$B$4:$J$35,8,0),"NA") -> 3: ~06-10 Projects / Phases | L11: =IFERROR(HLOOKUP($K$3,'04. Job Descriptions'!$M$3:$R$35,9,0),"NA") -> 1.8 | M11: =IF(G11<L11,"Yes","No") -> No
B12: ='04. Job Descriptions'!B12 -> Community Contributions | C12: ='04. Job Descriptions'!D12 -> Business Analyst Activities to support/training other projects/team, presenter of workshop, contribute IP/solution… | D12: ='04. Job Descriptions'!C12 -> 0.02 | E12: 3: Lecturer/Trainer of Technical workshop of FSU | G12: =IFERROR((LEFT(E12,1)*D12/'04. Job Descriptions'!K12)*100,0) -> 1.5 | H12: =IFERROR(HLOOKUP($H$3,'04. Job Descriptions'!$B$4:$J$35,9,0),"NA") -> 2: Contribute >= 1 IP/Solution at project level | I12: =IFERROR(HLOOKUP($H$3,'04. Job Descriptions'!$M$3:$R$35,10,0),"NA") -> 1 | K12: =IFERROR(HLOOKUP($K$3,'04. Job Descriptions'!$B$4:$J$35,9,0),"NA") -> 2: Contribute >= 1 IP/Solution at project level | L12: =IFERROR(HLOOKUP($K$3,'04. Job Descriptions'!$M$3:$R$35,10,0),"NA") -> 1 | M12: =IF(G12<L12,"Yes","No") -> No
B13: ='04. Job Descriptions'!B13 -> Industry Experiences (IT and Non-IT fields) | C13: ='04. Job Descriptions'!D13 -> Banking, Finance, Insurance, Aviation, Automotive, Oil and Gas, Health Care, ERP, Data Warehouse, Logistic, Real estate, Telecom, … | D13: ='04. Job Descriptions'!C13 -> 0.1 | E13: 3: 3-5 years experience | G13: =IFERROR((LEFT(E13,1)*D13/'04. Job Descriptions'!K13)*100,0) -> 7.5 | H13: =IFERROR(HLOOKUP($H$3,'04. Job Descriptions'!$B$4:$J$35,10,0),"NA") -> 2: 2-3 years experience | I13: =IFERROR(HLOOKUP($H$3,'04. Job Descriptions'!$M$3:$R$35,11,0),"NA") -> 5 | K13: =IFERROR(HLOOKUP($K$3,'04. Job Descriptions'!$B$4:$J$35,10,0),"NA") -> 2: 2-3 years experience | L13: =IFERROR(HLOOKUP($K$3,'04. Job Descriptions'!$M$3:$R$35,11,0),"NA") -> 5 | M13: =IF(G13<L13,"Yes","No") -> No
B14: ='04. Job Descriptions'!B14 -> Consulting for Sales/Biding Teams | C14: ='04. Job Descriptions'!D14 -> Business Requirements, Technology Stack, Customer Experience, Vision Development, Processes and Activities, Pricing and Positioning Strategies, Drive Product Launch, … | D14: ='04. Job Descriptions'!C14 -> 0.02 | E14: 3: 3-5 years experience | G14: =IFERROR((LEFT(E14,1)*D14/'04. Job Descriptions'!K14)*100,0) -> 1.5 | H14: =IFERROR(HLOOKUP($H$3,'04. Job Descriptions'!$B$4:$J$35,11,0),"NA") -> 2: 2-3 years experience | I14: =IFERROR(HLOOKUP($H$3,'04. Job Descriptions'!$M$3:$R$35,12,0),"NA") -> 1 | K14: =IFERROR(HLOOKUP($K$3,'04. Job Descriptions'!$B$4:$J$35,11,0),"NA") -> 2: 2-3 years experience | L14: =IFERROR(HLOOKUP($K$3,'04. Job Descriptions'!$M$3:$R$35,12,0),"NA") -> 1 | M14: =IF(G14<L14,"Yes","No") -> No
B15: ='04. Job Descriptions'!B15 -> Professional Business Analysis Skills | C15: ='04. Job Descriptions'!D15 -> FSOFTER is required to have one or more of the following specialized skills to perform assigned tasks | D15: ='04. Job Descriptions'!C15 -> 0.4 | G15: =SUM(G16:G24) -> 27.4 | I15: =SUM(I16:I24) -> 29 | L15: =SUM(L16:L24) -> 29
B16: ='04. Job Descriptions'!B16 -> Business Analysis Planning & Monitoring (*) | C16: ='04. Job Descriptions'!D16 -> - Plan Business Analysis Approach - Plan Stakeholders Engagement - Plan Business Analysis Governance - Plan Business Analysis Information Management - Identify Business Analysis Performance Improvement | D16: ='04. Job Descriptions'!C16 -> 0.08 | E16: 2: Limited Experience | G16: =IFERROR((LEFT(E16,1)*D16/'04. Job Descriptions'!K16)*100,0) -> 3.2 | H16: =IFERROR(HLOOKUP($H$3,'04. Job Descriptions'!$B$4:$J$35,13,0),"NA") -> 3: Intermediate | I16: =IFERROR(HLOOKUP($H$3,'04. Job Descriptions'!$M$3:$R$35,14,0),"NA") -> 4.8 | J16: =IF(G16<I16,"Yes","No") -> Yes | K16: =IFERROR(HLOOKUP($K$3,'04. Job Descriptions'!$B$4:$J$35,13,0),"NA") -> 3: Intermediate | L16: =IFERROR(HLOOKUP($K$3,'04. Job Descriptions'!$M$3:$R$35,14,0),"NA") -> 4.8 | M16: =IF(G16<L16,"Yes","No") -> Yes
B17: ='04. Job Descriptions'!B17 -> Requirement Elicitation & Collaboration (*) | C17: ='04. Job Descriptions'!D17 -> - Elicitation Preparation - Requirement Workshop / Conduct Elicitation - Requirement Transfer & Confirmation - Requirement Management & Communication - Stakeholders Management | D17: ='04. Job Descriptions'!C17 -> 0.07 | E17: 3: Intermediate | G17: =IFERROR((LEFT(E17,1)*D17/'04. Job Descriptions'!K17)*100,0) -> 4.2 | H17: =IFERROR(HLOOKUP($H$3,'04. Job Descriptions'!$B$4:$J$35,14,0),"NA") -> 3: Intermediate | I17: =IFERROR(HLOOKUP($H$3,'04. Job Descriptions'!$M$3:$R$35,15,0),"NA") -> 4.2 | J17: =IF(G17<I17,"Yes","No") -> No | K17: =IFERROR(HLOOKUP($K$3,'04. Job Descriptions'!$B$4:$J$35,14,0),"NA") -> 3: Intermediate | L17: =IFERROR(HLOOKUP($K$3,'04. Job Descriptions'!$M$3:$R$35,15,0),"NA") -> 4.2 | M17: =IF(G17<L17,"Yes","No") -> No
B18: ='04. Job Descriptions'!B18 -> Business Requirement Analysis (*) | C18: ='04. Job Descriptions'!D18 -> - Requirement Specification - Requirement Verification - Requirement Validation - Requirement UI/UX Behavior Design & Principles - Requirement CX (Customer Experience / Customer Journey) - Solution Definition & Assessment | D18: ='04. Job Descriptions'!C18 -> 0.1 | E18: 4: Advanced | G18: =IFERROR((LEFT(E18,1)*D18/'04. Job Descriptions'!K18)*100,0) -> 8 | H18: =IFERROR(HLOOKUP($H$3,'04. Job Descriptions'!$B$4:$J$35,15,0),"NA") -> 4: Advanced | I18: =IFERROR(HLOOKUP($H$3,'04. Job Descriptions'!$M$3:$R$35,16,0),"NA") -> 8 | J18: =IF(G18<I18,"Yes","No") -> No | K18: =IFERROR(HLOOKUP($K$3,'04. Job Descriptions'!$B$4:$J$35,15,0),"NA") -> 4: Advanced | L18: =IFERROR(HLOOKUP($K$3,'04. Job Descriptions'!$M$3:$R$35,16,0),"NA") -> 8 | M18: =IF(G18<L18,"Yes","No") -> No
B19: ='04. Job Descriptions'!B19 -> Business Solution Evaluation | C19: ='04. Job Descriptions'!D19 -> - Measure Solution Performance - Analyze Performance Measured - Assess Solution Limitations - Assess Enterprise Limitations - Recommend Actions to Increase Solution's Value | D19: ='04. Job Descriptions'!C19 -> 0.05 | E19: 4: Advanced | G19: =IFERROR((LEFT(E19,1)*D19/'04. Job Descriptions'!K19)*100,0) -> 4 | H19: =IFERROR(HLOOKUP($H$3,'04. Job Descriptions'!$B$4:$J$35,16,0),"NA") -> 4: Advanced | I19: =IFERROR(HLOOKUP($H$3,'04. Job Descriptions'!$M$3:$R$35,17,0),"NA") -> 4 | K19: =IFERROR(HLOOKUP($K$3,'04. Job Descriptions'!$B$4:$J$35,16,0),"NA") -> 4: Advanced | L19: =IFERROR(HLOOKUP($K$3,'04. Job Descriptions'!$M$3:$R$35,17,0),"NA") -> 4 | M19: =IF(G19<L19,"Yes","No") -> No
B20: ='04. Job Descriptions'!B20 -> Business Requirement Life-Cycle | C20: ='04. Job Descriptions'!D20 -> - Requirement Tracing - Requirement Maintenance - Requirement Prioritization - Requirement Change Management - Requirement Approval | D20: ='04. Job Descriptions'!C20 -> 0.02 | E20: 4: Advanced | G20: =IFERROR((LEFT(E20,1)*D20/'04. Job Descriptions'!K20)*100,0) -> 1.6 | H20: =IFERROR(HLOOKUP($H$3,'04. Job Descriptions'!$B$4:$J$35,17,0),"NA") -> 4: Advanced | I20: =IFERROR(HLOOKUP($H$3,'04. Job Descriptions'!$M$3:$R$35,18,0),"NA") -> 1.6 | K20: =IFERROR(HLOOKUP($K$3,'04. Job Descriptions'!$B$4:$J$35,17,0),"NA") -> 4: Advanced | L20: =IFERROR(HLOOKUP($K$3,'04. Job Descriptions'!$M$3:$R$35,18,0),"NA") -> 1.6 | M20: =IF(G20<L20,"Yes","No") -> No
B21: ='04. Job Descriptions'!B21 -> Business Strategy Design | C21: ='04. Job Descriptions'!D21 -> - Current State Analysis - Future State Analysis - Risk Analysis - Define Change Strategy | D21: ='04. Job Descriptions'!C21 -> 0.02 | E21: 4: Advanced | G21: =IFERROR((LEFT(E21,1)*D21/'04. Job Descriptions'!K21)*100,0) -> 1.6 | H21: =IFERROR(HLOOKUP($H$3,'04. Job Descriptions'!$B$4:$J$35,18,0),"NA") -> 4: Advanced | I21: =IFERROR(HLOOKUP($H$3,'04. Job Descriptions'!$M$3:$R$35,19,0),"NA") -> 1.6 | K21: =IFERROR(HLOOKUP($K$3,'04. Job Descriptions'!$B$4:$J$35,18,0),"NA") -> 4: Advanced | L21: =IFERROR(HLOOKUP($K$3,'04. Job Descriptions'!$M$3:$R$35,19,0),"NA") -> 1.6 | M21: =IF(G21<L21,"Yes","No") -> No
B22: ='04. Job Descriptions'!B22 -> Business Acumen and Mindsets | C22: ='04. Job Descriptions'!D22 -> - Understanding of fundamental business principles and best practices. - Analysis mindsets | D22: ='04. Job Descriptions'!C22 -> 0.03 | E22: 4: Advanced | G22: =IFERROR((LEFT(E22,1)*D22/'04. Job Descriptions'!K22)*100,0) -> 2.4 | H22: =IFERROR(HLOOKUP($H$3,'04. Job Descriptions'!$B$4:$J$35,19,0),"NA") -> 4: Advanced | I22: =IFERROR(HLOOKUP($H$3,'04. Job Descriptions'!$M$3:$R$35,20,0),"NA") -> 2.4 | K22: =IFERROR(HLOOKUP($K$3,'04. Job Descriptions'!$B$4:$J$35,19,0),"NA") -> 4: Advanced | L22: =IFERROR(HLOOKUP($K$3,'04. Job Descriptions'!$M$3:$R$35,20,0),"NA") -> 2.4 | M22: =IF(G22<L22,"Yes","No") -> No
B23: ='04. Job Descriptions'!B23 -> Software Design and Technology Stack | C23: ='04. Job Descriptions'!D23 -> - Software Architecture Design - Object Oriented Design - Relational and Non-Relational Database Platforms | D23: ='04. Job Descriptions'!C23 -> 0.01 | E23: 4: Advanced | G23: =IFERROR((LEFT(E23,1)*D23/'04. Job Descriptions'!K23)*100,0) -> 0.8 | H23: =IFERROR(HLOOKUP($H$3,'04. Job Descriptions'!$B$4:$J$35,20,0),"NA") -> 4: Advanced | I23: =IFERROR(HLOOKUP($H$3,'04. Job Descriptions'!$M$3:$R$35,21,0),"NA") -> 0.8 | K23: =IFERROR(HLOOKUP($K$3,'04. Job Descriptions'!$B$4:$J$35,20,0),"NA") -> 4: Advanced | L23: =IFERROR(HLOOKUP($K$3,'04. Job Descriptions'!$M$3:$R$35,21,0),"NA") -> 0.8 | M23: =IF(G23<L23,"Yes","No") -> No
B24: ='04. Job Descriptions'!B24 -> Business Analysis Tools | C24: ='04. Job Descriptions'!D24 -> - Business Analysis Tools - UI/UX Design Tools - Architecture Design Tools - Communication Tools | D24: ='04. Job Descriptions'!C24 -> 0.02 | E24: 4: Advanced | G24: =IFERROR((LEFT(E24,1)*D24/'04. Job Descriptions'!K24)*100,0) -> 1.6 | H24: =IFERROR(HLOOKUP($H$3,'04. Job Descriptions'!$B$4:$J$35,21,0),"NA") -> 4: Advanced | I24: =IFERROR(HLOOKUP($H$3,'04. Job Descriptions'!$M$3:$R$35,22,0),"NA") -> 1.6 | K24: =IFERROR(HLOOKUP($K$3,'04. Job Descriptions'!$B$4:$J$35,21,0),"NA") -> 4: Advanced | L24: =IFERROR(HLOOKUP($K$3,'04. Job Descriptions'!$M$3:$R$35,22,0),"NA") -> 1.6 | M24: =IF(G24<L24,"Yes","No") -> No
B25: ='04. Job Descriptions'!B25 -> Foreign Language & Certificates | C25: ='04. Job Descriptions'!D25 -> FSOFTER may have one or more of the following Foreign Language/Technical qualifications to perform assigned tasks | D25: ='04. Job Descriptions'!C25 -> 0.1 | G25: =SUM(G26:G29) -> 8.6666667 | I25: =SUM(I26:I29) -> 8.6666667 | L25: =SUM(L26:L29) -> 8.6666667
B26: ='04. Job Descriptions'!B26 -> Foreign Language | C26: ='04. Job Descriptions'!D26 -> - Language Proficiency: English, Japanese, Korean, Chinese, Germany, French, Thailand | D26: ='04. Job Descriptions'!C26 -> 0.05 | E26: 5: TOEIC 701-800, TOELF iBT 71-80, IELTS 6.6-7.5, CEFR B2+, JP N3+ or equivalent | G26: =IFERROR((LEFT(E26,1)*D26/'04. Job Descriptions'!K26)*100,0) -> 5 | H26: =IFERROR(HLOOKUP($H$3,'04. Job Descriptions'!$B$4:$J$35,23,0),"NA") -> 5: TOEIC 701-800, TOELF iBT 71-80, IELTS 6.6-7.5, CEFR B2+, JP N3+ or equivalent | I26: =IFERROR(HLOOKUP($H$3,'04. Job Descriptions'!$M$3:$R$35,24,0),"NA") -> 5 | K26: =IFERROR(HLOOKUP($K$3,'04. Job Descriptions'!$B$4:$J$35,23,0),"NA") -> 5: TOEIC 701-800, TOELF iBT 71-80, IELTS 6.6-7.5, CEFR B2+, JP N3+ or equivalent | L26: =IFERROR(HLOOKUP($K$3,'04. Job Descriptions'!$M$3:$R$35,24,0),"NA") -> 5 | M26: =IF(G26<L26,"Yes","No") -> No
B27: ='04. Job Descriptions'!B27 -> Education Background | C27: ='04. Job Descriptions'!D27 -> Required one of degree in Engineering and Non-Engineering: - Engineering: Computer Science | Information Technology | Computer Engineering | Software Engineering, ... - Non-Engineering: Economics, Finances, Administrations, Social Science, Supply Chain, Logistics, ... | D27: ='04. Job Descriptions'!C27 -> 0.02 | E27: 3-Bachelor Degree / Post-Baccalaureate Certificate | G27: =IFERROR((LEFT(E27,1)*D27/'04. Job Descriptions'!K27)*100,0) -> 2 | H27: =IFERROR(HLOOKUP($H$3,'04. Job Descriptions'!$B$4:$J$35,24,0),"NA") -> 3-Bachelor Degree / Post-Baccalaureate Certificate | I27: =IFERROR(HLOOKUP($H$3,'04. Job Descriptions'!$M$3:$R$35,25,0),"NA") -> 2 | K27: =IFERROR(HLOOKUP($K$3,'04. Job Descriptions'!$B$4:$J$35,24,0),"NA") -> 3-Bachelor Degree / Post-Baccalaureate Certificate | L27: =IFERROR(HLOOKUP($K$3,'04. Job Descriptions'!$M$3:$R$35,25,0),"NA") -> 2 | M27: =IF(G27<L27,"Yes","No") -> No
B28: ='04. Job Descriptions'!B28 -> Business Analysis Certifications | C28: ='04. Job Descriptions'!D28 -> - Required certificates in Business Analysis: Business Analyst, Software Business Analyst | D28: ='04. Job Descriptions'!C28 -> 0.02 | E28: 2: Certified Business Analyst Advance or Equivalent | G28: =IFERROR((LEFT(E28,1)*D28/'04. Job Descriptions'!K28)*100,0) -> 1 | H28: =IFERROR(HLOOKUP($H$3,'04. Job Descriptions'!$B$4:$J$35,25,0),"NA") -> 2: Certified Business Analyst Advance or Equivalent | I28: =IFERROR(HLOOKUP($H$3,'04. Job Descriptions'!$M$3:$R$35,26,0),"NA") -> 1 | K28: =IFERROR(HLOOKUP($K$3,'04. Job Descriptions'!$B$4:$J$35,25,0),"NA") -> 2: Certified Business Analyst Advance or Equivalent | L28: =IFERROR(HLOOKUP($K$3,'04. Job Descriptions'!$M$3:$R$35,26,0),"NA") -> 1 | M28: =IF(G28<L28,"Yes","No") -> No
B29: ='04. Job Descriptions'!B29 -> Individual Learning in Year | C29: ='04. Job Descriptions'!D29 -> - Joined the training courses of any FSOFT program (upskilling, reskilling, fasttrack, internal training) related to Business Analysis in year (ranking year) | D29: ='04. Job Descriptions'!C29 -> 0.01 | E29: 2: Join >=3 training or workshop | G29: =IFERROR((LEFT(E29,1)*D29/'04. Job Descriptions'!K29)*100,0) -> 0.66666667 | H29: =IFERROR(HLOOKUP($H$3,'04. Job Descriptions'!$B$4:$J$35,26,0),"NA") -> 2: Join >=3 training or workshop | I29: =IFERROR(HLOOKUP($H$3,'04. Job Descriptions'!$M$3:$R$35,27,0),"NA") -> 0.66666667 | K29: =IFERROR(HLOOKUP($K$3,'04. Job Descriptions'!$B$4:$J$35,26,0),"NA") -> 2: Join >=3 training or workshop | L29: =IFERROR(HLOOKUP($K$3,'04. Job Descriptions'!$M$3:$R$35,27,0),"NA") -> 0.66666667 | M29: =IF(G29<L29,"Yes","No") -> No
B30: ='04. Job Descriptions'!B30 -> Non-Engineering and Softskills | C30: ='04. Job Descriptions'!D30 -> FSOFTER is required to have one or more of the following soft skills and other skills to perform assigned tasks | D30: ='04. Job Descriptions'!C30 -> 0.1 | G30: =SUM(G31:G35) -> 6.5 | I30: =SUM(I31:I35) -> 6.5 | L30: =SUM(L31:L35) -> 6.5
B31: ='04. Job Descriptions'!B31 -> Communication and Problem Solving | C31: ='04. Job Descriptions'!D31 -> - Team Work - Leadership & Motivation - Communication - Problem Solving - Change Management - Networking/ Relationship building | D31: ='04. Job Descriptions'!C31 -> 0.03 | E31: 2: Limited Experience | G31: =IFERROR((LEFT(E31,1)*D31/'04. Job Descriptions'!K31)*100,0) -> 1.5 | H31: =IFERROR(HLOOKUP($H$3,'04. Job Descriptions'!$B$4:$J$35,28,0),"NA") -> 2: Limited Experience | I31: =IFERROR(HLOOKUP($H$3,'04. Job Descriptions'!$M$3:$R$35,29,0),"NA") -> 1.5 | K31: =IFERROR(HLOOKUP($K$3,'04. Job Descriptions'!$B$4:$J$35,28,0),"NA") -> 2: Limited Experience | L31: =IFERROR(HLOOKUP($K$3,'04. Job Descriptions'!$M$3:$R$35,29,0),"NA") -> 1.5 | M31: =IF(G31<L31,"Yes","No") -> No
B32: ='04. Job Descriptions'!B32 -> Analytical and Critical Thinking | C32: ='04. Job Descriptions'!D32 -> - Research - Forecasting - Data mining - Data and metrics interpreting - Reporting - Organization | D32: ='04. Job Descriptions'!C32 -> 0.02 | E32: 3: Intermediate | G32: =IFERROR((LEFT(E32,1)*D32/'04. Job Descriptions'!K32)*100,0) -> 1.5 | H32: =IFERROR(HLOOKUP($H$3,'04. Job Descriptions'!$B$4:$J$35,29,0),"NA") -> 3: Intermediate | I32: =IFERROR(HLOOKUP($H$3,'04. Job Descriptions'!$M$3:$R$35,30,0),"NA") -> 1.5 | K32: =IFERROR(HLOOKUP($K$3,'04. Job Descriptions'!$B$4:$J$35,29,0),"NA") -> 3: Intermediate | L32: =IFERROR(HLOOKUP($K$3,'04. Job Descriptions'!$M$3:$R$35,30,0),"NA") -> 1.5 | M32: =IF(G32<L32,"Yes","No") -> No
B33: ='04. Job Descriptions'!B33 -> Organization and Industry Knowledge | C33: ='04. Job Descriptions'!D33 -> - Agile Mindset - Process Understanding - Product Understanding - Market trends & Challenges - Market drivers - Customer Segmentation Understanding - Organization Knowledge | D33: ='04. Job Descriptions'!C33 -> 0.02 | E33: 3: Intermediate | G33: =IFERROR((LEFT(E33,1)*D33/'04. Job Descriptions'!K33)*100,0) -> 1.5 | H33: =IFERROR(HLOOKUP($H$3,'04. Job Descriptions'!$B$4:$J$35,30,0),"NA") -> 3: Intermediate | I33: =IFERROR(HLOOKUP($H$3,'04. Job Descriptions'!$M$3:$R$35,31,0),"NA") -> 1.5 | K33: =IFERROR(HLOOKUP($K$3,'04. Job Descriptions'!$B$4:$J$35,30,0),"NA") -> 3: Intermediate | L33: =IFERROR(HLOOKUP($K$3,'04. Job Descriptions'!$M$3:$R$35,31,0),"NA") -> 1.5 | M33: =IF(G33<L33,"Yes","No") -> No
B34: ='04. Job Descriptions'!B34 -> Project Risk Management | C34: ='04. Job Descriptions'!D34 -> - Understand and utilize process of implementing risk response plans - Tracking identified risks, monitoring residual risks, identifying new risks - Evaluating risk process effectiveness throughout the project. - Forecast risk that may occur in range of project that the team is responsible for. - Analyze and perform preventitive actions to reduce risks raised by members. - In the case that risks cannot be closed, raise the risk to leader/mamager and discuss with leader/manger to find out preventitive actions then follow up. (the risk in Methodology is the risk of Business solution. the risk mentioned in this sheet derives from project activities, especially in oursourcing project.) | D34: ='04. Job Descriptions'!C34 -> 0.02 | E34: 3: Intermediate | G34: =IFERROR((LEFT(E34,1)*D34/'04. Job Descriptions'!K34)*100,0) -> 1.5 | H34: =IFERROR(HLOOKUP($H$3,'04. Job Descriptions'!$B$4:$J$35,31,0),"NA") -> 3: Intermediate | I34: =IFERROR(HLOOKUP($H$3,'04. Job Descriptions'!$M$3:$R$35,32,0),"NA") -> 1.5 | K34: =IFERROR(HLOOKUP($K$3,'04. Job Descriptions'!$B$4:$J$35,31,0),"NA") -> 3: Intermediate | L34: =IFERROR(HLOOKUP($K$3,'04. Job Descriptions'!$M$3:$R$35,32,0),"NA") -> 1.5 | M34: =IF(G34<L34,"Yes","No") -> No
B35: ='04. Job Descriptions'!B35 -> Project Human Resource Management | C35: ='04. Job Descriptions'!D35 -> - Understand the ability of each BA to assign appropriate projects/tasks. - Understand project request for BA service to determine proper resource plan. - Regularly control BA allocation to optimize resource. - Monitor and control progress and status of BA involvement in each and every project; detect, resolve and followup to close any issue arising. - Evaluate performance, identify strengths as well as improvement points and propose career path for each BA | D35: ='04. Job Descriptions'!C35 -> 0.01 | E35: 2: Limited Experience | G35: =IFERROR((LEFT(E35,1)*D35/'04. Job Descriptions'!K35)*100,0) -> 0.5 | H35: =IFERROR(HLOOKUP($H$3,'04. Job Descriptions'!$B$4:$J$35,32,0),"NA") -> 2: Limited Experience | I35: =IFERROR(HLOOKUP($H$3,'04. Job Descriptions'!$M$3:$R$35,33,0),"NA") -> 0.5 | K35: =IFERROR(HLOOKUP($K$3,'04. Job Descriptions'!$B$4:$J$35,32,0),"NA") -> 2: Limited Experience | L35: =IFERROR(HLOOKUP($K$3,'04. Job Descriptions'!$M$3:$R$35,33,0),"NA") -> 0.5 | M35: =IF(G35<L35,"Yes","No") -> No

Sheet 06. Assessment Summary
A1: Assessment Summary
B3: OVERALL CAPABILITIES | D3: ='05. Job Rankings'!B3 -> [Name] - [Account] | K3: CANDIDATE'S SELF-RANKED RESULTS SCORED BY MANAGER / LEADER / HOD | Q3: YOU ARE EXPECTED RANK | T3: YOU ARE SELF-RANKED SCORE BETWEEN HIGHER AND LOWER
B4: ID | C4: Requirement Items | D4: Weight % | E4: ='04. Job Descriptions'!E3 -> Associate Business Analyst | F4: ='04. Job Descriptions'!F3 -> Business Analyst | G4: ='04. Job Descriptions'!G3 -> Senior Business Analyst | H4: ='04. Job Descriptions'!H3 -> Business Analysis Leader | I4: ='04. Job Descriptions'!I3 -> Senior Business Analysis Consultant / Leader | J4: ='04. Job Descriptions'!J3 -> Principal Business Analysis Consultant / Leader | K4: ='05. Job Rankings'!E3 -> YOU ACHIEVED RANK: Senior Business Analyst-BANE03 | O4: BONUS POINTS total <= 5 for whole items | Q4: ACTIONS TO FILL GAPS FOR RANK | T4: =IF(T6>='04. Job Descriptions'!R4,'04. Job Descriptions'!R2&"-"&'04. Job Descriptions'!R3,IF(T6>='04. Job Descriptions'!Q4,'04. Job Descriptions'!Q2&"-"&'04. Job Descriptions'!Q3,IF(T6>='04. Job Descriptions'!P4,'04. Job Descriptions'!P2&"-"&'04. Job Descriptions'!P3,IF(T6>='04. Job Descriptions'!O4,'04. Job Descriptions'!O2&"-"&'04. Job Descriptions'!O3,IF(T6>='04. Job Descriptions'!N4,'04. Job Descriptions'!N2&"-"&'04. Job Descriptions'!N3,IF(T6>='04. Job Descriptions'!M4,'04. Job Descriptions'!M2&"-"&'04. Job Descriptions'!M3,"Not Ranked")))))) -> Business Analysis Leader-BANE04 | U4: =IF(U6>='04. Job Descriptions'!R4,'04. Job Descriptions'!R2&"-"&'04. Job Descriptions'!R3,IF(U6>='04. Job Descriptions'!Q4,'04. Job Descriptions'!Q2&"-"&'04. Job Descriptions'!Q3,IF(U6>='04. Job Descriptions'!P4,'04. Job Descriptions'!P2&"-"&'04. Job Descriptions'!P3,IF(U6>='04. Job Descriptions'!O4,'04. Job Descriptions'!O2&"-"&'04. Job Descriptions'!O3,IF(U6>='04. Job Descriptions'!N4,'04. Job Descriptions'!N2&"-"&'04. Job Descriptions'!N3,IF(U6>='04. Job Descriptions'!M4,'04. Job Descriptions'!M2&"-"&'04. Job Descriptions'!M3,"Not Ranked")))))) -> Senior Business Analysis Consultant / Leader-BANE05
E5: ='04. Job Descriptions'!M3 -> BANE01 | F5: ='04. Job Descriptions'!N3 -> BANE02 | G5: ='04. Job Descriptions'!O3 -> BANE03 | H5: ='04. Job Descriptions'!P3 -> BANE04 | I5: ='04. Job Descriptions'!Q3 -> BANE05 | J5: ='04. Job Descriptions'!R3 -> BANE06 | K5: ACTUAL RANKED SCORE | L5: ACTUAL RANKED LEVEL | M5: ="Needs to be improved items as below to reach the " &K4 -> Needs to be improved items as below to reach the YOU ACHIEVED RANK: Senior Business Analyst-BANE03 | O5: BONUS Points | P5: BONUS Descriptions | Q5: ="REQUIRED SCORE FOR " & '05. Job Rankings'!K3 -> REQUIRED SCORE FOR BANE04 | R5: ="Needs to be improved items as below :"& '05. Job Rankings'!K3 -> Needs to be improved items as below :BANE04 | T5: ="SCORE of LOWER RANK" -> SCORE of LOWER RANK | U5: ="SCORE of HIGHER RANK" -> SCORE of HIGHER RANK
D6: =SUM(D7:D19) -> 1 | E6: =SUM(E7:E19) -> 25.733333 | F6: =SUM(F7:F19) -> 34.233333 | G6: =SUM(G7:G19) -> 49.916667 | H6: =SUM(H7:H19) -> 67.816667 | I6: =SUM(I7:I19) -> 81 | J6: =SUM(J7:J19) -> 100 | K6: =SUM(K7:K19) -> 70.316667 | L6: =K6+O6 -> 70.316667 | M6: Gaps | N6: Skills | O6: =IF(SUM(O7:O19)>5,5, SUM(O7:O19)) -> 0 | Q6: =SUM(Q7:Q19) -> 67.816667 | R6: Gaps | S6: Skills | T6: =SUM(T7:T19) -> 67.816667 | U6: =SUM(U7:U19) -> 81
B7: 1 | C7: ='04. Job Descriptions'!B6 -> Roles and Responsibilities | D7: ='04. Job Descriptions'!C5 -> 0.15 | E7: ='04. Job Descriptions'!M5 -> 2.4 | F7: ='04. Job Descriptions'!N5 -> 4.8 | G7: ='04. Job Descriptions'!O5 -> 7.2 | H7: ='04. Job Descriptions'!P5 -> 10.35 | I7: ='04. Job Descriptions'!Q5 -> 11.85 | J7: ='04. Job Descriptions'!R5 -> 15 | K7: ='05. Job Rankings'!G5 -> 10.35 | L7: =IF(K7>=I7,$I$5,IF(K7>=H7,$H$5,IF(K7>=G7,$G$5,IF(K7>=F7,$F$5,IF(K7>=E7,$E$5,$J$5))))) -> BANE04 | M7: =IF(T7>K7,"O","") | Q7: ='05. Job Rankings'!L5 -> 10.35 | R7: =IF(Q7>K7,"O","") | T7: =IF($K$6>$I$6,$I7,IF($K$6>$H$6,$H7,IF($K$6>$G$6,$G7,IF($K$6>$F$6,$F7,$E7)))) -> 10.35 | U7: =IF($K$6<$E$6,$E7,IF($K$6<$F$6,$F7,IF($K$6<$G$6,$G7,IF($K$6<$H$6,$H7,IF($K$6<$I$6,$I7,$J7))))) -> 11.85
B8: 2 | C8: ='04. Job Descriptions'!B10 -> Subordinate Development | D8: ='04. Job Descriptions'!C10 -> 0.03 | E8: ='04. Job Descriptions'!M10 -> 0 | F8: ='04. Job Descriptions'!N10 -> 0 | G8: ='04. Job Descriptions'!O10 -> 0.75 | H8: ='04. Job Descriptions'!P10 -> 1.5 | I8: ='04. Job Descriptions'!Q10 -> 2.25 | J8: ='04. Job Descriptions'!R10 -> 3 | K8: ='05. Job Rankings'!G10 -> 1.5 | L8: =IF(K8>=I8,$I$5,IF(K8>=H8,$H$5,IF(K8>=G8,$G$5,IF(K8>=F8,$F$5,IF(K8>=E8,$E$5,$J$5))))) -> BANE04 | M8: =IF(T8>K8,"O","") | Q8: ='05. Job Rankings'!L10 -> 1.5 | R8: =IF(Q8>K8,"O","") | T8: =IF($K$6>$I$6,$I8,IF($K$6>$H$6,$H8,IF($K$6>$G$6,$G8,IF($K$6>$F$6,$F8,$E8)))) -> 1.5 | U8: =IF($K$6<$E$6,$E8,IF($K$6<$F$6,$F8,IF($K$6<$G$6,$G8,IF($K$6<$H$6,$H8,IF($K$6<$I$6,$I8,$J8))))) -> 2.25
B9: 3 | C9: ='04. Job Descriptions'!B9 -> Business Analysis Experiences (*) | D9: ='04. Job Descriptions'!C9 -> 0.05 | E9: ='04. Job Descriptions'!M9 -> 0 | F9: ='04. Job Descriptions'!N9 -> 1 | G9: ='04. Job Descriptions'!O9 -> 2 | H9: ='04. Job Descriptions'!P9 -> 3 | I9: ='04. Job Descriptions'!Q9 -> 4 | J9: ='04. Job Descriptions'!R9 -> 5 | K9: ='05. Job Rankings'!G9 -> 3 | L9: =IF(K9>=I9,$I$5,IF(K9>=H9,$H$5,IF(K9>=G9,$G$5,IF(K9>=F9,$F$5,IF(K9>=E9,$E$5,$J$5))))) -> BANE04 | M9: =IF(T9>K9,"O","") | Q9: ='05. Job Rankings'!L9 -> 3 | R9: =IF(Q9>K9,"O","") | T9: =IF($K$6>$I$6,$I9,IF($K$6>$H$6,$H9,IF($K$6>$G$6,$G9,IF($K$6>$F$6,$F9,$E9)))) -> 3 | U9: =IF($K$6<$E$6,$E9,IF($K$6<$F$6,$F9,IF($K$6<$G$6,$G9,IF($K$6<$H$6,$H9,IF($K$6<$I$6,$I9,$J9))))) -> 4
B10: 4 | C10: ='04. Job Descriptions'!B28 -> Business Analysis Certifications | D10: ='04. Job Descriptions'!C28+'04. Job Descriptions'!C27 -> 0.04 | E10: ='04. Job Descriptions'!M28+'04. Job Descriptions'!M27 -> 2.5 | F10: ='04. Job Descriptions'!N28+'04. Job Descriptions'!N27 -> 2.5 | G10: ='04. Job Descriptions'!O28+'04. Job Descriptions'!O27 -> 3 | H10: ='04. Job Descriptions'!P28+'04. Job Descriptions'!P27 -> 3 | I10: ='04. Job Descriptions'!Q28+'04. Job Descriptions'!Q27 -> 3.5 | J10: ='04. Job Descriptions'!R28+'04. Job Descriptions'!R27 -> 4 | K10: ='05. Job Rankings'!G28+'05. Job Rankings'!G27 -> 3 | L10: =IF(K10>=I10,$I$5,IF(K10>=H10,$H$5,IF(K10>=G10,$G$5,IF(K10>=F10,$F$5,IF(K10>=E10,$E$5,$J$5))))) -> BANE04 | M10: =IF(T10>K10,"O","") | Q10: ='05. Job Rankings'!L27+'05. Job Rankings'!L28 -> 3 | R10: =IF(Q10>K10,"O","") | T10: =IF($K$6>$I$6,$I10,IF($K$6>$H$6,$H10,IF($K$6>$G$6,$G10,IF($K$6>$F$6,$F10,$E10)))) -> 3 | U10: =IF($K$6<$E$6,$E10,IF($K$6<$F$6,$F10,IF($K$6<$G$6,$G10,IF($K$6<$H$6,$H10,IF($K$6<$I$6,$I10,$J10))))) -> 3.5
B11: 5 | C11: ='04. Job Descriptions'!B11 -> Number of Projects/Phases | D11: ='04. Job Descriptions'!C11 -> 0.03 | E11: ='04. Job Descriptions'!M11 -> 0 | F11: ='04. Job Descriptions'!N11 -> 0.6 | G11: ='04. Job Descriptions'!O11 -> 1.2 | H11: ='04. Job Descriptions'!P11 -> 1.8 | I11: ='04. Job Descriptions'!Q11 -> 2.4 | J11: ='04. Job Descriptions'!R11 -> 3 | K11: ='05. Job Rankings'!G11 -> 2.4 | L11: =IF(K11>=I11,$I$5,IF(K11>=H11,$H$5,IF(K11>=G11,$G$5,IF(K11>=F11,$F$5,IF(K11>=E11,$E$5,$J$5))))) -> BANE05 | M11: =IF(T11>K11,"O","") | Q11: ='05. Job Rankings'!L11 -> 1.8 | R11: =IF(Q11>K11,"O","") | T11: =IF($K$6>$I$6,$I11,IF($K$6>$H$6,$H11,IF($K$6>$G$6,$G11,IF($K$6>$F$6,$F11,$E11)))) -> 1.8 | U11: =IF($K$6<$E$6,$E11,IF($K$6<$F$6,$F11,IF($K$6<$G$6,$G11,IF($K$6<$H$6,$H11,IF($K$6<$I$6,$I11,$J11))))) -> 2.4
B12: 6 | C12: Organization and Project Contributions | D12: =SUM('04. Job Descriptions'!C12,'04. Job Descriptions'!C14) -> 0.04 | E12: =SUM('04. Job Descriptions'!M12,'04. Job Descriptions'!M14) -> 0 | F12: =SUM('04. Job Descriptions'!N12,'04. Job Descriptions'!N14) -> 0 | G12: =SUM('04. Job Descriptions'!O12,'04. Job Descriptions'!O14) -> 1 | H12: =SUM('04. Job Descriptions'!P12,'04. Job Descriptions'!P14) -> 2 | I12: =SUM('04. Job Descriptions'!Q12,'04. Job Descriptions'!Q14) -> 3 | J12: =SUM('04. Job Descriptions'!R12,'04. Job Descriptions'!R14) -> 4 | K12: =SUM('05. Job Rankings'!G12,'05. Job Rankings'!G14) -> 3 | L12: =IF(K12>=I12,$I$5,IF(K12>=H12,$H$5,IF(K12>=G12,$G$5,IF(K12>=F12,$F$5,IF(K12>=E12,$E$5,$J$5))))) -> BANE05 | M12: =IF(T12>K12,"O","") | Q12: =SUM('05. Job Rankings'!L12,'05. Job Rankings'!L14) -> 2 | R12: =IF(Q12>K12,"O","") | T12: =IF($K$6>$I$6,$I12,IF($K$6>$H$6,$H12,IF($K$6>$G$6,$G12,IF($K$6>$F$6,$F12,$E12)))) -> 2 | U12: =IF($K$6<$E$6,$E12,IF($K$6<$F$6,$F12,IF($K$6<$G$6,$G12,IF($K$6<$H$6,$H12,IF($K$6<$I$6,$I12,$J12))))) -> 3
B13: 7 | C13: ='04. Job Descriptions'!B26 -> Foreign Language | D13: ='04. Job Descriptions'!C26 -> 0.05 | E13: ='04. Job Descriptions'!M26 -> 2 | F13: ='04. Job Descriptions'!N26 -> 3 | G13: ='04. Job Descriptions'!O26 -> 4 | H13: ='04. Job Descriptions'!P26 -> 5 | I13: ='04. Job Descriptions'!Q26 -> 5 | J13: ='04. Job Descriptions'!R26 -> 5 | K13: ='05. Job Rankings'!G26 -> 5 | L13: =IF(K13>=I13,$I$5,IF(K13>=H13,$H$5,IF(K13>=G13,$G$5,IF(K13>=F13,$F$5,IF(K13>=E13,$E$5,$J$5))))) -> BANE05 | M13: =IF(T13>K13,"O","") | Q13: ='05. Job Rankings'!L26 -> 5 | R13: =IF(Q13>K13,"O","") | T13: =IF($K$6>$I$6,$I13,IF($K$6>$H$6,$H13,IF($K$6>$G$6,$G13,IF($K$6>$F$6,$F13,$E13)))) -> 5 | U13: =IF($K$6<$E$6,$E13,IF($K$6<$F$6,$F13,IF($K$6<$G$6,$G13,IF($K$6<$H$6,$H13,IF($K$6<$I$6,$I13,$J13))))) -> 5
B14: 8 | C14: Software Business Analytics (*) | D14: =SUM('04. Job Descriptions'!C16:C21) -> 0.34 | E14: =SUM('04. Job Descriptions'!M16:M21) -> 13.6 | F14: =SUM('04. Job Descriptions'!N16:N21) -> 15.6 | G14: =SUM('04. Job Descriptions'!O16:O21) -> 19 | H14: =SUM('04. Job Descriptions'!P16:P21) -> 24.2 | I14: =SUM('04. Job Descriptions'!Q16:Q21) -> 27.2 | J14: =SUM('04. Job Descriptions'!R16:R21) -> 34 | K14: =SUM('05. Job Rankings'!G16:G21) -> 22.6 | L14: =IF(K14>=I14,$I$5,IF(K14>=H14,$H$5,IF(K14>=G14,$G$5,IF(K14>=F14,$F$5,IF(K14>=E14,$E$5,$J$5))))) -> BANE03 | M14: =IF(T14>K14,"O","") -> O | Q14: =SUM('05. Job Rankings'!L16:L21) -> 24.2 | R14: =IF(Q14>K14,"O","") -> O | T14: =IF($K$6>$I$6,$I14,IF($K$6>$H$6,$H14,IF($K$6>$G$6,$G14,IF($K$6>$F$6,$F14,$E14)))) -> 24.2 | U14: =IF($K$6<$E$6,$E14,IF($K$6<$F$6,$F14,IF($K$6<$G$6,$G14,IF($K$6<$H$6,$H14,IF($K$6<$I$6,$I14,$J14))))) -> 27.2
B15: 9 | C15: ='04. Job Descriptions'!B22 -> Business Acumen and Mindsets | D15: ='04. Job Descriptions'!C22 -> 0.03 | E15: ='04. Job Descriptions'!M22 -> 1.2 | F15: ='04. Job Descriptions'!N22 -> 1.8 | G15: ='04. Job Descriptions'!O22 -> 1.8 | H15: ='04. Job Descriptions'!P22 -> 2.4 | I15: ='04. Job Descriptions'!Q22 -> 2.4 | J15: ='04. Job Descriptions'!R22 -> 3 | K15: ='05. Job Rankings'!G22 -> 2.4 | L15: =IF(K15>=I15,$I$5,IF(K15>=H15,$H$5,IF(K15>=G15,$G$5,IF(K15>=F15,$F$5,IF(K15>=E15,$E$5,$J$5))))) -> BANE05 | M15: =IF(T15>K15,"O","") | Q15: ='05. Job Rankings'!L22 -> 2.4 | R15: =IF(Q15>K15,"O","") | T15: =IF($K$6>$I$6,$I15,IF($K$6>$H$6,$H15,IF($K$6>$G$6,$G15,IF($K$6>$F$6,$F15,$E15)))) -> 2.4 | U15: =IF($K$6<$E$6,$E15,IF($K$6<$F$6,$F15,IF($K$6<$G$6,$G15,IF($K$6<$H$6,$H15,IF($K$6<$I$6,$I15,$J15))))) -> 2.4
B16: 10 | C16: Business Analysis and Software Design Tools | D16: =SUM('04. Job Descriptions'!C23:C24) -> 0.03 | E16: =SUM('04. Job Descriptions'!M23:M24) -> 1.2 | F16: =SUM('04. Job Descriptions'!N23:N24) -> 1.6 | G16: =SUM('04. Job Descriptions'!O23:O24) -> 1.8 | H16: =SUM('04. Job Descriptions'!P23:P24) -> 2.4 | I16: =SUM('04. Job Descriptions'!Q23:Q24) -> 2.4 | J16: =SUM('04. Job Descriptions'!R23:R24) -> 3 | K16: =SUM('05. Job Rankings'!G23:G24) -> 2.4 | L16: =IF(K16>=I16,$I$5,IF(K16>=H16,$H$5,IF(K16>=G16,$G$5,IF(K16>=F16,$F$5,IF(K16>=E16,$E$5,$J$5))))) -> BANE05 | M16: =IF(T16>K16,"O","") | Q16: =SUM('05. Job Rankings'!L23:L24) -> 2.4 | R16: =IF(Q16>K16,"O","") | T16: =IF($K$6>$I$6,$I16,IF($K$6>$H$6,$H16,IF($K$6>$G$6,$G16,IF($K$6>$F$6,$F16,$E16)))) -> 2.4 | U16: =IF($K$6<$E$6,$E16,IF($K$6<$F$6,$F16,IF($K$6<$G$6,$G16,IF($K$6<$H$6,$H16,IF($K$6<$I$6,$I16,$J16))))) -> 2.4
B17: 11 | C17: ='04. Job Descriptions'!B30 -> Non-Engineering and Softskills | D17: ='04. Job Descriptions'!C30 -> 0.1 | E17: ='04. Job Descriptions'!M30 -> 2.5 | F17: ='04. Job Descriptions'!N30 -> 3 | G17: ='04. Job Descriptions'!O30 -> 5 | H17: ='04. Job Descriptions'!P30 -> 6.5 | I17: ='04. Job Descriptions'!Q30 -> 8.5 | J17: ='04. Job Descriptions'!R30 -> 10 | K17: ='05. Job Rankings'!G30 -> 6.5 | L17: =IF(K17>=I17,$I$5,IF(K17>=H17,$H$5,IF(K17>=G17,$G$5,IF(K17>=F17,$F$5,IF(K17>=E17,$E$5,$J$5))))) -> BANE04 | M17: =IF(T17>K17,"O","") | Q17: ='05. Job Rankings'!L30 -> 6.5 | R17: =IF(Q17>K17,"O","") | T17: =IF($K$6>$I$6,$I17,IF($K$6>$H$6,$H17,IF($K$6>$G$6,$G17,IF($K$6>$F$6,$F17,$E17)))) -> 6.5 | U17: =IF($K$6<$E$6,$E17,IF($K$6<$F$6,$F17,IF($K$6<$G$6,$G17,IF($K$6<$H$6,$H17,IF($K$6<$I$6,$I17,$J17))))) -> 8.5
B18: 12 | C18: ='04. Job Descriptions'!B13 -> Industry Experiences (IT and Non-IT fields) | D18: ='04. Job Descriptions'!C13 -> 0.1 | E18: ='04. Job Descriptions'!M13 -> 0 | F18: ='04. Job Descriptions'!N13 -> 0 | G18: ='04. Job Descriptions'!O13 -> 2.5 | H18: ='04. Job Descriptions'!P13 -> 5 | I18: ='04. Job Descriptions'!Q13 -> 7.5 | J18: ='04. Job Descriptions'!R13 -> 10 | K18: ='05. Job Rankings'!G13 -> 7.5 | L18: =IF(K18>=I18,$I$5,IF(K18>=H18,$H$5,IF(K18>=G18,$G$5,IF(K18>=F18,$F$5,IF(K18>=E18,$E$5,$J$5))))) -> BANE05 | M18: =IF(T18>K18,"O","") | Q18: ='05. Job Rankings'!L13 -> 5 | R18: =IF(Q18>K18,"O","") | T18: =IF($K$6>$I$6,$I18,IF($K$6>$H$6,$H18,IF($K$6>$G$6,$G18,IF($K$6>$F$6,$F18,$E18)))) -> 5 | U18: =IF($K$6<$E$6,$E18,IF($K$6<$F$6,$F18,IF($K$6<$G$6,$G18,IF($K$6<$H$6,$H18,IF($K$6<$I$6,$I18,$J18))))) -> 7.5
B19: 13 | C19: ='04. Job Descriptions'!B29 -> Individual Learning in Year | D19: ='04. Job Descriptions'!C29 -> 0.01 | E19: ='04. Job Descriptions'!M29 -> 0.33333333 | F19: ='04. Job Descriptions'!N29 -> 0.33333333 | G19: ='04. Job Descriptions'!O29 -> 0.66666667 | H19: ='04. Job Descriptions'!P29 -> 0.66666667 | I19: ='04. Job Descriptions'!Q29 -> 1 | J19: ='04. Job Descriptions'!R29 -> 1 | K19: ='05. Job Rankings'!G29 -> 0.66666667 | L19: =IF(K19>=I19,$I$5,IF(K19>=H19,$H$5,IF(K19>=G19,$G$5,IF(K19>=F19,$F$5,IF(K19>=E19,$E$5,$J$5))))) -> BANE04 | M19: =IF(T19>K19,"O","") | Q19: ='05. Job Rankings'!L29 -> 0.66666667 | R19: =IF(Q19>K19,"O","") | T19: =IF($K$6>$I$6,$I19,IF($K$6>$H$6,$H19,IF($K$6>$G$6,$G19,IF($K$6>$F$6,$F19,$E19)))) -> 0.66666667 | U19: =IF($K$6<$E$6,$E19,IF($K$6<$F$6,$F19,IF($K$6<$G$6,$G19,IF($K$6<$H$6,$H19,IF($K$6<$I$6,$I19,$J19))))) -> 1
B21: Final judgement by Leader/Manager
B22: 1 | C22: Proposed Job Rank | D22: BANE03 | F22: =IFERROR(VLOOKUP(D22,'08. Definitions'!C14:D20,2,FALSE),"") -> Senior Business Analyst
B23: 2 | C23: Recommendation for FSOFTER
B24: 3 | C24: Recommendation for Leader/Manager
Q27: ="Prerequisite Skills for Expected Rank " & '05. Job Rankings'!K3 -> Prerequisite Skills for Expected Rank BANE04 | Y27: Data for Speedometer Chart
Y28: Start | Z28: 0.5 | AA28: Ranking Index
Y29: Not ranked | Z29: =16 -> 16
Q30: Check number of mandatory items: | U30: =COUNTIF(U31:U34,"Yes") -> 1 | Y30: ='04. Job Descriptions'!E3 -> Associate Business Analyst | Z30: =AA31-AA30-Z28 -> 8 | AA30: =HLOOKUP(Y30,'04. Job Descriptions'!$M$2:$R$4,3,0) -> 25.733333
Q31: ='04. Job Descriptions'!B9 -> Business Analysis Experiences (*) | U31: =VLOOKUP(Q31,'05. Job Rankings'!$B$5:$M$35,9,0) -> No | Y31: ='04. Job Descriptions'!F3 -> Business Analyst | Z31: =AA32-AA31 -> 15.683333 | AA31: =HLOOKUP(Y31,'04. Job Descriptions'!$M$2:$R$4,3,0) -> 34.233333
Q32: ='04. Job Descriptions'!B16 -> Business Analysis Planning & Monitoring (*) | U32: =VLOOKUP(Q32,'05. Job Rankings'!$B$5:$M$35,9,0) -> Yes | Y32: ='04. Job Descriptions'!G3 -> Senior Business Analyst | Z32: =AA33-AA32 -> 17.9 | AA32: =HLOOKUP(Y32,'04. Job Descriptions'!$M$2:$R$4,3,0) -> 49.916667
Q33: ='04. Job Descriptions'!B17 -> Requirement Elicitation & Collaboration (*) | U33: =VLOOKUP(Q33,'05. Job Rankings'!$B$5:$M$35,9,0) -> No | Y33: ='04. Job Descriptions'!H3 -> Business Analysis Leader | Z33: =AA34-AA33 -> 13.183333 | AA33: =HLOOKUP(Y33,'04. Job Descriptions'!$M$2:$R$4,3,0) -> 67.816667
Q34: ='04. Job Descriptions'!B18 -> Business Requirement Analysis (*) | U34: =VLOOKUP(Q34,'05. Job Rankings'!$B$5:$M$35,9,0) -> No | Y34: ='04. Job Descriptions'!I3 -> Senior Business Analysis Consultant / Leader | Z34: =AA35-AA34 -> 19 | AA34: =HLOOKUP(Y34,'04. Job Descriptions'!$M$2:$R$4,3,0) -> 81
Y35: ='04. Job Descriptions'!J3 -> Principal Business Analysis Consultant / Leader | Z35: =AA36-AA35 -> 11 | AA35: =HLOOKUP(Y35,'04. Job Descriptions'!$M$2:$R$4,3,0) -> 100
Y36: Shadow | Z36: 100 | AA36: 111
Y37: Your Index | Z37: ='05. Job Rankings'!G3 -> 70.316667
Y38: Pointer | Z38: 1
Y39: End Point | Z39: =200-(Z38+Z37) -> 128.68333

Sheet 07. Roles & Responsibilities
A1: Roles & Responsibilities
B2: FSOFTER is required to take some the responsibilities and roles as below | C2: ='04. Job Descriptions'!E4 & " - " & '04. Job Descriptions'!E3 -> BANE01 - Associate Business Analyst | D2: ='04. Job Descriptions'!F4 & " - " & '04. Job Descriptions'!F3 -> BANE02 - Business Analyst | E2: ='04. Job Descriptions'!G4 & " - " & '04. Job Descriptions'!G3 -> BANE03 - Senior Business Analyst | F2: ='04. Job Descriptions'!H4 & " - " & '04. Job Descriptions'!H3 -> BANE04 - Business Analysis Leader | G2: ='04. Job Descriptions'!I4 & " - " & '04. Job Descriptions'!I3 -> BANE05 - Senior Business Analysis Consultant / Leader | H2: ='04. Job Descriptions'!J4 & " - " & '04. Job Descriptions'!J3 -> BANE06 - Principal Business Analysis Consultant / Leader
A3: ='04. Job Descriptions'!B6 -> Roles and Responsibilities | B3: Implementing all the processes and activities related to business analysis which can be analyzing and designing functional and non-functional requirements to the development, client or production environment, including but not limited to following responsibilities: BANE01: - Has responsibility for documenting requirement, supporting communicate requirement to stakeholders (under guidance) as role BA member. - Project Diversity and Complexity - Low: >=5 items in Elementary Complexity Criteria BANE02: - Has responsibility for gathering requirement, elaborating and validating gathered requirement as role BA member. - Project Diversity and Complexity - Normal: All items of Elementary Complexity Criteria & >= 1 item in General Advanced Complexity Criteria BANE03: - Has responsibility for designing, analyzing and evaluating business solution to ensure that it aligns with the project's goal as role BA member. - Project Diversity and Complexity - Medium: >= 4 items of General Advanced Complexity Criteria & >= 2 items of Management Complexity Criteria OR >= 4 items of General Advanced Complexity Criteria & >=1 item in Consultant Complexity Criteria BANE04: - Has responsibility for defining requirement approach & process, planning and monitoring business analysis activities as role BA consultant. - Project Diversity and Complexity - Complex: >= 4 items in General Advanced Complexity Criteria & All items in Management Complexity Criteria OR >= 5 items in General Advanced Complexity Criteria & >= 2 item of Consultant Complexity Criteria BANE05: - Has responsibility for performing system evaluation & enterprise solution consultation as role BA consultant. - Project Diversity and Complexity - Complex: >= 4 items in General Advanced Complexity Criteria & All items in Management Complexity Criteria OR >= 5 items in General Advanced Complexity Criteria & >= 2 item of Consultant Complexity Criteria BANE06: - Has responsibility for performing system evaluation & enterprise solution consultation as role BA consultant. - Project Diversity and Complexity - Very Complex: >= 4 items of Advanced Complexity Criteria & All items of Management Complexity Criteria OR All items in General Advanced & All Consultant Complexity Criteria | C3: Has responsibility for documenting requirement, supporting communicate requirement to stakeholders (under guidance) as role BA member. | D3: Has responsibility for gathering requirement, elaborating and validating gathered requirement as role BA member. | E3: Has responsibility for designing, analyzing and evaluating business solution to ensure that it aligns with the project's goal as role BA member. | F3: Has responsibility for defining requirement approach & process, planning and monitoring business analysis activities as role BA consultant. | G3: Has responsibility for performing system evaluation & enterprise solution consultation as role BA consultant. | H3: Has responsibility for performing system evaluation & enterprise solution consultation as role BA consultant.

Sheet 08. Definitions
A1: Definitions | K1: The Level of Responsibility | M1: Option List | N1: Definition | P1: Explanation
B2: Job Family: | C2: Business Analyst | K2: 5 | L2: Design (BANE05/BANE06) | M2: =K2&": "&L2 -> 5: Design (BANE05/BANE06) | N2: Instruct/Solution design at program/account/BU level | O2: - Be responsible for the whole process from requirement to production deployment - Can review code/mentor for junior developers - Can study new technology and framework to build new teams - Can create solution proposals and present to the customers. - Expert in one area (.NET/Java/Python/AWS/ReacJS/Mobile,...) | P2: Performs a commander role with overall responsibility for projects based on multiple platforms and business domains while supervising teams of professionals and middle management.
B3: Stream: | C3: Individual Professional | K3: 4 | L3: Create (BANE04) | M3: =K3&": "&L3 -> 4: Create (BANE04) | N3: Performs a senior lead/management role | O3: - Be responsible for the whole process from requirement to production deployment - Can review code/mentor for junior developers - Can study new technology and framework to build new teams - Can create solution proposals and present to the customers. | P3: Performs a senior management role with overall responsibility for projects while supervising teams of professionals.
B4: Job Function: | C4: Software Development (SWD) | K4: 3 | L4: Apply (BANE03) | M4: =K4&": "&L4 -> 3: Apply (BANE03) | N4: Performs tasks independently (Project level) | O4: - Can define solutions/code/UT/IT for complex modules - Can review code/mentor for junior developers - Have experience with package deployment - Can study new technology and framework to build new teams | P4: Works in a complex technological area without direct supervision (independently). Receives broad task objectives, is responsible for significant technical decisions and may train other professionals.
B5: Job Sub-Function: | C5: Software Development (SWD) | K5: 2 | L5: Assist (BANE02) | M5: =K5&": "&L5 -> 2: Assist (BANE02) | N5: Performs tasks with limited direct supervision (Project level) | O5: - Can define solutions for simple or medium requirements - Can code and perform UT for complex modules - Can investigate, debug and fix but IT | P5: Performs technical tasks with limited direct supervision and solves problems based on principles of applied science technology. Also makes some decisions for which they assume responsibility.
B6: Job Category: | C6: Software Development | K6: 1 | L6: Follow (BANE01) | M6: =K6&": "&L6 -> 1: Follow (BANE01) | N6: Performs assigned tasks under guideline from supervision (Project level) | O6: - Basic knowledge of one programming language/framework - Can code under guideline or predefine solutions - Can debug and UT | P6: Receives on-the-job training in a variety of new environments while working under close supervision as they gain experience, typically working on small tasks within larger projects.
B7: Job Sub-Category | C7: Software Business Analysis
B8: Specialty Field | C8: Software Product Development | K8: Experience level | M8: Option List
B9: Job Purpose: | C9: Enable change in an enterprise by defining needs and recommend solutions that deliver value to stakeholders via the following activities: - Strategy analysis (Define goals & objectives) - Business analysis planning & monitoring and requirement life cycle management. - Elicitation and collaboration (Requirement gathering) - Requirement analysis and design definition (Define business solution from requirement) - Solution evaluation (Demo prototype & UAT) | K9: 8 | L9: >15 years experience | M9: =K9&": "&L9 -> 8: >15 years experience
B10: Update History: | C10: =MAX('09. Record of Change'!B4:B24) -> 45000 | K10: 7 | L10: 13-15 years experience | M10: =K10&": "&L10 -> 7: 13-15 years experience
K11: 6 | L11: 10-12 years experience | M11: =K11&": "&L11 -> 6: 10-12 years experience
K12: 5 | L12: 8-10 years experience | M12: =K12&": "&L12 -> 5: 8-10 years experience
B13: Job Rank | C13: Code | D13: Job Title | G13: ITM Job Title | K13: 4 | L13: 5-7 years experience | M13: =K13&": "&L13 -> 4: 5-7 years experience
B14: BA | C14: BANE01 | D14: Associate Business Analyst | G14: Software Business Analyst 1 | K14: 3 | L14: 3-5 years experience | M14: =K14&": "&L14 -> 3: 3-5 years experience
C15: BANE02 | D15: Business Analyst | G15: Software Business Analyst 2 | K15: 2 | L15: 2-3 years experience | M15: =K15&": "&L15 -> 2: 2-3 years experience
C16: BANE03 | D16: Senior Business Analyst | G16: Software Business Analyst 3 | K16: 1 | L16: ~1 year experience | M16: =K16&": "&L16 -> 1: ~1 year experience
C17: BANE04 | D17: Business Analysis Leader | G17: Software Business Analysis Leader 4 | K17: 0 | L17: Fundamental awareness | M17: =K17&": "&L17 -> 0: Fundamental awareness
C18: BANE04 | D18: Business Analysis Consultant | G18: Software Business Analysis Consultant 4 | K18: 0 | L18: Not Required | M18: =K18&": "&L18 -> 0: Not Required
C19: BANE05 | D19: Senior Business Analysis Consultant / Leader | G19: Software Business Analyst 5
C20: BANE06 | D20: Principal Business Analysis Consultant / Leader | G20: Software Business Analyst 6 | K20: BA Team Size Indicator | M20: Option List | N20: Explanation
K21: 4 | L21: Global Level | M21: =K21&": "&L21 -> 4: Global Level | N21: Have at least 70% BA2, 10% BA3, 3% BA4, 0.75%BA5
K22: 3 | L22: FSOFT Level | M22: =K22&": "&L22 -> 3: FSOFT Level | N22: Have at least 50% BA2, 10% BA3, 3% BA4, 0.75%BA5
B23: POINTS = LEVEL (selected) * Weight% / MAX Level of Proficiency / 100 | K23: 2 | L23: FSU Level | M23: =K23&": "&L23 -> 2: FSU Level | N23: Have at least 50% BA2, 12% BA3, 3% BA4
B24: CTC: Corporate Training Center | K24: 1 | L24: BU Level | M24: =K24&": "&L24 -> 1: BU Level | N24: Have at least 50% BA2, 12% BA3
B25: AkaLink: Skills Rankings System | K25: 0 | L25: Not Requried | M25: =K25&": "&L25 -> 0: Not Requried | N25: Not Required BA3, BA4
B26: POD: Project Opening Decision
B27: Reference: SEFIX Model | K27: Industry Requirement Complexity level | M27: Option List | N27: Explanation
K28: 5 | L28: Very Complex | M28: =K28&": "&L28 -> 5: Very Complex | N28: >= 4 items of Advanced Complexity Criteria All items of Management Complexity Criteria OR All items in General Advanced All Consultant Complexity Criteria
K29: 4 | L29: Complex | M29: =K29&": "&L29 -> 4: Complex | N29: >= 4 items in General Advanced Complexity Criteria All items in Management Complexity Criteria OR >= 5 items in General Advanced Complexity Criteria >= 2 item of Consultant Complexity Criteria
K30: 3 | L30: Medium | M30: =K30&": "&L30 -> 3: Medium | N30: >= 4 items of General Advanced Complexity Criteria >= 2 items of Management Complexity Criteria OR >=1 item in Consultant Complexity Criteria
K31: 2 | L31: Normal | M31: =K31&": "&L31 -> 2: Normal | N31: All items of Elementary Complexity Criteria >= 1 item in General Advanced Complexity Criteria
K32: 1 | L32: Low | M32: =K32&": "&L32 -> 1: Low | N32: >= 5 items in Elementary Complexity Criteria
K33: 0 | L33: No Complexity | M33: =K33&": "&L33 -> 0: No Complexity | N33: No Complexity
K34: 0 | L34: Not Required. | M34: =K34&": "&L34 -> 0: Not Required. | N34: Not Required.
N35: =1500*3000 -> 4500000
K36: Subordinate Development (1) | M36: Option List | N36: Remark
K37: 4 | L37: >20 Members or Coaching 3-4 Senior BA | M37: =K37&": "&L37 -> 4: >20 Members or Coaching 3-4 Senior BA | N37: Team size average for project at least 3 months experience
K38: 3 | L38: 10-20 Members or Coaching 1-2 Senior BA | M38: =K38&": "&L38 -> 3: 10-20 Members or Coaching 1-2 Senior BA | N38: Team size average for project at least 3 months experience
K39: 2 | L39: 5-10 Members or Coaching 3-4 Junior BA | M39: =K39&": "&L39 -> 2: 5-10 Members or Coaching 3-4 Junior BA | N39: Team size average for project at least 3 months experience
K40: 1 | L40: 1-5 Members or Coaching 1-2 Junior BA | M40: =K40&": "&L40 -> 1: 1-5 Members or Coaching 1-2 Junior BA | N40: Team size average for project at least 3 months experience
K41: 0 | L41: No Member/No Contribution | M41: =K41&": "&L41 -> 0: No Member/No Contribution | N41: Team size average for project at least 3 months experience
K42: 0 | L42: Not Required | M42: =K42&": "&L42 -> 0: Not Required | N42: Not Required
K44: Subordinate Development (2) | M44: Option List | N44: Explanation
K45: 4 | L45: Coaching 3-4 Senior BA | M45: =K45&": "&L45 -> 4: Coaching 3-4 Senior BA
K46: 3 | L46: Coaching 1-2 Senior BA | M46: =K46&": "&L46 -> 3: Coaching 1-2 Senior BA
K47: 2 | L47: Coaching 3-4 Junior BA | M47: =K47&": "&L47 -> 2: Coaching 3-4 Junior BA
K48: 1 | L48: Coaching 1-2 Junior BA | M48: =K48&": "&L48 -> 1: Coaching 1-2 Junior BA
K49: 0 | L49: No Contribution | M49: =K49&": "&L49 -> 0: No Contribution
K50: 0 | L50: No Required | M50: =K50&": "&L50 -> 0: No Required
K52: Skill Level | M52: Option List | N52: Explanation
K53: 6 | L53: Master | M53: =K53&": "&L53 -> 6: Master | N53: In-Depth knowledge and skills as Insider, Scientist, Researcher, Producer, Creator, Inventor, Core Handler.
K54: 5 | L54: Expert | M54: =K54&": "&L54 -> 5: Expert | N54: Is known as an expert in this field; Able to apply the competency in considerably difficult cases; Can provide the guidance, troubleshoot and answer the questions related to this areas of expertise and fields where the skills are used. • Focus on strategy; • Has demonstrated the consistent excellence in applying this competency across multiple projects and/or organizations; • Is considered the “go to” person in this field within department or organizations; • Can create new applications and lead the development of reference resources for this competency; • Able to diagram or explain the process elements and issues related to organizational issues and trends in sufficient details during discussions and presentations, to foster a greater understanding among internal and external colleagues.
K55: 4 | L55: Advanced | M55: =K55&": "&L55 -> 4: Advanced | N55: Be able to perform the duties associated with the competency and skill without any assistances; Able to apply the competency in considerable difficult cases; Would be immediately recognized within organization as "answer specialist / a person to ask" when the difficult questions are arising regarding this skill. • Focus on broad of the organizational or professional issues; • Has consistently provided practical/relevant ideas and perspectives on process or practice improvements which may easily be implemented; • Has ability of coaching the others in the application of this competency by translating complex nuances relating to this competency into easily understand the terms; • Has participated senior level discussions regarding this competency; • Has assisted the development of reference resources for this competency.
K56: 3 | L56: Intermediate | M56: =K56&": "&L56 -> 3: Intermediate | N56: Has ability to implement successfully the duties in the competency if required; Able to apply the competency in difficult cases; Can often perform the skills independently with or without requested help from an expert by time to time. • Focus on applying for and improving of the knowledge or skill; • Has applied this competency in situations that occasionally needs minimal guidance to perform them successfully; • Able to discuss how to apply and the impact of the changes for processes, policies, and procedures in this field.
K57: 2 | L57: Limited Experience | M57: =K57&": "&L57 -> 2: Limited Experience | N57: Has the level of experience in classroom, scenario of experiment or as a trainee on-the-job; Can apply the competency in the simplest cases; Can getting support when implementation of these skills if needed. • Focus on the development through on-the-job experience; • Able to discuss terminologies, concepts, principles, and relevant issues; • Use the full range of reference resources in this competency.
K58: 1 | L58: Fundamental Awareness | M58: =K58&": "&L58 -> 1: Fundamental Awareness | N58: Has a common knowledge or an understanding of basic techniques and theoretical concepts. • Focus on learning and theory.
K59: 0 | L59: No Knowledge | M59: =K59&": "&L59 -> 0: No Knowledge | N59: Have no knowledge and experience.
K60: 0 | L60: Not Required | M60: =K60&": "&L60 -> 0: Not Required | N60: Not requried knowledge and experience.
K62: Foreign Language Skill Level | M62: Option List | N62: Explanation
K63: 7 | L63: TOEIC >901, TOELF iBT 96-120, IELTS 8.6-9.0, CEFR C2, JP N1 or equivalent | M63: =K63&": "&L63 -> 7: TOEIC >901, TOELF iBT 96-120, IELTS 8.6-9.0, CEFR C2, JP N1 or equivalent | N63: Can use the language in the way similar educated native speakers would.
K64: 6 | L64: TOEIC 801-900, TOELF iBT 81-95, IELTS 7.6-8.5, CEFR C1, JP N2 or equivalent | M64: =K64&": "&L64 -> 6: TOEIC 801-900, TOELF iBT 81-95, IELTS 7.6-8.5, CEFR C1, JP N2 or equivalent | N64: Can participate in all manners of the conversations with ease and rarely makes grammatical mistakes.
K65: 5 | L65: TOEIC 701-800, TOELF iBT 71-80, IELTS 6.6-7.5, CEFR B2+, JP N3+ or equivalent | M65: =K65&": "&L65 -> 5: TOEIC 701-800, TOELF iBT 71-80, IELTS 6.6-7.5, CEFR B2+, JP N3+ or equivalent | N65: Can participate in all manners of the conversations with ease and rarely makes grammatical mistakes.
K66: 4 | L66: TOEIC 601-700, TOELF iBT 61-70, IELTS 5.6-6.5, CEFR B2, JP N3 or equivalent | M66: =K66&": "&L66 -> 4: TOEIC 601-700, TOELF iBT 61-70, IELTS 5.6-6.5, CEFR B2, JP N3 or equivalent | N66: Can easily discuss a variety of topics and almost totally understand what others are saying in the conversation.
K67: 3 | L67: TOEIC 501-600, TOELF iBT 51-60, IELTS 4.6-5.5, CEFR B1+, JP N4+ or equivalent | M67: =K67&": "&L67 -> 3: TOEIC 501-600, TOELF iBT 51-60, IELTS 4.6-5.5, CEFR B1+, JP N4+ or equivalent | N67: Can fulfill the talking about social interactions such as self-introduction, introducing about family, and debate the current events.
K68: 2 | L68: TOEIC 451-500, TOELF iBT 42-50, IELTS 4.0-4.5, CEFR B1, JP N4 or equivalent | M68: =K68&": "&L68 -> 2: TOEIC 451-500, TOELF iBT 42-50, IELTS 4.0-4.5, CEFR B1, JP N4 or equivalent | N68: Can fulfill the basic knowledge of a foreign language, such as ordering meals, the question of the time, and the question of the directions.
K69: 1 | L69: TOEIC <=450, TOELF iBT <=41, IELTS 3.5-3.9, CEFR A2, JP N5 or equivalent | M69: =K69&": "&L69 -> 1: TOEIC <=450, TOELF iBT <=41, IELTS 3.5-3.9, CEFR A2, JP N5 or equivalent | N69: Can read the basic knowledge of a foreign language, such as ordering meals, the question of the time, and the question of the directions.
K70: 0 | L70: No Practical Proficiency | M70: =K70&": "&L70 -> 0: No Practical Proficiency
K71: 0 | L71: Not Required | M71: =K71&": "&L71 -> 0: Not Required
K73: Business Analyst Certificates level | M73: Level Label | N73: Explanation
K74: 5 | L74: >=4 Certificates of Business Analyst Advance or upper Advance | M74: =K74&": "&L74 -> 5: >=4 Certificates of Business Analyst Advance or upper Advance
K75: 4 | L75: >=3 Certificates of Business Analyst Advance or Equivalent | M75: =K75&": "&L75 -> 4: >=3 Certificates of Business Analyst Advance or Equivalent
K76: 3 | L76: >=2 Certificates of Business Analyst Advance or Equivalent | M76: =K76&": "&L76 -> 3: >=2 Certificates of Business Analyst Advance or Equivalent
K77: 2 | L77: Certified Business Analyst Advance or Equivalent | M77: =K77&": "&L77 -> 2: Certified Business Analyst Advance or Equivalent
K78: 1 | L78: At least 1 Certified Business Analyst Foundation or Equivalent | M78: =K78&": "&L78 -> 1: At least 1 Certified Business Analyst Foundation or Equivalent
K79: 0 | L79: No Certificate or Award | M79: =K79&": "&L79 -> 0: No Certificate or Award
K80: 0 | L80: Not Required | M80: =K80&": "&L80 -> 0: Not Required
K82: Training course in year | M82: Level Label
K83: 4 | L83: Join >=7 training or workshop | M83: =K83&": "&L83 -> 4: Join >=7 training or workshop
K84: 3 | L84: Join >=5 training or workshop | M84: =K84&": "&L84 -> 3: Join >=5 training or workshop
K85: 2 | L85: Join >=3 training or workshop | M85: =K85&": "&L85 -> 2: Join >=3 training or workshop
K86: 1 | L86: Join <=2 training or workshop | M86: =K86&": "&L86 -> 1: Join <=2 training or workshop
K87: 0 | L87: No training/workshop | M87: =K87&": "&L87 -> 0: No training/workshop
K88: 0 | L88: Not Required | M88: =K88&": "&L88 -> 0: Not Required
K90: Community Contributions | M90: Level Label
K91: 4 | L91: Lecturer of Technical workshop of FSOFT | M91: =K91&": "&L91 -> 4: Lecturer of Technical workshop of FSOFT
K92: 4 | L92: Contribute >= 1 IP/Solution at FSOFT level | M92: =K92&": "&L92 -> 4: Contribute >= 1 IP/Solution at FSOFT level
K93: 4 | L93: Trainer of CTC/FSOFT | M93: =K93&": "&L93 -> 4: Trainer of CTC/FSOFT
K94: 3 | L94: Contribute >= 1 IP/Solution at BU/FSU level | M94: =K94&": "&L94 -> 3: Contribute >= 1 IP/Solution at BU/FSU level
K95: 3 | L95: Lecturer/Trainer of Technical workshop of FSU | M95: =K95&": "&L95 -> 3: Lecturer/Trainer of Technical workshop of FSU
K96: 2 | L96: Trainer of Technical training of BU | M96: =K96&": "&L96 -> 2: Trainer of Technical training of BU
K97: 2 | L97: Contribute >= 1 IP/Solution at project level | M97: =K97&": "&L97 -> 2: Contribute >= 1 IP/Solution at project level
K98: 1 | L98: Training, support other projects | M98: =K98&": "&L98 -> 1: Training, support other projects
K99: 0 | L99: No Contribution | M99: =K99&": "&L99 -> 0: No Contribution
K100: 0 | L100: Not Required | M100: =K100&": "&L100 -> 0: Not Required
K102: Graduate Certificates and Degrees
K103: 8 | L103: Doctorate Degree (Ph.D) | M103: =K103&"-"&L103 -> 8-Doctorate Degree (Ph.D)
K104: 7 | L104: Post-Master's Certificate / Master's Degree +3 Years of Experience | M104: =K104&"-"&L104 -> 7-Post-Master's Certificate / Master's Degree +3 Years of Experience
K105: 6 | L105: Master's Degree or 3 Years of Experience | M105: =K105&"-"&L105 -> 6-Master's Degree or 3 Years of Experience
K106: 5 | L106: Master's Degree | M106: =K106&"-"&L106 -> 5-Master's Degree
K107: 4 | L107: Graduate Degree / Bachelor Degree + 5 Years of Experience | M107: =K107&"-"&L107 -> 4-Graduate Degree / Bachelor Degree + 5 Years of Experience
...

Sheet 09. Career Development
B1: Courses for Reskilling & Upskilling
B2: No | C2: Source | D2: Course Title | E2: Course URL | F2: Course Description | G2: Lessons | H2: Time
B3: 1 | C3: Udemy | D3: Fundamentals of Business Analysis | E3: https://fpt-software.udemy.com/course/businessanalysis/learn/lecture/6916848 | F3: Get the foundation in business analysis you need to solve your organization's biggest problems. | G3: 121 of 121 items | H3: 6hr 4min
B4: 2 | C4: Udemy | D4: Agile Business Analysis | E4: https://fpt-software.udemy.com/course/agile-business-analysis/learn/lecture/8003724 | F4: Developing the analysis maturity and confidence you need... to deliver products in an agile way... | G4: 33 of 33 items | H4: 1hr 35min
B5: 3 | C5: Udemy | D5: Business Analysis: Developing Irresistible Business Cases | E5: https://fpt-software.udemy.com/course/business-cases/learn/lecture/8565686 | F5: Building the business acumen you need to promote your projects to management | G5: 24 of 24 items | H5: 2hr 8min
B6: 4 | C6: Udemy | D6: Business Analysis: Working with Use Cases | E6: https://fpt-software.udemy.com/course/usecases/learn/lecture/10171542 | F6: An introductory course on use case modeling for Business Analysts or those looking to transition into a BA role. | G6: 33 of 33 items | H6: 2hr 6min
B7: 5 | C7: Udemy | D7: Business Analysis: Functional & Non-Functional Requirements | E7: https://fpt-software.udemy.com/course/identify-functional-and-non-functional-requirements/learn/lecture/1608010 | F7: Simple Requirements Decomposition / Drill-Down Techniques for Defining Product Behaviors and Qualities | G7: 19 of 19 items | H7: 56min
B8: 6 | C8: Udemy | D8: Business Analysis: Data Flow Diagrams to Visualize Workflows | E8: https://fpt-software.udemy.com/course/project-management-for-business-analyst/learn/lecture/5454838 | F8: Process Modeling Techniques for Requirements Elicitation and Workflow Analysis | G8: 30 of 30 items | H8: 2hr 28min
B9: 7 | C9: Udemy | D9: Business Analyst: Project Management Techniques and Tools | E9: https://fpt-software.udemy.com/course/project-management-for-business-analyst/learn/lecture/5454838 | F9: Learn project management techniques to increase your project success rate as a Business Analyst! | G9: 53 of 53 items | H9: 5hr 13min
B10: 8 | C10: Udemy | D10: Strategy for Management Consultants & Business Analysts | E10: https://fpt-software.udemy.com/course/strategy-for-management-consultants-business-analysts/learn/lecture/10178254 | F10: Top advices from consulting practice with examples and case studies | G10: 137 of 137 items | H10: 6hr 18min
B11: 9 | C11: Udemy | D11: POSTMAN API Testing - Step by Step for Beginners | E11: https://fpt-software.udemy.com/course/postman-api-testing-step-by-step-for-beginners/learn/lecture/23643176 | F11: learn POSTMAN Step by Step from scratch with real world examples | G11: 39 of 39 items | H11: 4hr 50min
B12: 10 | C12: Udemy | D12: Full Business Analysis Study Guide (CCBA®/CBAP® endorsed) | E12: https://fpt-software.udemy.com/course/business-analysis-study-guide/learn/lecture/15304154 | F12: Sharpen your BA skills for a better career and get prepared for a CBAP® or CCBA® exam! | G12: 110 of 110 items | H12: 5hr 35min

Sheet 10. Job Interview
B1: Software Business Analyst Role - Job Interview | E1: CANDIDATE RESULTS INTERVIEWED BY INTERVIEWER | H1: CHOOSE LEVEL / RANK Ú TO BE HIRED | J1: ACTIONS TO IMPROVE CANDIDATE'S RANK
B3: Nguyen Van An - AnNV19 | D3: BUY-IN Weighted % | E3: =IF('06. Assessment Summary'!U30>0,"Not Satisfied RANK","Satisfied RANK")&": "&IF(G3>='04. Job Descriptions'!R4,'04. Job Descriptions'!R2&"-"&'04. Job Descriptions'!R3,IF(G3>='04. Job Descriptions'!Q4,'04. Job Descriptions'!Q2&"-"&'04. Job Descriptions'!Q3,IF(G3>='04. Job Descriptions'!P4,'04. Job Descriptions'!P2&"-"&'04. Job Descriptions'!P3,IF(G3>='04. Job Descriptions'!O4,'04. Job Descriptions'!O2&"-"&'04. Job Descriptions'!O3,IF(G3>='04. Job Descriptions'!N4,'04. Job Descriptions'!N2&"-"&'04. Job Descriptions'!N3,IF(G3>='04. Job Descriptions'!M4,'04. Job Descriptions'!M2&"-"&'04. Job Descriptions'!M3,"Not Ranked")))))) -> Not Satisfied RANK: Not Ranked | G3: =ROUND(G5+G9+G19+G24,0) -> 0 | H3: SBA04 | I3: =ROUND(I5+I9+I19+I24,0) -> 0
B4: Interview Items | C4: Explanation of Interview Items | D4: =SUM(D5,D9,D19,D24) -> #REF! | E4: CHOOSE Competency Level for each evaluation criteria Ú | F4: ADD remarks or evidences for each evaluation Ú | G4: Actual Score | H4: Required Competency Level for an expected Candidate | I4: Required Score | J4: Need to improve? | K4: Action to improve rankings | L4: Deadline
B5: ='04. Job Descriptions'!B8 -> Experiences & Contributions | C5: CANDIDATE is required to have one or more of the following professional experiences and project contributions | D5: ='04. Job Descriptions'!#REF! -> #REF! | G5: =SUM(G6:G8) -> 0 | I5: =SUM(I6:I8) -> 0
B6: ='04. Job Descriptions'!B9 -> Business Analysis Experiences (*) | C6: ='04. Job Descriptions'!D9 -> Number of years working as Business Analyst, Software Business Analyst, Software Development Life Cycle, Team Work, Agile Mindset | D6: ='04. Job Descriptions'!#REF! -> #REF! | E6: 2: 2-3 years experience | G6: =IFERROR((LEFT(E6,1)*D6/'04. Job Descriptions'!K9)*100,0) -> 0 | H6: =IFERROR(HLOOKUP($H$3,'04. Job Descriptions'!$B$4:$J$35,7,0),"NA") -> NA | I6: =IFERROR(HLOOKUP($H$3,'04. Job Descriptions'!$M$3:$R$35,8,0),"NA") -> NA | J6: =IF(G6<I6,"Yes","No") -> Yes
B7: ='04. Job Descriptions'!B11 -> Number of Projects/Phases | C7: ='04. Job Descriptions'!D11 -> The successful projects in business requirements that you have done at least one of the following tasks: analyze, design, develop, support, migrate, deploy, manage software projects or phases (FSOFTER can provide joined project is project rank of Project Rank A, Project Rank B, Project Rank C in Evidence section) | D7: ='04. Job Descriptions'!#REF! -> #REF! | E7: 4: ~11-15 Projects / Phases | G7: =IFERROR((LEFT(E7,1)*D7/'04. Job Descriptions'!K11)*100,0) -> 0 | H7: =IFERROR(HLOOKUP($H$3,'04. Job Descriptions'!$B$4:$J$35,9,0),"NA") -> NA | I7: =IFERROR(HLOOKUP($H$3,'04. Job Descriptions'!$M$3:$R$35,10,0),"NA") -> NA | J7: =IF(G7<I7,"Yes","No") -> Yes
B8: ='04. Job Descriptions'!B13 -> Industry Experiences (IT and Non-IT fields) | C8: ='04. Job Descriptions'!D13 -> Banking, Finance, Insurance, Aviation, Automotive, Oil and Gas, Health Care, ERP, Data Warehouse, Logistic, Real estate, Telecom, … | D8: ='04. Job Descriptions'!#REF! -> #REF! | E8: 3: 3-5 years experience | G8: =IFERROR((LEFT(E8,1)*D8/'04. Job Descriptions'!K13)*100,0) -> 0 | H8: =IFERROR(HLOOKUP($H$3,'04. Job Descriptions'!$B$4:$J$35,11,0),"NA") -> NA | I8: =IFERROR(HLOOKUP($H$3,'04. Job Descriptions'!$M$3:$R$35,12,0),"NA") -> NA | J8: =IF(G8<I8,"Yes","No") -> Yes
B9: ='04. Job Descriptions'!B15 -> Professional Business Analysis Skills | C9: CANDIDATE is required to have one or more of the following specialized skills to perform assigned tasks | D9: ='04. Job Descriptions'!#REF! -> #REF! | G9: =SUM(G10:G18) -> 0 | I9: =SUM(I10:I18) -> 0
B10: ='04. Job Descriptions'!B16 -> Business Analysis Planning & Monitoring (*) | C10: ='04. Job Descriptions'!D16 -> - Plan Business Analysis Approach - Plan Stakeholders Engagement - Plan Business Analysis Governance - Plan Business Analysis Information Management - Identify Business Analysis Performance Improvement | D10: ='04. Job Descriptions'!#REF! -> #REF! | E10: 4: Advanced | G10: =IFERROR((LEFT(E10,1)*D10/'04. Job Descriptions'!K16)*100,0) -> 0 | H10: =IFERROR(HLOOKUP($H$3,'04. Job Descriptions'!$B$4:$J$35,14,0),"NA") -> NA | I10: =IFERROR(HLOOKUP($H$3,'04. Job Descriptions'!$M$3:$R$35,15,0),"NA") -> NA | J10: =IF(G10<I10,"Yes","No") -> Yes
B11: ='04. Job Descriptions'!B17 -> Requirement Elicitation & Collaboration (*) | C11: ='04. Job Descriptions'!D17 -> - Elicitation Preparation - Requirement Workshop / Conduct Elicitation - Requirement Transfer & Confirmation - Requirement Management & Communication - Stakeholders Management | D11: ='04. Job Descriptions'!#REF! -> #REF! | E11: 4: Advanced | G11: =IFERROR((LEFT(E11,1)*D11/'04. Job Descriptions'!K17)*100,0) -> 0 | H11: =IFERROR(HLOOKUP($H$3,'04. Job Descriptions'!$B$4:$J$35,15,0),"NA") -> NA | I11: =IFERROR(HLOOKUP($H$3,'04. Job Descriptions'!$M$3:$R$35,16,0),"NA") -> NA | J11: =IF(G11<I11,"Yes","No") -> Yes
B12: ='04. Job Descriptions'!B18 -> Business Requirement Analysis (*) | C12: ='04. Job Descriptions'!D18 -> - Requirement Specification - Requirement Verification - Requirement Validation - Requirement UI/UX Behavior Design & Principles - Requirement CX (Customer Experience / Customer Journey) - Solution Definition & Assessment | D12: ='04. Job Descriptions'!#REF! -> #REF! | E12: 4: Advanced | G12: =IFERROR((LEFT(E12,1)*D12/'04. Job Descriptions'!K18)*100,0) -> 0 | H12: =IFERROR(HLOOKUP($H$3,'04. Job Descriptions'!$B$4:$J$35,16,0),"NA") -> NA | I12: =IFERROR(HLOOKUP($H$3,'04. Job Descriptions'!$M$3:$R$35,17,0),"NA") -> NA | J12: =IF(G12<I12,"Yes","No") -> Yes
B13: ='04. Job Descriptions'!B19 -> Business Solution Evaluation | C13: ='04. Job Descriptions'!D19 -> - Measure Solution Performance - Analyze Performance Measured - Assess Solution Limitations - Assess Enterprise Limitations - Recommend Actions to Increase Solution's Value | D13: ='04. Job Descriptions'!#REF! -> #REF! | E13: 4: Advanced | G13: =IFERROR((LEFT(E13,1)*D13/'04. Job Descriptions'!K19)*100,0) -> 0 | H13: =IFERROR(HLOOKUP($H$3,'04. Job Descriptions'!$B$4:$J$35,17,0),"NA") -> NA | I13: =IFERROR(HLOOKUP($H$3,'04. Job Descriptions'!$M$3:$R$35,18,0),"NA") -> NA | J13: =IF(G13<I13,"Yes","No") -> Yes
B14: ='04. Job Descriptions'!B20 -> Business Requirement Life-Cycle | C14: ='04. Job Descriptions'!D20 -> - Requirement Tracing - Requirement Maintenance - Requirement Prioritization - Requirement Change Management - Requirement Approval | D14: ='04. Job Descriptions'!#REF! -> #REF! | E14: 3: Intermediate | G14: =IFERROR((LEFT(E14,1)*D14/'04. Job Descriptions'!K20)*100,0) -> 0 | H14: =IFERROR(HLOOKUP($H$3,'04. Job Descriptions'!$B$4:$J$35,18,0),"NA") -> NA | I14: =IFERROR(HLOOKUP($H$3,'04. Job Descriptions'!$M$3:$R$35,19,0),"NA") -> NA | J14: =IF(G14<I14,"Yes","No") -> Yes
B15: ='04. Job Descriptions'!B21 -> Business Strategy Design | C15: ='04. Job Descriptions'!D21 -> - Current State Analysis - Future State Analysis - Risk Analysis - Define Change Strategy | D15: ='04. Job Descriptions'!#REF! -> #REF! | E15: 3: Intermediate | G15: =IFERROR((LEFT(E15,1)*D15/'04. Job Descriptions'!K21)*100,0) -> 0 | H15: =IFERROR(HLOOKUP($H$3,'04. Job Descriptions'!$B$4:$J$35,19,0),"NA") -> NA | I15: =IFERROR(HLOOKUP($H$3,'04. Job Descriptions'!$M$3:$R$35,20,0),"NA") -> NA | J15: =IF(G15<I15,"Yes","No") -> Yes
B16: ='04. Job Descriptions'!B22 -> Business Acumen and Mindsets | C16: ='04. Job Descriptions'!D22 -> - Understanding of fundamental business principles and best practices. - Analysis mindsets | D16: ='04. Job Descriptions'!#REF! -> #REF! | E16: 3: Intermediate | G16: =IFERROR((LEFT(E16,1)*D16/'04. Job Descriptions'!K22)*100,0) -> 0 | H16: =IFERROR(HLOOKUP($H$3,'04. Job Descriptions'!$B$4:$J$35,20,0),"NA") -> NA | I16: =IFERROR(HLOOKUP($H$3,'04. Job Descriptions'!$M$3:$R$35,21,0),"NA") -> NA | J16: =IF(G16<I16,"Yes","No") -> Yes
B17: ='04. Job Descriptions'!B23 -> Software Design and Technology Stack | C17: ='04. Job Descriptions'!D23 -> - Software Architecture Design - Object Oriented Design - Relational and Non-Relational Database Platforms | D17: ='04. Job Descriptions'!#REF! -> #REF! | E17: 4: Advanced | G17: =IFERROR((LEFT(E17,1)*D17/'04. Job Descriptions'!K23)*100,0) -> 0 | H17: =IFERROR(HLOOKUP($H$3,'04. Job Descriptions'!$B$4:$J$35,21,0),"NA") -> NA | I17: =IFERROR(HLOOKUP($H$3,'04. Job Descriptions'!$M$3:$R$35,22,0),"NA") -> NA | J17: =IF(G17<I17,"Yes","No") -> Yes
B18: ='04. Job Descriptions'!B24 -> Business Analysis Tools | C18: ='04. Job Descriptions'!D24 -> - Business Analysis Tools - UI/UX Design Tools - Architecture Design Tools - Communication Tools | D18: ='04. Job Descriptions'!#REF! -> #REF! | E18: 3: Intermediate | G18: =IFERROR((LEFT(E18,1)*D18/'04. Job Descriptions'!K24)*100,0) -> 0 | H18: =IFERROR(HLOOKUP($H$3,'04. Job Descriptions'!$B$4:$J$35,22,0),"NA") -> NA | I18: =IFERROR(HLOOKUP($H$3,'04. Job Descriptions'!$M$3:$R$35,23,0),"NA") -> NA | J18: =IF(G18<I18,"Yes","No") -> Yes
B19: ='04. Job Descriptions'!B25 -> Foreign Language & Certificates | C19: CANDIDATE may have one or more of the following Foreign Language/Technical qualifications to perform assigned tasks | D19: ='04. Job Descriptions'!#REF! -> #REF! | G19: =SUM(G20:G23) -> 0 | I19: =SUM(I20:I23) -> 0
B20: ='04. Job Descriptions'!B26 -> Foreign Language | C20: ='04. Job Descriptions'!D26 -> - Language Proficiency: English, Japanese, Korean, Chinese, Germany, French, Thailand | D20: ='04. Job Descriptions'!#REF! -> #REF! | E20: 3: TOEIC 501-600, TOELF iBT 51-60, IELTS 4.6-5.5, CEFR B1+, JP N4+ or equivalent | G20: =IFERROR((LEFT(E20,1)*D20/'04. Job Descriptions'!K26)*100,0) -> 0 | H20: =IFERROR(HLOOKUP($H$3,'04. Job Descriptions'!$B$4:$J$35,24,0),"NA") -> NA | I20: =IFERROR(HLOOKUP($H$3,'04. Job Descriptions'!$M$3:$R$35,25,0),"NA") -> NA | J20: =IF(G20<I20,"Yes","No") -> Yes
B21: ='04. Job Descriptions'!B27 -> Education Background | C21: ='04. Job Descriptions'!D27 -> Required one of degree in Engineering and Non-Engineering: - Engineering: Computer Science | Information Technology | Computer Engineering | Software Engineering, ... - Non-Engineering: Economics, Finances, Administrations, Social Science, Supply Chain, Logistics, ... | D21: ='04. Job Descriptions'!#REF! -> #REF! | E21: 3-Bachelor Degree / Post-Baccalaureate Certificate | G21: =IFERROR((LEFT(E21,1)*D21/'04. Job Descriptions'!K27)*100,0) -> 0 | H21: =IFERROR(HLOOKUP($H$3,'04. Job Descriptions'!$B$4:$J$35,25,0),"NA") -> NA | I21: =IFERROR(HLOOKUP($H$3,'04. Job Descriptions'!$M$3:$R$35,26,0),"NA") -> NA | J21: =IF(G21<I21,"Yes","No") -> Yes
B22: ='04. Job Descriptions'!B28 -> Business Analysis Certifications | C22: ='04. Job Descriptions'!D28 -> - Required certificates in Business Analysis: Business Analyst, Software Business Analyst | D22: ='04. Job Descriptions'!#REF! -> #REF! | E22: 2: Certified Business Analyst Advance or Equivalent | G22: =IFERROR((LEFT(E22,1)*D22/'04. Job Descriptions'!K28)*100,0) -> 0 | H22: =IFERROR(HLOOKUP($H$3,'04. Job Descriptions'!$B$4:$J$35,26,0),"NA") -> NA | I22: =IFERROR(HLOOKUP($H$3,'04. Job Descriptions'!$M$3:$R$35,27,0),"NA") -> NA | J22: =IF(G22<I22,"Yes","No") -> Yes
B23: ='04. Job Descriptions'!B29 -> Individual Learning in Year | C23: ='04. Job Descriptions'!D29 -> - Joined the training courses of any FSOFT program (upskilling, reskilling, fasttrack, internal training) related to Business Analysis in year (ranking year) | D23: ='04. Job Descriptions'!#REF! -> #REF! | E23: 2: Join >=3 training or workshop | G23: =IFERROR((LEFT(E23,1)*D23/'04. Job Descriptions'!K29)*100,0) -> 0 | H23: =IFERROR(HLOOKUP($H$3,'04. Job Descriptions'!$B$4:$J$35,27,0),"NA") -> NA | I23: =IFERROR(HLOOKUP($H$3,'04. Job Descriptions'!$M$3:$R$35,28,0),"NA") -> NA | J23: =IF(G23<I23,"Yes","No") -> Yes
B24: ='04. Job Descriptions'!B30 -> Non-Engineering and Softskills | C24: CANDIDATE is required to have one or more of the following soft skills and other skills to perform assigned tasks | D24: ='04. Job Descriptions'!#REF! -> #REF! | G24: =SUM(G25:G29) -> 0 | I24: =SUM(I25:I29) -> 0
B25: ='04. Job Descriptions'!B31 -> Communication and Problem Solving | C25: ='04. Job Descriptions'!D31 -> - Team Work - Leadership & Motivation - Communication - Problem Solving - Change Management - Networking/ Relationship building | D25: ='04. Job Descriptions'!#REF! -> #REF! | E25: 3: Intermediate | G25: =IFERROR((LEFT(E25,1)*D25/'04. Job Descriptions'!K31)*100,0) -> 0 | H25: =IFERROR(HLOOKUP($H$3,'04. Job Descriptions'!$B$4:$J$35,29,0),"NA") -> NA | I25: =IFERROR(HLOOKUP($H$3,'04. Job Descriptions'!$M$3:$R$35,30,0),"NA") -> NA | J25: =IF(G25<I25,"Yes","No") -> Yes
B26: ='04. Job Descriptions'!B32 -> Analytical and Critical Thinking | C26: ='04. Job Descriptions'!D32 -> - Research - Forecasting - Data mining - Data and metrics interpreting - Reporting - Organization | D26: ='04. Job Descriptions'!#REF! -> #REF! | E26: 3: Intermediate | G26: =IFERROR((LEFT(E26,1)*D26/'04. Job Descriptions'!K32)*100,0) -> 0 | H26: =IFERROR(HLOOKUP($H$3,'04. Job Descriptions'!$B$4:$J$35,31,0),"NA") -> NA | I26: =IFERROR(HLOOKUP($H$3,'04. Job Descriptions'!$M$3:$R$35,32,0),"NA") -> NA | J26: =IF(G26<I26,"Yes","No") -> Yes
B27: ='04. Job Descriptions'!B33 -> Organization and Industry Knowledge | C27: ='04. Job Descriptions'!D33 -> - Agile Mindset - Process Understanding - Product Understanding - Market trends & Challenges - Market drivers - Customer Segmentation Understanding - Organization Knowledge | D27: ='04. Job Descriptions'!#REF! -> #REF! | E27: 3: Intermediate | G27: =IFERROR((LEFT(E27,1)*D27/'04. Job Descriptions'!K33)*100,0) -> 0 | H27: =IFERROR(HLOOKUP($H$3,'04. Job Descriptions'!$B$4:$J$35,30,0),"NA") -> NA | I27: =IFERROR(HLOOKUP($H$3,'04. Job Descriptions'!$M$3:$R$35,31,0),"NA") -> NA | J27: =IF(G27<I27,"Yes","No") -> Yes
B28: ='04. Job Descriptions'!B34 -> Project Risk Management | C28: ='04. Job Descriptions'!D34 -> - Understand and utilize process of implementing risk response plans - Tracking identified risks, monitoring residual risks, identifying new risks - Evaluating risk process effectiveness throughout the project. - Forecast risk that may occur in range of project that the team is responsible for. - Analyze and perform preventitive actions to reduce risks raised by members. - In the case that risks cannot be closed, raise the risk to leader/mamager and discuss with leader/manger to find out preventitive actions then follow up. (the risk in Methodology is the risk of Business solution. the risk mentioned in this sheet derives from project activities, especially in oursourcing project.) | D28: ='04. Job Descriptions'!#REF! -> #REF! | E28: 3: Intermediate | G28: =IFERROR((LEFT(E28,1)*D28/'04. Job Descriptions'!K34)*100,0) -> 0 | H28: =IFERROR(HLOOKUP($H$3,'04. Job Descriptions'!$B$4:$J$35,32,0),"NA") -> NA | I28: =IFERROR(HLOOKUP($H$3,'04. Job Descriptions'!$M$3:$R$35,33,0),"NA") -> NA | J28: =IF(G28<I28,"Yes","No") -> Yes
B29: ='04. Job Descriptions'!B35 -> Project Human Resource Management | C29: ='04. Job Descriptions'!D35 -> - Understand the ability of each BA to assign appropriate projects/tasks. - Understand project request for BA service to determine proper resource plan. - Regularly control BA allocation to optimize resource. - Monitor and control progress and status of BA involvement in each and every project; detect, resolve and followup to close any issue arising. - Evaluate performance, identify strengths as well as improvement points and propose career path for each BA | D29: ='04. Job Descriptions'!#REF! -> #REF! | E29: 3: Intermediate | G29: =IFERROR((LEFT(E29,1)*D29/'04. Job Descriptions'!K35)*100,0) -> 0 | H29: =IFERROR(HLOOKUP($H$3,'04. Job Descriptions'!$B$4:$J$35,33,0),"NA") -> NA | I29: =IFERROR(HLOOKUP($H$3,'04. Job Descriptions'!$M$3:$R$35,34,0),"NA") -> NA | J29: =IF(G29<I29,"Yes","No") -> Yes

Sheet 09. Record of Change
A1: Record of Change
B3: Date | C3: File Version | D3: #ID | E3: Action | F3: Author/Editor | G3: Requirement | H3: Reviewer | I3: Approver | J3: Description
B4: 44629 | C4: Competency-Based.SBA.JobDescription.FSOFT.v1.0.xlsx | E4: Clone | F4: KhangPH | G4: HR | J4: Cloned for BA Job Roles based on SEFIX Framework
B5: 44630 | C5: Competency-Based.SBA.JobDescription.FSOFT.v1.0.xlsx | E5: Merge | F5: KhangPH | G5: HR | J5: Merged items of JD_Business Analyst_BA_v0.80.xlsx from F-Career
B6: 44656 | C6: Competency-Based.SBA.JobDescription.FSOFT.v1.1.xlsx | E6: Update | F6: KhangPH | G6: HR | J6: Added and Updated Models, JD, JA, Summary and Responsibilities
B7: 44706 | C7: Competency-Based.SBA.JobDescription.FSOFT.v1.2.xlsx | E7: Update | F7: KhangPH | G7: HR | J7: Changed levels of English / Japanese according policy of FSOFT 2022
B8: 44737 | C8: Competency-Based.SBA.JobDescription.FSOFT.v1.3.xlsx | E8: Update | F8: KhangPH | G8: HR | J8: Translated header text of cell: E5, E9, E16, E26, E31 to English in "04. Job Descriptions" Added new sheet "07. Job Interview" and use BUY-IN % in "02. Models" for Interview activity Added new sheet "09. Career Development" for Reskilling & Upskilling
B9: 22-09-2022 | C9: Competency-Based.SBA.JobDescription.FSOFT.v1.4.xlsx | E9: Updated | F9: KhangPH | G9: HR | J9: Hide sheets of "10. Job Interview" "09. Career Development" Corrected job code from "SBA" to "BANE" Increased Industry Experiences from 2% to 10%
B10: 44867 | C10: Competency-Based.SBA.JobDescription.FSOFT.v1.5.xlsx | E10: Updated | F10: KhangPH | G10: ChiNTT | J10: Corrected the formula of cell E3 from =IF('06. Assessment Summary'!S29>0,"Not Satisfied RANK","Satisfied RANK") to =IF(G3<'06. Assessment Summary'!R5,"Not Qualified RANK","Qualified RANK") in sheet "05. Job Rankings"
B11: 44873 | C11: Competency-Based.SBA.JobDescription.FSOFT.v1.6.xlsx | E11: Updated | F11: KhangPH | G11: ChiNTT | J11: Updated template 1. Thêm stopped message cho các cô O7:O19 cho user biết tổng số bonus <=5 points "Sorry,you are allowed to add Bonus points less than 5 points." 2. Thay chữ "Not Rank" => RANK 1 thấp nhất của Job Title. Thay đổi biểu thức ô E3=> '06. Assessment Summary'!E5 3. Nếu Score >= Score của RANK i, nhưng có 1 Mandatory thì vẫn chưa đạt Thay đổi biểu thức ô E3 => IF('06. Assessment Summary'!U30>0,"Not Qualified RANK", 4. Nếu Score < Score của RANK 1, thì vẫn chưa đạt RANK 1 Thay đổi biểu thức ô E3 => IF(G3<'06. Assessment Summary'!E6,"Not Qualified RANK"&"-"& '06. Assessment Summary'!E5, 5. Thêm mới Table of Content và add các link để trỏ đến sheet tương ứng 6. Xóa các thông tin chi tiết trong sheet "Cover", chỉ giữ lại JOB, tên Job và Code, Version, Effect Date 7. Đổi số thứ tự 03. Models => 02. Models, 02. Career Paths => 03. Career Paths, History of Changes => 09. Record of Change 8. Thay đổi biểu thức ô ô L6 =K6+O6 (actual score + bonus score)
B12: 44985 | C12: Competency-Based.SBA.JobDescription.FSOFT.v1.7.xlsx | E12: Updated | F12: KhangPH | G12: ChiNTT, FHM, FDN (Viên), FHN (Hưng) | J12: Updated comments of BU in Summary_JD Feedback from FSU_2023.xlsx in loop email "Mời review New JD/JA Business Analyst 2022" - Removed out PM career path in sheet "03. Career Paths" - Removed out section of Project Diversity and Complexity and its weight, add this weight to Roles and Responsibilities in sheet "02. Models" - Removed out section of Project Diversity and Complexity and its weight in sheet "05. Job Rankings" and sheet "04. Job Descriptions" - Merged C3:H3 to B3 in sheet "07. Roles & Responsibilities" and copy B3 to D6 in sheet "04. Job Descriptions" - Merged section of Project Diversity and Complexity and its description to Roles and Responsibilities in sheet "04. Job Descriptions" - Add RANK (BANE01-BANE06) after role level in section of The Level of Responsibility in sheet "08. Definitions" - Re-select level for each RANK in section of Roles and Responsibilities in sheet "04. Job Descriptions" and sheet "05. Job Rankings" - Updated formula of cell H9:I15 in sheet "05. Job Rankings" - Renamed text of "Business Analysis Team Size To Lead" section to "Team Size To Lead for BA Leader" in sheet "02. Models" - Updated BANE04 -> BU Level, BANE05-> FSU Level, BANE06-> FSOFT Level in section of Business Analysis Team Size To Lead in sheet "04. Job Descriptions" - Added "Software Development Life Cycle", "Team Work" & "Agile Mindset" into section of Experience & Contributions in sheet "04. Job Descriptions" - Added Team Work, Agile Mindset into section of Communication and Problem Solving, Analytical and Critical Thinking in sheet "04. Job Descriptions" - Selected Limited Expereiene for sections of Business Solution Evaluation (*), Business Strategy Design, Software Design and Technology Stack for BANE02 - Selected IELTS 6.0 for BANE02, IELTS 6.5 BANE03, IELTS 7.0 for BANE04-BANE06 in sheet "04. Job Descriptions" - Updated Solution Evaluation downed 10% to 5%, increased the Planining 5% up 7%, and increased the Elicitation 5% up 8% in sheet "02. Models" - Set mandatory for sections of Planning & Monitoring and Elicitation and removed out mandatory for section of Solution Evaluation in sheet "02. Models" - Selected for mandatory for sections of Planning & Monitoring and Elicitation in sheet "06. Assessment Summary" - Added UI/UX Behavior Design & Principles, CX (Customer Experience / Customer Journey) to section of Business Requirement Analysis (*) in sheet "04. Job Descriptions" - Updated "Industry Experiences" to "Industry Experiences (IT and Non-IT fields) in sheet "02. Models" - Updated "Requirement Workshop => Requirement Workshop / Conduct Elicitation in sheet "04. Job Descriptions" - Replaced "Project Point" in section of "Number of Projects/Phases" by "FSOFTER can provide joined project is project rank of Project Rank A, Project Rank B, Project Rank C in Evidence section" in sheet "04. Job Descriptions"
B13: 44992 | C13: Competency-Based.SBA.JobDescription.FSOFT.v1.8.xlsx | E13: Updated | F13: KhangPH | G13: FDN (Viên) | J13: Updated comments of 10, 14, 15, 34 in Summary_JD Feedback from FSU_2023 (FDN updated).xlsx in loop email "Mời review New JD/JA Business Analyst 2022"
B14: 44994 | C14: Competency-Based.SBA.JobDescription.FSOFT.v1.9.xlsx | E14: Updated | F14: KhangPH | G14: ChiNT, FHN (Viên) | J14: Updated comments of ChiNTT in loop email "Updated BA's comments from BA team" on Mar 09 2023 Corrected "The successful projects in business requirements that you have done at least one of the following tasks: analyze, design, develop, support, migrate, deploy, manage software projects or phases (FSOFTER can provide joined project is project rank of Project Rank A, Project Rank B, Project Rank C in Evidence section)"
B15: 45000 | C15: Competency-Based.SBA.JobDescription.FSOFT.v1.10.xlsx | E15: Updated | F15: KhangPH | G15: ChiNT, FHN (Viên) | J15: Updated comments of ChiNTT in loop email "Updated BA's comments from BA team" on Mar 09 2023 Added drop down list option 0 to items in column E

Sheet Explanation of Skills
B1: Items in old Framework are migrated to | C1: 02. Models 04. Job Descriptions
B2: Business Analysis | C2: ROW 18 | D2: Requirement Elicitation & Collaboration | E2: - Elicitation Preparation - Requirement Workshop - Requirement Transfer & Confirmation - Requirement Management & Communication | F2: Can be assessed on following knowledge items Elicitation Preparation - Study materials (tender, existing system's documentation, etc.) - Understand elicitation scope. - Ensure necessary logistics. - Define meeting agenda & schedule. Requirement Workshop - Guide stakeholders during requirement workshops. - Capture requirement elicited during workshop. Requirement Transfer & Confirmation - Transfer requirement document to customer & confirm requirement's completeness. - Acquire confirmation that requirement captured is accurate. Stakeholders Management - Transfer requirement to other stakeholders. - Communicate with stakeholders to clarify requirements for/with them. Work with stakeholders & manage their expectations of both the product and project deliverables.
C3: ROW 17 | D3: Planning & Monitoring | E3: - Plan Business Analysis Approach - Plan Stakeholders Engagement - Plan Business Analysis Governance - Plan Business Analysis Information Management - Identify Business Analysis Performance Improvement | F3: Can be assessed on following knowledge items Plan Business Analysis Approach - Define methodology: Agile or Waterfall. - Define deliverables. - Define activities & tasks Plan Stakeholders Engagement - Identify relevant stakeholders. - Define required input for each stakeholders. - Define desired output from each stakeholders. - Define collaboration method. Plan Business Analysis Governance - Define criteria for dividing business into components. - Define criteria for consistent decision making during requirement planning phase, including: roles & responsibilities in each requirement processes; process of change proposition, analysis and approval. Plan Business Analysis Information Management - Define method of capturing information. - Define information storage method + process to utilize stored information. Identify Business Analysis Performance Improvement - Measure quality of performance for business analysis activities. - Analyze root cause of negative performance issues. - Define appropriate adjustment to improve performance based on above result.
C4: ROW 19 | D4: Requirement Analysis | E4: - Requirement Specification - Requirement Verification - Requirement Validation - Solution Definition & Assessment | F4: Can be assessed on following knowledge items Requirement Specification Documentation of gathered requirement. Requirement Verification Verify that the requirement matches what the customer wants. Requirement Validation Verify that the requirement will be able to solve business challenges/issues. Solution Definition & Assessment Define solutions for business based on challenges & assess their theoretical pros and cons in order to recommend the most suitable solution.
C5: ROW 20 | D5: Solution Evaluation | E5: - Measure Solution Performance - Analyze Performance Measured - Assess Solution Limitations - Assess Enterprise Limitations - Recommend Actions to Increase Solution's Value | F5: Can be assessed on following knowledge items Measure Solution Performance - Define method(s) to measure "performance" of business after implementation of solution based on suitable metrics. - Collect data based on defined method(s). Analyze Performance Measured - Analyze business value of solution. - Identify value vs performance metrics, including possible risks, trends that may affect the accuracy or meaningfulness of measured results. Assess Solution Limitations - Identify limitations of current solutions. - Define impacts of said limitations. Assess Enterprise Limitations Investigate the following factors and define whether they will be compatible with the solution: - Enterprise Culture - Impacted Stakeholders - Organizational Structure changes - Compatibility with Current Operation Process Recommend Actions to Increase Solution's Value Propose suitable adjustment or revamp of the current solution.
C6: ROW 21 | D6: Requirement Life-Cycle | E6: - Requirement Tracing - Requirement Maintenance - Requirement Prioritization - Requirement Change Management - Requirement Approval | F6: Can be assessed on following knowledge items Requirement Tracing - Divide the requirement into components. - Trace the relationship between these components. Requirement Maintenance - Ensure that the requirement is always updated. - Ensure consistent requirement documentation after updates. Requirement Prioritization Prioritize requirement components based on their: - Benefit - Penalty - Cost - Risk - Dependency - Urgency - Stability - Requisite Compliance to Regulatory or Policies of the Enterprise Requirement Change Management - Validate requirement changes against the project's scope of work. - Impact analysis of requested requirement changes, based on the following: + Change aligned with overall strategy? + Value delivered impacted? + Timeline/resource plan impacted? + Any possible risk, opportunity, constraint? Requirement Approval - Identify Stakeholder Roles - Manage requirement conflicts & gain consensus from all stakeholders - Track & communicate requirement approval
C7: ROW 22 | D7: Strategy Design | E7: - Current State Analysis - Future State Analysis - Risk Analysis - Define Change Strategy | F7: Can be assessed on following knowledge items Current State Analysis - Understand business needs, issues and challenges. - Understand current enterprise & market context Future State Analysis - Define goals & objectives within planned future state. - Identify parts of the enterprise that will be part of the scope of change based on above defined future state. - Define constraints that will limit possible future states, or some of its aspects. Risk Analysis Evaluate likelihood and impact of each possible change. - Probability of risk happening - Constraints, assumptions and dependencies associated with the risk in question - Impact level of risk - Business' level of tolerance for risk in question Recommend solutions and/or adaptation that will "optimize" future state according to the risk analyzed. Define Change Strategy - Gap analysis between current and planned future state. - Define possible options to enable planned future state. - Evaluate & define optimal solution based on above results.
C8: ROW 23 | D8: Business Acumen | E8: Business Acumen | F8: Understanding of fundamental business principles and best practices.
B9: Knowledge | C9: ROW 33 | D9: Industry Knowledge | E9: - Process Understanding - Product Understanding - Market trends & Challenges - Market drivers - Customer Segmentation Understanding | F9: Can be assessed on following knowledge items Process Understanding Understanding on the operation flow (common steps, advanced steps, actor in each step, best practices in operation) in the domain. Product Understanding Understanding on the product/service provided in that domain.: - List of product/service and features of each. - Comparing pros and cons among products/services. - Customer segmentation each product/service aiming to serve. Market trends & Challenges Understanding: - the trends in market (operation and technology) in that domain. - the challenges Market drivers The drivers that impact the growth of the business like: weather, labor, related industries and how they impact the business. Customer Segmentation Understanding Understanding the customer segmentation in the domain: - Features of each segment - Impact from segmentation to operation of the business. - Identify competitors in the same segmentation of the business.
C10: ROW 33 | D10: Organization Knowledge | E10: Organization Knowledge | F10: Understanding of the management, structure and business architecture of the enterprise.
B11: Software Design | C11: ROW 24 | D11: Software Design | E11: - Software Architecture - Database | F11: Can be assessed on following knowledge items Software Architecture - Basic Understanding about main components in a system (server, database, active directory, message broker, front end, API...) - Basic Interaction among components Database - Main types of database (structure vs unstructure, in memory database) - Attributes, data type - Relation among records
C12: ROW 24 | D12: Object Oriented Design | E12: Object Oriented Design | F12: - Object oriented concepts (object/class, inheritance, interface, encapsulation, polymorphism) - Design concepts: Defining object, creating class diagram, identify attributes, use design pattern, application framework - Object oriented design principles (Single-responsiblity, Open-closed, Liskov substitution, Interface segregation, Dependency Inversion)
C13: ROW 25 | D13: Technology Solution for Domain | E13: Technological Solutions | F13: Understanding about a technology solutions that serves in domain: - Standard features - Customized features - Benefit and Limitation
B14: Tools | C14: ROW 25 | D14: Requirement Tools | E14: Requirement Tools | F14: Know how to use tools for requirement work: - Mock up: basalmiq, visio... - Requirement management: jira, confluence, workspace…
C15: ROW 25 | D15: Office Tools | E15: Office Tools | F15: Know how to use basic document processing/data processing tool (microsoft office)
C16: ROW 25 | D16: Communication Tools | E16: Communication Tools | F16: Know how to use different tools to communicate (email, chat tool, online meeting tools…)
B17: Program Management | C17: ROW 35 ROW 36 | D17: Project Management | E17: - Project Time Management - Project Human Resource Management - Project Quality Management - Project risk Management | F17: Can be assessed on following knowledge items 1. Project Time Management Define activities (tasks) Sequence activities, Estimate activity resource Estimate activity schedule Develop schedule & Schedule Optimization (Critical path) Control schedule 2. Project Quality Management - Quality Planning (Quality metrics, Audit & Inspection plan, Training & Preventive actions plan) - Perform Quality Assurance (audit) - Perform Quality Control using Quality Control Techniques (Run charts, Pareto Charts, Flow charts, Scatter diagram, Cause & Effect Diagram, Control Chart, 5Whys, Inspection) 3. Project Risk Management - Develop Risk Management Plan - Identify risks - Analyze risk qualitatively and quantitatively - Develop risk response plan - Risk monitoring and management 4. Project Human Resource Management '- Understand the ability of each BA to assign appropriate projects/tasks. - Understand project request for BA service to determine proper resource plan. - Regularly control BA allocation to optimize resource. - Monitor and control progress and status of BA involvement in each and every project; detect, resolve and followup to close any issue arising. - Evaluate performance, identify strengths as well as improvement points and propose career path for each BA. 5. Project Risk Management '- Understand and utilize process of implementing risk response plans, tracking identified risks, monitoring residual risks, identifying new risks, and evaluating risk process effectiveness throughout the project. - Forecast risk that may occur in range of project that the team is responsible for. - Analyze and perform preventitive actions to reduce risks raised by members. - In the case that risks cannot be closed, raise the risk to leader/mamager and discuss with leader/manger to find out preventitive actions then follow up. (The risk in Methodology is the risk of business solution. The risk mentioned in this sheet derives from project activities, especially in oursourcing project.)
B18: Personal Skills | C18: ROW 32 ROW 33 | D18: Leadership | E18: Leadership | F18: - Work with team to set Project/Team Objectives - Promote teamwork and communication, collaboration between team members - Fostering Loyalty and Trust - Motivating & challenge team members, provision for feelings of accomplishment - Managing Distributed Teams
D19: Communication | E19: - Report Writing - Technical Documentation - Presentation - 2-Way Communication | F19: - Writing project status report, issue report,… - Understand and apply techniques & best practices in writing technical document such as user manual, SRS, Design documents, test cases… - Understand and utilize Presentation techniques - Utilization and Practice of Communication Techniques, Effective Listening & effective speaking in Information Transfering, dialog and interview
D20: Time Management | E20: Personal Time Management | F20: Skill for effectively manage your time, do more in less time, avoid stress, by utilize following techniques - Action plan, Prioritise tasks, organizing, - Delegate, Share tasks or problems with others, Avoid distractions and interuptions to your work, avoid procastination, Take a regular break, Create habits
D21: Problem solving | E21: Problem solving | F21: The process & technique of working through details of a problem to reach a solution
D22: Counselling | E22: Counselling | F22: Understand the process & techniques, quality required for effectively assisting and guiding others to explore difficulties by helping the client to see things more clearly, possibly from a different view-point,
D23: Teamwork | E23: Teamwork | F23: Working collaboratively with a group of people in order to achieve a goal by trying to cooperate, using their individual skills and providing constructive feedback.
B24: Foreign languages | C24: ROW 27 | D24: Foreign Language | E24: - Reading - Writing - Listening - Speaking | F24: - Reading email, documents, newspaper, books in foreign language - Writing email, documents, specification in a foreign language - Listening to conversations, speech in a foreign language - Speaking and express the ideas in foreign languages
B27: Elementary Complexity Criteria
B29: Plan and estimation for requirement elicitation and documentation. & Monitoring according to plan and define risk during requirement phase in the project.
B30: Gather & clarify requirements from the detailed requirement stakeholders provide using common techniques such as: + Document analysis, + Existing system analysis. + Research
B31: Prepare, conduct requirement elicitation workshop & confirm elicitation result with stakeholders.
B32: Document requirement and design using common technique such as diagram, user story, use case, mock-up…
B33: Communicate requirement, including one of the following tasks: + Walkthrough and confirm captured requirement and business solution with stakeholders to ensure shared understanding on business analysis information. + Transfer requirement to implementation team.
B34: Trace and maintain the relationship among requirement components, solution components and requirements, including all the following tasks: + Trace the relationship between user requirement and system requirement to make sure all requirements will be satisfied. + Trace the relationship among requirements themselves so we can conduct impact analysis in case of change.
B35: Support UAT, including all following tasks: + Analyze bugs in requirement perspective (whether it is a bug or a change requirement...) + Support team to communicate with customer to troubleshoot on bugs
B36: Assess Requirement Change, including all following tasks: + Verify and analyze impact, value and risk of change requirement. + Discuss with stakeholders on the information to reach out for best conclusion. + Update changes in other requirement/design impacted from change requirement.
B37: (If the description does not mention how many items that need to be satisfied then all is needed)
B39: General Advanced Complexity Criteria
B41: Plan BA approach & Information management, including at least 3 of the following tasks: + Define appropriate working model + Define deliverables + Break down general task and working process + Define detail level of information, how information is organized and maintained.
... B51: Consult or define the approach and process for requirement phase of project with high complexity (requirement phase size >= 10 MM)
B52: Strategy analysis for business: analyze the current state, define desired future state and plan for actions to take. | E52: Plan and estimation for requirement documentation.
B53: Build domain capability for BA team at BU level or above. | E53: Plan and estimation for requirement documentation.
B55: Management Complexity Criteria
B56: Perform team management activities, for example: BA evaluation and project resource allocation | E56: Transfer requirement to development team (include both transferring and clarifying requirement during development phase).
B57: Measure performance and define improvement for BA team and business analysis activities. (via CAR meeting, measure defect rate, organize sharing, create case study…). | E57: Transfer requirement to development team (include both transferring and clarifying requirement during development phase).
B58: Define and maintain BA templates and processes for BA activities in the organization. | E58: Transfer requirement to development team (include both transferring and clarifying requirement during development phase).
B59: Perform BA team development activities: recruitment, training, career guidance…
B61: Requirement Complexity
B63: Complexity | D63: Description
B64: Simple | D64: Requirement of a system with: - No workflow (Information Repository system) - OR simple workflow (3-step flow or similar step like approval workflow with multiple level, collect feedback flow with multiple reviewers…)
B65: Medium | D65: Requirement of a system with: - Medium workflow (more than 3 steps which are not similar) - OR contain integration with at least 3 systems.
B67: Basic Competency
B69: Have knowledge in documenting detailed requirement in one of following methods: - Use Case (Document all requirement and design in a document, includes high level requirement and details for function and screen. When there is change, update the latest requirement in the document itself) - User Story (Break requirement into User Story (title-description-acceptance criteria) in backlog and drag to each sprint to implement. When there is change, create a new User Story instead updating on the old one)
B70: Have knowlegde in gathering requirement in one of following types: - Collaborative: meeting with stakeholders to gather requirements. - Reverse Engineering: study old system (reading code, running program…) to capture functional requirement. - Data Mapping in BI project.
B71: Have knowledge in requirement process and life cycle for one of the following working models: - Waterfall - Agile
B73: Advanced Competency
B75: Have knowledge in defining requirement by one of following methods: - Research: involves systematically discovering and studying information from materials or sources that are not directly known by stakeholders involved in the changes. Stakeholders might still participate in research. Research can include analysis of historical data to identify trends or past results. (Like advising features for stakeholders, perform market research to define requirement for a product...) - Experiments: involves identifying information that could not be known without some sort of controlled test. Some information cannot be drawn from people or documents. Experiments can include observation studies, proof of concept, prototypes.
B76: Have knowledge in one domain with following information: - Understanding on process, product. - Market drivers - Market trends and challenges - Technology Solutions
B77: Have knowledge in one platform/technology such as: SharePoint (for collaboration work), Odoo (for logistics), IoT, etc.
B79: Level of competency
B80: 4_Master and contribute to the community (Company, FSU)
B81: 3_Master and instruct junior work
B82: 2_Can perform independently or with very little support
... B96: □ Publication of a book
