Workbook

Sheet PHƯƠNG
A1: 2024
A2: SUM của Số tiền | B2: Tháng
A3: Báo cáo dòng tiền | B3: =$A$1&"."&"01" -> 2024.01 | C3: =$A$1&"."&"02" -> 2024.02 | D3: =$A$1&"."&"03" -> 2024.03 | F3: =$A$1&"."&"04" -> 2024.04 | G3: =$A$1&"."&"05" -> 2024.05 | H3: =$A$1&"."&"06" -> 2024.06 | I3: =$A$1&"."&"07" -> 2024.07 | J3: =$A$1&"."&"08" -> 2024.08 | K3: =$A$1&"."&"09" -> 2024.09 | L3: =$A$1&"."&"10" -> 2024.10 | M3: =$A$1&"."&"11" -> 2024.11 | N3: =$A$1&"."&"12" -> 2024.12 | O3: Tổng
A4: Biến phí | B4: =vlookup(B3,#REF!,2,0) -> #REF! | C4: =vlookup(C3,#REF!,2,0) -> #REF! | D4: =vlookup(D3,#REF!,2,0) -> #REF! | F4: =vlookup(F3,#REF!,2,0) -> #REF! | G4: =vlookup(G3,#REF!,2,0) -> #REF! | H4: =vlookup(H3,#REF!,2,0) -> #REF! | I4: =vlookup(I3,#REF!,2,0) -> #REF! | J4: =vlookup(J3,#REF!,2,0) -> #REF! | K4: =vlookup(K3,#REF!,2,0) -> #REF! | L4: =vlookup(L3,#REF!,2,0) -> #REF! | M4: =vlookup(M3,#REF!,2,0) -> #REF! | N4: =vlookup(N3,#REF!,2,0) -> #REF! | O4: 950042901
A5: Chi phí khác | B5: =vlookup(B3,#REF!,3,0) -> #REF! | C5: =vlookup(C3,#REF!,3,0) -> #REF! | D5: =vlookup(D3,#REF!,3,0) -> #REF! | F5: =vlookup(F3,#REF!,3,0) -> #REF! | G5: =vlookup(G3,#REF!,3,0) -> #REF! | H5: =vlookup(H3,#REF!,3,0) -> #REF! | I5: =vlookup(I3,#REF!,3,0) -> #REF! | J5: =vlookup(J3,#REF!,3,0) -> #REF! | K5: =vlookup(K3,#REF!,3,0) -> #REF! | L5: =vlookup(L3,#REF!,3,0) -> #REF! | M5: =vlookup(M3,#REF!,3,0) -> #REF! | N5: =vlookup(N3,#REF!,3,0) -> #REF! | O5: 119364240
A6: Định phí | B6: =vlookup(B3,#REF!,4,0) -> #REF! | C6: =vlookup(C3,#REF!,4,0) -> #REF! | D6: =vlookup(D3,#REF!,4,0) -> #REF! | F6: =vlookup(F3,#REF!,4,0) -> #REF! | G6: =vlookup(G3,#REF!,4,0) -> #REF! | H6: =vlookup(H3,#REF!,4,0) -> #REF! | I6: =vlookup(I3,#REF!,4,0) -> #REF! | J6: =vlookup(J3,#REF!,4,0) -> #REF! | K6: =vlookup(K3,#REF!,4,0) -> #REF! | L6: =vlookup(L3,#REF!,4,0) -> #REF! | M6: =vlookup(M3,#REF!,4,0) -> #REF! | N6: =vlookup(N3,#REF!,4,0) -> #REF! | O6: 1223293543
A7: Giá vốn | B7: =vlookup(B3,#REF!,5,0) -> #REF! | C7: =vlookup(C3,#REF!,5,0) -> #REF! | D7: =vlookup(D3,#REF!,5,0) -> #REF! | F7: =vlookup(F3,#REF!,5,0) -> #REF! | G7: =vlookup(G3,#REF!,5,0) -> #REF! | H7: =vlookup(H3,#REF!,5,0) -> #REF! | I7: =vlookup(I3,#REF!,5,0) -> #REF! | J7: =vlookup(J3,#REF!,5,0) -> #REF! | K7: =vlookup(K3,#REF!,5,0) -> #REF! | L7: =vlookup(L3,#REF!,5,0) -> #REF! | M7: =vlookup(M3,#REF!,5,0) -> #REF! | N7: =vlookup(N3,#REF!,5,0) -> #REF! | O7: 1855790333
A8: Hành chính | B8: =vlookup(B3,#REF!,6,0) -> #REF! | C8: =vlookup(C3,#REF!,6,0) -> #REF! | D8: =vlookup(D3,#REF!,6,0) -> #REF! | F8: =vlookup(F3,#REF!,6,0) -> #REF! | G8: =vlookup(G3,#REF!,6,0) -> #REF! | H8: =vlookup(H3,#REF!,6,0) -> #REF! | I8: =vlookup(I3,#REF!,6,0) -> #REF! | J8: =vlookup(J3,#REF!,6,0) -> #REF! | K8: =vlookup(K3,#REF!,6,0) -> #REF! | L8: =vlookup(L3,#REF!,6,0) -> #REF! | M8: =vlookup(M3,#REF!,6,0) -> #REF! | N8: =vlookup(N3,#REF!,6,0) -> #REF! | O8: 252733853
A9: Marketing | B9: =vlookup(B3,#REF!,7,0) -> #REF! | C9: =vlookup(C3,#REF!,7,0) -> #REF! | D9: =vlookup(D3,#REF!,7,0) -> #REF! | F9: =vlookup(F3,#REF!,7,0) -> #REF! | G9: =vlookup(G3,#REF!,7,0) -> #REF! | H9: =vlookup(H3,#REF!,7,0) -> #REF! | I9: =vlookup(I3,#REF!,7,0) -> #REF! | J9: =vlookup(J3,#REF!,7,0) -> #REF! | K9: =vlookup(K3,#REF!,7,0) -> #REF! | L9: =vlookup(L3,#REF!,7,0) -> #REF! | M9: =vlookup(M3,#REF!,7,0) -> #REF! | N9: =vlookup(N3,#REF!,7,0) -> #REF! | O9: 1855109996
A10: Tài sản | B10: =vlookup(B3,#REF!,8,0) -> #REF! | C10: =vlookup(C3,#REF!,8,0) -> #REF! | D10: =vlookup(D3,#REF!,8,0) -> #REF! | F10: =vlookup(F3,#REF!,8,0) -> #REF! | G10: =vlookup(G3,#REF!,8,0) -> #REF! | H10: =vlookup(H3,#REF!,8,0) -> #REF! | I10: =vlookup(I3,#REF!,8,0) -> #REF! | J10: =vlookup(J3,#REF!,8,0) -> #REF! | K10: =vlookup(K3,#REF!,8,0) -> #REF! | L10: =vlookup(L3,#REF!,8,0) -> #REF! | M10: =vlookup(M3,#REF!,8,0) -> #REF! | N10: =vlookup(N3,#REF!,8,0) -> #REF! | O10: 141458334
A11: Tổng cộng | B11: 2826933299 | C11: 1704981149 | D11: 1865878752 | F11: 0 | G11: 0 | H11: 0 | I11: 0 | J11: 0 | K11: 0 | L11: 0 | M11: 0 | N11: 0 | O11: 6397793200
A13: Định phí | B13: =$A$1&"."&"01" -> 2024.01 | C13: =$A$1&"."&"02" -> 2024.02 | D13: =$A$1&"."&"03" -> 2024.03 | F13: =$A$1&"."&"04" -> 2024.04 | G13: =$A$1&"."&"05" -> 2024.05 | H13: =$A$1&"."&"06" -> 2024.06 | I13: =$A$1&"."&"07" -> 2024.07 | J13: =$A$1&"."&"08" -> 2024.08 | K13: =$A$1&"."&"09" -> 2024.09 | L13: =$A$1&"."&"10" -> 2024.10 | M13: =$A$1&"."&"11" -> 2024.11 | N13: =$A$1&"."&"12" -> 2024.12 | O13: Tổng
A14: [Định phí]. Lương cứng | B14: =vlookup(B13,'Report_Chi phi'!$A$3:$P$51,4,0) -> #N/A | C14: =vlookup(C13,'Report_Chi phi'!$A$3:$P$51,4,0) -> #N/A | D14: =vlookup(D13,'Report_Chi phi'!$A$3:$P$51,4,0) -> #N/A | F14: =vlookup(F13,'Report_Chi phi'!$A$3:$P$51,4,0) -> #N/A | G14: =vlookup(G13,'Report_Chi phi'!$A$3:$P$51,4,0) -> #N/A | H14: =vlookup(H13,'Report_Chi phi'!$A$3:$P$51,4,0) -> #N/A | I14: =vlookup(I13,'Report_Chi phi'!$A$3:$P$51,4,0) -> #N/A | J14: =vlookup(J13,'Report_Chi phi'!$A$3:$P$51,4,0) -> #N/A | K14: =vlookup(K13,'Report_Chi phi'!$A$3:$P$51,4,0) -> #N/A | L14: =vlookup(L13,'Report_Chi phi'!$A$3:$P$51,4,0) -> #N/A | M14: =vlookup(M13,'Report_Chi phi'!$A$3:$P$51,4,0) -> #N/A | N14: =vlookup(N13,'Report_Chi phi'!$A$3:$P$51,4,0) -> #N/A | O14: =sum(B14:N14) -> #N/A
A15: [Định phí]. Mặt bằng | B15: =vlookup(B13,'Report_Chi phi'!$A$3:$P$51,5,0) -> #N/A | C15: =vlookup(C13,'Report_Chi phi'!$A$3:$P$51,5,0) -> #N/A | D15: =vlookup(D13,'Report_Chi phi'!$A$3:$P$51,5,0) -> #N/A | F15: =vlookup(F13,'Report_Chi phi'!$A$3:$P$51,5,0) -> #N/A | G15: =vlookup(G13,'Report_Chi phi'!$A$3:$P$51,5,0) -> #N/A | H15: =vlookup(H13,'Report_Chi phi'!$A$3:$P$51,5,0) -> #N/A | I15: =vlookup(I13,'Report_Chi phi'!$A$3:$P$51,5,0) -> #N/A | J15: =vlookup(J13,'Report_Chi phi'!$A$3:$P$51,5,0) -> #N/A | K15: =vlookup(K13,'Report_Chi phi'!$A$3:$P$51,5,0) -> #N/A | L15: =vlookup(L13,'Report_Chi phi'!$A$3:$P$51,5,0) -> #N/A | M15: =vlookup(M13,'Report_Chi phi'!$A$3:$P$51,5,0) -> #N/A | N15: =vlookup(N13,'Report_Chi phi'!$A$3:$P$51,5,0) -> #N/A | O15: =sum(B15:N15) -> #N/A
A16: [Định phí]. Thuê bằng | B16: =vlookup(B13,'Report_Chi phi'!$A$3:$P$51,6,0) -> #N/A | C16: =vlookup(C13,'Report_Chi phi'!$A$3:$P$51,6,0) -> #N/A | D16: =vlookup(D13,'Report_Chi phi'!$A$3:$P$51,6,0) -> #N/A | F16: =vlookup(F13,'Report_Chi phi'!$A$3:$P$51,6,0) -> #N/A | G16: =vlookup(G13,'Report_Chi phi'!$A$3:$P$51,6,0) -> #N/A | H16: =vlookup(H13,'Report_Chi phi'!$A$3:$P$51,6,0) -> #N/A | I16: =vlookup(I13,'Report_Chi phi'!$A$3:$P$51,6,0) -> #N/A | J16: =vlookup(J13,'Report_Chi phi'!$A$3:$P$51,6,0) -> #N/A | K16: =vlookup(K13,'Report_Chi phi'!$A$3:$P$51,6,0) -> #N/A | L16: =vlookup(L13,'Report_Chi phi'!$A$3:$P$51,6,0) -> #N/A | M16: =vlookup(M13,'Report_Chi phi'!$A$3:$P$51,6,0) -> #N/A | N16: =vlookup(N13,'Report_Chi phi'!$A$3:$P$51,6,0) -> #N/A | O16: =sum(B16:N16) -> #N/A
A17: [Định phí]. Bảo hiểm | B17: =vlookup(B13,'Report_Chi phi'!$A$3:$P$51,3,0) -> #N/A | C17: =vlookup(C13,'Report_Chi phi'!$A$3:$P$51,3,0) -> #N/A | D17: =vlookup(D13,'Report_Chi phi'!$A$3:$P$51,3,0) -> #N/A | F17: =vlookup(F13,'Report_Chi phi'!$A$3:$P$51,3,0) -> #N/A | G17: =vlookup(G13,'Report_Chi phi'!$A$3:$P$51,3,0) -> #N/A | H17: =vlookup(H13,'Report_Chi phi'!$A$3:$P$51,3,0) -> #N/A | I17: =vlookup(I13,'Report_Chi phi'!$A$3:$P$51,3,0) -> #N/A | J17: =vlookup(J13,'Report_Chi phi'!$A$3:$P$51,3,0) -> #N/A | K17: =vlookup(K13,'Report_Chi phi'!$A$3:$P$51,3,0) -> #N/A | L17: =vlookup(L13,'Report_Chi phi'!$A$3:$P$51,3,0) -> #N/A | M17: =vlookup(M13,'Report_Chi phi'!$A$3:$P$51,3,0) -> #N/A | N17: =vlookup(N13,'Report_Chi phi'!$A$3:$P$51,3,0) -> #N/A | O17: =sum(B17:N17) -> #N/A
O18: =sum(B18:N18) -> 0
A19: Biến phí | B19: =$A$1&"."&"01" -> 2024.01 | C19: =$A$1&"."&"02" -> 2024.02 | D19: =$A$1&"."&"03" -> 2024.03 | F19: =$A$1&"."&"04" -> 2024.04 | G19: =$A$1&"."&"05" -> 2024.05 | H19: =$A$1&"."&"06" -> 2024.06 | I19: =$A$1&"."&"07" -> 2024.07 | J19: =$A$1&"."&"08" -> 2024.08 | K19: =$A$1&"."&"09" -> 2024.09 | L19: =$A$1&"."&"10" -> 2024.10 | M19: =$A$1&"."&"11" -> 2024.11 | N19: =$A$1&"."&"12" -> 2024.12 | O19: Tổng
A20: [Bán hàng]. Marketing | B20: =vlookup(B19,'Report_Chi phi'!$A$3:$P$51,2,0) -> #N/A | C20: =vlookup(C19,'Report_Chi phi'!$A$3:$P$51,2,0) -> #N/A | D20: =vlookup(D19,'Report_Chi phi'!$A$3:$P$51,2,0) -> #N/A | F20: =vlookup(F19,'Report_Chi phi'!$A$3:$P$51,2,0) -> #N/A | G20: =vlookup(G19,'Report_Chi phi'!$A$3:$P$51,2,0) -> #N/A | H20: =vlookup(H19,'Report_Chi phi'!$A$3:$P$51,2,0) -> #N/A | I20: =vlookup(I19,'Report_Chi phi'!$A$3:$P$51,2,0) -> #N/A | J20: =vlookup(J19,'Report_Chi phi'!$A$3:$P$51,2,0) -> #N/A | K20: =vlookup(K19,'Report_Chi phi'!$A$3:$P$51,2,0) -> #N/A | L20: =vlookup(L19,'Report_Chi phi'!$A$3:$P$51,2,0) -> #N/A | M20: =vlookup(M19,'Report_Chi phi'!$A$3:$P$51,2,0) -> #N/A | N20: =vlookup(N19,'Report_Chi phi'!$A$3:$P$51,2,0) -> #N/A | O20: =sum(B20:N20) -> #N/A
A21: KPI | B21: =vlookup(B19,'Report_Chi phi'!$A$3:$P$51,15,0) -> #N/A | C21: =vlookup(C19,'Report_Chi phi'!$A$3:$P$51,15,0) -> #N/A | D21: =vlookup(D19,'Report_Chi phi'!$A$3:$P$51,15,0) -> #N/A | F21: =vlookup(F19,'Report_Chi phi'!$A$3:$P$51,15,0) -> #N/A | G21: =vlookup(G19,'Report_Chi phi'!$A$3:$P$51,15,0) -> #N/A | H21: =vlookup(H19,'Report_Chi phi'!$A$3:$P$51,15,0) -> #N/A | I21: =vlookup(I19,'Report_Chi phi'!$A$3:$P$51,15,0) -> #N/A | J21: =vlookup(J19,'Report_Chi phi'!$A$3:$P$51,15,0) -> #N/A | K21: =vlookup(K19,'Report_Chi phi'!$A$3:$P$51,15,0) -> #N/A | L21: =vlookup(L19,'Report_Chi phi'!$A$3:$P$51,15,0) -> #N/A | M21: =vlookup(M19,'Report_Chi phi'!$A$3:$P$51,15,0) -> #N/A | N21: =vlookup(N19,'Report_Chi phi'!$A$3:$P$51,15,0) -> #N/A | O21: =sum(B21:N21) -> #N/A
A22: Giá vốn | B22: =$A$1&"."&"01" -> 2024.01 | C22: =$A$1&"."&"02" -> 2024.02 | D22: =$A$1&"."&"03" -> 2024.03 | F22: =$A$1&"."&"04" -> 2024.04 | G22: =$A$1&"."&"05" -> 2024.05 | H22: =$A$1&"."&"06" -> 2024.06 | I22: =$A$1&"."&"07" -> 2024.07 | J22: =$A$1&"."&"08" -> 2024.08 | K22: =$A$1&"."&"09" -> 2024.09 | L22: =$A$1&"."&"10" -> 2024.10 | M22: =$A$1&"."&"11" -> 2024.11 | N22: =$A$1&"."&"12" -> 2024.12 | O22: Tổng
A23: [Giá vốn]. Vật liệu | B23: =vlookup(B22,'Report_Chi phi'!$A$3:$P$51,8,0) -> #N/A | C23: =vlookup(C22,'Report_Chi phi'!$A$3:$P$51,8,0) -> #N/A | D23: =vlookup(D22,'Report_Chi phi'!$A$3:$P$51,8,0) -> #N/A | F23: =vlookup(F22,'Report_Chi phi'!$A$3:$P$51,8,0) -> #N/A | G23: =vlookup(G22,'Report_Chi phi'!$A$3:$P$51,8,0) -> #N/A | H23: =vlookup(H22,'Report_Chi phi'!$A$3:$P$51,8,0) -> #N/A | I23: =vlookup(I22,'Report_Chi phi'!$A$3:$P$51,8,0) -> #N/A | J23: =vlookup(J22,'Report_Chi phi'!$A$3:$P$51,8,0) -> #N/A | K23: =vlookup(K22,'Report_Chi phi'!$A$3:$P$51,8,0) -> #N/A | L23: =vlookup(L22,'Report_Chi phi'!$A$3:$P$51,8,0) -> #N/A | M23: =vlookup(M22,'Report_Chi phi'!$A$3:$P$51,8,0) -> #N/A | N23: =vlookup(N22,'Report_Chi phi'!$A$3:$P$51,8,0) -> #N/A | O23: =sum(B23:N23) -> #N/A
A24: [Giá vốn]. Labo | B24: =vlookup(B22,'Report_Chi phi'!$A$3:$P$51,7,0) -> #N/A | C24: =vlookup(C22,'Report_Chi phi'!$A$3:$P$51,7,0) -> #N/A | D24: =vlookup(D22,'Report_Chi phi'!$A$3:$P$51,7,0) -> #N/A | F24: =vlookup(F22,'Report_Chi phi'!$A$3:$P$51,7,0) -> #N/A | G24: =vlookup(G22,'Report_Chi phi'!$A$3:$P$51,7,0) -> #N/A | H24: =vlookup(H22,'Report_Chi phi'!$A$3:$P$51,7,0) -> #N/A | I24: =vlookup(I22,'Report_Chi phi'!$A$3:$P$51,7,0) -> #N/A | J24: =vlookup(J22,'Report_Chi phi'!$A$3:$P$51,7,0) -> #N/A | K24: =vlookup(K22,'Report_Chi phi'!$A$3:$P$51,7,0) -> #N/A | L24: =vlookup(L22,'Report_Chi phi'!$A$3:$P$51,7,0) -> #N/A | M24: =vlookup(M22,'Report_Chi phi'!$A$3:$P$51,7,0) -> #N/A | N24: =vlookup(N22,'Report_Chi phi'!$A$3:$P$51,7,0) -> #N/A | O24: =sum(B24:N24) -> #N/A
B25: =sum(B23:B24) -> #N/A | C25: =sum(C23:C24) -> #N/A | D25: =sum(D23:D24) -> #N/A | F25: =sum(F23:F24) -> #N/A | G25: =sum(G23:G24) -> #N/A | H25: =sum(H23:H24) -> #N/A | I25: =sum(I23:I24) -> #N/A | J25: =sum(J23:J24) -> #N/A | K25: =sum(K23:K24) -> #N/A | L25: =sum(L23:L24) -> #N/A | M25: =sum(M23:M24) -> #N/A | N25: =sum(N23:N24) -> #N/A
A26: Hành chính | B26: =$A$1&"."&"01" -> 2024.01 | C26: =$A$1&"."&"02" -> 2024.02 | D26: =$A$1&"."&"03" -> 2024.03 | F26: =$A$1&"."&"04" -> 2024.04 | G26: =$A$1&"."&"05" -> 2024.05 | H26: =$A$1&"."&"06" -> 2024.06 | I26: =$A$1&"."&"07" -> 2024.07 | J26: =$A$1&"."&"08" -> 2024.08 | K26: =$A$1&"."&"09" -> 2024.09 | L26: =$A$1&"."&"10" -> 2024.10 | M26: =$A$1&"."&"11" -> 2024.11 | N26: =$A$1&"."&"12" -> 2024.12 | O26: Tổng
A27: [Hành chính].Điện | B27: =vlookup(B26,'Report_Chi phi'!$A$3:$P$51,10,0) -> #N/A | C27: =vlookup(C26,'Report_Chi phi'!$A$3:$P$51,10,0) -> #N/A | D27: =vlookup(D26,'Report_Chi phi'!$A$3:$P$51,10,0) -> #N/A | F27: =vlookup(F26,'Report_Chi phi'!$A$3:$P$51,10,0) -> #N/A | G27: =vlookup(G26,'Report_Chi phi'!$A$3:$P$51,10,0) -> #N/A | H27: =vlookup(H26,'Report_Chi phi'!$A$3:$P$51,10,0) -> #N/A | I27: =vlookup(I26,'Report_Chi phi'!$A$3:$P$51,10,0) -> #N/A | J27: =vlookup(J26,'Report_Chi phi'!$A$3:$P$51,10,0) -> #N/A | K27: =vlookup(K26,'Report_Chi phi'!$A$3:$P$51,10,0) -> #N/A | L27: =vlookup(L26,'Report_Chi phi'!$A$3:$P$51,10,0) -> #N/A | M27: =vlookup(M26,'Report_Chi phi'!$A$3:$P$51,10,0) -> #N/A | N27: =vlookup(N26,'Report_Chi phi'!$A$3:$P$51,10,0) -> #N/A | O27: =sum(B27:N27) -> #N/A
A28: [Hành chính].Nước | B28: =vlookup(B26,'Report_Chi phi'!$A$3:$P$51,11,0) -> #N/A | C28: =vlookup(C26,'Report_Chi phi'!$A$3:$P$51,11,0) -> #N/A | D28: =vlookup(D26,'Report_Chi phi'!$A$3:$P$51,11,0) -> #N/A | F28: =vlookup(F26,'Report_Chi phi'!$A$3:$P$51,11,0) -> #N/A | G28: =vlookup(G26,'Report_Chi phi'!$A$3:$P$51,11,0) -> #N/A | H28: =vlookup(H26,'Report_Chi phi'!$A$3:$P$51,11,0) -> #N/A | I28: =vlookup(I26,'Report_Chi phi'!$A$3:$P$51,11,0) -> #N/A | J28: =vlookup(J26,'Report_Chi phi'!$A$3:$P$51,11,0) -> #N/A | K28: =vlookup(K26,'Report_Chi phi'!$A$3:$P$51,11,0) -> #N/A | L28: =vlookup(L26,'Report_Chi phi'!$A$3:$P$51,11,0) -> #N/A | M28: =vlookup(M26,'Report_Chi phi'!$A$3:$P$51,11,0) -> #N/A | N28: =vlookup(N26,'Report_Chi phi'!$A$3:$P$51,11,0) -> #N/A | O28: =sum(B28:N28) -> #N/A
A29: [Hành chính].Chung | B29: =vlookup(B26,'Report_Chi phi'!$A$3:$P$51,9,0) -> #N/A | C29: =vlookup(C26,'Report_Chi phi'!$A$3:$P$51,9,0) -> #N/A | D29: =vlookup(D26,'Report_Chi phi'!$A$3:$P$51,9,0) -> #N/A | F29: =vlookup(F26,'Report_Chi phi'!$A$3:$P$51,9,0) -> #N/A | G29: =vlookup(G26,'Report_Chi phi'!$A$3:$P$51,9,0) -> #N/A | H29: =vlookup(H26,'Report_Chi phi'!$A$3:$P$51,9,0) -> #N/A | I29: =vlookup(I26,'Report_Chi phi'!$A$3:$P$51,9,0) -> #N/A | J29: =vlookup(J26,'Report_Chi phi'!$A$3:$P$51,9,0) -> #N/A | K29: =vlookup(K26,'Report_Chi phi'!$A$3:$P$51,9,0) -> #N/A | L29: =vlookup(L26,'Report_Chi phi'!$A$3:$P$51,9,0) -> #N/A | M29: =vlookup(M26,'Report_Chi phi'!$A$3:$P$51,9,0) -> #N/A | N29: =vlookup(N26,'Report_Chi phi'!$A$3:$P$51,9,0) -> #N/A | O29: =sum(B29:N29) -> #N/A
B30: =sum(B27:B29) -> #N/A | C30: =sum(C27:C29) -> #N/A | D30: =sum(D27:D29) -> #N/A | F30: =sum(F27:F29) -> #N/A | G30: =sum(G27:G29) -> #N/A | H30: =sum(H27:H29) -> #N/A | I30: =sum(I27:I29) -> #N/A | J30: =sum(J27:J29) -> #N/A | K30: =sum(K27:K29) -> #N/A | L30: =sum(L27:L29) -> #N/A | M30: =sum(M27:M29) -> #N/A | N30: =sum(N27:N29) -> #N/A
A31: Cấu hình tính giá vốn | B31: =$A$1&"."&"01" -> 2024.01 | C31: =$A$1&"."&"02" -> 2024.02 | D31: =$A$1&"."&"03" -> 2024.03 | F31: =$A$1&"."&"04" -> 2024.04 | G31: =$A$1&"."&"05" -> 2024.05 | H31: =$A$1&"."&"06" -> 2024.06 | I31: =$A$1&"."&"07" -> 2024.07 | J31: =$A$1&"."&"08" -> 2024.08 | K31: =$A$1&"."&"09" -> 2024.09 | L31: =$A$1&"."&"10" -> 2024.10 | M31: =$A$1&"."&"11" -> 2024.11 | N31: =$A$1&"."&"12" -> 2024.12 | O31: Tổng
A32: Giá vốn 1 răng | B32: 1000000 | C32: 1000000 | D32: 1000000 | F32: 2000000 | G32: 1000000 | H32: 1000000 | I32: 1000000 | J32: 1000000 | K32: 1000000 | L32: 1000000 | M32: 1000000 | N32: 1000000
A33: Đơn giá răng sứ | B33: 3000000 | C33: 2500000 | D33: 2500000 | F33: 2500000 | G33: 2500000 | H33: 2200000 | I33: 2500000 | J33: 2500000 | K33: 2500000 | L33: 2500000 | M33: 2500000 | N33: 2500000
A34: Biến phí | B34: =sum(B20:B21) -> #N/A | C34: =sum(C20:C21) -> #N/A | D34: =sum(D20:D21) -> #N/A | F34: =sum(F20:F21) -> #N/A | G34: =sum(G20:G21) -> #N/A | H34: =sum(H20:H21) -> #N/A | I34: =sum(I20:I21) -> #N/A | J34: =sum(J20:J21) -> #N/A | K34: =sum(K20:K21) -> #N/A | L34: =sum(L20:L21) -> #N/A | M34: =sum(M20:M21) -> #N/A | N34: =sum(N20:N21) -> #N/A
A35: Số răng sứ | B35: =round(B7/B32,1) -> #REF! | C35: =round(C7/C32,1) -> #REF! | D35: =round(D7/D32,1) -> #REF! | F35: =round(F7/F32,1) -> #REF! | G35: =round(G7/G32,1) -> #REF! | H35: =round(H7/H32,1) -> #REF! | I35: =round(I7/I32,1) -> #REF! | J35: =round(J7/J32,1) -> #REF! | K35: =round(K7/K32,1) -> #REF! | L35: =round(L7/L32,1) -> #REF! | M35: =round(M7/M32,1) -> #REF! | N35: =round(N7/N32,1) -> #REF!
A36: Doanh thu tính theo răng sứ | B36: =B33*B35 -> #REF! | C36: =C33*C35 -> #REF! | D36: =D33*D35 -> #REF! | F36: =F33*F35 -> #REF! | G36: =G33*G35 -> #REF! | H36: =H33*H35 -> #REF! | I36: =I33*I35 -> #REF! | J36: =J33*J35 -> #REF! | K36: =K33*K35 -> #REF! | L36: =L33*L35 -> #REF! | M36: =M33*M35 -> #REF! | N36: =N33*N35 -> #REF!
A37: Doanh thu thực tế | B37: =vlookup(B31,'Report_Doanh thu'!$A$2:$H$50,7,0) -> 3517022000 | C37: =vlookup(C31,'Report_Doanh thu'!$A$2:$H$50,7,0) -> 1700101000 | D37: =vlookup(D31,'Report_Doanh thu'!$A$2:$H$50,7,0) -> 2020806000 | F37: =vlookup(F31,'Report_Doanh thu'!$A$2:$H$50,7,0) -> 1711707000 | G37: =vlookup(G31,'Report_Doanh thu'!$A$2:$H$50,7,0) -> 1562947800 | H37: =vlookup(H31,'Report_Doanh thu'!$A$2:$H$50,7,0) -> 2122290000 | I37: =vlookup(I31,'Report_Doanh thu'!$A$2:$H$50,7,0) -> 3300551002 | J37: =vlookup(J31,'Report_Doanh thu'!$A$2:$H$50,7,0) -> 2090704801 | K37: =vlookup(K31,'Report_Doanh thu'!$A$2:$H$50,7,0) -> 2082261500 | L37: =vlookup(L31,'Report_Doanh thu'!$A$2:$H$50,7,0) -> 0 | M37: =vlookup(M31,'Report_Doanh thu'!$A$2:$H$50,7,0) -> 0 | N37: =vlookup(N31,'Report_Doanh thu'!$A$2:$H$50,7,0) -> 0
A38: KPI_BS(30%) | B38: =B36*0.3 -> #REF! | C38: =C36*0.3 -> #REF! | D38: =D36*0.3 -> #REF! | F38: =F36*0.3 -> #REF! | G38: =G36*0.3 -> #REF! | H38: =H36*0.3 -> #REF! | I38: =I36*0.3 -> #REF! | J38: =J36*0.3 -> #REF! | K38: =K36*0.3 -> #REF! | L38: =L36*0.3 -> #REF! | M38: =M36*0.3 -> #REF! | N38: =N36*0.3 -> #REF!
A39: Giá vốn (21%) | B39: 803070000 | C39: 526283000 | D39: 526437333 | F39: 325571166 | G39: 258758000
A40: Marketing (tuỳ ý phân bổ) | B40: 734000000 | C40: 454705933 | D40: 477778721 | F40: 305919900 | G40: 337589083
A41: chi phí marketing trên mỗi chiếc răng | B41: =B40/B35 -> #REF! | C41: =C40/C35 -> #REF! | D41: =D40/D35 -> #REF! | F41: =F40/F35 -> #REF! | G41: =G40/G35 -> #REF! | H41: =H40/H35 -> #REF! | I41: =I40/I35 -> #REF! | J41: =J40/J35 -> #REF! | K41: =K40/K35 -> #REF! | L41: =L40/L35 -> #REF! | M41: =M40/M35 -> #REF! | N41: =N40/N35 -> #REF!
A42: %marketing trên doanh thu | B42: =B40/B37 -> 0.20869929 | C42: =C40/C37 -> 0.26745819 | D42: =D40/D37 -> 0.23642978 | F42: =F40/F37 -> 0.17872212 | G42: =G40/G37 -> 0.21599511 | H42: =H40/H37 -> 0 | I42: =I40/I37 -> 0 | J42: =J40/J37 -> 0 | K42: =K40/K37 -> 0 | L42: =L40/L37 -> #DIV/0! | M42: =M40/M37 -> #DIV/0! | N42: =N40/N37 -> #DIV/0!
A43: %giá vốn trên doanh thu | B43: =B39/B37 -> 0.22833807 | C43: =C39/C37 -> 0.30955984 | D43: =D39/D37 -> 0.2605086 | F43: =F39/F37 -> 0.19020263 | G43: =G39/G37 -> 0.16555767 | H43: =H39/H37 -> 0 | I43: =I39/I37 -> 0 | J43: =J39/J37 -> 0 | K43: =K39/K37 -> 0 | L43: =L39/L37 -> #DIV/0! | M43: =M39/M37 -> #DIV/0! | N43: =N39/N37 -> #DIV/0!
A44: %KPI trên doanh thu | B44: =B21/B37 -> #N/A | C44: =C21/C37 -> #N/A | D44: =D21/D37 -> #N/A | F44: =F21/F37 -> #N/A | G44: =G21/G37 -> #N/A | H44: =H21/H37 -> #N/A | I44: =I21/I37 -> #N/A | J44: =J21/J37 -> #N/A | K44: =K21/K37 -> #N/A | L44: =L21/L37 -> #N/A | M44: =M21/M37 -> #N/A | N44: =N21/N37 -> #N/A
A46: Cấu hình Điểm hoà vốn | B46: SP dẫn | C46: SP trung bình | D46: SP cao | G46: Mục tiêu bán | H46: 6 | I46: Đơn vị răng
A47: Thay đổi giá vốn 1 răng | B47: =(4*1040000)+4500000+30000000 -> 38660000 | C47: =(4*2500000)+4500000+30000000 -> 44500000 | D47: =(4*3500000)+4500000+30000000 -> 48500000 | G47: SP dẫn | H47: =round($H$46*I47,0) -> 1 | I47: 0.1
A48: Số lượng bán | B48: =H47 -> 1 | C48: =H48 -> 5 | D48: =H49 -> 1 | G48: SP trung bình | H48: =round($H$46*I48,0) -> 5 | I48: 0.8
A49: Thay đổi đơn giá răng sứ | B49: 176600000 | C49: 192200000 | D49: 228000000 | G49: SP cao | H49: =round($H$46*I49,0) -> 1 | I49: 0.1
A50: Doanh số | B50: =B48*B49 -> 176600000 | C50: =C48*C49 -> 961000000 | D50: =D48*D49 -> 228000000 | F50: =sum(B50:D50) -> 1365600000 | G50: Dự toán chi phí | H50: Lãi mong muốn | I50: Doanh thu dự kiến
B51: Min | C51: Average | D51: Max | E51: SUM | G51: 2000000000 | H51: 0.1 | I51: =G51*(1+H51) -> 2200000000
A52: Doanh thu theo răng sứ | B52: =B50 -> 176600000 | C52: =C50 -> 961000000 | D52: =D50 -> 228000000 | E52: =B52+C52+D52 -> 1365600000 | G52: To hiennt150787@gmail.com
A53: KPI trên doanh thu | B53: 0.12 | C53: 0.12 | D53: 0.12
A54: KPI tiền thưởng | B54: =B52*B53 -> 21192000 | C54: =C52*C53 -> 115320000 | D54: =D52*D53 -> 27360000 | E54: =B54+C54+D54 -> 163872000 | G54: Điền dự toán chi phí vào ô F47
A55: Định phí | B55: =450000000/3 -> 150000000 | C55: =450000000/3 -> 150000000 | D55: =450000000/3 -> 150000000 | E55: =B55+C55+D55 -> 450000000 | G55: Điền mức lãi mong muốn vào ô G47, ví dụ 10%
A56: Giá vốn (vật liệu + labo) theo răng sứ | B56: =B48*B47 -> 38660000 | C56: =C48*C47 -> 222500000 | D56: =D48*D47 -> 48500000 | E56: =B56+C56+D56 -> 309660000 | G56: Cấu hình 1: giá vốn của 1 răng sứ, đơn giá bán của 1 răng sứ
A57: Hành chính | B57: =140000000/3 -> 46666667 | C57: =140000000/3 -> 46666667 | D57: =140000000/3 -> 46666667 | E57: =B57+C57+D57 -> 140000000 | G57: Cấu hình 2: thay đổi số lượng răng sứ bán ra
A58: Marketing online theo doanh thu | B58: 0.178 | C58: 0.178 | D58: 0.178 | E58: =B58+C58+D58 -> 0.534 | G58: Cấu hình 3: % marketing online, offline hoặc thay đổi ngân sách marketing
A59: Marketing | B59: =B52*B58 -> 31434800 | C59: =C52*C58 -> 171058000 | D59: =D52*D58 -> 40584000 | E59: =B59+C59+D59 -> 243076800 | G59: Kết quả
A60: Marketing offline theo doanh thu | B60: 0.02 | C60: 0.02 | D60: 0.02 | E60: =B60+C60+D60 -> 0.06 | H60: Ô Chi phí ngoài dự toán: tổng chi phí sẽ vượt ngân sách bao nhiêu
A61: Marketing offline | B61: =B52*B60 -> 3532000 | C61: =C52*C60 -> 19220000 | D61: =D52*D60 -> 4560000 | E61: =B61+C61+D61 -> 27312000 | H61: Doanh thu trừ chi phí thực tế sẽ lãi, lỗ bao nhiêu
A62: Chi phí khác | B62: 10000000 | C62: 20000000 | D62: 40000000 | E62: =B62+C62+D62 -> 70000000 | G62: Nếu cần thêm chương trình khuyến mãi như chiết khấu theo kênh KOL, kênh online, theo số lượng bán... thì chèn thêm
A63: Mua sắm tài sản | B63: 10000000 | C63: 20000000 | D63: 40000000 | E63: =B63+C63+D63 -> 70000000
A64: Tổng chi phí | B64: =sum(B54,B55,B56,B57,B59,B61,B62,B63) -> 3.1148547e+08 | C64: =sum(C54,C55,C56,C57,C59,C61,C62,C63) -> 7.6476467e+08 | D64: =sum(D54,D55,D56,D57,D59,D61,D62,D63) -> 3.9767067e+08 | E64: =B64+C64+D64 -> 1473920800
A65: Chi phí ngoài dự toán | B65: =$G$51-B64 -> 1688514533 | C65: =$G$51-C64 -> 1235235333 | D65: =$G$51-D64 -> 1602329333 | E65: =B65+C65+D65 -> 4526079200
A66: Lãi/lỗ thực tế | B66: =B52-B64 -> -1.3488547e+08 | C66: =C52-C64 -> 1.9623533e+08 | D66: =D52-D64 -> -1.6967067e+08 | E66: =B66+C66+D66 -> -108320800
A67: Biên lợi nhuận | B67: =B66/B52 -> -0.76379086 | C67: =C66/C52 -> 0.2041991 | D67: =D66/D52 -> -0.74416959 | E67: =E66/F50 -> -0.079321031
A72: Điểm hoà vốn | B72: Biến phí | F72: Định phí | I72: Marketing | L72: Phương án 10 | M72: Phương án 11 | N72: Phương án 12 | O72: Tổng
B73: Min | C73: Average | D73: Max | F73: Min | G73: Average | H73: Max | I73: Min | J73: Average | K73: Max
A74: Thay đổi giá vốn 1 răng | B74: 2000000 | C74: 2000000 | D74: 2000000 | F74: 2000000 | G74: 2000000 | H74: 2000000 | I74: 2000000 | J74: 2000000 | K74: 2000000 | L74: 2000000 | M74: 2000000 | N74: 2000000
A75: Thay đổi đơn giá răng sứ | B75: 2500000 | C75: 2500000 | D75: 2500000 | F75: 2500000 | G75: 2500000 | H75: 2200000 | I75: 2500000 | J75: 2500000 | K75: 2500000 | L75: 2500000 | M75: 2500000 | N75: 2500000
A76: Biến phí | B76: 0.278 | C76: 0.333 | D76: 0.365 | F76: 0.333 | G76: 0.333 | H76: 0.333 | I76: 0.333 | J76: 0.333 | K76: 0.333 | L76: 0.333 | M76: 0.333 | N76: 0.333
A77: Định phí | B77: 450000000 | C77: 450000000 | D77: 450000000 | F77: 416000000 | G77: 450000000 | H77: 472000000 | I77: 450000000 | J77: 450000000 | K77: 450000000 | L77: 450000000 | M77: 450000000 | N77: 450000000
A78: Giá vốn | B78: 0.23 | C78: 0.23 | D78: 0.23 | F78: 0.23 | G78: 0.23 | H78: 0.23 | I78: 0.23 | J78: 0.23 | K78: 0.23 | L78: 0.165 | M78: 0.23 | N78: 0.3
A79: Hành chính | B79: 140000000 | C79: 140000000 | D79: 140000000 | F79: 140000000 | G79: 140000000 | H79: 140000000 | I79: 140000000 | J79: 140000000 | K79: 140000000 | L79: 140000000 | M79: 140000000 | N79: 140000000
A80: Marketing | B80: 0.221 | C80: 0.221 | D80: 0.221 | F80: 0.221 | G80: 0.221 | H80: 0.221 | I80: 0.178 | J80: 0.221 | K80: 0.267 | L80: 0.221 | M80: 0.221 | N80: 0.221
A82: Dự toán phân bổ chi phí | B82: Biến phí | F82: Định phí | I82: Marketing | L82: Phương án 10 | M82: Phương án 11 | N82: Phương án 12 | O82: Tổng
A83: 1500000000 | B83: Min | C83: Average | D83: Max | F83: Min | G83: Average | H83: Max | I83: Min | J83: Average | K83: Max
A84: Thay đổi giá vốn 1 răng | B84: 1000000 | C84: 1000000 | D84: 1000000 | F84: 1000000 | G84: 1000000 | H84: 1000000 | I84: 1000000 | J84: 1000000 | K84: 1000000 | L84: 1000000 | M84: 1000000 | N84: 1000000
A85: Thay đổi đơn giá răng sứ | B85: 2500000 | C85: 2000000 | D85: 2500000 | F85: 1500000 | G85: 3000000 | H85: 2200000 | I85: 2500000 | J85: 2500000 | K85: 2500000 | L85: 2500000 | M85: 2500000 | N85: 2500000
A86: Biến phí | B86: =$A$83*B76 -> 417000000 | C86: =$A$83*C76 -> 499500000 | D86: =$A$83*D76 -> 547500000 | F86: =$A$83*F76 -> 499500000 | G86: =$A$83*G76 -> 499500000 | H86: =$A$83*H76 -> 499500000 | I86: =$A$83*I76 -> 499500000 | J86: =$A$83*J76 -> 499500000 | K86: =$A$83*K76 -> 499500000 | L86: =$A$83*L76 -> 499500000 | M86: =$A$83*M76 -> 499500000 | N86: =$A$83*N76 -> 499500000
A87: Định phí | B87: 450000000 | C87: 450000000 | D87: 450000000 | F87: 416000000 | G87: 450000000 | H87: 472000000 | I87: 450000000 | J87: 450000000 | K87: 450000000 | L87: 450000000 | M87: 450000000 | N87: 450000000
A88: Giá vốn | B88: =$A$83*B78 -> 345000000 | C88: =$A$83*C78 -> 345000000 | D88: =$A$83*D78 -> 345000000 | F88: =$A$83*F78 -> 345000000 | G88: =$A$83*G78 -> 345000000 | H88: =$A$83*H78 -> 345000000 | I88: =$A$83*I78 -> 345000000 | J88: =$A$83*J78 -> 345000000 | K88: =$A$83*K78 -> 345000000 | L88: =$A$83*L78 -> 247500000 | M88: =$A$83*M78 -> 345000000 | N88: =$A$83*N78 -> 450000000
A89: Hành chính | B89: 140000000 | C89: 140000000 | D89: 140000000 | F89: 140000000 | G89: 140000000 | H89: 140000000 | I89: 140000000 | J89: 140000000 | K89: 140000000 | L89: 140000000 | M89: 140000000 | N89: 140000000
A90: Marketing | B90: =$A$83*B80 -> 331500000 | C90: =$A$83*C80 -> 331500000 | D90: =$A$83*D80 -> 331500000 | F90: =$A$83*F80 -> 331500000 | G90: =$A$83*G80 -> 331500000 | H90: =$A$83*H80 -> 331500000 | I90: =$A$83*I80 -> 267000000 | J90: =$A$83*J80 -> 331500000 | K90: =$A$83*K80 -> 400500000 | L90: =$A$83*L80 -> 331500000 | M90: =$A$83*M80 -> 331500000 | N90: =$A$83*N80 -> 331500000
A91: Chi phí khác | B91: 40000000 | C91: 40000000 | D91: 40000000 | F91: 40000000 | G91: 40000000 | H91: 40000000 | I91: 40000000 | J91: 40000000 | K91: 40000000 | L91: 40000000 | M91: 40000000 | N91: 40000000
A92: Mua sắm tài sản | B92: 42000000 | C92: 42000000 | D92: 42000000 | F92: 42000000 | G92: 42000000 | H92: 42000000 | I92: 42000000 | J92: 42000000 | K92: 42000000 | L92: 42000000 | M92: 42000000 | N92: 42000000
A93: Tổng chi phí | B93: =sum(B86:B92) -> 1765500000 | C93: =sum(C86:C92) -> 1848000000 | D93: =sum(D86:D92) -> 1896000000 | F93: =sum(F86:F92) -> 1814000000 | G93: =sum(G86:G92) -> 1848000000 | H93: =sum(H86:H92) -> 1870000000 | I93: =sum(I86:I92) -> 1783500000 | J93: =sum(J86:J92) -> 1848000000 | K93: =sum(K86:K92) -> 1917000000 | L93: =sum(L86:L92) -> 1750500000 | M93: =sum(M86:M92) -> 1848000000 | N93: =sum(N86:N92) -> 1953000000
A112: Số lượng đơn hàng | B112: 246 | C112: 259.50557 | D112: 526.3 | F112: 526.4 | G112: 803.1
A113: Giá= bán | B113: 3000000 | C113: 3000000 | D113: 3000000 | F113: 3000000 | G113: 3000000
A114: Doanh thu | B114: =B112*3000000 -> 738000000 | C114: =C112*3000000 -> 778516707 | D114: =D112*3000000 -> 1578900000 | F114: =F112*3000000 -> 1579200000 | G114: =G112*3000000 -> 2409300000
A115: Chi phí cố định | B115: =$C$104 | C115: =$C$104 | D115: =$C$104 | F115: =$C$104 | G115: =$C$104
A116: Biến phí (35.5%) | B116: =B114*0.355 -> 261990000 | C116: =C114*0.355 -> 276373431 | D116: =D114*0.355 -> 560509500 | F116: =F114*0.355 -> 560616000 | G116: =G114*0.355 -> 855301500
A117: Tổng chi phí | B117: =B115+B116 -> 261990000 | C117: =C115+C116 -> 276373431 | D117: =D115+D116 -> 560509500 | F117: =F115+F116 -> 560616000 | G117: =G115+G116 -> 855301500
A118: tháng | B118: =hlookup(B112,$B$35:$N$35,2,false) -> #REF! | C118: =hlookup(C112,$B$35:$N$35,2,false) -> #REF! | D118: =hlookup(D112,$B$35:$N$35,2,false) -> #REF! | F118: =hlookup(F112,$B$35:$N$35,2,false) -> #REF! | G118: =hlookup(G112,$B$35:$N$35,2,false) -> #REF!
A119: Doanh thu thực tế | B119: =hlookup(B118,'BC năm theo dòng tiền'!$D$3:$O$4,2,false) -> #REF! | C119: =hlookup(C118,'BC năm theo dòng tiền'!$D$3:$O$4,2,false) -> #REF! | D119: =hlookup(D118,'BC năm theo dòng tiền'!$D$3:$O$4,2,false) -> #REF! | F119: =hlookup(F118,'BC năm theo dòng tiền'!$D$3:$O$4,2,false) -> #REF! | G119: =hlookup(G118,'BC năm theo dòng tiền'!$D$3:$O$4,2,false) -> #REF!

Sheet Master data
A1: Phân loại | B1: Tài chính | C1: Dòng tiền | D1: Ngân sách | E1: Tỷ lệ | F1: Tháng cần so sánh | G1: 2024.08 | H1: 2000000000 | I1: Số tương đối | J1: Số tuyệt đối
A2: Marketing chạy Quảng cáo | B2: Chi phí bán hàng | C2: Biến phí | D2: 300000000 | E2: =D2/$D$30 -> 0.1540832 | F2: =vlookup($G$1,'Report_Chi phi'!$A$3:$AD$89,12,0) -> #N/A | G2: =F2/$F$30 -> #N/A | H2: =$H$1*E2 -> 3.0816641e+08 | I2: =F2-D2 -> #N/A | J2: =(E2-G2) -> #N/A
A3: KPI | B3: Chi phí bán hàng | C3: Biến phí | D3: 260000000 | E3: =D3/$D$30 -> 0.13353878 | F3: =vlookup($G$1,'Report_Chi phi'!$A$3:$AD$89,10,0) -> #N/A | G3: =F3/$F$30 -> #N/A | H3: =$H$1*E3 -> 2.6707756e+08 | I3: =F3-D3 -> #N/A | J3: =(E3-G3) -> #N/A
A4: Cộng tác viên | B4: Chi phí bán hàng | C4: Biến phí | D4: 40000000 | E4: =D4/$D$30 -> 0.020544427 | F4: =vlookup($G$1,'Report_Chi phi'!$A$3:$AD$89,4,0) -> #N/A | G4: =F4/$F$30 -> #N/A | H4: =$H$1*E4 -> 41088855 | I4: =F4-D4 -> #N/A | J4: =(E4-G4) -> #N/A
A5: Quỹ thưởng gián tiếp | B5: Chi phí bán hàng | C5: Biến phí | D5: 10000000 | E5: =D5/$D$30 -> 0.0051361068 | F5: =vlookup($G$1,'Report_Chi phi'!$A$3:$AD$89,16,0) -> #N/A | G5: =F5/$F$30 -> #N/A | H5: =$H$1*E5 -> 10272214 | I5: =F5-D5 -> #N/A | J5: =(E5-G5) -> #N/A
A6: Tiền vật liệu | B6: Chi phí giá vốn | C6: Biến phí | D6: 70000000 | E6: =D6/$D$30 -> 0.035952748 | F6: =vlookup($G$1,'Report_Chi phi'!$A$3:$AD$89,26,0) -> #N/A | G6: =F6/$F$30 -> #N/A | H6: =$H$1*E6 -> 71905496 | I6: =F6-D6 -> #N/A | J6: =(E6-G6) -> #N/A
A7: Hành chính MKT | B7: Chi phí bán hàng | C7: Biến phí | D7: 15000000 | E7: =D7/$D$30 -> 0.0077041602 | F7: =vlookup($G$1,'Report_Chi phi'!$A$3:$AD$89,8,0) -> #N/A | G7: =F7/$F$30 -> #N/A | H7: =$H$1*E7 -> 15408320 | I7: =F7-D7 -> #N/A | J7: =(E7-G7) -> #N/A
A8: Tiền Lab | B8: Chi phí giá vốn | C8: Biến phí | D8: 344000000 | E8: =D8/$D$30 -> 0.17668207 | F8: =vlookup($G$1,'Report_Chi phi'!$A$3:$AD$89,23,0) -> #N/A | G8: =F8/$F$30 -> #N/A | H8: =$H$1*E8 -> 353364150 | I8: =F8-D8 -> #N/A | J8: =(E8-G8) -> #N/A
A9: Hoa hồng giới thiệu | B9: Chi phí bán hàng | C9: Biến phí | D9: 40000000 | E9: =D9/$D$30 -> 0.020544427 | F9: =vlookup($G$1,'Report_Chi phi'!$A$3:$AD$89,9,0) -> #N/A | G9: =F9/$F$30 -> #N/A | H9: =$H$1*E9 -> 41088855 | I9: =F9-D9 -> #N/A | J9: =(E9-G9) -> #N/A
A10: Tiktok | B10: Chi phí bán hàng | C10: Biến phí | D10: 40000000 | E10: =D10/$D$30 -> 0.020544427 | F10: =vlookup($G$1,'Report_Chi phi'!$A$3:$AD$89,29,0) -> #N/A | G10: =F10/$F$30 -> #N/A | H10: =$H$1*E10 -> 41088855 | I10: =F10-D10 -> #N/A | J10: =(E10-G10) -> #N/A
A11: SEO | B11: Chi phí bán hàng | C11: Biến phí | D11: 15000000 | E11: =D11/$D$30 -> 0.0077041602 | F11: =vlookup($G$1,'Report_Chi phi'!$A$3:$AD$89,18,0) -> #N/A | G11: =F11/$F$30 -> #N/A | H11: =$H$1*E11 -> 15408320 | I11: =F11-D11 -> #N/A | J11: =(E11-G11) -> #N/A
A12: Phí cà thẻ | B12: Chi phí bán hàng | C12: Biến phí | D12: 5000000 | E12: =D12/$D$30 -> 0.0025680534 | F12: =vlookup($G$1,'Report_Chi phi'!$A$3:$AD$89,15,0) -> #N/A | G12: =F12/$F$30 -> #N/A | H12: =$H$1*E12 -> 5136106.8 | I12: =F12-D12 -> #N/A | J12: =(E12-G12) -> #N/A
A13: Tặng phẩm khách | B13: Chi phí bán hàng | C13: Biến phí | D13: 20000000 | E13: =D13/$D$30 -> 0.010272214 | F13: =vlookup($G$1,'Report_Chi phi'!$A$3:$AD$89,20,0) -> #N/A | G13: =F13/$F$30 -> #N/A | H13: =$H$1*E13 -> 20544427 | I13: =F13-D13 -> #N/A | J13: =(E13-G13) -> #N/A
A14: Tiếp khách phòng khám | B14: Chi phí bán hàng | C14: Biến phí | D14: 20000000 | E14: =D14/$D$30 -> 0.010272214 | F14: =vlookup($G$1,'Report_Chi phi'!$A$3:$AD$89,27,0) -> #N/A | G14: =F14/$F$30 -> #N/A | H14: =$H$1*E14 -> 20544427 | I14: =F14-D14 -> #N/A | J14: =(E14-G14) -> #N/A
A15: Lương | B15: Chi phí QLDN | C15: Định phí | D15: 320000000 | E15: =D15/$D$30 -> 0.16435542 | F15: =vlookup($G$1,'Report_Chi phi'!$A$3:$AD$89,11,0) -> #N/A | G15: =F15/$F$30 -> #N/A | H15: =$H$1*E15 -> 3.2871084e+08 | I15: =F15-D15 -> #N/A | J15: =(E15-G15) -> #N/A
A16: Quỹ thưởng tổng cuối năm | B16: Chi phí khác | C16: Định phí | D16: 30000000 | E16: =D16/$D$30 -> 0.01540832 | F16: =vlookup($G$1,'Report_Chi phi'!$A$3:$AD$89,17,0) -> #N/A | G16: =F16/$F$30 -> #N/A | H16: =$H$1*E16 -> 30816641 | I16: =F16-D16 -> #N/A | J16: =(E16-G16) -> #N/A
A17: Mua đồ hành chính | B17: Chi phí hành chính | C17: Biến phí | D17: 30000000 | E17: =D17/$D$30 -> 0.01540832 | F17: =vlookup($G$1,'Report_Chi phi'!$A$3:$AD$89,13,0) -> #N/A | G17: =F17/$F$30 -> #N/A | H17: =$H$1*E17 -> 30816641 | I17: =F17-D17 -> #N/A | J17: =(E17-G17) -> #N/A
A18: Sửa chữa | B18: Chi phí hành chính | C18: Định phí | D18: 12000000 | E18: =D18/$D$30 -> 0.0061633282 | F18: =vlookup($G$1,'Report_Chi phi'!$A$3:$AD$89,19,0) -> #N/A | G18: =F18/$F$30 -> #N/A | H18: =$H$1*E18 -> 12326656 | I18: =F18-D18 -> #N/A | J18: =(E18-G18) -> #N/A
A19: Tiền thuê xe | B19: Chi phí hành chính | C19: Định phí | D19: 23000000 | E19: =D19/$D$30 -> 0.011813046 | F19: =vlookup($G$1,'Report_Chi phi'!$A$3:$AD$89,24,0) -> #N/A | G19: =F19/$F$30 -> #N/A | H19: =$H$1*E19 -> 23626091 | I19: =F19-D19 -> #N/A | J19: =(E19-G19) -> #N/A
A20: Điện + Nước | B20: Chi phí hành chính | C20: Định phí | D20: 20000000 | E20: =D20/$D$30 -> 0.010272214 | F20: =vlookup($G$1,'Report_Chi phi'!$A$3:$AD$89,7,0) -> #N/A | G20: =F20/$F$30 -> #N/A | H20: =$H$1*E20 -> 20544427 | I20: =F20-D20 -> #N/A | J20: =(E20-G20) -> #N/A
A21: Đi trường | B21: Chi phí bán hàng | C21: Định phí | D21: 20000000 | E21: =D21/$D$30 -> 0.010272214 | F21: =vlookup($G$1,'Report_Chi phi'!$A$3:$AD$89,6,0) -> #N/A | G21: =F21/$F$30 -> #N/A | H21: =$H$1*E21 -> 20544427 | I21: =F21-D21 -> #N/A | J21: =(E21-G21) -> #N/A
A22: Tiếp khách | B22: Chi phí hành chính | C22: Định phí | D22: 20000000 | E22: =D22/$D$30 -> 0.010272214 | F22: =vlookup($G$1,'Report_Chi phi'!$A$3:$AD$89,27,0) -> #N/A | G22: =F22/$F$30 -> #N/A | H22: =$H$1*E22 -> 20544427 | I22: =F22-D22 -> #N/A | J22: =(E22-G22) -> #N/A
A23: Tiền dự trù phát sinh | B23: Chi phí khác | C23: Định phí | D23: 50000000 | E23: =D23/$D$30 -> 0.025680534 | F23: =vlookup($G$1,'Report_Chi phi'!$A$3:$AD$89,22,0) -> #N/A | G23: =F23/$F$30 -> #N/A | H23: =$H$1*E23 -> 51361068 | I23: =F23-D23 -> #N/A | J23: =(E23-G23) -> #N/A
A24: Chi phí Mặt bằng | B24: Chi phí QLDN | C24: Định phí | D24: 110000000 | E24: =D24/$D$30 -> 0.056497175 | F24: =vlookup($G$1,'Report_Chi phi'!$A$3:$AD$89,3,0) -> #N/A | G24: =F24/$F$30 -> #N/A | H24: =$H$1*E24 -> 1.1299435e+08 | I24: =F24-D24 -> #N/A | J24: =(E24-G24) -> #N/A
A25: Bảo hiểm | B25: Chi phí QLDN | C25: Định phí | D25: 20000000 | E25: =D25/$D$30 -> 0.010272214 | F25: =vlookup($G$1,'Report_Chi phi'!$A$3:$AD$89,2,0) -> #N/A | G25: =F25/$F$30 -> #N/A | H25: =$H$1*E25 -> 20544427 | I25: =F25-D25 -> #N/A | J25: =(E25-G25) -> #N/A
A26: Tiền thưởng nóng + liên hoan | B26: Chi phí khác | C26: Định phí | D26: 20000000 | E26: =D26/$D$30 -> 0.010272214 | F26: =vlookup($G$1,'Report_Chi phi'!$A$3:$AD$89,25,0) -> #N/A | G26: =F26/$F$30 -> #N/A | H26: =$H$1*E26 -> 20544427 | I26: =F26-D26 -> #N/A | J26: =(E26-G26) -> #N/A
A27: Thuê bằng | B27: Chi phí QLDN | C27: Định phí | D27: 18000000 | E27: =D27/$D$30 -> 0.0092449923 | F27: =vlookup($G$1,'Report_Chi phi'!$A$3:$AD$89,21,0) -> #N/A | G27: =F27/$F$30 -> #N/A | H27: =$H$1*E27 -> 18489985 | I27: =F27-D27 -> #N/A | J27: =(E27-G27) -> #N/A
A28: Đào tạo | B28: Chi phí khác | C28: Chi phí khác | D28: 5000000 | E28: =D28/$D$30 -> 0.0025680534 | F28: =vlookup($G$1,'Report_Chi phi'!$A$3:$AD$89,5,0) -> #N/A | G28: =F28/$F$30 -> #N/A | H28: =$H$1*E28 -> 5136106.8 | I28: =F28-D28 -> #N/A | J28: =(E28-G28) -> #N/A
A29: Mua sắm tài sản | B29: Chi phí khác | C29: Chi phí khác | D29: 70000000 | E29: =D29/$D$30 -> 0.035952748 | F29: =vlookup($G$1,'Report_Chi phi'!$A$3:$AD$89,14,0) -> #N/A | G29: =F29/$F$30 -> #N/A | H29: =$H$1*E29 -> 71905496 | I29: =F29-D29 -> #N/A | J29: =(E29-G29) -> #N/A
D30: =sum(D2:D29) -> 1947000000 | E30: =D30/$D$30 -> 1 | F30: =sum(F2:F29) -> #N/A | H30: =sum(H2:H29) -> 2000000000

Sheet Master_data
A1: ID | B1: Phân loại chi | C1: Tài chính | D1: Dòng tiền | F1: Tháng | G1: Năm | I1: Phân loại thu | K1: SAN | L1: Họ tên | M1: Bộ phận | O1: Nha khoa | Q1: TEENNIE | R1: Họ tên | S1: Bộ phận | T1: Tình trạng | U1: Nha khoa | W1: IMPLANT | X1: Họ tên | Y1: Bộ phận | Z1: Tình trạng | AA1: Nha khoa
A2: 2 | B2: Bảo hiểm | C2: Chi phí QLDN | D2: Định phí | F2: 01 | G2: 2018 | I2: Tiền mặt | K2: BS01 | L2: BS Công | M2: Bác sĩ | O2: SAN | Q2: 1 | R2: BS Công | S2: Bác sĩ | T2: Hoạt động | U2: TEENNIE | W2: 1 | X2: BS Công | Y2: Bác sĩ | Z2: Hoạt động | AA2: IMPLANT
A3: 3 | B3: Chi phí Mặt bằng | C3: Chi phí QLDN | D3: Định phí | F3: 02 | G3: 2019 | I3: Cà thẻ | K3: BS02 | L3: Bs Phong | M3: Bác sĩ | O3: SAN | Q3: 2 | R3: Bs Phong | S3: Bác sĩ | T3: Hoạt động | U3: TEENNIE | W3: 2 | X3: Bs Phong | Y3: Bác sĩ | Z3: Hoạt động | AA3: IMPLANT
A4: 4 | B4: Cộng tác viên | C4: Chi phí bán hàng | D4: Biến phí | F4: 03 | G4: 2020 | I4: Chuyển khoản | K4: BS03 | L4: Bs Tú | M4: Bác sĩ | O4: SAN | Q4: 3 | R4: Bs Tú | S4: Bác sĩ | T4: Hoạt động | U4: TEENNIE | W4: 3 | X4: Bs Tú | Y4: Bác sĩ | Z4: Hoạt động | AA4: IMPLANT
A5: 5 | B5: Đào tạo | C5: Chi phí khác | D5: Chi phí khác | F5: 04 | G5: 2021 | I5: Thực nhận cà thẻ | K5: BS04 | L5: Bs Dũng | M5: Bác sĩ | O5: SAN | Q5: 4 | R5: Bs Dũng | S5: Bác sĩ | T5: Hoạt động | U5: TEENNIE | W5: 4 | X5: Bs Dũng | Y5: Bác sĩ | Z5: Hoạt động | AA5: IMPLANT
A6: 6 | B6: Đi trường | C6: Chi phí bán hàng | D6: Định phí | F6: 05 | G6: 2022 | I6: Trả góp | K6: BS05 | L6: Bs Hải Anh | M6: Bác sĩ | O6: SAN
A7: 7 | B7: Điện + Nước | C7: Chi phí hành chính | D7: Định phí | F7: 06 | G7: 2023 | I7: Trả cọc | K7: VP01 | L7: Lương 3CĐ | M7: Văn phòng | O7: SAN
A8: 8 | B8: Hành chính MKT | C8: Chi phí bán hàng | D8: Biến phí | F8: 07 | G8: 2024 | I8: Tổng phí trừ cà thẻ | K8: PT01 | L8: PT Ngọc Tiên | M8: Phụ tá | O8: SAN | Q8: 5 | R8: PT Ngọc Tiên | S8: Phụ tá | T8: Hoạt động | U8: TEENNIE | W8: 5 | X8: PT Ngọc Tiên | Y8: Phụ tá | Z8: Hoạt động | AA8: IMPLANT
A9: 9 | B9: Hoa hồng giới thiệu | C9: Chi phí bán hàng | D9: Biến phí | F9: 08 | G9: 2025 | I9: Phí cà thẻ | K9: PT02 | L9: PT Cẩm Tiên | M9: Phụ tá | O9: SAN | Q9: 6 | R9: PT Cẩm Tiên | S9: Phụ tá | T9: Hoạt động | U9: TEENNIE | W9: 6 | X9: PT Cẩm Tiên | Y9: Phụ tá | Z9: Hoạt động | AA9: IMPLANT
A10: 10 | B10: KPI | C10: Chi phí bán hàng | D10: Biến phí | F10: 09 | G10: 2026 | K10: PT03 | L10: PT Ly | M10: Phụ tá | O10: SAN | Q10: 7 | R10: PT Ly | S10: Phụ tá | T10: Hoạt động | U10: TEENNIE | W10: 7 | X10: PT Ly | Y10: Phụ tá | Z10: Hoạt động | AA10: IMPLANT
A11: 11 | B11: Lương | C11: Chi phí QLDN | D11: Định phí | F11: 10 | G11: 2027 | K11: PT04 | L11: PT Kha | M11: Phụ tá | O11: SAN | Q11: 8 | R11: PT Kha | S11: Phụ tá | T11: Hoạt động | U11: TEENNIE | W11: 8 | X11: PT Kha | Y11: Phụ tá | Z11: Hoạt động | AA11: IMPLANT
A12: 12 | B12: Marketing chạy Quảng cáo | C12: Chi phí bán hàng | D12: Biến phí | G12: 2028 | K12: PT05 | L12: PT Kiều | M12: Phụ tá | O12: SAN | Q12: 9 | R12: PT Kiều | S12: Phụ tá | T12: Hoạt động | U12: TEENNIE | W12: 9 | X12: PT Kiều | Y12: Phụ tá | Z12: Hoạt động | AA12: IMPLANT
A13: 13 | B13: Mua đồ hành chính | C13: Chi phí hành chính | D13: Biến phí | G13: 2029 | K13: PT06 | L13: PT Trân | M13: Phụ tá | O13: SAN | Q13: 10 | R13: PT Trân | S13: Phụ tá | T13: Hoạt động | U13: TEENNIE | W13: 10 | X13: PT Trân | Y13: Phụ tá | Z13: Hoạt động | AA13: IMPLANT
A14: 14 | B14: Mua sắm tài sản | C14: Chi phí khác | D14: Chi phí khác | G14: 2030 | K14: PT07 | L14: PT Thế Anh | M14: Phụ tá | O14: SAN
A15: 15 | B15: Phí cà thẻ | C15: Chi phí bán hàng | D15: Biến phí | K15: PT08 | L15: PT Thanh Loan | M15: Phụ tá | O15: SAN | Q15: 11 | R15: LT Quỳnh Như | S15: Lễ tân | T15: Hoạt động | U15: TEENNIE | W15: 11 | X15: LT Quỳnh Như | Y15: Lễ tân | Z15: Hoạt động | AA15: IMPLANT
A16: 16 | B16: Quỹ thưởng gián tiếp | C16: Chi phí bán hàng | D16: Biến phí | K16: PT09 | L16: PT Thành học việc | M16: Phụ tá | O16: SAN | Q16: 12 | R16: LT Kim Ngân | S16: Lễ tân | T16: Hoạt động | U16: TEENNIE | W16: 12 | X16: LT Kim Ngân | Y16: Lễ tân | Z16: Hoạt động | AA16: IMPLANT
A17: 17 | B17: Quỹ thưởng tổng cuối năm | C17: Chi phí khác | D17: Định phí | K17: PT10 | L17: PT TRƯỞNG Cẩm Loan | M17: Phụ tá | O17: SAN | Q17: 13 | R17: Lt Tú Nhi | S17: Lễ tân | T17: Hoạt động | U17: TEENNIE | W17: 13 | X17: Lt Tú Nhi | Y17: Lễ tân | Z17: Hoạt động | AA17: IMPLANT
A18: 18 | B18: SEO | C18: Chi phí bán hàng | D18: Biến phí | K18: LT01 | L18: LT Quỳnh Như | M18: Lễ tân | O18: SAN | Q18: 14 | R18: LT Văn Tính | S18: Lễ tân | T18: Hoạt động | U18: TEENNIE | W18: 14 | X18: LT Văn Tính | Y18: Lễ tân | Z18: Hoạt động | AA18: IMPLANT
A19: 19 | B19: Sửa chữa | C19: Chi phí hành chính | D19: Định phí | K19: LT02 | L19: LT Kim Ngân | M19: Lễ tân | O19: SAN | Q19: 15 | R19: TV Đông | S19: Tư vấn | T19: Hoạt động | U19: TEENNIE | W19: 15 | X19: TV Đông | Y19: Tư vấn | Z19: Hoạt động | AA19: IMPLANT
A20: 20 | B20: Tặng phẩm khách | C20: Chi phí bán hàng | D20: Biến phí | K20: LT04 | L20: Lt Tú Nhi | M20: Lễ tân | O20: SAN | Q20: 16 | R20: Tv Na | S20: Tư vấn | T20: Hoạt động | U20: TEENNIE | W20: 16 | X20: Tv Na | Y20: Tư vấn | Z20: Hoạt động | AA20: IMPLANT
A21: 21 | B21: Thuê bằng | C21: Chi phí QLDN | D21: Định phí | K21: LT05 | L21: LT Văn Tính | M21: Lễ tân | O21: SAN | Q21: 17 | R21: Telesale Bí Nhi | S21: Telesale | T21: Hoạt động | U21: TEENNIE | W21: 17 | X21: Telesale Bí Nhi | Y21: Telesale | Z21: Hoạt động | AA21: IMPLANT
A22: 22 | B22: Tiền dự trù phát sinh | C22: Chi phí khác | D22: Định phí | K22: TV00 | L22: TV Đông | M22: Tư vấn | O22: SAN | Q22: 18 | R22: Telesale Yến | S22: Telesale | T22: Hoạt động | U22: TEENNIE | W22: 18 | X22: Telesale Yến | Y22: Telesale | Z22: Hoạt động | AA22: IMPLANT
A23: 23 | B23: Tiền Lab | C23: Chi phí giá vốn | D23: Biến phí | K23: TV01 | L23: Tv Na | M23: Tư vấn | O23: SAN | Q23: 19 | R23: Telesale Uyển Nhi | S23: Telesale | T23: Hoạt động | U23: TEENNIE | W23: 19 | X23: Telesale Uyển Nhi | Y23: Telesale | Z23: Hoạt động | AA23: IMPLANT
A24: 24 | B24: Tiền thuê xe | C24: Chi phí hành chính | D24: Định phí | K24: TV02 | L24: Tv Vy | M24: Tư vấn | O24: SAN | Q24: 20 | R24: Thầy Vinh PT | S24: Thầy | T24: Hoạt động | U24: TEENNIE | W24: 20 | X24: Thầy Vinh PT | Y24: Thầy | Z24: Hoạt động | AA24: IMPLANT
A25: 25 | B25: Tiền thưởng nóng + liên hoan | C25: Chi phí khác | D25: Định phí | K25: TV03 | L25: Telesale Bí Nhi | M25: Telesale | O25: SAN
A26: 26 | B26: Tiền vật liệu | C26: Chi phí giá vốn | D26: Biến phí | K26: TV04 | L26: Telesale Yến | M26: Telesale | O26: SAN | Q26: 21 | R26: Anh Hiền | S26: Văn phòng | T26: Hoạt động | U26: TEENNIE | W26: 21 | X26: Anh Hiền | Y26: Văn phòng | Z26: Hoạt động | AA26: IMPLANT
A27: 27 | B27: Tiếp khách | C27: Chi phí hành chính | D27: Định phí | K27: TV05 | L27: Telesale Uyển Nhi | M27: Telesale | O27: SAN | Q27: 22 | R27: Hiến | S27: Văn phòng | T27: Hoạt động | U27: TEENNIE | W27: 22 | X27: Hiến | Y27: Văn phòng | Z27: Hoạt động | AA27: IMPLANT
A28: 28 | B28: Tiktok | C28: Chi phí bán hàng | D28: Biến phí | K28: VP18 | L28: Thầy Vinh PT | M28: Văn phòng | O28: SAN | Q28: 23 | R28: Chị Phượng | S28: Văn phòng | T28: Hoạt động | U28: TEENNIE | W28: 23 | X28: Chị Phượng | Y28: Văn phòng | Z28: Hoạt động | AA28: IMPLANT
K29: TV07 | L29: CSKH Hoàng Lan | M29: CSKH | O29: SAN | Q29: 24 | R29: Duyên HCNS | S29: Văn phòng | T29: Hoạt động | U29: TEENNIE | W29: 24 | X29: Duyên HCNS | Y29: Văn phòng | Z29: Hoạt động | AA29: IMPLANT
K30: VP02 | L30: Anh Hiền | M30: Văn phòng | O30: SAN | Q30: 25 | R30: Kiểm soát Ngọc Lệ | S30: Văn phòng | T30: Hoạt động | U30: TEENNIE | W30: 25 | X30: Kiểm soát Ngọc Lệ | Y30: Văn phòng | Z30: Hoạt động | AA30: IMPLANT
K31: VP03 | L31: Hiến | M31: Văn phòng | O31: SAN | Q31: 26 | R31: Kim Hồng | S31: Văn phòng | T31: Hoạt động | U31: TEENNIE | W31: 26 | X31: Kim Hồng | Y31: Văn phòng | Z31: Hoạt động | AA31: IMPLANT
K32: VP04 | L32: Chị Phượng | M32: Văn phòng | O32: SAN | Q32: 27 | R32: Nhi (ngoc nhi 2727) | S32: Văn phòng | T32: Hoạt động | U32: TEENNIE | W32: 27 | X32: Nhi (ngoc nhi 2727) | Y32: Văn phòng | Z32: Hoạt động | AA32: IMPLANT
K33: VP05 | L33: Duyên HCNS | M33: Văn phòng | O33: SAN
K34: VP06 | L34: Kiểm soát Ngọc Lệ | M34: Văn phòng | O34: SAN | Q34: 28 | R34: MKT Minh Lâm | S34: Marketing | T34: Hoạt động | U34: TEENNIE | W34: 28 | X34: MKT Minh Lâm | Y34: Marketing | Z34: Hoạt động | AA34: IMPLANT
K35: VP07 | L35: Kim Hồng | M35: Văn phòng | O35: SAN | Q35: 29 | R35: MKT Bông | S35: Marketing | T35: Hoạt động | U35: TEENNIE | W35: 29 | X35: MKT Bông | Y35: Marketing | Z35: Hoạt động | AA35: IMPLANT
K36: VP08 | L36: Nhi (ngoc nhi 2727) | M36: Văn phòng | O36: SAN | Q36: 30 | R36: Trung Hào | S36: Marketing | T36: Hoạt động | U36: TEENNIE | W36: 30 | X36: Trung Hào | Y36: Marketing | Z36: Hoạt động | AA36: IMPLANT
K37: VP09 | L37: MKT Minh Lâm | M37: Marketing | O37: SAN | Q37: 31 | R37: Chụp hình Hùng | S37: Marketing | T37: Hoạt động | U37: TEENNIE | W37: 31 | X37: Chụp hình Hùng | Y37: Marketing | Z37: Hoạt động | AA37: IMPLANT
K38: VP10 | L38: MKT Bông | M38: Marketing | O38: SAN | Q38: 32 | R38: Lâm Trần Tuấn | S38: Marketing | T38: Hoạt động | U38: TEENNIE | W38: 32 | X38: Lâm Trần Tuấn | Y38: Marketing | Z38: Hoạt động | AA38: IMPLANT
K39: VP11 | L39: Trung Hào | M39: Marketing | O39: SAN | Q39: 33 | R39: MKT Anh TRung | S39: Marketing | T39: Hoạt động | U39: TEENNIE | W39: 33 | X39: MKT Anh TRung | Y39: Marketing | Z39: Hoạt động | AA39: IMPLANT
K40: VP12 | L40: Chụp hình Hùng | M40: Marketing | O40: SAN | Q40: 34 | R40: Kế toán + thuế | S40: Văn phòng | T40: Hoạt động | U40: TEENNIE | W40: 34 | X40: Kế toán + thuế | Y40: Văn phòng | Z40: Hoạt động | AA40: IMPLANT
K41: VP13 | L41: Lâm Trần Tuấn | M41: Marketing | O41: SAN
K42: VP14 | L42: MKT Anh TRung | M42: Marketing | O42: SAN | Q42: 35 | R42: GV Hiền | S42: Sảnh + bếp | T42: Hoạt động | U42: SAN | W42: 35 | X42: GV Hiền | Y42: Sảnh + bếp | Z42: Hoạt động | AA42: SAN
K43: VP16 | L43: Bảo Nghi | M43: Văn phòng | O43: SAN | Q43: 36 | R43: Chị Trang | S43: Sảnh + bếp | T43: Hoạt động | U43: SAN | W43: 36 | X43: Chị Trang | Y43: Sảnh + bếp | Z43: Hoạt động | AA43: SAN
K44: VP17 | L44: Kế toán tài chính Thái | M44: Văn phòng | O44: SAN | Q44: 37 | R44: Chị Trang VP | S44: Sảnh + bếp | T44: Hoạt động | U44: SAN | W44: 37 | X44: Chị Trang VP | Y44: Sảnh + bếp | Z44: Hoạt động | AA44: SAN
K45: VP15 | L45: Kế toán + thuế | M45: Văn phòng | O45: SAN | Q45: 38 | R45: GV Linh | S45: Sảnh + bếp | T45: Hoạt động | U45: SAN | W45: 38 | X45: GV Linh | Y45: Sảnh + bếp | Z45: Hoạt động | AA45: SAN
K46: K01 | L46: GV Hiền | M46: Sảnh + bếp | O46: SAN | Q46: 39 | R46: BV Trung | S46: Sảnh + bếp | T46: Hoạt động | U46: SAN | W46: 39 | X46: BV Trung | Y46: Sảnh + bếp | Z46: Hoạt động | AA46: SAN
K47: K02 | L47: Chị Trang | M47: Sảnh + bếp | O47: SAN | Q47: 40 | R47: BV Cang | S47: Sảnh + bếp | T47: Hoạt động | U47: SAN | W47: 40 | X47: BV Cang | Y47: Sảnh + bếp | Z47: Hoạt động | AA47: SAN
K48: K03 | L48: Chị Trang VP | M48: Sảnh + bếp | O48: SAN | Q48: 41 | R48: TX Đức | S48: Sảnh + bếp | T48: Hoạt động | U48: SAN | W48: 41 | X48: TX Đức | Y48: Sảnh + bếp | Z48: Hoạt động | AA48: SAN
K49: K04 | L49: GV Linh | M49: Sảnh + bếp | O49: SAN | Q49: 42 | R49: TX Oanh | S49: Sảnh + bếp | T49: Hoạt động | U49: SAN | W49: 42 | X49: TX Oanh | Y49: Sảnh + bếp | Z49: Hoạt động | AA49: SAN
K50: K05 | L50: BV Trung | M50: Sảnh + bếp | O50: SAN
K51: K06 | L51: BV Cang | M51: Sảnh + bếp | O51: SAN
K52: K07 | L52: TX Đức | M52: Sảnh + bếp | O52: SAN
K53: K08 | L53: TX Oanh | M53: Sảnh + bếp | O53: SAN

Sheet Chi phi_San
A1: THÁNG | B1: NỘI DUNG CHI | C1: PHÂN LOẠI | D1: SỐ TIỀN | E1: DÒNG TIỀN | F1: TÀI CHÍNH
A2: 2021.01 | B2: Tổng hợp | C2: Mua đồ hành chính | D2: 0 | E2: =iferror(vlookup(C2,'Master data'!$A$2:$C$29,3,0),"-/-") -> Biến phí | F2: =iferror(vlookup(C2,'Master data'!$A$2:$C$29,2,0),"-/-") -> Chi phí hành chính
A3: 2021.01 | B3: hoa trái cây | C3: Mua đồ hành chính | D3: 948000 | E3: =iferror(vlookup(C3,'Master data'!$A$2:$C$29,3,0),"-/-") -> Biến phí | F3: =iferror(vlookup(C3,'Master data'!$A$2:$C$29,2,0),"-/-") -> Chi phí hành chính
A4: 2021.01 | B4: hoa trái cây | C4: Mua đồ hành chính | D4: 905000 | E4: =iferror(vlookup(C4,'Master data'!$A$2:$C$29,3,0),"-/-") -> Biến phí | F4: =iferror(vlookup(C4,'Master data'!$A$2:$C$29,2,0),"-/-") -> Chi phí hành chính
A5: 2021.01 | B5: hoa bi | C5: Mua đồ hành chính | D5: 120000 | E5: =iferror(vlookup(C5,'Master data'!$A$2:$C$29,3,0),"-/-") -> Biến phí | F5: =iferror(vlookup(C5,'Master data'!$A$2:$C$29,2,0),"-/-") -> Chi phí hành chính
A6: 2021.01 | B6: Lương cứng t1 | C6: Lương | D6: 366774927 | E6: =iferror(vlookup(C6,'Master data'!$A$2:$C$29,3,0),"-/-") -> Định phí | F6: =iferror(vlookup(C6,'Master data'!$A$2:$C$29,2,0),"-/-") -> Chi phí QLDN
A7: 2021.01 | B7: Lương KPI t1 | C7: KPI | D7: 340881611 | E7: =iferror(vlookup(C7,'Master data'!$A$2:$C$29,3,0),"-/-") -> Biến phí | F7: =iferror(vlookup(C7,'Master data'!$A$2:$C$29,2,0),"-/-") -> Chi phí bán hàng
A8: 2021.01 | B8: hoa trái cây | C8: Mua đồ hành chính | D8: 895000 | E8: =iferror(vlookup(C8,'Master data'!$A$2:$C$29,3,0),"-/-") -> Biến phí | F8: =iferror(vlookup(C8,'Master data'!$A$2:$C$29,2,0),"-/-") -> Chi phí hành chính
A9: 2021.01 | B9: cúng m2 | C9: Mua đồ hành chính | D9: 1264000 | E9: =iferror(vlookup(C9,'Master data'!$A$2:$C$29,3,0),"-/-") -> Biến phí | F9: =iferror(vlookup(C9,'Master data'!$A$2:$C$29,2,0),"-/-") -> Chi phí hành chính
A10: 2021.01 | B10: hoa trái cây | C10: Mua đồ hành chính | D10: 910000 | E10: =iferror(vlookup(C10,'Master data'!$A$2:$C$29,3,0),"-/-") -> Biến phí | F10: =iferror(vlookup(C10,'Master data'!$A$2:$C$29,2,0),"-/-") -> Chi phí hành chính
A11: 2021.01 | B11: hoa trái cây | C11: Mua đồ hành chính | D11: 910000 | E11: =iferror(vlookup(C11,'Master data'!$A$2:$C$29,3,0),"-/-") -> Biến phí | F11: =iferror(vlookup(C11,'Master data'!$A$2:$C$29,2,0),"-/-") -> Chi phí hành chính
A12: 2021.01 | B12: cúng m16 | C12: Mua đồ hành chính | D12: 880000 | E12: =iferror(vlookup(C12,'Master data'!$A$2:$C$29,3,0),"-/-") -> Biến phí | F12: =iferror(vlookup(C12,'Master data'!$A$2:$C$29,2,0),"-/-") -> Chi phí hành chính
A13: 2021.01 | B13: 1thang chè vp+203 | C13: Mua đồ hành chính | D13: 1200000 | E13: =iferror(vlookup(C13,'Master data'!$A$2:$C$29,3,0),"-/-") -> Biến phí | F13: =iferror(vlookup(C13,'Master data'!$A$2:$C$29,2,0),"-/-") -> Chi phí hành chính
... A5713: 2025.10 | B5713: đào tạo nhân sự | C5713: Đào tạo | D5713: 5751667 | E5713: =iferror(vlookup(C5713,'Master data'!$A$2:$C$29,3,0),"-/-") -> Chi phí khác | F5713: =iferror(vlookup(C5713,'Master data'!$A$2:$C$29,2,0),"-/-") -> Chi phí khác
D5714: 0 | E5714: =iferror(vlookup(C5714,'Master data'!$A$2:$C$29,3,0),"-/-") -> -/- | F5714: =iferror(vlookup(C5714,'Master data'!$A$2:$C$29,2,0),"-/-") -> -/-
D5715: 0 | E5715: =iferror(vlookup(C5715,'Master data'!$A$2:$C$29,3,0),"-/-") -> -/- | F5715: =iferror(vlookup(C5715,'Master data'!$A$2:$C$29,2,0),"-/-") -> -/-
D5716: 0 | E5716: =iferror(vlookup(C5716,'Master data'!$A$2:$C$29,3,0),"-/-") -> -/- | F5716: =iferror(vlookup(C5716,'Master data'!$A$2:$C$29,2,0),"-/-") -> -/-
D5717: 0 | E5717: =iferror(vlookup(C5717,'Master data'!$A$2:$C$29,3,0),"-/-") -> -/- | F5717: =iferror(vlookup(C5717,'Master data'!$A$2:$C$29,2,0),"-/-") -> -/-
D5718: 0 | E5718: =iferror(vlookup(C5718,'Master data'!$A$2:$C$29,3,0),"-/-") -> -/- | F5718: =iferror(vlookup(C5718,'Master data'!$A$2:$C$29,2,0),"-/-") -> -/-
D5719: 0 | E5719: =iferror(vlookup(C5719,'Master data'!$A$2:$C$29,3,0),"-/-") -> -/- | F5719: =iferror(vlookup(C5719,'Master data'!$A$2:$C$29,2,0),"-/-") -> -/-
D5720: 0 | E5720: =iferror(vlookup(C5720,'Master data'!$A$2:$C$29,3,0),"-/-") -> -/- | F5720: =iferror(vlookup(C5720,'Master data'!$A$2:$C$29,2,0),"-/-") -> -/-
D5721: 0 | E5721: =iferror(vlookup(C5721,'Master data'!$A$2:$C$29,3,0),"-/-") -> -/- | F5721: =iferror(vlookup(C5721,'Master data'!$A$2:$C$29,2,0),"-/-") -> -/-
D5722: 0 | E5722: =iferror(vlookup(C5722,'Master data'!$A$2:$C$29,3,0),"-/-") -> -/- | F5722: =iferror(vlookup(C5722,'Master data'!$A$2:$C$29,2,0),"-/-") -> -/-
D5723: 0 | E5723: =iferror(vlookup(C5723,'Master data'!$A$2:$C$29,3,0),"-/-") -> -/- | F5723: =iferror(vlookup(C5723,'Master data'!$A$2:$C$29,2,0),"-/-") -> -/-
D5724: 0 | E5724: =iferror(vlookup(C5724,'Master data'!$A$2:$C$29,3,0),"-/-") -> -/- | F5724: =iferror(vlookup(C5724,'Master data'!$A$2:$C$29,2,0),"-/-") -> -/-
D5725: 0 | E5725: =iferror(vlookup(C5725,'Master data'!$A$2:$C$29,3,0),"-/-") -> -/- | F5725: =iferror(vlookup(C5725,'Master data'!$A$2:$C$29,2,0),"-/-") -> -/-
... D6940: 0 | E6940: =iferror(vlookup(C6940,'Master data'!$A$2:$C$29,3,0),"-/-") -> -/- | F6940: =iferror(vlookup(C6940,'Master data'!$A$2:$C$29,2,0),"-/-") -> -/-
D6941: 0 | E6941: =vlookup(C6941,'Master data'!$A$2:$C$29,3,0) -> #N/A | F6941: =vlookup(C6941,'Master data'!$A$2:$C$29,2,0) -> #N/A
D6942: 0 | E6942: =vlookup(C6942,'Master data'!$A$2:$C$29,3,0) -> #N/A | F6942: =vlookup(C6942,'Master data'!$A$2:$C$29,2,0) -> #N/A
D6943: 0 | E6943: =vlookup(C6943,'Master data'!$A$2:$C$29,3,0) -> #N/A | F6943: =vlookup(C6943,'Master data'!$A$2:$C$29,2,0) -> #N/A
D6944: 0 | E6944: =vlookup(C6944,'Master data'!$A$2:$C$29,3,0) -> #N/A | F6944: =vlookup(C6944,'Master data'!$A$2:$C$29,2,0) -> #N/A
D6945: 0 | E6945: =vlookup(C6945,'Master data'!$A$2:$C$29,3,0) -> #N/A | F6945: =vlookup(C6945,'Master data'!$A$2:$C$29,2,0) -> #N/A
D6946: 0 | E6946: =vlookup(C6946,'Master data'!$A$2:$C$29,3,0) -> #N/A | F6946: =vlookup(C6946,'Master data'!$A$2:$C$29,2,0) -> #N/A
D6947: 0 | E6947: =vlookup(C6947,'Master data'!$A$2:$C$29,3,0) -> #N/A | F6947: =vlookup(C6947,'Master data'!$A$2:$C$29,2,0) -> #N/A
D6948: 0 | E6948: =vlookup(C6948,'Master data'!$A$2:$C$29,3,0) -> #N/A | F6948: =vlookup(C6948,'Master data'!$A$2:$C$29,2,0) -> #N/A
D6949: 0 | E6949: =vlookup(C6949,'Master data'!$A$2:$C$29,3,0) -> #N/A | F6949: =vlookup(C6949,'Master data'!$A$2:$C$29,2,0) -> #N/A
D6950: 0 | E6950: =vlookup(C6950,'Master data'!$A$2:$C$29,3,0) -> #N/A | F6950: =vlookup(C6950,'Master data'!$A$2:$C$29,2,0) -> #N/A
D6951: 0 | E6951: =vlookup(C6951,'Master data'!$A$2:$C$29,3,0) -> #N/A | F6951: =vlookup(C6951,'Master data'!$A$2:$C$29,2,0) -> #N/A
D6952: 0 | E6952: =vlookup(C6952,'Master data'!$A$2:$C$29,3,0) -> #N/A | F6952: =vlookup(C6952,'Master data'!$A$2:$C$29,2,0) -> #N/A
... D7831: 0 | E7831: =vlookup(C7831,'Master data'!$A$2:$C$29,3,0) -> #N/A | F7831: =vlookup(C7831,'Master data'!$A$2:$C$29,2,0) -> #N/A

Sheet Doanh thu_San
A1: THÁNG | B1: NGÀY | C1: TIỀN MẶT | D1: CÀ THẺ | E1: THỰC NHẬN CÀ THẺ | F1: CHUYỂN KHOẢN | G1: TRẢ GÓP | H1: TRẢ CỌC | I1: TỔNG | J1: TỔNG TRỪ PHÍ CÀ THẺ
A2: 2021.01 | B2: 44197 | C2: 0 | D2: 0 | E2: 0 | F2: 0 | H2: 0 | I2: 0 | J2: 0
A3: 2021.01 | B3: 44198 | C3: 94400000 | D3: 14280000 | E3: 14059710 | F3: 0 | H3: 0 | I3: 108680000 | J3: 108459710
A4: 2021.01 | B4: 44199 | C4: 9308000 | D4: 65000000 | E4: 63903500 | F4: 10400000 | H4: 0 | I4: 84708000 | J4: 83611500
A5: 2021.01 | B5: 44200 | C5: 8401000 | D5: 0 | E5: 0 | F5: 13780000 | H5: 0 | I5: 22181000 | J5: 22181000
A6: 2021.01 | B6: 44201 | C6: 127000000 | D6: 0 | E6: 0 | F6: 45000000 | H6: 0 | I6: 172000000 | J6: 172000000
A7: 2021.01 | B7: 44202 | C7: 36650000 | D7: 40000000 | E7: 39280000 | F7: 21730000 | H7: 0 | I7: 98380000 | J7: 97660000
A8: 2021.01 | B8: 44203 | C8: 5000000 | D8: 10000000 | E8: 9815000 | F8: 0 | H8: 0 | I8: 15000000 | J8: 14815000
A9: 2021.01 | B9: 44204 | C9: 112778000 | D9: 0 | E9: 0 | F9: 10000000 | H9: 10800000 | I9: 122778000 | J9: 122778000
A10: 2021.01 | B10: 44205 | C10: 11000000 | D10: 21870000 | E10: 21476340 | F10: 0 | H10: 0 | I10: 32870000 | J10: 32476340
A11: 2021.01 | B11: 44206 | C11: 12000000 | D11: 9050000 | E11: 8888000 | F11: 37295000 | H11: 0 | I11: 58345000 | J11: 58183000
A12: 2021.01 | B12: 44207 | C12: 0 | D12: 34680000 | E12: 34461385 | F12: 100225000 | H12: 0 | I12: 134905000 | J12: 134686385
A13: 2021.01 | B13: 44208 | C13: 99360000 | D13: 40297500 | E13: 40125364 | F13: 16738000 | H13: 0 | I13: 156395500 | J13: 156223364
... A365: 2021.12 | B365: 44560 | C365: 44780000 | D365: 27180000 | E365: 27016680 | F365: 1450000 | H365: 0 | I365: 73410000 | J365: 73246680
A366: 2021.12 | B366: 44561 | C366: 31200000 | D366: 10000000 | E366: 9939760 | H366: 0 | I366: 41200000 | J366: 41139760
A367: 2022.01 | B367: 44562 | C367: 0 | D367: 0 | E367: 0 | F367: 0 | H367: 0 | I367: 0 | J367: 0
A368: 2022.01 | B368: 44563 | C368: 0 | D368: 0 | E368: 0 | F368: 0 | H368: 0 | I368: 0 | J368: 0
A369: 2022.01 | B369: 44564 | C369: 20700000 | D369: 0 | E369: 0 | F369: 0 | H369: 0 | I369: 20700000 | J369: 20700000
A370: 2022.01 | B370: 44565 | C370: 5000000 | D370: 5350000 | E370: 5317060 | F370: 42450000 | H370: 0 | I370: 52800000 | J370: 52767060
A371: 2022.01 | B371: 44566 | C371: 18930000 | D371: 630000 | E371: 619920 | F371: 70000000 | H371: 1780000 | I371: 87780000 | J371: 87769920
A372: 2022.01 | B372: 44567 | C372: 17350000 | D372: 0 | E372: 0 | F372: 0 | H372: 0 | I372: 17350000 | J372: 17350000
A373: 2022.01 | B373: 44568 | C373: 700000 | D373: 0 | E373: 0 | F373: 100745300 | H373: 10000000 | I373: 91445300 | J373: 91445300
A374: 2022.01 | B374: 44569 | C374: 10123000 | D374: 56000000 | E374: 55103360 | F374: 0 | H374: 0 | I374: 66123000 | J374: 65226360
A375: 2022.01 | B375: 44570 | C375: 2500000 | D375: 11110000 | E375: 10939000 | F375: 129000000 | H375: 0 | I375: 142610000 | J375: 142439000
A376: 2022.01 | B376: 44571 | C376: 8300000 | D376: 100000000 | E376: 98400000 | F376: 0 | H376: 0 | I376: 108300000 | J376: 106700000
A377: 2022.01 | B377: 44572 | C377: 89253000 | D377: 1550000 | E377: 1524000 | F377: 93805000 | H377: 0 | I377: 184608000 | J377: 184582000
A378: 2022.01 | B378: 44573 | C378: 0 | D378: 0 | E378: 0 | F378: 11100000 | H378: 0 | I378: 11100000 | J378: 11100000
... A392: 2022.01 | B392: 44587 | C392: 0 | D392: 0 | E392: 0 | F392: 8600000 | H392: 0 | I392: 8600000 | J392: 8600000
A393: 2022.01 | B393: 44588 | C393: 5750000 | D393: 2500000 | E393: 2458000 | F393: 5100000 | I393: 13350000 | J393: 13308000
A394: 2022.01 | B394: 44589 | C394: 0 | D394: 0 | E394: 0 | F394: 0 | H394: 0 | I394: 0 | J394: 0
A395: 2022.01 | B395: 44590 | C395: 0 | D395: 0 | E395: 0 | F395: 0 | H395: 0 | I395: 0 | J395: 0
A396: 2022.01 | B396: 44591 | C396: 0 | D396: 0 | E396: 0 | F396: 0 | H396: 0 | I396: 0 | J396: 0
A397: 2022.01 | B397: 44592 | C397: 0 | D397: 0 | E397: 0 | F397: 0 | H397: 0 | I397: 0 | J397: 0
A398: 2022.02 | B398: 44593 | C398: 0 | D398: 0 | E398: 0 | F398: 0 | H398: 0 | I398: 0 | J398: 0
A399: 2022.02 | B399: 44594 | C399: 0 | D399: 0 | E399: 0 | F399: 0 | H399: 0 | I399: 0 | J399: 0
A400: 2022.02 | B400: 44595 | C400: 0 | D400: 0 | E400: 0 | F400: 0 | H400: 0 | I400: 0 | J400: 0
A401: 2022.02 | B401: 44596 | C401: 0 | D401: 0 | E401: 0 | F401: 0 | H401: 0 | I401: 0 | J401: 0
A402: 2022.02 | B402: 44597 | C402: 0 | D402: 0 | E402: 0 | F402: 0 | H402: 0 | I402: 0 | J402: 0
A403: 2022.02 | B403: 44598 | C403: 0 | D403: 0 | E403: 0 | F403: 0 | H403: 0 | I403: 0 | J403: 0
A404: 2022.02 | B404: 44599 | C404: 0 | D404: 0 | E404: 0 | F404: 0 | H404: 0 | I404: 0 | J404: 0
A405: 2022.02 | B405: 44600 | C405: 0 | D405: 0 | E405: 0 | F405: 0 | H405: 0 | I405: 0 | J405: 0
... A425: 2022.02 | B425: 44620 | C425: 3000000 | D425: 0 | E425: 0 | F425: 60450000 | H425: 0 | I425: 63450000 | J425: 63450000
A426: 2022.02 | B426: 44620 | C426: 10500000 | I426: 10500000 | J426: 10500000
A427: 2022.03 | B427: 44621 | C427: 1350000 | D427: 2400000 | E427: 2361600 | F427: 17000000 | H427: 0 | I427: 20750000 | J427: 20711600
A428: 2022.03 | B428: 44622 | C428: 2000000 | D428: 0 | E428: 0 | F428: 27415000 | H428: 0 | I428: 29415000 | J428: 29415000
A429: 2022.03 | B429: 44623 | C429: 350000 | D429: 55640000 | E429: 54749760 | F429: 107100000 | H429: 0 | I429: 163090000 | J429: 162199760
A430: 2022.03 | B430: 44624 | C430: 8955000 | D430: 0 | E430: 0 | F430: 254660500 | H430: 0 | I430: 263615500 | J430: 263615500
A431: 2022.03 | B431: 44625 | C431: 1400000 | D431: 10800000 | E431: 10627000 | F431: 119000000 | H431: 0 | I431: 131200000 | J431: 131027000
A432: 2022.03 | B432: 44626 | C432: 78160000 | D432: 0 | E432: 0 | F432: 0 | H432: 0 | I432: 78160000 | J432: 78160000
A433: 2022.03 | B433: 44627 | C433: 19825000 | D433: 350000 | E433: 336800 | F433: 227000000 | H433: 0 | I433: 247175000 | J433: 247161800
A434: 2022.03 | B434: 44628 | C434: 8425000 | D434: 0 | E434: 0 | F434: 18000000 | H434: 0 | I434: 26425000 | J434: 26425000
A435: 2022.03 | B435: 44629 | C435: 69300000 | D435: 59350000 | E435: 58490400 | F435: 0 | H435: 0 | I435: 128650000 | J435: 127790400
A436: 2022.03 | B436: 44630 | C436: 2850000 | D436: 0 | E436: 0 | F436: 150000000 | H436: 0 | I436: 152850000 | J436: 152850000
A437: 2022.03 | B437: 44631 | C437: 7000000 | D437: 0 | E437: 0 | F437: 13000000 | H437: 4650000 | I437: 15350000 | J437: 15350000
A438: 2022.03 | B438: 44632 | C438: 13300000 | D438: 100000000 | E438: 98400000 | F438: 3000000 | H438: 0 | I438: 116300000 | J438: 114700000
... A456: 2022.03 | B456: 44650 | C456: 53945000 | D456: 50000000 | E456: 49200000 | F456: 18000000 | H456: 0 | I456: 121945000 | J456: 121145000
A457: 2022.03 | B457: 44651 | C457: 59820000 | D457: 1215000 | E457: 1195000 | H457: 0 | I457: 61035000 | J457: 61015000
A458: 2022.03 | B458: 44621 | C458: 50000000 | I458: 50000000 | J458: 50000000
A459: 2022.04 | B459: 44652 | C459: 0 | D459: 1720000 | E459: 1698480 | F459: 65940000 | H459: 1500000 | I459: 66160000 | J459: 66138480
A460: 2022.04 | B460: 44653 | C460: 16700000 | D460: 0 | E460: 0 | F460: 0 | H460: 0 | I460: 16700000 | J460: 16700000
A461: 2022.04 | B461: 44654 | C461: 3350000 | D461: 1174500 | E461: 1155300 | F461: 0 | H461: 0 | I461: 4524500 | J461: 4505300
A462: 2022.04 | B462: 44655 | C462: 15500000 | D462: 125758000 | E462: 123745872 | F462: 33100000 | H462: 0 | I462: 174358000 | J462: 172345872
A463: 2022.04 | B463: 44656 | C463: 15140000 | D463: 54988000 | E463: 54108000 | F463: 93850000 | H463: 2000000 | I463: 161978000 | J463: 161098000
A464: 2022.04 | B464: 44657 | C464: 19184000 | D464: 0 | E464: 0 | F464: 20000000 | H464: 0 | I464: 39184000 | J464: 39184000
A465: 2022.04 | B465: 44658 | C465: 31714000 | D465: 0 | E465: 0 | F465: 43000000 | H465: 0 | I465: 74714000 | J465: 74714000
A466: 2022.04 | B466: 44659 | C466: 2700000 | D466: 1600000 | E466: 1590000 | F466: 25900000 | H466: 0 | I466: 30200000 | J466: 30190000
A467: 2022.04 | B467: 44660 | C467: 2150000 | D467: 25000000 | E467: 24850000 | F467: 500000 | H467: 0 | I467: 27650000 | J467: 27500000
A468: 2022.04 | B468: 44661 | C468: 0 | D468: 0 | E468: 0 | F468: 0 | H468: 0 | I468: 0 | J468: 0
A469: 2022.04 | B469: 44662 | C469: 0 | D469: 0 | E469: 0 | F469: 0 | H469: 0 | I469: 0 | J469: 0
A470: 2022.04 | B470: 44663 | C470: 5602500 | D470: 2400000 | E470: 2385000 | F470: 0 | H470: 0 | I470: 8002500 | J470: 7987500
... A549: 2022.06 | B549: 44742 | C549: 29654500 | D549: 0 | E549: 0 | F549: 19200000 | H549: 0 | I549: 48854500 | J549: 48854500
A550: 2022.06 | B550: 44713 | C550: 7955000 | I550: 7955000 | J550: 7955000
A551: 2022.07 | B551: 44743 | C551: 0 | D551: 0 | E551: 0 | F551: 100000000 | H551: 0 | I551: 100000000 | J551: 100000000
A552: 2022.07 | B552: 44744 | C552: 350000 | D552: 0 | E552: 0 | F552: 35000000 | H552: 0 | I552: 35350000 | J552: 35350000
A553: 2022.07 | B553: 44745 | C553: 25000000 | D553: 0 | E553: 0 | F553: 7000000 | H553: 0 | I553: 32000000 | J553: 32000000
A554: 2022.07 | B554: 44746 | C554: 0 | D554: 2500000 | E554: 2460000 | F554: 123200000 | H554: 0 | I554: 125700000 | J554: 125660000
A555: 2022.07 | B555: 44747 | C555: 30000000 | D555: 0 | E555: 0 | F555: 0 | H555: 0 | I555: 30000000 | J555: 30000000
A556: 2022.07 | B556: 44748 | C556: 1250000 | D556: 5450000 | E556: 5362800 | F556: 81000000 | H556: 0 | I556: 87700000 | J556: 87612800
A557: 2022.07 | B557: 44749 | C557: 44925000 | D557: 0 | E557: 0 | F557: 225000000 | H557: 25000000 | I557: 244925000 | J557: 244925000
A558: 2022.07 | B558: 44750 | C558: 163100000 | D558: 8464000 | E558: 8413216 | F558: 71000000 | H558: 0 | I558: 242564000 | J558: 242513216
A559: 2022.07 | B559: 44751 | C559: 14676000 | D559: 1040000 | E559: 1023360 | F559: 21800000 | H559: 0 | I559: 37516000 | J559: 37499360
A560: 2022.07 | B560: 44752 | C560: 1850000 | D560: 0 | E560: 0 | F560: 1850000 | H560: 0 | I560: 3700000 | J560: 3700000
A561: 2022.07 | B561: 44753 | C561: 287454000 | D561: 46000000 | E561: 45654000 | F561: 100500000 | H561: 0 | I561: 433954000 | J561: 433608000
A562: 2022.07 | B562: 44754 | C562: 42800000 | D562: 0 | E562: 0 | F562: 0 | H562: 0 | I562: 42800000 | J562: 42800000
... A765: 2023.01 | B765: 44957 | C765: 0 | D765: 0 | E765: 0 | F765: 0 | H765: 0 | I765: 0 | J765: 0
A766: 2023.01 | B766: 44957 | C766: 15470000 | I766: 15470000 | J766: 15470000
A767: 2023.02 | B767: 44958 | C767: 172000000 | D767: 9350000 | E767: 9250400 | F767: 130000000 | H767: 0 | I767: 311350000 | J767: 311250400
A768: 2023.02 | B768: 44959 | C768: 34350000 | D768: 21350000 | E768: 20906400 | F768: 20300000 | H768: 0 | I768: 76000000 | J768: 75556400
A769: 2023.02 | B769: 44960 | C769: 203737000 | D769: 500000 | E769: 492000 | F769: 179200000 | H769: 1700000 | I769: 381737000 | J769: 381729000
A770: 2023.02 | B770: 44961 | C770: 110000000 | D770: 107997000 | E770: 106269000 | F770: 28550000 | H770: 0 | I770: 246547000 | J770: 244819000
A771: 2023.02 | B771: 44962 | C771: 87350000 | D771: 2000000 | E771: 1956000 | F771: 134965000 | H771: 0 | I771: 224315000 | J771: 224271000
A772: 2023.02 | B772: 44963 | C772: 84153000 | D772: 12850000 | E772: 12743400 | F772: 217645000 | H772: 0 | I772: 314648000 | J772: 314541400
A773: 2023.02 | B773: 44964 | C773: 125820000 | D773: 110430000 | E773: 108670369 | F773: 153328000 | H773: 0 | I773: 389578000 | J773: 387818369
A774: 2023.02 | B774: 44965 | C774: 163450500 | D774: 48236000 | E774: 47656584 | F774: 39050000 | H774: 0 | I774: 250736500 | J774: 250157084
A775: 2023.02 | B775: 44966 | C775: 95415000 | D775: 4900000 | E775: 4821600 | F775: 0 | H775: 12420000 | I775: 87895000 | J775: 87816600
A776: 2023.02 | B776: 44967 | C776: 93500000 | D776: 49350000 | E776: 48560400 | F776: 74300000 | H776: 8145000 | I776: 209005000 | J776: 208215400
A777: 2023.02 | B777: 44968 | C777: 79276000 | D777: 6100000 | E777: 6038400 | F777: 2350000 | H777: 0 | I777: 87726000 | J777: 87664400
A778: 2023.02 | B778: 44969 | C778: 6200000 | D778: 38400000 | E778: 38188800 | F778: 104100000 | H778: 0 | I778: 148700000 | J778: 148488800
... A794: 2023.02 | B794: 44985 | C794: 174149000 | D794: 40000000 | E794: 39260000 | F794: 6191000 | H794: 0 | I794: 220340000 | J794: 219600000
A795: 2023.02 | B795: 44958 | C795: 143300000 | I795: 143300000 | J795: 143300000
...

Sheet Lương_SAN
A1: Tháng | B1: ID | C1: Chức danh | D1: Họ và Tên | E1: LCB | F1: Năng lực | G1: Thâm niên | H1: Kiêm việc | I1: Trợ cấp | J1: Công chuẩn | K1: Công thực tế | L1: Số giờ tăng ca | M1: Tiền tăng ca | N1: Khấu trừ | O1: Tạm ứng | P1: KPI công việc | Q1: KPI doanh số 15 | R1: Lương cứng | S1: Tổng lương | T1: Thực nhận | U1: Cột 21
A2: 2024.01 | B2: BS01 | C2: =iferror(vlookup($B2,Master_data!$K$1:$M$190,3,0),"--") -> Bác sĩ | D2: =iferror(vlookup($B2,Master_data!$K$1:$M$190,2,0),"--") -> BS Công | E2: 25000000 | F2: 0 | G2: 0 | H2: 0 | I2: 0 | J2: 22 | K2: 24 | L2: 0 | M2: 0 | N2: 0 | P2: 0 | Q2: 107565816 | S2: 29790210 | T2: 137356026
A3: 2024.01 | B3: BS02 | C3: =iferror(vlookup($B3,Master_data!$K$1:$M$190,3,0),"--") -> Bác sĩ | D3: =iferror(vlookup($B3,Master_data!$K$1:$M$190,2,0),"--") -> Bs Phong | E3: 15000000 | F3: 0 | G3: 0 | H3: 0 | I3: 0 | J3: 26 | K3: 25 | L3: 0 | M3: 0 | N3: 0 | P3: 0 | Q3: 47337895 | S3: 14423077 | T3: 61760972
A4: 2024.01 | B4: BS03 | C4: =iferror(vlookup($B4,Master_data!$K$1:$M$190,3,0),"--") -> Bác sĩ | D4: =iferror(vlookup($B4,Master_data!$K$1:$M$190,2,0),"--") -> Bs Tú | E4: 15000000 | F4: 0 | G4: 0 | H4: 0 | I4: 0 | J4: 26 | K4: 27.5 | L4: 0 | M4: 0 | N4: 0 | P4: 0 | Q4: 103537080 | S4: 15865385 | T4: 119402465
A5: 2024.01 | B5: BS04 | C5: =iferror(vlookup($B5,Master_data!$K$1:$M$190,3,0),"--") -> Bác sĩ | D5: =iferror(vlookup($B5,Master_data!$K$1:$M$190,2,0),"--") -> Bs Dũng | E5: 0 | F5: 0 | G5: 0 | H5: 0 | I5: 0 | J5: 0 | K5: 0 | L5: 0 | M5: 0 | N5: 0 | P5: 0 | Q5: 152200000 | S5: 0 | T5: 152200000
A6: 2024.01 | B6: PT01 | C6: =iferror(vlookup($B6,Master_data!$K$1:$M$190,3,0),"--") -> Phụ tá | D6: =iferror(vlookup($B6,Master_data!$K$1:$M$190,2,0),"--") -> PT Ngọc Tiên | E6: 5000000 | F6: 500000 | G6: 0 | H6: 0 | I6: 300000 | J6: 26 | K6: 32.5 | L6: 0 | M6: 0 | N6: 0 | P6: 0 | Q6: 5300000 | S6: 8550000 | T6: 13850000
A7: 2024.01 | B7: PT02 | C7: =iferror(vlookup($B7,Master_data!$K$1:$M$190,3,0),"--") -> Phụ tá | D7: =iferror(vlookup($B7,Master_data!$K$1:$M$190,2,0),"--") -> PT Cẩm Tiên | E7: 5000000 | F7: 500000 | G7: 0 | H7: 500000 | I7: 300000 | J7: 26 | K7: 27.965 | L7: 0 | M7: 0 | N7: 525840 | P7: 1500000 | Q7: 4235000 | S7: 7652045 | T7: 12412885
A8: 2024.01 | B8: PT03 | C8: =iferror(vlookup($B8,Master_data!$K$1:$M$190,3,0),"--") -> Phụ tá | D8: =iferror(vlookup($B8,Master_data!$K$1:$M$190,2,0),"--") -> PT Ly | E8: 5000000 | F8: 1000000 | G8: 1000000 | H8: 0 | I8: 300000 | J8: 26 | K8: 31.8 | L8: 0 | M8: 0 | N8: 525840 | P8: 1500000 | Q8: 6075000 | S8: 9389545 | T8: 15990385
A9: 2024.01 | B9: PT04 | C9: =iferror(vlookup($B9,Master_data!$K$1:$M$190,3,0),"--") -> Phụ tá | D9: =iferror(vlookup($B9,Master_data!$K$1:$M$190,2,0),"--") -> PT Kha | E9: 5000000 | F9: 1000000 | G9: 0 | H9: 0 | I9: 300000 | J9: 26 | K9: 28.68 | L9: 0 | M9: 0 | N9: 0 | P9: 1500000 | Q9: 3790000 | S9: 8315385 | T9: 12105385
A10: 2024.01 | B10: PT05 | C10: =iferror(vlookup($B10,Master_data!$K$1:$M$190,3,0),"--") -> Phụ tá | D10: =iferror(vlookup($B10,Master_data!$K$1:$M$190,2,0),"--") -> PT Kiều | E10: 6800000 | F10: 0 | G10: 0 | H10: 0 | I10: 0 | J10: 26 | K10: 27.0625 | L10: 0 | M10: 0 | N10: 0 | P10: 1500000 | Q10: 1110000 | S10: 7148317 | T10: 8258317
A11: 2024.01 | B11: PT06 | C11: =iferror(vlookup($B11,Master_data!$K$1:$M$190,3,0),"--") -> Phụ tá | D11: =iferror(vlookup($B11,Master_data!$K$1:$M$190,2,0),"--") -> PT Trân | E11: 7650000 | F11: 0 | G11: 0 | H11: 0 | I11: 0 | J11: 26 | K11: 28.206 | L11: 0 | M11: 0 | N11: 0 | P11: -200000 | Q11: 0 | S11: 8249073 | T11: 8249073
A12: 2024.01 | B12: LT01 | C12: =iferror(vlookup($B12,Master_data!$K$1:$M$190,3,0),"--") -> Lễ tân | D12: =iferror(vlookup($B12,Master_data!$K$1:$M$190,2,0),"--") -> LT Quỳnh Như | E12: 3500000 | F12: 2500000 | G12: 0 | H12: 0 | I12: 300000 | J12: 26 | K12: 26 | L12: 0 | M12: 0 | N12: 5525840 | P12: -50000 | Q12: 2196062 | S12: 774160 | T12: 8496062
A13: 2024.01 | B13: LT02 | C13: =iferror(vlookup($B13,Master_data!$K$1:$M$190,3,0),"--") -> Lễ tân | D13: =iferror(vlookup($B13,Master_data!$K$1:$M$190,2,0),"--") -> LT Kim Ngân | E13: 2500000 | F13: 1000000 | G13: 0 | H13: 0 | I13: 150000 | J13: 26 | K13: 26.3125 | L13: 0 | M13: 0 | N13: 5525840 | P13: 0 | Q13: 2196062 | S13: -1170792 | T13: 6551110
... A47: 2024.02 | B47: BS04 | C47: =iferror(vlookup($B47,Master_data!$K$1:$M$190,3,0),"--") -> Bác sĩ | D47: =iferror(vlookup($B47,Master_data!$K$1:$M$190,2,0),"--") -> Bs Dũng | E47: 0 | F47: 0 | G47: 0 | H47: 0 | I47: 0 | J47: 0 | K47: 0 | L47: 0 | M47: 0 | N47: 0 | P47: 0 | Q47: 0 | S47: 0 | T47: 0
A48: 2024.02 | B48: PT01 | C48: =iferror(vlookup($B48,Master_data!$K$1:$M$190,3,0),"--") -> Phụ tá | D48: =iferror(vlookup($B48,Master_data!$K$1:$M$190,2,0),"--") -> PT Ngọc Tiên | E48: 5000000 | F48: 500000 | G48: 0 | H48: 0 | I48: 300000 | J48: 26 | K48: 25.75 | L48: 16.4 | M48: 394231 | P48: 1500000 | Q48: 2465000 | S48: 7646154 | T48: 10111154
A49: 2024.02 | B49: PT02 | C49: =iferror(vlookup($B49,Master_data!$K$1:$M$190,3,0),"--") -> Phụ tá | D49: =iferror(vlookup($B49,Master_data!$K$1:$M$190,2,0),"--") -> PT Cẩm Tiên | E49: 5000000 | F49: 500000 | G49: 0 | H49: 500000 | I49: 300000 | J49: 26 | K49: 26 | L49: 9.7 | M49: 233173 | N49: 525840 | P49: 1500000 | Q49: 1310000 | S49: 7507333 | T49: 9343173
A50: 2024.02 | B50: PT03 | C50: =iferror(vlookup($B50,Master_data!$K$1:$M$190,3,0),"--") -> Phụ tá | D50: =iferror(vlookup($B50,Master_data!$K$1:$M$190,2,0),"--") -> PT Ly | E50: 5000000 | F50: 1000000 | G50: 1000000 | I50: 300000 | J50: 26 | K50: 26 | L50: 14.65 | M50: 352163 | N50: 525840 | P50: 1500000 | Q50: 2200000 | S50: 8626323 | T50: 11352163
A51: 2024.02 | B51: PT04 | C51: =iferror(vlookup($B51,Master_data!$K$1:$M$190,3,0),"--") -> Phụ tá | D51: =iferror(vlookup($B51,Master_data!$K$1:$M$190,2,0),"--") -> PT Kha | E51: 5000000 | F51: 1000000 | I51: 300000 | J51: 26 | K51: 22.70625 | L51: 8.1 | M51: 194712 | P51: 1500000 | Q51: 2490000 | S51: 7361298 | T51: 9851298
A52: 2024.02 | B52: PT05 | C52: =iferror(vlookup($B52,Master_data!$K$1:$M$190,3,0),"--") -> Phụ tá | D52: =iferror(vlookup($B52,Master_data!$K$1:$M$190,2,0),"--") -> PT Kiều | E52: 6800000 | F52: 500000 | I52: 300000 | J52: 26 | K52: 22.875 | L52: 9.4 | M52: 225962 | P52: 1500000 | Q52: 1560000 | S52: 6925000 | T52: 8485000
A53: 2024.02 | B53: PT06 | C53: =iferror(vlookup($B53,Master_data!$K$1:$M$190,3,0),"--") -> Phụ tá | D53: =iferror(vlookup($B53,Master_data!$K$1:$M$190,2,0),"--") -> PT Trân | E53: 7650000 | F53: 500000 | G53: 0 | H53: 0 | I53: 300000 | J53: 26 | K53: 23.1375 | L53: 10.8 | M53: 259615 | P53: 1500000 | Q53: 1255000 | S53: 7009135 | T53: 8264135
A54: 2024.02 | B54: LT01 | C54: =iferror(vlookup($B54,Master_data!$K$1:$M$190,3,0),"--") -> Lễ tân | D54: =iferror(vlookup($B54,Master_data!$K$1:$M$190,2,0),"--") -> LT Quỳnh Như | E54: 3500000 | F54: 2500000 | G54: 0 | H54: 0 | I54: 300000 | J54: 26 | K54: 24.5 | L54: 0 | M54: 0 | N54: 2525840 | P54: 0 | Q54: 544458 | S54: 3572237 | T54: 6642535
A55: 2024.02 | B55: LT02 | C55: =iferror(vlookup($B55,Master_data!$K$1:$M$190,3,0),"--") -> Lễ tân | D55: =iferror(vlookup($B55,Master_data!$K$1:$M$190,2,0),"--") -> LT Kim Ngân | E55: 2500000 | F55: 1000000 | G55: 0 | H55: 0 | I55: 150000 | J55: 26 | K55: 22.5 | L55: 5 | M55: 60096 | N55: 525840 | P55: 725000 | Q55: 544458 | S55: 3572718 | T55: 4643016
A56: 2024.02 | B56: LT04 | C56: =iferror(vlookup($B56,Master_data!$K$1:$M$190,3,0),"--") -> Lễ tân | D56: =iferror(vlookup($B56,Master_data!$K$1:$M$190,2,0),"--") -> Lt Tú Nhi | E56: 2500000 | F56: 750000 | G56: 0 | H56: 0 | I56: 150000 | J56: 26 | K56: 26 | L56: 4 | M56: 48077 | N56: 525840 | P56: 725000 | Q56: 544458 | S56: 3647237 | T56: 4717535
A57: 2024.02 | B57: LT05 | C57: =iferror(vlookup($B57,Master_data!$K$1:$M$190,3,0),"--") -> Lễ tân | D57: =iferror(vlookup($B57,Master_data!$K$1:$M$190,2,0),"--") -> LT Văn Tính | E57: 2500000 | F57: 750000 | G57: 0 | H57: 0 | I57: 150000 | J57: 26 | K57: 25.75 | L57: 4 | M57: 48077 | N57: 525840 | P57: 700000 | Q57: 544458 | S57: 3598198 | T57: 4668496
A58: 2024.02 | B58: TV00 | C58: =iferror(vlookup($B58,Master_data!$K$1:$M$190,3,0),"--") -> Tư vấn | D58: =iferror(vlookup($B58,Master_data!$K$1:$M$190,2,0),"--") -> TV Đông | E58: 2500000 | F58: 500000 | G58: 0 | H58: 0 | I58: 150000 | J58: 26 | K58: 24.22 | L58: 0 | M58: 0 | N58: 525840 | P58: 50000 | Q58: 5628279 | S58: 2503006 | T58: 8657125
A59: 2024.02 | B59: TV01 | C59: =iferror(vlookup($B59,Master_data!$K$1:$M$190,3,0),"--") -> Tư vấn | D59: =iferror(vlookup($B59,Master_data!$K$1:$M$190,2,0),"--") -> Tv Na | E59: 2500000 | F59: 500000 | G59: 0 | H59: 0 | I59: 150000 | J59: 26 | K59: 24.85 | L59: 5.7 | M59: 68510 | N59: 525840 | P59: 50000 | Q59: 5121267 | S59: 2632093 | T59: 8279200
A60: 2024.02 | B60: TV03 | C60: =iferror(vlookup($B60,Master_data!$K$1:$M$190,3,0),"--") -> Telesale | D60: =iferror(vlookup($B60,Master_data!$K$1:$M$190,2,0),"--") -> Telesale Bí Nhi | E60: 1666667 | F60: 333333 | G60: 0 | H60: 0 | I60: 100000 | J60: 26 | K60: 34 | L60: 0 | M60: 0 | N60: 525840 | P60: -100000 | Q60: 6379914 | S60: 1986981 | T60: 8892735
A61: 2024.02 | B61: TV04 | C61: =iferror(vlookup($B61,Master_data!$K$1:$M$190,3,0),"--") -> Telesale | D61: =iferror(vlookup($B61,Master_data!$K$1:$M$190,2,0),"--") -> Telesale Yến | E61: 1666667 | F61: 333333 | G61: 0 | H61: 0 | I61: 100000 | J61: 26 | K61: 31.5 | L61: 0 | M61: 0 | P61: -50000 | Q61: 5866132 | S61: 2402564 | T61: 8268696
A62: 2024.02 | B62: TV05 | C62: =iferror(vlookup($B62,Master_data!$K$1:$M$190,3,0),"--") -> Telesale | D62: =iferror(vlookup($B62,Master_data!$K$1:$M$190,2,0),"--") -> Telesale Uyển Nhi | E62: 3333333 | F62: 0 | G62: 0 | H62: 0 | I62: 0 | J62: 26 | K62: 26 | L62: 0 | M62: 0 | N62: 525840 | P62: 0 | Q62: 0 | S62: 2807493 | T62: 3333333
A63: 2024.02 | B63: VP02 | C63: =iferror(vlookup($B63,Master_data!$K$1:$M$190,3,0),"--") -> Văn phòng | D63: =iferror(vlookup($B63,Master_data!$K$1:$M$190,2,0),"--") -> Anh Hiền | E63: 20333333 | F63: 0 | G63: 0 | H63: 0 | I63: 0 | J63: 26 | K63: 26 | L63: 0 | M63: 0 | N63: 333333 | P63: 0 | Q63: 0 | S63: 20000000 | T63: 20333333
A64: 2024.02 | B64: VP03 | C64: =iferror(vlookup($B64,Master_data!$K$1:$M$190,3,0),"--") -> Văn phòng | D64: =iferror(vlookup($B64,Master_data!$K$1:$M$190,2,0),"--") -> Hiến | E64: 18333333 | F64: 0 | G64: 0 | H64: 0 | I64: 0 | J64: 26 | K64: 26 | L64: 0 | M64: 0 | N64: 525840 | P64: 0 | Q64: 0 | S64: 17807493 | T64: 18333333
A65: 2024.02 | B65: VP04 | C65: =iferror(vlookup($B65,Master_data!$K$1:$M$190,3,0),"--") -> Văn phòng | D65: =iferror(vlookup($B65,Master_data!$K$1:$M$190,2,0),"--") -> Chị Phượng | E65: 15000000 | F65: 0 | G65: 0 | H65: 0 | I65: 0 | J65: 26 | K65: 26 | L65: 0 | M65: 0 | N65: 1383333 | P65: 0 | Q65: 0 | S65: 13616667 | T65: 15000000
A66: 2024.02 | B66: VP05 | C66: =iferror(vlookup($B66,Master_data!$K$1:$M$190,3,0),"--") -> Văn phòng | D66: =iferror(vlookup($B66,Master_data!$K$1:$M$190,2,0),"--") -> Duyên HCNS | E66: 5333333 | F66: 0 | G66: 0 | H66: 0 | I66: 0 | J66: 26 | K66: 26 | L66: 0 | M66: 0 | N66: 333333 | P66: 0 | Q66: 0 | S66: 5000000 | T66: 5333333
A67: 2024.02 | B67: VP06 | C67: =iferror(vlookup($B67,Master_data!$K$1:$M$190,3,0),"--") -> Văn phòng | D67: =iferror(vlookup($B67,Master_data!$K$1:$M$190,2,0),"--") -> Kiểm soát Ngọc Lệ | E67: 6000000 | F67: 0 | G67: 0 | H67: 0 | I67: 0 | J67: 26 | K67: 26 | L67: 0 | M67: 0 | N67: 525840 | P67: 0 | Q67: 0 | S67: 5474160 | T67: 6000000
A68: 2024.02 | B68: VP07 | C68: =iferror(vlookup($B68,Master_data!$K$1:$M$190,3,0),"--") -> Văn phòng | D68: =iferror(vlookup($B68,Master_data!$K$1:$M$190,2,0),"--") -> Kim Hồng | E68: 4166667 | F68: 0 | G68: 0 | H68: 0 | I68: 0 | J68: 26 | K68: 23.5 | L68: 0 | M68: 0 | N68: 0 | P68: 0 | Q68: 527778 | S68: 3766026 | T68: 4293803
A69: 2024.02 | B69: VP08 | C69: =iferror(vlookup($B69,Master_data!$K$1:$M$190,3,0),"--") -> Văn phòng | D69: =iferror(vlookup($B69,Master_data!$K$1:$M$190,2,0),"--") -> Nhi (ngoc nhi 2727) | E69: 2666667 | F69: 0 | G69: 0 | H69: 0 | I69: 0 | J69: 26 | K69: 26 | L69: 0 | M69: 0 | N69: 0 | P69: 0 | Q69: 0 | S69: 2666667 | T69: 2666667
A70: 2024.02 | B70: VP09 | C70: =iferror(vlookup($B70,Master_data!$K$1:$M$190,3,0),"--") -> Marketing | D70: =iferror(vlookup($B70,Master_data!$K$1:$M$190,2,0),"--") -> MKT Minh Lâm | E70: 6666667 | F70: 0 | G70: 0 | H70: 0 | I70: 0 | J70: 26 | K70: 24 | L70: 0 | M70: 0 | N70: 630000 | P70: 0 | Q70: 0 | S70: 5523846 | T70: 6153846
A71: 2024.02 | B71: VP10 | C71: =iferror(vlookup($B71,Master_data!$K$1:$M$190,3,0),"--") -> Marketing | D71: =iferror(vlookup($B71,Master_data!$K$1:$M$190,2,0),"--") -> MKT Bông | E71: 8333333 | F71: 0 | G71: 0 | H71: 0 | I71: 0 | J71: 26 | K71: 26 | L71: 0 | M71: 0 | N71: 735000 | P71: 0 | Q71: 0 | S71: 7598333 | T71: 8333333
A72: 2024.02 | B72: VP11 | C72: =iferror(vlookup($B72,Master_data!$K$1:$M$190,3,0),"--") -> Marketing | D72: =iferror(vlookup($B72,Master_data!$K$1:$M$190,2,0),"--") -> Trung Hào | E72: 4000000 | F72: 0 | G72: 0 | H72: 0 | I72: 0 | J72: 26 | K72: 25.875 | L72: 16.75 | M72: 322115 | N72: 5000000 | P72: 0 | Q72: 808889 | S72: -697115 | T72: 5111774
A73: 2024.02 | B73: VP12 | C73: =iferror(vlookup($B73,Master_data!$K$1:$M$190,3,0),"--") -> Marketing | D73: =iferror(vlookup($B73,Master_data!$K$1:$M$190,2,0),"--") -> Chụp hình Hùng | E73: 4333333 | F73: 0 | G73: 0 | H73: 0 | I73: 0 | J73: 26 | K73: 26 | L73: 6 | M73: 125000 | N73: 0 | P73: 0 | Q73: 785556 | S73: 4458333 | T73: 5243889
... A75: 2024.02 | B75: VP14 | C75: =iferror(vlookup($B75,Master_data!$K$1:$M$190,3,0),"--") -> Marketing | D75: =iferror(vlookup($B75,Master_data!$K$1:$M$190,2,0),"--") -> MKT Anh TRung | E75: 8333333 | F75: 0 | G75: 0 | H75: 0 | I75: 0 | J75: 26 | K75: 24.5 | L75: 0 | M75: 0 | N75: 0 | P75: 0 | Q75: 0 | S75: 7852564 | T75: 7852564
A76: 2024.02 | B76: VP16 | C76: =iferror(vlookup($B76,Master_data!$K$1:$M$190,3,0),"--") -> Văn phòng | D76: =iferror(vlookup($B76,Master_data!$K$1:$M$190,2,0),"--") -> Bảo Nghi | E76: 3966667 | F76: 0 | G76: 0 | H76: 0 | I76: 0 | J76: 26 | K76: 4 | M76: 0 | S76: 610256 | T76: 610256
A77: 2024.02 | B77: VP15 | C77: =iferror(vlookup($B77,Master_data!$K$1:$M$190,3,0),"--") -> Văn phòng | D77: =iferror(vlookup($B77,Master_data!$K$1:$M$190,2,0),"--") -> Kế toán + thuế | E77: 12000000 | F77: 0 | G77: 0 | H77: 0 | I77: 0 | J77: 26 | K77: 26 | M77: 0 | S77: 12000000 | T77: 12000000
A78: 2024.02 | B78: K01 | C78: =iferror(vlookup($B78,Master_data!$K$1:$M$190,3,0),"--") -> Sảnh + bếp | D78: =iferror(vlookup($B78,Master_data!$K$1:$M$190,2,0),"--") -> GV Hiền | E78: 2100000 | F78: 566667 | G78: 0 | H78: 0 | I78: 0 | J78: 26 | K78: 26 | M78: 0 | S78: 2666667 | T78: 2666667
A79: 2024.02 | B79: K02 | C79: =iferror(vlookup($B79,Master_data!$K$1:$M$190,3,0),"--") -> Sảnh + bếp | D79: =iferror(vlookup($B79,Master_data!$K$1:$M$190,2,0),"--") -> Chị Trang | E79: 2100000 | F79: 566667 | G79: 0 | H79: 0 | I79: 0 | J79: 26 | K79: 26 | L79: 9.5 | M79: 95913 | N79: 525840 | S79: 2236740 | T79: 2762580
A80: 2024.02 | B80: K03 | C80: =iferror(vlookup($B80,Master_data!$K$1:$M$190,3,0),"--") -> Sảnh + bếp | D80: =iferror(vlookup($B80,Master_data!$K$1:$M$190,2,0),"--") -> Chị Trang VP | E80: 666667 | G80: 0 | H80: 0 | I80: 0 | J80: 26 | K80: 26 | M80: 0 | S80: 666667 | T80: 666667
A81: 2024.02 | B81: K04 | C81: =iferror(vlookup($B81,Master_data!$K$1:$M$190,3,0),"--") -> Sảnh + bếp | D81: =iferror(vlookup($B81,Master_data!$K$1:$M$190,2,0),"--") -> GV Linh | E81: 2666667 | G81: 0 | H81: 0 | I81: 0 | J81: 26 | K81: 25.75 | L81: 0.5 | M81: 6410 | N81: 525840 | S81: 2121596 | T81: 2647436
A82: 2024.02 | B82: K05 | C82: =iferror(vlookup($B82,Master_data!$K$1:$M$190,3,0),"--") -> Sảnh + bếp | D82: =iferror(vlookup($B82,Master_data!$K$1:$M$190,2,0),"--") -> BV Trung | E82: 3666667 | F82: 0 | G82: 0 | H82: 0 | I82: 0 | J82: 28 | K82: 26 | L82: 11 | M82: 180060 | P82: 216667 | S82: 3801488 | T82: 3801488
A83: 2024.02 | B83: K06 | C83: =iferror(vlookup($B83,Master_data!$K$1:$M$190,3,0),"--") -> Sảnh + bếp | D83: =iferror(vlookup($B83,Master_data!$K$1:$M$190,2,0),"--") -> BV Cang | E83: 3666667 | F83: 0 | G83: 0 | H83: 0 | I83: 0 | J83: 28 | K83: 26 | L83: 10.5 | M83: 171875 | N83: 525840 | S83: 3050797 | T83: 3576637
A84: 2024.02 | B84: K07 | C84: =iferror(vlookup($B84,Master_data!$K$1:$M$190,3,0),"--") -> Sảnh + bếp | D84: =iferror(vlookup($B84,Master_data!$K$1:$M$190,2,0),"--") -> TX Đức | E84: 5500000 | F84: 0 | G84: 0 | H84: 0 | I84: 0 | J84: 28 | K84: 26 | L84: 25.65 | M84: 629799 | S84: 5736942 | T84: 5736942
A85: 2024.02 | B85: K08 | C85: =iferror(vlookup($B85,Master_data!$K$1:$M$190,3,0),"--") -> Sảnh + bếp | D85: =iferror(vlookup($B85,Master_data!$K$1:$M$190,2,0),"--") -> TX Oanh | E85: 5000000 | J85: 28 | K85: 26 | L85: 33.65 | M85: 751116 | S85: 5393973 | T85: 5393973
A86: 2024.03 | B86: BS01 | C86: =iferror(vlookup($B86,Master_data!$K$1:$M$190,3,0),"--") -> Bác sĩ | D86: =iferror(vlookup($B86,Master_data!$K$1:$M$190,2,0),"--") -> BS Công | E86: 35000000 | F86: 0 | G86: 0 | H86: 0 | I86: 0 | J86: 26 | K86: 24.7375 | L86: 1 | M86: 168269 | P86: 0 | Q86: 128837600 | S86: 33468750 | T86: 162306350
A87: 2024.03 | B87: BS02 | C87: =iferror(vlookup($B87,Master_data!$K$1:$M$190,3,0),"--") -> Bác sĩ | D87: =iferror(vlookup($B87,Master_data!$K$1:$M$190,2,0),"--") -> Bs Phong | E87: 15000000 | F87: 0 | G87: 0 | H87: 0 | I87: 0 | J87: 26 | K87: 8.28125 | M87: 0 | P87: 0 | Q87: 4176650 | S87: 4777644 | T87: 8954294
A88: 2024.03 | B88: BS03 | C88: =iferror(vlookup($B88,Master_data!$K$1:$M$190,3,0),"--") -> Bác sĩ | D88: =iferror(vlookup($B88,Master_data!$K$1:$M$190,2,0),"--") -> Bs Tú | E88: 15000000 | J88: 26 | K88: 26 | M88: 0 | Q88: 40304250 | S88: 15000000 | T88: 55304250
A89: 2024.03 | B89: BS05 | C89: =iferror(vlookup($B89,Master_data!$K$1:$M$190,3,0),"--") -> Bác sĩ | D89: =iferror(vlookup($B89,Master_data!$K$1:$M$190,2,0),"--") -> Bs Hải Anh | E89: 25000000 | F89: 0 | G89: 0 | H89: 0 | I89: 0 | J89: 26 | K89: 26 | P89: 0 | Q89: 0 | S89: 25000000 | T89: 25000000
A90: 2024.03 | B90: VP01 | C90: =iferror(vlookup($B90,Master_data!$K$1:$M$190,3,0),"--") -> Văn phòng | D90: =iferror(vlookup($B90,Master_data!$K$1:$M$190,2,0),"--") -> Lương 3CĐ | E90: 8500000 | J90: 26 | K90: 18.5 | Q90: 0 | S90: 6048077 | T90: 6048077
A91: 2024.03 | B91: PT01 | C91: =iferror(vlookup($B91,Master_data!$K$1:$M$190,3,0),"--") -> Phụ tá | D91: =iferror(vlookup($B91,Master_data!$K$1:$M$190,2,0),"--") -> PT Ngọc Tiên | E91: 5000000 | F91: 500000 | G91: 0 | H91: 0 | I91: 300000 | J91: 26 | K91: 26.1875 | L91: 24.65 | M91: 592548 | P91: 1350000 | Q91: 3830000 | S91: 7778606 | T91: 11608606
A92: 2024.03 | B92: PT02 | C92: =iferror(vlookup($B92,Master_data!$K$1:$M$190,3,0),"--") -> Phụ tá | D92: =iferror(vlookup($B92,Master_data!$K$1:$M$190,2,0),"--") -> PT Cẩm Tiên | E92: 5000000 | F92: 500000 | G92: 0 | H92: 500000 | I92: 300000 | J92: 26 | K92: 25.9875 | L92: 17.5 | M92: 420673 | N92: 525840 | P92: 1500000 | Q92: 2185000 | S92: 7692429 | T92: 10403269
A93: 2024.03 | B93: PT03 | C93: =iferror(vlookup($B93,Master_data!$K$1:$M$190,3,0),"--") -> Phụ tá | D93: =iferror(vlookup($B93,Master_data!$K$1:$M$190,2,0),"--") -> PT Ly | E93: 5000000 | F93: 1000000 | G93: 1000000 | I93: 300000 | J93: 26 | K93: 25.875 | L93: 18.05 | M93: 433894 | N93: 525840 | P93: 1500000 | Q93: 4180000 | S93: 8684016 | T93: 13389856
A94: 2024.03 | B94: PT04 | C94: =iferror(vlookup($B94,Master_data!$K$1:$M$190,3,0),"--") -> Phụ tá | D94: =iferror(vlookup($B94,Master_data!$K$1:$M$190,2,0),"--") -> PT Kha | E94: 5000000 | F94: 1000000 | I94: 300000 | J94: 26 | K94: 25.575 | L94: 18.7 | M94: 449519 | P94: 1500000 | Q94: 3490000 | S94: 8167788 | T94: 11657788
A95: 2024.03 | B95: PT05 | C95: =iferror(vlookup($B95,Master_data!$K$1:$M$190,3,0),"--") -> Phụ tá | D95: =iferror(vlookup($B95,Master_data!$K$1:$M$190,2,0),"--") -> PT Kiều | E95: 5000000 | F95: 500000 | I95: 300000 | J95: 26 | K95: 25.8125 | L95: 20.8 | M95: 500000 | N95: 525840 | P95: 1250000 | Q95: 2950000 | S95: 6988102 | T95: 10463942
A96: 2024.03 | B96: PT06 | C96: =iferror(vlookup($B96,Master_data!$K$1:$M$190,3,0),"--") -> Phụ tá | D96: =iferror(vlookup($B96,Master_data!$K$1:$M$190,2,0),"--") -> PT Trân | E96: 5000000 | F96: 500000 | G96: 0 | H96: 0 | I96: 300000 | J96: 26 | K96: 25.2625 | L96: 15.7 | M96: 377404 | P96: 1300000 | Q96: 1550000 | S96: 7335577 | T96: 8885577
A97: 2024.03 | B97: LT01 | C97: =iferror(vlookup($B97,Master_data!$K$1:$M$190,3,0),"--") -> Lễ tân | D97: =iferror(vlookup($B97,Master_data!$K$1:$M$190,2,0),"--") -> LT Quỳnh Như | E97: 3500000 | F97: 2500000 | G97: 0 | H97: 0 | I97: 300000 | J97: 26 | K97: 25 | M97: 0 | N97: 525840 | P97: 0 | Q97: 693056 | S97: 5639545 | T97: 6858440
A98: 2024.03 | B98: LT02 | C98: =iferror(vlookup($B98,Master_data!$K$1:$M$190,3,0),"--") -> Lễ tân | D98: =iferror(vlookup($B98,Master_data!$K$1:$M$190,2,0),"--") -> LT Kim Ngân | E98: 2500000 | F98: 1000000 | G98: 0 | H98: 0 | I98: 150000 | J98: 26 | K98: 24.6375 | L98: 5.25 | M98: 63101 | N98: 525840 | P98: 725000 | Q98: 693056 | S98: 3781251 | T98: 5000147
A99: 2024.03 | B99: LT04 | C99: =iferror(vlookup($B99,Master_data!$K$1:$M$190,3,0),"--") -> Lễ tân | D99: =iferror(vlookup($B99,Master_data!$K$1:$M$190,2,0),"--") -> Lt Tú Nhi | E99: 2500000 | F99: 750000 | G99: 0 | H99: 0 | I99: 150000 | J99: 26 | K99: 24.75 | L99: 3.5 | M99: 42067 | N99: 525840 | P99: 1000000 | Q99: 693056 | S99: 3796035 | T99: 5014931
A100: 2024.03 | B100: LT05 | C100: =iferror(vlookup($B100,Master_data!$K$1:$M$190,3,0),"--") -> Lễ tân | D100: =iferror(vlookup($B100,Master_data!$K$1:$M$190,2,0),"--") -> LT Văn Tính | E100: 2500000 | F100: 750000 | G100: 0 | H100: 0 | I100: 150000 | J100: 26 | K100: 25.34375 | M100: 0 | N100: 525840 | P100: 725000 | Q100: 693056 | S100: 3536059 | T100: 4754955
A101: 2024.03 | B101: TV00 | C101: =iferror(vlookup($B101,Master_data!$K$1:$M$190,3,0),"--") -> Tư vấn | D101: =iferror(vlookup($B101,Master_data!$K$1:$M$190,2,0),"--") -> TV Đông | E101: 2500000 | F101: 500000 | G101: 0 | H101: 0 | I101: 150000 | J101: 26 | K101: 24.96875 | L101: 4 | M101: 48077 | N101: 525840 | P101: 50000 | Q101: 4622740 | S101: 2623078 | T101: 7771658
A102: 2024.03 | B102: TV01 | C102: =iferror(vlookup($B102,Master_data!$K$1:$M$190,3,0),"--") -> Tư vấn | D102: =iferror(vlookup($B102,Master_data!$K$1:$M$190,2,0),"--") -> Tv Na | E102: 2500000 | F102: 500000 | G102: 0 | H102: 0 | I102: 150000 | J102: 26 | K102: 25.6875 | L102: 4 | M102: 48077 | N102: 525840 | P102: 75000 | Q102: 7414930 | S102: 2717189 | T102: 10657959
A103: 2024.03 | B103: TV02 | C103: =iferror(vlookup($B103,Master_data!$K$1:$M$190,3,0),"--") -> Tư vấn | D103: =iferror(vlookup($B103,Master_data!$K$1:$M$190,2,0),"--") -> Tv Vy | E103: 2550000 | F103: 0 | G103: 0 | H103: 0 | I103: 0 | J103: 26 | K103: 16.975 | L103: 0 | M103: 0 | N103: 0 | P103: 0 | Q103: 1964430 | S103: 1664856 | T103: 3629286
A104: 2024.03 | B104: TV03 | C104: =iferror(vlookup($B104,Master_data!$K$1:$M$190,3,0),"--") -> Telesale | D104: =iferror(vlookup($B104,Master_data!$K$1:$M$190,2,0),"--") -> Telesale Bí Nhi | E104: 1666667 | F104: 333333 | G104: 0 | H104: 0 | I104: 100000 | J104: 26 | K104: 31 | M104: 0 | N104: 525840 | P104: 466667 | Q104: 4432621 | S104: 2361339 | T104: 7319800
A105: 2024.03 | B105: TV04 | C105: =iferror(vlookup($B105,Master_data!$K$1:$M$190,3,0),"--") -> Telesale | D105: =iferror(vlookup($B105,Master_data!$K$1:$M$190,2,0),"--") -> Telesale Yến | E105: 1666667 | F105: 333333 | G105: 0 | H105: 0 | I105: 100000 | J105: 26 | K105: 30.5 | M105: 0 | P105: 450000 | Q105: 9102474 | S105: 2838462 | T105: 11940936
A106: 2024.03 | B106: TV05 | C106: =iferror(vlookup($B106,Master_data!$K$1:$M$190,3,0),"--") -> Telesale | D106: =iferror(vlookup($B106,Master_data!$K$1:$M$190,2,0),"--") -> Telesale Uyển Nhi | E106: 3333333 | F106: 0 | G106: 0 | H106: 0 | I106: 0 | J106: 26 | K106: 26 | M106: 0 | N106: 525840 | S106: 2807493 | T106: 3333333
A107: 2024.03 | B107: TV07 | C107: =iferror(vlookup($B107,Master_data!$K$1:$M$190,3,0),"--") -> CSKH | D107: =iferror(vlookup($B107,Master_data!$K$1:$M$190,2,0),"--") -> CSKH Hoàng Lan | E107: 3333333 | F107: 0 | G107: 0 | H107: 0 | I107: 0 | J107: 26 | K107: 9 | M107: 0 | N107: 0 | P107: 0 | Q107: 0 | S107: 1153846 | T107: 1153846
A108: 2024.03 | B108: VP02 | C108: =iferror(vlookup($B108,Master_data!$K$1:$M$190,3,0),"--") -> Văn phòng | D108: =iferror(vlookup($B108,Master_data!$K$1:$M$190,2,0),"--") -> Anh Hiền | E108: 30333333 | F108: 0 | G108: 0 | H108: 0 | I108: 0 | J108: 26 | K108: 26 | M108: 0 | S108: 30333333 | T108: 30333333
A109: 2024.03 | B109: VP03 | C109: =iferror(vlookup($B109,Master_data!$K$1:$M$190,3,0),"--") -> Văn phòng | D109: =iferror(vlookup($B109,Master_data!$K$1:$M$190,2,0),"--") -> Hiến | E109: 18333333 | F109: 0 | G109: 0 | H109: 0 | I109: 0 | J109: 26 | K109: 26 | M109: 0 | N109: 525840 | S109: 17807493 | T109: 18333333
A110: 2024.03 | B110: VP04 | C110: =iferror(vlookup($B110,Master_data!$K$1:$M$190,3,0),"--") -> Văn phòng | D110: =iferror(vlookup($B110,Master_data!$K$1:$M$190,2,0),"--") -> Chị Phượng | E110: 15000000 | F110: 0 | G110: 0 | H110: 0 | I110: 0 | J110: 26 | K110: 26 | M110: 0 | N110: 1050000 | S110: 13950000 | T110: 15000000
A111: 2024.03 | B111: VP05 | C111: =iferror(vlookup($B111,Master_data!$K$1:$M$190,3,0),"--") -> Văn phòng | D111: =iferror(vlookup($B111,Master_data!$K$1:$M$190,2,0),"--") -> Duyên HCNS | E111: 5333333 | F111: 0 | G111: 0 | H111: 0 | I111: 0 | J111: 26 | K111: 26 | M111: 0 | S111: 5333333 | T111: 5333333
A112: 2024.03 | B112: VP06 | C112: =iferror(vlookup($B112,Master_data!$K$1:$M$190,3,0),"--") -> Văn phòng | D112: =iferror(vlookup($B112,Master_data!$K$1:$M$190,2,0),"--") -> Kiểm soát Ngọc Lệ | E112: 6000000 | F112: 0 | G112: 0 | H112: 0 | I112: 0 | J112: 26 | K112: 24.5 | M112: 0 | N112: 10525840 | S112: -4871994 | T112: 5653846
A113: 2024.03 | B113: VP07 | C113: =iferror(vlookup($B113,Master_data!$K$1:$M$190,3,0),"--") -> Văn phòng | D113: =iferror(vlookup($B113,Master_data!$K$1:$M$190,2,0),"--") -> Kim Hồng | E113: 4166667 | F113: 0 | G113: 0 | H113: 0 | I113: 0 | J113: 26 | K113: 26 | M113: 0 | Q113: 866667 | S113: 4166667 | T113: 5033333
A114: 2024.03 | B114: VP08 | C114: =iferror(vlookup($B114,Master_data!$K$1:$M$190,3,0),"--") -> Văn phòng | D114: =iferror(vlookup($B114,Master_data!$K$1:$M$190,2,0),"--") -> Nhi (ngoc nhi 2727) | E114: 6666667 | F114: 0 | G114: 0 | H114: 0 | I114: 0 | J114: 26 | K114: 26 | M114: 0 | N114: 630000 | S114: 6036667 | T114: 6666667
A115: 2024.03 | B115: VP09 | C115: =iferror(vlookup($B115,Master_data!$K$1:$M$190,3,0),"--") -> Marketing | D115: =iferror(vlookup($B115,Master_data!$K$1:$M$190,2,0),"--") -> MKT Minh Lâm | E115: 8333333 | F115: 0 | G115: 0 | H115: 0 | I115: 0 | J115: 26 | K115: 26 | M115: 0 | N115: 5735000 | S115: 2598333 | T115: 8333333
A116: 2024.03 | B116: VP10 | C116: =iferror(vlookup($B116,Master_data!$K$1:$M$190,3,0),"--") -> Marketing | D116: =iferror(vlookup($B116,Master_data!$K$1:$M$190,2,0),"--") -> MKT Bông | E116: 4000000 | F116: 0 | G116: 0 | H116: 0 | I116: 0 | J116: 26 | K116: 25.75 | L116: 16 | M116: 307692 | N116: 3525840 | Q116: 900000 | S116: 743391 | T116: 5169231
A117: 2024.03 | B117: VP11 | C117: =iferror(vlookup($B117,Master_data!$K$1:$M$190,3,0),"--") -> Marketing | D117: =iferror(vlookup($B117,Master_data!$K$1:$M$190,2,0),"--") -> Trung Hào | E117: 4333333 | F117: 0 | G117: 0 | H117: 0 | I117: 0 | J117: 26 | K117: 26 | L117: 17.85 | M117: 371875 | Q117: 1080000 | S117: 4705208 | T117: 5785208
A118: 2024.03 | B118: VP12 | C118: =iferror(vlookup($B118,Master_data!$K$1:$M$190,3,0),"--") -> Marketing | D118: =iferror(vlookup($B118,Master_data!$K$1:$M$190,2,0),"--") -> Chụp hình Hùng | E118: 4333333 | F118: 0 | G118: 0 | H118: 0 | I118: 0 | J118: 26 | K118: 25.4375 | L118: 1.5 | M118: 31250 | N118: 525840 | Q118: 1053333 | S118: 3744993 | T118: 5324167
A119: 2024.03 | B119: VP13 | C119: =iferror(vlookup($B119,Master_data!$K$1:$M$190,3,0),"--") -> Marketing | D119: =iferror(vlookup($B119,Master_data!$K$1:$M$190,2,0),"--") -> Lâm Trần Tuấn | E119: 3400000 | J119: 26 | K119: 28 | S119: 3661538 | T119: 3661538
A120: 2024.03 | B120: VP14 | C120: =iferror(vlookup($B120,Master_data!$K$1:$M$190,3,0),"--") -> Marketing | D120: =iferror(vlookup($B120,Master_data!$K$1:$M$190,2,0),"--") -> MKT Anh TRung | E120: 8333333 | F120: 0 | G120: 0 | H120: 0 | I120: 0 | J120: 26 | K120: 7 | M120: 0 | S120: 2243590 | T120: 2243590
A121: 2024.03 | B121: VP16 | C121: =iferror(vlookup($B121,Master_data!$K$1:$M$190,3,0),"--") -> Văn phòng | D121: =iferror(vlookup($B121,Master_data!$K$1:$M$190,2,0),"--") -> Bảo Nghi | E121: 4666667 | F121: 0 | G121: 0 | H121: 0 | I121: 0 | J121: 26 | K121: 26 | M121: 0 | S121: 4666667 | T121: 4666667
A122: 2024.03 | B122: VP17 | C122: =iferror(vlookup($B122,Master_data!$K$1:$M$190,3,0),"--") -> Văn phòng | D122: =iferror(vlookup($B122,Master_data!$K$1:$M$190,2,0),"--") -> Kế toán tài chính Thái | E122: 5000000 | F122: 0 | G122: 0 | H122: 0 | I122: 0 | J122: 26 | K122: 9 | S122: 1730769 | T122: 1730769
A123: 2024.03 | B123: VP15 | C123: =iferror(vlookup($B123,Master_data!$K$1:$M$190,3,0),"--") -> Văn phòng | D123: =iferror(vlookup($B123,Master_data!$K$1:$M$190,2,0),"--") -> Kế toán + thuế | E123: 12000000 | F123: 0 | G123: 0 | H123: 0 | I123: 0 | J123: 26 | K123: 26 | M123: 0 | S123: 12000000 | T123: 12000000
A124: 2024.03 | B124: K01 | C124: =iferror(vlookup($B124,Master_data!$K$1:$M$190,3,0),"--") -> Sảnh + bếp | D124: =iferror(vlookup($B124,Master_data!$K$1:$M$190,2,0),"--") -> GV Hiền | E124: 2100000 | F124: 566667 | G124: 0 | H124: 0 | I124: 0 | J124: 26 | K124: 26 | M124: 0 | S124: 2666667 | T124: 2666667
A125: 2024.03 | B125: K02 | C125: =iferror(vlookup($B125,Master_data!$K$1:$M$190,3,0),"--") -> Sảnh + bếp | D125: =iferror(vlookup($B125,Master_data!$K$1:$M$190,2,0),"--") -> Chị Trang | E125: 2100000 | F125: 566667 | G125: 0 | H125: 0 | I125: 0 | J125: 26 | K125: 29 | L125: 12.5 | M125: 126202 | N125: 3525840 | S125: -490664 | T125: 3035176
A126: 2024.03 | B126: K03 | C126: =iferror(vlookup($B126,Master_data!$K$1:$M$190,3,0),"--") -> Sảnh + bếp | D126: =iferror(vlookup($B126,Master_data!$K$1:$M$190,2,0),"--") -> Chị Trang VP | E126: 666667 | G126: 0 | H126: 0 | I126: 0 | J126: 26 | K126: 26 | M126: 0 | S126: 666667 | T126: 666667
A127: 2024.03 | B127: K04 | C127: =iferror(vlookup($B127,Master_data!$K$1:$M$190,3,0),"--") -> Sảnh + bếp | D127: =iferror(vlookup($B127,Master_data!$K$1:$M$190,2,0),"--") -> GV Linh | E127: 2666667 | G127: 0 | H127: 0 | I127: 0 | J127: 26 | K127: 27.625 | M127: 0 | N127: 525840 | S127: 2307493 | T127: 2833333
A128: 2024.03 | B128: K05 | C128: =iferror(vlookup($B128,Master_data!$K$1:$M$190,3,0),"--") -> Sảnh + bếp | D128: =iferror(vlookup($B128,Master_data!$K$1:$M$190,2,0),"--") -> BV Trung | E128: 3666667 | F128: 0 | G128: 0 | H128: 0 | I128: 0 | J128: 28 | K128: 29 | L128: 12.35 | M128: 202158 | S128: 3999777 | T128: 3999777
A129: 2024.03 | B129: K06 | C129: =iferror(vlookup($B129,Master_data!$K$1:$M$190,3,0),"--") -> Sảnh + bếp | D129: =iferror(vlookup($B129,Master_data!$K$1:$M$190,2,0),"--") -> BV Cang | E129: 3666667 | F129: 0 | G129: 0 | H129: 0 | I129: 0 | J129: 28 | K129: 28.4625 | L129: 29.5 | M129: 482887 | N129: 3525840 | S129: 684279 | T129: 4210119
A130: 2024.03 | B130: K07 | C130: =iferror(vlookup($B130,Master_data!$K$1:$M$190,3,0),"--") -> Sảnh + bếp | D130: =iferror(vlookup($B130,Master_data!$K$1:$M$190,2,0),"--") -> TX Đức | E130: 5500000 | F130: 0 | G130: 0 | H130: 0 | I130: 0 | J130: 28 | K130: 29 | L130: 37.2 | M130: 913393 | P130: 500000 | S130: 7109821 | T130: 7109821
A131: 2024.03 | B131: K08 | C131: =iferror(vlookup($B131,Master_data!$K$1:$M$190,3,0),"--") -> Sảnh + bếp | D131: =iferror(vlookup($B131,Master_data!$K$1:$M$190,2,0),"--") -> TX Oanh | E131: 5000000 | J131: 28 | K131: 27.5 | L131: 35.35 | M131: 789063 | P131: 500000 | S131: 6199777 | T131: 6199777
A132: 2024.04 | D132: BS Công | E132: 35000000 | F132: 0 | G132: 0 | H132: 0 | I132: 0 | J132: 26 | K132: 22.2926 | M132: 0 | P132: 0 | Q132: 79709580 | R132: 30009269 | S132: 109718849 | T132: 109718849
A133: 2024.04 | C133: =iferror(vlookup($B133,Master_data!$K$1:$M$190,3,0),"--") -> -- | D133: Bs Tú | E133: 15000000 | J133: 26 | K133: 25.8466 | M133: 0 | Q133: 50348925 | R133: 14911500 | S133: 65260425 | T133: 65260425
A134: 2024.04 | D134: Lương 3cđ | E134: 25000000 | F134: 0 | G134: 0 | H134: 0 | I134: 0 | J134: 26 | K134: 26 | P134: 0 | R134: 25000000 | S134: 25000000 | T134: 25000000
...

Sheet PL.Lương SAN
A1: SAN | B1: Tháng 1 | C1: Lương CB | D1: Ngày công chuẩn | E1: Ngày công thực tế | F1: Số ngày tăng ca | G1: Tăng ca | H1: Năng lực | I1: Thâm niên | J1: Kiêm việc | K1: Trợ cấp | L1: KPI Công việc | M1: KPI Doanh số 15 | N1: Thưởng tháng 13 | O1: Đào tạo | P1: Tổng lương | Q1: Bảo hiểm | R1: Khấu trừ | S1: Tạm ứng | T1: Thực nhận
B2: BAN CỐ VẤN | C2: =sum(C3) -> 55000000 | G2: =sum(G3) -> 0 | H2: =sum(H3) -> 0 | I2: =sum(I3) -> 0 | J2: =sum(J3) -> 0 | K2: =sum(K3) -> 0 | L2: =sum(L3) -> 0 | M2: =sum(M3) -> 0 | N2: =sum(N3) -> 0 | ... T2: =sum(T3) -> 55000000
B3: Lương CĐ | C3: 55000000 | D3: 26 | E3: 26 | F3: 0 | G3: 0 | H3: 0 | I3: 0 | J3: 0 | K3: 0 | L3: 0 | M3: 0 | N3: 0 | O3: 0 | P3: 55000000 | Q3: 0 | R3: 0 | S3: 0 | T3: =P3-Q3-R3-S3 -> 55000000
B4: HỘI ĐỒNG THÀNH VIÊN
B6: BAN GIÁM ĐỐC
B8: KINH DOANH | C8: =sum(C9:C17) -> 30166667 | G8: =sum(G9:G17) -> 602051 | H8: =sum(H9:H17) -> 0 | I8: =sum(I9:I17) -> 0 | J8: =sum(J9:J17) -> 0 | K8: =sum(K9:K17) -> 0 | L8: =sum(L9:L17) -> 0 | M8: =sum(M9:M17) -> 54501585 | N8: =sum(N9:N17) -> 0 | ... T8: =sum(T9:T17) -> 84200663
B9: Thầy Vinh PT | C9: 5000000 | D9: 26 | E9: 26 | P9: 5000000 | T9: 5000000
B10: Tiền PT của LT | P10: 66667 | T10: 66667
B11: Tv Minh Hạnh | C11: 3250000 | D11: 26 | E11: 24.7407 | F11: 1 | G11: 15625 | M11: 9970747 | P11: 13078960 | T11: 13078960
B12: Tv Bảo | C12: 3250000 | D12: 26 | E12: 26.449 | F12: 12.48 | G12: 195000 | M12: 20211186 | P12: 23712311 | T12: 23712311
B13: Telesale Bí Nhi | C13: 2166667 | D13: 26 | E13: 34 | G13: 0 | M13: 10306980 | P13: 13140313 | R13: 175280 | T13: 12965033
B14: Telesale Yến | C14: 2166667 | D14: 26 | E14: 32.5 | F14: 4.5 | G14: 46875 | M14: 14012672 | P14: 16767880 | R14: 175280 | T14: 16592600
B15: TBP CSKH Chuyên | C15: 6666667 | D15: 26 | E15: 20.8017 | G15: 0 | P15: 5333769 | T15: 5333769
B16: CSKH Thảo Uyên | C16: 3333333 | D16: 26 | E16: 23 | F16: 8.5 | G16: 136218 | P16: 3084936 | T16: 3084936
B17: CSKH Hoàng Lan | C17: 4333333 | D17: 26 | E17: 26 | F17: 10 | G17: 208333 | P17: 4541667 | R17: 175280 | T17: 4366387
B18: KẾ TOÁN - KHO | C18: =sum(C19:C20) -> 13333333 | G18: =sum(G19:G20) -> 0 | H18: =sum(H19:H20) -> 0 | I18: =sum(I19:I20) -> 0 | J18: =sum(J19:J20) -> 0 | K18: =sum(K19:K20) -> 0 | L18: =sum(L19:L20) -> 0 | M18: =sum(M19:M20) -> 0 | N18: =sum(N19:N20) -> 0 | ... T18: =sum(T19:T20) -> 13333333
B19: Kế toán tài chính Thái | C19: 5000000 | D19: 26 | E19: 26 | P19: 5000000 | T19: 5000000
B20: Kế toán + thuế | C20: 8333333 | D20: 26 | E20: 26 | P20: 8333333 | T20: 8333333
B21: HÀNH CHÍNH - NHÂN SỰ | C21: =sum(C22:C32) -> 75366666 | G21: =sum(G22:G32) -> 2438520 | H21: =sum(H22:H32) -> 1133334 | I21: =sum(I22:I32) -> 0 | J21: =sum(J22:J32) -> 666667 | K21: =sum(K22:K32) -> 0 | L21: =sum(L22:L32) -> 150000 | M21: =sum(M22:M32) -> 0 | N21: =sum(N22:N32) -> 0 | ... T21: =sum(T22:T32) -> 74655194
B22: TP HCNS Nga | C22: 8333333 | D22: 26 | E22: 26 | P22: 8333333 | R22: 245000 | T22: 8088333
B23: Anh Hiền | C23: 30333333 | D23: 26 | E23: 26 | P23: 30333333 | T23: 30333333
B24: Duyên HCNS | C24: 5333333 | D24: 26 | E24: 26 | P24: 5333333 | R24: 175280 | T24: 5158053
B25: Anh Bảo đào tạo | C25: 5000000 | D25: 26 | E25: 25.4313 | P25: 4890635 | R25: 175280 | T25: 4715355
B26: GV Hiền | C26: 2100000 | D26: 26 | E26: 25.9538 | G26: 0 | H26: 566667 | J26: 0 | P26: 2662935 | R26: 175280 | T26: 2487655
B27: Chị Trang | C27: 2100000 | D27: 26 | E27: 28.9971 | F27: 14.37 | G27: 145082 | H27: 566667 | J27: 666667 | P27: 3720489 | R27: 175280 | S27: 1333333 | T27: 2211875
B28: Cô Liên tạp vụ | C28: 2666667 | D28: 26 | E28: 24 | G28: 0 | P28: 2461538 | T28: 2461538
B29: Bv Trung | C29: 4000000 | D29: 28 | E29: 27.9241 | F29: 5.32 | G29: 95000 | H29: 0 | J29: 0 | L29: 50000 | P29: 4134157 | R29: 175280 | S29: 2000000 | T29: 1958877
B30: BV Cang | C30: 4000000 | D30: 28 | E30: 29 | F30: 11.21 | G30: 200179 | H30: 0 | J30: 0 | L30: 100000 | P30: 4443036 | R30: 175280 | T30: 4267756
B31: TX Đức | C31: 6000000 | D31: 28 | E31: 28 | F31: 38.87 | G31: 1041161 | H31: 0 | J31: 0 | P31: 7041161 | R31: 262920 | T31: 6778241
B32: TX Oanh | C32: 5500000 | D32: 28 | E32: 28 | F32: 38.98 | G32: 957098 | P32: 6457098 | R32: 262920 | T32: 6194178
B33: VẬN HÀNH | C33: =sum(C34:C44) -> 51166664 | G33: =sum(G34:G44) -> 625249 | H33: =sum(H34:H44) -> 5999998 | I33: =sum(I34:I44) -> 0 | J33: =sum(J34:J44) -> 0 | K33: =sum(K34:K44) -> 0 | L33: =sum(L34:L44) -> 0 | M33: =sum(M34:M44) -> 11402912 | N33: =sum(N34:N44) -> 0 | ... T33: =sum(T34:T44) -> 59041161
B34: LT Quỳnh Như | C34: 2666667 | D34: 26 | E34: 25.808 | F34: 0.5 | G34: 6410 | H34: 3333333 | P34: 5986718 | R34: 175280 | T34: 5811438
B35: LT Bích Nhi | C35: 1833333 | D35: 26 | E35: 24.3374 | F35: 9.59 | G35: 84527 | H35: 333333 | M35: 1577531 | P35: 3711491 | R35: 175280 | T35: 3536211
B36: LT Tường Vy | C36: 1833333 | D36: 26 | E36: 25.8213 | F36: 14.61 | G36: 128774 | H36: 333333 | M36: 1673716 | P36: 3956557 | R36: 175280 | T36: 3781277
B37: LT Tuyết Ngọc | C37: 1833333 | D37: 26 | E37: 25 | F37: 13.73 | G37: 121018 | H37: 333333 | M37: 1620480 | P37: 3837652 | T37: 3837652
B38: LT Kim Ngân | C38: 1833333 | D38: 26 | E38: 25.5645 | F38: 4.26 | G38: 37548 | H38: 666667 | M38: 1657071 | P38: 4163911 | R38: 175280 | T38: 3988631
B39: Lt Tú Nhi | C39: 1833333 | D39: 26 | E39: 25.9699 | F39: 6.07 | G39: 53502 | H39: 333333 | M39: 1683349 | P39: 3901394 | R39: 175280 | T39: 3726114
B40: LT Văn Tính | C40: 1833333 | D40: 26 | E40: 26 | F40: 11.34 | G40: 99952 | H40: 333333 | M40: 1685300 | P40: 3951918 | R40: 175280 | T40: 3776638
B41: LT Trâm Anh | C41: 1833333 | D41: 26 | E41: 23.2256 | F41: 10.61 | G41: 93518 | H41: 333333 | M41: 1505465 | P41: 3570019 | T41: 3570019
B42: Quản lý Tiến | C42: 13333333 | D42: 26 | E42: 22 | P42: 11282051 | S42: 5000000 | T42: 6282051
B43: Chị Phượng | C43: 18333333 | D43: 26 | E43: 26 | P43: 18333333 | R43: 350000 | T43: 17983333
B44: Uyên kiểm soát | C44: 4000000 | D44: 26 | E44: 19 | G44: 0 | H44: 0 | P44: 2923077 | R44: 175280 | T44: 2747797
B45: MARKETING | C45: =sum(C46:C58) -> 91508613 | G45: =sum(G46:G58) -> 507740 | H45: =sum(H46:H58) -> 0 | I45: =sum(I46:I58) -> 0 | J45: =sum(J46:J58) -> 0 | K45: =sum(K46:K58) -> 0 | L45: =sum(L46:L58) -> 0 | M45: =sum(M46:M58) -> 2606250 | N45: =sum(N46:N58) -> 0 | ... T45: =sum(T46:T58) -> 92639437
B46: Hiến | C46: 21666667 | D46: 26 | E46: 26 | P46: 21666667 | R46: 175280 | T46: 21491387
B47: Ánh Nguyệt content | C47: 5333333 | D47: 26 | E47: 26 | G47: 0 | P47: 5333333 | R47: 175280 | T47: 5158053
B48: XIÊM QUỐC THU quay dựng | C48: 7666667 | D48: 26 | E48: 26 | G48: 0 | P48: 7666667 | R48: 175280 | T48: 7491387
B49: Thành media | C49: 6666667 | D49: 26 | E49: 25.9604 | G49: 0 | P49: 6656513 | R49: 175280 | T49: 6481233
B50: MKT Minh Lâm | C50: 8333333 | D50: 26 | E50: 26 | G50: 0 | P50: 8333333 | R50: 210000 | T50: 8123333
B51: MKT Bông | C51: 8333333 | D51: 26 | E51: 26 | G51: 0 | P51: 8333333 | T51: 8333333
B52: Trung Hào | C52: 4000000 | D52: 26 | E52: 27 | F52: 17.66 | G52: 339615 | M52: 868750 | P52: 5362212 | R52: 175280 | T52: 5186932
B53: Chụp hình Hùng | C53: 4333333 | D53: 26 | E53: 26 | F53: 7.07 | G53: 147292 | M53: 868750 | P53: 5349375 | T53: 5349375
B54: Lâm Trần Tuấn | C54: 4333333 | D54: 26 | E54: 25.8606 | F54: 1 | G54: 20833 | M54: 868750 | P54: 5199683 | R54: 175280 | S54: 666667 | T54: 4357737
B55: Đức Thuận | C55: 4000000 | D55: 26 | E55: 26 | G55: 0 | P55: 4000000 | T55: 4000000
B56: Bảo Nghi | C56: 5841947 | D56: 26 | E56: 26 | G56: 0 | P56: 5841947 | R56: 175280 | T56: 5666667
B57: đội sedding NK | C57: 9333333 | D57: 26 | E57: 26 | P57: 9333333 | T57: 9333333
B58: Phiên dịch Trang | C58: 1666667 | D58: 26 | E58: 26 | P58: 1666667 | T58: 1666667
B59: NGHIỆP VỤ | C59: =sum(C60:C74) -> 70666667 | G59: =sum(G60:G74) -> 4021697 | H59: =sum(H60:H74) -> 9500000 | I59: =sum(I60:I74) -> 2000000 | J59: =sum(J60:J74) -> 0 | K59: =sum(K60:K74) -> 100000 | L59: =sum(L60:L74) -> 0 | M59: =sum(M60:M74) -> 247239923 | N59: =sum(N60:N74) -> 0 | ... T59: =sum(T60:T74) -> 329183097
B60: PT TRƯỞNG Cẩm Loan | C60: 6666667 | D60: 26 | E60: 29 | F60: 40.37 | G60: 1293910 | M60: 783333 | P60: 9513141 | R60: 315000 | T60: 9198141
B61: PT Kim Ánh | C61: 2000000 | D61: 26 | E61: 26.569 | F61: 16.18 | G61: 155577 | H61: 1333333 | M61: 1285000 | P61: 4817679 | R61: 175280 | T61: 4642399
B62: PT Anh Như | C62: 2000000 | D62: 26 | E62: 25.8918 | F62: 30.57 | G62: 293942 | H62: 1000000 | I62: 2000000 | K62: 100000 | M62: 1335000 | P62: 6720619 | R62: 175280 | T62: 6545339
B63: PT Kiều | C63: 2000000 | D63: 26 | E63: 26.5852 | F63: 9 | G63: 86538 | H63: 500000 | M63: 841667 | P63: 3473221 | R63: 175280 | T63: 3297941
B64: PT Điệp | C64: 2000000 | D64: 26 | E64: 14.8814 | F64: 2.5 | G64: 24038 | H64: 333333 | M64: 828333 | P64: 2330428 | T64: 2330428
B65: PT Ngọc Nhi | C65: 2000000 | D65: 26 | E65: 24.3875 | F65: 21.86 | G65: 210192 | H65: 500000 | M65: 1276667 | P65: 3862821 | R65: 175280 | T65: 3687541
B66: PT Thanh Thi | C66: 2000000 | D66: 26 | E66: 25.4518 | F66: 16.75 | G66: 161058 | H66: 500000 | M66: 1053333 | P66: 3672222 | T66: 3672222
B67: PT Dung | C67: 2000000 | D67: 26 | E67: 26.8157 | F67: 15.55 | G67: 149519 | H67: 1000000 | M67: 1836667 | P67: 5048932 | R67: 175280 | T67: 4873652
B68: PT Tuyết Trang | C68: 2000000 | D68: 26 | E68: 26.7559 | F68: 12.64 | G68: 121538 | H68: 1000000 | I68: 0 | M68: 1520000 | P68: 4699685 | R68: 175280 | S68: 2000000 | T68: 2524405
B69: PT Ánh Thúy | C69: 2000000 | D69: 26 | E69: 26.8197 | F69: 23.25 | G69: 223558 | H69: 1000000 | I69: 0 | M69: 1783333 | P69: 5069945 | R69: 175280 | T69: 4894665
B70: PT Y Bình | C70: 2000000 | D70: 26 | E70: 19 | F70: 9.59 | G70: 92212 | H70: 1000000 | I70: 0 | M70: 880000 | P70: 3433750 | R70: 175280 | T70: 3258470
B71: PT Kiều Oanh | C71: 2000000 | D71: 26 | E71: 26.8955 | F71: 17.12 | G71: 164615 | H71: 666667 | M71: 1755000 | P71: 4655167 | R71: 175280 | T71: 4479887
B72: PT Đông Tuyết | C72: 2000000 | D72: 26 | E72: 28.3734 | F72: 16.58 | G72: 159423 | H72: 666667 | M72: 1661667 | P72: 4670326 | R72: 175280 | T72: 4495046
B73: Bs Hoàng | C73: 20000000 | D73: 26 | E73: 26 | M73: 99264595 | P73: 119264595 | Q73: 0 | R73: 0 | S73: 0 | T73: =P73-Q73-R73-S73 -> 119264595
B74: BS LÂM | C74: 20000000 | D74: 26 | E74: 26.9522 | F74: 9.21 | G74: 885577 | M74: 131135328 | P74: 152753366 | Q74: 0 | R74: 735000 | S74: 0 | T74: =P74-Q74-R74-S74 -> 152018366
A75: SAN | B75: Tháng 2 | C75: Lương CB | G75: Tăng ca | H75: Năng lực | I75: Thâm niên | J75: Kiêm việc | K75: Trợ cấp | L75: KPI Công việc | M75: KPI Doanh số 15 | N75: Thưởng tháng 13 | O75: Đào tạo | P75: Tổng lương | Q75: Bảo hiểm | R75: Khấu trừ | S75: Tạm ứng | T75: Thực nhận
B76: BAN CỐ VẤN | C76: =sum(C77) -> 55000000 | G76: =sum(G77) -> 0 | H76: =sum(H77) -> 0 | I76: =sum(I77) -> 0 | J76: =sum(J77) -> 0 | K76: =sum(K77) -> 0 | L76: =sum(L77) -> 0 | M76: =sum(M77) -> 0 | N76: =sum(N77) -> 0 | ... T76: =sum(T77) -> 55000000
B77: Lương CĐ | C77: 55000000 | G77: 0 | H77: 0 | I77: 0 | J77: 0 | K77: 0 | L77: 0 | M77: 0 | N77: 0 | O77: 0 | P77: =sum(C77:N77) -> 55000000 | Q77: 0 | R77: 0 | S77: 0 | T77: =P77-Q77-R77-S77 -> 55000000
B78: HỘI ĐỒNG THÀNH VIÊN
B80: BAN GIÁM ĐỐC
B82: KINH DOANH | C82: =sum(C83:C91) -> 30166667 | G82: =sum(G83:G91) -> 602051 | H82: =sum(H83:H91) -> 0 | I82: =sum(I83:I91) -> 0 | J82: =sum(J83:J91) -> 0 | K82: =sum(K83:K91) -> 0 | L82: =sum(L83:L91) -> 0 | M82: =sum(M83:M91) -> 54501585 | N82: =sum(N83:N91) -> 0 | ... T82: =sum(T83:T91) -> 84200663
B83: Thầy Vinh PT | C83: 5000000 | P83: 5000000 | T83: 5000000
B84: Tiền PT của LT | P84: 66667 | T84: 66667
B85: Tv Minh Hạnh | C85: 3250000 | G85: 15625 | M85: 9970747 | P85: 13078960 | T85: 13078960
B86: Tv Bảo | C86: 3250000 | G86: 195000 | M86: 20211186 | P86: 23712311 | T86: 23712311
B87: Telesale Bí Nhi | C87: 2166667 | G87: 0 | M87: 10306980 | P87: 13140313 | R87: 175280 | T87: 12965033
B88: Telesale Yến | C88: 2166667 | G88: 46875 | M88: 14012672 | P88: 16767880 | R88: 175280 | T88: 16592600
B89: TBP CSKH Chuyên | C89: 6666667 | G89: 0 | P89: 5333769 | T89: 5333769
B90: CSKH Thảo Uyên | C90: 3333333 | G90: 136218 | P90: 3084936 | T90: 3084936
B91: CSKH Hoàng Lan | C91: 4333333 | G91: 208333 | P91: 4541667 | R91: 175280 | T91: 4366387
B92: KẾ TOÁN - KHO | C92: =sum(C93:C94) -> 13333333 | G92: =sum(G93:G94) -> 0 | H92: =sum(H93:H94) -> 0 | I92: =sum(I93:I94) -> 0 | J92: =sum(J93:J94) -> 0 | K92: =sum(K93:K94) -> 0 | L92: =sum(L93:L94) -> 0 | M92: =sum(M93:M94) -> 0 | N92: =sum(N93:N94) -> 0 | ... T92: =sum(T93:T94) -> 13333333
B93: Kế toán tài chính Thái | C93: 5000000 | P93: 5000000 | T93: 5000000
B94: Kế toán + thuế | C94: 8333333 | P94: 8333333 | T94: 8333333
B95: HÀNH CHÍNH - NHÂN SỰ | C95: =sum(C96:C106) -> 75366666 | G95: =sum(G96:G106) -> 2438520 | H95: =sum(H96:H106) -> 1133334 | I95: =sum(I96:I106) -> 0 | J95: =sum(J96:J106) -> 666667 | K95: =sum(K96:K106) -> 0 | L95: =sum(L96:L106) -> 150000 | M95: =sum(M96:M106) -> 0 | N95: =sum(N96:N106) -> 0 | ... T95: =sum(T96:T106) -> 74655194
B96: TP HCNS Nga | C96: 8333333 | P96: 8333333 | R96: 245000 | T96: 8088333
B97: Anh Hiền | C97: 30333333 | P97: 30333333 | T97: 30333333
B98: Duyên HCNS | C98: 5333333 | P98: 5333333 | R98: 175280 | T98: 5158053
B99: Anh Bảo đào tạo | C99: 5000000 | P99: 4890635 | R99: 175280 | T99: 4715355
B100: GV Hiền | C100: 2100000 | G100: 0 | H100: 566667 | J100: 0 | P100: 2662935 | R100: 175280 | T100: 2487655
B101: Chị Trang | C101: 2100000 | G101: 145082 | H101: 566667 | J101: 666667 | P101: 3720489 | R101: 175280 | S101: 1333333 | T101: 2211875
B102: Cô Liên tạp vụ | C102: 2666667 | G102: 0 | P102: 2461538 | T102: 2461538
B103: Bv Trung | C103: 4000000 | G103: 95000 | H103: 0 | J103: 0 | L103: 50000 | P103: 4134157 | R103: 175280 | S103: 2000000 | T103: 1958877
B104: BV Cang | C104: 4000000 | G104: 200179 | H104: 0 | J104: 0 | L104: 100000 | P104: 4443036 | R104: 175280 | T104: 4267756
...

Sheet Chi phi_Teennie
A1: THÁNG | B1: NỘI DUNG CHI | C1: PHÂN LOẠI | D1: SỐ TIỀN | E1: DÒNG TIỀN | F1: TÀI CHÍNH
A2: 2023.01 | B2: hoa trái cây | C2: Mua đồ hành chính | D2: 315000 | E2: =vlookup(C2,'Master data'!$A$1:$C$29,3,0) -> Biến phí | F2: =vlookup(C2,'Master data'!$A$1:$C$29,2,0) -> Chi phí hành chính
A3: 2023.01 | B3: chè t12 | C3: Mua đồ hành chính | D3: 620000 | E3: =vlookup(C3,'Master data'!$A$1:$C$29,3,0) -> Biến phí | F3: =vlookup(C3,'Master data'!$A$1:$C$29,2,0) -> Chi phí hành chính
A4: 2023.01 | B4: cúng m16 | C4: Mua đồ hành chính | D4: 325000 | E4: =vlookup(C4,'Master data'!$A$1:$C$29,3,0) -> Biến phí | F4: =vlookup(C4,'Master data'!$A$1:$C$29,2,0) -> Chi phí hành chính
A5: 2023.01 | B5: cúng vp mới | C5: Mua đồ hành chính | D5: 600000 | E5: =vlookup(C5,'Master data'!$A$1:$C$29,3,0) -> Biến phí | F5: =vlookup(C5,'Master data'!$A$1:$C$29,2,0) -> Chi phí hành chính
A6: 2023.01 | B6: phí cúng vp | C6: Mua đồ hành chính | D6: 2000000 | E6: =vlookup(C6,'Master data'!$A$1:$C$29,3,0) -> Biến phí | F6: =vlookup(C6,'Master data'!$A$1:$C$29,2,0) -> Chi phí hành chính
A7: 2023.01 | B7: trái cây | C7: Mua đồ hành chính | D7: 276000 | E7: =vlookup(C7,'Master data'!$A$1:$C$29,3,0) -> Biến phí | F7: =vlookup(C7,'Master data'!$A$1:$C$29,2,0) -> Chi phí hành chính
A8: 2023.01 | B8: hoa trái cây | C8: Mua đồ hành chính | D8: 500000 | E8: =vlookup(C8,'Master data'!$A$1:$C$29,3,0) -> Biến phí | F8: =vlookup(C8,'Master data'!$A$1:$C$29,2,0) -> Chi phí hành chính
A9: 2023.01 | B9: đồ cúng | C9: Mua đồ hành chính | D9: 750000 | E9: =vlookup(C9,'Master data'!$A$1:$C$29,3,0) -> Biến phí | F9: =vlookup(C9,'Master data'!$A$1:$C$29,2,0) -> Chi phí hành chính
A10: 2023.01 | B10: cúng cuối năm | C10: Mua đồ hành chính | D10: 1000000 | E10: =vlookup(C10,'Master data'!$A$1:$C$29,3,0) -> Biến phí | F10: =vlookup(C10,'Master data'!$A$1:$C$29,2,0) -> Chi phí hành chính
A11: 2023.01 | B11: hotlime teennie | C11: Mua đồ hành chính | D11: 1377000 | E11: =vlookup(C11,'Master data'!$A$1:$C$29,3,0) -> Biến phí | F11: =vlookup(C11,'Master data'!$A$1:$C$29,2,0) -> Chi phí hành chính
A12: 2023.01 | B12: TN | C12: Mua đồ hành chính | D12: 17787000 | E12: =vlookup(C12,'Master data'!$A$1:$C$29,3,0) -> Biến phí | F12: =vlookup(C12,'Master data'!$A$1:$C$29,2,0) -> Chi phí hành chính
A13: 2023.01 | B13: 353 gth 527 | C13: Mua đồ hành chính | D13: 2000000 | E13: =vlookup(C13,'Master data'!$A$1:$C$29,3,0) -> Biến phí | F13: =vlookup(C13,'Master data'!$A$1:$C$29,2,0) -> Chi phí hành chính
... A195: 2023.07 | B195: Morrlly | C195: Tiền vật liệu | D195: 38747800 | E195: =vlookup(C195,'Master data'!$A$1:$C$29,3,0) -> Biến phí | F195: =vlookup(C195,'Master data'!$A$1:$C$29,2,0) -> Chi phí giá vốn
A196: 2023.08 | B196: Tổng hợp | C196: Mua đồ hành chính | D196: 0 | E196: Biến phí | F196: Chi phí hành chính
A197: 2023.08 | B197: Hộp quà khách tháo niềng | C197: Mua đồ hành chính | D197: 1480000 | E197: =vlookup(C197,'Master data'!$A$1:$C$29,3,0) -> Biến phí | F197: =vlookup(C197,'Master data'!$A$1:$C$29,2,0) -> Chi phí hành chính
A198: 2023.08 | B198: Khung tranh cho khách tháo niềng | C198: Mua đồ hành chính | D198: 1300000 | E198: =vlookup(C198,'Master data'!$A$1:$C$29,3,0) -> Biến phí | F198: =vlookup(C198,'Master data'!$A$1:$C$29,2,0) -> Chi phí hành chính
A199: 2023.08 | B199: 31 máy tăm nước | C199: Mua đồ hành chính | D199: 17787000 | E199: =vlookup(C199,'Master data'!$A$1:$C$29,3,0) -> Biến phí | F199: =vlookup(C199,'Master data'!$A$1:$C$29,2,0) -> Chi phí hành chính
A200: 2023.08 | B200: Seo web | C200: Mua đồ hành chính | D200: 10000000 | E200: =vlookup(C200,'Master data'!$A$1:$C$29,3,0) -> Biến phí | F200: =vlookup(C200,'Master data'!$A$1:$C$29,2,0) -> Chi phí hành chính
A201: 2023.08 | B201: 785 san gth 1165, 400 gth1167 | C201: Mua đồ hành chính | D201: 2000000 | E201: =vlookup(C201,'Master data'!$A$1:$C$29,3,0) -> Biến phí | F201: =vlookup(C201,'Master data'!$A$1:$C$29,2,0) -> Chi phí hành chính
A202: 2023.08 | B202: in chăm sóc sau gắn mc | C202: Mua đồ hành chính | D202: 340000 | E202: =vlookup(C202,'Master data'!$A$1:$C$29,3,0) -> Biến phí | F202: =vlookup(C202,'Master data'!$A$1:$C$29,2,0) -> Chi phí hành chính
A203: 2023.08 | B203: chi hh teennie | C203: Mua đồ hành chính | D203: 6000000 | E203: =vlookup(C203,'Master data'!$A$1:$C$29,3,0) -> Biến phí | F203: =vlookup(C203,'Master data'!$A$1:$C$29,2,0) -> Chi phí hành chính
A204: 2023.08 | B204: kéo tặng khách | C204: Mua đồ hành chính | D204: 2509000 | E204: =vlookup(C204,'Master data'!$A$1:$C$29,3,0) -> Biến phí | F204: =vlookup(C204,'Master data'!$A$1:$C$29,2,0) -> Chi phí hành chính
A205: 2023.08 | B205: hộp quà | C205: Mua đồ hành chính | D205: 1376000 | E205: =vlookup(C205,'Master data'!$A$1:$C$29,3,0) -> Biến phí | F205: =vlookup(C205,'Master data'!$A$1:$C$29,2,0) -> Chi phí hành chính
A206: 2023.08 | B206: bàn chải kẽ | C206: Mua đồ hành chính | D206: 550000 | E206: =vlookup(C206,'Master data'!$A$1:$C$29,3,0) -> Biến phí | F206: =vlookup(C206,'Master data'!$A$1:$C$29,2,0) -> Chi phí hành chính
A207: 2023.08 | B207: 62 TN tee | C207: Mua đồ hành chính | D207: 34117000 | E207: =vlookup(C207,'Master data'!$A$1:$C$29,3,0) -> Biến phí | F207: =vlookup(C207,'Master data'!$A$1:$C$29,2,0) -> Chi phí hành chính
A208: 2023.08 | B208: ship tặng quà bình nước Teennie cho đối tác | C208: Mua đồ hành chính | D208: 20000 | E208: =vlookup(C208,'Master data'!$A$1:$C$29,3,0) -> Biến phí | F208: =vlookup(C208,'Master data'!$A$1:$C$29,2,0) -> Chi phí hành chính
... A233: 2023.08 | B233: khí cụ T7+8 | C233: Tiền vật liệu | D233: 42300000 | E233: =vlookup(C233,'Master data'!$A$1:$C$29,3,0) -> Biến phí | F233: =vlookup(C233,'Master data'!$A$1:$C$29,2,0) -> Chi phí giá vốn
A234: 2023.09 | B234: Tổng hợp | C234: Mua đồ hành chính | D234: 0 | E234: Biến phí | F234: Chi phí hành chính
A235: 2023.09 | B235: quạt đèn gương chụ trong miệng | C235: Mua đồ hành chính | D235: 1595000 | E235: =vlookup(C235,'Master data'!$A$1:$C$29,3,0) -> Biến phí | F235: =vlookup(C235,'Master data'!$A$1:$C$29,2,0) -> Chi phí hành chính
A236: 2023.09 | B236: Seo web | C236: Mua đồ hành chính | D236: 10000000 | E236: =vlookup(C236,'Master data'!$A$1:$C$29,3,0) -> Biến phí | F236: =vlookup(C236,'Master data'!$A$1:$C$29,2,0) -> Chi phí hành chính
A237: 2023.09 | B237: Cọc lên tick xanh | C237: Mua đồ hành chính | D237: 5000000 | E237: =vlookup(C237,'Master data'!$A$1:$C$29,3,0) -> Biến phí | F237: =vlookup(C237,'Master data'!$A$1:$C$29,2,0) -> Chi phí hành chính
A238: 2023.09 | B238: 1032 gth 1270 | C238: Mua đồ hành chính | D238: 1000000 | E238: =vlookup(C238,'Master data'!$A$1:$C$29,3,0) -> Biến phí | F238: =vlookup(C238,'Master data'!$A$1:$C$29,2,0) -> Chi phí hành chính
A239: 2023.09 | B239: sửa ghế nha | C239: Mua đồ hành chính | D239: 200000 | E239: =vlookup(C239,'Master data'!$A$1:$C$29,3,0) -> Biến phí | F239: =vlookup(C239,'Master data'!$A$1:$C$29,2,0) -> Chi phí hành chính
A240: 2023.09 | B240: balo tặng khách | C240: Mua đồ hành chính | D240: 38415000 | E240: =vlookup(C240,'Master data'!$A$1:$C$29,3,0) -> Biến phí | F240: =vlookup(C240,'Master data'!$A$1:$C$29,2,0) -> Chi phí hành chính
A241: 2023.09 | B241: tiền seeding+mua tài khoản | C241: Mua đồ hành chính | D241: 5500000 | E241: =vlookup(C241,'Master data'!$A$1:$C$29,3,0) -> Biến phí | F241: =vlookup(C241,'Master data'!$A$1:$C$29,2,0) -> Chi phí hành chính
A242: 2023.09 | B242: 31TN Teennie | C242: Mua đồ hành chính | D242: 16517000 | E242: =vlookup(C242,'Master data'!$A$1:$C$29,3,0) -> Biến phí | F242: =vlookup(C242,'Master data'!$A$1:$C$29,2,0) -> Chi phí hành chính
A243: 2023.09 | B243: bàn chải kẽ | C243: Mua đồ hành chính | D243: 800000 | E243: =vlookup(C243,'Master data'!$A$1:$C$29,3,0) -> Biến phí | F243: =vlookup(C243,'Master data'!$A$1:$C$29,2,0) -> Chi phí hành chính
A244: 2023.09 | B244: đông phục teennie | C244: Mua đồ hành chính | D244: 4340000 | E244: =vlookup(C244,'Master data'!$A$1:$C$29,3,0) -> Biến phí | F244: =vlookup(C244,'Master data'!$A$1:$C$29,2,0) -> Chi phí hành chính
A245: 2023.09 | B245: 980 gth 1179 và 826 gth 1207 | C245: Mua đồ hành chính | D245: 2000000 | E245: =vlookup(C245,'Master data'!$A$1:$C$29,3,0) -> Biến phí | F245: =vlookup(C245,'Master data'!$A$1:$C$29,2,0) -> Chi phí hành chính
A246: 2023.09 | B246: phí sms brand name | C246: Mua đồ hành chính | D246: 400000 | E246: =vlookup(C246,'Master data'!$A$1:$C$29,3,0) -> Biến phí | F246: =vlookup(C246,'Master data'!$A$1:$C$29,2,0) -> Chi phí hành chính
... A507: 2024.01 | B507: Tổng hợp | C507: Mua đồ hành chính | D507: 0 | E507: =vlookup(C507,'Master data'!$A$1:$C$29,3,0) -> Biến phí | F507: =vlookup(C507,'Master data'!$A$1:$C$29,2,0) -> Chi phí hành chính
A508: 2024.01 | B508: Marketing | C508: Marketing chạy Quảng cáo | D508: =20000000+50000000+5000000+50000000+20000000+20000000+20000000+20000000 -> 205000000 | E508: =vlookup(C508,'Master data'!$A$1:$C$29,3,0) -> Biến phí | F508: =vlookup(C508,'Master data'!$A$1:$C$29,2,0) -> Chi phí bán hàng
A509: 2024.01 | B509: Số 5 kỳ Đồng | C509: Chi phí Mặt bằng | D509: =274725000/3 -> 91575000 | E509: =vlookup(C509,'Master data'!$A$1:$C$29,3,0) -> Định phí | F509: =vlookup(C509,'Master data'!$A$1:$C$29,2,0) -> Chi phí QLDN
A510: 2024.01 | B510: Điện kỳ đồng | C510: Điện + Nước | D510: =(36312000+3282000+4241000)/3 -> 14611667 | E510: =vlookup(C510,'Master data'!$A$1:$C$29,3,0) -> Định phí | F510: =vlookup(C510,'Master data'!$A$1:$C$29,2,0) -> Chi phí hành chính
A511: 2024.01 | B511: Hành chính chung | C511: Mua đồ hành chính | D511: 134960633 | E511: =vlookup(C511,'Master data'!$A$1:$C$29,3,0) -> Biến phí | F511: =vlookup(C511,'Master data'!$A$1:$C$29,2,0) -> Chi phí hành chính
A512: 2024.01 | B512: BH NV | C512: Bảo hiểm | D512: =21470720 -> 21470720 | E512: =vlookup(C512,'Master data'!$A$1:$C$29,3,0) -> Định phí | F512: =vlookup(C512,'Master data'!$A$1:$C$29,2,0) -> Chi phí QLDN
A513: 2024.01 | B513: bằng BS Huân | C513: Thuê bằng | D513: =22000000 -> 22000000 | E513: =vlookup(C513,'Master data'!$A$1:$C$29,3,0) -> Định phí | F513: =vlookup(C513,'Master data'!$A$1:$C$29,2,0) -> Chi phí QLDN
A514: 2024.01 | B514: thuê vp | C514: Chi phí Mặt bằng | D514: =24292000/3 -> 8097333.3 | E514: =vlookup(C514,'Master data'!$A$1:$C$29,3,0) -> Định phí | F514: =vlookup(C514,'Master data'!$A$1:$C$29,2,0) -> Chi phí QLDN
A515: 2024.01 | B515: Thuê bằng điều dưỡng cô Châu T1,2,3 | C515: Thuê bằng | D515: =9000000 -> 9000000 | E515: =vlookup(C515,'Master data'!$A$1:$C$29,3,0) -> Định phí | F515: =vlookup(C515,'Master data'!$A$1:$C$29,2,0) -> Chi phí QLDN
A516: 2024.01 | B516: wf | C516: Mua đồ hành chính | D516: =(1000000+1450000)/3 -> 816666.67 | E516: =vlookup(C516,'Master data'!$A$1:$C$29,3,0) -> Biến phí | F516: =vlookup(C516,'Master data'!$A$1:$C$29,2,0) -> Chi phí hành chính
A517: 2024.01 | B517: tiền xe nv t1 | C517: Tiền thuê xe | D517: 2333333 | E517: =vlookup(C517,'Master data'!$A$1:$C$29,3,0) -> Định phí | F517: =vlookup(C517,'Master data'!$A$1:$C$29,2,0) -> Chi phí hành chính
A518: 2024.01 | B518: lương bs | C518: Lương | D518: 136930000 | E518: =vlookup(C518,'Master data'!$A$1:$C$29,3,0) -> Định phí | F518: =vlookup(C518,'Master data'!$A$1:$C$29,2,0) -> Chi phí QLDN
A519: 2024.01 | B519: %bs | C519: KPI | D519: 418857023 | E519: =vlookup(C519,'Master data'!$A$1:$C$29,3,0) -> Biến phí | F519: =vlookup(C519,'Master data'!$A$1:$C$29,2,0) -> Chi phí bán hàng
A520: 2024.01 | B520: lương nv | C520: Lương | D520: 221899765 | E520: =vlookup(C520,'Master data'!$A$1:$C$29,3,0) -> Định phí | F520: =vlookup(C520,'Master data'!$A$1:$C$29,2,0) -> Chi phí QLDN
A521: 2024.01 | B521: % nv | C521: KPI | D521: 99379314 | E521: =vlookup(C521,'Master data'!$A$1:$C$29,3,0) -> Biến phí | F521: =vlookup(C521,'Master data'!$A$1:$C$29,2,0) -> Chi phí bán hàng
A522: 2024.01 | B522: vật liệu chỉnh nha(có kềm) | C522: Tiền vật liệu | D522: 6604000 | E522: =vlookup(C522,'Master data'!$A$1:$C$29,3,0) -> Biến phí | F522: =vlookup(C522,'Master data'!$A$1:$C$29,2,0) -> Chi phí giá vốn
A523: 2024.01 | B523: kềm bẻ dây cung | C523: Tiền vật liệu | D523: 4200000 | E523: =vlookup(C523,'Master data'!$A$1:$C$29,3,0) -> Biến phí | F523: =vlookup(C523,'Master data'!$A$1:$C$29,2,0) -> Chi phí giá vốn
A524: 2024.01 | B524: thun | C524: Tiền vật liệu | D524: 15150000 | E524: =vlookup(C524,'Master data'!$A$1:$C$29,3,0) -> Biến phí | F524: =vlookup(C524,'Master data'!$A$1:$C$29,2,0) -> Chi phí giá vốn
A525: 2024.01 | B525: Vật liệu morille t12/23 | C525: Tiền vật liệu | D525: 58336500 | E525: =vlookup(C525,'Master data'!$A$1:$C$29,3,0) -> Biến phí | F525: =vlookup(C525,'Master data'!$A$1:$C$29,2,0) -> Chi phí giá vốn
A526: 2024.01 | B526: thun | C526: Tiền vật liệu | D526: 5760000 | E526: =vlookup(C526,'Master data'!$A$1:$C$29,3,0) -> Biến phí | F526: =vlookup(C526,'Master data'!$A$1:$C$29,2,0) -> Chi phí giá vốn
A527: 2024.01 | B527: Mua khâu | C527: Tiền vật liệu | D527: 35616700 | E527: =vlookup(C527,'Master data'!$A$1:$C$29,3,0) -> Biến phí | F527: =vlookup(C527,'Master data'!$A$1:$C$29,2,0) -> Chi phí giá vốn
A528: 2024.01 | B528: Vật liệu Thanh Ngọc T12/23 | C528: Tiền vật liệu | D528: 32865000 | E528: =vlookup(C528,'Master data'!$A$1:$C$29,3,0) -> Biến phí | F528: =vlookup(C528,'Master data'!$A$1:$C$29,2,0) -> Chi phí giá vốn
A529: 2024.01 | B529: khis cụ t1/24 | C529: Tiền vật liệu | D529: 12600000 | E529: =vlookup(C529,'Master data'!$A$1:$C$29,3,0) -> Biến phí | F529: =vlookup(C529,'Master data'!$A$1:$C$29,2,0) -> Chi phí giá vốn
A530: 2024.01 | B530: Thưởng cuối năm | C530: Quỹ thưởng tổng cuối năm | D530: =7237269.094 -> 7237269.1 | E530: =vlookup(C530,'Master data'!$A$1:$C$29,3,0) -> Định phí | F530: =vlookup(C530,'Master data'!$A$1:$C$29,2,0) -> Chi phí khác
A531: 2024.01 | B531: lễ tất niên | C531: Quỹ thưởng tổng cuối năm | D531: 11111111 | E531: =vlookup(C531,'Master data'!$A$1:$C$29,3,0) -> Định phí | F531: =vlookup(C531,'Master data'!$A$1:$C$29,2,0) -> Chi phí khác
A532: 2024.01 | B532: Tài sản | C532: Mua sắm tài sản | D532: 0 | E532: =vlookup(C532,'Master data'!$A$1:$C$29,3,0) -> Chi phí khác | F532: =vlookup(C532,'Master data'!$A$1:$C$29,2,0) -> Chi phí khác
A533: 2024.02 | B533: Tổng hợp | C533: Mua đồ hành chính | D533: 0 | E533: =vlookup(C533,'Master data'!$A$1:$C$29,3,0) -> Biến phí | F533: =vlookup(C533,'Master data'!$A$1:$C$29,2,0) -> Chi phí hành chính
A534: 2024.02 | B534: Hành chính chung | C534: Mua đồ hành chính | D534: 37180335 | E534: =vlookup(C534,'Master data'!$A$1:$C$29,3,0) -> Biến phí | F534: =vlookup(C534,'Master data'!$A$1:$C$29,2,0) -> Chi phí hành chính
A535: 2024.02 | B535: 675 gth 1681 | C535: Marketing chạy Quảng cáo | D535: 1000000 | E535: =vlookup(C535,'Master data'!$A$1:$C$29,3,0) -> Biến phí | F535: =vlookup(C535,'Master data'!$A$1:$C$29,2,0) -> Chi phí bán hàng
A536: 2024.02 | B536: hộp quà+túi Teennie, in logo dán hộp quà+hình nghẹ sĩ, in bằng tốt nghiêph | C536: Marketing chạy Quảng cáo | D536: 1780000 | E536: =vlookup(C536,'Master data'!$A$1:$C$29,3,0) -> Biến phí | F536: =vlookup(C536,'Master data'!$A$1:$C$29,2,0) -> Chi phí bán hàng
A537: 2024.02 | B537: Hạt điều tặng khách+tiền nem+tiền ship quà+thịt rừng tặng sếp | C537: Marketing chạy Quảng cáo | D537: 6686666 | E537: =vlookup(C537,'Master data'!$A$1:$C$29,3,0) -> Biến phí | F537: =vlookup(C537,'Master data'!$A$1:$C$29,2,0) -> Chi phí bán hàng
A538: 2024.02 | B538: khách xem phong thuỷ | C538: Marketing chạy Quảng cáo | D538: 5416667 | E538: =vlookup(C538,'Master data'!$A$1:$C$29,3,0) -> Biến phí | F538: =vlookup(C538,'Master data'!$A$1:$C$29,2,0) -> Chi phí bán hàng
A539: 2024.02 | B539: phí cà thẻ T2 | C539: Phí cà thẻ | D539: 2637676 | E539: =vlookup(C539,'Master data'!$A$1:$C$29,3,0) -> Biến phí | F539: =vlookup(C539,'Master data'!$A$1:$C$29,2,0) -> Chi phí bán hàng
A540: 2024.02 | B540: nạp qc | C540: Marketing chạy Quảng cáo | D540: 175000000 | E540: =vlookup(C540,'Master data'!$A$1:$C$29,3,0) -> Biến phí | F540: =vlookup(C540,'Master data'!$A$1:$C$29,2,0) -> Chi phí bán hàng
A541: 2024.02 | B541: SEO web | C541: Marketing chạy Quảng cáo | D541: 11000000 | E541: =vlookup(C541,'Master data'!$A$1:$C$29,3,0) -> Biến phí | F541: =vlookup(C541,'Master data'!$A$1:$C$29,2,0) -> Chi phí bán hàng
A542: 2024.02 | B542: Số 5 kỳ Đồng | C542: Chi phí Mặt bằng | D542: =276300000/3 -> 92100000 | E542: =vlookup(C542,'Master data'!$A$1:$C$29,3,0) -> Định phí | F542: =vlookup(C542,'Master data'!$A$1:$C$29,2,0) -> Chi phí QLDN
A543: 2024.02 | B543: Điện kỳ đồng | C543: Điện + Nước | D543: =(4209257+4168660+44598163)/3 -> 17658693 | E543: =vlookup(C543,'Master data'!$A$1:$C$29,3,0) -> Định phí | F543: =vlookup(C543,'Master data'!$A$1:$C$29,2,0) -> Chi phí hành chính
A544: 2024.02 | B544: Nước kỳ đồng T1 | C544: Điện + Nước | D544: =4085027/3 -> 1361675.7 | E544: =vlookup(C544,'Master data'!$A$1:$C$29,3,0) -> Định phí | F544: =vlookup(C544,'Master data'!$A$1:$C$29,2,0) -> Chi phí hành chính
A545: 2024.02 | B545: BH NV( 7.045.080 ) | C545: Bảo hiểm | D545: 21470720 | E545: =vlookup(C545,'Master data'!$A$1:$C$29,3,0) -> Định phí | F545: =vlookup(C545,'Master data'!$A$1:$C$29,2,0) -> Chi phí QLDN
A546: 2024.02 | B546: bằng BS Huân | C546: Thuê bằng | D546: 22000000 | E546: =vlookup(C546,'Master data'!$A$1:$C$29,3,0) -> Định phí | F546: =vlookup(C546,'Master data'!$A$1:$C$29,2,0) -> Chi phí QLDN
A547: 2024.02 | B547: thuê vp | C547: Chi phí Mặt bằng | D547: =23602000/3 -> 7867333.3 | E547: =vlookup(C547,'Master data'!$A$1:$C$29,3,0) -> Định phí | F547: =vlookup(C547,'Master data'!$A$1:$C$29,2,0) -> Chi phí QLDN
A548: 2024.02 | B548: wf | C548: Mua đồ hành chính | D548: =(1145000+1000000)/3 -> 715000 | E548: =vlookup(C548,'Master data'!$A$1:$C$29,3,0) -> Biến phí | F548: =vlookup(C548,'Master data'!$A$1:$C$29,2,0) -> Chi phí hành chính
A549: 2024.02 | B549: Nước kỳ đồng T2 | C549: Điện + Nước | D549: =4388296/3 -> 1462765.3 | E549: =vlookup(C549,'Master data'!$A$1:$C$29,3,0) -> Định phí | F549: =vlookup(C549,'Master data'!$A$1:$C$29,2,0) -> Chi phí hành chính
A550: 2024.02 | B550: (đô thị 2, TCAP 1, PCA 1, giao thông2) | C550: Mua đồ hành chính | D550: 5700000 | E550: =vlookup(C550,'Master data'!$A$1:$C$29,3,0) -> Biến phí | F550: =vlookup(C550,'Master data'!$A$1:$C$29,2,0) -> Chi phí hành chính
A551: 2024.02 | B551: Cho thuế hàng tháng (t1,2,3) | C551: Mua đồ hành chính | D551: 1000000 | E551: =vlookup(C551,'Master data'!$A$1:$C$29,3,0) -> Biến phí | F551: =vlookup(C551,'Master data'!$A$1:$C$29,2,0) -> Chi phí hành chính
A552: 2024.02 | B552: lương bs | C552: Lương | D552: 99597895 | E552: =vlookup(C552,'Master data'!$A$1:$C$29,3,0) -> Định phí | F552: =vlookup(C552,'Master data'!$A$1:$C$29,2,0) -> Chi phí QLDN
A553: 2024.02 | B553: %bs | C553: KPI | D553: 262272235 | E553: =vlookup(C553,'Master data'!$A$1:$C$29,3,0) -> Biến phí | F553: =vlookup(C553,'Master data'!$A$1:$C$29,2,0) -> Chi phí bán hàng
A554: 2024.02 | B554: lương nv | C554: Lương | D554: 202157609 | E554: =vlookup(C554,'Master data'!$A$1:$C$29,3,0) -> Định phí | F554: =vlookup(C554,'Master data'!$A$1:$C$29,2,0) -> Chi phí QLDN
A555: 2024.02 | B555: % nv | C555: KPI | D555: 40929313 | E555: =vlookup(C555,'Master data'!$A$1:$C$29,3,0) -> Biến phí | F555: =vlookup(C555,'Master data'!$A$1:$C$29,2,0) -> Chi phí bán hàng
A556: 2024.02 | B556: vít chỉnh nha | C556: Tiền vật liệu | D556: 15000000 | E556: =vlookup(C556,'Master data'!$A$1:$C$29,3,0) -> Biến phí | F556: =vlookup(C556,'Master data'!$A$1:$C$29,2,0) -> Chi phí giá vốn
A557: 2024.02 | B557: vật tư Teennie | C557: Tiền vật liệu | D557: 5176000 | E557: =vlookup(C557,'Master data'!$A$1:$C$29,3,0) -> Biến phí | F557: =vlookup(C557,'Master data'!$A$1:$C$29,2,0) -> Chi phí giá vốn
A558: 2024.02 | B558: lò xo | C558: Tiền vật liệu | D558: 880000 | E558: =vlookup(C558,'Master data'!$A$1:$C$29,3,0) -> Biến phí | F558: =vlookup(C558,'Master data'!$A$1:$C$29,2,0) -> Chi phí giá vốn
A559: 2024.02 | B559: 100 tặng 20b mắc cài | C559: Tiền vật liệu | D559: 36750000 | E559: =vlookup(C559,'Master data'!$A$1:$C$29,3,0) -> Biến phí | F559: =vlookup(C559,'Master data'!$A$1:$C$29,2,0) -> Chi phí giá vốn
A560: 2024.02 | B560: nhựa hàm duy trì | C560: Tiền vật liệu | D560: 965000 | E560: =vlookup(C560,'Master data'!$A$1:$C$29,3,0) -> Biến phí | F560: =vlookup(C560,'Master data'!$A$1:$C$29,2,0) -> Chi phí giá vốn
A561: 2024.02 | B561: khay tinh chỉnh | C561: Tiền vật liệu | D561: 405000 | E561: =vlookup(C561,'Master data'!$A$1:$C$29,3,0) -> Biến phí | F561: =vlookup(C561,'Master data'!$A$1:$C$29,2,0) -> Chi phí giá vốn
A562: 2024.02 | B562: Thanh Ngọc T1 | C562: Tiền vật liệu | D562: 28635000 | E562: =vlookup(C562,'Master data'!$A$1:$C$29,3,0) -> Biến phí | F562: =vlookup(C562,'Master data'!$A$1:$C$29,2,0) -> Chi phí giá vốn
A563: 2024.02 | B563: mua máy in+ổ cứng | C563: Mua sắm tài sản | D563: =16535000/3 -> 5511666.7 | E563: =vlookup(C563,'Master data'!$A$1:$C$29,3,0) -> Chi phí khác | F563: =vlookup(C563,'Master data'!$A$1:$C$29,2,0) -> Chi phí khác
A564: 2024.02 | B564: mua xe đẩy | C564: Mua sắm tài sản | D564: 1650000 | E564: =vlookup(C564,'Master data'!$A$1:$C$29,3,0) -> Chi phí khác | F564: =vlookup(C564,'Master data'!$A$1:$C$29,2,0) -> Chi phí khác
A565: 2024.02 | B565: Trích quỹ tất niên | C565: Quỹ thưởng tổng cuối năm | D565: =(400000000/3)/12 -> 11111111 | E565: =vlookup(C565,'Master data'!$A$1:$C$29,3,0) -> Định phí | F565: =vlookup(C565,'Master data'!$A$1:$C$29,2,0) -> Chi phí khác
...

Sheet Doanh thu_Teennie
A1: THÁNG | B1: NGÀY | C1: TIỀN MẶT | D1: CÀ THẺ | E1: THỰC NHẬN CÀ THẺ | F1: CHUYỂN KHOẢN | G1: TRẢ CỌC | H1: TỔNG | I1: TỔNG TRỪ PHÍ CÀ THẺ
A2: 2023.01 | B2: 44927 | C2: 8600000 | D2: 9600000 | E2: 9501000 | F2: 7400000 | G2: 0 | H2: 25600000 | I2: 25501000
A3: 2023.01 | B3: 44928 | C3: 0 | D3: 0 | E3: 0 | F3: 0 | G3: 0 | H3: 0 | I3: 0
A4: 2023.01 | B4: 44929 | C4: 11290000 | D4: 4700000 | E4: 4637300 | F4: 15230000 | G4: 0 | H4: 31220000 | I4: 31157300
A5: 2023.01 | B5: 44930 | C5: 12840000 | D5: 41320000 | E5: 40678880 | F5: 16920000 | G5: 0 | H5: 71080000 | I5: 70438880
A6: 2023.01 | B6: 44931 | C6: 36045000 | D6: 5250000 | E6: 5186800 | F6: 5140000 | G6: 0 | H6: 46435000 | I6: 46371800
A7: 2023.01 | B7: 44932 | C7: 12100000 | D7: 7500000 | E7: 7430500 | F7: 36490000 | G7: 0 | H7: 56090000 | I7: 56020500
A8: 2023.01 | B8: 44933 | C8: 12730000 | D8: 16060000 | E8: 15803040 | F8: 13970000 | G8: 0 | H8: 42760000 | I8: 42503040
A9: 2023.01 | B9: 44934 | C9: 13650000 | D9: 4200000 | E9: 4132800 | F9: 8750000 | G9: 0 | H9: 26600000 | I9: 26532800
A10: 2023.01 | B10: 44935 | C10: 5150000 | D10: 13045000 | E10: 12859780 | F10: 10015000 | G10: 0 | H10: 28210000 | I10: 28024780
A11: 2023.01 | B11: 44936 | C11: 5245000 | D11: 3400000 | E11: 3338100 | F11: 27040000 | G11: 0 | H11: 35685000 | I11: 35623100
A12: 2023.01 | B12: 44937 | C12: 3505000 | D12: 9045000 | E12: 8900000 | F12: 23090000 | G12: 0 | H12: 35640000 | I12: 35495000
A13: 2023.01 | B13: 44938 | C13: 10100000 | D13: 3650000 | E13: 3604000 | F13: 10540000 | G13: 0 | H13: 24290000 | I13: 24244000
... A349: 2023.12 | B349: 45291 | C349: 21742555 | D349: 9395000 | E349: 9237680 | F349: 36267000 | G349: 0 | H349: 67404555 | I349: 67247235
A350: 2024.01 | B350: 45292 | C350: 0 | D350: 0 | E350: 0 | F350: 0 | G350: 0 | H350: =C350+D350+F350-G350 -> 0 | I350: =((C350+E350)+F350)-G350 -> 0
A351: 2024.01 | B351: 45293 | C351: 9895000 | D351: 29515000 | E351: 20046710 | F351: 9665000 | G351: 0 | H351: =C351+D351+F351-G351 -> 49075000 | I351: =C351+E350+F351-G351 -> 19560000
A352: 2024.01 | B352: 45294 | C352: 13887000 | D352: 12195000 | E352: 11989880 | F352: 25318000 | G352: 0 | H352: =C352+D352+F352-G352 -> 51400000 | I352: =C352+E352+F352-G352 -> 51194880
A353: 2024.01 | B353: 45295 | C353: 16850000 | D353: 25740000 | E353: 25334660 | F353: 19755000 | G353: 0 | H353: =C353+D353+F353-G353 -> 62345000 | I353: =C353+E353+F353-G353 -> 61939660
A354: 2024.01 | B354: 45296 | C354: 10050000 | D354: 20050000 | E354: 19730200 | F354: 61067000 | G354: 0 | H354: =C354+D354+F354-G354 -> 91167000 | I354: =C354+E354+F354-G354 -> 90847200
A355: 2024.01 | B355: 45297 | C355: 24269000 | D355: 68380000 | E355: 67317420 | F355: 36465000 | G355: 0 | H355: =C355+D355+F355-G355 -> 129114000 | I355: =C355+E355+F355-G355 -> 128051420
A356: 2024.01 | B356: 45298 | C356: 19055000 | D356: 27455000 | E356: 27015720 | F356: 43418333 | G356: 0 | H356: =C356+D356+F356-G356 -> 89928333 | I356: =C356+E356+F356-G356 -> 89489053
A357: 2024.01 | B357: 45299 | C357: 40495000 | D357: 5505000 | E357: 5421870 | F357: 35787000 | G357: 0 | H357: =C357+D357+F357-G357 -> 81787000 | I357: =C357+E357+F357-G357 -> 81703870
A358: 2024.01 | B358: 45300 | C358: 12780000 | D358: 4645000 | E358: 4577860 | F358: 17155000 | G358: 0 | H358: =C358+D358+F358-G358 -> 34580000 | I358: =C358+E358+F358-G358 -> 34512860
A359: 2024.01 | B359: 45301 | C359: 8232000 | D359: 4585000 | E359: 4516590 | F359: 34065000 | G359: 0 | H359: =C359+D359+F359-G359 -> 46882000 | I359: =C359+E359+F359-G359 -> 46813590
A360: 2024.01 | B360: 45302 | C360: 13145000 | D360: 3250000 | E360: 3198000 | F360: 27380818 | G360: 0 | H360: =C360+D360+F360-G360 -> 43775818 | I360: =C360+E360+F360-G360 -> 43723818
A361: 2024.01 | B361: 45303 | C361: 11955000 | D361: 7695000 | E361: 7568180 | F361: 47172000 | G361: 0 | H361: =C361+D361+F361-G361 -> 66822000 | I361: =C361+E361+F361-G361 -> 66695180
A362: 2024.01 | B362: 45304 | C362: 33926000 | D362: 17380000 | E362: 17100450 | F362: 26015000 | G362: 0 | H362: =C362+D362+F362-G362 -> 77321000 | I362: =C362+E362+F362-G362 -> 77041450
A363: 2024.01 | B363: 45305 | C363: 5950000 | D363: 1660000 | E363: 1633440 | F363: 28690000 | G363: 0 | H363: =C363+D363+F363-G363 -> 36300000 | I363: =C363+E363+F363-G363 -> 36273440
... A367: 2024.01 | B367: 45309 | C367: 10195000 | D367: 7100000 | E367: 6977200 | F367: 40945000 | G367: 0 | H367: =C367+D367+F367-G367 -> 58240000 | I367: =C367+E367+F367-G367 -> 58117200
A368: 2024.01 | B368: 45310 | C368: 9470000 | D368: 9955000 | E368: 9784800 | F368: =20925000+12580000 -> 33505000 | G368: 0 | H368: =C368+D368+F368-G368 -> 52930000 | I368: =C368+E368+F368-G368 -> 52759800
A369: 2024.01 | B369: 45311 | C369: 12907000 | D369: 9190000 | E369: 9035960 | F369: 33171666 | G369: 0 | H369: =C369+D369+F369-G369 -> 55268666 | I369: =C369+E369+F369-G369 -> 55114626
A370: 2024.01 | B370: 45312 | C370: 23950000 | D370: 13130000 | E370: 12925370 | F370: 33335000 | G370: 0 | H370: =C370+D370+F370-G370 -> 70415000 | I370: =C370+E370+F370-G370 -> 70210370
A371: 2024.01 | B371: 45313 | C371: 6891000 | D371: 16145000 | E371: 15886370 | F371: 21451666 | G371: 0 | H371: =C371+D371+F371-G371 -> 44487666 | I371: =C371+E371+F371-G371 -> 44229036
A372: 2024.01 | B372: 45314 | C372: 16305000 | D372: 3715000 | E372: 3655540 | F372: 18177000 | G372: 0 | H372: =C372+D372+F372-G372 -> 38197000 | I372: =C372+E372+F372-G372 -> 38137540
A373: 2024.01 | B373: 45315 | C373: 7180000 | D373: 245000 | E373: 241080 | F373: 25535000 | G373: 0 | H373: =C373+D373+F373-G373 -> 32960000 | I373: =C373+E373+F373-G373 -> 32956080
A374: 2024.01 | B374: 45316 | C374: 5900000 | D374: 2100000 | E374: 2061400 | F374: 39465000 | G374: 0 | H374: =C374+D374+F374-G374 -> 47465000 | I374: =C374+E374+F374-G374 -> 47426400
A375: 2024.01 | B375: 45317 | C375: 28960000 | D375: 4194444 | E375: 4127333 | F375: 37735000 | G375: 0 | H375: =C375+D375+F375-G375 -> 70889444 | I375: =C375+E375+F375-G375 -> 70822333
A376: 2024.01 | B376: 45318 | C376: 10940000 | D376: 9495000 | E376: 9294680 | F376: 33790555 | G376: 0 | H376: =C376+D376+F376-G376 -> 54225555 | I376: =C376+E376+F376-G376 -> 54025235
A377: 2024.01 | B377: 45319 | C377: 27715000 | D377: 24010000 | E377: 23625840 | F377: 49224000 | G377: 0 | H377: =C377+D377+F377-G377 -> 100949000 | I377: =C377+E377+F377-G377 -> 100564840
A378: 2024.01 | B378: 45320 | C378: 12965000 | D378: 3095000 | E378: 3049010 | F378: 7070000 | G378: 0 | H378: =C378+D378+F378-G378 -> 23130000 | I378: =C378+E378+F378-G378 -> 23084010
A379: 2024.01 | B379: 45321 | C379: 7495000 | D379: 15245000 | E379: 15001080 | F379: 19940000 | G379: 0 | H379: =C379+D379+F379-G379 -> 42680000 | I379: =C379+E379+F379-G379 -> 42436080
A380: 2024.01 | B380: 45322 | C380: 4590000 | D380: 2450000 | E380: 2410800 | F380: 28982000 | G380: 0 | H380: =C380+D380+F380-G380 -> 36022000 | I380: =C380+E380+F380-G380 -> 35982800
A381: 2024.02 | B381: 45323 | C381: 17810000 | D381: 19265000 | E381: 18933460 | F381: 30231000 | G381: 0 | H381: 67306000 | I381: 66974460
A382: 2024.02 | B382: 45324 | C382: 7900000 | D382: 12790000 | E382: 12573360 | F382: 35035000 | G382: 0 | H382: 55725000 | I382: 55508360
A383: 2024.02 | B383: 45325 | C383: 20075000 | D383: 8750000 | E383: 8643500 | F383: 25415000 | G383: 0 | H383: 54240000 | I383: 54133500
A384: 2024.02 | B384: 45326 | C384: 5450000 | D384: 2500000 | E384: 2442160 | F384: 5850000 | G384: 0 | H384: 13800000 | I384: 13742160
A385: 2024.02 | B385: 45327 | C385: 0 | D385: 0 | E385: 0 | F385: 0 | G385: 0 | H385: 0 | I385: 0
A386: 2024.02 | B386: 45328 | C386: 0 | D386: 0 | E386: 0 | F386: 0 | G386: 0 | H386: 0 | I386: 0
A387: 2024.02 | B387: 45329 | C387: 0 | D387: 0 | E387: 0 | F387: 0 | G387: 0 | H387: 0 | I387: 0
A388: 2024.02 | B388: 45330 | C388: 0 | D388: 0 | E388: 0 | F388: 0 | G388: 0 | H388: 0 | I388: 0
A389: 2024.02 | B389: 45331 | C389: 0 | D389: 0 | E389: 0 | F389: 0 | G389: 0 | H389: 0 | I389: 0
A390: 2024.02 | B390: 45332 | C390: 0 | D390: 0 | E390: 0 | F390: 0 | G390: 0 | H390: 0 | I390: 0
A391: 2024.02 | B391: 45333 | C391: 0 | D391: 0 | E391: 0 | F391: 0 | G391: 0 | H391: 0 | I391: 0
A392: 2024.02 | B392: 45334 | C392: 0 | D392: 0 | E392: 0 | F392: 0 | G392: 0 | H392: 0 | I392: 0
... A409: 2024.02 | B409: 45351 | C409: 18550000 | D409: 4530000 | E409: 4457510 | F409: 57075000 | G409: 0 | H409: 80155000 | I409: 80082510
A410: 2024.03 | B410: 45352 | C410: 10100000 | D410: 6595000 | E410: 6501480 | F410: 64461000 | G410: 0 | H410: =C410+D410+F410-G410 -> 81156000 | I410: =((C410+E410)+F410)-G410 -> 81062480
A411: 2024.03 | B411: 45353 | C411: 17906000 | D411: 23100000 | E411: 22743400 | F411: 64734000 | G411: 0 | H411: =C411+D411+F411-G411 -> 105740000 | I411: =C411+E411+F411-G411 -> 105383400
A412: 2024.03 | B412: 45354 | C412: 26327000 | D412: 8695000 | E412: 8555880 | F412: 38581818 | G412: 0 | H412: =C412+D412+F412-G412 -> 73603818 | I412: =C412+E412+F412-G412 -> 73464698
A413: 2024.03 | B413: 45355 | C413: 21995000 | D413: 5500000 | E413: 5412000 | F413: 23570000 | G413: 0 | H413: =C413+D413+F413-G413 -> 51065000 | I413: =C413+E413+F413-G413 -> 50977000
A414: 2024.03 | B414: 45356 | C414: 8700000 | D414: 8180000 | E414: 8039040 | F414: 37966666 | G414: 500000 | H414: =C414+D414+F414-G414 -> 54346666 | I414: =C414+E414+F414-G414 -> 54205706
A415: 2024.03 | B415: 45357 | C415: 19520000 | D415: 245000 | E415: 241080 | F415: 29290000 | G415: 0 | H415: =C415+D415+F415-G415 -> 49055000 | I415: =C415+E415+F415-G415 -> 49051080
A416: 2024.03 | B416: 45358 | C416: 20175000 | D416: 1395000 | E416: 1384180 | F416: 23340000 | G416: 0 | H416: =C416+D416+F416-G416 -> 44910000 | I416: =C416+E416+F416-G416 -> 44899180
A417: 2024.03 | B417: 45359 | C417: 3420000 | D417: 3050000 | E417: 3001200 | F417: 8990000 | G417: 0 | H417: =C417+D417+F417-G417 -> 15460000 | I417: =C417+E417+F417-G417 -> 15411200
A418: 2024.03 | B418: 45360 | C418: 22720000 | D418: 4985000 | E418: 4913400 | F418: 81630000 | G418: 0 | H418: =C418+D418+F418-G418 -> 109335000 | I418: =C418+E418+F418-G418 -> 109263400
A419: 2024.03 | B419: 45361 | C419: 41775000 | D419: 10150000 | E419: 10008600 | F419: 34820000 | G419: 0 | H419: =C419+D419+F419-G419 -> 86745000 | I419: =C419+E419+F419-G419 -> 86603600
A420: 2024.03 | B420: 45362 | C420: 6595000 | D420: 350000 | E420: 344400 | F420: 15595000 | G420: 0 | H420: =C420+D420+F420-G420 -> 22540000 | I420: =C420+E420+F420-G420 -> 22534400
A421: 2024.03 | B421: 45363 | C421: 3960000 | D421: 1500000 | E421: 1485000 | F421: 21420000 | G421: 0 | H421: =C421+D421+F421-G421 -> 26880000 | I421: =C421+E421+F421-G421 -> 26865000
A422: 2024.03 | B422: 45364 | C422: 9190000 | D422: 3632500 | E422: 3598208 | F422: 24702000 | G422: 0 | H422: =C422+D422+F422-G422 -> 37524500 | I422: =C422+E422+F422-G422 -> 37490208
... A438: 2024.03 | B438: 45380 | C438: 10717000 | D438: 5200000 | E438: 5125800 | F438: 46211666 | G438: 0 | H438: =C438+D438+F438-G438 -> 62128666 | I438: =C438+E438+F438-G438 -> 62054466
A439: 2024.03 | B439: 45381 | C439: 19035000 | D439: 22140000 | E439: =14288895+7468560 -> 21757455 | F439: 91528714 | G439: 0 | H439: =C439+D439+F439-G439 -> 132703714 | I439: =C439+E439+F439-G439 -> 132321169
A440: 2024.03 | B440: 45382 | C440: 36585000 | D440: 6250000 | E440: 6150000 | F440: 22895000 | G440: 0 | H440: =C440+D440+F440-G440 -> 65730000 | I440: =C440+E440+F440-G440 -> 65630000
A441: 2024.04 | B441: 45383 | C441: 5200000 | D441: 0 | E441: 0 | F441: 18950000 | G441: 0 | H441: =C441+D441+F441-G441 -> 24150000 | I441: =((C441+E441)+F441)-G441 -> 24150000
A442: 2024.04 | B442: 45384 | C442: 15510000 | D442: 7620000 | E442: 7488480 | F442: 46764444 | G442: 0 | H442: =C442+D442+F442-G442 -> 69894444 | I442: =C442+E442+F442-G442 -> 69762924
A443: 2024.04 | B443: 45385 | C443: 3545000 | D443: 8950000 | E443: 8809800 | F443: 12250000 | G443: 0 | H443: =C443+D443+F443-G443 -> 24745000 | I443: =C443+E443+F443-G443 -> 24604800
A444: 2024.04 | B444: 45386 | C444: 10610000 | D444: 6595000 | E444: 6498580 | F444: 50487727 | G444: 0 | H444: =C444+D444+F444-G444 -> 67692727 | I444: =C444+E444+F444-G444 -> 67596307
A445: 2024.04 | B445: 45387 | C445: 8060000 | D445: 2450000 | E445: 2412800 | F445: 36210000 | G445: 1895000 | H445: =C445+D445+F445-G445 -> 44825000 | I445: =C445+E445+F445-G445 -> 44787800
A446: 2024.04 | B446: 45388 | C446: 24412000 | D446: 11085000 | E446: 10908840 | F446: 37759666 | G446: 0 | H446: =C446+D446+F446-G446 -> 73256666 | I446: =C446+E446+F446-G446 -> 73080506
A447: 2024.04 | B447: 45389 | C447: 15065000 | D447: 11135000 | E447: 10956840 | F447: 51905000 | G447: 0 | H447: =C447+D447+F447-G447 -> 78105000 | I447: =C447+E447+F447-G447 -> 77926840
A448: 2024.04 | B448: 45390 | C448: 5750000 | D448: 2900000 | E448: 2853600 | F448: 22050000 | G448: 0 | H448: =C448+D448+F448-G448 -> 30700000 | I448: =C448+E448+F448-G448 -> 30653600
A449: 2024.04 | B449: 45391 | C449: 560000 | D449: 1050000 | E449: 1033700 | F449: 13910000 | G449: 0 | H449: =C449+D449+F449-G449 -> 15520000 | I449: =C449+E449+F449-G449 -> 15503700
A450: 2024.04 | B450: 45392 | C450: 2070000 | D450: 2692500 | E450: 2651345 | F450: 17812000 | G450: 0 | H450: =C450+D450+F450-G450 -> 22574500 | I450: =C450+E450+F450-G450 -> 22533345
A451: 2024.04 | B451: 45393 | C451: 2060000 | D451: 4680000 | E451: 4597110 | F451: 45210000 | G451: 0 | H451: =C451+D451+F451-G451 -> 51950000 | I451: =C451+E451+F451-G451 -> 51867110
A452: 2024.04 | B452: 45394 | C452: 7575000 | D452: 8035000 | E452: 7891880 | F452: 21365000 | G452: 0 | H452: =C452+D452+F452-G452 -> 36975000 | I452: =C452+E452+F452-G452 -> 36831880
A453: 2024.04 | B453: 45395 | C453: 22385000 | D453: 12545000 | E453: 12350280 | F453: 45566000 | G453: 0 | H453: =C453+D453+F453-G453 -> 80496000 | I453: =C453+E453+F453-G453 -> 80301280
... A459: 2024.04 | B459: 45401 | C459: 10210000 | D459: 3950000 | E459: 3916300 | F459: 29891666 | G459: 0 | H459: =C459+D459+F459-G459 -> 44051666 | I459: =C459+E459+F459-G459 -> 44017966
A460: 2024.04 | B460: 45402 | C460: 20520000 | D460: 24753846 | E460: =17676593+6636784 -> 24313377 | F460: 53110909 | G460: 0 | H460: =C460+D460+F460-G460 -> 98384755 | I460: =C460+E460+F460-G460 -> 97944286
A461: 2024.04 | B461: 45403 | C461: 29515000 | D461: 8344444 | E461: 8208133 | F461: 51417151 | G461: 0 | H461: =C461+D461+F461-G461 -> 89276595 | I461: =C461+E461+F461-G461 -> 89140284
A462: 2024.04 | B462: 45404 | C462: 6450000 | D462: 2750000 | E462: 2706000 | F462: 30160000 | G462: 0 | H462: =C462+D462+F462-G462 -> 39360000 | I462: =C462+E462+F462-G462 -> 39316000
A463: 2024.04 | B463: 45405 | C463: 19480000 | D463: 5300000 | E463: 5215200 | F463: 33385000 | G463: 0 | H463: =C463+D463+F463-G463 -> 58165000 | I463: =C463+E463+F463-G463 -> 58080200
A464: 2024.04 | B464: 45406 | C464: 18767000 | D464: 2350000 | E464: 2315400 | F464: 30342000 | G464: 0 | H464: =C464+D464+F464-G464 -> 51459000 | I464: =C464+E464+F464-G464 -> 51424400
A465: 2024.04 | B465: 45407 | C465: 13030000 | D465: 20035000 | E465: 19654440 | F465: 95470000 | G465: 0 | H465: =C465+D465+F465-G465 -> 128535000 | I465: =C465+E465+F465-G465 -> 128154440
A466: 2024.04 | B466: 45408 | C466: 2800000 | D466: 2600000 | E466: 2558400 | F466: 18160000 | G466: 0 | H466: =C466+D466+F466-G466 -> 23560000 | I466: =C466+E466+F466-G466 -> 23518400
A467: 2024.04 | B467: 45409 | C467: 15500000 | D467: 4695000 | E467: 4625880 | F467: 40655714 | G467: 0 | H467: =C467+D467+F467-G467 -> 60850714 | I467: =C467+E467+F467-G467 -> 60781594
A468: 2024.04 | B468: 45410 | C468: 23197000 | D468: 10225000 | E468: 10016400 | F468: 32779000 | G468: 0 | H468: =C468+D468+F468-G468 -> 66201000 | I468: =C468+E468+F468-G468 -> 65992400
A469: 2024.04 | B469: 45411 | C469: 1500000 | D469: 2850000 | E469: 2804400 | F469: 17160000 | G469: 0 | H469: =C469+D469+F469-G469 -> 21510000 | I469: =C469+E469+F469-G469 -> 21464400
A470: 2024.04 | B470: 45412 | C470: 0 | D470: 0 | E470: 0 | F470: 0 | G470: 0 | H470: =C470+D470+F470-G470 -> 0 | I470: =C470+E470+F470-G470 -> 0
A471: 2024.05 | B471: 45413 | C471: 0 | D471: 0 | E471: 0 | F471: 0 | G471: 0 | H471: 0 | I471: 0
A472: 2024.05 | B472: 45414 | C472: 10370000 | D472: 2950000 | E472: 2889100 | F472: 28675909 | G472: 0 | H472: 41995909 | I472: 41935009
A473: 2024.05 | B473: 45415 | C473: 12450000 | D473: 9800000 | E473: 9643200 | F473: 19295000 | G473: 0 | H473: 41545000 | I473: 41388200
A474: 2024.05 | B474: 45416 | C474: 15677000 | D474: 7850000 | E474: 7724400 | F474: 34470000 | G474: 0 | H474: 57997000 | I474: 57871400
...

Sheet Nhật ký doanh thu
A1: THÁNG | B1: NGÀY | C1: TIỀN MẶT | D1: CÀ THẺ | E1: THỰC NHẬN CÀ THẺ | F1: CHUYỂN KHOẢN | G1: TRẢ CỌC | H1: TỔNG | I1: TỔNG TRỪ PHÍ CÀ THẺ
A2: 2021.01 | B2: 44197 | C2: 0 | D2: 0 | E2: 0 | F2: 0 | G2: 0 | H2: 0 | I2: 0
A3: 2021.01 | B3: 44198 | C3: 94400000 | D3: 14280000 | E3: 14059710 | F3: 0 | G3: 0 | H3: 108680000 | I3: 108459710
A4: 2021.01 | B4: 44199 | C4: 9308000 | D4: 65000000 | E4: 63903500 | F4: 10400000 | G4: 0 | H4: 84708000 | I4: 83611500
A5: 2021.01 | B5: 44200 | C5: 8401000 | D5: 0 | E5: 0 | F5: 13780000 | G5: 0 | H5: 22181000 | I5: 22181000
A6: 2021.01 | B6: 44201 | C6: 127000000 | D6: 0 | E6: 0 | F6: 45000000 | G6: 0 | H6: 172000000 | I6: 172000000
A7: 2021.01 | B7: 44202 | C7: 36650000 | D7: 40000000 | E7: 39280000 | F7: 21730000 | G7: 0 | H7: 98380000 | I7: 97660000
A8: 2021.01 | B8: 44203 | C8: 5000000 | D8: 10000000 | E8: 9815000 | F8: 0 | G8: 0 | H8: 15000000 | I8: 14815000
A9: 2021.01 | B9: 44204 | C9: 112778000 | D9: 0 | E9: 0 | F9: 10000000 | G9: 10800000 | H9: 122778000 | I9: 122778000
A10: 2021.01 | B10: 44205 | C10: 11000000 | D10: 21870000 | E10: 21476340 | F10: 0 | G10: 0 | H10: 32870000 | I10: 32476340
A11: 2021.01 | B11: 44206 | C11: 12000000 | D11: 9050000 | E11: 8888000 | F11: 37295000 | G11: 0 | H11: 58345000 | I11: 58183000
A12: 2021.01 | B12: 44207 | C12: 0 | D12: 34680000 | E12: 34461385 | F12: 100225000 | G12: 0 | H12: 134905000 | I12: 134686385
A13: 2021.01 | B13: 44208 | C13: 99360000 | D13: 40297500 | E13: 40125364 | F13: 16738000 | G13: 0 | H13: 156395500 | I13: 156223364
... A365: 2021.12 | B365: 44560 | C365: 44780000 | D365: 27180000 | E365: 27016680 | F365: 1450000 | G365: 0 | H365: 73410000 | I365: 73246680
A366: 2021.12 | B366: 44561 | C366: 31200000 | D366: 10000000 | E366: 9939760 | G366: 0 | H366: 41200000 | I366: 41139760
A367: 2022.01 | B367: 44562 | C367: 0 | D367: 0 | E367: 0 | F367: 0 | G367: 0 | H367: 0 | I367: 0
A368: 2022.01 | B368: 44563 | C368: 0 | D368: 0 | E368: 0 | F368: 0 | G368: 0 | H368: 0 | I368: 0
A369: 2022.01 | B369: 44564 | C369: 20700000 | D369: 0 | E369: 0 | F369: 0 | G369: 0 | H369: 20700000 | I369: 20700000
A370: 2022.01 | B370: 44565 | C370: 5000000 | D370: 5350000 | E370: 5317060 | F370: 42450000 | G370: 0 | H370: 52800000 | I370: 52767060
A371: 2022.01 | B371: 44566 | C371: 18930000 | D371: 630000 | E371: 619920 | F371: 70000000 | G371: 1780000 | H371: 87780000 | I371: 87769920
A372: 2022.01 | B372: 44567 | C372: 17350000 | D372: 0 | E372: 0 | F372: 0 | G372: 0 | H372: 17350000 | I372: 17350000
A373: 2022.01 | B373: 44568 | C373: 700000 | D373: 0 | E373: 0 | F373: 100745300 | G373: 10000000 | H373: 91445300 | I373: 91445300
A374: 2022.01 | B374: 44569 | C374: 10123000 | D374: 56000000 | E374: 55103360 | F374: 0 | G374: 0 | H374: 66123000 | I374: 65226360
A375: 2022.01 | B375: 44570 | C375: 2500000 | D375: 11110000 | E375: 10939000 | F375: 129000000 | G375: 0 | H375: 142610000 | I375: 142439000
A376: 2022.01 | B376: 44571 | C376: 8300000 | D376: 100000000 | E376: 98400000 | F376: 0 | G376: 0 | H376: 108300000 | I376: 106700000
A377: 2022.01 | B377: 44572 | C377: 89253000 | D377: 1550000 | E377: 1524000 | F377: 93805000 | G377: 0 | H377: 184608000 | I377: 184582000
A378: 2022.01 | B378: 44573 | C378: 0 | D378: 0 | E378: 0 | F378: 11100000 | G378: 0 | H378: 11100000 | I378: 11100000
... A392: 2022.01 | B392: 44587 | C392: 0 | D392: 0 | E392: 0 | F392: 8600000 | G392: 0 | H392: 8600000 | I392: 8600000
A393: 2022.01 | B393: 44588 | C393: 5750000 | D393: 2500000 | E393: 2458000 | F393: 5100000 | H393: 13350000 | I393: 13308000
A394: 2022.01 | B394: 44589 | C394: 0 | D394: 0 | E394: 0 | F394: 0 | G394: 0 | H394: 0 | I394: 0
A395: 2022.01 | B395: 44590 | C395: 0 | D395: 0 | E395: 0 | F395: 0 | G395: 0 | H395: 0 | I395: 0
A396: 2022.01 | B396: 44591 | C396: 0 | D396: 0 | E396: 0 | F396: 0 | G396: 0 | H396: 0 | I396: 0
A397: 2022.01 | B397: 44592 | C397: 0 | D397: 0 | E397: 0 | F397: 0 | G397: 0 | H397: 0 | I397: 0
A398: 2022.02 | B398: 44593 | C398: 0 | D398: 0 | E398: 0 | F398: 0 | G398: 0 | H398: 0 | I398: 0
A399: 2022.02 | B399: 44594 | C399: 0 | D399: 0 | E399: 0 | F399: 0 | G399: 0 | H399: 0 | I399: 0
A400: 2022.02 | B400: 44595 | C400: 0 | D400: 0 | E400: 0 | F400: 0 | G400: 0 | H400: 0 | I400: 0
A401: 2022.02 | B401: 44596 | C401: 0 | D401: 0 | E401: 0 | F401: 0 | G401: 0 | H401: 0 | I401: 0
A402: 2022.02 | B402: 44597 | C402: 0 | D402: 0 | E402: 0 | F402: 0 | G402: 0 | H402: 0 | I402: 0
A403: 2022.02 | B403: 44598 | C403: 0 | D403: 0 | E403: 0 | F403: 0 | G403: 0 | H403: 0 | I403: 0
A404: 2022.02 | B404: 44599 | C404: 0 | D404: 0 | E404: 0 | F404: 0 | G404: 0 | H404: 0 | I404: 0
A405: 2022.02 | B405: 44600 | C405: 0 | D405: 0 | E405: 0 | F405: 0 | G405: 0 | H405: 0 | I405: 0
... A425: 2022.02 | B425: 44620 | C425: 3000000 | D425: 0 | E425: 0 | F425: 60450000 | G425: 0 | H425: 63450000 | I425: 63450000
A426: 2022.02 | B426: 44620 | C426: 10500000 | H426: 10500000 | I426: 10500000
A427: 2022.03 | B427: 44621 | C427: 1350000 | D427: 2400000 | E427: 2361600 | F427: 17000000 | G427: 0 | H427: 20750000 | I427: 20711600
A428: 2022.03 | B428: 44622 | C428: 2000000 | D428: 0 | E428: 0 | F428: 27415000 | G428: 0 | H428: 29415000 | I428: 29415000
A429: 2022.03 | B429: 44623 | C429: 350000 | D429: 55640000 | E429: 54749760 | F429: 107100000 | G429: 0 | H429: 163090000 | I429: 162199760
A430: 2022.03 | B430: 44624 | C430: 8955000 | D430: 0 | E430: 0 | F430: 254660500 | G430: 0 | H430: 263615500 | I430: 263615500
A431: 2022.03 | B431: 44625 | C431: 1400000 | D431: 10800000 | E431: 10627000 | F431: 119000000 | G431: 0 | H431: 131200000 | I431: 131027000
A432: 2022.03 | B432: 44626 | C432: 78160000 | D432: 0 | E432: 0 | F432: 0 | G432: 0 | H432: 78160000 | I432: 78160000
A433: 2022.03 | B433: 44627 | C433: 19825000 | D433: 350000 | E433: 336800 | F433: 227000000 | G433: 0 | H433: 247175000 | I433: 247161800
A434: 2022.03 | B434: 44628 | C434: 8425000 | D434: 0 | E434: 0 | F434: 18000000 | G434: 0 | H434: 26425000 | I434: 26425000
A435: 2022.03 | B435: 44629 | C435: 69300000 | D435: 59350000 | E435: 58490400 | F435: 0 | G435: 0 | H435: 128650000 | I435: 127790400
A436: 2022.03 | B436: 44630 | C436: 2850000 | D436: 0 | E436: 0 | F436: 150000000 | G436: 0 | H436: 152850000 | I436: 152850000
A437: 2022.03 | B437: 44631 | C437: 7000000 | D437: 0 | E437: 0 | F437: 13000000 | G437: 4650000 | H437: 15350000 | I437: 15350000
A438: 2022.03 | B438: 44632 | C438: 13300000 | D438: 100000000 | E438: 98400000 | F438: 3000000 | G438: 0 | H438: 116300000 | I438: 114700000
... A456: 2022.03 | B456: 44650 | C456: 53945000 | D456: 50000000 | E456: 49200000 | F456: 18000000 | G456: 0 | H456: 121945000 | I456: 121145000
A457: 2022.03 | B457: 44651 | C457: 59820000 | D457: 1215000 | E457: 1195000 | G457: 0 | H457: 61035000 | I457: 61015000
A458: 2022.03 | B458: 44621 | C458: 50000000 | H458: 50000000 | I458: 50000000
A459: 2022.04 | B459: 44652 | C459: 0 | D459: 1720000 | E459: 1698480 | F459: 65940000 | G459: 1500000 | H459: 66160000 | I459: 66138480
A460: 2022.04 | B460: 44653 | C460: 16700000 | D460: 0 | E460: 0 | F460: 0 | G460: 0 | H460: 16700000 | I460: 16700000
A461: 2022.04 | B461: 44654 | C461: 3350000 | D461: 1174500 | E461: 1155300 | F461: 0 | G461: 0 | H461: 4524500 | I461: 4505300
A462: 2022.04 | B462: 44655 | C462: 15500000 | D462: 125758000 | E462: 123745872 | F462: 33100000 | G462: 0 | H462: 174358000 | I462: 172345872
A463: 2022.04 | B463: 44656 | C463: 15140000 | D463: 54988000 | E463: 54108000 | F463: 93850000 | G463: 2000000 | H463: 161978000 | I463: 161098000
A464: 2022.04 | B464: 44657 | C464: 19184000 | D464: 0 | E464: 0 | F464: 20000000 | G464: 0 | H464: 39184000 | I464: 39184000
A465: 2022.04 | B465: 44658 | C465: 31714000 | D465: 0 | E465: 0 | F465: 43000000 | G465: 0 | H465: 74714000 | I465: 74714000
A466: 2022.04 | B466: 44659 | C466: 2700000 | D466: 1600000 | E466: 1590000 | F466: 25900000 | G466: 0 | H466: 30200000 | I466: 30190000
A467: 2022.04 | B467: 44660 | C467: 2150000 | D467: 25000000 | E467: 24850000 | F467: 500000 | G467: 0 | H467: 27650000 | I467: 27500000
A468: 2022.04 | B468: 44661 | C468: 0 | D468: 0 | E468: 0 | F468: 0 | G468: 0 | H468: 0 | I468: 0
A469: 2022.04 | B469: 44662 | C469: 0 | D469: 0 | E469: 0 | F469: 0 | G469: 0 | H469: 0 | I469: 0
A470: 2022.04 | B470: 44663 | C470: 5602500 | D470: 2400000 | E470: 2385000 | F470: 0 | G470: 0 | H470: 8002500 | I470: 7987500
... A549: 2022.06 | B549: 44742 | C549: 29654500 | D549: 0 | E549: 0 | F549: 19200000 | G549: 0 | H549: 48854500 | I549: 48854500
A550: 2022.06 | B550: 44713 | C550: 7955000 | H550: 7955000 | I550: 7955000
A551: 2022.07 | B551: 44743 | C551: 0 | D551: 0 | E551: 0 | F551: 100000000 | G551: 0 | H551: 100000000 | I551: 100000000
A552: 2022.07 | B552: 44744 | C552: 350000 | D552: 0 | E552: 0 | F552: 35000000 | G552: 0 | H552: 35350000 | I552: 35350000
A553: 2022.07 | B553: 44745 | C553: 25000000 | D553: 0 | E553: 0 | F553: 7000000 | G553: 0 | H553: 32000000 | I553: 32000000
A554: 2022.07 | B554: 44746 | C554: 0 | D554: 2500000 | E554: 2460000 | F554: 123200000 | G554: 0 | H554: 125700000 | I554: 125660000
A555: 2022.07 | B555: 44747 | C555: 30000000 | D555: 0 | E555: 0 | F555: 0 | G555: 0 | H555: 30000000 | I555: 30000000
A556: 2022.07 | B556: 44748 | C556: 1250000 | D556: 5450000 | E556: 5362800 | F556: 81000000 | G556: 0 | H556: 87700000 | I556: 87612800
A557: 2022.07 | B557: 44749 | C557: 44925000 | D557: 0 | E557: 0 | F557: 225000000 | G557: 25000000 | H557: 244925000 | I557: 244925000
A558: 2022.07 | B558: 44750 | C558: 163100000 | D558: 8464000 | E558: 8413216 | F558: 71000000 | G558: 0 | H558: 242564000 | I558: 242513216
A559: 2022.07 | B559: 44751 | C559: 14676000 | D559: 1040000 | E559: 1023360 | F559: 21800000 | G559: 0 | H559: 37516000 | I559: 37499360
A560: 2022.07 | B560: 44752 | C560: 1850000 | D560: 0 | E560: 0 | F560: 1850000 | G560: 0 | H560: 3700000 | I560: 3700000
A561: 2022.07 | B561: 44753 | C561: 287454000 | D561: 46000000 | E561: 45654000 | F561: 100500000 | G561: 0 | H561: 433954000 | I561: 433608000
A562: 2022.07 | B562: 44754 | C562: 42800000 | D562: 0 | E562: 0 | F562: 0 | G562: 0 | H562: 42800000 | I562: 42800000
... A765: 2023.01 | B765: 44957 | C765: 0 | D765: 0 | E765: 0 | F765: 0 | G765: 0 | H765: 0 | I765: 0
A766: 2023.01 | B766: 44957 | C766: 15470000 | H766: 15470000 | I766: 15470000
A767: 2023.02 | B767: 44958 | C767: 172000000 | D767: 9350000 | E767: 9250400 | F767: 130000000 | G767: 0 | H767: 311350000 | I767: 311250400
A768: 2023.02 | B768: 44959 | C768: 34350000 | D768: 21350000 | E768: 20906400 | F768: 20300000 | G768: 0 | H768: 76000000 | I768: 75556400
A769: 2023.02 | B769: 44960 | C769: 203737000 | D769: 500000 | E769: 492000 | F769: 179200000 | G769: 1700000 | H769: 381737000 | I769: 381729000
A770: 2023.02 | B770: 44961 | C770: 110000000 | D770: 107997000 | E770: 106269000 | F770: 28550000 | G770: 0 | H770: 246547000 | I770: 244819000
A771: 2023.02 | B771: 44962 | C771: 87350000 | D771: 2000000 | E771: 1956000 | F771: 134965000 | G771: 0 | H771: 224315000 | I771: 224271000
A772: 2023.02 | B772: 44963 | C772: 84153000 | D772: 12850000 | E772: 12743400 | F772: 217645000 | G772: 0 | H772: 314648000 | I772: 314541400
A773: 2023.02 | B773: 44964 | C773: 125820000 | D773: 110430000 | E773: 108670369 | F773: 153328000 | G773: 0 | H773: 389578000 | I773: 387818369
A774: 2023.02 | B774: 44965 | C774: 163450500 | D774: 48236000 | E774: 47656584 | F774: 39050000 | G774: 0 | H774: 250736500 | I774: 250157084
A775: 2023.02 | B775: 44966 | C775: 95415000 | D775: 4900000 | E775: 4821600 | F775: 0 | G775: 12420000 | H775: 87895000 | I775: 87816600
A776: 2023.02 | B776: 44967 | C776: 93500000 | D776: 49350000 | E776: 48560400 | F776: 74300000 | G776: 8145000 | H776: 209005000 | I776: 208215400
A777: 2023.02 | B777: 44968 | C777: 79276000 | D777: 6100000 | E777: 6038400 | F777: 2350000 | G777: 0 | H777: 87726000 | I777: 87664400
A778: 2023.02 | B778: 44969 | C778: 6200000 | D778: 38400000 | E778: 38188800 | F778: 104100000 | G778: 0 | H778: 148700000 | I778: 148488800
... A794: 2023.02 | B794: 44985 | C794: 174149000 | D794: 40000000 | E794: 39260000 | F794: 6191000 | G794: 0 | H794: 220340000 | I794: 219600000
A795: 2023.02 | B795: 44958 | C795: 143300000 | H795: 143300000 | I795: 143300000
...

Sheet PL.Lương Teennie
A1: TEENNIE | B1: Tháng 1 | C1: Lương CB | D1: Ngày công chuẩn | E1: Ngày công thực tế | F1: Số ngày tăng ca | G1: Tăng ca | H1: Năng lực | I1: Thâm niên | J1: Kiêm việc | K1: Trợ cấp | L1: KPI Công việc | M1: KPI Doanh số 15 | N1: Thưởng tháng 13 | O1: Đào tạo | P1: Tổng lương | Q1: Bảo hiểm | R1: Khấu trừ | S1: Tạm ứng | T1: Thực nhận
B2: BAN CỐ VẤN | C2: =sum(C3) -> 55000000 | G2: =sum(G3) -> 0 | H2: =sum(H3) -> 0 | I2: =sum(I3) -> 0 | J2: =sum(J3) -> 0 | K2: =sum(K3) -> 0 | L2: =sum(L3) -> 0 | M2: =sum(M3) -> 0 | N2: =sum(N3) -> 0 | ... T2: =sum(T3) -> 55000000
B3: Lương CĐ | C3: 55000000 | D3: 26 | E3: 26 | F3: 0 | G3: 0 | H3: 0 | I3: 0 | J3: 0 | K3: 0 | L3: 0 | M3: 0 | N3: 0 | O3: 0 | P3: 55000000 | Q3: 0 | R3: 0 | S3: 0 | T3: =P3-Q3-R3-S3 -> 55000000
B4: HỘI ĐỒNG THÀNH VIÊN | C4: =sum(C79) -> 0 | G4: =sum(G79) -> 0 | H4: =sum(H79) -> 0 | I4: =sum(I79) -> 0 | J4: =sum(J79) -> 0 | K4: =sum(K79) -> 0 | L4: =sum(L79) -> 0 | M4: =sum(M79) -> 0 | N4: =sum(N79) -> 0 | ... T4: =sum(T79) -> 0
B6: BAN GIÁM ĐỐC
B8: KINH DOANH | C8: =sum(C9:C17) -> 36666667 | G8: =sum(G9:G17) -> 975489 | H8: =sum(H9:H17) -> 0 | I8: =sum(I9:I17) -> 0 | J8: =sum(J9:J17) -> 0 | K8: =sum(K9:K17) -> 0 | L8: =sum(L9:L17) -> 0 | M8: =sum(M9:M17) -> 0 | N8: =sum(N9:N17) -> 0 | ... T8: =sum(T9:T17) -> 57439285
B9: Thầy Vinh PT | C9: 5000000 | D9: 26 | E9: 26 | P9: 5000000 | T9: 5000000
B10: Tiền PT của LT | P10: 66667 | T10: 66667
B11: Sale Minh Nguyệt | C11: 6500000 | D11: 26 | E11: 24 | F11: 11.48 | G11: 358750 | P11: 16405780 | R11: 525840 | T11: 15879940
B12: Sale Quế Chi | C12: 6500000 | D12: 26 | E12: 22.3214 | F12: 7.21 | G12: 225313 | P12: 14770295 | R12: 525840 | T12: 14244455
B13: Telesale Bí Nhi | C13: 2166667 | D13: 26 | E13: 34 | G13: 0 | P13: 5265733 | R13: 175280 | T13: 5090453
B14: Telesale Yến | C14: 2166667 | D14: 26 | E14: 32.5 | F14: 4.5 | G14: 46875 | P14: 4547958 | R14: 175280 | T14: 4372678
B15: TBP CSKH Chuyên | C15: 6666667 | D15: 26 | E15: 20.8017 | G15: 0 | P15: 5333769 | T15: 5333769
B16: CSKH Thảo Uyên | C16: 3333333 | D16: 26 | E16: 23 | F16: 8.5 | G16: 136218 | P16: 3084936 | T16: 3084936
B17: CSKH Hoàng Lan | C17: 4333333 | D17: 26 | E17: 26 | F17: 10 | G17: 208333 | P17: 4541667 | R17: 175280 | T17: 4366387
B18: KẾ TOÁN - KHO | C18: =sum(C19:C20) -> 13333333 | G18: =sum(G19:G20) -> 0 | H18: =sum(H19:H20) -> 0 | I18: =sum(I19:I20) -> 0 | J18: =sum(J19:J20) -> 0 | K18: =sum(K19:K20) -> 0 | L18: =sum(L19:L20) -> 0 | M18: =sum(M19:M20) -> 0 | N18: =sum(N19:N20) -> 0 | ... T18: =sum(T19:T20) -> 13333333
B19: Kế toán tài chính Thái | C19: 5000000 | D19: 26 | E19: 26 | P19: 5000000 | T19: 5000000
B20: Kế toán + thuế | C20: 8333333 | D20: 26 | E20: 26 | P20: 8333333 | T20: 8333333
B21: HÀNH CHÍNH - NHÂN SỰ | C21: =sum(C22:C30) -> 63866666 | G21: =sum(G22:G30) -> 440261 | H21: =sum(H22:H30) -> 1133334 | I21: =sum(I22:I30) -> 666667 | J21: =sum(J22:J30) -> 0 | K21: =sum(K22:K30) -> 0 | L21: =sum(L22:L30) -> 0 | M21: =sum(M22:M30) -> 0 | N21: =sum(N22:N30) -> 0 | ... T21: =sum(T22:T30) -> 37631493
B22: TP HCNS Nga | C22: 8333333 | D22: 26 | E22: 26 | P22: 11282051 | R22: 245000 | T22: 6282051
B23: Anh Hiền | C23: 30333333 | D23: 26 | E23: 26 | P23: 8333333 | T23: 8088333
B24: Duyên HCNS | C24: 5333333 | D24: 26 | E24: 26 | P24: 5333333 | R24: 175280 | T24: 5158053
B25: Anh Bảo đào tạo | C25: 5000000 | D25: 26 | E25: 25.4313 | P25: 4890635 | R25: 175280 | T25: 4715355
B26: GV Hiền | C26: 2100000 | D26: 26 | E26: 25.9538 | G26: 0 | H26: 566667 | I26: 0 | P26: 2662935 | R26: 175280 | T26: 2487655
B27: Chị Trang | C27: 2100000 | D27: 26 | E27: 28.9971 | F27: 14.37 | G27: 145082 | H27: 566667 | I27: 666667 | P27: 3720489 | R27: 175280 | S27: 1333333 | T27: 2211875
B28: Cô Liên tạp vụ | C28: 2666667 | D28: 26 | E28: 24 | G28: 0 | P28: 2461538 | T28: 2461538
B29: Bv Trung | C29: 4000000 | D29: 28 | E29: 27.9241 | F29: 5.32 | G29: 95000 | H29: 0 | I29: 0 | P29: 4134157 | R29: 175280 | S29: 2000000 | T29: 1958877
B30: BV Cang | C30: 4000000 | D30: 28 | E30: 29 | F30: 11.21 | G30: 200179 | P30: 4443036 | R30: 175280 | T30: 4267756
B31: VẬN HÀNH | C31: =sum(C32:C42) -> 51166664 | G31: =sum(G32:G42) -> 625249 | H31: =sum(H32:H42) -> 5999998 | I31: =sum(I32:I42) -> 0 | J31: =sum(J32:J42) -> 0 | K31: =sum(K32:K42) -> 0 | L31: =sum(L32:L42) -> 0 | M31: =sum(M32:M42) -> 11402912 | N31: =sum(N32:N42) -> 0 | ... T31: =sum(T32:T42) -> 59041161
B32: LT Quỳnh Như | C32: 2666667 | D32: 26 | E32: 25.808 | F32: 0.5 | G32: 6410 | H32: 3333333 | P32: 5986718 | R32: 175280 | T32: 5811438
B33: LT Bích Nhi | C33: 1833333 | D33: 26 | E33: 24.3374 | F33: 9.59 | G33: 84527 | H33: 333333 | M33: 1577531 | P33: 3711491 | R33: 175280 | T33: 3536211
B34: LT Tường Vy | C34: 1833333 | D34: 26 | E34: 25.8213 | F34: 14.61 | G34: 128774 | H34: 333333 | M34: 1673716 | P34: 3956557 | R34: 175280 | T34: 3781277
B35: LT Tuyết Ngọc | C35: 1833333 | D35: 26 | E35: 25 | F35: 13.73 | G35: 121018 | H35: 333333 | M35: 1620480 | P35: 3837652 | T35: 3837652
B36: LT Kim Ngân | C36: 1833333 | D36: 26 | E36: 25.5645 | F36: 4.26 | G36: 37548 | H36: 666667 | M36: 1657071 | P36: 4163911 | R36: 175280 | T36: 3988631
B37: Lt Tú Nhi | C37: 1833333 | D37: 26 | E37: 25.9699 | F37: 6.07 | G37: 53502 | H37: 333333 | M37: 1683349 | P37: 3901394 | R37: 175280 | T37: 3726114
B38: LT Văn Tính | C38: 1833333 | D38: 26 | E38: 26 | F38: 11.34 | G38: 99952 | H38: 333333 | M38: 1685300 | P38: 3951918 | R38: 175280 | T38: 3776638
B39: LT Trâm Anh | C39: 1833333 | D39: 26 | E39: 23.2256 | F39: 10.61 | G39: 93518 | H39: 333333 | M39: 1505465 | P39: 3570019 | T39: 3570019
B40: Quản lý Tiến | C40: 13333333 | D40: 26 | E40: 22 | P40: 11282051 | R40: 5000000 | T40: 6282051
B41: Chị Phượng | C41: 18333333 | D41: 26 | E41: 26 | P41: 18333333 | R41: 350000 | T41: 17983333
B42: Uyên kiểm soát | C42: 4000000 | D42: 26 | E42: 19 | P42: 2923077 | R42: 175280 | T42: 2747797
B43: MARKETING | C43: =sum(C44:C56) -> 91508613 | G43: =sum(G44:G56) -> 507740 | H43: =sum(H44:H56) -> 0 | I43: =sum(I44:I56) -> 0 | J43: =sum(J44:J56) -> 0 | K43: =sum(K44:K56) -> 0 | L43: =sum(L44:L56) -> 0 | M43: =sum(M44:M56) -> 0 | N43: =sum(N44:N56) -> 0 | ... T43: =sum(T44:T56) -> 92639437
B44: Hiến | C44: 21666667 | D44: 26 | E44: 26 | P44: 21666667 | R44: 175280 | T44: 21491387
B45: Ánh Nguyệt content | C45: 5333333 | D45: 26 | E45: 26 | G45: 0 | P45: 5333333 | R45: 175280 | T45: 5158053
B46: XIÊM QUỐC THU quay dựng | C46: 7666667 | D46: 26 | E46: 26 | G46: 0 | P46: 7666667 | R46: 175280 | T46: 7491387
B47: Thành media | C47: 6666667 | D47: 26 | E47: 25.9604 | G47: 0 | P47: 6656513 | R47: 175280 | T47: 6481233
B48: MKT Minh Lâm | C48: 8333333 | D48: 26 | E48: 26 | G48: 0 | P48: 8333333 | R48: 210000 | T48: 8123333
B49: MKT Bông | C49: 8333333 | D49: 26 | E49: 26 | G49: 0 | P49: 8333333 | T49: 8333333
B50: Trung Hào | C50: 4000000 | D50: 26 | E50: 27 | F50: 17.66 | G50: 339615 | P50: 5362212 | R50: 175280 | T50: 5186932
B51: Chụp hình Hùng | C51: 4333333 | D51: 26 | E51: 26 | F51: 7.07 | G51: 147292 | P51: 5349375 | T51: 5349375
B52: Lâm Trần Tuấn | C52: 4333333 | D52: 26 | E52: 25.8606 | F52: 1 | G52: 20833 | P52: 5199683 | R52: 175280 | T52: 4357737
B53: Đức Thuận | C53: 4000000 | D53: 26 | E53: 26 | G53: 0 | P53: 4000000 | T53: 4000000
B54: Bảo Nghi | C54: 5841947 | D54: 26 | E54: 26 | G54: 0 | P54: 5841947 | R54: 175280 | T54: 5666667
B55: đội sedding NK | C55: 9333333 | D55: 26 | E55: 26 | P55: 9333333 | T55: 9333333
B56: Phiên dịch Trang | C56: 1666667 | D56: 26 | E56: 26 | P56: 1666667 | T56: 1666667
B57: NGHIỆP VỤ | C57: =sum(C58:C79) -> 116666667 | G57: =sum(G58:G79) -> 3136120 | H57: =sum(H58:H79) -> 9500000 | I57: =sum(I58:I79) -> 0 | J57: =sum(J58:J79) -> 0 | K57: =sum(K58:K79) -> 0 | L57: =sum(L58:L79) -> 0 | M57: =sum(M58:M79) -> 495402648 | N57: =sum(N58:N79) -> 0 | ... T57: =sum(T58:T79) -> 643939150
B58: BS Huy | C58: 60000000 | D58: 0 | P58: 60000000 | T58: 60000000
B59: BS Tân | C59: 1000000 | D59: 0 | E59: 8.4785 | M59: 92938163 | P59: 101416616 | T59: 101416616
B60: Bs Sáng | C60: 1000000 | D60: 0 | E60: 9.5934 | M60: 120160875 | P60: 129754243 | R60: 735000 | T60: 129019243
B61: BS Hương | C61: 1000000 | D61: 0 | E61: 3.5623 | M61: 23931110 | P61: 27493415 | T61: 27493415
B62: BS Quang | C62: 1000000 | D62: 0 | E62: 1.8936 | M62: 18136875 | P62: 20030443 | T62: 20030443
B63: Bs Vy | C63: 1000000 | D63: 0 | E63: 10.6484 | M63: 126142500 | P63: 136790942 | T63: 136790942
B64: Bs Tuyền | C64: 1000000 | D64: 0 | E64: 8.7719 | M64: 50896000 | P64: 59667926 | R64: 630000 | T64: 59037926
B65: Bs Thọ | C65: 20000000 | D65: 23 | E65: 6.7773 | M65: 46357125 | P65: 52250429 | T65: 52250429
B66: PT TRƯỞNG Cẩm Loan | C66: 6666667 | D66: 26 | E66: 29 | F66: 40.37 | G66: 1293910 | M66: 783333 | P66: 9513141 | R66: 315000 | T66: 9198141
B67: PT Kim Ánh | C67: 2000000 | D67: 26 | E67: 26.569 | F67: 16.18 | G67: 155577 | H67: 1333333 | M67: 1285000 | P67: 4817679 | R67: 175280 | T67: 4642399
B68: PT Anh Như | C68: 2000000 | D68: 26 | E68: 25.8918 | F68: 30.57 | G68: 293942 | H68: 1000000 | M68: 1335000 | P68: 4720619 | R68: 175280 | T68: 4545339
B69: PT Kiều | C69: 2000000 | D69: 26 | E69: 26.5852 | F69: 9 | G69: 86538 | H69: 500000 | M69: 841667 | P69: 3473221 | R69: 175280 | T69: 3297941
B70: PT Điệp | C70: 2000000 | D70: 26 | E70: 14.8814 | F70: 2.5 | G70: 24038 | H70: 333333 | M70: 828333 | P70: 2330428 | T70: 2330428
B71: PT Ngọc Nhi | C71: 2000000 | D71: 26 | E71: 24.3875 | F71: 21.86 | G71: 210192 | H71: 500000 | M71: 1276667 | P71: 3862821 | R71: 175280 | T71: 3687541
B72: PT Thanh Thi | C72: 2000000 | D72: 26 | E72: 25.4518 | F72: 16.75 | G72: 161058 | H72: 500000 | M72: 1053333 | P72: 3672222 | T72: 3672222
B73: PT Dung | C73: 2000000 | D73: 26 | E73: 26.8157 | F73: 15.55 | G73: 149519 | H73: 1000000 | M73: 1836667 | P73: 5048932 | R73: 175280 | T73: 4873652
B74: PT Tuyết Trang | C74: 2000000 | D74: 26 | E74: 26.7559 | F74: 12.64 | G74: 121538 | H74: 1000000 | M74: 1520000 | P74: 6699685 | R74: 175280 | T74: 4524405
B75: PT Ánh Thúy | C75: 2000000 | D75: 26 | E75: 26.8197 | F75: 23.25 | G75: 223558 | H75: 1000000 | M75: 1783333 | P75: 5069945 | R75: 175280 | T75: 4894665
B76: PT Y Bình | C76: 2000000 | D76: 26 | E76: 19 | F76: 9.59 | G76: 92212 | H76: 1000000 | M76: 880000 | P76: 3433750 | R76: 175280 | T76: 3258470
B77: PT Kiều Oanh | C77: 2000000 | D77: 26 | E77: 26.8955 | F77: 17.12 | G77: 164615 | H77: 666667 | M77: 1755000 | P77: 4655167 | R77: 175280 | T77: 4479887
B78: PT Đông Tuyết | C78: 2000000 | D78: 26 | E78: 28.3734 | F78: 16.58 | G78: 159423 | H78: 666667 | M78: 1661667 | P78: 4670326 | R78: 175280 | T78: 4495046
A80: TEENNIE | B80: Tháng 2 | C80: Lương CB | D80: Ngày công chuẩn | E80: Ngày công thực tế | F80: Số ngày tăng ca | G80: Tăng ca | H80: Năng lực | I80: Thâm niên | J80: Kiêm việc | K80: Trợ cấp | L80: KPI Công việc | M80: KPI Doanh số 15 | N80: Thưởng tháng 13 | O80: Đào tạo | P80: Tổng lương | Q80: Bảo hiểm | R80: Khấu trừ | S80: Tạm ứng | T80: Thực nhận
B81: BAN CỐ VẤN | C81: =sum(C82) -> 55000000 | G81: =sum(G82) -> 0 | H81: =sum(H82) -> 0 | I81: =sum(I82) -> 0 | J81: =sum(J82) -> 0 | K81: =sum(K82) -> 0 | L81: =sum(L82) -> 0 | M81: =sum(M82) -> 0 | N81: =sum(N82) -> 0 | ... T81: =sum(T82) -> 55000000
B82: Lương CĐ | C82: 55000000 | D82: 26 | E82: 26 | F82: 0 | G82: 0 | H82: 0 | I82: 0 | J82: 0 | K82: 0 | L82: 0 | M82: 0 | N82: 0 | O82: 0 | P82: 55000000 | Q82: 0 | R82: 0 | S82: 0 | T82: =P82-Q82-R82-S82 -> 55000000
B83: HỘI ĐỒNG THÀNH VIÊN | C83: =sum(C158) -> 0 | G83: =sum(G158) -> 0 | H83: =sum(H158) -> 0 | I83: =sum(I158) -> 0 | J83: =sum(J158) -> 0 | K83: =sum(K158) -> 0 | L83: =sum(L158) -> 0 | M83: =sum(M158) -> 0 | N83: =sum(N158) -> 0 | ... T83: =sum(T158) -> 0
B85: BAN GIÁM ĐỐC
B87: KINH DOANH | C87: =sum(C88:C96) -> 36666667 | G87: =sum(G88:G96) -> 975489 | H87: =sum(H88:H96) -> 0 | I87: =sum(I88:I96) -> 0 | J87: =sum(J88:J96) -> 0 | K87: =sum(K88:K96) -> 0 | L87: =sum(L88:L96) -> 0 | M87: =sum(M88:M96) -> 0 | N87: =sum(N88:N96) -> 0 | ... T87: =sum(T88:T96) -> 57439285
B88: Thầy Vinh PT | C88: 5000000 | D88: 26 | E88: 26 | P88: 5000000 | T88: 5000000
B89: Tiền PT của LT | P89: 66667 | T89: 66667
B90: Sale Minh Nguyệt | C90: 6500000 | D90: 26 | E90: 24 | F90: 11.48 | G90: 358750 | P90: 16405780 | R90: 525840 | T90: 15879940
B91: Sale Quế Chi | C91: 6500000 | D91: 26 | E91: 22.3214 | F91: 7.21 | G91: 225313 | P91: 14770295 | R91: 525840 | T91: 14244455
B92: Telesale Bí Nhi | C92: 2166667 | D92: 26 | E92: 34 | G92: 0 | P92: 5265733 | R92: 175280 | T92: 5090453
B93: Telesale Yến | C93: 2166667 | D93: 26 | E93: 32.5 | F93: 4.5 | G93: 46875 | P93: 4547958 | R93: 175280 | T93: 4372678
B94: TBP CSKH Chuyên | C94: 6666667 | D94: 26 | E94: 20.8017 | G94: 0 | P94: 5333769 | T94: 5333769
B95: CSKH Thảo Uyên | C95: 3333333 | D95: 26 | E95: 23 | F95: 8.5 | G95: 136218 | P95: 3084936 | T95: 3084936
B96: CSKH Hoàng Lan | C96: 4333333 | D96: 26 | E96: 26 | F96: 10 | G96: 208333 | P96: 4541667 | R96: 175280 | T96: 4366387
B97: KẾ TOÁN - KHO | C97: =sum(C98:C99) -> 13333333 | G97: =sum(G98:G99) -> 0 | H97: =sum(H98:H99) -> 0 | I97: =sum(I98:I99) -> 0 | J97: =sum(J98:J99) -> 0 | K97: =sum(K98:K99) -> 0 | L97: =sum(L98:L99) -> 0 | M97: =sum(M98:M99) -> 0 | N97: =sum(N98:N99) -> 0 | ... T97: =sum(T98:T99) -> 13333333
B98: Kế toán tài chính Thái | C98: 5000000 | D98: 26 | E98: 26 | P98: 5000000 | T98: 5000000
B99: Kế toán + thuế | C99: 8333333 | D99: 26 | E99: 26 | P99: 8333333 | T99: 8333333
B100: HÀNH CHÍNH - NHÂN SỰ | C100: =sum(C101:C109) -> 63866666 | G100: =sum(G101:G109) -> 440261 | H100: =sum(H101:H109) -> 1133334 | I100: =sum(I101:I109) -> 666667 | J100: =sum(J101:J109) -> 0 | K100: =sum(K101:K109) -> 0 | L100: =sum(L101:L109) -> 0 | M100: =sum(M101:M109) -> 0 | N100: =sum(N101:N109) -> 0 | ... T100: =sum(T101:T109) -> 37631493
B101: TP HCNS Nga | C101: 8333333 | D101: 26 | E101: 26 | P101: 11282051 | R101: 245000 | T101: 6282051
B102: Anh Hiền | C102: 30333333 | D102: 26 | E102: 26 | P102: 8333333 | T102: 8088333
B103: Duyên HCNS | C103: 5333333 | D103: 26 | E103: 26 | P103: 5333333 | R103: 175280 | T103: 5158053
B104: Anh Bảo đào tạo | C104: 5000000 | D104: 26 | E104: 25.4313 | P104: 4890635 | R104: 175280 | T104: 4715355
B105: GV Hiền | C105: 2100000 | D105: 26 | E105: 25.9538 | G105: 0 | H105: 566667 | I105: 0 | P105: 2662935 | R105: 175280 | T105: 2487655
...

Sheet Chi phi_Implant
A1: THÁNG | B1: NỘI DUNG CHI | C1: PHÂN LOẠI | D1: SỐ TIỀN | E1: DÒNG TIỀN | F1: TÀI CHÍNH
A2: 2024.01 | B2: Tổng hợp | C2: Mua đồ hành chính | D2: 0 | E2: =vlookup(C2,'Master data'!$A$1:$C$29,3,0) -> Biến phí | F2: =vlookup(C2,'Master data'!$A$1:$C$29,2,0) -> Chi phí hành chính
A3: 2024.01 | B3: lương cứng tháng 1 | C3: Lương | D3: 319716510 | E3: =vlookup(C3,'Master data'!$A$1:$C$29,3,0) -> Định phí | F3: =vlookup(C3,'Master data'!$A$1:$C$29,2,0) -> Chi phí QLDN
A4: 2024.01 | B4: lương KPI tháng 1 | C4: KPI | D4: 139238306 | E4: =vlookup(C4,'Master data'!$A$1:$C$29,3,0) -> Biến phí | F4: =vlookup(C4,'Master data'!$A$1:$C$29,2,0) -> Chi phí bán hàng
A5: 2024.01 | B5: Chè | C5: Mua đồ hành chính | D5: 206667 | E5: =vlookup(C5,'Master data'!$A$1:$C$29,3,0) -> Biến phí | F5: =vlookup(C5,'Master data'!$A$1:$C$29,2,0) -> Chi phí hành chính
A6: 2024.01 | B6: Hoa trái cây | C6: Mua đồ hành chính | D6: 673333 | E6: =vlookup(C6,'Master data'!$A$1:$C$29,3,0) -> Biến phí | F6: =vlookup(C6,'Master data'!$A$1:$C$29,2,0) -> Chi phí hành chính
A7: 2024.01 | B7: ồ cúng | C7: Mua đồ hành chính | D7: 687333 | E7: =vlookup(C7,'Master data'!$A$1:$C$29,3,0) -> Biến phí | F7: =vlookup(C7,'Master data'!$A$1:$C$29,2,0) -> Chi phí hành chính
A8: 2024.01 | B8: Nước suối | C8: Mua đồ hành chính | D8: 3760000 | E8: =vlookup(C8,'Master data'!$A$1:$C$29,3,0) -> Biến phí | F8: =vlookup(C8,'Master data'!$A$1:$C$29,2,0) -> Chi phí hành chính
A9: 2024.01 | B9: Nước bình | C9: Mua đồ hành chính | D9: 618001 | E9: =vlookup(C9,'Master data'!$A$1:$C$29,3,0) -> Biến phí | F9: =vlookup(C9,'Master data'!$A$1:$C$29,2,0) -> Chi phí hành chính
A10: 2024.01 | B10: Kho tạp vụ | C10: Mua đồ hành chính | D10: 4106000 | E10: =vlookup(C10,'Master data'!$A$1:$C$29,3,0) -> Biến phí | F10: =vlookup(C10,'Master data'!$A$1:$C$29,2,0) -> Chi phí hành chính
A11: 2024.01 | B11: Bánh keọ | C11: Mua đồ hành chính | D11: 358667 | E11: =vlookup(C11,'Master data'!$A$1:$C$29,3,0) -> Biến phí | F11: =vlookup(C11,'Master data'!$A$1:$C$29,2,0) -> Chi phí hành chính
A12: 2024.01 | B12: ồ ăn khách | C12: Mua đồ hành chính | D12: 702500 | E12: =vlookup(C12,'Master data'!$A$1:$C$29,3,0) -> Biến phí | F12: =vlookup(C12,'Master data'!$A$1:$C$29,2,0) -> Chi phí hành chính
A13: 2024.01 | B13: _x0008_Sữa | C13: Mua đồ hành chính | D13: 0 | E13: =vlookup(C13,'Master data'!$A$1:$C$29,3,0) -> Biến phí | F13: =vlookup(C13,'Master data'!$A$1:$C$29,2,0) -> Chi phí hành chính
... A122: 2024.03 | B122: trả góp 57420 | C122: Hành chính MKT | D122: 4076000 | E122: =vlookup(C122,'Master data'!$A$1:$C$29,3,0) -> Biến phí | F122: =vlookup(C122,'Master data'!$A$1:$C$29,2,0) -> Chi phí bán hàng
A123: 2024.03 | B123: 57464 | C123: Hành chính MKT | D123: 2472000 | E123: =vlookup(C123,'Master data'!$A$1:$C$29,3,0) -> Biến phí | F123: =vlookup(C123,'Master data'!$A$1:$C$29,2,0) -> Chi phí bán hàng
A124: 2024.03 | B124: 57428 | C124: Hành chính MKT | D124: 1696000 | E124: =vlookup(C124,'Master data'!$A$1:$C$29,3,0) -> Biến phí | F124: =vlookup(C124,'Master data'!$A$1:$C$29,2,0) -> Chi phí bán hàng
A125: 2024.03 | B125: xnm | C125: Hành chính MKT | D125: 159000 | E125: =vlookup(C125,'Master data'!$A$1:$C$29,3,0) -> Biến phí | F125: =vlookup(C125,'Master data'!$A$1:$C$29,2,0) -> Chi phí bán hàng
A126: 2024.03 | B126: 20 dép khách | C126: Hành chính MKT | D126: 266667 | E126: =vlookup(C126,'Master data'!$A$1:$C$29,3,0) -> Biến phí | F126: =vlookup(C126,'Master data'!$A$1:$C$29,2,0) -> Chi phí bán hàng
A127: 2024.03 | B127: gương phòng điều trị | C127: Hành chính MKT | D127: 337667 | E127: =vlookup(C127,'Master data'!$A$1:$C$29,3,0) -> Biến phí | F127: =vlookup(C127,'Master data'!$A$1:$C$29,2,0) -> Chi phí bán hàng
A128: 2024.03 | B128: phí cà thẻ | C128: Phí cà thẻ | D128: 3417324 | E128: =vlookup(C128,'Master data'!$A$1:$C$29,3,0) -> Biến phí | F128: =vlookup(C128,'Master data'!$A$1:$C$29,2,0) -> Chi phí bán hàng
A129: 2024.03 | B129: KH xem PT | C129: Hành chính MKT | D129: 9166667 | E129: =vlookup(C129,'Master data'!$A$1:$C$29,3,0) -> Biến phí | F129: =vlookup(C129,'Master data'!$A$1:$C$29,2,0) -> Chi phí bán hàng
A130: 2024.03 | B130: QC | C130: Marketing chạy Quảng cáo | D130: 296300000 | E130: =vlookup(C130,'Master data'!$A$1:$C$29,3,0) -> Biến phí | F130: =vlookup(C130,'Master data'!$A$1:$C$29,2,0) -> Chi phí bán hàng
A131: 2024.03 | B131: off voice goc khuất implant | C131: Marketing chạy Quảng cáo | D131: 200000 | E131: =vlookup(C131,'Master data'!$A$1:$C$29,3,0) -> Biến phí | F131: =vlookup(C131,'Master data'!$A$1:$C$29,2,0) -> Chi phí bán hàng
A132: 2024.03 | B132: Seo web | C132: Marketing chạy Quảng cáo | D132: 7000000 | E132: =vlookup(C132,'Master data'!$A$1:$C$29,3,0) -> Biến phí | F132: =vlookup(C132,'Master data'!$A$1:$C$29,2,0) -> Chi phí bán hàng
A133: 2024.03 | B133: thẻ acb chạy qc+phí thường niên | C133: Marketing chạy Quảng cáo | D133: 400000 | E133: =vlookup(C133,'Master data'!$A$1:$C$29,3,0) -> Biến phí | F133: =vlookup(C133,'Master data'!$A$1:$C$29,2,0) -> Chi phí bán hàng
A134: 2024.03 | B134: Đi truyền hình HTV9 | C134: Marketing chạy Quảng cáo | D134: 20000000 | E134: =vlookup(C134,'Master data'!$A$1:$C$29,3,0) -> Biến phí | F134: =vlookup(C134,'Master data'!$A$1:$C$29,2,0) -> Chi phí bán hàng
A135: 2024.03 | B135: Gia hạn tên miền | C135: Marketing chạy Quảng cáo | D135: 739800 | E135: =vlookup(C135,'Master data'!$A$1:$C$29,3,0) -> Biến phí | F135: =vlookup(C135,'Master data'!$A$1:$C$29,2,0) -> Chi phí bán hàng
A136: 2024.03 | B136: SSL Bảo Mật Thegioiimplant. | C136: Marketing chạy Quảng cáo | D136: 1342000 | E136: =vlookup(C136,'Master data'!$A$1:$C$29,3,0) -> Biến phí | F136: =vlookup(C136,'Master data'!$A$1:$C$29,2,0) -> Chi phí bán hàng
... A295: 2023.12 | B295: Số 5 kỳ ồng | C295: Chi phí Mặt bằng | D295: 91462500 | E295: =vlookup(C295,'Master data'!$A$1:$C$29,3,0) -> Định phí | F295: =vlookup(C295,'Master data'!$A$1:$C$29,2,0) -> Chi phí QLDN
A296: 2023.12 | B296: wf | C296: Chi phí Mặt bằng | E296: =vlookup(C296,'Master data'!$A$1:$C$29,3,0) -> Định phí | F296: =vlookup(C296,'Master data'!$A$1:$C$29,2,0) -> Chi phí QLDN
A297: 2023.12 | B297: iện kỳ ồng | C297: Điện + Nước | D297: 9674667 | E297: =vlookup(C297,'Master data'!$A$1:$C$29,3,0) -> Định phí | F297: =vlookup(C297,'Master data'!$A$1:$C$29,2,0) -> Chi phí hành chính
A298: 2023.12 | B298: Nước kỳ ồng t11 | C298: Điện + Nước | D298: 1932549 | E298: =vlookup(C298,'Master data'!$A$1:$C$29,3,0) -> Định phí | F298: =vlookup(C298,'Master data'!$A$1:$C$29,2,0) -> Chi phí hành chính
A299: 2023.12 | B299: BH NV | C299: Bảo hiểm | D299: 6888600 | E299: =vlookup(C299,'Master data'!$A$1:$C$29,3,0) -> Định phí | F299: =vlookup(C299,'Master data'!$A$1:$C$29,2,0) -> Chi phí QLDN
A300: 2023.12 | B300: quỹ thưởng nv T12/23 | C300: Quỹ thưởng tổng cuối năm | D300: 7287500 | E300: =vlookup(C300,'Master data'!$A$1:$C$29,3,0) -> Định phí | F300: =vlookup(C300,'Master data'!$A$1:$C$29,2,0) -> Chi phí khác
A301: 2023.12 | B301: 1h-3 màng xương osteobiol | C301: Tiền vật liệu | D301: 7950000 | E301: =vlookup(C301,'Master data'!$A$1:$C$29,3,0) -> Biến phí | F301: =vlookup(C301,'Master data'!$A$1:$C$29,2,0) -> Chi phí giá vốn
A302: 2023.12 | B302: Phí xét nghiệm máu 19/10-11/12/23 | C302: Tiền vật liệu | D302: 3800000 | E302: =vlookup(C302,'Master data'!$A$1:$C$29,3,0) -> Biến phí | F302: =vlookup(C302,'Master data'!$A$1:$C$29,2,0) -> Chi phí giá vốn
A303: 2023.12 | B303: zimmer t11 | C303: Tiền vật liệu | D303: 18007500 | E303: =vlookup(C303,'Master data'!$A$1:$C$29,3,0) -> Biến phí | F303: =vlookup(C303,'Master data'!$A$1:$C$29,2,0) -> Chi phí giá vốn
A304: 2023.12 | B304: task | C304: Tiền vật liệu | D304: 4400000 | E304: =vlookup(C304,'Master data'!$A$1:$C$29,3,0) -> Biến phí | F304: =vlookup(C304,'Master data'!$A$1:$C$29,2,0) -> Chi phí giá vốn
A305: 2023.12 | B305: hd dentium | C305: Tiền vật liệu | D305: 112100000 | E305: =vlookup(C305,'Master data'!$A$1:$C$29,3,0) -> Biến phí | F305: =vlookup(C305,'Master data'!$A$1:$C$29,2,0) -> Chi phí giá vốn
A306: 2023.12 | B306: 4 trụ ip strauman khách Thịnh (56715) | C306: Tiền vật liệu | D306: 52640000 | E306: =vlookup(C306,'Master data'!$A$1:$C$29,3,0) -> Biến phí | F306: =vlookup(C306,'Master data'!$A$1:$C$29,2,0) -> Chi phí giá vốn
A307: 2023.12 | B307: Mũi cắt xương, MTA (Việt ăng) | C307: Tiền vật liệu | D307: 11624000 | E307: =vlookup(C307,'Master data'!$A$1:$C$29,3,0) -> Biến phí | F307: =vlookup(C307,'Master data'!$A$1:$C$29,2,0) -> Chi phí giá vốn
A308: 2023.12 | B308: Pin cố ịnh màng xương | C308: Tiền vật liệu | D308: 7176406 | E308: =vlookup(C308,'Master data'!$A$1:$C$29,3,0) -> Biến phí | F308: =vlookup(C308,'Master data'!$A$1:$C$29,2,0) -> Chi phí giá vốn
... A318: 2023.10 | B318: lương cứng t10 | C318: Lương | D318: 80310894 | E318: =vlookup(C318,'Master data'!$A$1:$C$29,3,0) -> Định phí | F318: =vlookup(C318,'Master data'!$A$1:$C$29,2,0) -> Chi phí QLDN
A319: 2023.10 | B319: lương kpi tháng 10 | C319: KPI | E319: =vlookup(C319,'Master data'!$A$1:$C$29,3,0) -> Biến phí | F319: =vlookup(C319,'Master data'!$A$1:$C$29,2,0) -> Chi phí bán hàng
A320: 2023.11 | B320: chi phường | C320: Mua đồ hành chính | D320: 1000000 | E320: =vlookup(C320,'Master data'!$A$1:$C$29,3,0) -> Biến phí | F320: =vlookup(C320,'Master data'!$A$1:$C$29,2,0) -> Chi phí hành chính
A321: 2023.11 | B321: áo blouse | C321: Mua đồ hành chính | D321: 1230000 | E321: =vlookup(C321,'Master data'!$A$1:$C$29,3,0) -> Biến phí | F321: =vlookup(C321,'Master data'!$A$1:$C$29,2,0) -> Chi phí hành chính
A322: 2023.11 | B322: in ấn/3 | C322: Mua đồ hành chính | D322: 1666667 | E322: =vlookup(C322,'Master data'!$A$1:$C$29,3,0) -> Biến phí | F322: =vlookup(C322,'Master data'!$A$1:$C$29,2,0) -> Chi phí hành chính
A323: 2023.11 | B323: Làm web | C323: Mua đồ hành chính | D323: 15000000 | E323: =vlookup(C323,'Master data'!$A$1:$C$29,3,0) -> Biến phí | F323: =vlookup(C323,'Master data'!$A$1:$C$29,2,0) -> Chi phí hành chính
A324: 2023.11 | B324: mua hộp nhựa ựng ồ chống sốc | C324: Mua đồ hành chính | D324: 200000 | E324: =vlookup(C324,'Master data'!$A$1:$C$29,3,0) -> Biến phí | F324: =vlookup(C324,'Master data'!$A$1:$C$29,2,0) -> Chi phí hành chính
A325: 2023.11 | B325: Phần mềm thiết kế máng hd pt | C325: Mua đồ hành chính | D325: 7000000 | E325: =vlookup(C325,'Master data'!$A$1:$C$29,3,0) -> Biến phí | F325: =vlookup(C325,'Master data'!$A$1:$C$29,2,0) -> Chi phí hành chính
A326: 2023.11 | B326: rèm cửa | C326: Mua đồ hành chính | D326: 2560000 | E326: =vlookup(C326,'Master data'!$A$1:$C$29,3,0) -> Biến phí | F326: =vlookup(C326,'Master data'!$A$1:$C$29,2,0) -> Chi phí hành chính
A327: 2023.11 | B327: bảng giá impl | C327: Mua đồ hành chính | D327: 1300000 | E327: =vlookup(C327,'Master data'!$A$1:$C$29,3,0) -> Biến phí | F327: =vlookup(C327,'Master data'!$A$1:$C$29,2,0) -> Chi phí hành chính
A328: 2023.11 | B328: thành lập cty | C328: Mua đồ hành chính | D328: 3200000 | E328: =vlookup(C328,'Master data'!$A$1:$C$29,3,0) -> Biến phí | F328: =vlookup(C328,'Master data'!$A$1:$C$29,2,0) -> Chi phí hành chính
A329: 2023.11 | B329: thay ổi tt lần 2 | C329: Mua đồ hành chính | D329: 3000000 | E329: =vlookup(C329,'Master data'!$A$1:$C$29,3,0) -> Biến phí | F329: =vlookup(C329,'Master data'!$A$1:$C$29,2,0) -> Chi phí hành chính
A330: 2023.11 | B330: chữ kí số | C330: Mua đồ hành chính | D330: 2200000 | E330: =vlookup(C330,'Master data'!$A$1:$C$29,3,0) -> Biến phí | F330: =vlookup(C330,'Master data'!$A$1:$C$29,2,0) -> Chi phí hành chính
A331: 2023.11 | B331: Mua tên miền | C331: Mua đồ hành chính | D331: 1782000 | E331: =vlookup(C331,'Master data'!$A$1:$C$29,3,0) -> Biến phí | F331: =vlookup(C331,'Master data'!$A$1:$C$29,2,0) -> Chi phí hành chính
... A355: 2023.11 | B355: lương cứng t10 | C355: Lương | D355: 135419587 | E355: =vlookup(C355,'Master data'!$A$1:$C$29,3,0) -> Định phí | F355: =vlookup(C355,'Master data'!$A$1:$C$29,2,0) -> Chi phí QLDN
A356: 2023.11 | B356: lương kpi tháng 10 | C356: KPI | E356: =vlookup(C356,'Master data'!$A$1:$C$29,3,0) -> Biến phí | F356: =vlookup(C356,'Master data'!$A$1:$C$29,2,0) -> Chi phí bán hàng
A357: 2024.05 | B357: Tổng hợp | C357: Mua đồ hành chính | D357: 0 | E357: =vlookup(C357,'Master data'!$A$1:$C$29,3,0) -> Biến phí | F357: =vlookup(C357,'Master data'!$A$1:$C$29,2,0) -> Chi phí hành chính
A358: 2024.05 | B358: lương cứng t5 | C358: Lương | D358: 333132498 | E358: =vlookup(C358,'Master data'!$A$1:$C$29,3,0) -> Định phí | F358: =vlookup(C358,'Master data'!$A$1:$C$29,2,0) -> Chi phí QLDN
A359: 2024.05 | B359: lương kpi tháng 5 | C359: KPI | D359: 225967462 | E359: =vlookup(C359,'Master data'!$A$1:$C$29,3,0) -> Biến phí | F359: =vlookup(C359,'Master data'!$A$1:$C$29,2,0) -> Chi phí bán hàng
A360: 2024.05 | B360: Hành chính | C360: Mua đồ hành chính | D360: 79216337 | E360: =vlookup(C360,'Master data'!$A$1:$C$29,3,0) -> Biến phí | F360: =vlookup(C360,'Master data'!$A$1:$C$29,2,0) -> Chi phí hành chính
A361: 2024.05 | B361: Phí kiểm ịnh 2 lò | C361: Mua đồ hành chính | D361: 800000 | E361: =vlookup(C361,'Master data'!$A$1:$C$29,3,0) -> Biến phí | F361: =vlookup(C361,'Master data'!$A$1:$C$29,2,0) -> Chi phí hành chính
A362: 2024.05 | B362: xnm | C362: Marketing chạy Quảng cáo | D362: 2067000 | E362: =vlookup(C362,'Master data'!$A$1:$C$29,3,0) -> Biến phí | F362: =vlookup(C362,'Master data'!$A$1:$C$29,2,0) -> Chi phí bán hàng
A363: 2024.05 | B363: làm giấy tờ huỷ hộ kinh doanh cá thể | C363: Mua đồ hành chính | D363: 550000 | E363: =vlookup(C363,'Master data'!$A$1:$C$29,3,0) -> Biến phí | F363: =vlookup(C363,'Master data'!$A$1:$C$29,2,0) -> Chi phí hành chính
A364: 2024.05 | B364: phí trả góp 57897 | C364: Marketing chạy Quảng cáo | D364: 3359000 | E364: =vlookup(C364,'Master data'!$A$1:$C$29,3,0) -> Biến phí | F364: =vlookup(C364,'Master data'!$A$1:$C$29,2,0) -> Chi phí bán hàng
A365: 2024.05 | B365: phí trả góp 57922 | C365: Marketing chạy Quảng cáo | D365: 779160 | E365: =vlookup(C365,'Master data'!$A$1:$C$29,3,0) -> Biến phí | F365: =vlookup(C365,'Master data'!$A$1:$C$29,2,0) -> Chi phí bán hàng
A366: 2024.05 | B366: phí sms tk T12/23, T1-T4/24 | C366: Marketing chạy Quảng cáo | D366: 80000 | E366: =vlookup(C366,'Master data'!$A$1:$C$29,3,0) -> Biến phí | F366: =vlookup(C366,'Master data'!$A$1:$C$29,2,0) -> Chi phí bán hàng
A367: 2024.05 | B367: chụp phim khách | C367: Marketing chạy Quảng cáo | D367: 400000 | E367: =vlookup(C367,'Master data'!$A$1:$C$29,3,0) -> Biến phí | F367: =vlookup(C367,'Master data'!$A$1:$C$29,2,0) -> Chi phí bán hàng
A368: 2024.05 | B368: Tăm nước tặng khacha | C368: Marketing chạy Quảng cáo | D368: 12628000 | E368: =vlookup(C368,'Master data'!$A$1:$C$29,3,0) -> Biến phí | F368: =vlookup(C368,'Master data'!$A$1:$C$29,2,0) -> Chi phí bán hàng
... A704: 2024.11 | B704: Thưởng gián tiếp | C704: Quỹ thưởng gián tiếp | D704: 7190000 | E704: =vlookup(C704,'Master data'!$A$1:$C$29,3,0) -> Biến phí | F704: =vlookup(C704,'Master data'!$A$1:$C$29,2,0) -> Chi phí bán hàng
A705: 2024.11 | B705: Đi trường | C705: Đi trường | E705: =vlookup(C705,'Master data'!$A$1:$C$29,3,0) -> Định phí | F705: =vlookup(C705,'Master data'!$A$1:$C$29,2,0) -> Chi phí bán hàng
A706: 2024.11 | B706: Hành chính MKT | C706: Hành chính MKT | D706: 108625667 | E706: =vlookup(C706,'Master data'!$A$1:$C$29,3,0) -> Biến phí | F706: =vlookup(C706,'Master data'!$A$1:$C$29,2,0) -> Chi phí bán hàng
A707: 2024.11 | B707: Hoa hòng gth | C707: Hoa hồng giới thiệu | D707: 18959840 | E707: =vlookup(C707,'Master data'!$A$1:$C$29,3,0) -> Biến phí | F707: =vlookup(C707,'Master data'!$A$1:$C$29,2,0) -> Chi phí bán hàng
A708: 2024.11 | B708: TikTok | C708: Tiktok | D708: 22500000 | E708: =vlookup(C708,'Master data'!$A$1:$C$29,3,0) -> Biến phí | F708: =vlookup(C708,'Master data'!$A$1:$C$29,2,0) -> Chi phí bán hàng
A709: 2024.11 | B709: SEO | C709: SEO | D709: 13750000 | E709: =vlookup(C709,'Master data'!$A$1:$C$29,3,0) -> Biến phí | F709: =vlookup(C709,'Master data'!$A$1:$C$29,2,0) -> Chi phí bán hàng
A710: 2024.11 | B710: % của NV | C710: KPI | D710: 241629886 | E710: =vlookup(C710,'Master data'!$A$1:$C$29,3,0) -> Biến phí | F710: =vlookup(C710,'Master data'!$A$1:$C$29,2,0) -> Chi phí bán hàng
A711: 2024.11 | B711: Phí cà thẻ | C711: Phí cà thẻ | D711: 8988850 | E711: =vlookup(C711,'Master data'!$A$1:$C$29,3,0) -> Biến phí | F711: =vlookup(C711,'Master data'!$A$1:$C$29,2,0) -> Chi phí bán hàng
A712: 2024.11 | B712: Tiếp khách pK(grab, chi phí khác) | C712: Tiếp khách | D712: 8435167 | E712: =vlookup(C712,'Master data'!$A$1:$C$29,3,0) -> Định phí | F712: =vlookup(C712,'Master data'!$A$1:$C$29,2,0) -> Chi phí hành chính
A713: 2024.11 | B713: Lương | C713: Lương | D713: 439834379 | E713: =vlookup(C713,'Master data'!$A$1:$C$29,3,0) -> Định phí | F713: =vlookup(C713,'Master data'!$A$1:$C$29,2,0) -> Chi phí QLDN
A714: 2024.11 | B714: Chi phí MB | C714: Chi phí Mặt bằng | D714: 127611167 | E714: =vlookup(C714,'Master data'!$A$1:$C$29,3,0) -> Định phí | F714: =vlookup(C714,'Master data'!$A$1:$C$29,2,0) -> Chi phí QLDN
A715: 2024.11 | B715: Bảo hiểm | C715: Bảo hiểm | D715: 27766613 | E715: =vlookup(C715,'Master data'!$A$1:$C$29,3,0) -> Định phí | F715: =vlookup(C715,'Master data'!$A$1:$C$29,2,0) -> Chi phí QLDN
A716: 2024.11 | B716: Thuê bằng bs | C716: Thuê bằng | D716: 15000000 | E716: =vlookup(C716,'Master data'!$A$1:$C$29,3,0) -> Định phí | F716: =vlookup(C716,'Master data'!$A$1:$C$29,2,0) -> Chi phí QLDN
A717: 2024.11 | B717: chi phí cho quận, phường | C717: Mua đồ hành chính | D717: 2333333 | E717: =vlookup(C717,'Master data'!$A$1:$C$29,3,0) -> Biến phí | F717: =vlookup(C717,'Master data'!$A$1:$C$29,2,0) -> Chi phí hành chính
A718: 2024.11 | B718: thuế | C718: Mua đồ hành chính | E718: =vlookup(C718,'Master data'!$A$1:$C$29,3,0) -> Biến phí | F718: =vlookup(C718,'Master data'!$A$1:$C$29,2,0) -> Chi phí hành chính
A719: 2024.11 | B719: thuốc tê | C719: Tiền vật liệu | D719: 10666667 | E719: =vlookup(C719,'Master data'!$A$1:$C$29,3,0) -> Biến phí | F719: =vlookup(C719,'Master data'!$A$1:$C$29,2,0) -> Chi phí giá vốn
A720: 2024.11 | B720: muan thuốc, mẫu hàm TGIP | C720: Tiền vật liệu | D720: 9195000 | E720: =vlookup(C720,'Master data'!$A$1:$C$29,3,0) -> Biến phí | F720: =vlookup(C720,'Master data'!$A$1:$C$29,2,0) -> Chi phí giá vốn
A721: 2024.11 | B721: tiền xét nghiệm máu | C721: Tiền vật liệu | D721: 3972000 | E721: =vlookup(C721,'Master data'!$A$1:$C$29,3,0) -> Biến phí | F721: =vlookup(C721,'Master data'!$A$1:$C$29,2,0) -> Chi phí giá vốn
A722: 2024.11 | B722: nhập kin | C722: Tiền vật liệu | D722: 5120000 | E722: =vlookup(C722,'Master data'!$A$1:$C$29,3,0) -> Biến phí | F722: =vlookup(C722,'Master data'!$A$1:$C$29,2,0) -> Chi phí giá vốn
A723: 2024.11 | B723: Implant biotem 50 trụ | C723: Tiền vật liệu | D723: 24900000 | E723: =vlookup(C723,'Master data'!$A$1:$C$29,3,0) -> Biến phí | F723: =vlookup(C723,'Master data'!$A$1:$C$29,2,0) -> Chi phí giá vốn
A724: 2024.11 | B724: mũi khoan,tiền kẹp phẫu,Tiền tay khoan khuỷ chậm | C724: Tiền vật liệu | D724: 13840000 | E724: =vlookup(C724,'Master data'!$A$1:$C$29,3,0) -> Biến phí | F724: =vlookup(C724,'Master data'!$A$1:$C$29,2,0) -> Chi phí giá vốn
A725: 2024.11 | B725: thanh toán xương zimmer | C725: Tiền vật liệu | D725: 14854000 | E725: =vlookup(C725,'Master data'!$A$1:$C$29,3,0) -> Biến phí | F725: =vlookup(C725,'Master data'!$A$1:$C$29,2,0) -> Chi phí giá vốn
A726: 2024.11 | B726: mua đĩa đánh bóng + thước đo cầu mão + bộ chụp ảnh TGIP | C726: Tiền vật liệu | D726: 5751000 | E726: =vlookup(C726,'Master data'!$A$1:$C$29,3,0) -> Biến phí | F726: =vlookup(C726,'Master data'!$A$1:$C$29,2,0) -> Chi phí giá vốn
A727: 2024.11 | B727: hd màn xương Osteobol đợt 5/7 | C727: Tiền vật liệu | D727: 31800000 | E727: =vlookup(C727,'Master data'!$A$1:$C$29,3,0) -> Biến phí | F727: =vlookup(C727,'Master data'!$A$1:$C$29,2,0) -> Chi phí giá vốn
A728: 2024.11 | B728: cọc bộ phẫu thuật nha chu (tổng 18tr) | C728: Tiền vật liệu | D728: 5000000 | E728: =vlookup(C728,'Master data'!$A$1:$C$29,3,0) -> Biến phí | F728: =vlookup(C728,'Master data'!$A$1:$C$29,2,0) -> Chi phí giá vốn
A729: 2024.11 | B729: vật tư cầm máu(TGIP) | C729: Tiền vật liệu | D729: 1740000 | E729: =vlookup(C729,'Master data'!$A$1:$C$29,3,0) -> Biến phí | F729: =vlookup(C729,'Master data'!$A$1:$C$29,2,0) -> Chi phí giá vốn
